{
  "id": "2023-09-04T14:31:59.719Z0.15204442556490116",
  "alert": "Start of result\nResult\n\nMinimum yearly repayment not met.\n\nThe amount of the loan not repaid at the end of income year 2023-24 is $56,430,526.91.\n\nThe private company may be taken to pay a dividend under Division 7A to the shareholder or shareholder's associate because the amount repaid during income year 2023-24 in relation to the amalgamated loan is less than the minimum yearly repayment required.\n\nInterest received by the private company must be included in the income tax return for 2023-24.\n\nMinimum yearly repayment\n\n$17,140,057.00\n\nBenchmark interest rate\n\n8.27%\n\nOpening balance:\n\nDate: 30/06/2023\n\nBalance: $56,430,526.91\n\nDays: 366\n\nInterest: $4,666,804.58\n\nTotal repayments\n\n$0\n\nTotal interest\n\n$4,666,804.58\n\nTotal principal\n\n$0\n\nClosing balance\n\nDate: 30/06/2024\n\nBalance: $56,430,526.91",
  "outputs": {
    "enquiryRateFormatted": "8.27%",
    "enquiryYearEndMinusOneDisplay": "30/06/2023",
    "amalgamatedLoanNotPaidByEOIYFormatted": "$56,430,526.91",
    "openingBalancePayDays": "366",
    "openingBalanceInterestFormatted": "$4,666,804.58",
    "totalAmountOfRepaymentFormatted": "$0",
    "totalInterestFormatted": "$4,666,804.58",
    "principalFormatted": "$0",
    "enquiryYearEndDisplay": "30/06/2024",
    "minimumYearRepaymentFormatted": "$17,140,057.00"
  },
  "repayments": [],
  "inputs": {
    "incomeYearOfLoan": 2022,
    "fullTermOfAmalgamatedLoan": 5,
    "incomeYearOfEnquiring": 2024,
    "amalgamatedLoanNotPaidByEOIY": 56430526.911302775,
    "repayments": null,
    "lodgement_date": null
  },
  "idx": 180
}