{
  "id": "2023-09-04T14:55:49.240Z0.3802634255328876",
  "alert": "Start of result\nResult\n\nMinimum yearly repayment not met.\n\nThe amount of the loan not repaid at the end of income year 2022-23 is $26,626,861.33.\n\nThe private company may be taken to pay a dividend under Division 7A to the shareholder or shareholder's associate because the amount repaid during income year 2022-23 in relation to the amalgamated loan is less than the minimum yearly repayment required.\n\nInterest received by the private company must be included in the income tax return for 2022-23.\n\nMinimum yearly repayment\n\n$14,268,856.00\n\nBenchmark interest rate\n\n4.77%\n\nOpening balance:\n\nDate: 30/06/2022\n\nBalance: $26,626,861.33\n\nDays: 0\n\nInterest: $0\n\nPayments\n\nDate: 01/07/2022\n\nAmount: $8,482.00\n\nBalance: $26,618,379.33\n\nDays: 365\n\nInterest: $1,269,696.69\n\n\n\n\nTotal repayments\n\n$8,482.00\n\nTotal interest\n\n$1,269,696.69\n\nTotal principal\n\n$0\n\nClosing balance\n\nDate: 30/06/2023\n\nBalance: $26,626,861.33",
  "outputs": {
    "enquiryRateFormatted": "4.77%",
    "enquiryYearEndMinusOneDisplay": "30/06/2022",
    "amalgamatedLoanNotPaidByEOIYFormatted": "$26,626,861.33",
    "openingBalancePayDays": "0",
    "openingBalanceInterestFormatted": "$0",
    "totalAmountOfRepaymentFormatted": "$8,482.00",
    "totalInterestFormatted": "$1,269,696.69",
    "principalFormatted": "$0",
    "enquiryYearEndDisplay": "30/06/2023",
    "minimumYearRepaymentFormatted": "$14,268,856.00"
  },
  "repayments": [
    {
      "rd": "1/7/2022",
      "ra": 8482
    }
  ],
  "inputs": {
    "incomeYearOfLoan": 2022,
    "fullTermOfAmalgamatedLoan": 2,
    "incomeYearOfEnquiring": 2023,
    "amalgamatedLoanNotPaidByEOIY": 26626861.336187653,
    "repayments": null,
    "lodgement_date": "27/4/2023"
  },
  "idx": 103
}