{
  "id": "2023-09-04T14:57:09.674Z0.1795981124591982",
  "alert": "Start of result\nResult\n\nMinimum yearly repayment not met.\n\nThe amount of the loan not repaid at the end of income year 2023-24 is $4,691.00.\n\nThe private company may be taken to pay a dividend under Division 7A to the shareholder or shareholder's associate because the amount repaid during income year 2023-24 in relation to the amalgamated loan is less than the minimum yearly repayment required.\n\nInterest received by the private company must be included in the income tax return for 2023-24.\n\nMinimum yearly repayment\n\n$2,640.00\n\nBenchmark interest rate\n\n8.27%\n\nOpening balance:\n\nDate: 30/06/2023\n\nBalance: $4,691.00\n\nDays: 0\n\nInterest: $0\n\nPayments\n\nDate: 01/07/2023\n\nAmount: $98.00\n\nBalance: $4,593.00\n\nDays: 366\n\nInterest: $379.84\n\n\n\n\nTotal repayments\n\n$98.00\n\nTotal interest\n\n$379.84\n\nTotal principal\n\n$0\n\nClosing balance\n\nDate: 30/06/2024\n\nBalance: $4,691.00",
  "outputs": {
    "enquiryRateFormatted": "8.27%",
    "enquiryYearEndMinusOneDisplay": "30/06/2023",
    "amalgamatedLoanNotPaidByEOIYFormatted": "$4,691.00",
    "openingBalancePayDays": "0",
    "openingBalanceInterestFormatted": "$0",
    "totalAmountOfRepaymentFormatted": "$98.00",
    "totalInterestFormatted": "$379.84",
    "principalFormatted": "$0",
    "enquiryYearEndDisplay": "30/06/2024",
    "minimumYearRepaymentFormatted": "$2,640.00"
  },
  "repayments": [
    {
      "rd": "1/7/2023",
      "ra": 98
    }
  ],
  "inputs": {
    "incomeYearOfLoan": 2022,
    "fullTermOfAmalgamatedLoan": 3,
    "incomeYearOfEnquiring": 2024,
    "amalgamatedLoanNotPaidByEOIY": 4691,
    "repayments": null,
    "lodgement_date": null
  },
  "idx": 111
}