{
  "id": "2023-09-04T14:49:59.270Z0.3425509152887005",
  "alert": "Start of result\nResult\n\nMinimum yearly repayment not met.\n\nThe amount of the loan not repaid at the end of income year 2023-24 is $80,606,079.16.\n\nThe private company may be taken to pay a dividend under Division 7A to the shareholder or shareholder's associate because the amount repaid during income year 2023-24 in relation to the amalgamated loan is less than the minimum yearly repayment required.\n\nInterest received by the private company must be included in the income tax return for 2023-24.\n\nMinimum yearly repayment\n\n$45,363,204.00\n\nBenchmark interest rate\n\n8.27%\n\nOpening balance:\n\nDate: 30/06/2023\n\nBalance: $80,606,079.16\n\nDays: 0\n\nInterest: $0\n\nPayments\n\nDate: 01/07/2023\n\nAmount: $9,953.00\n\nBalance: $80,596,126.16\n\nDays: 366\n\nInterest: $6,665,299.63\n\n\n\n\nTotal repayments\n\n$9,953.00\n\nTotal interest\n\n$6,665,299.63\n\nTotal principal\n\n$0\n\nClosing balance\n\nDate: 30/06/2024\n\nBalance: $80,606,079.16",
  "outputs": {
    "enquiryRateFormatted": "8.27%",
    "enquiryYearEndMinusOneDisplay": "30/06/2023",
    "amalgamatedLoanNotPaidByEOIYFormatted": "$80,606,079.16",
    "openingBalancePayDays": "0",
    "openingBalanceInterestFormatted": "$0",
    "totalAmountOfRepaymentFormatted": "$9,953.00",
    "totalInterestFormatted": "$6,665,299.63",
    "principalFormatted": "$0",
    "enquiryYearEndDisplay": "30/06/2024",
    "minimumYearRepaymentFormatted": "$45,363,204.00"
  },
  "repayments": [
    {
      "rd": "1/7/2023",
      "ra": 9953
    }
  ],
  "inputs": {
    "incomeYearOfLoan": 2023,
    "fullTermOfAmalgamatedLoan": 2,
    "incomeYearOfEnquiring": 2024,
    "amalgamatedLoanNotPaidByEOIY": 80606079.16743453,
    "repayments": null,
    "lodgement_date": "17/1/2024"
  },
  "idx": 17
}