{
  "id": "2023-09-04T14:51:42.453Z0.9284058781081899",
  "alert": "Start of result\nResult\n\nMinimum yearly repayment not met.\n\nThe amount of the loan not repaid at the end of income year 2023-24 is $61,119,549.86.\n\nThe private company may be taken to pay a dividend under Division 7A to the shareholder or shareholder's associate because the amount repaid during income year 2023-24 in relation to the amalgamated loan is less than the minimum yearly repayment required.\n\nInterest received by the private company must be included in the income tax return for 2023-24.\n\nMinimum yearly repayment\n\n$11,848,002.00\n\nBenchmark interest rate\n\n8.27%\n\nOpening balance:\n\nDate: 30/06/2023\n\nBalance: $61,119,549.86\n\nDays: 366\n\nInterest: $5,054,586.77\n\nTotal repayments\n\n$0\n\nTotal interest\n\n$5,054,586.77\n\nTotal principal\n\n$0\n\nClosing balance\n\nDate: 30/06/2024\n\nBalance: $61,119,549.86",
  "outputs": {
    "enquiryRateFormatted": "8.27%",
    "enquiryYearEndMinusOneDisplay": "30/06/2023",
    "amalgamatedLoanNotPaidByEOIYFormatted": "$61,119,549.86",
    "openingBalancePayDays": "366",
    "openingBalanceInterestFormatted": "$5,054,586.77",
    "totalAmountOfRepaymentFormatted": "$0",
    "totalInterestFormatted": "$5,054,586.77",
    "principalFormatted": "$0",
    "enquiryYearEndDisplay": "30/06/2024",
    "minimumYearRepaymentFormatted": "$11,848,002.00"
  },
  "repayments": [],
  "inputs": {
    "incomeYearOfLoan": 2023,
    "fullTermOfAmalgamatedLoan": 7,
    "incomeYearOfEnquiring": 2024,
    "amalgamatedLoanNotPaidByEOIY": 61119549.869390704,
    "repayments": null,
    "lodgement_date": "9/10/2023"
  },
  "idx": 61
}