{
  "id": "2023-09-06T21:31:30.917Z0.08969582602633563",
  "alert": "Start of result\nResult\n\nMinimum yearly repayment met.\n\nThe amount of the loan not repaid at the end of income year 2006-07 is $0.03.\n\nThe amalgamated loan will not be taken to be a dividend because the total repayments made are equal to or greater than the minimum yearly repayment required for income year 2006-07.\n\nInterest received by the private company must be included in the income tax return for 2006-07.\n\nMinimum yearly repayment\n\n$46.00\n\nBenchmark interest rate\n\n7.55%\n\nOpening balance:\n\nDate: 30/06/2006\n\nBalance: $82.68\n\nDays: 2\n\nInterest: $0.03\n\nPayments\n\nDate: 03/07/2006\n\nAmount: $82.68\n\nBalance: $0\n\nDays: 363\n\nInterest: $0\n\n\n\n\nTotal repayments\n\n$82.68\n\nTotal interest\n\n$0.03\n\nTotal principal\n\n$82.65\n\nClosing balance\n\nDate: 30/06/2007\n\nBalance: $0.03",
  "outputs": {
    "enquiryRateFormatted": "7.55%",
    "enquiryYearEndMinusOneDisplay": "30/06/2006",
    "amalgamatedLoanNotPaidByEOIYFormatted": "$82.68",
    "openingBalancePayDays": "2",
    "openingBalanceInterestFormatted": "$0.03",
    "totalAmountOfRepaymentFormatted": "$82.68",
    "totalInterestFormatted": "$0.03",
    "principalFormatted": "$82.65",
    "enquiryYearEndDisplay": "30/06/2007",
    "minimumYearRepaymentFormatted": "$46.00"
  },
  "repayments": [
    {
      "rd": "3/7/2006",
      "ra": 82.68806620191845
    }
  ],
  "inputs": {
    "incomeYearOfLoan": 2002,
    "fullTermOfAmalgamatedLoan": 6,
    "incomeYearOfEnquiring": 2007,
    "amalgamatedLoanNotPaidByEOIY": 82.68806620191845,
    "repayments": null,
    "lodgement_date": null
  },
  "idx": 5913
}