{
  "id": "2023-10-31T17:09:29.679Z0.8159676536263777",
  "alert": "Start of result\nResult\n\nAmalgamated loan fully repaid.\n\nThe amalgamated loan has been paid in full.\u000bThe private company is not taken under Division 7A to pay a dividend to the shareholder or shareholder's associate.\n\nInterest received by the private company must be included in the income tax return for 2023-24.\n\nMinimum yearly repayment\n\n$1,805.00\n\nBenchmark interest rate\n\n8.27%\n\nOpening balance:\n\nDate: 30/06/2023\n\nBalance: $4,629.00\n\nDays: 288\n\nInterest: $301.23\n\nPayments\n\nDate: 14/04/2024\n\nAmount: $7,343.00\n\nBalance: $0\n\nDays: 78\n\nInterest: $0\n\n\n\n\nTotal repayments\n\n$7,343.00\n\nTotal interest\n\n$301.23\n\nTotal principal\n\n$7,041.77\n\nClosing balance\n\nDate: 30/06/2024\n\nBalance: $0",
  "outputs": {
    "enquiryRateFormatted": "8.27%",
    "enquiryYearEndMinusOneDisplay": "30/06/2023",
    "amalgamatedLoanNotPaidByEOIYFormatted": "$4,629.00",
    "openingBalancePayDays": "288",
    "openingBalanceInterestFormatted": "$301.23",
    "totalAmountOfRepaymentFormatted": "$7,343.00",
    "totalInterestFormatted": "$301.23",
    "principalFormatted": "$7,041.77",
    "enquiryYearEndDisplay": "30/06/2024",
    "minimumYearRepaymentFormatted": "$1,805.00",
    "loanAmountFormatted": "$0"
  },
  "repayments": [
    {
      "rd": "14/4/2024",
      "ra": 7343
    }
  ],
  "inputs": {
    "incomeYearOfLoan": 2022,
    "fullTermOfAmalgamatedLoan": 4,
    "incomeYearOfEnquiring": 2024,
    "amalgamatedLoanNotPaidByEOIY": 4629,
    "repayments": null,
    "lodgement_date": null
  },
  "idx": 257
}