{
  "id": "2023-09-07T00:43:13.861Z0.015685376984125643",
  "alert": "Start of result\nResult\n\nMinimum yearly repayment met.\n\nThe amount of the loan not repaid at the end of income year 2000-01 is $0.55.\n\nThe amalgamated loan will not be taken to be a dividend because the total repayments made are equal to or greater than the minimum yearly repayment required for income year 2000-01.\n\nInterest received by the private company must be included in the income tax return for 2000-01.\n\nMinimum yearly repayment\n\n$2.00\n\nBenchmark interest rate\n\n7.8%\n\nOpening balance:\n\nDate: 30/06/2000\n\nBalance: $9.77\n\nDays: 265\n\nInterest: $0.55\n\nPayments\n\nDate: 23/03/2001\n\nAmount: $9.77\n\nBalance: $0\n\nDays: 100\n\nInterest: $0\n\n\n\n\nTotal repayments\n\n$9.77\n\nTotal interest\n\n$0.55\n\nTotal principal\n\n$9.22\n\nClosing balance\n\nDate: 30/06/2001\n\nBalance: $0.55",
  "outputs": {
    "enquiryRateFormatted": "7.8%",
    "enquiryYearEndMinusOneDisplay": "30/06/2000",
    "amalgamatedLoanNotPaidByEOIYFormatted": "$9.77",
    "openingBalancePayDays": "265",
    "openingBalanceInterestFormatted": "$0.55",
    "totalAmountOfRepaymentFormatted": "$9.77",
    "totalInterestFormatted": "$0.55",
    "principalFormatted": "$9.22",
    "enquiryYearEndDisplay": "30/06/2001",
    "minimumYearRepaymentFormatted": "$2.00"
  },
  "repayments": [
    {
      "rd": "23/3/2001",
      "ra": 9.779555653231
    }
  ],
  "inputs": {
    "incomeYearOfLoan": 2000,
    "fullTermOfAmalgamatedLoan": 6,
    "incomeYearOfEnquiring": 2001,
    "amalgamatedLoanNotPaidByEOIY": 9.779555653231451,
    "repayments": null,
    "lodgement_date": "9/8/2000"
  },
  "idx": 7795
}