{
  "id": "2023-10-31T20:08:57.056Z0.5078221823589558",
  "alert": "Start of result\nResult\n\nMinimum yearly repayment not met.\n\nThe amount of the loan not repaid at the end of income year 2001-02 is $6.61.\n\nThe private company may be taken to pay a dividend under Division 7A to the shareholder or shareholder's associate because the amount repaid during income year 2001-02 in relation to the amalgamated loan is less than the minimum yearly repayment required.\n\nInterest received by the private company must be included in the income tax return for 2001-02.\n\nMinimum yearly repayment\n\n$7.00\n\nBenchmark interest rate\n\n6.8%\n\nOpening balance:\n\nDate: 30/06/2001\n\nBalance: $6.61\n\nDays: 365\n\nInterest: $0.45\n\nTotal repayments\n\n$0\n\nTotal interest\n\n$0.45\n\nTotal principal\n\n$0\n\nClosing balance\n\nDate: 30/06/2002\n\nBalance: $6.61",
  "outputs": {
    "enquiryRateFormatted": "6.8%",
    "enquiryYearEndMinusOneDisplay": "30/06/2001",
    "amalgamatedLoanNotPaidByEOIYFormatted": "$6.61",
    "openingBalancePayDays": "365",
    "openingBalanceInterestFormatted": "$0.45",
    "totalAmountOfRepaymentFormatted": "$0",
    "totalInterestFormatted": "$0.45",
    "principalFormatted": "$0",
    "enquiryYearEndDisplay": "30/06/2002",
    "minimumYearRepaymentFormatted": "$7.00",
    "loanAmountFormatted": "$6.61"
  },
  "repayments": [],
  "inputs": {
    "incomeYearOfLoan": 2001,
    "fullTermOfAmalgamatedLoan": 1,
    "incomeYearOfEnquiring": 2002,
    "amalgamatedLoanNotPaidByEOIY": 6.614691254784353,
    "repayments": null,
    "lodgement_date": "29/10/2001"
  },
  "idx": 6212
}