{
  "id": "2023-09-05T17:21:42.378Z0.7354482481398934",
  "alert": "Start of result\nResult\n\nMinimum yearly repayment not met.\n\nThe amount of the loan not repaid at the end of income year 2020-21 is $23.31.\n\nThe private company may be taken to pay a dividend under Division 7A to the shareholder or shareholder's associate because the amount repaid during income year 2020-21 in relation to the amalgamated loan is less than the minimum yearly repayment required.\n\nInterest received by the private company must be included in the income tax return for 2020-21.\n\nMinimum yearly repayment\n\n$5.00\n\nBenchmark interest rate\n\n4.52%\n\nOpening balance:\n\nDate: 30/06/2020\n\nBalance: $23.31\n\nDays: 365\n\nInterest: $1.05\n\nTotal repayments\n\n$0\n\nTotal interest\n\n$1.05\n\nTotal principal\n\n$0\n\nClosing balance\n\nDate: 30/06/2021\n\nBalance: $23.31",
  "outputs": {
    "enquiryRateFormatted": "4.52%",
    "enquiryYearEndMinusOneDisplay": "30/06/2020",
    "amalgamatedLoanNotPaidByEOIYFormatted": "$23.31",
    "openingBalancePayDays": "365",
    "openingBalanceInterestFormatted": "$1.05",
    "totalAmountOfRepaymentFormatted": "$0",
    "totalInterestFormatted": "$1.05",
    "principalFormatted": "$0",
    "enquiryYearEndDisplay": "30/06/2021",
    "minimumYearRepaymentFormatted": "$5.00"
  },
  "repayments": [],
  "inputs": {
    "incomeYearOfLoan": 2019,
    "fullTermOfAmalgamatedLoan": 7,
    "incomeYearOfEnquiring": 2021,
    "amalgamatedLoanNotPaidByEOIY": 23.310112835014884,
    "repayments": null,
    "lodgement_date": null
  },
  "idx": 4075
}