{
  "id": "2023-09-05T16:41:04.686Z0.7869750969356906",
  "alert": "Start of result\nResult\n\nMinimum yearly repayment met.\n\nThe amount of the loan not repaid at the end of income year 2020-21 is $81.73.\n\nThe amalgamated loan will not be taken to be a dividend because the total repayments made are equal to or greater than the minimum yearly repayment required for income year 2020-21.\n\nInterest received by the private company must be included in the income tax return for 2020-21.\n\nMinimum yearly repayment\n\n$953.00\n\nBenchmark interest rate\n\n4.52%\n\nOpening balance:\n\nDate: 30/06/2020\n\nBalance: $2,619.00\n\nDays: 252\n\nInterest: $81.73\n\nPayments\n\nDate: 10/03/2021\n\nAmount: $2,619.00\n\nBalance: $0\n\nDays: 113\n\nInterest: $0\n\n\n\n\nTotal repayments\n\n$2,619.00\n\nTotal interest\n\n$81.73\n\nTotal principal\n\n$2,537.27\n\nClosing balance\n\nDate: 30/06/2021\n\nBalance: $81.73",
  "outputs": {
    "enquiryRateFormatted": "4.52%",
    "enquiryYearEndMinusOneDisplay": "30/06/2020",
    "amalgamatedLoanNotPaidByEOIYFormatted": "$2,619.00",
    "openingBalancePayDays": "252",
    "openingBalanceInterestFormatted": "$81.73",
    "totalAmountOfRepaymentFormatted": "$2,619.00",
    "totalInterestFormatted": "$81.73",
    "principalFormatted": "$2,537.27",
    "enquiryYearEndDisplay": "30/06/2021",
    "minimumYearRepaymentFormatted": "$953.00"
  },
  "repayments": [
    {
      "rd": "10/3/2021",
      "ra": 2619
    }
  ],
  "inputs": {
    "incomeYearOfLoan": 2019,
    "fullTermOfAmalgamatedLoan": 4,
    "incomeYearOfEnquiring": 2021,
    "amalgamatedLoanNotPaidByEOIY": 2619,
    "repayments": null,
    "lodgement_date": null
  },
  "idx": 1480
}