{
  "id": "2023-09-07T00:07:06.055Z0.7785213553764214",
  "alert": "Start of result\nResult\n\nMinimum yearly repayment met.\n\nThe amount of the loan not repaid at the end of income year 2001-02 is $1.72.\n\nThe amalgamated loan will not be taken to be a dividend because the total repayments made are equal to or greater than the minimum yearly repayment required for income year 2001-02.\n\nInterest received by the private company must be included in the income tax return for 2001-02.\n\nMinimum yearly repayment\n\n$16.00\n\nBenchmark interest rate\n\n6.8%\n\nOpening balance:\n\nDate: 30/06/2001\n\nBalance: $41.69\n\nDays: 222\n\nInterest: $1.72\n\nPayments\n\nDate: 08/02/2002\n\nAmount: $41.69\n\nBalance: $0\n\nDays: 143\n\nInterest: $0\n\n\n\n\nTotal repayments\n\n$41.69\n\nTotal interest\n\n$1.72\n\nTotal principal\n\n$39.97\n\nClosing balance\n\nDate: 30/06/2002\n\nBalance: $1.72",
  "outputs": {
    "enquiryRateFormatted": "6.8%",
    "enquiryYearEndMinusOneDisplay": "30/06/2001",
    "amalgamatedLoanNotPaidByEOIYFormatted": "$41.69",
    "openingBalancePayDays": "222",
    "openingBalanceInterestFormatted": "$1.72",
    "totalAmountOfRepaymentFormatted": "$41.69",
    "totalInterestFormatted": "$1.72",
    "principalFormatted": "$39.97",
    "enquiryYearEndDisplay": "30/06/2002",
    "minimumYearRepaymentFormatted": "$16.00"
  },
  "repayments": [
    {
      "rd": "8/2/2002",
      "ra": 41.69407507800884
    }
  ],
  "inputs": {
    "incomeYearOfLoan": 2000,
    "fullTermOfAmalgamatedLoan": 4,
    "incomeYearOfEnquiring": 2002,
    "amalgamatedLoanNotPaidByEOIY": 41.69407507800889,
    "repayments": null,
    "lodgement_date": null
  },
  "idx": 5907
}