{
  "id": "2023-10-31T19:53:11.713Z0.9203486378867255",
  "alert": "Start of result\nResult\n\nMinimum yearly repayment not met.\n\nThe amount of the loan not repaid at the end of income year 2002-03 is $8,626.95.\n\nThe private company may be taken to pay a dividend under Division 7A to the shareholder or shareholder's associate because the amount repaid during income year 2002-03 in relation to the amalgamated loan is less than the minimum yearly repayment required.\n\nInterest received by the private company must be included in the income tax return for 2002-03.\n\nMinimum yearly repayment\n\n$10,360.00\n\nBenchmark interest rate\n\n6.3%\n\nOpening balance:\n\nDate: 30/06/2002\n\nBalance: $9,746.00\n\nDays: 123\n\nInterest: $206.91\n\nPayments\n\nDate: 01/11/2002\n\nAmount: $492.00\n\nBalance: $9,254.00\n\nDays: 211\n\nInterest: $337.02\n\n\n\n\nDate: 31/05/2003\n\nAmount: $1,214.00\n\nBalance: $8,040.00\n\nDays: 31\n\nInterest: $43.02\n\n\n\n\nTotal repayments\n\n$1,706.00\n\nTotal interest\n\n$586.95\n\nTotal principal\n\n$1,119.05\n\nClosing balance\n\nDate: 30/06/2003\n\nBalance: $8,626.95",
  "outputs": {
    "enquiryRateFormatted": "6.3%",
    "enquiryYearEndMinusOneDisplay": "30/06/2002",
    "amalgamatedLoanNotPaidByEOIYFormatted": "$9,746.00",
    "openingBalancePayDays": "123",
    "openingBalanceInterestFormatted": "$206.91",
    "totalAmountOfRepaymentFormatted": "$1,706.00",
    "totalInterestFormatted": "$586.95",
    "principalFormatted": "$1,119.05",
    "enquiryYearEndDisplay": "30/06/2003",
    "minimumYearRepaymentFormatted": "$10,360.00",
    "loanAmountFormatted": "$8,626.95"
  },
  "repayments": [
    {
      "rd": "1/11/2002",
      "ra": 492
    },
    {
      "rd": "31/5/2003",
      "ra": 1214
    }
  ],
  "inputs": {
    "incomeYearOfLoan": 2002,
    "fullTermOfAmalgamatedLoan": 1,
    "incomeYearOfEnquiring": 2003,
    "amalgamatedLoanNotPaidByEOIY": 9746,
    "repayments": null,
    "lodgement_date": "1/7/2002"
  },
  "idx": 5952
}