{
  "id": "2023-10-31T17:42:38.820Z0.6513706894429928",
  "alert": "Start of result\nResult\n\nMinimum yearly repayment not met.\n\nThe amount of the loan not repaid at the end of income year 2015-16 is $347.00.\n\nThe private company may be taken to pay a dividend under Division 7A to the shareholder or shareholder's associate because the amount repaid during income year 2015-16 in relation to the amalgamated loan is less than the minimum yearly repayment required.\n\nInterest received by the private company must be included in the income tax return for 2015-16.\n\nMinimum yearly repayment\n\n$69.00\n\nBenchmark interest rate\n\n5.45%\n\nOpening balance:\n\nDate: 30/06/2015\n\nBalance: $347.00\n\nDays: 366\n\nInterest: $18.91\n\nTotal repayments\n\n$0\n\nTotal interest\n\n$18.91\n\nTotal principal\n\n$0\n\nClosing balance\n\nDate: 30/06/2016\n\nBalance: $347.00",
  "outputs": {
    "enquiryRateFormatted": "5.45%",
    "enquiryYearEndMinusOneDisplay": "30/06/2015",
    "amalgamatedLoanNotPaidByEOIYFormatted": "$347.00",
    "openingBalancePayDays": "366",
    "openingBalanceInterestFormatted": "$18.91",
    "totalAmountOfRepaymentFormatted": "$0",
    "totalInterestFormatted": "$18.91",
    "principalFormatted": "$0",
    "enquiryYearEndDisplay": "30/06/2016",
    "minimumYearRepaymentFormatted": "$69.00",
    "loanAmountFormatted": "$347.00"
  },
  "repayments": [],
  "inputs": {
    "incomeYearOfLoan": 2015,
    "fullTermOfAmalgamatedLoan": 6,
    "incomeYearOfEnquiring": 2016,
    "amalgamatedLoanNotPaidByEOIY": 347,
    "repayments": null,
    "lodgement_date": "28/12/2015"
  },
  "idx": 2347
}