{
  "id": "2023-09-06T02:35:22.218Z0.4722124013485154",
  "alert": "Start of result\nResult\n\nMinimum yearly repayment not met.\n\nThe amount of the loan not repaid at the end of income year 2013-14 is $6,496.00.\n\nThe private company may be taken to pay a dividend under Division 7A to the shareholder or shareholder's associate because the amount repaid during income year 2013-14 in relation to the amalgamated loan is less than the minimum yearly repayment required.\n\nInterest received by the private company must be included in the income tax return for 2013-14.\n\nMinimum yearly repayment\n\n$3,553.00\n\nBenchmark interest rate\n\n6.2%\n\nOpening balance:\n\nDate: 30/06/2013\n\nBalance: $6,496.00\n\nDays: 365\n\nInterest: $402.75\n\nTotal repayments\n\n$0\n\nTotal interest\n\n$402.75\n\nTotal principal\n\n$0\n\nClosing balance\n\nDate: 30/06/2014\n\nBalance: $6,496.00",
  "outputs": {
    "enquiryRateFormatted": "6.2%",
    "enquiryYearEndMinusOneDisplay": "30/06/2013",
    "amalgamatedLoanNotPaidByEOIYFormatted": "$6,496.00",
    "openingBalancePayDays": "365",
    "openingBalanceInterestFormatted": "$402.75",
    "totalAmountOfRepaymentFormatted": "$0",
    "totalInterestFormatted": "$402.75",
    "principalFormatted": "$0",
    "enquiryYearEndDisplay": "30/06/2014",
    "minimumYearRepaymentFormatted": "$3,553.00"
  },
  "repayments": [],
  "inputs": {
    "incomeYearOfLoan": 2013,
    "fullTermOfAmalgamatedLoan": 2,
    "incomeYearOfEnquiring": 2014,
    "amalgamatedLoanNotPaidByEOIY": 6496,
    "repayments": null,
    "lodgement_date": "12/8/2013"
  },
  "idx": 776
}