{
  "id": "2023-10-31T17:29:47.997Z0.061074946732789126",
  "alert": "Start of result\nResult\n\nMinimum yearly repayment not met.\n\nThe amount of the loan not repaid at the end of income year 2019-20 is $10,511.87.\n\nThe private company may be taken to pay a dividend under Division 7A to the shareholder or shareholder's associate because the amount repaid during income year 2019-20 in relation to the amalgamated loan is less than the minimum yearly repayment required.\n\nInterest received by the private company must be included in the income tax return for 2019-20.\n\nMinimum yearly repayment\n\n$3,498.00\n\nBenchmark interest rate\n\n5.37%\n\nOpening balance:\n\nDate: 30/06/2019\n\nBalance: $12,299.00\n\nDays: 294\n\nInterest: $530.53\n\nPayments\n\nDate: 20/04/2020\n\nAmount: $2,422.00\n\nBalance: $9,877.00\n\nDays: 72\n\nInterest: $104.34\n\n\n\n\nTotal repayments\n\n$2,422.00\n\nTotal interest\n\n$634.87\n\nTotal principal\n\n$1,787.13\n\nClosing balance\n\nDate: 30/06/2020\n\nBalance: $10,511.87",
  "outputs": {
    "enquiryRateFormatted": "5.37%",
    "enquiryYearEndMinusOneDisplay": "30/06/2019",
    "amalgamatedLoanNotPaidByEOIYFormatted": "$12,299.00",
    "openingBalancePayDays": "294",
    "openingBalanceInterestFormatted": "$530.53",
    "totalAmountOfRepaymentFormatted": "$2,422.00",
    "totalInterestFormatted": "$634.87",
    "principalFormatted": "$1,787.13",
    "enquiryYearEndDisplay": "30/06/2020",
    "minimumYearRepaymentFormatted": "$3,498.00",
    "loanAmountFormatted": "$10,511.87"
  },
  "repayments": [
    {
      "rd": "20/4/2020",
      "ra": 2422
    }
  ],
  "inputs": {
    "incomeYearOfLoan": 2017,
    "fullTermOfAmalgamatedLoan": 6,
    "incomeYearOfEnquiring": 2020,
    "amalgamatedLoanNotPaidByEOIY": 12299,
    "repayments": null,
    "lodgement_date": null
  },
  "idx": 1681
}