{
  "id": "2023-09-04T16:28:35.911Z0.5369936021783244",
  "alert": "Start of result\nResult\n\nMinimum yearly repayment not met.\n\nThe amount of the loan not repaid at the end of income year 2019-20 is $55,409,078.33.\n\nThe private company may be taken to pay a dividend under Division 7A to the shareholder or shareholder's associate because the amount repaid during income year 2019-20 in relation to the amalgamated loan is less than the minimum yearly repayment required.\n\nInterest received by the private company must be included in the income tax return for 2019-20.\n\nMinimum yearly repayment\n\n$29,955,590.00\n\nBenchmark interest rate\n\n5.37%\n\nOpening balance:\n\nDate: 30/06/2019\n\nBalance: $55,409,078.33\n\nDays: 366\n\nInterest: $2,975,467.51\n\nTotal repayments\n\n$0\n\nTotal interest\n\n$2,975,467.51\n\nTotal principal\n\n$0\n\nClosing balance\n\nDate: 30/06/2020\n\nBalance: $55,409,078.33",
  "outputs": {
    "enquiryRateFormatted": "5.37%",
    "enquiryYearEndMinusOneDisplay": "30/06/2019",
    "amalgamatedLoanNotPaidByEOIYFormatted": "$55,409,078.33",
    "openingBalancePayDays": "366",
    "openingBalanceInterestFormatted": "$2,975,467.51",
    "totalAmountOfRepaymentFormatted": "$0",
    "totalInterestFormatted": "$2,975,467.51",
    "principalFormatted": "$0",
    "enquiryYearEndDisplay": "30/06/2020",
    "minimumYearRepaymentFormatted": "$29,955,590.00"
  },
  "repayments": [],
  "inputs": {
    "incomeYearOfLoan": 2018,
    "fullTermOfAmalgamatedLoan": 3,
    "incomeYearOfEnquiring": 2020,
    "amalgamatedLoanNotPaidByEOIY": 55409078.33439049,
    "repayments": null,
    "lodgement_date": null
  },
  "idx": 593
}