{
  "id": "2023-10-31T19:01:52.227Z0.6681636525020086",
  "alert": "Start of result\nResult\n\nAmalgamated loan fully repaid.\n\nThe amalgamated loan has been paid in full.\u000bThe private company is not taken under Division 7A to pay a dividend to the shareholder or shareholder's associate.\n\nInterest received by the private company must be included in the income tax return for 2007-08.\n\nMinimum yearly repayment\n\n$5,111.00\n\nBenchmark interest rate\n\n8.05%\n\nOpening balance:\n\nDate: 30/06/2007\n\nBalance: $9,108.00\n\nDays: 97\n\nInterest: $194.32\n\nPayments\n\nDate: 06/10/2007\n\nAmount: $5,879.00\n\nBalance: $3,229.00\n\nDays: 39\n\nInterest: $27.70\n\n\n\n\nDate: 14/11/2007\n\nAmount: $8,707.00\n\nBalance: $0\n\nDays: 230\n\nInterest: $0\n\n\n\n\nTotal repayments\n\n$14,586.00\n\nTotal interest\n\n$222.02\n\nTotal principal\n\n$14,363.98\n\nClosing balance\n\nDate: 30/06/2008\n\nBalance: $0",
  "outputs": {
    "enquiryRateFormatted": "8.05%",
    "enquiryYearEndMinusOneDisplay": "30/06/2007",
    "amalgamatedLoanNotPaidByEOIYFormatted": "$9,108.00",
    "openingBalancePayDays": "97",
    "openingBalanceInterestFormatted": "$194.32",
    "totalAmountOfRepaymentFormatted": "$14,586.00",
    "totalInterestFormatted": "$222.02",
    "principalFormatted": "$14,363.98",
    "enquiryYearEndDisplay": "30/06/2008",
    "minimumYearRepaymentFormatted": "$5,111.00",
    "loanAmountFormatted": "$0"
  },
  "repayments": [
    {
      "rd": "6/10/2007",
      "ra": 5879
    },
    {
      "rd": "14/11/2007",
      "ra": 8707
    }
  ],
  "inputs": {
    "incomeYearOfLoan": 2006,
    "fullTermOfAmalgamatedLoan": 3,
    "incomeYearOfEnquiring": 2008,
    "amalgamatedLoanNotPaidByEOIY": 9108,
    "repayments": null,
    "lodgement_date": null
  },
  "idx": 4916
}