{
  "id": "2023-09-05T20:21:46.067Z0.23818792585051463",
  "alert": "Start of result\nResult\n\nMinimum yearly repayment met.\n\nThe amount of the loan not repaid at the end of income year 2020-21 is $1.89.\n\nThe amalgamated loan will not be taken to be a dividend because the total repayments made are equal to or greater than the minimum yearly repayment required for income year 2020-21.\n\nInterest received by the private company must be included in the income tax return for 2020-21.\n\nMinimum yearly repayment\n\n$17.00\n\nBenchmark interest rate\n\n4.52%\n\nOpening balance:\n\nDate: 30/06/2020\n\nBalance: $46.90\n\nDays: 326\n\nInterest: $1.89\n\nPayments\n\nDate: 23/05/2021\n\nAmount: $46.90\n\nBalance: $0\n\nDays: 39\n\nInterest: $0\n\n\n\n\nTotal repayments\n\n$46.90\n\nTotal interest\n\n$1.89\n\nTotal principal\n\n$45.01\n\nClosing balance\n\nDate: 30/06/2021\n\nBalance: $1.89",
  "outputs": {
    "enquiryRateFormatted": "4.52%",
    "enquiryYearEndMinusOneDisplay": "30/06/2020",
    "amalgamatedLoanNotPaidByEOIYFormatted": "$46.90",
    "openingBalancePayDays": "326",
    "openingBalanceInterestFormatted": "$1.89",
    "totalAmountOfRepaymentFormatted": "$46.90",
    "totalInterestFormatted": "$1.89",
    "principalFormatted": "$45.01",
    "enquiryYearEndDisplay": "30/06/2021",
    "minimumYearRepaymentFormatted": "$17.00"
  },
  "repayments": [
    {
      "rd": "23/5/2021",
      "ra": 46.90567009258626
    }
  ],
  "inputs": {
    "incomeYearOfLoan": 2017,
    "fullTermOfAmalgamatedLoan": 6,
    "incomeYearOfEnquiring": 2021,
    "amalgamatedLoanNotPaidByEOIY": 46.90567009258624,
    "repayments": null,
    "lodgement_date": null
  },
  "idx": 5893
}