{
  "id": "2023-10-31T20:15:46.598Z0.5689219776546536",
  "alert": "Start of result\nResult\n\nMinimum yearly repayment not met.\n\nThe amount of the loan not repaid at the end of income year 2001-02 is $10,654.00.\n\nThe private company may be taken to pay a dividend under Division 7A to the shareholder or shareholder's associate because the amount repaid during income year 2001-02 in relation to the amalgamated loan is less than the minimum yearly repayment required.\n\nInterest received by the private company must be included in the income tax return for 2001-02.\n\nMinimum yearly repayment\n\n$3,131.00\n\nBenchmark interest rate\n\n6.8%\n\nOpening balance:\n\nDate: 30/06/2001\n\nBalance: $10,654.00\n\nDays: 365\n\nInterest: $724.47\n\nTotal repayments\n\n$0\n\nTotal interest\n\n$724.47\n\nTotal principal\n\n$0\n\nClosing balance\n\nDate: 30/06/2002\n\nBalance: $10,654.00",
  "outputs": {
    "enquiryRateFormatted": "6.8%",
    "enquiryYearEndMinusOneDisplay": "30/06/2001",
    "amalgamatedLoanNotPaidByEOIYFormatted": "$10,654.00",
    "openingBalancePayDays": "365",
    "openingBalanceInterestFormatted": "$724.47",
    "totalAmountOfRepaymentFormatted": "$0",
    "totalInterestFormatted": "$724.47",
    "principalFormatted": "$0",
    "enquiryYearEndDisplay": "30/06/2002",
    "minimumYearRepaymentFormatted": "$3,131.00",
    "loanAmountFormatted": "$10,654.00"
  },
  "repayments": [],
  "inputs": {
    "incomeYearOfLoan": 2001,
    "fullTermOfAmalgamatedLoan": 4,
    "incomeYearOfEnquiring": 2002,
    "amalgamatedLoanNotPaidByEOIY": 10654,
    "repayments": null,
    "lodgement_date": "30/6/2002"
  },
  "idx": 6319
}