{
  "id": "2023-09-06T05:15:28.789Z0.3112299003183858",
  "alert": "Start of result\nResult\n\nMinimum yearly repayment not met.\n\nThe amount of the loan not repaid at the end of income year 2017-18 is $3.84.\n\nThe private company may be taken to pay a dividend under Division 7A to the shareholder or shareholder's associate because the amount repaid during income year 2017-18 in relation to the amalgamated loan is less than the minimum yearly repayment required.\n\nInterest received by the private company must be included in the income tax return for 2017-18.\n\nMinimum yearly repayment\n\n$111.00\n\nBenchmark interest rate\n\n5.3%\n\nOpening balance:\n\nDate: 30/06/2017\n\nBalance: $105.71\n\nDays: 250\n\nInterest: $3.84\n\nPayments\n\nDate: 08/03/2018\n\nAmount: $105.71\n\nBalance: $0\n\nDays: 115\n\nInterest: $0\n\n\n\n\nTotal repayments\n\n$105.71\n\nTotal interest\n\n$3.84\n\nTotal principal\n\n$101.87\n\nClosing balance\n\nDate: 30/06/2018\n\nBalance: $3.84",
  "outputs": {
    "enquiryRateFormatted": "5.3%",
    "enquiryYearEndMinusOneDisplay": "30/06/2017",
    "amalgamatedLoanNotPaidByEOIYFormatted": "$105.71",
    "openingBalancePayDays": "250",
    "openingBalanceInterestFormatted": "$3.84",
    "totalAmountOfRepaymentFormatted": "$105.71",
    "totalInterestFormatted": "$3.84",
    "principalFormatted": "$101.87",
    "enquiryYearEndDisplay": "30/06/2018",
    "minimumYearRepaymentFormatted": "$111.00"
  },
  "repayments": [
    {
      "rd": "8/3/2018",
      "ra": 105.71397439125985
    }
  ],
  "inputs": {
    "incomeYearOfLoan": 2012,
    "fullTermOfAmalgamatedLoan": 6,
    "incomeYearOfEnquiring": 2018,
    "amalgamatedLoanNotPaidByEOIY": 105.71397439125971,
    "repayments": null,
    "lodgement_date": null
  },
  "idx": 1474
}