{
  "id": "2023-10-31T17:20:51.795Z0.8818521173702989",
  "alert": "Start of result\nResult\n\nMinimum yearly repayment not met.\n\nThe amount of the loan not repaid at the end of income year 2020-21 is $7,795.44.\n\nThe private company may be taken to pay a dividend under Division 7A to the shareholder or shareholder's associate because the amount repaid during income year 2020-21 in relation to the amalgamated loan is less than the minimum yearly repayment required.\n\nInterest received by the private company must be included in the income tax return for 2020-21.\n\nMinimum yearly repayment\n\n$2,333.00\n\nBenchmark interest rate\n\n4.52%\n\nOpening balance:\n\nDate: 30/06/2020\n\nBalance: $8,366.00\n\nDays: 342\n\nInterest: $354.31\n\nPayments\n\nDate: 08/06/2021\n\nAmount: $946.00\n\nBalance: $7,420.00\n\nDays: 23\n\nInterest: $21.13\n\n\n\n\nTotal repayments\n\n$946.00\n\nTotal interest\n\n$375.44\n\nTotal principal\n\n$570.56\n\nClosing balance\n\nDate: 30/06/2021\n\nBalance: $7,795.44",
  "outputs": {
    "enquiryRateFormatted": "4.52%",
    "enquiryYearEndMinusOneDisplay": "30/06/2020",
    "amalgamatedLoanNotPaidByEOIYFormatted": "$8,366.00",
    "openingBalancePayDays": "342",
    "openingBalanceInterestFormatted": "$354.31",
    "totalAmountOfRepaymentFormatted": "$946.00",
    "totalInterestFormatted": "$375.44",
    "principalFormatted": "$570.56",
    "enquiryYearEndDisplay": "30/06/2021",
    "minimumYearRepaymentFormatted": "$2,333.00",
    "loanAmountFormatted": "$7,795.44"
  },
  "repayments": [
    {
      "rd": "8/6/2021",
      "ra": 946
    }
  ],
  "inputs": {
    "incomeYearOfLoan": 2019,
    "fullTermOfAmalgamatedLoan": 5,
    "incomeYearOfEnquiring": 2021,
    "amalgamatedLoanNotPaidByEOIY": 8366,
    "repayments": null,
    "lodgement_date": null
  },
  "idx": 1150
}