{
  "id": "2023-09-04T17:23:30.993Z0.20544444359241854",
  "alert": "Start of result\nResult\n\nMinimum yearly repayment not met.\n\nThe amount of the loan not repaid at the end of income year 2013-14 is $1,446,025.22.\n\nThe private company may be taken to pay a dividend under Division 7A to the shareholder or shareholder's associate because the amount repaid during income year 2013-14 in relation to the amalgamated loan is less than the minimum yearly repayment required.\n\nInterest received by the private company must be included in the income tax return for 2013-14.\n\nMinimum yearly repayment\n\n$345,151.00\n\nBenchmark interest rate\n\n6.2%\n\nOpening balance:\n\nDate: 30/06/2013\n\nBalance: $1,446,025.22\n\nDays: 365\n\nInterest: $89,653.56\n\nTotal repayments\n\n$0\n\nTotal interest\n\n$89,653.56\n\nTotal principal\n\n$0\n\nClosing balance\n\nDate: 30/06/2014\n\nBalance: $1,446,025.22",
  "outputs": {
    "enquiryRateFormatted": "6.2%",
    "enquiryYearEndMinusOneDisplay": "30/06/2013",
    "amalgamatedLoanNotPaidByEOIYFormatted": "$1,446,025.22",
    "openingBalancePayDays": "365",
    "openingBalanceInterestFormatted": "$89,653.56",
    "totalAmountOfRepaymentFormatted": "$0",
    "totalInterestFormatted": "$89,653.56",
    "principalFormatted": "$0",
    "enquiryYearEndDisplay": "30/06/2014",
    "minimumYearRepaymentFormatted": "$345,151.00"
  },
  "repayments": [],
  "inputs": {
    "incomeYearOfLoan": 2013,
    "fullTermOfAmalgamatedLoan": 5,
    "incomeYearOfEnquiring": 2014,
    "amalgamatedLoanNotPaidByEOIY": 1446025.2200590551,
    "repayments": null,
    "lodgement_date": "27/4/2014"
  },
  "idx": 2080
}