{
  "id": "2023-09-06T05:12:25.602Z0.038752596502863",
  "alert": "Start of result\nResult\n\nMinimum yearly repayment met.\n\nThe amount of the loan not repaid at the end of income year 2012-13 is $3.87.\n\nThe amalgamated loan will not be taken to be a dividend because the total repayments made are equal to or greater than the minimum yearly repayment required for income year 2012-13.\n\nInterest received by the private company must be included in the income tax return for 2012-13.\n\nMinimum yearly repayment\n\n$25.00\n\nBenchmark interest rate\n\n7.05%\n\nOpening balance:\n\nDate: 30/06/2012\n\nBalance: $101.26\n\nDays: 198\n\nInterest: $3.87\n\nPayments\n\nDate: 15/01/2013\n\nAmount: $101.26\n\nBalance: $0\n\nDays: 167\n\nInterest: $0\n\n\n\n\nTotal repayments\n\n$101.26\n\nTotal interest\n\n$3.87\n\nTotal principal\n\n$97.39\n\nClosing balance\n\nDate: 30/06/2013\n\nBalance: $3.87",
  "outputs": {
    "enquiryRateFormatted": "7.05%",
    "enquiryYearEndMinusOneDisplay": "30/06/2012",
    "amalgamatedLoanNotPaidByEOIYFormatted": "$101.26",
    "openingBalancePayDays": "198",
    "openingBalanceInterestFormatted": "$3.87",
    "totalAmountOfRepaymentFormatted": "$101.26",
    "totalInterestFormatted": "$3.87",
    "principalFormatted": "$97.39",
    "enquiryYearEndDisplay": "30/06/2013",
    "minimumYearRepaymentFormatted": "$25.00"
  },
  "repayments": [
    {
      "rd": "15/1/2013",
      "ra": 101.26139648447133
    }
  ],
  "inputs": {
    "incomeYearOfLoan": 2012,
    "fullTermOfAmalgamatedLoan": 5,
    "incomeYearOfEnquiring": 2013,
    "amalgamatedLoanNotPaidByEOIY": 101.26139648447148,
    "repayments": null,
    "lodgement_date": "5/12/2012"
  },
  "idx": 1264
}