{
  "id": "2023-09-06T22:50:27.954Z0.10784461895654651",
  "alert": "Start of result\nResult\n\nMinimum yearly repayment met.\n\nThe amount of the loan not repaid at the end of income year 2001-02 is $1,902.37.\n\nThe amalgamated loan will not be taken to be a dividend because the total repayments made are equal to or greater than the minimum yearly repayment required for income year 2001-02.\n\nInterest received by the private company must be included in the income tax return for 2001-02.\n\nMinimum yearly repayment\n\n$1,954.00\n\nBenchmark interest rate\n\n6.8%\n\nOpening balance:\n\nDate: 30/06/2001\n\nBalance: $6,650.00\n\nDays: 360\n\nInterest: $446.01\n\nPayments\n\nDate: 26/06/2002\n\nAmount: $5,195.00\n\nBalance: $1,455.00\n\nDays: 5\n\nInterest: $1.36\n\n\n\n\nTotal repayments\n\n$5,195.00\n\nTotal interest\n\n$447.37\n\nTotal principal\n\n$4,747.63\n\nClosing balance\n\nDate: 30/06/2002\n\nBalance: $1,902.37",
  "outputs": {
    "enquiryRateFormatted": "6.8%",
    "enquiryYearEndMinusOneDisplay": "30/06/2001",
    "amalgamatedLoanNotPaidByEOIYFormatted": "$6,650.00",
    "openingBalancePayDays": "360",
    "openingBalanceInterestFormatted": "$446.01",
    "totalAmountOfRepaymentFormatted": "$5,195.00",
    "totalInterestFormatted": "$447.37",
    "principalFormatted": "$4,747.63",
    "enquiryYearEndDisplay": "30/06/2002",
    "minimumYearRepaymentFormatted": "$1,954.00"
  },
  "repayments": [
    {
      "rd": "26/6/2002",
      "ra": 5195
    }
  ],
  "inputs": {
    "incomeYearOfLoan": 2001,
    "fullTermOfAmalgamatedLoan": 4,
    "incomeYearOfEnquiring": 2002,
    "amalgamatedLoanNotPaidByEOIY": 6650,
    "repayments": null,
    "lodgement_date": "29/8/2001"
  },
  "idx": 1163
}