{
  "id": "2023-10-31T17:44:23.749Z0.47776918375300126",
  "alert": "Start of result\nResult\n\nAmalgamated loan fully repaid.\n\nThe amalgamated loan has been paid in full.\u000bThe private company is not taken under Division 7A to pay a dividend to the shareholder or shareholder's associate.\n\nInterest received by the private company must be included in the income tax return for 2014-15.\n\nMinimum yearly repayment\n\n-$4,432.00\n\nBenchmark interest rate\n\n5.95%\n\nOpening balance:\n\nDate: 30/06/2014\n\nBalance: $5,723.00\n\nDays: 68\n\nInterest: $63.44\n\nPayments\n\nDate: 07/09/2014\n\nAmount: $9,906.00\n\nBalance: $0\n\nDays: 297\n\nInterest: $0\n\n\n\n\nTotal repayments\n\n$9,906.00\n\nTotal interest\n\n$63.44\n\nTotal principal\n\n$9,842.56\n\nClosing balance\n\nDate: 30/06/2015\n\nBalance: $0",
  "outputs": {
    "enquiryRateFormatted": "5.95%",
    "enquiryYearEndMinusOneDisplay": "30/06/2014",
    "amalgamatedLoanNotPaidByEOIYFormatted": "$5,723.00",
    "openingBalancePayDays": "68",
    "openingBalanceInterestFormatted": "$63.44",
    "totalAmountOfRepaymentFormatted": "$9,906.00",
    "totalInterestFormatted": "$63.44",
    "principalFormatted": "$9,842.56",
    "enquiryYearEndDisplay": "30/06/2015",
    "minimumYearRepaymentFormatted": "-$4,432.00",
    "loanAmountFormatted": "$0"
  },
  "repayments": [
    {
      "rd": "7/9/2014",
      "ra": 9906
    }
  ],
  "inputs": {
    "incomeYearOfLoan": 2014,
    "fullTermOfAmalgamatedLoan": 1,
    "incomeYearOfEnquiring": 2015,
    "amalgamatedLoanNotPaidByEOIY": 5723,
    "repayments": null,
    "lodgement_date": "28/12/2014"
  },
  "idx": 2429
}