{
  "id": "2023-10-31T20:03:13.554Z0.5545635257497556",
  "alert": "Start of result\nResult\n\nAmalgamated loan fully repaid.\n\nThe amalgamated loan has been paid in full.\u000bThe private company is not taken under Division 7A to pay a dividend to the shareholder or shareholder's associate.\n\nInterest received by the private company must be included in the income tax return for 2007-08.\n\nMinimum yearly repayment\n\n$74.00\n\nBenchmark interest rate\n\n8.05%\n\nOpening balance:\n\nDate: 30/06/2007\n\nBalance: $68.03\n\nDays: 243\n\nInterest: $3.64\n\nPayments\n\nDate: 29/02/2008\n\nAmount: $680.35\n\nBalance: $0\n\nDays: 123\n\nInterest: $0\n\n\n\n\nTotal repayments\n\n$680.35\n\nTotal interest\n\n$3.64\n\nTotal principal\n\n$676.71\n\nClosing balance\n\nDate: 30/06/2008\n\nBalance: $0",
  "outputs": {
    "enquiryRateFormatted": "8.05%",
    "enquiryYearEndMinusOneDisplay": "30/06/2007",
    "amalgamatedLoanNotPaidByEOIYFormatted": "$68.03",
    "openingBalancePayDays": "243",
    "openingBalanceInterestFormatted": "$3.64",
    "totalAmountOfRepaymentFormatted": "$680.35",
    "totalInterestFormatted": "$3.64",
    "principalFormatted": "$676.71",
    "enquiryYearEndDisplay": "30/06/2008",
    "minimumYearRepaymentFormatted": "$74.00",
    "loanAmountFormatted": "$0"
  },
  "repayments": [
    {
      "rd": "29/2/2008",
      "ra": 680.3515988549766
    }
  ],
  "inputs": {
    "incomeYearOfLoan": 2002,
    "fullTermOfAmalgamatedLoan": 6,
    "incomeYearOfEnquiring": 2008,
    "amalgamatedLoanNotPaidByEOIY": 68.03515988549765,
    "repayments": null,
    "lodgement_date": null
  },
  "idx": 6122
}