{
  "id": "2023-10-31T18:37:49.762Z0.9576808563338443",
  "alert": "Start of result\nResult\n\nMinimum yearly repayment not met.\n\nThe amount of the loan not repaid at the end of income year 2008-09 is $10,015.00.\n\nThe private company may be taken to pay a dividend under Division 7A to the shareholder or shareholder's associate because the amount repaid during income year 2008-09 in relation to the amalgamated loan is less than the minimum yearly repayment required.\n\nInterest received by the private company must be included in the income tax return for 2008-09.\n\nMinimum yearly repayment\n\n$3,988.00\n\nBenchmark interest rate\n\n9.45%\n\nOpening balance:\n\nDate: 30/06/2008\n\nBalance: $10,015.00\n\nDays: 278\n\nInterest: $720.83\n\nPayments\n\nDate: 05/04/2009\n\nAmount: $364.00\n\nBalance: $9,651.00\n\nDays: 87\n\nInterest: $217.39\n\n\n\n\nTotal repayments\n\n$364.00\n\nTotal interest\n\n$938.22\n\nTotal principal\n\n$0\n\nClosing balance\n\nDate: 30/06/2009\n\nBalance: $10,015.00",
  "outputs": {
    "enquiryRateFormatted": "9.45%",
    "enquiryYearEndMinusOneDisplay": "30/06/2008",
    "amalgamatedLoanNotPaidByEOIYFormatted": "$10,015.00",
    "openingBalancePayDays": "278",
    "openingBalanceInterestFormatted": "$720.83",
    "totalAmountOfRepaymentFormatted": "$364.00",
    "totalInterestFormatted": "$938.22",
    "principalFormatted": "$0",
    "enquiryYearEndDisplay": "30/06/2009",
    "minimumYearRepaymentFormatted": "$3,988.00",
    "loanAmountFormatted": "$10,015.00"
  },
  "repayments": [
    {
      "rd": "5/4/2009",
      "ra": 364
    }
  ],
  "inputs": {
    "incomeYearOfLoan": 2008,
    "fullTermOfAmalgamatedLoan": 3,
    "incomeYearOfEnquiring": 2009,
    "amalgamatedLoanNotPaidByEOIY": 10015,
    "repayments": null,
    "lodgement_date": "28/11/2008"
  },
  "idx": 4296
}