{
  "id": "2023-09-07T02:30:43.300Z0.18004601392165887",
  "alert": "Start of result\nResult\n\nMinimum yearly repayment not met.\n\nThe amount of the loan not repaid at the end of income year 2003-04 is $10,336.77.\n\nThe private company may be taken to pay a dividend under Division 7A to the shareholder or shareholder's associate because the amount repaid during income year 2003-04 in relation to the amalgamated loan is less than the minimum yearly repayment required.\n\nInterest received by the private company must be included in the income tax return for 2003-04.\n\nMinimum yearly repayment\n\n$4,321.00\n\nBenchmark interest rate\n\n6.55%\n\nOpening balance:\n\nDate: 30/06/2003\n\nBalance: $11,433.00\n\nDays: 194\n\nInterest: $396.94\n\nPayments\n\nDate: 11/01/2004\n\nAmount: $1,790.00\n\nBalance: $9,643.00\n\nDays: 172\n\nInterest: $296.83\n\n\n\n\nTotal repayments\n\n$1,790.00\n\nTotal interest\n\n$693.77\n\nTotal principal\n\n$1,096.23\n\nClosing balance\n\nDate: 30/06/2004\n\nBalance: $10,336.77",
  "outputs": {
    "enquiryRateFormatted": "6.55%",
    "enquiryYearEndMinusOneDisplay": "30/06/2003",
    "amalgamatedLoanNotPaidByEOIYFormatted": "$11,433.00",
    "openingBalancePayDays": "194",
    "openingBalanceInterestFormatted": "$396.94",
    "totalAmountOfRepaymentFormatted": "$1,790.00",
    "totalInterestFormatted": "$693.77",
    "principalFormatted": "$1,096.23",
    "enquiryYearEndDisplay": "30/06/2004",
    "minimumYearRepaymentFormatted": "$4,321.00"
  },
  "repayments": [
    {
      "rd": "11/1/2004",
      "ra": 1790
    }
  ],
  "inputs": {
    "incomeYearOfLoan": 1999,
    "fullTermOfAmalgamatedLoan": 7,
    "incomeYearOfEnquiring": 2004,
    "amalgamatedLoanNotPaidByEOIY": 11433,
    "repayments": null,
    "lodgement_date": null
  },
  "idx": 5173
}