{
  "id": "2023-10-31T17:52:10.224Z0.29048763547739276",
  "alert": "Start of result\nResult\n\nAmalgamated loan fully repaid.\n\nThe amalgamated loan has been paid in full.\u000bThe private company is not taken under Division 7A to pay a dividend to the shareholder or shareholder's associate.\n\nInterest received by the private company must be included in the income tax return for 2015-16.\n\nMinimum yearly repayment\n\n$9.00\n\nBenchmark interest rate\n\n5.45%\n\nOpening balance:\n\nDate: 30/06/2015\n\nBalance: $42.59\n\nDays: 122\n\nInterest: $0.77\n\nPayments\n\nDate: 31/10/2015\n\nAmount: $425.98\n\nBalance: $0\n\nDays: 244\n\nInterest: $0\n\n\n\n\nTotal repayments\n\n$425.98\n\nTotal interest\n\n$0.77\n\nTotal principal\n\n$425.21\n\nClosing balance\n\nDate: 30/06/2016\n\nBalance: $0",
  "outputs": {
    "enquiryRateFormatted": "5.45%",
    "enquiryYearEndMinusOneDisplay": "30/06/2015",
    "amalgamatedLoanNotPaidByEOIYFormatted": "$42.59",
    "openingBalancePayDays": "122",
    "openingBalanceInterestFormatted": "$0.77",
    "totalAmountOfRepaymentFormatted": "$425.98",
    "totalInterestFormatted": "$0.77",
    "principalFormatted": "$425.21",
    "enquiryYearEndDisplay": "30/06/2016",
    "minimumYearRepaymentFormatted": "$9.00",
    "loanAmountFormatted": "$0"
  },
  "repayments": [
    {
      "rd": "31/10/2015",
      "ra": 425.98491400902094
    }
  ],
  "inputs": {
    "incomeYearOfLoan": 2014,
    "fullTermOfAmalgamatedLoan": 7,
    "incomeYearOfEnquiring": 2016,
    "amalgamatedLoanNotPaidByEOIY": 42.59849140090214,
    "repayments": null,
    "lodgement_date": null
  },
  "idx": 2776
}