{
  "id": "2023-09-06T14:41:15.290Z0.2082056964374266",
  "alert": "Start of result\nResult\n\nMinimum yearly repayment not met.\n\nThe amount of the loan not repaid at the end of income year 2010-11 is $5.04.\n\nThe private company may be taken to pay a dividend under Division 7A to the shareholder or shareholder's associate because the amount repaid during income year 2010-11 in relation to the amalgamated loan is less than the minimum yearly repayment required.\n\nInterest received by the private company must be included in the income tax return for 2010-11.\n\nMinimum yearly repayment\n\n$133.00\n\nBenchmark interest rate\n\n7.4%\n\nOpening balance:\n\nDate: 30/06/2010\n\nBalance: $123.69\n\nDays: 201\n\nInterest: $5.04\n\nPayments\n\nDate: 18/01/2011\n\nAmount: $123.69\n\nBalance: $0\n\nDays: 164\n\nInterest: $0\n\n\n\n\nTotal repayments\n\n$123.69\n\nTotal interest\n\n$5.04\n\nTotal principal\n\n$118.65\n\nClosing balance\n\nDate: 30/06/2011\n\nBalance: $5.04",
  "outputs": {
    "enquiryRateFormatted": "7.4%",
    "enquiryYearEndMinusOneDisplay": "30/06/2010",
    "amalgamatedLoanNotPaidByEOIYFormatted": "$123.69",
    "openingBalancePayDays": "201",
    "openingBalanceInterestFormatted": "$5.04",
    "totalAmountOfRepaymentFormatted": "$123.69",
    "totalInterestFormatted": "$5.04",
    "principalFormatted": "$118.65",
    "enquiryYearEndDisplay": "30/06/2011",
    "minimumYearRepaymentFormatted": "$133.00"
  },
  "repayments": [
    {
      "rd": "18/1/2011",
      "ra": 123.69699355271246
    }
  ],
  "inputs": {
    "incomeYearOfLoan": 2006,
    "fullTermOfAmalgamatedLoan": 5,
    "incomeYearOfEnquiring": 2011,
    "amalgamatedLoanNotPaidByEOIY": 123.69699355271256,
    "repayments": null,
    "lodgement_date": null
  },
  "idx": 6275
}