{
  "id": "2023-10-31T19:05:11.133Z0.4555274434012724",
  "alert": "Start of result\nResult\n\nAmalgamated loan fully repaid.\n\nThe amalgamated loan has been paid in full.\u000bThe private company is not taken under Division 7A to pay a dividend to the shareholder or shareholder's associate.\n\nInterest received by the private company must be included in the income tax return for 2009-10.\n\nMinimum yearly repayment\n\n$32.00\n\nBenchmark interest rate\n\n5.75%\n\nOpening balance:\n\nDate: 30/06/2009\n\nBalance: $58.88\n\nDays: 102\n\nInterest: $0.95\n\nPayments\n\nDate: 11/10/2009\n\nAmount: $588.88\n\nBalance: $0\n\nDays: 263\n\nInterest: $0\n\n\n\n\nTotal repayments\n\n$588.88\n\nTotal interest\n\n$0.95\n\nTotal principal\n\n$587.93\n\nClosing balance\n\nDate: 30/06/2010\n\nBalance: $0",
  "outputs": {
    "enquiryRateFormatted": "5.75%",
    "enquiryYearEndMinusOneDisplay": "30/06/2009",
    "amalgamatedLoanNotPaidByEOIYFormatted": "$58.88",
    "openingBalancePayDays": "102",
    "openingBalanceInterestFormatted": "$0.95",
    "totalAmountOfRepaymentFormatted": "$588.88",
    "totalInterestFormatted": "$0.95",
    "principalFormatted": "$587.93",
    "enquiryYearEndDisplay": "30/06/2010",
    "minimumYearRepaymentFormatted": "$32.00",
    "loanAmountFormatted": "$0"
  },
  "repayments": [
    {
      "rd": "11/10/2009",
      "ra": 588.889191377777
    }
  ],
  "inputs": {
    "incomeYearOfLoan": 2006,
    "fullTermOfAmalgamatedLoan": 5,
    "incomeYearOfEnquiring": 2010,
    "amalgamatedLoanNotPaidByEOIY": 58.88891913777767,
    "repayments": null,
    "lodgement_date": null
  },
  "idx": 4996
}