{
  "id": "2023-09-06T18:14:25.129Z0.6307019479847571",
  "alert": "Start of result\nResult\n\nMinimum yearly repayment met.\n\nThe amount of the loan not repaid at the end of income year 2007-08 is $0.59.\n\nThe amalgamated loan will not be taken to be a dividend because the total repayments made are equal to or greater than the minimum yearly repayment required for income year 2007-08.\n\nInterest received by the private company must be included in the income tax return for 2007-08.\n\nMinimum yearly repayment\n\n$5.00\n\nBenchmark interest rate\n\n8.05%\n\nOpening balance:\n\nDate: 30/06/2007\n\nBalance: $9.61\n\nDays: 277\n\nInterest: $0.59\n\nPayments\n\nDate: 03/04/2008\n\nAmount: $9.61\n\nBalance: $0\n\nDays: 89\n\nInterest: $0\n\n\n\n\nTotal repayments\n\n$9.61\n\nTotal interest\n\n$0.59\n\nTotal principal\n\n$9.02\n\nClosing balance\n\nDate: 30/06/2008\n\nBalance: $0.59",
  "outputs": {
    "enquiryRateFormatted": "8.05%",
    "enquiryYearEndMinusOneDisplay": "30/06/2007",
    "amalgamatedLoanNotPaidByEOIYFormatted": "$9.61",
    "openingBalancePayDays": "277",
    "openingBalanceInterestFormatted": "$0.59",
    "totalAmountOfRepaymentFormatted": "$9.61",
    "totalInterestFormatted": "$0.59",
    "principalFormatted": "$9.02",
    "enquiryYearEndDisplay": "30/06/2008",
    "minimumYearRepaymentFormatted": "$5.00"
  },
  "repayments": [
    {
      "rd": "3/4/2008",
      "ra": 9.615166579340439
    }
  ],
  "inputs": {
    "incomeYearOfLoan": 2004,
    "fullTermOfAmalgamatedLoan": 5,
    "incomeYearOfEnquiring": 2008,
    "amalgamatedLoanNotPaidByEOIY": 9.615166579340173,
    "repayments": null,
    "lodgement_date": null
  },
  "idx": 1473
}