{
  "id": "2023-09-04T22:02:04.709Z0.2947916231514589",
  "alert": "Start of result\nResult\n\nMinimum yearly repayment not met.\n\nThe amount of the loan not repaid at the end of income year 2006-07 is $9,400.95.\n\nThe private company may be taken to pay a dividend under Division 7A to the shareholder or shareholder's associate because the amount repaid during income year 2006-07 in relation to the amalgamated loan is less than the minimum yearly repayment required.\n\nInterest received by the private company must be included in the income tax return for 2006-07.\n\nMinimum yearly repayment\n\n$6,310.00\n\nBenchmark interest rate\n\n7.55%\n\nOpening balance:\n\nDate: 30/06/2006\n\nBalance: $11,322.00\n\nDays: 0\n\nInterest: $0\n\nPayments\n\nDate: 01/07/2006\n\nAmount: $2,581.00\n\nBalance: $8,741.00\n\nDays: 365\n\nInterest: $659.95\n\n\n\n\nTotal repayments\n\n$2,581.00\n\nTotal interest\n\n$659.95\n\nTotal principal\n\n$1,921.05\n\nClosing balance\n\nDate: 30/06/2007\n\nBalance: $9,400.95",
  "outputs": {
    "enquiryRateFormatted": "7.55%",
    "enquiryYearEndMinusOneDisplay": "30/06/2006",
    "amalgamatedLoanNotPaidByEOIYFormatted": "$11,322.00",
    "openingBalancePayDays": "0",
    "openingBalanceInterestFormatted": "$0",
    "totalAmountOfRepaymentFormatted": "$2,581.00",
    "totalInterestFormatted": "$659.95",
    "principalFormatted": "$1,921.05",
    "enquiryYearEndDisplay": "30/06/2007",
    "minimumYearRepaymentFormatted": "$6,310.00"
  },
  "repayments": [
    {
      "rd": "1/7/2006",
      "ra": 2581
    }
  ],
  "inputs": {
    "incomeYearOfLoan": 2004,
    "fullTermOfAmalgamatedLoan": 4,
    "incomeYearOfEnquiring": 2007,
    "amalgamatedLoanNotPaidByEOIY": 11322,
    "repayments": null,
    "lodgement_date": null
  },
  "idx": 47
}