{
  "id": "2023-09-05T17:21:36.483Z0.6567016961740293",
  "alert": "Start of result\nResult\n\nMinimum yearly repayment met.\n\nThe amount of the loan not repaid at the end of income year 2022-23 is $108.33.\n\nThe amalgamated loan will not be taken to be a dividend because the total repayments made are equal to or greater than the minimum yearly repayment required for income year 2022-23.\n\nInterest received by the private company must be included in the income tax return for 2022-23.\n\nMinimum yearly repayment\n\n$1,453.00\n\nBenchmark interest rate\n\n4.77%\n\nOpening balance:\n\nDate: 30/06/2022\n\nBalance: $5,181.00\n\nDays: 160\n\nInterest: $108.33\n\nPayments\n\nDate: 08/12/2022\n\nAmount: $5,181.00\n\nBalance: $0\n\nDays: 205\n\nInterest: $0\n\n\n\n\nTotal repayments\n\n$5,181.00\n\nTotal interest\n\n$108.33\n\nTotal principal\n\n$5,072.67\n\nClosing balance\n\nDate: 30/06/2023\n\nBalance: $108.33",
  "outputs": {
    "enquiryRateFormatted": "4.77%",
    "enquiryYearEndMinusOneDisplay": "30/06/2022",
    "amalgamatedLoanNotPaidByEOIYFormatted": "$5,181.00",
    "openingBalancePayDays": "160",
    "openingBalanceInterestFormatted": "$108.33",
    "totalAmountOfRepaymentFormatted": "$5,181.00",
    "totalInterestFormatted": "$108.33",
    "principalFormatted": "$5,072.67",
    "enquiryYearEndDisplay": "30/06/2023",
    "minimumYearRepaymentFormatted": "$1,453.00"
  },
  "repayments": [
    {
      "rd": "8/12/2022",
      "ra": 5181
    }
  ],
  "inputs": {
    "incomeYearOfLoan": 2019,
    "fullTermOfAmalgamatedLoan": 7,
    "incomeYearOfEnquiring": 2023,
    "amalgamatedLoanNotPaidByEOIY": 5181,
    "repayments": null,
    "lodgement_date": null
  },
  "idx": 4072
}