{
  "id": "2023-10-31T18:36:02.452Z0.5350384258610166",
  "alert": "Start of result\nResult\n\nAmalgamated loan fully repaid.\n\nThe amalgamated loan has been paid in full.\u000bThe private company is not taken under Division 7A to pay a dividend to the shareholder or shareholder's associate.\n\nInterest received by the private company must be included in the income tax return for 2009-10.\n\nMinimum yearly repayment\n\n$2,712.00\n\nBenchmark interest rate\n\n5.75%\n\nOpening balance:\n\nDate: 30/06/2009\n\nBalance: $2,565.00\n\nDays: 149\n\nInterest: $60.21\n\nPayments\n\nDate: 27/11/2009\n\nAmount: $6,597.00\n\nBalance: $0\n\nDays: 216\n\nInterest: $0\n\n\n\n\nTotal repayments\n\n$6,597.00\n\nTotal interest\n\n$60.21\n\nTotal principal\n\n$6,536.79\n\nClosing balance\n\nDate: 30/06/2010\n\nBalance: $0",
  "outputs": {
    "enquiryRateFormatted": "5.75%",
    "enquiryYearEndMinusOneDisplay": "30/06/2009",
    "amalgamatedLoanNotPaidByEOIYFormatted": "$2,565.00",
    "openingBalancePayDays": "149",
    "openingBalanceInterestFormatted": "$60.21",
    "totalAmountOfRepaymentFormatted": "$6,597.00",
    "totalInterestFormatted": "$60.21",
    "principalFormatted": "$6,536.79",
    "enquiryYearEndDisplay": "30/06/2010",
    "minimumYearRepaymentFormatted": "$2,712.00",
    "loanAmountFormatted": "$0"
  },
  "repayments": [
    {
      "rd": "27/11/2009",
      "ra": 6597
    }
  ],
  "inputs": {
    "incomeYearOfLoan": 2008,
    "fullTermOfAmalgamatedLoan": 2,
    "incomeYearOfEnquiring": 2010,
    "amalgamatedLoanNotPaidByEOIY": 2565,
    "repayments": null,
    "lodgement_date": null
  },
  "idx": 4243
}