{
  "id": "2023-10-31T18:27:11.786Z0.46776714516167417",
  "alert": "Start of result\nResult\n\nMinimum yearly repayment not met.\n\nThe amount of the loan not repaid at the end of income year 2010-11 is $2,327.30.\n\nThe private company may be taken to pay a dividend under Division 7A to the shareholder or shareholder's associate because the amount repaid during income year 2010-11 in relation to the amalgamated loan is less than the minimum yearly repayment required.\n\nInterest received by the private company must be included in the income tax return for 2010-11.\n\nMinimum yearly repayment\n\n$11,136.00\n\nBenchmark interest rate\n\n7.4%\n\nOpening balance:\n\nDate: 30/06/2010\n\nBalance: $10,369.00\n\nDays: 294\n\nInterest: $618.05\n\nPayments\n\nDate: 21/04/2011\n\nAmount: $8,684.00\n\nBalance: $1,685.00\n\nDays: 71\n\nInterest: $24.25\n\n\n\n\nTotal repayments\n\n$8,684.00\n\nTotal interest\n\n$642.30\n\nTotal principal\n\n$8,041.70\n\nClosing balance\n\nDate: 30/06/2011\n\nBalance: $2,327.30",
  "outputs": {
    "enquiryRateFormatted": "7.4%",
    "enquiryYearEndMinusOneDisplay": "30/06/2010",
    "amalgamatedLoanNotPaidByEOIYFormatted": "$10,369.00",
    "openingBalancePayDays": "294",
    "openingBalanceInterestFormatted": "$618.05",
    "totalAmountOfRepaymentFormatted": "$8,684.00",
    "totalInterestFormatted": "$642.30",
    "principalFormatted": "$8,041.70",
    "enquiryYearEndDisplay": "30/06/2011",
    "minimumYearRepaymentFormatted": "$11,136.00",
    "loanAmountFormatted": "$2,327.30"
  },
  "repayments": [
    {
      "rd": "21/4/2011",
      "ra": 8684
    }
  ],
  "inputs": {
    "incomeYearOfLoan": 2009,
    "fullTermOfAmalgamatedLoan": 2,
    "incomeYearOfEnquiring": 2011,
    "amalgamatedLoanNotPaidByEOIY": 10369,
    "repayments": null,
    "lodgement_date": null
  },
  "idx": 3999
}