{
  "id": "2023-09-06T10:43:48.912Z0.0001072708611240536",
  "alert": "Start of result\nResult\n\nMinimum yearly repayment not met.\n\nThe amount of the loan not repaid at the end of income year 2008-09 is $87.00.\n\nThe private company may be taken to pay a dividend under Division 7A to the shareholder or shareholder's associate because the amount repaid during income year 2008-09 in relation to the amalgamated loan is less than the minimum yearly repayment required.\n\nInterest received by the private company must be included in the income tax return for 2008-09.\n\nMinimum yearly repayment\n\n$95.00\n\nBenchmark interest rate\n\n9.45%\n\nOpening balance:\n\nDate: 30/06/2008\n\nBalance: $87.00\n\nDays: 365\n\nInterest: $8.22\n\nTotal repayments\n\n$0\n\nTotal interest\n\n$8.22\n\nTotal principal\n\n$0\n\nClosing balance\n\nDate: 30/06/2009\n\nBalance: $87.00",
  "outputs": {
    "enquiryRateFormatted": "9.45%",
    "enquiryYearEndMinusOneDisplay": "30/06/2008",
    "amalgamatedLoanNotPaidByEOIYFormatted": "$87.00",
    "openingBalancePayDays": "365",
    "openingBalanceInterestFormatted": "$8.22",
    "totalAmountOfRepaymentFormatted": "$0",
    "totalInterestFormatted": "$8.22",
    "principalFormatted": "$0",
    "enquiryYearEndDisplay": "30/06/2009",
    "minimumYearRepaymentFormatted": "$95.00"
  },
  "repayments": [],
  "inputs": {
    "incomeYearOfLoan": 2008,
    "fullTermOfAmalgamatedLoan": 1,
    "incomeYearOfEnquiring": 2009,
    "amalgamatedLoanNotPaidByEOIY": 87,
    "repayments": null,
    "lodgement_date": "24/9/2008"
  },
  "idx": 1561
}