{
  "id": "2023-10-31T17:42:25.907Z0.3477285870968848",
  "alert": "Start of result\nResult\n\nAmalgamated loan fully repaid.\n\nThe amalgamated loan has been paid in full.\u000bThe private company is not taken under Division 7A to pay a dividend to the shareholder or shareholder's associate.\n\nInterest received by the private company must be included in the income tax return for 2017-18.\n\nMinimum yearly repayment\n\n$10.00\n\nBenchmark interest rate\n\n5.3%\n\nOpening balance:\n\nDate: 30/06/2017\n\nBalance: $33.77\n\nDays: 256\n\nInterest: $1.26\n\nPayments\n\nDate: 14/03/2018\n\nAmount: $337.74\n\nBalance: $0\n\nDays: 109\n\nInterest: $0\n\n\n\n\nTotal repayments\n\n$337.74\n\nTotal interest\n\n$1.26\n\nTotal principal\n\n$336.48\n\nClosing balance\n\nDate: 30/06/2018\n\nBalance: $0",
  "outputs": {
    "enquiryRateFormatted": "5.3%",
    "enquiryYearEndMinusOneDisplay": "30/06/2017",
    "amalgamatedLoanNotPaidByEOIYFormatted": "$33.77",
    "openingBalancePayDays": "256",
    "openingBalanceInterestFormatted": "$1.26",
    "totalAmountOfRepaymentFormatted": "$337.74",
    "totalInterestFormatted": "$1.26",
    "principalFormatted": "$336.48",
    "enquiryYearEndDisplay": "30/06/2018",
    "minimumYearRepaymentFormatted": "$10.00",
    "loanAmountFormatted": "$0"
  },
  "repayments": [
    {
      "rd": "14/3/2018",
      "ra": 337.74576027222975
    }
  ],
  "inputs": {
    "incomeYearOfLoan": 2015,
    "fullTermOfAmalgamatedLoan": 6,
    "incomeYearOfEnquiring": 2018,
    "amalgamatedLoanNotPaidByEOIY": 33.774576027222956,
    "repayments": null,
    "lodgement_date": null
  },
  "idx": 2338
}