{
  "id": "2023-09-04T22:24:54.218Z0.8788727076074738",
  "alert": "Start of result\nResult\n\nMinimum yearly repayment met.\n\nThe amount of the loan not repaid at the end of income year 2002-03 is $308.27.\n\nThe amalgamated loan will not be taken to be a dividend because the total repayments made are equal to or greater than the minimum yearly repayment required for income year 2002-03.\n\nInterest received by the private company must be included in the income tax return for 2002-03.\n\nMinimum yearly repayment\n\n$960.00\n\nBenchmark interest rate\n\n6.3%\n\nOpening balance:\n\nDate: 30/06/2002\n\nBalance: $2,552.00\n\nDays: 0\n\nInterest: $0\n\nPayments\n\nDate: 01/07/2002\n\nAmount: $2,262.00\n\nBalance: $290.00\n\nDays: 365\n\nInterest: $18.27\n\n\n\n\nTotal repayments\n\n$2,262.00\n\nTotal interest\n\n$18.27\n\nTotal principal\n\n$2,243.73\n\nClosing balance\n\nDate: 30/06/2003\n\nBalance: $308.27",
  "outputs": {
    "enquiryRateFormatted": "6.3%",
    "enquiryYearEndMinusOneDisplay": "30/06/2002",
    "amalgamatedLoanNotPaidByEOIYFormatted": "$2,552.00",
    "openingBalancePayDays": "0",
    "openingBalanceInterestFormatted": "$0",
    "totalAmountOfRepaymentFormatted": "$2,262.00",
    "totalInterestFormatted": "$18.27",
    "principalFormatted": "$2,243.73",
    "enquiryYearEndDisplay": "30/06/2003",
    "minimumYearRepaymentFormatted": "$960.00"
  },
  "repayments": [
    {
      "rd": "1/7/2002",
      "ra": 2262
    }
  ],
  "inputs": {
    "incomeYearOfLoan": 2000,
    "fullTermOfAmalgamatedLoan": 5,
    "incomeYearOfEnquiring": 2003,
    "amalgamatedLoanNotPaidByEOIY": 2552,
    "repayments": null,
    "lodgement_date": null
  },
  "idx": 889
}