{
  "id": "2023-09-05T01:22:57.744Z0.3033323918515387",
  "alert": "Start of result\nResult\n\nMinimum yearly repayment not met.\n\nThe amount of the loan not repaid at the end of income year 1999-00 is $4,953.32.\n\nThe private company may be taken to pay a dividend under Division 7A to the shareholder or shareholder's associate because the amount repaid during income year 1999-00 in relation to the amalgamated loan is less than the minimum yearly repayment required.\n\nInterest received by the private company must be included in the income tax return for 1999-00.\n\nMinimum yearly repayment\n\n$4,855.00\n\nBenchmark interest rate\n\n6.5%\n\nOpening balance:\n\nDate: 30/06/1999\n\nBalance: $8,839.00\n\nDays: 0\n\nInterest: $0\n\nPayments\n\nDate: 01/07/1999\n\nAmount: $4,188.00\n\nBalance: $4,651.00\n\nDays: 366\n\nInterest: $302.32\n\n\n\n\nTotal repayments\n\n$4,188.00\n\nTotal interest\n\n$302.32\n\nTotal principal\n\n$3,885.68\n\nClosing balance\n\nDate: 30/06/2000\n\nBalance: $4,953.32",
  "outputs": {
    "enquiryRateFormatted": "6.5%",
    "enquiryYearEndMinusOneDisplay": "30/06/1999",
    "amalgamatedLoanNotPaidByEOIYFormatted": "$8,839.00",
    "openingBalancePayDays": "0",
    "openingBalanceInterestFormatted": "$0",
    "totalAmountOfRepaymentFormatted": "$4,188.00",
    "totalInterestFormatted": "$302.32",
    "principalFormatted": "$3,885.68",
    "enquiryYearEndDisplay": "30/06/2000",
    "minimumYearRepaymentFormatted": "$4,855.00"
  },
  "repayments": [
    {
      "rd": "1/7/1999",
      "ra": 4188
    }
  ],
  "inputs": {
    "incomeYearOfLoan": 1998,
    "fullTermOfAmalgamatedLoan": 3,
    "incomeYearOfEnquiring": 2000,
    "amalgamatedLoanNotPaidByEOIY": 8839,
    "repayments": null,
    "lodgement_date": null
  },
  "idx": 1837
}