{
  "id": "2023-09-07T02:05:34.462Z0.046819365817361014",
  "alert": "Start of result\nResult\n\nMinimum yearly repayment met.\n\nThe amount of the loan not repaid at the end of income year 2001-02 is $2.90.\n\nThe amalgamated loan will not be taken to be a dividend because the total repayments made are equal to or greater than the minimum yearly repayment required for income year 2001-02.\n\nInterest received by the private company must be included in the income tax return for 2001-02.\n\nMinimum yearly repayment\n\n$27.00\n\nBenchmark interest rate\n\n6.8%\n\nOpening balance:\n\nDate: 30/06/2001\n\nBalance: $69.81\n\nDays: 223\n\nInterest: $2.90\n\nPayments\n\nDate: 09/02/2002\n\nAmount: $69.81\n\nBalance: $0\n\nDays: 142\n\nInterest: $0\n\n\n\n\nTotal repayments\n\n$69.81\n\nTotal interest\n\n$2.90\n\nTotal principal\n\n$66.91\n\nClosing balance\n\nDate: 30/06/2002\n\nBalance: $2.90",
  "outputs": {
    "enquiryRateFormatted": "6.8%",
    "enquiryYearEndMinusOneDisplay": "30/06/2001",
    "amalgamatedLoanNotPaidByEOIYFormatted": "$69.81",
    "openingBalancePayDays": "223",
    "openingBalanceInterestFormatted": "$2.90",
    "totalAmountOfRepaymentFormatted": "$69.81",
    "totalInterestFormatted": "$2.90",
    "principalFormatted": "$66.91",
    "enquiryYearEndDisplay": "30/06/2002",
    "minimumYearRepaymentFormatted": "$27.00"
  },
  "repayments": [
    {
      "rd": "9/2/2002",
      "ra": 69.81101957821807
    }
  ],
  "inputs": {
    "incomeYearOfLoan": 1999,
    "fullTermOfAmalgamatedLoan": 5,
    "incomeYearOfEnquiring": 2002,
    "amalgamatedLoanNotPaidByEOIY": 69.811019578218,
    "repayments": null,
    "lodgement_date": null
  },
  "idx": 3687
}