{
  "id": "2023-10-31T17:52:55.780Z0.11551911125643877",
  "alert": "Start of result\nResult\n\nMinimum yearly repayment met.\n\nThe amount of the loan not repaid at the end of income year 2014-15 is $960.32.\n\n\u000b\n\nThe amalgamated loan will not be taken to be a dividend because the total repayments made are equal to or greater than the minimum yearly repayment required for income year 2014-15.\n\nInterest received by the private company must be included in the income tax return for 2014-15.\n\nMinimum yearly repayment\n\n$1,278.00\n\nBenchmark interest rate\n\n5.95%\n\nOpening balance:\n\nDate: 30/06/2014\n\nBalance: $10,188.00\n\nDays: 103\n\nInterest: $171.06\n\nPayments\n\nDate: 12/10/2014\n\nAmount: $3,043.00\n\nBalance: $7,145.00\n\nDays: 81\n\nInterest: $94.34\n\n\n\n\nDate: 01/01/2015\n\nAmount: $6,470.00\n\nBalance: $675.00\n\nDays: 181\n\nInterest: $19.92\n\n\n\n\nTotal repayments\n\n$9,513.00\n\nTotal interest\n\n$285.32\n\nTotal principal\n\n$9,227.68\n\nClosing balance\n\nDate: 30/06/2015\n\nBalance: $960.32",
  "outputs": {
    "enquiryRateFormatted": "5.95%",
    "enquiryYearEndMinusOneDisplay": "30/06/2014",
    "amalgamatedLoanNotPaidByEOIYFormatted": "$10,188.00",
    "openingBalancePayDays": "103",
    "openingBalanceInterestFormatted": "$171.06",
    "totalAmountOfRepaymentFormatted": "$9,513.00",
    "totalInterestFormatted": "$285.32",
    "principalFormatted": "$9,227.68",
    "enquiryYearEndDisplay": "30/06/2015",
    "minimumYearRepaymentFormatted": "$1,278.00",
    "loanAmountFormatted": "$960.32"
  },
  "repayments": [
    {
      "rd": "12/10/2014",
      "ra": 3043
    },
    {
      "rd": "1/1/2015",
      "ra": 6470
    }
  ],
  "inputs": {
    "incomeYearOfLoan": 2014,
    "fullTermOfAmalgamatedLoan": 7,
    "incomeYearOfEnquiring": 2015,
    "amalgamatedLoanNotPaidByEOIY": 10188,
    "repayments": null,
    "lodgement_date": "28/11/2014"
  },
  "idx": 2810
}