{
  "id": "2023-09-06T02:59:06.426Z0.6941299781609034",
  "alert": "Start of result\nResult\n\nMinimum yearly repayment met.\n\nThe amount of the loan not repaid at the end of income year 2013-14 is $209.24.\n\nThe amalgamated loan will not be taken to be a dividend because the total repayments made are equal to or greater than the minimum yearly repayment required for income year 2013-14.\n\nInterest received by the private company must be included in the income tax return for 2013-14.\n\nMinimum yearly repayment\n\n$1,664.00\n\nBenchmark interest rate\n\n6.2%\n\nOpening balance:\n\nDate: 30/06/2013\n\nBalance: $4,431.00\n\nDays: 278\n\nInterest: $209.24\n\nPayments\n\nDate: 05/04/2014\n\nAmount: $4,431.00\n\nBalance: $0\n\nDays: 87\n\nInterest: $0\n\n\n\n\nTotal repayments\n\n$4,431.00\n\nTotal interest\n\n$209.24\n\nTotal principal\n\n$4,221.76\n\nClosing balance\n\nDate: 30/06/2014\n\nBalance: $209.24",
  "outputs": {
    "enquiryRateFormatted": "6.2%",
    "enquiryYearEndMinusOneDisplay": "30/06/2013",
    "amalgamatedLoanNotPaidByEOIYFormatted": "$4,431.00",
    "openingBalancePayDays": "278",
    "openingBalanceInterestFormatted": "$209.24",
    "totalAmountOfRepaymentFormatted": "$4,431.00",
    "totalInterestFormatted": "$209.24",
    "principalFormatted": "$4,221.76",
    "enquiryYearEndDisplay": "30/06/2014",
    "minimumYearRepaymentFormatted": "$1,664.00"
  },
  "repayments": [
    {
      "rd": "5/4/2014",
      "ra": 4431
    }
  ],
  "inputs": {
    "incomeYearOfLoan": 2013,
    "fullTermOfAmalgamatedLoan": 3,
    "incomeYearOfEnquiring": 2014,
    "amalgamatedLoanNotPaidByEOIY": 4431,
    "repayments": null,
    "lodgement_date": "27/1/2014"
  },
  "idx": 2412
}