{
  "id": "2023-09-04T16:57:02.029Z0.7904564239991965",
  "alert": "Start of result\nResult\n\nMinimum yearly repayment met.\n\nThe amount of the loan not repaid at the end of income year 2016-17 is $394.20.\n\nThe amalgamated loan will not be taken to be a dividend because the total repayments made are equal to or greater than the minimum yearly repayment required for income year 2016-17.\n\nInterest received by the private company must be included in the income tax return for 2016-17.\n\nMinimum yearly repayment\n\n$1,121.00\n\nBenchmark interest rate\n\n5.4%\n\nOpening balance:\n\nDate: 30/06/2016\n\nBalance: $5,618.00\n\nDays: 0\n\nInterest: $0\n\nPayments\n\nDate: 01/07/2016\n\nAmount: $5,244.00\n\nBalance: $374.00\n\nDays: 365\n\nInterest: $20.20\n\n\n\n\nTotal repayments\n\n$5,244.00\n\nTotal interest\n\n$20.20\n\nTotal principal\n\n$5,223.80\n\nClosing balance\n\nDate: 30/06/2017\n\nBalance: $394.20",
  "outputs": {
    "enquiryRateFormatted": "5.4%",
    "enquiryYearEndMinusOneDisplay": "30/06/2016",
    "amalgamatedLoanNotPaidByEOIYFormatted": "$5,618.00",
    "openingBalancePayDays": "0",
    "openingBalanceInterestFormatted": "$0",
    "totalAmountOfRepaymentFormatted": "$5,244.00",
    "totalInterestFormatted": "$20.20",
    "principalFormatted": "$5,223.80",
    "enquiryYearEndDisplay": "30/06/2017",
    "minimumYearRepaymentFormatted": "$1,121.00"
  },
  "repayments": [
    {
      "rd": "1/7/2016",
      "ra": 5244
    }
  ],
  "inputs": {
    "incomeYearOfLoan": 2015,
    "fullTermOfAmalgamatedLoan": 7,
    "incomeYearOfEnquiring": 2017,
    "amalgamatedLoanNotPaidByEOIY": 5618,
    "repayments": null,
    "lodgement_date": null
  },
  "idx": 1445
}