{
  "id": "2023-09-04T22:10:07.214Z0.9537536398076034",
  "alert": "Start of result\nResult\n\nMinimum yearly repayment met.\n\nThe amount of the loan not repaid at the end of income year 2004-05 is $2,507.11.\n\nThe amalgamated loan will not be taken to be a dividend because the total repayments made are equal to or greater than the minimum yearly repayment required for income year 2004-05.\n\nInterest received by the private company must be included in the income tax return for 2004-05.\n\nMinimum yearly repayment\n\n$5,472.00\n\nBenchmark interest rate\n\n7.05%\n\nOpening balance:\n\nDate: 30/06/2004\n\nBalance: $9,887.00\n\nDays: 0\n\nInterest: $0\n\nPayments\n\nDate: 01/07/2004\n\nAmount: $7,545.00\n\nBalance: $2,342.00\n\nDays: 365\n\nInterest: $165.11\n\n\n\n\nTotal repayments\n\n$7,545.00\n\nTotal interest\n\n$165.11\n\nTotal principal\n\n$7,379.89\n\nClosing balance\n\nDate: 30/06/2005\n\nBalance: $2,507.11",
  "outputs": {
    "enquiryRateFormatted": "7.05%",
    "enquiryYearEndMinusOneDisplay": "30/06/2004",
    "amalgamatedLoanNotPaidByEOIYFormatted": "$9,887.00",
    "openingBalancePayDays": "0",
    "openingBalanceInterestFormatted": "$0",
    "totalAmountOfRepaymentFormatted": "$7,545.00",
    "totalInterestFormatted": "$165.11",
    "principalFormatted": "$7,379.89",
    "enquiryYearEndDisplay": "30/06/2005",
    "minimumYearRepaymentFormatted": "$5,472.00"
  },
  "repayments": [
    {
      "rd": "1/7/2004",
      "ra": 7545
    }
  ],
  "inputs": {
    "incomeYearOfLoan": 2002,
    "fullTermOfAmalgamatedLoan": 4,
    "incomeYearOfEnquiring": 2005,
    "amalgamatedLoanNotPaidByEOIY": 9887,
    "repayments": null,
    "lodgement_date": null
  },
  "idx": 370
}