{
  "id": "2023-09-06T16:55:30.629Z0.8775698405667176",
  "alert": "Start of result\nResult\n\nMinimum yearly repayment met.\n\nThe amount of the loan not repaid at the end of income year 2007-08 is $0.07.\n\nThe amalgamated loan will not be taken to be a dividend because the total repayments made are equal to or greater than the minimum yearly repayment required for income year 2007-08.\n\nInterest received by the private company must be included in the income tax return for 2007-08.\n\nMinimum yearly repayment\n\n$38.00\n\nBenchmark interest rate\n\n8.05%\n\nOpening balance:\n\nDate: 30/06/2007\n\nBalance: $150.00\n\nDays: 2\n\nInterest: $0.07\n\nPayments\n\nDate: 03/07/2007\n\nAmount: $150.00\n\nBalance: $0\n\nDays: 364\n\nInterest: $0\n\n\n\n\nTotal repayments\n\n$150.00\n\nTotal interest\n\n$0.07\n\nTotal principal\n\n$149.93\n\nClosing balance\n\nDate: 30/06/2008\n\nBalance: $0.07",
  "outputs": {
    "enquiryRateFormatted": "8.05%",
    "enquiryYearEndMinusOneDisplay": "30/06/2007",
    "amalgamatedLoanNotPaidByEOIYFormatted": "$150.00",
    "openingBalancePayDays": "2",
    "openingBalanceInterestFormatted": "$0.07",
    "totalAmountOfRepaymentFormatted": "$150.00",
    "totalInterestFormatted": "$0.07",
    "principalFormatted": "$149.93",
    "enquiryYearEndDisplay": "30/06/2008",
    "minimumYearRepaymentFormatted": "$38.00"
  },
  "repayments": [
    {
      "rd": "3/7/2007",
      "ra": 150
    }
  ],
  "inputs": {
    "incomeYearOfLoan": 2005,
    "fullTermOfAmalgamatedLoan": 7,
    "incomeYearOfEnquiring": 2008,
    "amalgamatedLoanNotPaidByEOIY": 150,
    "repayments": null,
    "lodgement_date": null
  },
  "idx": 5536
}