{
  "id": "2023-09-04T16:26:14.199Z0.07460162404347903",
  "alert": "Start of result\nResult\n\nMinimum yearly repayment not met.\n\nThe amount of the loan not repaid at the end of income year 2019-20 is $3,297.03.\n\nThe private company may be taken to pay a dividend under Division 7A to the shareholder or shareholder's associate because the amount repaid during income year 2019-20 in relation to the amalgamated loan is less than the minimum yearly repayment required.\n\nInterest received by the private company must be included in the income tax return for 2019-20.\n\nMinimum yearly repayment\n\n$624.00\n\nBenchmark interest rate\n\n5.37%\n\nOpening balance:\n\nDate: 30/06/2019\n\nBalance: $3,447.00\n\nDays: 0\n\nInterest: $0\n\nPayments\n\nDate: 01/07/2019\n\nAmount: $318.00\n\nBalance: $3,129.00\n\nDays: 366\n\nInterest: $168.03\n\n\n\n\nTotal repayments\n\n$318.00\n\nTotal interest\n\n$168.03\n\nTotal principal\n\n$149.97\n\nClosing balance\n\nDate: 30/06/2020\n\nBalance: $3,297.03",
  "outputs": {
    "enquiryRateFormatted": "5.37%",
    "enquiryYearEndMinusOneDisplay": "30/06/2019",
    "amalgamatedLoanNotPaidByEOIYFormatted": "$3,447.00",
    "openingBalancePayDays": "0",
    "openingBalanceInterestFormatted": "$0",
    "totalAmountOfRepaymentFormatted": "$318.00",
    "totalInterestFormatted": "$168.03",
    "principalFormatted": "$149.97",
    "enquiryYearEndDisplay": "30/06/2020",
    "minimumYearRepaymentFormatted": "$624.00"
  },
  "repayments": [
    {
      "rd": "1/7/2019",
      "ra": 318
    }
  ],
  "inputs": {
    "incomeYearOfLoan": 2019,
    "fullTermOfAmalgamatedLoan": 6,
    "incomeYearOfEnquiring": 2020,
    "amalgamatedLoanNotPaidByEOIY": 3447,
    "repayments": null,
    "lodgement_date": "26/4/2020"
  },
  "idx": 505
}