{
  "id": "2023-10-31T17:25:58.625Z0.47459277937695876",
  "alert": "Start of result\nResult\n\nAmalgamated loan fully repaid.\n\nThe amalgamated loan has been paid in full.\u000bThe private company is not taken under Division 7A to pay a dividend to the shareholder or shareholder's associate.\n\nInterest received by the private company must be included in the income tax return for 2023-24.\n\nMinimum yearly repayment\n\n$38.00\n\nBenchmark interest rate\n\n8.27%\n\nOpening balance:\n\nDate: 30/06/2023\n\nBalance: $67.77\n\nDays: 196\n\nInterest: $3.00\n\nPayments\n\nDate: 13/01/2024\n\nAmount: $677.73\n\nBalance: $0\n\nDays: 170\n\nInterest: $0\n\n\n\n\nTotal repayments\n\n$677.73\n\nTotal interest\n\n$3.00\n\nTotal principal\n\n$674.73\n\nClosing balance\n\nDate: 30/06/2024\n\nBalance: $0",
  "outputs": {
    "enquiryRateFormatted": "8.27%",
    "enquiryYearEndMinusOneDisplay": "30/06/2023",
    "amalgamatedLoanNotPaidByEOIYFormatted": "$67.77",
    "openingBalancePayDays": "196",
    "openingBalanceInterestFormatted": "$3.00",
    "totalAmountOfRepaymentFormatted": "$677.73",
    "totalInterestFormatted": "$3.00",
    "principalFormatted": "$674.73",
    "enquiryYearEndDisplay": "30/06/2024",
    "minimumYearRepaymentFormatted": "$38.00",
    "loanAmountFormatted": "$0"
  },
  "repayments": [
    {
      "rd": "13/1/2024",
      "ra": 677.7388529512727
    }
  ],
  "inputs": {
    "incomeYearOfLoan": 2018,
    "fullTermOfAmalgamatedLoan": 7,
    "incomeYearOfEnquiring": 2024,
    "amalgamatedLoanNotPaidByEOIY": 67.77388529512724,
    "repayments": null,
    "lodgement_date": null
  },
  "idx": 1466
}