{
  "id": "2023-09-06T16:42:05.249Z0.17055885497623513",
  "alert": "Start of result\nResult\n\nMinimum yearly repayment met.\n\nThe amount of the loan not repaid at the end of income year 2007-08 is $3,762.36.\n\nThe amalgamated loan will not be taken to be a dividend because the total repayments made are equal to or greater than the minimum yearly repayment required for income year 2007-08.\n\nInterest received by the private company must be included in the income tax return for 2007-08.\n\nMinimum yearly repayment\n\n$2,614.00\n\nBenchmark interest rate\n\n8.05%\n\nOpening balance:\n\nDate: 30/06/2007\n\nBalance: $8,648.00\n\nDays: 279\n\nInterest: $530.68\n\nPayments\n\nDate: 05/04/2008\n\nAmount: $5,477.00\n\nBalance: $3,171.00\n\nDays: 87\n\nInterest: $60.68\n\n\n\n\nTotal repayments\n\n$5,477.00\n\nTotal interest\n\n$591.36\n\nTotal principal\n\n$4,885.64\n\nClosing balance\n\nDate: 30/06/2008\n\nBalance: $3,762.36",
  "outputs": {
    "enquiryRateFormatted": "8.05%",
    "enquiryYearEndMinusOneDisplay": "30/06/2007",
    "amalgamatedLoanNotPaidByEOIYFormatted": "$8,648.00",
    "openingBalancePayDays": "279",
    "openingBalanceInterestFormatted": "$530.68",
    "totalAmountOfRepaymentFormatted": "$5,477.00",
    "totalInterestFormatted": "$591.36",
    "principalFormatted": "$4,885.64",
    "enquiryYearEndDisplay": "30/06/2008",
    "minimumYearRepaymentFormatted": "$2,614.00"
  },
  "repayments": [
    {
      "rd": "5/4/2008",
      "ra": 5477
    }
  ],
  "inputs": {
    "incomeYearOfLoan": 2005,
    "fullTermOfAmalgamatedLoan": 6,
    "incomeYearOfEnquiring": 2008,
    "amalgamatedLoanNotPaidByEOIY": 8648,
    "repayments": null,
    "lodgement_date": null
  },
  "idx": 4791
}