{
  "id": "2023-10-31T17:59:36.595Z0.6940890265565812",
  "alert": "Start of result\nResult\n\nAmalgamated loan fully repaid.\n\nThe amalgamated loan has been paid in full.\u000bThe private company is not taken under Division 7A to pay a dividend to the shareholder or shareholder's associate.\n\nInterest received by the private company must be included in the income tax return for 2013-14.\n\nMinimum yearly repayment\n\n-$148.00\n\nBenchmark interest rate\n\n6.2%\n\nOpening balance:\n\nDate: 30/06/2013\n\nBalance: $90.97\n\nDays: 20\n\nInterest: $0.31\n\nPayments\n\nDate: 21/07/2013\n\nAmount: $909.76\n\nBalance: $0\n\nDays: 345\n\nInterest: $0\n\n\n\n\nTotal repayments\n\n$909.76\n\nTotal interest\n\n$0.31\n\nTotal principal\n\n$909.45\n\nClosing balance\n\nDate: 30/06/2014\n\nBalance: $0",
  "outputs": {
    "enquiryRateFormatted": "6.2%",
    "enquiryYearEndMinusOneDisplay": "30/06/2013",
    "amalgamatedLoanNotPaidByEOIYFormatted": "$90.97",
    "openingBalancePayDays": "20",
    "openingBalanceInterestFormatted": "$0.31",
    "totalAmountOfRepaymentFormatted": "$909.76",
    "totalInterestFormatted": "$0.31",
    "principalFormatted": "$909.45",
    "enquiryYearEndDisplay": "30/06/2014",
    "minimumYearRepaymentFormatted": "-$148.00",
    "loanAmountFormatted": "$0"
  },
  "repayments": [
    {
      "rd": "21/7/2013",
      "ra": 909.7661934041562
    }
  ],
  "inputs": {
    "incomeYearOfLoan": 2013,
    "fullTermOfAmalgamatedLoan": 7,
    "incomeYearOfEnquiring": 2014,
    "amalgamatedLoanNotPaidByEOIY": 90.97661934041565,
    "repayments": null,
    "lodgement_date": "27/1/2014"
  },
  "idx": 3073
}