{
  "id": "2023-10-31T17:25:18.352Z0.19158999258839093",
  "alert": "Start of result\nResult\n\nMinimum yearly repayment not met.\n\nThe amount of the loan not repaid at the end of income year 2023-24 is $1,332.10.\n\nThe private company may be taken to pay a dividend under Division 7A to the shareholder or shareholder's associate because the amount repaid during income year 2023-24 in relation to the amalgamated loan is less than the minimum yearly repayment required.\n\nInterest received by the private company must be included in the income tax return for 2023-24.\n\nMinimum yearly repayment\n\n$1,779.00\n\nBenchmark interest rate\n\n8.27%\n\nOpening balance:\n\nDate: 30/06/2023\n\nBalance: $1,643.00\n\nDays: 267\n\nInterest: $99.12\n\nPayments\n\nDate: 24/03/2024\n\nAmount: $437.00\n\nBalance: $1,206.00\n\nDays: 99\n\nInterest: $26.98\n\n\n\n\nTotal repayments\n\n$437.00\n\nTotal interest\n\n$126.10\n\nTotal principal\n\n$310.90\n\nClosing balance\n\nDate: 30/06/2024\n\nBalance: $1,332.10",
  "outputs": {
    "enquiryRateFormatted": "8.27%",
    "enquiryYearEndMinusOneDisplay": "30/06/2023",
    "amalgamatedLoanNotPaidByEOIYFormatted": "$1,643.00",
    "openingBalancePayDays": "267",
    "openingBalanceInterestFormatted": "$99.12",
    "totalAmountOfRepaymentFormatted": "$437.00",
    "totalInterestFormatted": "$126.10",
    "principalFormatted": "$310.90",
    "enquiryYearEndDisplay": "30/06/2024",
    "minimumYearRepaymentFormatted": "$1,779.00",
    "loanAmountFormatted": "$1,332.10"
  },
  "repayments": [
    {
      "rd": "24/3/2024",
      "ra": 437
    }
  ],
  "inputs": {
    "incomeYearOfLoan": 2018,
    "fullTermOfAmalgamatedLoan": 6,
    "incomeYearOfEnquiring": 2024,
    "amalgamatedLoanNotPaidByEOIY": 1643,
    "repayments": null,
    "lodgement_date": null
  },
  "idx": 1428
}