{
  "id": "2023-10-31T19:01:13.038Z0.22303006821734062",
  "alert": "Start of result\nResult\n\nAmalgamated loan fully repaid.\n\nThe amalgamated loan has been paid in full.\u000bThe private company is not taken under Division 7A to pay a dividend to the shareholder or shareholder's associate.\n\nInterest received by the private company must be included in the income tax return for 2006-07.\n\nMinimum yearly repayment\n\n-$243.00\n\nBenchmark interest rate\n\n7.55%\n\nOpening balance:\n\nDate: 30/06/2006\n\nBalance: $48.38\n\nDays: 44\n\nInterest: $0.44\n\nPayments\n\nDate: 14/08/2006\n\nAmount: $483.88\n\nBalance: $0\n\nDays: 321\n\nInterest: $0\n\n\n\n\nTotal repayments\n\n$483.88\n\nTotal interest\n\n$0.44\n\nTotal principal\n\n$483.44\n\nClosing balance\n\nDate: 30/06/2007\n\nBalance: $0",
  "outputs": {
    "enquiryRateFormatted": "7.55%",
    "enquiryYearEndMinusOneDisplay": "30/06/2006",
    "amalgamatedLoanNotPaidByEOIYFormatted": "$48.38",
    "openingBalancePayDays": "44",
    "openingBalanceInterestFormatted": "$0.44",
    "totalAmountOfRepaymentFormatted": "$483.88",
    "totalInterestFormatted": "$0.44",
    "principalFormatted": "$483.44",
    "enquiryYearEndDisplay": "30/06/2007",
    "minimumYearRepaymentFormatted": "-$243.00",
    "loanAmountFormatted": "$0"
  },
  "repayments": [
    {
      "rd": "14/8/2006",
      "ra": 483.8813766838907
    }
  ],
  "inputs": {
    "incomeYearOfLoan": 2006,
    "fullTermOfAmalgamatedLoan": 2,
    "incomeYearOfEnquiring": 2007,
    "amalgamatedLoanNotPaidByEOIY": 48.388137668389064,
    "repayments": null,
    "lodgement_date": "30/8/2006"
  },
  "idx": 4900
}