{
  "id": "2023-10-31T17:43:18.976Z0.6159384772498963",
  "alert": "Start of result\nResult\n\nMinimum yearly repayment not met.\n\nThe amount of the loan not repaid at the end of income year 2017-18 is $121.97.\n\nThe private company may be taken to pay a dividend under Division 7A to the shareholder or shareholder's associate because the amount repaid during income year 2017-18 in relation to the amalgamated loan is less than the minimum yearly repayment required.\n\nInterest received by the private company must be included in the income tax return for 2017-18.\n\nMinimum yearly repayment\n\n$28.00\n\nBenchmark interest rate\n\n5.3%\n\nOpening balance:\n\nDate: 30/06/2017\n\nBalance: $121.97\n\nDays: 365\n\nInterest: $6.46\n\nTotal repayments\n\n$0\n\nTotal interest\n\n$6.46\n\nTotal principal\n\n$0\n\nClosing balance\n\nDate: 30/06/2018\n\nBalance: $121.97",
  "outputs": {
    "enquiryRateFormatted": "5.3%",
    "enquiryYearEndMinusOneDisplay": "30/06/2017",
    "amalgamatedLoanNotPaidByEOIYFormatted": "$121.97",
    "openingBalancePayDays": "365",
    "openingBalanceInterestFormatted": "$6.46",
    "totalAmountOfRepaymentFormatted": "$0",
    "totalInterestFormatted": "$6.46",
    "principalFormatted": "$0",
    "enquiryYearEndDisplay": "30/06/2018",
    "minimumYearRepaymentFormatted": "$28.00",
    "loanAmountFormatted": "$121.97"
  },
  "repayments": [],
  "inputs": {
    "incomeYearOfLoan": 2015,
    "fullTermOfAmalgamatedLoan": 7,
    "incomeYearOfEnquiring": 2018,
    "amalgamatedLoanNotPaidByEOIY": 121.97110682833166,
    "repayments": null,
    "lodgement_date": null
  },
  "idx": 2377
}