{
  "id": "2023-10-31T19:07:31.928Z0.5683292106433575",
  "alert": "Start of result\nResult\n\nMinimum yearly repayment not met.\n\nThe amount of the loan not repaid at the end of income year 2006-07 is $76.25.\n\nThe private company may be taken to pay a dividend under Division 7A to the shareholder or shareholder's associate because the amount repaid during income year 2006-07 in relation to the amalgamated loan is less than the minimum yearly repayment required.\n\nInterest received by the private company must be included in the income tax return for 2006-07.\n\nMinimum yearly repayment\n\n$16.00\n\nBenchmark interest rate\n\n7.55%\n\nOpening balance:\n\nDate: 30/06/2006\n\nBalance: $76.25\n\nDays: 365\n\nInterest: $5.76\n\nTotal repayments\n\n$0\n\nTotal interest\n\n$5.76\n\nTotal principal\n\n$0\n\nClosing balance\n\nDate: 30/06/2007\n\nBalance: $76.25",
  "outputs": {
    "enquiryRateFormatted": "7.55%",
    "enquiryYearEndMinusOneDisplay": "30/06/2006",
    "amalgamatedLoanNotPaidByEOIYFormatted": "$76.25",
    "openingBalancePayDays": "365",
    "openingBalanceInterestFormatted": "$5.76",
    "totalAmountOfRepaymentFormatted": "$0",
    "totalInterestFormatted": "$5.76",
    "principalFormatted": "$0",
    "enquiryYearEndDisplay": "30/06/2007",
    "minimumYearRepaymentFormatted": "$16.00",
    "loanAmountFormatted": "$76.25"
  },
  "repayments": [],
  "inputs": {
    "incomeYearOfLoan": 2006,
    "fullTermOfAmalgamatedLoan": 6,
    "incomeYearOfEnquiring": 2007,
    "amalgamatedLoanNotPaidByEOIY": 76.25345969315954,
    "repayments": null,
    "lodgement_date": "31/7/2006"
  },
  "idx": 5046
}