{
  "id": "2023-09-04T16:54:49.389Z0.5790648444660051",
  "alert": "Start of result\nResult\n\nMinimum yearly repayment not met.\n\nThe amount of the loan not repaid at the end of income year 2019-20 is $121,259,544.15.\n\nThe private company may be taken to pay a dividend under Division 7A to the shareholder or shareholder's associate because the amount repaid during income year 2019-20 in relation to the amalgamated loan is less than the minimum yearly repayment required.\n\nInterest received by the private company must be included in the income tax return for 2019-20.\n\nMinimum yearly repayment\n\n$65,556,067.00\n\nBenchmark interest rate\n\n5.37%\n\nOpening balance:\n\nDate: 30/06/2019\n\nBalance: $121,259,544.15\n\nDays: 366\n\nInterest: $6,511,637.52\n\nTotal repayments\n\n$0\n\nTotal interest\n\n$6,511,637.52\n\nTotal principal\n\n$0\n\nClosing balance\n\nDate: 30/06/2020\n\nBalance: $121,259,544.15",
  "outputs": {
    "enquiryRateFormatted": "5.37%",
    "enquiryYearEndMinusOneDisplay": "30/06/2019",
    "amalgamatedLoanNotPaidByEOIYFormatted": "$121,259,544.15",
    "openingBalancePayDays": "366",
    "openingBalanceInterestFormatted": "$6,511,637.52",
    "totalAmountOfRepaymentFormatted": "$0",
    "totalInterestFormatted": "$6,511,637.52",
    "principalFormatted": "$0",
    "enquiryYearEndDisplay": "30/06/2020",
    "minimumYearRepaymentFormatted": "$65,556,067.00"
  },
  "repayments": [],
  "inputs": {
    "incomeYearOfLoan": 2015,
    "fullTermOfAmalgamatedLoan": 6,
    "incomeYearOfEnquiring": 2020,
    "amalgamatedLoanNotPaidByEOIY": 121259544.15837388,
    "repayments": null,
    "lodgement_date": null
  },
  "idx": 1394
}