{
  "id": "2023-09-04T17:26:09.068Z0.6616761631990633",
  "alert": "Start of result\nResult\n\nMinimum yearly repayment not met.\n\nThe amount of the loan not repaid at the end of income year 2013-14 is $106,835,714.69.\n\nThe private company may be taken to pay a dividend under Division 7A to the shareholder or shareholder's associate because the amount repaid during income year 2013-14 in relation to the amalgamated loan is less than the minimum yearly repayment required.\n\nInterest received by the private company must be included in the income tax return for 2013-14.\n\nMinimum yearly repayment\n\n$19,274,283.00\n\nBenchmark interest rate\n\n6.2%\n\nOpening balance:\n\nDate: 30/06/2013\n\nBalance: $106,835,714.69\n\nDays: 365\n\nInterest: $6,623,814.31\n\nTotal repayments\n\n$0\n\nTotal interest\n\n$6,623,814.31\n\nTotal principal\n\n$0\n\nClosing balance\n\nDate: 30/06/2014\n\nBalance: $106,835,714.69",
  "outputs": {
    "enquiryRateFormatted": "6.2%",
    "enquiryYearEndMinusOneDisplay": "30/06/2013",
    "amalgamatedLoanNotPaidByEOIYFormatted": "$106,835,714.69",
    "openingBalancePayDays": "365",
    "openingBalanceInterestFormatted": "$6,623,814.31",
    "totalAmountOfRepaymentFormatted": "$0",
    "totalInterestFormatted": "$6,623,814.31",
    "principalFormatted": "$0",
    "enquiryYearEndDisplay": "30/06/2014",
    "minimumYearRepaymentFormatted": "$19,274,283.00"
  },
  "repayments": [],
  "inputs": {
    "incomeYearOfLoan": 2013,
    "fullTermOfAmalgamatedLoan": 7,
    "incomeYearOfEnquiring": 2014,
    "amalgamatedLoanNotPaidByEOIY": 106835714.6902382,
    "repayments": null,
    "lodgement_date": "17/1/2014"
  },
  "idx": 2136
}