{
  "id": "2023-10-31T18:40:48.431Z0.11210808707285325",
  "alert": "Start of result\nResult\n\nAmalgamated loan fully repaid.\n\nThe amalgamated loan has been paid in full.\u000bThe private company is not taken under Division 7A to pay a dividend to the shareholder or shareholder's associate.\n\nInterest received by the private company must be included in the income tax return for 2013-14.\n\nMinimum yearly repayment\n\n$112.00\n\nBenchmark interest rate\n\n6.2%\n\nOpening balance:\n\nDate: 30/06/2013\n\nBalance: $105.49\n\nDays: 93\n\nInterest: $1.67\n\nPayments\n\nDate: 02/10/2013\n\nAmount: $1,054.93\n\nBalance: $0\n\nDays: 272\n\nInterest: $0\n\n\n\n\nTotal repayments\n\n$1,054.93\n\nTotal interest\n\n$1.67\n\nTotal principal\n\n$1,053.26\n\nClosing balance\n\nDate: 30/06/2014\n\nBalance: $0",
  "outputs": {
    "enquiryRateFormatted": "6.2%",
    "enquiryYearEndMinusOneDisplay": "30/06/2013",
    "amalgamatedLoanNotPaidByEOIYFormatted": "$105.49",
    "openingBalancePayDays": "93",
    "openingBalanceInterestFormatted": "$1.67",
    "totalAmountOfRepaymentFormatted": "$1,054.93",
    "totalInterestFormatted": "$1.67",
    "principalFormatted": "$1,053.26",
    "enquiryYearEndDisplay": "30/06/2014",
    "minimumYearRepaymentFormatted": "$112.00",
    "loanAmountFormatted": "$0"
  },
  "repayments": [
    {
      "rd": "2/10/2013",
      "ra": 1054.934084824221
    }
  ],
  "inputs": {
    "incomeYearOfLoan": 2008,
    "fullTermOfAmalgamatedLoan": 6,
    "incomeYearOfEnquiring": 2014,
    "amalgamatedLoanNotPaidByEOIY": 105.49340848242214,
    "repayments": null,
    "lodgement_date": null
  },
  "idx": 4376
}