{
  "id": "2023-10-31T17:16:05.563Z0.04068646404077281",
  "alert": "Start of result\nResult\n\nAmalgamated loan fully repaid.\n\nThe amalgamated loan has been paid in full.\u000bThe private company is not taken under Division 7A to pay a dividend to the shareholder or shareholder's associate.\n\nInterest received by the private company must be included in the income tax return for 2021-22.\n\nMinimum yearly repayment\n\n$7.00\n\nBenchmark interest rate\n\n4.52%\n\nOpening balance:\n\nDate: 30/06/2021\n\nBalance: $19.49\n\nDays: 325\n\nInterest: $0.78\n\nPayments\n\nDate: 22/05/2022\n\nAmount: $194.92\n\nBalance: $0\n\nDays: 40\n\nInterest: $0\n\n\n\n\nTotal repayments\n\n$194.92\n\nTotal interest\n\n$0.78\n\nTotal principal\n\n$194.14\n\nClosing balance\n\nDate: 30/06/2022\n\nBalance: $0",
  "outputs": {
    "enquiryRateFormatted": "4.52%",
    "enquiryYearEndMinusOneDisplay": "30/06/2021",
    "amalgamatedLoanNotPaidByEOIYFormatted": "$19.49",
    "openingBalancePayDays": "325",
    "openingBalanceInterestFormatted": "$0.78",
    "totalAmountOfRepaymentFormatted": "$194.92",
    "totalInterestFormatted": "$0.78",
    "principalFormatted": "$194.14",
    "enquiryYearEndDisplay": "30/06/2022",
    "minimumYearRepaymentFormatted": "$7.00",
    "loanAmountFormatted": "$0"
  },
  "repayments": [
    {
      "rd": "22/5/2022",
      "ra": 194.92679337740628
    }
  ],
  "inputs": {
    "incomeYearOfLoan": 2020,
    "fullTermOfAmalgamatedLoan": 4,
    "incomeYearOfEnquiring": 2022,
    "amalgamatedLoanNotPaidByEOIY": 19.492679337740608,
    "repayments": null,
    "lodgement_date": null
  },
  "idx": 803
}