{
  "id": "2023-09-06T21:30:36.259Z0.5540491835673067",
  "alert": "Start of result\nResult\n\nMinimum yearly repayment met.\n\nThe amount of the loan not repaid at the end of income year 2002-03 is $14.85.\n\nThe amalgamated loan will not be taken to be a dividend because the total repayments made are equal to or greater than the minimum yearly repayment required for income year 2002-03.\n\nInterest received by the private company must be included in the income tax return for 2002-03.\n\nMinimum yearly repayment\n\n$3.00\n\nBenchmark interest rate\n\n6.3%\n\nOpening balance:\n\nDate: 30/06/2002\n\nBalance: $57.57\n\nDays: 191\n\nInterest: $1.90\n\nPayments\n\nDate: 08/01/2003\n\nAmount: $45.00\n\nBalance: $12.57\n\nDays: 174\n\nInterest: $0.38\n\n\n\n\nTotal repayments\n\n$45.00\n\nTotal interest\n\n$2.28\n\nTotal principal\n\n$42.72\n\nClosing balance\n\nDate: 30/06/2003\n\nBalance: $14.85",
  "outputs": {
    "enquiryRateFormatted": "6.3%",
    "enquiryYearEndMinusOneDisplay": "30/06/2002",
    "amalgamatedLoanNotPaidByEOIYFormatted": "$57.57",
    "openingBalancePayDays": "191",
    "openingBalanceInterestFormatted": "$1.90",
    "totalAmountOfRepaymentFormatted": "$45.00",
    "totalInterestFormatted": "$2.28",
    "principalFormatted": "$42.72",
    "enquiryYearEndDisplay": "30/06/2003",
    "minimumYearRepaymentFormatted": "$3.00"
  },
  "repayments": [
    {
      "rd": "8/1/2003",
      "ra": 45
    }
  ],
  "inputs": {
    "incomeYearOfLoan": 2002,
    "fullTermOfAmalgamatedLoan": 5,
    "incomeYearOfEnquiring": 2003,
    "amalgamatedLoanNotPaidByEOIY": 57.579760566843916,
    "repayments": null,
    "lodgement_date": "21/5/2003"
  },
  "idx": 5868
}