{
  "id": "2023-10-31T17:34:27.812Z0.7156584414488921",
  "alert": "Start of result\nResult\n\nAmalgamated loan fully repaid.\n\nThe amalgamated loan has been paid in full.\u000bThe private company is not taken under Division 7A to pay a dividend to the shareholder or shareholder's associate.\n\nInterest received by the private company must be included in the income tax return for 2017-18.\n\nMinimum yearly repayment\n\n$1,080.00\n\nBenchmark interest rate\n\n5.3%\n\nOpening balance:\n\nDate: 30/06/2017\n\nBalance: $2,925.00\n\nDays: 320\n\nInterest: $135.91\n\nPayments\n\nDate: 17/05/2018\n\nAmount: $7,139.00\n\nBalance: $0\n\nDays: 45\n\nInterest: $0\n\n\n\n\nTotal repayments\n\n$7,139.00\n\nTotal interest\n\n$135.91\n\nTotal principal\n\n$7,003.09\n\nClosing balance\n\nDate: 30/06/2018\n\nBalance: $0",
  "outputs": {
    "enquiryRateFormatted": "5.3%",
    "enquiryYearEndMinusOneDisplay": "30/06/2017",
    "amalgamatedLoanNotPaidByEOIYFormatted": "$2,925.00",
    "openingBalancePayDays": "320",
    "openingBalanceInterestFormatted": "$135.91",
    "totalAmountOfRepaymentFormatted": "$7,139.00",
    "totalInterestFormatted": "$135.91",
    "principalFormatted": "$7,003.09",
    "enquiryYearEndDisplay": "30/06/2018",
    "minimumYearRepaymentFormatted": "$1,080.00",
    "loanAmountFormatted": "$0"
  },
  "repayments": [
    {
      "rd": "17/5/2018",
      "ra": 7139
    }
  ],
  "inputs": {
    "incomeYearOfLoan": 2016,
    "fullTermOfAmalgamatedLoan": 4,
    "incomeYearOfEnquiring": 2018,
    "amalgamatedLoanNotPaidByEOIY": 2925,
    "repayments": null,
    "lodgement_date": null
  },
  "idx": 1945
}