{
  "id": "2023-09-05T01:11:30.625Z0.34506424004773195",
  "alert": "Start of result\nResult\n\nMinimum yearly repayment met.\n\nThe amount of the loan not repaid at the end of income year 1998-99 is $731.76.\n\nThe amalgamated loan will not be taken to be a dividend because the total repayments made are equal to or greater than the minimum yearly repayment required for income year 1998-99.\n\nInterest received by the private company must be included in the income tax return for 1998-99.\n\nMinimum yearly repayment\n\n$355.00\n\nBenchmark interest rate\n\n6.7%\n\nOpening balance:\n\nDate: 30/06/1998\n\nBalance: $9,527.00\n\nDays: 0\n\nInterest: $0\n\nPayments\n\nDate: 01/07/1998\n\nAmount: $430.00\n\nBalance: $9,097.00\n\nDays: 234\n\nInterest: $390.75\n\n\n\n\nDate: 20/02/1999\n\nAmount: $8,764.00\n\nBalance: $333.00\n\nDays: 131\n\nInterest: $8.01\n\n\n\n\nTotal repayments\n\n$9,194.00\n\nTotal interest\n\n$398.76\n\nTotal principal\n\n$8,795.24\n\nClosing balance\n\nDate: 30/06/1999\n\nBalance: $731.76",
  "outputs": {
    "enquiryRateFormatted": "6.7%",
    "enquiryYearEndMinusOneDisplay": "30/06/1998",
    "amalgamatedLoanNotPaidByEOIYFormatted": "$9,527.00",
    "openingBalancePayDays": "0",
    "openingBalanceInterestFormatted": "$0",
    "totalAmountOfRepaymentFormatted": "$9,194.00",
    "totalInterestFormatted": "$398.76",
    "principalFormatted": "$8,795.24",
    "enquiryYearEndDisplay": "30/06/1999",
    "minimumYearRepaymentFormatted": "$355.00"
  },
  "repayments": [
    {
      "rd": "1/7/1998",
      "ra": 430
    },
    {
      "rd": "20/2/1999",
      "ra": 8764
    }
  ],
  "inputs": {
    "incomeYearOfLoan": 1998,
    "fullTermOfAmalgamatedLoan": 1,
    "incomeYearOfEnquiring": 1999,
    "amalgamatedLoanNotPaidByEOIY": 9527,
    "repayments": null,
    "lodgement_date": "15/5/1999"
  },
  "idx": 1050
}