{
  "id": "2023-10-31T18:03:40.289Z0.7390869602772722",
  "alert": "Start of result\nResult\n\nAmalgamated loan fully repaid.\n\nThe amalgamated loan has been paid in full.\u000bThe private company is not taken under Division 7A to pay a dividend to the shareholder or shareholder's associate.\n\nInterest received by the private company must be included in the income tax return for 2015-16.\n\nMinimum yearly repayment\n\n$3,701.00\n\nBenchmark interest rate\n\n5.45%\n\nOpening balance:\n\nDate: 30/06/2015\n\nBalance: $6,838.00\n\nDays: 125\n\nInterest: $127.28\n\nPayments\n\nDate: 03/11/2015\n\nAmount: $3,731.00\n\nBalance: $3,107.00\n\nDays: 23\n\nInterest: $10.64\n\n\n\n\nDate: 26/11/2015\n\nAmount: $4,385.00\n\nBalance: $0\n\nDays: 19\n\nInterest: $0\n\n\n\n\nDate: 15/12/2015\n\nAmount: $5,355.00\n\nBalance: $0\n\nDays: 199\n\nInterest: $0\n\n\n\n\nTotal repayments\n\n$13,471.00\n\nTotal interest\n\n$137.92\n\nTotal principal\n\n$13,333.08\n\nClosing balance\n\nDate: 30/06/2016\n\nBalance: $0",
  "outputs": {
    "enquiryRateFormatted": "5.45%",
    "enquiryYearEndMinusOneDisplay": "30/06/2015",
    "amalgamatedLoanNotPaidByEOIYFormatted": "$6,838.00",
    "openingBalancePayDays": "125",
    "openingBalanceInterestFormatted": "$127.28",
    "totalAmountOfRepaymentFormatted": "$13,471.00",
    "totalInterestFormatted": "$137.92",
    "principalFormatted": "$13,333.08",
    "enquiryYearEndDisplay": "30/06/2016",
    "minimumYearRepaymentFormatted": "$3,701.00",
    "loanAmountFormatted": "$0"
  },
  "repayments": [
    {
      "rd": "3/11/2015",
      "ra": 3731
    },
    {
      "rd": "26/11/2015",
      "ra": 4385
    },
    {
      "rd": "15/12/2015",
      "ra": 5355
    }
  ],
  "inputs": {
    "incomeYearOfLoan": 2012,
    "fullTermOfAmalgamatedLoan": 5,
    "incomeYearOfEnquiring": 2016,
    "amalgamatedLoanNotPaidByEOIY": 6838,
    "repayments": null,
    "lodgement_date": null
  },
  "idx": 3228
}