{
  "id": "2023-10-31T17:14:57.451Z0.4262119132059564",
  "alert": "Start of result\nResult\n\nMinimum yearly repayment not met.\n\nThe amount of the loan not repaid at the end of income year 2020-21 is $3,605.96.\n\nThe private company may be taken to pay a dividend under Division 7A to the shareholder or shareholder's associate because the amount repaid during income year 2020-21 in relation to the amalgamated loan is less than the minimum yearly repayment required.\n\nInterest received by the private company must be included in the income tax return for 2020-21.\n\nMinimum yearly repayment\n\n$3,588.00\n\nBenchmark interest rate\n\n4.52%\n\nOpening balance:\n\nDate: 30/06/2020\n\nBalance: $4,682.00\n\nDays: 115\n\nInterest: $66.68\n\nPayments\n\nDate: 24/10/2020\n\nAmount: $1,249.00\n\nBalance: $3,433.00\n\nDays: 250\n\nInterest: $106.28\n\n\n\n\nTotal repayments\n\n$1,249.00\n\nTotal interest\n\n$172.96\n\nTotal principal\n\n$1,076.04\n\nClosing balance\n\nDate: 30/06/2021\n\nBalance: $3,605.96",
  "outputs": {
    "enquiryRateFormatted": "4.52%",
    "enquiryYearEndMinusOneDisplay": "30/06/2020",
    "amalgamatedLoanNotPaidByEOIYFormatted": "$4,682.00",
    "openingBalancePayDays": "115",
    "openingBalanceInterestFormatted": "$66.68",
    "totalAmountOfRepaymentFormatted": "$1,249.00",
    "totalInterestFormatted": "$172.96",
    "principalFormatted": "$1,076.04",
    "enquiryYearEndDisplay": "30/06/2021",
    "minimumYearRepaymentFormatted": "$3,588.00",
    "loanAmountFormatted": "$3,605.96"
  },
  "repayments": [
    {
      "rd": "24/10/2020",
      "ra": 1249
    }
  ],
  "inputs": {
    "incomeYearOfLoan": 2020,
    "fullTermOfAmalgamatedLoan": 1,
    "incomeYearOfEnquiring": 2021,
    "amalgamatedLoanNotPaidByEOIY": 4682,
    "repayments": null,
    "lodgement_date": "29/10/2020"
  },
  "idx": 721
}