{
  "id": "2023-10-31T18:51:30.260Z0.5874847901439457",
  "alert": "Start of result\nResult\n\nAmalgamated loan fully repaid.\n\nThe amalgamated loan has been paid in full.\u000bThe private company is not taken under Division 7A to pay a dividend to the shareholder or shareholder's associate.\n\nInterest received by the private company must be included in the income tax return for 2008-09.\n\nMinimum yearly repayment\n\n$1.00\n\nBenchmark interest rate\n\n9.45%\n\nOpening balance:\n\nDate: 30/06/2008\n\nBalance: $4.20\n\nDays: 361\n\nInterest: $0.39\n\nPayments\n\nDate: 27/06/2009\n\nAmount: $42.03\n\nBalance: $0\n\nDays: 4\n\nInterest: $0\n\n\n\n\nTotal repayments\n\n$42.03\n\nTotal interest\n\n$0.39\n\nTotal principal\n\n$41.64\n\nClosing balance\n\nDate: 30/06/2009\n\nBalance: $0",
  "outputs": {
    "enquiryRateFormatted": "9.45%",
    "enquiryYearEndMinusOneDisplay": "30/06/2008",
    "amalgamatedLoanNotPaidByEOIYFormatted": "$4.20",
    "openingBalancePayDays": "361",
    "openingBalanceInterestFormatted": "$0.39",
    "totalAmountOfRepaymentFormatted": "$42.03",
    "totalInterestFormatted": "$0.39",
    "principalFormatted": "$41.64",
    "enquiryYearEndDisplay": "30/06/2009",
    "minimumYearRepaymentFormatted": "$1.00",
    "loanAmountFormatted": "$0"
  },
  "repayments": [
    {
      "rd": "27/6/2009",
      "ra": 42.03215970263136
    }
  ],
  "inputs": {
    "incomeYearOfLoan": 2007,
    "fullTermOfAmalgamatedLoan": 5,
    "incomeYearOfEnquiring": 2009,
    "amalgamatedLoanNotPaidByEOIY": 4.203215970263122,
    "repayments": null,
    "lodgement_date": null
  },
  "idx": 4658
}