{
  "id": "2023-09-05T23:52:32.450Z0.8886646244838377",
  "alert": "Start of result\nResult\n\nMinimum yearly repayment not met.\n\nThe amount of the loan not repaid at the end of income year 2017-18 is $9,475.25.\n\nThe private company may be taken to pay a dividend under Division 7A to the shareholder or shareholder's associate because the amount repaid during income year 2017-18 in relation to the amalgamated loan is less than the minimum yearly repayment required.\n\nInterest received by the private company must be included in the income tax return for 2017-18.\n\nMinimum yearly repayment\n\n$3,923.00\n\nBenchmark interest rate\n\n5.3%\n\nOpening balance:\n\nDate: 30/06/2017\n\nBalance: $10,623.00\n\nDays: 151\n\nInterest: $232.92\n\nPayments\n\nDate: 29/11/2017\n\nAmount: $39.00\n\nBalance: $10,584.00\n\nDays: 107\n\nInterest: $164.44\n\n\n\n\nDate: 16/03/2018\n\nAmount: $1,645.00\n\nBalance: $8,939.00\n\nDays: 107\n\nInterest: $138.89\n\n\n\n\nTotal repayments\n\n$1,684.00\n\nTotal interest\n\n$536.25\n\nTotal principal\n\n$1,147.75\n\nClosing balance\n\nDate: 30/06/2018\n\nBalance: $9,475.25",
  "outputs": {
    "enquiryRateFormatted": "5.3%",
    "enquiryYearEndMinusOneDisplay": "30/06/2017",
    "amalgamatedLoanNotPaidByEOIYFormatted": "$10,623.00",
    "openingBalancePayDays": "151",
    "openingBalanceInterestFormatted": "$232.92",
    "totalAmountOfRepaymentFormatted": "$1,684.00",
    "totalInterestFormatted": "$536.25",
    "principalFormatted": "$1,147.75",
    "enquiryYearEndDisplay": "30/06/2018",
    "minimumYearRepaymentFormatted": "$3,923.00"
  },
  "repayments": [
    {
      "rd": "29/11/2017",
      "ra": 39
    },
    {
      "rd": "16/3/2018",
      "ra": 1645
    }
  ],
  "inputs": {
    "incomeYearOfLoan": 2015,
    "fullTermOfAmalgamatedLoan": 5,
    "incomeYearOfEnquiring": 2018,
    "amalgamatedLoanNotPaidByEOIY": 10623,
    "repayments": null,
    "lodgement_date": null
  },
  "idx": 740
}