{
  "id": "2023-09-04T16:13:01.884Z0.6868855182011235",
  "alert": "Start of result\nResult\n\nMinimum yearly repayment not met.\n\nThe amount of the loan not repaid at the end of income year 2022-23 is $4,287,009.52.\n\nThe private company may be taken to pay a dividend under Division 7A to the shareholder or shareholder's associate because the amount repaid during income year 2022-23 in relation to the amalgamated loan is less than the minimum yearly repayment required.\n\nInterest received by the private company must be included in the income tax return for 2022-23.\n\nMinimum yearly repayment\n\n$1,202,535.00\n\nBenchmark interest rate\n\n4.77%\n\nOpening balance:\n\nDate: 30/06/2022\n\nBalance: $4,287,009.52\n\nDays: 365\n\nInterest: $204,490.35\n\nTotal repayments\n\n$0\n\nTotal interest\n\n$204,490.35\n\nTotal principal\n\n$0\n\nClosing balance\n\nDate: 30/06/2023\n\nBalance: $4,287,009.52",
  "outputs": {
    "enquiryRateFormatted": "4.77%",
    "enquiryYearEndMinusOneDisplay": "30/06/2022",
    "amalgamatedLoanNotPaidByEOIYFormatted": "$4,287,009.52",
    "openingBalancePayDays": "365",
    "openingBalanceInterestFormatted": "$204,490.35",
    "totalAmountOfRepaymentFormatted": "$0",
    "totalInterestFormatted": "$204,490.35",
    "principalFormatted": "$0",
    "enquiryYearEndDisplay": "30/06/2023",
    "minimumYearRepaymentFormatted": "$1,202,535.00"
  },
  "repayments": [],
  "inputs": {
    "incomeYearOfLoan": 2022,
    "fullTermOfAmalgamatedLoan": 4,
    "incomeYearOfEnquiring": 2023,
    "amalgamatedLoanNotPaidByEOIY": 4287009.525838114,
    "repayments": null,
    "lodgement_date": "9/10/2022"
  },
  "idx": 1
}