{
  "id": "2023-09-05T20:49:53.343Z0.47241340402774634",
  "alert": "Start of result\nResult\n\nMinimum yearly repayment met.\n\nThe amount of the loan not repaid at the end of income year 2017-18 is $7,125.97.\n\nThe amalgamated loan will not be taken to be a dividend because the total repayments made are equal to or greater than the minimum yearly repayment required for income year 2017-18.\n\nInterest received by the private company must be included in the income tax return for 2017-18.\n\nMinimum yearly repayment\n\n$1,180.00\n\nBenchmark interest rate\n\n5.3%\n\nOpening balance:\n\nDate: 30/06/2017\n\nBalance: $8,540.00\n\nDays: 50\n\nInterest: $62.00\n\nPayments\n\nDate: 20/08/2017\n\nAmount: $1,785.00\n\nBalance: $6,755.00\n\nDays: 315\n\nInterest: $308.97\n\n\n\n\nTotal repayments\n\n$1,785.00\n\nTotal interest\n\n$370.97\n\nTotal principal\n\n$1,414.03\n\nClosing balance\n\nDate: 30/06/2018\n\nBalance: $7,125.97",
  "outputs": {
    "enquiryRateFormatted": "5.3%",
    "enquiryYearEndMinusOneDisplay": "30/06/2017",
    "amalgamatedLoanNotPaidByEOIYFormatted": "$8,540.00",
    "openingBalancePayDays": "50",
    "openingBalanceInterestFormatted": "$62.00",
    "totalAmountOfRepaymentFormatted": "$1,785.00",
    "totalInterestFormatted": "$370.97",
    "principalFormatted": "$1,414.03",
    "enquiryYearEndDisplay": "30/06/2018",
    "minimumYearRepaymentFormatted": "$1,180.00"
  },
  "repayments": [
    {
      "rd": "20/8/2017",
      "ra": 1785
    }
  ],
  "inputs": {
    "incomeYearOfLoan": 2017,
    "fullTermOfAmalgamatedLoan": 7,
    "incomeYearOfEnquiring": 2018,
    "amalgamatedLoanNotPaidByEOIY": 8540,
    "repayments": null,
    "lodgement_date": "16/6/2018"
  },
  "idx": 7360
}