{
  "id": "2023-09-06T08:22:32.490Z0.2777448132347291",
  "alert": "Start of result\nResult\n\nMinimum yearly repayment not met.\n\nThe amount of the loan not repaid at the end of income year 2015-16 is $0.66.\n\nThe private company may be taken to pay a dividend under Division 7A to the shareholder or shareholder's associate because the amount repaid during income year 2015-16 in relation to the amalgamated loan is less than the minimum yearly repayment required.\n\nInterest received by the private company must be included in the income tax return for 2015-16.\n\nMinimum yearly repayment\n\n$21.00\n\nBenchmark interest rate\n\n5.45%\n\nOpening balance:\n\nDate: 30/06/2015\n\nBalance: $19.55\n\nDays: 228\n\nInterest: $0.66\n\nPayments\n\nDate: 14/02/2016\n\nAmount: $19.55\n\nBalance: $0\n\nDays: 138\n\nInterest: $0\n\n\n\n\nTotal repayments\n\n$19.55\n\nTotal interest\n\n$0.66\n\nTotal principal\n\n$18.89\n\nClosing balance\n\nDate: 30/06/2016\n\nBalance: $0.66",
  "outputs": {
    "enquiryRateFormatted": "5.45%",
    "enquiryYearEndMinusOneDisplay": "30/06/2015",
    "amalgamatedLoanNotPaidByEOIYFormatted": "$19.55",
    "openingBalancePayDays": "228",
    "openingBalanceInterestFormatted": "$0.66",
    "totalAmountOfRepaymentFormatted": "$19.55",
    "totalInterestFormatted": "$0.66",
    "principalFormatted": "$18.89",
    "enquiryYearEndDisplay": "30/06/2016",
    "minimumYearRepaymentFormatted": "$21.00"
  },
  "repayments": [
    {
      "rd": "14/2/2016",
      "ra": 19.55055913390379
    }
  ],
  "inputs": {
    "incomeYearOfLoan": 2010,
    "fullTermOfAmalgamatedLoan": 6,
    "incomeYearOfEnquiring": 2016,
    "amalgamatedLoanNotPaidByEOIY": 19.550559133903764,
    "repayments": null,
    "lodgement_date": null
  },
  "idx": 2948
}