{
  "id": "2023-09-06T23:41:19.548Z0.8576594816878123",
  "alert": "Start of result\nResult\n\nMinimum yearly repayment not met.\n\nThe amount of the loan not repaid at the end of income year 2001-02 is $2,247.00.\n\nThe private company may be taken to pay a dividend under Division 7A to the shareholder or shareholder's associate because the amount repaid during income year 2001-02 in relation to the amalgamated loan is less than the minimum yearly repayment required.\n\nInterest received by the private company must be included in the income tax return for 2001-02.\n\nMinimum yearly repayment\n\n$2,400.00\n\nBenchmark interest rate\n\n6.8%\n\nOpening balance:\n\nDate: 30/06/2001\n\nBalance: $2,247.00\n\nDays: 365\n\nInterest: $152.80\n\nTotal repayments\n\n$0\n\nTotal interest\n\n$152.80\n\nTotal principal\n\n$0\n\nClosing balance\n\nDate: 30/06/2002\n\nBalance: $2,247.00",
  "outputs": {
    "enquiryRateFormatted": "6.8%",
    "enquiryYearEndMinusOneDisplay": "30/06/2001",
    "amalgamatedLoanNotPaidByEOIYFormatted": "$2,247.00",
    "openingBalancePayDays": "365",
    "openingBalanceInterestFormatted": "$152.80",
    "totalAmountOfRepaymentFormatted": "$0",
    "totalInterestFormatted": "$152.80",
    "principalFormatted": "$0",
    "enquiryYearEndDisplay": "30/06/2002",
    "minimumYearRepaymentFormatted": "$2,400.00"
  },
  "repayments": [],
  "inputs": {
    "incomeYearOfLoan": 2000,
    "fullTermOfAmalgamatedLoan": 2,
    "incomeYearOfEnquiring": 2002,
    "amalgamatedLoanNotPaidByEOIY": 2247,
    "repayments": null,
    "lodgement_date": null
  },
  "idx": 4432
}