{
  "id": "2023-10-31T18:39:24.949Z0.30523605922885166",
  "alert": "Start of result\nResult\n\nMinimum yearly repayment not met.\n\nThe amount of the loan not repaid at the end of income year 2012-13 is $3,172.89.\n\nThe private company may be taken to pay a dividend under Division 7A to the shareholder or shareholder's associate because the amount repaid during income year 2012-13 in relation to the amalgamated loan is less than the minimum yearly repayment required.\n\nInterest received by the private company must be included in the income tax return for 2012-13.\n\nMinimum yearly repayment\n\n$7,273.00\n\nBenchmark interest rate\n\n7.05%\n\nOpening balance:\n\nDate: 30/06/2012\n\nBalance: $6,794.00\n\nDays: 123\n\nInterest: $161.41\n\nPayments\n\nDate: 01/11/2012\n\nAmount: $3,917.00\n\nBalance: $2,877.00\n\nDays: 242\n\nInterest: $134.48\n\n\n\n\nTotal repayments\n\n$3,917.00\n\nTotal interest\n\n$295.89\n\nTotal principal\n\n$3,621.11\n\nClosing balance\n\nDate: 30/06/2013\n\nBalance: $3,172.89",
  "outputs": {
    "enquiryRateFormatted": "7.05%",
    "enquiryYearEndMinusOneDisplay": "30/06/2012",
    "amalgamatedLoanNotPaidByEOIYFormatted": "$6,794.00",
    "openingBalancePayDays": "123",
    "openingBalanceInterestFormatted": "$161.41",
    "totalAmountOfRepaymentFormatted": "$3,917.00",
    "totalInterestFormatted": "$295.89",
    "principalFormatted": "$3,621.11",
    "enquiryYearEndDisplay": "30/06/2013",
    "minimumYearRepaymentFormatted": "$7,273.00",
    "loanAmountFormatted": "$3,172.89"
  },
  "repayments": [
    {
      "rd": "1/11/2012",
      "ra": 3917
    }
  ],
  "inputs": {
    "incomeYearOfLoan": 2008,
    "fullTermOfAmalgamatedLoan": 5,
    "incomeYearOfEnquiring": 2013,
    "amalgamatedLoanNotPaidByEOIY": 6794,
    "repayments": null,
    "lodgement_date": null
  },
  "idx": 4340
}