{
  "id": "2023-10-31T18:34:01.731Z0.3266078423957519",
  "alert": "Start of result\nResult\n\nAmalgamated loan fully repaid.\n\nThe amalgamated loan has been paid in full.\u000bThe private company is not taken under Division 7A to pay a dividend to the shareholder or shareholder's associate.\n\nInterest received by the private company must be included in the income tax return for 2010-11.\n\nMinimum yearly repayment\n\n$3.00\n\nBenchmark interest rate\n\n7.4%\n\nOpening balance:\n\nDate: 30/06/2010\n\nBalance: $12.98\n\nDays: 162\n\nInterest: $0.43\n\nPayments\n\nDate: 10/12/2010\n\nAmount: $129.81\n\nBalance: $0\n\nDays: 203\n\nInterest: $0\n\n\n\n\nTotal repayments\n\n$129.81\n\nTotal interest\n\n$0.43\n\nTotal principal\n\n$129.38\n\nClosing balance\n\nDate: 30/06/2011\n\nBalance: $0",
  "outputs": {
    "enquiryRateFormatted": "7.4%",
    "enquiryYearEndMinusOneDisplay": "30/06/2010",
    "amalgamatedLoanNotPaidByEOIYFormatted": "$12.98",
    "openingBalancePayDays": "162",
    "openingBalanceInterestFormatted": "$0.43",
    "totalAmountOfRepaymentFormatted": "$129.81",
    "totalInterestFormatted": "$0.43",
    "principalFormatted": "$129.38",
    "enquiryYearEndDisplay": "30/06/2011",
    "minimumYearRepaymentFormatted": "$3.00",
    "loanAmountFormatted": "$0"
  },
  "repayments": [
    {
      "rd": "10/12/2010",
      "ra": 129.81326841350256
    }
  ],
  "inputs": {
    "incomeYearOfLoan": 2009,
    "fullTermOfAmalgamatedLoan": 7,
    "incomeYearOfEnquiring": 2011,
    "amalgamatedLoanNotPaidByEOIY": 12.981326841350212,
    "repayments": null,
    "lodgement_date": null
  },
  "idx": 4185
}