{
  "id": "2023-09-04T20:56:01.810Z0.9969514910031889",
  "alert": "Start of result\nResult\n\nMinimum yearly repayment not met.\n\nThe amount of the loan not repaid at the end of income year 2010-11 is $43,833,858.65.\n\nThe private company may be taken to pay a dividend under Division 7A to the shareholder or shareholder's associate because the amount repaid during income year 2010-11 in relation to the amalgamated loan is less than the minimum yearly repayment required.\n\nInterest received by the private company must be included in the income tax return for 2010-11.\n\nMinimum yearly repayment\n\n$13,058,035.00\n\nBenchmark interest rate\n\n7.4%\n\nOpening balance:\n\nDate: 30/06/2010\n\nBalance: $43,833,858.65\n\nDays: 0\n\nInterest: $0\n\nPayments\n\nDate: 01/07/2010\n\nAmount: $21.00\n\nBalance: $43,833,837.65\n\nDays: 365\n\nInterest: $3,243,703.99\n\n\n\n\nTotal repayments\n\n$21.00\n\nTotal interest\n\n$3,243,703.99\n\nTotal principal\n\n$0\n\nClosing balance\n\nDate: 30/06/2011\n\nBalance: $43,833,858.65",
  "outputs": {
    "enquiryRateFormatted": "7.4%",
    "enquiryYearEndMinusOneDisplay": "30/06/2010",
    "amalgamatedLoanNotPaidByEOIYFormatted": "$43,833,858.65",
    "openingBalancePayDays": "0",
    "openingBalanceInterestFormatted": "$0",
    "totalAmountOfRepaymentFormatted": "$21.00",
    "totalInterestFormatted": "$3,243,703.99",
    "principalFormatted": "$0",
    "enquiryYearEndDisplay": "30/06/2011",
    "minimumYearRepaymentFormatted": "$13,058,035.00"
  },
  "repayments": [
    {
      "rd": "1/7/2010",
      "ra": 21
    }
  ],
  "inputs": {
    "incomeYearOfLoan": 2010,
    "fullTermOfAmalgamatedLoan": 4,
    "incomeYearOfEnquiring": 2011,
    "amalgamatedLoanNotPaidByEOIY": 43833858.650511585,
    "repayments": null,
    "lodgement_date": "17/1/2011"
  },
  "idx": 330
}