{
  "id": "2023-09-07T00:49:54.302Z0.3775820097219711",
  "alert": "Start of result\nResult\n\nMinimum yearly repayment not met.\n\nThe amount of the loan not repaid at the end of income year 2006-07 is $1.11.\n\nThe private company may be taken to pay a dividend under Division 7A to the shareholder or shareholder's associate because the amount repaid during income year 2006-07 in relation to the amalgamated loan is less than the minimum yearly repayment required.\n\nInterest received by the private company must be included in the income tax return for 2006-07.\n\nMinimum yearly repayment\n\n$36.00\n\nBenchmark interest rate\n\n7.55%\n\nOpening balance:\n\nDate: 30/06/2006\n\nBalance: $33.89\n\nDays: 159\n\nInterest: $1.11\n\nPayments\n\nDate: 07/12/2006\n\nAmount: $33.89\n\nBalance: $0\n\nDays: 206\n\nInterest: $0\n\n\n\n\nTotal repayments\n\n$33.89\n\nTotal interest\n\n$1.11\n\nTotal principal\n\n$32.78\n\nClosing balance\n\nDate: 30/06/2007\n\nBalance: $1.11",
  "outputs": {
    "enquiryRateFormatted": "7.55%",
    "enquiryYearEndMinusOneDisplay": "30/06/2006",
    "amalgamatedLoanNotPaidByEOIYFormatted": "$33.89",
    "openingBalancePayDays": "159",
    "openingBalanceInterestFormatted": "$1.11",
    "totalAmountOfRepaymentFormatted": "$33.89",
    "totalInterestFormatted": "$1.11",
    "principalFormatted": "$32.78",
    "enquiryYearEndDisplay": "30/06/2007",
    "minimumYearRepaymentFormatted": "$36.00"
  },
  "repayments": [
    {
      "rd": "7/12/2006",
      "ra": 33.89343846353131
    }
  ],
  "inputs": {
    "incomeYearOfLoan": 2000,
    "fullTermOfAmalgamatedLoan": 7,
    "incomeYearOfEnquiring": 2007,
    "amalgamatedLoanNotPaidByEOIY": 33.89343846353153,
    "repayments": null,
    "lodgement_date": null
  },
  "idx": 8123
}