{
  "id": "2023-09-04T16:31:05.775Z0.12857814966296122",
  "alert": "Start of result\nResult\n\nMinimum yearly repayment met.\n\nThe amount of the loan not repaid at the end of income year 2021-22 is $2,338.11.\n\nThe amalgamated loan will not be taken to be a dividend because the total repayments made are equal to or greater than the minimum yearly repayment required for income year 2021-22.\n\nInterest received by the private company must be included in the income tax return for 2021-22.\n\nMinimum yearly repayment\n\n$2,587.00\n\nBenchmark interest rate\n\n4.52%\n\nOpening balance:\n\nDate: 30/06/2021\n\nBalance: $7,108.00\n\nDays: 0\n\nInterest: $0\n\nPayments\n\nDate: 01/07/2021\n\nAmount: $4,871.00\n\nBalance: $2,237.00\n\nDays: 365\n\nInterest: $101.11\n\n\n\n\nTotal repayments\n\n$4,871.00\n\nTotal interest\n\n$101.11\n\nTotal principal\n\n$4,769.89\n\nClosing balance\n\nDate: 30/06/2022\n\nBalance: $2,338.11",
  "outputs": {
    "enquiryRateFormatted": "4.52%",
    "enquiryYearEndMinusOneDisplay": "30/06/2021",
    "amalgamatedLoanNotPaidByEOIYFormatted": "$7,108.00",
    "openingBalancePayDays": "0",
    "openingBalanceInterestFormatted": "$0",
    "totalAmountOfRepaymentFormatted": "$4,871.00",
    "totalInterestFormatted": "$101.11",
    "principalFormatted": "$4,769.89",
    "enquiryYearEndDisplay": "30/06/2022",
    "minimumYearRepaymentFormatted": "$2,587.00"
  },
  "repayments": [
    {
      "rd": "1/7/2021",
      "ra": 4871
    }
  ],
  "inputs": {
    "incomeYearOfLoan": 2018,
    "fullTermOfAmalgamatedLoan": 6,
    "incomeYearOfEnquiring": 2022,
    "amalgamatedLoanNotPaidByEOIY": 7108,
    "repayments": null,
    "lodgement_date": null
  },
  "idx": 678
}