{
  "id": "2023-10-31T17:43:13.730Z0.18458081201584853",
  "alert": "Start of result\nResult\n\nMinimum yearly repayment not met.\n\nThe amount of the loan not repaid at the end of income year 2019-20 is $10,786.00.\n\nThe private company may be taken to pay a dividend under Division 7A to the shareholder or shareholder's associate because the amount repaid during income year 2019-20 in relation to the amalgamated loan is less than the minimum yearly repayment required.\n\nInterest received by the private company must be included in the income tax return for 2019-20.\n\nMinimum yearly repayment\n\n$3,988.00\n\nBenchmark interest rate\n\n5.37%\n\nOpening balance:\n\nDate: 30/06/2019\n\nBalance: $10,786.00\n\nDays: 359\n\nInterest: $568.13\n\nPayments\n\nDate: 24/06/2020\n\nAmount: $316.00\n\nBalance: $10,470.00\n\nDays: 7\n\nInterest: $10.75\n\n\n\n\nTotal repayments\n\n$316.00\n\nTotal interest\n\n$578.88\n\nTotal principal\n\n$0\n\nClosing balance\n\nDate: 30/06/2020\n\nBalance: $10,786.00",
  "outputs": {
    "enquiryRateFormatted": "5.37%",
    "enquiryYearEndMinusOneDisplay": "30/06/2019",
    "amalgamatedLoanNotPaidByEOIYFormatted": "$10,786.00",
    "openingBalancePayDays": "359",
    "openingBalanceInterestFormatted": "$568.13",
    "totalAmountOfRepaymentFormatted": "$316.00",
    "totalInterestFormatted": "$578.88",
    "principalFormatted": "$0",
    "enquiryYearEndDisplay": "30/06/2020",
    "minimumYearRepaymentFormatted": "$3,988.00",
    "loanAmountFormatted": "$10,786.00"
  },
  "repayments": [
    {
      "rd": "24/6/2020",
      "ra": 316
    }
  ],
  "inputs": {
    "incomeYearOfLoan": 2015,
    "fullTermOfAmalgamatedLoan": 7,
    "incomeYearOfEnquiring": 2020,
    "amalgamatedLoanNotPaidByEOIY": 10786,
    "repayments": null,
    "lodgement_date": null
  },
  "idx": 2374
}