{
  "id": "2023-10-31T17:16:00.881Z0.05119537339217428",
  "alert": "Start of result\nResult\n\nAmalgamated loan fully repaid.\n\nThe amalgamated loan has been paid in full.\u000bThe private company is not taken under Division 7A to pay a dividend to the shareholder or shareholder's associate.\n\nInterest received by the private company must be included in the income tax return for 2023-24.\n\nMinimum yearly repayment\n\n$6,485.00\n\nBenchmark interest rate\n\n8.27%\n\nOpening balance:\n\nDate: 30/06/2023\n\nBalance: $5,990.00\n\nDays: 309\n\nInterest: $418.22\n\nPayments\n\nDate: 05/05/2024\n\nAmount: $8,033.00\n\nBalance: $0\n\nDays: 57\n\nInterest: $0\n\n\n\n\nTotal repayments\n\n$8,033.00\n\nTotal interest\n\n$418.22\n\nTotal principal\n\n$7,614.78\n\nClosing balance\n\nDate: 30/06/2024\n\nBalance: $0",
  "outputs": {
    "enquiryRateFormatted": "8.27%",
    "enquiryYearEndMinusOneDisplay": "30/06/2023",
    "amalgamatedLoanNotPaidByEOIYFormatted": "$5,990.00",
    "openingBalancePayDays": "309",
    "openingBalanceInterestFormatted": "$418.22",
    "totalAmountOfRepaymentFormatted": "$8,033.00",
    "totalInterestFormatted": "$418.22",
    "principalFormatted": "$7,614.78",
    "enquiryYearEndDisplay": "30/06/2024",
    "minimumYearRepaymentFormatted": "$6,485.00",
    "loanAmountFormatted": "$0"
  },
  "repayments": [
    {
      "rd": "5/5/2024",
      "ra": 8033
    }
  ],
  "inputs": {
    "incomeYearOfLoan": 2020,
    "fullTermOfAmalgamatedLoan": 4,
    "incomeYearOfEnquiring": 2024,
    "amalgamatedLoanNotPaidByEOIY": 5990,
    "repayments": null,
    "lodgement_date": null
  },
  "idx": 799
}