{
  "id": "2023-10-31T20:10:14.973Z0.5932971643822958",
  "alert": "Start of result\nResult\n\nAmalgamated loan fully repaid.\n\nThe amalgamated loan has been paid in full.\u000bThe private company is not taken under Division 7A to pay a dividend to the shareholder or shareholder's associate.\n\nInterest received by the private company must be included in the income tax return for 2001-02.\n\nMinimum yearly repayment\n\n-$64.00\n\nBenchmark interest rate\n\n6.8%\n\nOpening balance:\n\nDate: 30/06/2001\n\nBalance: $6.61\n\nDays: 221\n\nInterest: $0.27\n\nPayments\n\nDate: 07/02/2002\n\nAmount: $66.14\n\nBalance: $0\n\nDays: 144\n\nInterest: $0\n\n\n\n\nTotal repayments\n\n$66.14\n\nTotal interest\n\n$0.27\n\nTotal principal\n\n$65.87\n\nClosing balance\n\nDate: 30/06/2002\n\nBalance: $0",
  "outputs": {
    "enquiryRateFormatted": "6.8%",
    "enquiryYearEndMinusOneDisplay": "30/06/2001",
    "amalgamatedLoanNotPaidByEOIYFormatted": "$6.61",
    "openingBalancePayDays": "221",
    "openingBalanceInterestFormatted": "$0.27",
    "totalAmountOfRepaymentFormatted": "$66.14",
    "totalInterestFormatted": "$0.27",
    "principalFormatted": "$65.87",
    "enquiryYearEndDisplay": "30/06/2002",
    "minimumYearRepaymentFormatted": "-$64.00",
    "loanAmountFormatted": "$0"
  },
  "repayments": [
    {
      "rd": "7/2/2002",
      "ra": 66.14691254784339
    }
  ],
  "inputs": {
    "incomeYearOfLoan": 2001,
    "fullTermOfAmalgamatedLoan": 1,
    "incomeYearOfEnquiring": 2002,
    "amalgamatedLoanNotPaidByEOIY": 6.614691254784353,
    "repayments": null,
    "lodgement_date": "30/6/2002"
  },
  "idx": 6235
}