{
  "id": "2023-09-06T01:51:23.869Z0.05641183848279452",
  "alert": "Start of result\nResult\n\nMinimum yearly repayment met.\n\nThe amount of the loan not repaid at the end of income year 2019-20 is $0.87.\n\nThe amalgamated loan will not be taken to be a dividend because the total repayments made are equal to or greater than the minimum yearly repayment required for income year 2019-20.\n\nInterest received by the private company must be included in the income tax return for 2019-20.\n\nMinimum yearly repayment\n\n$3,223.00\n\nBenchmark interest rate\n\n5.37%\n\nOpening balance:\n\nDate: 30/06/2019\n\nBalance: $5,962.00\n\nDays: 1\n\nInterest: $0.87\n\nPayments\n\nDate: 02/07/2019\n\nAmount: $5,962.00\n\nBalance: $0\n\nDays: 365\n\nInterest: $0\n\n\n\n\nTotal repayments\n\n$5,962.00\n\nTotal interest\n\n$0.87\n\nTotal principal\n\n$5,961.13\n\nClosing balance\n\nDate: 30/06/2020\n\nBalance: $0.87",
  "outputs": {
    "enquiryRateFormatted": "5.37%",
    "enquiryYearEndMinusOneDisplay": "30/06/2019",
    "amalgamatedLoanNotPaidByEOIYFormatted": "$5,962.00",
    "openingBalancePayDays": "1",
    "openingBalanceInterestFormatted": "$0.87",
    "totalAmountOfRepaymentFormatted": "$5,962.00",
    "totalInterestFormatted": "$0.87",
    "principalFormatted": "$5,961.13",
    "enquiryYearEndDisplay": "30/06/2020",
    "minimumYearRepaymentFormatted": "$3,223.00"
  },
  "repayments": [
    {
      "rd": "2/7/2019",
      "ra": 5962
    }
  ],
  "inputs": {
    "incomeYearOfLoan": 2014,
    "fullTermOfAmalgamatedLoan": 7,
    "incomeYearOfEnquiring": 2020,
    "amalgamatedLoanNotPaidByEOIY": 5962,
    "repayments": null,
    "lodgement_date": null
  },
  "idx": 7759
}