{
  "id": "2023-09-07T02:30:38.905Z0.20105580003313372",
  "alert": "Start of result\nResult\n\nMinimum yearly repayment not met.\n\nThe amount of the loan not repaid at the end of income year 2004-05 is $6,321.29.\n\nThe private company may be taken to pay a dividend under Division 7A to the shareholder or shareholder's associate because the amount repaid during income year 2004-05 in relation to the amalgamated loan is less than the minimum yearly repayment required.\n\nInterest received by the private company must be included in the income tax return for 2004-05.\n\nMinimum yearly repayment\n\n$3,677.00\n\nBenchmark interest rate\n\n7.05%\n\nOpening balance:\n\nDate: 30/06/2004\n\nBalance: $6,644.00\n\nDays: 318\n\nInterest: $408.09\n\nPayments\n\nDate: 15/05/2005\n\nAmount: $784.00\n\nBalance: $5,860.00\n\nDays: 47\n\nInterest: $53.20\n\n\n\n\nTotal repayments\n\n$784.00\n\nTotal interest\n\n$461.29\n\nTotal principal\n\n$322.71\n\nClosing balance\n\nDate: 30/06/2005\n\nBalance: $6,321.29",
  "outputs": {
    "enquiryRateFormatted": "7.05%",
    "enquiryYearEndMinusOneDisplay": "30/06/2004",
    "amalgamatedLoanNotPaidByEOIYFormatted": "$6,644.00",
    "openingBalancePayDays": "318",
    "openingBalanceInterestFormatted": "$408.09",
    "totalAmountOfRepaymentFormatted": "$784.00",
    "totalInterestFormatted": "$461.29",
    "principalFormatted": "$322.71",
    "enquiryYearEndDisplay": "30/06/2005",
    "minimumYearRepaymentFormatted": "$3,677.00"
  },
  "repayments": [
    {
      "rd": "15/5/2005",
      "ra": 784
    }
  ],
  "inputs": {
    "incomeYearOfLoan": 1999,
    "fullTermOfAmalgamatedLoan": 7,
    "incomeYearOfEnquiring": 2005,
    "amalgamatedLoanNotPaidByEOIY": 6644,
    "repayments": null,
    "lodgement_date": null
  },
  "idx": 5171
}