{
  "id": "2023-09-04T16:14:46.049Z0.3162844759199801",
  "alert": "Start of result\nResult\n\nMinimum yearly repayment met.\n\nThe amount of the loan not repaid at the end of income year 2021-22 is $3,182.63.\n\nThe amalgamated loan will not be taken to be a dividend because the total repayments made are equal to or greater than the minimum yearly repayment required for income year 2021-22.\n\nInterest received by the private company must be included in the income tax return for 2021-22.\n\nMinimum yearly repayment\n\n$1,108.00\n\nBenchmark interest rate\n\n4.52%\n\nOpening balance:\n\nDate: 30/06/2021\n\nBalance: $9,701.00\n\nDays: 0\n\nInterest: $0\n\nPayments\n\nDate: 01/07/2021\n\nAmount: $6,656.00\n\nBalance: $3,045.00\n\nDays: 365\n\nInterest: $137.63\n\n\n\n\nTotal repayments\n\n$6,656.00\n\nTotal interest\n\n$137.63\n\nTotal principal\n\n$6,518.37\n\nClosing balance\n\nDate: 30/06/2022\n\nBalance: $3,182.63",
  "outputs": {
    "enquiryRateFormatted": "4.52%",
    "enquiryYearEndMinusOneDisplay": "30/06/2021",
    "amalgamatedLoanNotPaidByEOIYFormatted": "$9,701.00",
    "openingBalancePayDays": "0",
    "openingBalanceInterestFormatted": "$0",
    "totalAmountOfRepaymentFormatted": "$6,656.00",
    "totalInterestFormatted": "$137.63",
    "principalFormatted": "$6,518.37",
    "enquiryYearEndDisplay": "30/06/2022",
    "minimumYearRepaymentFormatted": "$1,108.00"
  },
  "repayments": [
    {
      "rd": "1/7/2021",
      "ra": 6656
    }
  ],
  "inputs": {
    "incomeYearOfLoan": 2021,
    "fullTermOfAmalgamatedLoan": 3,
    "incomeYearOfEnquiring": 2022,
    "amalgamatedLoanNotPaidByEOIY": 9701,
    "repayments": null,
    "lodgement_date": "27/4/2022"
  },
  "idx": 88
}