{
  "id": "2023-09-04T22:11:43.935Z0.2663842501411047",
  "alert": "Start of result\nResult\n\nMinimum yearly repayment not met.\n\nThe amount of the loan not repaid at the end of income year 2002-03 is $90,701,507.33.\n\nThe private company may be taken to pay a dividend under Division 7A to the shareholder or shareholder's associate because the amount repaid during income year 2002-03 in relation to the amalgamated loan is less than the minimum yearly repayment required.\n\nInterest received by the private company must be included in the income tax return for 2002-03.\n\nMinimum yearly repayment\n\n$18,618,803.00\n\nBenchmark interest rate\n\n6.3%\n\nOpening balance:\n\nDate: 30/06/2002\n\nBalance: $90,701,507.33\n\nDays: 0\n\nInterest: $0\n\nPayments\n\nDate: 01/07/2002\n\nAmount: $3,469.00\n\nBalance: $90,698,038.33\n\nDays: 365\n\nInterest: $5,713,976.41\n\n\n\n\nTotal repayments\n\n$3,469.00\n\nTotal interest\n\n$5,713,976.41\n\nTotal principal\n\n$0\n\nClosing balance\n\nDate: 30/06/2003\n\nBalance: $90,701,507.33",
  "outputs": {
    "enquiryRateFormatted": "6.3%",
    "enquiryYearEndMinusOneDisplay": "30/06/2002",
    "amalgamatedLoanNotPaidByEOIYFormatted": "$90,701,507.33",
    "openingBalancePayDays": "0",
    "openingBalanceInterestFormatted": "$0",
    "totalAmountOfRepaymentFormatted": "$3,469.00",
    "totalInterestFormatted": "$5,713,976.41",
    "principalFormatted": "$0",
    "enquiryYearEndDisplay": "30/06/2003",
    "minimumYearRepaymentFormatted": "$18,618,803.00"
  },
  "repayments": [
    {
      "rd": "1/7/2002",
      "ra": 3469
    }
  ],
  "inputs": {
    "incomeYearOfLoan": 2002,
    "fullTermOfAmalgamatedLoan": 6,
    "incomeYearOfEnquiring": 2003,
    "amalgamatedLoanNotPaidByEOIY": 90701507.3394742,
    "repayments": null,
    "lodgement_date": "17/1/2003"
  },
  "idx": 430
}