{
  "id": "2023-10-31T17:20:30.681Z0.23534649851729517",
  "alert": "Start of result\nResult\n\nMinimum yearly repayment met.\n\nThe amount of the loan not repaid at the end of income year 2019-20 is $3,044.47.\n\n\u000b\n\nThe amalgamated loan will not be taken to be a dividend because the total repayments made are equal to or greater than the minimum yearly repayment required for income year 2019-20.\n\nInterest received by the private company must be included in the income tax return for 2019-20.\n\nMinimum yearly repayment\n\n$2,532.00\n\nBenchmark interest rate\n\n5.37%\n\nOpening balance:\n\nDate: 30/06/2019\n\nBalance: $8,901.00\n\nDays: 57\n\nInterest: $74.44\n\nPayments\n\nDate: 27/08/2019\n\nAmount: $1,530.00\n\nBalance: $7,371.00\n\nDays: 95\n\nInterest: $102.74\n\n\n\n\nDate: 30/11/2019\n\nAmount: $4,591.00\n\nBalance: $2,780.00\n\nDays: 214\n\nInterest: $87.29\n\n\n\n\nTotal repayments\n\n$6,121.00\n\nTotal interest\n\n$264.47\n\nTotal principal\n\n$5,856.53\n\nClosing balance\n\nDate: 30/06/2020\n\nBalance: $3,044.47",
  "outputs": {
    "enquiryRateFormatted": "5.37%",
    "enquiryYearEndMinusOneDisplay": "30/06/2019",
    "amalgamatedLoanNotPaidByEOIYFormatted": "$8,901.00",
    "openingBalancePayDays": "57",
    "openingBalanceInterestFormatted": "$74.44",
    "totalAmountOfRepaymentFormatted": "$6,121.00",
    "totalInterestFormatted": "$264.47",
    "principalFormatted": "$5,856.53",
    "enquiryYearEndDisplay": "30/06/2020",
    "minimumYearRepaymentFormatted": "$2,532.00",
    "loanAmountFormatted": "$3,044.47"
  },
  "repayments": [
    {
      "rd": "27/8/2019",
      "ra": 1530
    },
    {
      "rd": "30/11/2019",
      "ra": 4591
    }
  ],
  "inputs": {
    "incomeYearOfLoan": 2019,
    "fullTermOfAmalgamatedLoan": 4,
    "incomeYearOfEnquiring": 2020,
    "amalgamatedLoanNotPaidByEOIY": 8901,
    "repayments": null,
    "lodgement_date": "31/7/2019"
  },
  "idx": 1129
}