{
  "id": "2023-10-31T17:08:09.738Z0.7956741455928903",
  "alert": "Start of result\nResult\n\nAmalgamated loan fully repaid.\n\nThe amalgamated loan has been paid in full.\u000bThe private company is not taken under Division 7A to pay a dividend to the shareholder or shareholder's associate.\n\nInterest received by the private company must be included in the income tax return for 2023-24.\n\nMinimum yearly repayment\n\n$20.00\n\nBenchmark interest rate\n\n8.27%\n\nOpening balance:\n\nDate: 30/06/2023\n\nBalance: $92.70\n\nDays: 180\n\nInterest: $3.77\n\nPayments\n\nDate: 28/12/2023\n\nAmount: $927.06\n\nBalance: $0\n\nDays: 186\n\nInterest: $0\n\n\n\n\nTotal repayments\n\n$927.06\n\nTotal interest\n\n$3.77\n\nTotal principal\n\n$923.29\n\nClosing balance\n\nDate: 30/06/2024\n\nBalance: $0",
  "outputs": {
    "enquiryRateFormatted": "8.27%",
    "enquiryYearEndMinusOneDisplay": "30/06/2023",
    "amalgamatedLoanNotPaidByEOIYFormatted": "$92.70",
    "openingBalancePayDays": "180",
    "openingBalanceInterestFormatted": "$3.77",
    "totalAmountOfRepaymentFormatted": "$927.06",
    "totalInterestFormatted": "$3.77",
    "principalFormatted": "$923.29",
    "enquiryYearEndDisplay": "30/06/2024",
    "minimumYearRepaymentFormatted": "$20.00",
    "loanAmountFormatted": "$0"
  },
  "repayments": [
    {
      "rd": "28/12/2023",
      "ra": 927.0625926720477
    }
  ],
  "inputs": {
    "incomeYearOfLoan": 2023,
    "fullTermOfAmalgamatedLoan": 6,
    "incomeYearOfEnquiring": 2024,
    "amalgamatedLoanNotPaidByEOIY": 92.70625926720479,
    "repayments": null,
    "lodgement_date": "30/8/2023"
  },
  "idx": 128
}