{
  "id": "2023-10-31T19:16:21.647Z0.10243548840404293",
  "alert": "Start of result\nResult\n\nMinimum yearly repayment not met.\n\nThe amount of the loan not repaid at the end of income year 2009-10 is $98.67.\n\nThe private company may be taken to pay a dividend under Division 7A to the shareholder or shareholder's associate because the amount repaid during income year 2009-10 in relation to the amalgamated loan is less than the minimum yearly repayment required.\n\nInterest received by the private company must be included in the income tax return for 2009-10.\n\nMinimum yearly repayment\n\n$3,197.00\n\nBenchmark interest rate\n\n5.75%\n\nOpening balance:\n\nDate: 30/06/2009\n\nBalance: $3,023.00\n\nDays: 224\n\nInterest: $106.67\n\nPayments\n\nDate: 10/02/2010\n\nAmount: $3,031.00\n\nBalance: $0\n\nDays: 141\n\nInterest: $0\n\n\n\n\nTotal repayments\n\n$3,031.00\n\nTotal interest\n\n$106.67\n\nTotal principal\n\n$2,924.33\n\nClosing balance\n\nDate: 30/06/2010\n\nBalance: $98.67",
  "outputs": {
    "enquiryRateFormatted": "5.75%",
    "enquiryYearEndMinusOneDisplay": "30/06/2009",
    "amalgamatedLoanNotPaidByEOIYFormatted": "$3,023.00",
    "openingBalancePayDays": "224",
    "openingBalanceInterestFormatted": "$106.67",
    "totalAmountOfRepaymentFormatted": "$3,031.00",
    "totalInterestFormatted": "$106.67",
    "principalFormatted": "$2,924.33",
    "enquiryYearEndDisplay": "30/06/2010",
    "minimumYearRepaymentFormatted": "$3,197.00",
    "loanAmountFormatted": "$98.67"
  },
  "repayments": [
    {
      "rd": "10/2/2010",
      "ra": 3031
    }
  ],
  "inputs": {
    "incomeYearOfLoan": 2005,
    "fullTermOfAmalgamatedLoan": 5,
    "incomeYearOfEnquiring": 2010,
    "amalgamatedLoanNotPaidByEOIY": 3023,
    "repayments": null,
    "lodgement_date": null
  },
  "idx": 5250
}