{
  "id": "2023-10-31T19:33:22.301Z0.9369183716603374",
  "alert": "Start of result\nResult\n\nMinimum yearly repayment not met.\n\nThe amount of the loan not repaid at the end of income year 2008-09 is $2.29.\n\nThe private company may be taken to pay a dividend under Division 7A to the shareholder or shareholder's associate because the amount repaid during income year 2008-09 in relation to the amalgamated loan is less than the minimum yearly repayment required.\n\nInterest received by the private company must be included in the income tax return for 2008-09.\n\nMinimum yearly repayment\n\n$1.00\n\nBenchmark interest rate\n\n9.45%\n\nOpening balance:\n\nDate: 30/06/2008\n\nBalance: $2.29\n\nDays: 365\n\nInterest: $0.22\n\nTotal repayments\n\n$0\n\nTotal interest\n\n$0.22\n\nTotal principal\n\n$0\n\nClosing balance\n\nDate: 30/06/2009\n\nBalance: $2.29",
  "outputs": {
    "enquiryRateFormatted": "9.45%",
    "enquiryYearEndMinusOneDisplay": "30/06/2008",
    "amalgamatedLoanNotPaidByEOIYFormatted": "$2.29",
    "openingBalancePayDays": "365",
    "openingBalanceInterestFormatted": "$0.22",
    "totalAmountOfRepaymentFormatted": "$0",
    "totalInterestFormatted": "$0.22",
    "principalFormatted": "$0",
    "enquiryYearEndDisplay": "30/06/2009",
    "minimumYearRepaymentFormatted": "$1.00",
    "loanAmountFormatted": "$2.29"
  },
  "repayments": [],
  "inputs": {
    "incomeYearOfLoan": 2004,
    "fullTermOfAmalgamatedLoan": 7,
    "incomeYearOfEnquiring": 2009,
    "amalgamatedLoanNotPaidByEOIY": 2.293622817151135,
    "repayments": null,
    "lodgement_date": null
  },
  "idx": 5592
}