{
  "id": "2023-09-06T20:08:55.907Z0.09825061494483611",
  "alert": "Start of result\nResult\n\nMinimum yearly repayment met.\n\nThe amount of the loan not repaid at the end of income year 2004-05 is $6,195.74.\n\nThe amalgamated loan will not be taken to be a dividend because the total repayments made are equal to or greater than the minimum yearly repayment required for income year 2004-05.\n\nInterest received by the private company must be included in the income tax return for 2004-05.\n\nMinimum yearly repayment\n\n$2,724.00\n\nBenchmark interest rate\n\n7.05%\n\nOpening balance:\n\nDate: 30/06/2004\n\nBalance: $11,153.00\n\nDays: 308\n\nInterest: $663.50\n\nPayments\n\nDate: 05/05/2005\n\nAmount: $5,681.00\n\nBalance: $5,472.00\n\nDays: 57\n\nInterest: $60.24\n\n\n\n\nTotal repayments\n\n$5,681.00\n\nTotal interest\n\n$723.74\n\nTotal principal\n\n$4,957.26\n\nClosing balance\n\nDate: 30/06/2005\n\nBalance: $6,195.74",
  "outputs": {
    "enquiryRateFormatted": "7.05%",
    "enquiryYearEndMinusOneDisplay": "30/06/2004",
    "amalgamatedLoanNotPaidByEOIYFormatted": "$11,153.00",
    "openingBalancePayDays": "308",
    "openingBalanceInterestFormatted": "$663.50",
    "totalAmountOfRepaymentFormatted": "$5,681.00",
    "totalInterestFormatted": "$723.74",
    "principalFormatted": "$4,957.26",
    "enquiryYearEndDisplay": "30/06/2005",
    "minimumYearRepaymentFormatted": "$2,724.00"
  },
  "repayments": [
    {
      "rd": "5/5/2005",
      "ra": 5681
    }
  ],
  "inputs": {
    "incomeYearOfLoan": 2003,
    "fullTermOfAmalgamatedLoan": 6,
    "incomeYearOfEnquiring": 2005,
    "amalgamatedLoanNotPaidByEOIY": 11153,
    "repayments": null,
    "lodgement_date": null
  },
  "idx": 743
}