{
  "id": "2023-10-31T17:29:36.617Z0.45193705699492925",
  "alert": "Start of result\nResult\n\nAmalgamated loan fully repaid.\n\nThe amalgamated loan has been paid in full.\u000bThe private company is not taken under Division 7A to pay a dividend to the shareholder or shareholder's associate.\n\nInterest received by the private company must be included in the income tax return for 2022-23.\n\nMinimum yearly repayment\n\n$83.00\n\nBenchmark interest rate\n\n4.77%\n\nOpening balance:\n\nDate: 30/06/2022\n\nBalance: $78.90\n\nDays: 210\n\nInterest: $2.17\n\nPayments\n\nDate: 27/01/2023\n\nAmount: $535.00\n\nBalance: $0\n\nDays: 155\n\nInterest: $0\n\n\n\n\nTotal repayments\n\n$535.00\n\nTotal interest\n\n$2.17\n\nTotal principal\n\n$532.83\n\nClosing balance\n\nDate: 30/06/2023\n\nBalance: $0",
  "outputs": {
    "enquiryRateFormatted": "4.77%",
    "enquiryYearEndMinusOneDisplay": "30/06/2022",
    "amalgamatedLoanNotPaidByEOIYFormatted": "$78.90",
    "openingBalancePayDays": "210",
    "openingBalanceInterestFormatted": "$2.17",
    "totalAmountOfRepaymentFormatted": "$535.00",
    "totalInterestFormatted": "$2.17",
    "principalFormatted": "$532.83",
    "enquiryYearEndDisplay": "30/06/2023",
    "minimumYearRepaymentFormatted": "$83.00",
    "loanAmountFormatted": "$0"
  },
  "repayments": [
    {
      "rd": "27/1/2023",
      "ra": 535
    }
  ],
  "inputs": {
    "incomeYearOfLoan": 2017,
    "fullTermOfAmalgamatedLoan": 6,
    "incomeYearOfEnquiring": 2023,
    "amalgamatedLoanNotPaidByEOIY": 78.90009791133384,
    "repayments": null,
    "lodgement_date": null
  },
  "idx": 1674
}