{
  "id": "2023-09-04T22:11:19.033Z0.24882067337656166",
  "alert": "Start of result\nResult\n\nMinimum yearly repayment not met.\n\nThe amount of the loan not repaid at the end of income year 2005-06 is $8,271.76.\n\nThe private company may be taken to pay a dividend under Division 7A to the shareholder or shareholder's associate because the amount repaid during income year 2005-06 in relation to the amalgamated loan is less than the minimum yearly repayment required.\n\nInterest received by the private company must be included in the income tax return for 2005-06.\n\nMinimum yearly repayment\n\n$4,634.00\n\nBenchmark interest rate\n\n7.3%\n\nOpening balance:\n\nDate: 30/06/2005\n\nBalance: $12,096.00\n\nDays: 0\n\nInterest: $0\n\nPayments\n\nDate: 01/07/2005\n\nAmount: $4,387.00\n\nBalance: $7,709.00\n\nDays: 365\n\nInterest: $562.76\n\n\n\n\nTotal repayments\n\n$4,387.00\n\nTotal interest\n\n$562.76\n\nTotal principal\n\n$3,824.24\n\nClosing balance\n\nDate: 30/06/2006\n\nBalance: $8,271.76",
  "outputs": {
    "enquiryRateFormatted": "7.3%",
    "enquiryYearEndMinusOneDisplay": "30/06/2005",
    "amalgamatedLoanNotPaidByEOIYFormatted": "$12,096.00",
    "openingBalancePayDays": "0",
    "openingBalanceInterestFormatted": "$0",
    "totalAmountOfRepaymentFormatted": "$4,387.00",
    "totalInterestFormatted": "$562.76",
    "principalFormatted": "$3,824.24",
    "enquiryYearEndDisplay": "30/06/2006",
    "minimumYearRepaymentFormatted": "$4,634.00"
  },
  "repayments": [
    {
      "rd": "1/7/2005",
      "ra": 4387
    }
  ],
  "inputs": {
    "incomeYearOfLoan": 2002,
    "fullTermOfAmalgamatedLoan": 6,
    "incomeYearOfEnquiring": 2006,
    "amalgamatedLoanNotPaidByEOIY": 12096,
    "repayments": null,
    "lodgement_date": null
  },
  "idx": 415
}