{
  "id": "2023-09-06T00:04:50.746Z0.27637801687307073",
  "alert": "Start of result\nResult\n\nMinimum yearly repayment not met.\n\nThe amount of the loan not repaid at the end of income year 2015-16 is $23.56.\n\nThe private company may be taken to pay a dividend under Division 7A to the shareholder or shareholder's associate because the amount repaid during income year 2015-16 in relation to the amalgamated loan is less than the minimum yearly repayment required.\n\nInterest received by the private company must be included in the income tax return for 2015-16.\n\nMinimum yearly repayment\n\n$5.00\n\nBenchmark interest rate\n\n5.45%\n\nOpening balance:\n\nDate: 30/06/2015\n\nBalance: $23.56\n\nDays: 366\n\nInterest: $1.28\n\nTotal repayments\n\n$0\n\nTotal interest\n\n$1.28\n\nTotal principal\n\n$0\n\nClosing balance\n\nDate: 30/06/2016\n\nBalance: $23.56",
  "outputs": {
    "enquiryRateFormatted": "5.45%",
    "enquiryYearEndMinusOneDisplay": "30/06/2015",
    "amalgamatedLoanNotPaidByEOIYFormatted": "$23.56",
    "openingBalancePayDays": "366",
    "openingBalanceInterestFormatted": "$1.28",
    "totalAmountOfRepaymentFormatted": "$0",
    "totalInterestFormatted": "$1.28",
    "principalFormatted": "$0",
    "enquiryYearEndDisplay": "30/06/2016",
    "minimumYearRepaymentFormatted": "$5.00"
  },
  "repayments": [],
  "inputs": {
    "incomeYearOfLoan": 2015,
    "fullTermOfAmalgamatedLoan": 6,
    "incomeYearOfEnquiring": 2016,
    "amalgamatedLoanNotPaidByEOIY": 23.569603362235544,
    "repayments": null,
    "lodgement_date": "12/10/2015"
  },
  "idx": 1591
}