{
  "id": "2023-09-07T02:07:36.407Z0.6824028854927011",
  "alert": "Start of result\nResult\n\nMinimum yearly repayment not met.\n\nThe amount of the loan not repaid at the end of income year 1999-00 is $112.64.\n\nThe private company may be taken to pay a dividend under Division 7A to the shareholder or shareholder's associate because the amount repaid during income year 1999-00 in relation to the amalgamated loan is less than the minimum yearly repayment required.\n\nInterest received by the private company must be included in the income tax return for 1999-00.\n\nMinimum yearly repayment\n\n$27.00\n\nBenchmark interest rate\n\n6.5%\n\nOpening balance:\n\nDate: 30/06/1999\n\nBalance: $112.64\n\nDays: 366\n\nInterest: $7.32\n\nTotal repayments\n\n$0\n\nTotal interest\n\n$7.32\n\nTotal principal\n\n$0\n\nClosing balance\n\nDate: 30/06/2000\n\nBalance: $112.64",
  "outputs": {
    "enquiryRateFormatted": "6.5%",
    "enquiryYearEndMinusOneDisplay": "30/06/1999",
    "amalgamatedLoanNotPaidByEOIYFormatted": "$112.64",
    "openingBalancePayDays": "366",
    "openingBalanceInterestFormatted": "$7.32",
    "totalAmountOfRepaymentFormatted": "$0",
    "totalInterestFormatted": "$7.32",
    "principalFormatted": "$0",
    "enquiryYearEndDisplay": "30/06/2000",
    "minimumYearRepaymentFormatted": "$27.00"
  },
  "repayments": [],
  "inputs": {
    "incomeYearOfLoan": 1999,
    "fullTermOfAmalgamatedLoan": 5,
    "incomeYearOfEnquiring": 2000,
    "amalgamatedLoanNotPaidByEOIY": 112.6415454332964,
    "repayments": null,
    "lodgement_date": "30/10/1999"
  },
  "idx": 3811
}