{
  "id": "2023-09-04T16:42:04.847Z0.5413038970456727",
  "alert": "Start of result\nResult\n\nMinimum yearly repayment not met.\n\nThe amount of the loan not repaid at the end of income year 2016-17 is $4,128.52.\n\nThe private company may be taken to pay a dividend under Division 7A to the shareholder or shareholder's associate because the amount repaid during income year 2016-17 in relation to the amalgamated loan is less than the minimum yearly repayment required.\n\nInterest received by the private company must be included in the income tax return for 2016-17.\n\nMinimum yearly repayment\n\n$4,503.00\n\nBenchmark interest rate\n\n5.4%\n\nOpening balance:\n\nDate: 30/06/2016\n\nBalance: $8,325.00\n\nDays: 0\n\nInterest: $0\n\nPayments\n\nDate: 01/07/2016\n\nAmount: $4,408.00\n\nBalance: $3,917.00\n\nDays: 365\n\nInterest: $211.52\n\n\n\n\nTotal repayments\n\n$4,408.00\n\nTotal interest\n\n$211.52\n\nTotal principal\n\n$4,196.48\n\nClosing balance\n\nDate: 30/06/2017\n\nBalance: $4,128.52",
  "outputs": {
    "enquiryRateFormatted": "5.4%",
    "enquiryYearEndMinusOneDisplay": "30/06/2016",
    "amalgamatedLoanNotPaidByEOIYFormatted": "$8,325.00",
    "openingBalancePayDays": "0",
    "openingBalanceInterestFormatted": "$0",
    "totalAmountOfRepaymentFormatted": "$4,408.00",
    "totalInterestFormatted": "$211.52",
    "principalFormatted": "$4,196.48",
    "enquiryYearEndDisplay": "30/06/2017",
    "minimumYearRepaymentFormatted": "$4,503.00"
  },
  "repayments": [
    {
      "rd": "1/7/2016",
      "ra": 4408
    }
  ],
  "inputs": {
    "incomeYearOfLoan": 2016,
    "fullTermOfAmalgamatedLoan": 2,
    "incomeYearOfEnquiring": 2017,
    "amalgamatedLoanNotPaidByEOIY": 8325,
    "repayments": null,
    "lodgement_date": "1/7/2016"
  },
  "idx": 1024
}