{
  "id": "2023-09-07T03:58:42.839Z0.5868267383702277",
  "alert": "Start of result\nResult\n\nMinimum yearly repayment not met.\n\nThe amount of the loan not repaid at the end of income year 2002-03 is $7,699.73.\n\nThe private company may be taken to pay a dividend under Division 7A to the shareholder or shareholder's associate because the amount repaid during income year 2002-03 in relation to the amalgamated loan is less than the minimum yearly repayment required.\n\nInterest received by the private company must be included in the income tax return for 2002-03.\n\nMinimum yearly repayment\n\n$6,272.00\n\nBenchmark interest rate\n\n6.3%\n\nOpening balance:\n\nDate: 30/06/2002\n\nBalance: $11,450.00\n\nDays: 346\n\nInterest: $683.80\n\nPayments\n\nDate: 12/06/2003\n\nAmount: $4,457.00\n\nBalance: $6,993.00\n\nDays: 19\n\nInterest: $22.93\n\n\n\n\nTotal repayments\n\n$4,457.00\n\nTotal interest\n\n$706.73\n\nTotal principal\n\n$3,750.27\n\nClosing balance\n\nDate: 30/06/2003\n\nBalance: $7,699.73",
  "outputs": {
    "enquiryRateFormatted": "6.3%",
    "enquiryYearEndMinusOneDisplay": "30/06/2002",
    "amalgamatedLoanNotPaidByEOIYFormatted": "$11,450.00",
    "openingBalancePayDays": "346",
    "openingBalanceInterestFormatted": "$683.80",
    "totalAmountOfRepaymentFormatted": "$4,457.00",
    "totalInterestFormatted": "$706.73",
    "principalFormatted": "$3,750.27",
    "enquiryYearEndDisplay": "30/06/2003",
    "minimumYearRepaymentFormatted": "$6,272.00"
  },
  "repayments": [
    {
      "rd": "12/6/2003",
      "ra": 4457
    }
  ],
  "inputs": {
    "incomeYearOfLoan": 1998,
    "fullTermOfAmalgamatedLoan": 6,
    "incomeYearOfEnquiring": 2003,
    "amalgamatedLoanNotPaidByEOIY": 11450,
    "repayments": null,
    "lodgement_date": null
  },
  "idx": 2213
}