{
  "id": "2023-09-04T22:05:14.053Z0.45703928708222374",
  "alert": "Start of result\nResult\n\nMinimum yearly repayment not met.\n\nThe amount of the loan not repaid at the end of income year 2005-06 is $7,557.00.\n\nThe private company may be taken to pay a dividend under Division 7A to the shareholder or shareholder's associate because the amount repaid during income year 2005-06 in relation to the amalgamated loan is less than the minimum yearly repayment required.\n\nInterest received by the private company must be included in the income tax return for 2005-06.\n\nMinimum yearly repayment\n\n$8,109.00\n\nBenchmark interest rate\n\n7.3%\n\nOpening balance:\n\nDate: 30/06/2005\n\nBalance: $7,557.00\n\nDays: 365\n\nInterest: $551.66\n\nTotal repayments\n\n$0\n\nTotal interest\n\n$551.66\n\nTotal principal\n\n$0\n\nClosing balance\n\nDate: 30/06/2006\n\nBalance: $7,557.00",
  "outputs": {
    "enquiryRateFormatted": "7.3%",
    "enquiryYearEndMinusOneDisplay": "30/06/2005",
    "amalgamatedLoanNotPaidByEOIYFormatted": "$7,557.00",
    "openingBalancePayDays": "365",
    "openingBalanceInterestFormatted": "$551.66",
    "totalAmountOfRepaymentFormatted": "$0",
    "totalInterestFormatted": "$551.66",
    "principalFormatted": "$0",
    "enquiryYearEndDisplay": "30/06/2006",
    "minimumYearRepaymentFormatted": "$8,109.00"
  },
  "repayments": [],
  "inputs": {
    "incomeYearOfLoan": 2003,
    "fullTermOfAmalgamatedLoan": 3,
    "incomeYearOfEnquiring": 2006,
    "amalgamatedLoanNotPaidByEOIY": 7557,
    "repayments": null,
    "lodgement_date": null
  },
  "idx": 179
}