{
  "id": "2023-09-05T20:12:18.784Z0.44964313653534793",
  "alert": "Start of result\nResult\n\nMinimum yearly repayment met.\n\nThe amount of the loan not repaid at the end of income year 2017-18 is $2,814.89.\n\nThe amalgamated loan will not be taken to be a dividend because the total repayments made are equal to or greater than the minimum yearly repayment required for income year 2017-18.\n\nInterest received by the private company must be included in the income tax return for 2017-18.\n\nMinimum yearly repayment\n\n$608.00\n\nBenchmark interest rate\n\n5.3%\n\nOpening balance:\n\nDate: 30/06/2017\n\nBalance: $9,325.00\n\nDays: 66\n\nInterest: $89.37\n\nPayments\n\nDate: 05/09/2017\n\nAmount: $6,214.00\n\nBalance: $3,111.00\n\nDays: 16\n\nInterest: $7.23\n\n\n\n\nDate: 21/09/2017\n\nAmount: $500.00\n\nBalance: $2,611.00\n\nDays: 283\n\nInterest: $107.29\n\n\n\n\nTotal repayments\n\n$6,714.00\n\nTotal interest\n\n$203.89\n\nTotal principal\n\n$6,510.11\n\nClosing balance\n\nDate: 30/06/2018\n\nBalance: $2,814.89",
  "outputs": {
    "enquiryRateFormatted": "5.3%",
    "enquiryYearEndMinusOneDisplay": "30/06/2017",
    "amalgamatedLoanNotPaidByEOIYFormatted": "$9,325.00",
    "openingBalancePayDays": "66",
    "openingBalanceInterestFormatted": "$89.37",
    "totalAmountOfRepaymentFormatted": "$6,714.00",
    "totalInterestFormatted": "$203.89",
    "principalFormatted": "$6,510.11",
    "enquiryYearEndDisplay": "30/06/2018",
    "minimumYearRepaymentFormatted": "$608.00"
  },
  "repayments": [
    {
      "rd": "5/9/2017",
      "ra": 6214
    },
    {
      "rd": "21/9/2017",
      "ra": 500
    }
  ],
  "inputs": {
    "incomeYearOfLoan": 2017,
    "fullTermOfAmalgamatedLoan": 5,
    "incomeYearOfEnquiring": 2018,
    "amalgamatedLoanNotPaidByEOIY": 9325,
    "repayments": null,
    "lodgement_date": "4/2/2018"
  },
  "idx": 5374
}