{
  "id": "2023-09-06T13:44:05.098Z0.14351504387320402",
  "alert": "Start of result\nResult\n\nMinimum yearly repayment met.\n\nThe amount of the loan not repaid at the end of income year 2007-08 is $5.71.\n\nThe amalgamated loan will not be taken to be a dividend because the total repayments made are equal to or greater than the minimum yearly repayment required for income year 2007-08.\n\nInterest received by the private company must be included in the income tax return for 2007-08.\n\nMinimum yearly repayment\n\n$14.00\n\nBenchmark interest rate\n\n8.05%\n\nOpening balance:\n\nDate: 30/06/2007\n\nBalance: $71.67\n\nDays: 362\n\nInterest: $5.71\n\nPayments\n\nDate: 27/06/2008\n\nAmount: $71.67\n\nBalance: $0\n\nDays: 4\n\nInterest: $0\n\n\n\n\nTotal repayments\n\n$71.67\n\nTotal interest\n\n$5.71\n\nTotal principal\n\n$65.96\n\nClosing balance\n\nDate: 30/06/2008\n\nBalance: $5.71",
  "outputs": {
    "enquiryRateFormatted": "8.05%",
    "enquiryYearEndMinusOneDisplay": "30/06/2007",
    "amalgamatedLoanNotPaidByEOIYFormatted": "$71.67",
    "openingBalancePayDays": "362",
    "openingBalanceInterestFormatted": "$5.71",
    "totalAmountOfRepaymentFormatted": "$71.67",
    "totalInterestFormatted": "$5.71",
    "principalFormatted": "$65.96",
    "enquiryYearEndDisplay": "30/06/2008",
    "minimumYearRepaymentFormatted": "$14.00"
  },
  "repayments": [
    {
      "rd": "27/6/2008",
      "ra": 71.67691946974355
    }
  ],
  "inputs": {
    "incomeYearOfLoan": 2007,
    "fullTermOfAmalgamatedLoan": 7,
    "incomeYearOfEnquiring": 2008,
    "amalgamatedLoanNotPaidByEOIY": 71.67691946974364,
    "repayments": null,
    "lodgement_date": "23/5/2008"
  },
  "idx": 2927
}