{
  "id": "2023-09-04T16:35:45.739Z0.5408479338012693",
  "alert": "Start of result\nResult\n\nMinimum yearly repayment met.\n\nThe amount of the loan not repaid at the end of income year 2017-18 is $9,075.81.\n\nThe amalgamated loan will not be taken to be a dividend because the total repayments made are equal to or greater than the minimum yearly repayment required for income year 2017-18.\n\nInterest received by the private company must be included in the income tax return for 2017-18.\n\nMinimum yearly repayment\n\n$2,007.00\n\nBenchmark interest rate\n\n5.3%\n\nOpening balance:\n\nDate: 30/06/2017\n\nBalance: $10,875.00\n\nDays: 0\n\nInterest: $0\n\nPayments\n\nDate: 01/07/2017\n\nAmount: $2,256.00\n\nBalance: $8,619.00\n\nDays: 365\n\nInterest: $456.81\n\n\n\n\nTotal repayments\n\n$2,256.00\n\nTotal interest\n\n$456.81\n\nTotal principal\n\n$1,799.19\n\nClosing balance\n\nDate: 30/06/2018\n\nBalance: $9,075.81",
  "outputs": {
    "enquiryRateFormatted": "5.3%",
    "enquiryYearEndMinusOneDisplay": "30/06/2017",
    "amalgamatedLoanNotPaidByEOIYFormatted": "$10,875.00",
    "openingBalancePayDays": "0",
    "openingBalanceInterestFormatted": "$0",
    "totalAmountOfRepaymentFormatted": "$2,256.00",
    "totalInterestFormatted": "$456.81",
    "principalFormatted": "$1,799.19",
    "enquiryYearEndDisplay": "30/06/2018",
    "minimumYearRepaymentFormatted": "$2,007.00"
  },
  "repayments": [
    {
      "rd": "1/7/2017",
      "ra": 2256
    }
  ],
  "inputs": {
    "incomeYearOfLoan": 2017,
    "fullTermOfAmalgamatedLoan": 5,
    "incomeYearOfEnquiring": 2018,
    "amalgamatedLoanNotPaidByEOIY": 10875,
    "repayments": null,
    "lodgement_date": "30/6/2018"
  },
  "idx": 828
}