{
  "id": "2023-10-31T18:56:07.541Z0.06173544021736255",
  "alert": "Start of result\nResult\n\nAmalgamated loan fully repaid.\n\nThe amalgamated loan has been paid in full.\u000bThe private company is not taken under Division 7A to pay a dividend to the shareholder or shareholder's associate.\n\nInterest received by the private company must be included in the income tax return for 2008-09.\n\nMinimum yearly repayment\n\n$6.00\n\nBenchmark interest rate\n\n9.45%\n\nOpening balance:\n\nDate: 30/06/2008\n\nBalance: $25.55\n\nDays: 106\n\nInterest: $0.70\n\nPayments\n\nDate: 15/10/2008\n\nAmount: $255.57\n\nBalance: $0\n\nDays: 259\n\nInterest: $0\n\n\n\n\nTotal repayments\n\n$255.57\n\nTotal interest\n\n$0.70\n\nTotal principal\n\n$254.87\n\nClosing balance\n\nDate: 30/06/2009\n\nBalance: $0",
  "outputs": {
    "enquiryRateFormatted": "9.45%",
    "enquiryYearEndMinusOneDisplay": "30/06/2008",
    "amalgamatedLoanNotPaidByEOIYFormatted": "$25.55",
    "openingBalancePayDays": "106",
    "openingBalanceInterestFormatted": "$0.70",
    "totalAmountOfRepaymentFormatted": "$255.57",
    "totalInterestFormatted": "$0.70",
    "principalFormatted": "$254.87",
    "enquiryYearEndDisplay": "30/06/2009",
    "minimumYearRepaymentFormatted": "$6.00",
    "loanAmountFormatted": "$0"
  },
  "repayments": [
    {
      "rd": "15/10/2008",
      "ra": 255.57444247007197
    }
  ],
  "inputs": {
    "incomeYearOfLoan": 2007,
    "fullTermOfAmalgamatedLoan": 7,
    "incomeYearOfEnquiring": 2009,
    "amalgamatedLoanNotPaidByEOIY": 25.557444247007208,
    "repayments": null,
    "lodgement_date": null
  },
  "idx": 4769
}