{
  "id": "2023-09-04T20:52:03.276Z0.6799319504435297",
  "alert": "Start of result\nResult\n\nMinimum yearly repayment not met.\n\nThe amount of the loan not repaid at the end of income year 2014-15 is $11,026.00.\n\nThe private company may be taken to pay a dividend under Division 7A to the shareholder or shareholder's associate because the amount repaid during income year 2014-15 in relation to the amalgamated loan is less than the minimum yearly repayment required.\n\nInterest received by the private company must be included in the income tax return for 2014-15.\n\nMinimum yearly repayment\n\n$4,121.00\n\nBenchmark interest rate\n\n5.95%\n\nOpening balance:\n\nDate: 30/06/2014\n\nBalance: $11,026.00\n\nDays: 365\n\nInterest: $656.05\n\nTotal repayments\n\n$0\n\nTotal interest\n\n$656.05\n\nTotal principal\n\n$0\n\nClosing balance\n\nDate: 30/06/2015\n\nBalance: $11,026.00",
  "outputs": {
    "enquiryRateFormatted": "5.95%",
    "enquiryYearEndMinusOneDisplay": "30/06/2014",
    "amalgamatedLoanNotPaidByEOIYFormatted": "$11,026.00",
    "openingBalancePayDays": "365",
    "openingBalanceInterestFormatted": "$656.05",
    "totalAmountOfRepaymentFormatted": "$0",
    "totalInterestFormatted": "$656.05",
    "principalFormatted": "$0",
    "enquiryYearEndDisplay": "30/06/2015",
    "minimumYearRepaymentFormatted": "$4,121.00"
  },
  "repayments": [],
  "inputs": {
    "incomeYearOfLoan": 2011,
    "fullTermOfAmalgamatedLoan": 6,
    "incomeYearOfEnquiring": 2015,
    "amalgamatedLoanNotPaidByEOIY": 11026,
    "repayments": null,
    "lodgement_date": null
  },
  "idx": 194
}