{
  "id": "2023-09-06T13:33:25.377Z0.333990384877221",
  "alert": "Start of result\nResult\n\nMinimum yearly repayment met.\n\nThe amount of the loan not repaid at the end of income year 2009-10 is $241.54.\n\nThe amalgamated loan will not be taken to be a dividend because the total repayments made are equal to or greater than the minimum yearly repayment required for income year 2009-10.\n\nInterest received by the private company must be included in the income tax return for 2009-10.\n\nMinimum yearly repayment\n\n$1,119.00\n\nBenchmark interest rate\n\n5.75%\n\nOpening balance:\n\nDate: 30/06/2009\n\nBalance: $4,747.00\n\nDays: 323\n\nInterest: $241.54\n\nPayments\n\nDate: 20/05/2010\n\nAmount: $4,747.00\n\nBalance: $0\n\nDays: 42\n\nInterest: $0\n\n\n\n\nTotal repayments\n\n$4,747.00\n\nTotal interest\n\n$241.54\n\nTotal principal\n\n$4,505.46\n\nClosing balance\n\nDate: 30/06/2010\n\nBalance: $241.54",
  "outputs": {
    "enquiryRateFormatted": "5.75%",
    "enquiryYearEndMinusOneDisplay": "30/06/2009",
    "amalgamatedLoanNotPaidByEOIYFormatted": "$4,747.00",
    "openingBalancePayDays": "323",
    "openingBalanceInterestFormatted": "$241.54",
    "totalAmountOfRepaymentFormatted": "$4,747.00",
    "totalInterestFormatted": "$241.54",
    "principalFormatted": "$4,505.46",
    "enquiryYearEndDisplay": "30/06/2010",
    "minimumYearRepaymentFormatted": "$1,119.00"
  },
  "repayments": [
    {
      "rd": "20/5/2010",
      "ra": 4747
    }
  ],
  "inputs": {
    "incomeYearOfLoan": 2007,
    "fullTermOfAmalgamatedLoan": 7,
    "incomeYearOfEnquiring": 2010,
    "amalgamatedLoanNotPaidByEOIY": 4747,
    "repayments": null,
    "lodgement_date": null
  },
  "idx": 2230
}