{
  "id": "2023-09-06T08:09:43.244Z0.39217436569784625",
  "alert": "Start of result\nResult\n\nMinimum yearly repayment met.\n\nThe amount of the loan not repaid at the end of income year 2010-11 is $0.67.\n\nThe amalgamated loan will not be taken to be a dividend because the total repayments made are equal to or greater than the minimum yearly repayment required for income year 2010-11.\n\nInterest received by the private company must be included in the income tax return for 2010-11.\n\nMinimum yearly repayment\n\n$0\n\nBenchmark interest rate\n\n7.4%\n\nOpening balance:\n\nDate: 30/06/2010\n\nBalance: $28.93\n\nDays: 115\n\nInterest: $0.67\n\nPayments\n\nDate: 24/10/2010\n\nAmount: $28.93\n\nBalance: $0\n\nDays: 250\n\nInterest: $0\n\n\n\n\nTotal repayments\n\n$28.93\n\nTotal interest\n\n$0.67\n\nTotal principal\n\n$28.26\n\nClosing balance\n\nDate: 30/06/2011\n\nBalance: $0.67",
  "outputs": {
    "enquiryRateFormatted": "7.4%",
    "enquiryYearEndMinusOneDisplay": "30/06/2010",
    "amalgamatedLoanNotPaidByEOIYFormatted": "$28.93",
    "openingBalancePayDays": "115",
    "openingBalanceInterestFormatted": "$0.67",
    "totalAmountOfRepaymentFormatted": "$28.93",
    "totalInterestFormatted": "$0.67",
    "principalFormatted": "$28.26",
    "enquiryYearEndDisplay": "30/06/2011",
    "minimumYearRepaymentFormatted": "$0"
  },
  "repayments": [
    {
      "rd": "24/10/2010",
      "ra": 28.93043542706073
    }
  ],
  "inputs": {
    "incomeYearOfLoan": 2010,
    "fullTermOfAmalgamatedLoan": 4,
    "incomeYearOfEnquiring": 2011,
    "amalgamatedLoanNotPaidByEOIY": 28.930435427061113,
    "repayments": null,
    "lodgement_date": "7/4/2011"
  },
  "idx": 2120
}