{
  "id": "2023-10-31T17:19:34.393Z0.1700253919704704",
  "alert": "Start of result\nResult\n\nAmalgamated loan fully repaid.\n\nThe amalgamated loan has been paid in full.\u000bThe private company is not taken under Division 7A to pay a dividend to the shareholder or shareholder's associate.\n\nInterest received by the private company must be included in the income tax return for 2021-22.\n\nMinimum yearly repayment\n\n$7,153.00\n\nBenchmark interest rate\n\n4.52%\n\nOpening balance:\n\nDate: 30/06/2021\n\nBalance: $6,844.00\n\nDays: 127\n\nInterest: $107.64\n\nPayments\n\nDate: 05/11/2021\n\nAmount: $7,846.00\n\nBalance: $0\n\nDays: 238\n\nInterest: $0\n\n\n\n\nTotal repayments\n\n$7,846.00\n\nTotal interest\n\n$107.64\n\nTotal principal\n\n$7,738.36\n\nClosing balance\n\nDate: 30/06/2022\n\nBalance: $0",
  "outputs": {
    "enquiryRateFormatted": "4.52%",
    "enquiryYearEndMinusOneDisplay": "30/06/2021",
    "amalgamatedLoanNotPaidByEOIYFormatted": "$6,844.00",
    "openingBalancePayDays": "127",
    "openingBalanceInterestFormatted": "$107.64",
    "totalAmountOfRepaymentFormatted": "$7,846.00",
    "totalInterestFormatted": "$107.64",
    "principalFormatted": "$7,738.36",
    "enquiryYearEndDisplay": "30/06/2022",
    "minimumYearRepaymentFormatted": "$7,153.00",
    "loanAmountFormatted": "$0"
  },
  "repayments": [
    {
      "rd": "5/11/2021",
      "ra": 7846
    }
  ],
  "inputs": {
    "incomeYearOfLoan": 2019,
    "fullTermOfAmalgamatedLoan": 3,
    "incomeYearOfEnquiring": 2022,
    "amalgamatedLoanNotPaidByEOIY": 6844,
    "repayments": null,
    "lodgement_date": null
  },
  "idx": 1063
}