{
  "id": "2023-09-06T13:33:11.897Z0.19629554860529086",
  "alert": "Start of result\nResult\n\nMinimum yearly repayment not met.\n\nThe amount of the loan not repaid at the end of income year 2013-14 is $0.81.\n\nThe private company may be taken to pay a dividend under Division 7A to the shareholder or shareholder's associate because the amount repaid during income year 2013-14 in relation to the amalgamated loan is less than the minimum yearly repayment required.\n\nInterest received by the private company must be included in the income tax return for 2013-14.\n\nMinimum yearly repayment\n\n$45.00\n\nBenchmark interest rate\n\n6.2%\n\nOpening balance:\n\nDate: 30/06/2013\n\nBalance: $41.96\n\nDays: 113\n\nInterest: $0.81\n\nPayments\n\nDate: 22/10/2013\n\nAmount: $41.96\n\nBalance: $0\n\nDays: 252\n\nInterest: $0\n\n\n\n\nTotal repayments\n\n$41.96\n\nTotal interest\n\n$0.81\n\nTotal principal\n\n$41.15\n\nClosing balance\n\nDate: 30/06/2014\n\nBalance: $0.81",
  "outputs": {
    "enquiryRateFormatted": "6.2%",
    "enquiryYearEndMinusOneDisplay": "30/06/2013",
    "amalgamatedLoanNotPaidByEOIYFormatted": "$41.96",
    "openingBalancePayDays": "113",
    "openingBalanceInterestFormatted": "$0.81",
    "totalAmountOfRepaymentFormatted": "$41.96",
    "totalInterestFormatted": "$0.81",
    "principalFormatted": "$41.15",
    "enquiryYearEndDisplay": "30/06/2014",
    "minimumYearRepaymentFormatted": "$45.00"
  },
  "repayments": [
    {
      "rd": "22/10/2013",
      "ra": 41.966079973148226
    }
  ],
  "inputs": {
    "incomeYearOfLoan": 2007,
    "fullTermOfAmalgamatedLoan": 7,
    "incomeYearOfEnquiring": 2014,
    "amalgamatedLoanNotPaidByEOIY": 41.96607997314835,
    "repayments": null,
    "lodgement_date": null
  },
  "idx": 2222
}