{
  "id": "2023-10-31T17:52:00.805Z0.051797540907221995",
  "alert": "Start of result\nResult\n\nMinimum yearly repayment not met.\n\nThe amount of the loan not repaid at the end of income year 2017-18 is $20.27.\n\nThe private company may be taken to pay a dividend under Division 7A to the shareholder or shareholder's associate because the amount repaid during income year 2017-18 in relation to the amalgamated loan is less than the minimum yearly repayment required.\n\nInterest received by the private company must be included in the income tax return for 2017-18.\n\nMinimum yearly repayment\n\n$6.00\n\nBenchmark interest rate\n\n5.3%\n\nOpening balance:\n\nDate: 30/06/2017\n\nBalance: $20.27\n\nDays: 365\n\nInterest: $1.07\n\nTotal repayments\n\n$0\n\nTotal interest\n\n$1.07\n\nTotal principal\n\n$0\n\nClosing balance\n\nDate: 30/06/2018\n\nBalance: $20.27",
  "outputs": {
    "enquiryRateFormatted": "5.3%",
    "enquiryYearEndMinusOneDisplay": "30/06/2017",
    "amalgamatedLoanNotPaidByEOIYFormatted": "$20.27",
    "openingBalancePayDays": "365",
    "openingBalanceInterestFormatted": "$1.07",
    "totalAmountOfRepaymentFormatted": "$0",
    "totalInterestFormatted": "$1.07",
    "principalFormatted": "$0",
    "enquiryYearEndDisplay": "30/06/2018",
    "minimumYearRepaymentFormatted": "$6.00",
    "loanAmountFormatted": "$20.27"
  },
  "repayments": [],
  "inputs": {
    "incomeYearOfLoan": 2014,
    "fullTermOfAmalgamatedLoan": 7,
    "incomeYearOfEnquiring": 2018,
    "amalgamatedLoanNotPaidByEOIY": 20.27384151441545,
    "repayments": null,
    "lodgement_date": null
  },
  "idx": 2771
}