{
  "id": "2023-09-07T01:53:47.331Z0.6462034011158719",
  "alert": "Start of result\nResult\n\nMinimum yearly repayment met.\n\nThe amount of the loan not repaid at the end of income year 2001-02 is $4.21.\n\nThe amalgamated loan will not be taken to be a dividend because the total repayments made are equal to or greater than the minimum yearly repayment required for income year 2001-02.\n\nInterest received by the private company must be included in the income tax return for 2001-02.\n\nMinimum yearly repayment\n\n$46.00\n\nBenchmark interest rate\n\n6.8%\n\nOpening balance:\n\nDate: 30/06/2001\n\nBalance: $82.79\n\nDays: 273\n\nInterest: $4.21\n\nPayments\n\nDate: 31/03/2002\n\nAmount: $82.79\n\nBalance: $0\n\nDays: 92\n\nInterest: $0\n\n\n\n\nTotal repayments\n\n$82.79\n\nTotal interest\n\n$4.21\n\nTotal principal\n\n$78.58\n\nClosing balance\n\nDate: 30/06/2002\n\nBalance: $4.21",
  "outputs": {
    "enquiryRateFormatted": "6.8%",
    "enquiryYearEndMinusOneDisplay": "30/06/2001",
    "amalgamatedLoanNotPaidByEOIYFormatted": "$82.79",
    "openingBalancePayDays": "273",
    "openingBalanceInterestFormatted": "$4.21",
    "totalAmountOfRepaymentFormatted": "$82.79",
    "totalInterestFormatted": "$4.21",
    "principalFormatted": "$78.58",
    "enquiryYearEndDisplay": "30/06/2002",
    "minimumYearRepaymentFormatted": "$46.00"
  },
  "repayments": [
    {
      "rd": "31/3/2002",
      "ra": 82.79350959480598
    }
  ],
  "inputs": {
    "incomeYearOfLoan": 1999,
    "fullTermOfAmalgamatedLoan": 4,
    "incomeYearOfEnquiring": 2002,
    "amalgamatedLoanNotPaidByEOIY": 82.7935095948056,
    "repayments": null,
    "lodgement_date": null
  },
  "idx": 2945
}