{
  "id": "2023-09-05T15:17:01.224Z0.4485874299475694",
  "alert": "Start of result\nResult\n\nMinimum yearly repayment not met.\n\nThe amount of the loan not repaid at the end of income year 2020-21 is $8,537.28.\n\nThe private company may be taken to pay a dividend under Division 7A to the shareholder or shareholder's associate because the amount repaid during income year 2020-21 in relation to the amalgamated loan is less than the minimum yearly repayment required.\n\nInterest received by the private company must be included in the income tax return for 2020-21.\n\nMinimum yearly repayment\n\n$3,088.00\n\nBenchmark interest rate\n\n4.52%\n\nOpening balance:\n\nDate: 30/06/2020\n\nBalance: $11,072.00\n\nDays: 243\n\nInterest: $333.18\n\nPayments\n\nDate: 01/03/2021\n\nAmount: $2,990.00\n\nBalance: $8,082.00\n\nDays: 122\n\nInterest: $122.10\n\n\n\n\nTotal repayments\n\n$2,990.00\n\nTotal interest\n\n$455.28\n\nTotal principal\n\n$2,534.72\n\nClosing balance\n\nDate: 30/06/2021\n\nBalance: $8,537.28",
  "outputs": {
    "enquiryRateFormatted": "4.52%",
    "enquiryYearEndMinusOneDisplay": "30/06/2020",
    "amalgamatedLoanNotPaidByEOIYFormatted": "$11,072.00",
    "openingBalancePayDays": "243",
    "openingBalanceInterestFormatted": "$333.18",
    "totalAmountOfRepaymentFormatted": "$2,990.00",
    "totalInterestFormatted": "$455.28",
    "principalFormatted": "$2,534.72",
    "enquiryYearEndDisplay": "30/06/2021",
    "minimumYearRepaymentFormatted": "$3,088.00"
  },
  "repayments": [
    {
      "rd": "1/3/2021",
      "ra": 2990
    }
  ],
  "inputs": {
    "incomeYearOfLoan": 2020,
    "fullTermOfAmalgamatedLoan": 4,
    "incomeYearOfEnquiring": 2021,
    "amalgamatedLoanNotPaidByEOIY": 11072,
    "repayments": null,
    "lodgement_date": "31/1/2021"
  },
  "idx": 5728
}