{
  "id": "2023-09-04T17:16:43.090Z0.03281915647710454",
  "alert": "Start of result\nResult\n\nMinimum yearly repayment not met.\n\nThe amount of the loan not repaid at the end of income year 2014-15 is $97,173,260.65.\n\nThe private company may be taken to pay a dividend under Division 7A to the shareholder or shareholder's associate because the amount repaid during income year 2014-15 in relation to the amalgamated loan is less than the minimum yearly repayment required.\n\nInterest received by the private company must be included in the income tax return for 2014-15.\n\nMinimum yearly repayment\n\n$19,729,315.00\n\nBenchmark interest rate\n\n5.95%\n\nOpening balance:\n\nDate: 30/06/2014\n\nBalance: $97,173,260.65\n\nDays: 0\n\nInterest: $0\n\nPayments\n\nDate: 01/07/2014\n\nAmount: $5,229.00\n\nBalance: $97,168,031.65\n\nDays: 365\n\nInterest: $5,781,497.88\n\n\n\n\nTotal repayments\n\n$5,229.00\n\nTotal interest\n\n$5,781,497.88\n\nTotal principal\n\n$0\n\nClosing balance\n\nDate: 30/06/2015\n\nBalance: $97,173,260.65",
  "outputs": {
    "enquiryRateFormatted": "5.95%",
    "enquiryYearEndMinusOneDisplay": "30/06/2014",
    "amalgamatedLoanNotPaidByEOIYFormatted": "$97,173,260.65",
    "openingBalancePayDays": "0",
    "openingBalanceInterestFormatted": "$0",
    "totalAmountOfRepaymentFormatted": "$5,229.00",
    "totalInterestFormatted": "$5,781,497.88",
    "principalFormatted": "$0",
    "enquiryYearEndDisplay": "30/06/2015",
    "minimumYearRepaymentFormatted": "$19,729,315.00"
  },
  "repayments": [
    {
      "rd": "1/7/2014",
      "ra": 5229
    }
  ],
  "inputs": {
    "incomeYearOfLoan": 2014,
    "fullTermOfAmalgamatedLoan": 6,
    "incomeYearOfEnquiring": 2015,
    "amalgamatedLoanNotPaidByEOIY": 97173260.65009701,
    "repayments": null,
    "lodgement_date": "17/1/2015"
  },
  "idx": 1935
}