{
  "id": "2023-10-31T17:09:42.536Z0.6705964051833925",
  "alert": "Start of result\nResult\n\nAmalgamated loan fully repaid.\n\nThe amalgamated loan has been paid in full.\u000bThe private company is not taken under Division 7A to pay a dividend to the shareholder or shareholder's associate.\n\nInterest received by the private company must be included in the income tax return for 2022-23.\n\nMinimum yearly repayment\n\n$26.00\n\nBenchmark interest rate\n\n4.77%\n\nOpening balance:\n\nDate: 30/06/2022\n\nBalance: $93.13\n\nDays: 285\n\nInterest: $3.47\n\nPayments\n\nDate: 12/04/2023\n\nAmount: $931.30\n\nBalance: $0\n\nDays: 80\n\nInterest: $0\n\n\n\n\nTotal repayments\n\n$931.30\n\nTotal interest\n\n$3.47\n\nTotal principal\n\n$927.83\n\nClosing balance\n\nDate: 30/06/2023\n\nBalance: $0",
  "outputs": {
    "enquiryRateFormatted": "4.77%",
    "enquiryYearEndMinusOneDisplay": "30/06/2022",
    "amalgamatedLoanNotPaidByEOIYFormatted": "$93.13",
    "openingBalancePayDays": "285",
    "openingBalanceInterestFormatted": "$3.47",
    "totalAmountOfRepaymentFormatted": "$931.30",
    "totalInterestFormatted": "$3.47",
    "principalFormatted": "$927.83",
    "enquiryYearEndDisplay": "30/06/2023",
    "minimumYearRepaymentFormatted": "$26.00",
    "loanAmountFormatted": "$0"
  },
  "repayments": [
    {
      "rd": "12/4/2023",
      "ra": 931.3024988393772
    }
  ],
  "inputs": {
    "incomeYearOfLoan": 2022,
    "fullTermOfAmalgamatedLoan": 4,
    "incomeYearOfEnquiring": 2023,
    "amalgamatedLoanNotPaidByEOIY": 93.13024988393774,
    "repayments": null,
    "lodgement_date": "29/9/2022"
  },
  "idx": 276
}