{
  "id": "2023-09-06T19:36:26.819Z0.6604551883429237",
  "alert": "Start of result\nResult\n\nMinimum yearly repayment met.\n\nThe amount of the loan not repaid at the end of income year 2003-04 is $1,318.61.\n\nThe amalgamated loan will not be taken to be a dividend because the total repayments made are equal to or greater than the minimum yearly repayment required for income year 2003-04.\n\nInterest received by the private company must be included in the income tax return for 2003-04.\n\nMinimum yearly repayment\n\n$359.00\n\nBenchmark interest rate\n\n6.55%\n\nOpening balance:\n\nDate: 30/06/2003\n\nBalance: $5,321.00\n\nDays: 11\n\nInterest: $10.47\n\nPayments\n\nDate: 12/07/2003\n\nAmount: $4,091.00\n\nBalance: $1,230.00\n\nDays: 355\n\nInterest: $78.14\n\n\n\n\nTotal repayments\n\n$4,091.00\n\nTotal interest\n\n$88.61\n\nTotal principal\n\n$4,002.39\n\nClosing balance\n\nDate: 30/06/2004\n\nBalance: $1,318.61",
  "outputs": {
    "enquiryRateFormatted": "6.55%",
    "enquiryYearEndMinusOneDisplay": "30/06/2003",
    "amalgamatedLoanNotPaidByEOIYFormatted": "$5,321.00",
    "openingBalancePayDays": "11",
    "openingBalanceInterestFormatted": "$10.47",
    "totalAmountOfRepaymentFormatted": "$4,091.00",
    "totalInterestFormatted": "$88.61",
    "principalFormatted": "$4,002.39",
    "enquiryYearEndDisplay": "30/06/2004",
    "minimumYearRepaymentFormatted": "$359.00"
  },
  "repayments": [
    {
      "rd": "12/7/2003",
      "ra": 4091
    }
  ],
  "inputs": {
    "incomeYearOfLoan": 2003,
    "fullTermOfAmalgamatedLoan": 4,
    "incomeYearOfEnquiring": 2004,
    "amalgamatedLoanNotPaidByEOIY": 5321,
    "repayments": null,
    "lodgement_date": "2/11/2003"
  },
  "idx": 6401
}