{
  "id": "2023-09-04T16:28:08.216Z0.8747072788731107",
  "alert": "Start of result\nResult\n\nMinimum yearly repayment not met.\n\nThe amount of the loan not repaid at the end of income year 2018-19 is $5,165.62.\n\nThe private company may be taken to pay a dividend under Division 7A to the shareholder or shareholder's associate because the amount repaid during income year 2018-19 in relation to the amalgamated loan is less than the minimum yearly repayment required.\n\nInterest received by the private company must be included in the income tax return for 2018-19.\n\nMinimum yearly repayment\n\n$2,645.00\n\nBenchmark interest rate\n\n5.2%\n\nOpening balance:\n\nDate: 30/06/2018\n\nBalance: $6,710.00\n\nDays: 0\n\nInterest: $0\n\nPayments\n\nDate: 01/07/2018\n\nAmount: $898.00\n\nBalance: $5,812.00\n\nDays: 23\n\nInterest: $19.04\n\n\n\n\nDate: 24/07/2018\n\nAmount: $236.00\n\nBalance: $5,576.00\n\nDays: 38\n\nInterest: $30.19\n\n\n\n\nDate: 31/08/2018\n\nAmount: $672.00\n\nBalance: $4,904.00\n\nDays: 304\n\nInterest: $212.39\n\n\n\n\nTotal repayments\n\n$1,806.00\n\nTotal interest\n\n$261.62\n\nTotal principal\n\n$1,544.38\n\nClosing balance\n\nDate: 30/06/2019\n\nBalance: $5,165.62",
  "outputs": {
    "enquiryRateFormatted": "5.2%",
    "enquiryYearEndMinusOneDisplay": "30/06/2018",
    "amalgamatedLoanNotPaidByEOIYFormatted": "$6,710.00",
    "openingBalancePayDays": "0",
    "openingBalanceInterestFormatted": "$0",
    "totalAmountOfRepaymentFormatted": "$1,806.00",
    "totalInterestFormatted": "$261.62",
    "principalFormatted": "$1,544.38",
    "enquiryYearEndDisplay": "30/06/2019",
    "minimumYearRepaymentFormatted": "$2,645.00"
  },
  "repayments": [
    {
      "rd": "1/7/2018",
      "ra": 898
    },
    {
      "rd": "24/7/2018",
      "ra": 236
    },
    {
      "rd": "31/8/2018",
      "ra": 672
    }
  ],
  "inputs": {
    "incomeYearOfLoan": 2018,
    "fullTermOfAmalgamatedLoan": 2,
    "incomeYearOfEnquiring": 2019,
    "amalgamatedLoanNotPaidByEOIY": 6710,
    "repayments": null,
    "lodgement_date": "27/4/2019"
  },
  "idx": 580
}