{
  "id": "2023-10-31T18:11:25.284Z0.09455425472600576",
  "alert": "Start of result\nResult\n\nMinimum yearly repayment not met.\n\nThe amount of the loan not repaid at the end of income year 2013-14 is $4,161.00.\n\nThe private company may be taken to pay a dividend under Division 7A to the shareholder or shareholder's associate because the amount repaid during income year 2013-14 in relation to the amalgamated loan is less than the minimum yearly repayment required.\n\nInterest received by the private company must be included in the income tax return for 2013-14.\n\nMinimum yearly repayment\n\n$1,562.00\n\nBenchmark interest rate\n\n6.2%\n\nOpening balance:\n\nDate: 30/06/2013\n\nBalance: $4,161.00\n\nDays: 365\n\nInterest: $257.98\n\nTotal repayments\n\n$0\n\nTotal interest\n\n$257.98\n\nTotal principal\n\n$0\n\nClosing balance\n\nDate: 30/06/2014\n\nBalance: $4,161.00",
  "outputs": {
    "enquiryRateFormatted": "6.2%",
    "enquiryYearEndMinusOneDisplay": "30/06/2013",
    "amalgamatedLoanNotPaidByEOIYFormatted": "$4,161.00",
    "openingBalancePayDays": "365",
    "openingBalanceInterestFormatted": "$257.98",
    "totalAmountOfRepaymentFormatted": "$0",
    "totalInterestFormatted": "$257.98",
    "principalFormatted": "$0",
    "enquiryYearEndDisplay": "30/06/2014",
    "minimumYearRepaymentFormatted": "$1,562.00",
    "loanAmountFormatted": "$4,161.00"
  },
  "repayments": [],
  "inputs": {
    "incomeYearOfLoan": 2011,
    "fullTermOfAmalgamatedLoan": 5,
    "incomeYearOfEnquiring": 2014,
    "amalgamatedLoanNotPaidByEOIY": 4161,
    "repayments": null,
    "lodgement_date": null
  },
  "idx": 3502
}