{
  "id": "2023-10-31T18:09:57.268Z0.7006766691055444",
  "alert": "Start of result\nResult\n\nAmalgamated loan fully repaid.\n\nThe amalgamated loan has been paid in full.\u000bThe private company is not taken under Division 7A to pay a dividend to the shareholder or shareholder's associate.\n\nInterest received by the private company must be included in the income tax return for 2011-12.\n\nMinimum yearly repayment\n\n$2,083.00\n\nBenchmark interest rate\n\n7.8%\n\nOpening balance:\n\nDate: 30/06/2011\n\nBalance: $5,388.00\n\nDays: 295\n\nInterest: $338.74\n\nPayments\n\nDate: 21/04/2012\n\nAmount: $4,568.00\n\nBalance: $820.00\n\nDays: 51\n\nInterest: $8.91\n\n\n\n\nDate: 11/06/2012\n\nAmount: $3,076.00\n\nBalance: $0\n\nDays: 20\n\nInterest: $0\n\n\n\n\nTotal repayments\n\n$7,644.00\n\nTotal interest\n\n$347.65\n\nTotal principal\n\n$7,296.35\n\nClosing balance\n\nDate: 30/06/2012\n\nBalance: $0",
  "outputs": {
    "enquiryRateFormatted": "7.8%",
    "enquiryYearEndMinusOneDisplay": "30/06/2011",
    "amalgamatedLoanNotPaidByEOIYFormatted": "$5,388.00",
    "openingBalancePayDays": "295",
    "openingBalanceInterestFormatted": "$338.74",
    "totalAmountOfRepaymentFormatted": "$7,644.00",
    "totalInterestFormatted": "$347.65",
    "principalFormatted": "$7,296.35",
    "enquiryYearEndDisplay": "30/06/2012",
    "minimumYearRepaymentFormatted": "$2,083.00",
    "loanAmountFormatted": "$0"
  },
  "repayments": [
    {
      "rd": "21/4/2012",
      "ra": 4568
    },
    {
      "rd": "11/6/2012",
      "ra": 3076
    }
  ],
  "inputs": {
    "incomeYearOfLoan": 2011,
    "fullTermOfAmalgamatedLoan": 3,
    "incomeYearOfEnquiring": 2012,
    "amalgamatedLoanNotPaidByEOIY": 5388,
    "repayments": null,
    "lodgement_date": "29/10/2011"
  },
  "idx": 3452
}