{
  "id": "2023-10-31T20:55:39.834Z0.322013851549941",
  "alert": "Start of result\nResult\n\nAmalgamated loan fully repaid.\n\nThe amalgamated loan has been paid in full.\u000bThe private company is not taken under Division 7A to pay a dividend to the shareholder or shareholder's associate.\n\nInterest received by the private company must be included in the income tax return for 1999-00.\n\nMinimum yearly repayment\n\n$45.00\n\nBenchmark interest rate\n\n6.5%\n\nOpening balance:\n\nDate: 30/06/1999\n\nBalance: $119.14\n\nDays: 344\n\nInterest: $7.28\n\nPayments\n\nDate: 09/06/2000\n\nAmount: $1,191.40\n\nBalance: $0\n\nDays: 22\n\nInterest: $0\n\n\n\n\nTotal repayments\n\n$1,191.40\n\nTotal interest\n\n$7.28\n\nTotal principal\n\n$1,184.12\n\nClosing balance\n\nDate: 30/06/2000\n\nBalance: $0",
  "outputs": {
    "enquiryRateFormatted": "6.5%",
    "enquiryYearEndMinusOneDisplay": "30/06/1999",
    "amalgamatedLoanNotPaidByEOIYFormatted": "$119.14",
    "openingBalancePayDays": "344",
    "openingBalanceInterestFormatted": "$7.28",
    "totalAmountOfRepaymentFormatted": "$1,191.40",
    "totalInterestFormatted": "$7.28",
    "principalFormatted": "$1,184.12",
    "enquiryYearEndDisplay": "30/06/2000",
    "minimumYearRepaymentFormatted": "$45.00",
    "loanAmountFormatted": "$0"
  },
  "repayments": [
    {
      "rd": "9/6/2000",
      "ra": 1191.402238489958
    }
  ],
  "inputs": {
    "incomeYearOfLoan": 1999,
    "fullTermOfAmalgamatedLoan": 3,
    "incomeYearOfEnquiring": 2000,
    "amalgamatedLoanNotPaidByEOIY": 119.14022384899583,
    "repayments": null,
    "lodgement_date": "28/12/1999"
  },
  "idx": 6872
}