{
  "id": "2023-09-04T16:41:26.006Z0.1899759504412315",
  "alert": "Start of result\nResult\n\nMinimum yearly repayment not met.\n\nThe amount of the loan not repaid at the end of income year 2017-18 is $106,980,206.80.\n\nThe private company may be taken to pay a dividend under Division 7A to the shareholder or shareholder's associate because the amount repaid during income year 2017-18 in relation to the amalgamated loan is less than the minimum yearly repayment required.\n\nInterest received by the private company must be included in the income tax return for 2017-18.\n\nMinimum yearly repayment\n\n$112,650,158.00\n\nBenchmark interest rate\n\n5.3%\n\nOpening balance:\n\nDate: 30/06/2017\n\nBalance: $106,980,206.80\n\nDays: 365\n\nInterest: $5,669,950.96\n\nTotal repayments\n\n$0\n\nTotal interest\n\n$5,669,950.96\n\nTotal principal\n\n$0\n\nClosing balance\n\nDate: 30/06/2018\n\nBalance: $106,980,206.80",
  "outputs": {
    "enquiryRateFormatted": "5.3%",
    "enquiryYearEndMinusOneDisplay": "30/06/2017",
    "amalgamatedLoanNotPaidByEOIYFormatted": "$106,980,206.80",
    "openingBalancePayDays": "365",
    "openingBalanceInterestFormatted": "$5,669,950.96",
    "totalAmountOfRepaymentFormatted": "$0",
    "totalInterestFormatted": "$5,669,950.96",
    "principalFormatted": "$0",
    "enquiryYearEndDisplay": "30/06/2018",
    "minimumYearRepaymentFormatted": "$112,650,158.00"
  },
  "repayments": [],
  "inputs": {
    "incomeYearOfLoan": 2016,
    "fullTermOfAmalgamatedLoan": 2,
    "incomeYearOfEnquiring": 2018,
    "amalgamatedLoanNotPaidByEOIY": 106980206.80519441,
    "repayments": null,
    "lodgement_date": null
  },
  "idx": 1008
}