{
  "id": "2023-10-31T17:15:04.744Z0.6663660091004617",
  "alert": "Start of result\nResult\n\nMinimum yearly repayment not met.\n\nThe amount of the loan not repaid at the end of income year 2021-22 is $94.90.\n\nThe private company may be taken to pay a dividend under Division 7A to the shareholder or shareholder's associate because the amount repaid during income year 2021-22 in relation to the amalgamated loan is less than the minimum yearly repayment required.\n\nInterest received by the private company must be included in the income tax return for 2021-22.\n\nMinimum yearly repayment\n\n$99.00\n\nBenchmark interest rate\n\n4.52%\n\nOpening balance:\n\nDate: 30/06/2021\n\nBalance: $94.90\n\nDays: 365\n\nInterest: $4.29\n\nTotal repayments\n\n$0\n\nTotal interest\n\n$4.29\n\nTotal principal\n\n$0\n\nClosing balance\n\nDate: 30/06/2022\n\nBalance: $94.90",
  "outputs": {
    "enquiryRateFormatted": "4.52%",
    "enquiryYearEndMinusOneDisplay": "30/06/2021",
    "amalgamatedLoanNotPaidByEOIYFormatted": "$94.90",
    "openingBalancePayDays": "365",
    "openingBalanceInterestFormatted": "$4.29",
    "totalAmountOfRepaymentFormatted": "$0",
    "totalInterestFormatted": "$4.29",
    "principalFormatted": "$0",
    "enquiryYearEndDisplay": "30/06/2022",
    "minimumYearRepaymentFormatted": "$99.00",
    "loanAmountFormatted": "$94.90"
  },
  "repayments": [],
  "inputs": {
    "incomeYearOfLoan": 2020,
    "fullTermOfAmalgamatedLoan": 2,
    "incomeYearOfEnquiring": 2022,
    "amalgamatedLoanNotPaidByEOIY": 94.90712868362981,
    "repayments": null,
    "lodgement_date": null
  },
  "idx": 731
}