{
  "id": "2023-10-31T19:06:46.354Z0.17772664308231556",
  "alert": "Start of result\nResult\n\nMinimum yearly repayment met.\n\nThe amount of the loan not repaid at the end of income year 2010-11 is $3,628.02.\n\n\u000b\n\nThe amalgamated loan will not be taken to be a dividend because the total repayments made are equal to or greater than the minimum yearly repayment required for income year 2010-11.\n\nInterest received by the private company must be included in the income tax return for 2010-11.\n\nMinimum yearly repayment\n\n$6,418.00\n\nBenchmark interest rate\n\n7.4%\n\nOpening balance:\n\nDate: 30/06/2010\n\nBalance: $11,539.00\n\nDays: 54\n\nInterest: $126.33\n\nPayments\n\nDate: 24/08/2010\n\nAmount: $8,245.00\n\nBalance: $3,294.00\n\nDays: 311\n\nInterest: $207.69\n\n\n\n\nTotal repayments\n\n$8,245.00\n\nTotal interest\n\n$334.02\n\nTotal principal\n\n$7,910.98\n\nClosing balance\n\nDate: 30/06/2011\n\nBalance: $3,628.02",
  "outputs": {
    "enquiryRateFormatted": "7.4%",
    "enquiryYearEndMinusOneDisplay": "30/06/2010",
    "amalgamatedLoanNotPaidByEOIYFormatted": "$11,539.00",
    "openingBalancePayDays": "54",
    "openingBalanceInterestFormatted": "$126.33",
    "totalAmountOfRepaymentFormatted": "$8,245.00",
    "totalInterestFormatted": "$334.02",
    "principalFormatted": "$7,910.98",
    "enquiryYearEndDisplay": "30/06/2011",
    "minimumYearRepaymentFormatted": "$6,418.00",
    "loanAmountFormatted": "$3,628.02"
  },
  "repayments": [
    {
      "rd": "24/8/2010",
      "ra": 8245
    }
  ],
  "inputs": {
    "incomeYearOfLoan": 2006,
    "fullTermOfAmalgamatedLoan": 6,
    "incomeYearOfEnquiring": 2011,
    "amalgamatedLoanNotPaidByEOIY": 11539,
    "repayments": null,
    "lodgement_date": null
  },
  "idx": 5032
}