{
  "id": "2023-10-31T19:13:00.113Z0.7503168484209226",
  "alert": "Start of result\nResult\n\nMinimum yearly repayment not met.\n\nThe amount of the loan not repaid at the end of income year 2005-06 is $8,040.00.\n\nThe private company may be taken to pay a dividend under Division 7A to the shareholder or shareholder's associate because the amount repaid during income year 2005-06 in relation to the amalgamated loan is less than the minimum yearly repayment required.\n\nInterest received by the private company must be included in the income tax return for 2005-06.\n\nMinimum yearly repayment\n\n$4,465.00\n\nBenchmark interest rate\n\n7.3%\n\nOpening balance:\n\nDate: 30/06/2005\n\nBalance: $8,040.00\n\nDays: 300\n\nInterest: $482.40\n\nPayments\n\nDate: 27/04/2006\n\nAmount: $230.00\n\nBalance: $7,810.00\n\nDays: 65\n\nInterest: $101.53\n\n\n\n\nTotal repayments\n\n$230.00\n\nTotal interest\n\n$583.93\n\nTotal principal\n\n$0\n\nClosing balance\n\nDate: 30/06/2006\n\nBalance: $8,040.00",
  "outputs": {
    "enquiryRateFormatted": "7.3%",
    "enquiryYearEndMinusOneDisplay": "30/06/2005",
    "amalgamatedLoanNotPaidByEOIYFormatted": "$8,040.00",
    "openingBalancePayDays": "300",
    "openingBalanceInterestFormatted": "$482.40",
    "totalAmountOfRepaymentFormatted": "$230.00",
    "totalInterestFormatted": "$583.93",
    "principalFormatted": "$0",
    "enquiryYearEndDisplay": "30/06/2006",
    "minimumYearRepaymentFormatted": "$4,465.00",
    "loanAmountFormatted": "$8,040.00"
  },
  "repayments": [
    {
      "rd": "27/4/2006",
      "ra": 230
    }
  ],
  "inputs": {
    "incomeYearOfLoan": 2005,
    "fullTermOfAmalgamatedLoan": 2,
    "incomeYearOfEnquiring": 2006,
    "amalgamatedLoanNotPaidByEOIY": 8040,
    "repayments": null,
    "lodgement_date": "28/3/2006"
  },
  "idx": 5172
}