{
  "id": "2023-10-31T18:28:59.562Z0.5056328523748971",
  "alert": "Start of result\nResult\n\nAmalgamated loan fully repaid.\n\nThe amalgamated loan has been paid in full.\u000bThe private company is not taken under Division 7A to pay a dividend to the shareholder or shareholder's associate.\n\nInterest received by the private company must be included in the income tax return for 2009-10.\n\nMinimum yearly repayment\n\n$40.00\n\nBenchmark interest rate\n\n5.75%\n\nOpening balance:\n\nDate: 30/06/2009\n\nBalance: $106.62\n\nDays: 291\n\nInterest: $4.89\n\nPayments\n\nDate: 18/04/2010\n\nAmount: $1,066.23\n\nBalance: $0\n\nDays: 74\n\nInterest: $0\n\n\n\n\nTotal repayments\n\n$1,066.23\n\nTotal interest\n\n$4.89\n\nTotal principal\n\n$1,061.34\n\nClosing balance\n\nDate: 30/06/2010\n\nBalance: $0",
  "outputs": {
    "enquiryRateFormatted": "5.75%",
    "enquiryYearEndMinusOneDisplay": "30/06/2009",
    "amalgamatedLoanNotPaidByEOIYFormatted": "$106.62",
    "openingBalancePayDays": "291",
    "openingBalanceInterestFormatted": "$4.89",
    "totalAmountOfRepaymentFormatted": "$1,066.23",
    "totalInterestFormatted": "$4.89",
    "principalFormatted": "$1,061.34",
    "enquiryYearEndDisplay": "30/06/2010",
    "minimumYearRepaymentFormatted": "$40.00",
    "loanAmountFormatted": "$0"
  },
  "repayments": [
    {
      "rd": "18/4/2010",
      "ra": 1066.2397929157223
    }
  ],
  "inputs": {
    "incomeYearOfLoan": 2009,
    "fullTermOfAmalgamatedLoan": 3,
    "incomeYearOfEnquiring": 2010,
    "amalgamatedLoanNotPaidByEOIY": 106.62397929157223,
    "repayments": null,
    "lodgement_date": "30/8/2009"
  },
  "idx": 4050
}