{
  "id": "2023-09-06T08:22:34.280Z0.3870426525699435",
  "alert": "Start of result\nResult\n\nMinimum yearly repayment not met.\n\nThe amount of the loan not repaid at the end of income year 2014-15 is $2,106.00.\n\nThe private company may be taken to pay a dividend under Division 7A to the shareholder or shareholder's associate because the amount repaid during income year 2014-15 in relation to the amalgamated loan is less than the minimum yearly repayment required.\n\nInterest received by the private company must be included in the income tax return for 2014-15.\n\nMinimum yearly repayment\n\n$1,148.00\n\nBenchmark interest rate\n\n5.95%\n\nOpening balance:\n\nDate: 30/06/2014\n\nBalance: $2,106.00\n\nDays: 365\n\nInterest: $125.31\n\nTotal repayments\n\n$0\n\nTotal interest\n\n$125.31\n\nTotal principal\n\n$0\n\nClosing balance\n\nDate: 30/06/2015\n\nBalance: $2,106.00",
  "outputs": {
    "enquiryRateFormatted": "5.95%",
    "enquiryYearEndMinusOneDisplay": "30/06/2014",
    "amalgamatedLoanNotPaidByEOIYFormatted": "$2,106.00",
    "openingBalancePayDays": "365",
    "openingBalanceInterestFormatted": "$125.31",
    "totalAmountOfRepaymentFormatted": "$0",
    "totalInterestFormatted": "$125.31",
    "principalFormatted": "$0",
    "enquiryYearEndDisplay": "30/06/2015",
    "minimumYearRepaymentFormatted": "$1,148.00"
  },
  "repayments": [],
  "inputs": {
    "incomeYearOfLoan": 2010,
    "fullTermOfAmalgamatedLoan": 6,
    "incomeYearOfEnquiring": 2015,
    "amalgamatedLoanNotPaidByEOIY": 2106,
    "repayments": null,
    "lodgement_date": null
  },
  "idx": 2949
}