{
  "id": "2023-09-05T18:59:18.521Z0.3507948972161621",
  "alert": "Start of result\nResult\n\nMinimum yearly repayment met.\n\nThe amount of the loan not repaid at the end of income year 2019-20 is $2.86.\n\nThe amalgamated loan will not be taken to be a dividend because the total repayments made are equal to or greater than the minimum yearly repayment required for income year 2019-20.\n\nInterest received by the private company must be included in the income tax return for 2019-20.\n\nMinimum yearly repayment\n\n$18.00\n\nBenchmark interest rate\n\n5.37%\n\nOpening balance:\n\nDate: 30/06/2019\n\nBalance: $92.23\n\nDays: 211\n\nInterest: $2.86\n\nPayments\n\nDate: 28/01/2020\n\nAmount: $92.23\n\nBalance: $0\n\nDays: 155\n\nInterest: $0\n\n\n\n\nTotal repayments\n\n$92.23\n\nTotal interest\n\n$2.86\n\nTotal principal\n\n$89.37\n\nClosing balance\n\nDate: 30/06/2020\n\nBalance: $2.86",
  "outputs": {
    "enquiryRateFormatted": "5.37%",
    "enquiryYearEndMinusOneDisplay": "30/06/2019",
    "amalgamatedLoanNotPaidByEOIYFormatted": "$92.23",
    "openingBalancePayDays": "211",
    "openingBalanceInterestFormatted": "$2.86",
    "totalAmountOfRepaymentFormatted": "$92.23",
    "totalInterestFormatted": "$2.86",
    "principalFormatted": "$89.37",
    "enquiryYearEndDisplay": "30/06/2020",
    "minimumYearRepaymentFormatted": "$18.00"
  },
  "repayments": [
    {
      "rd": "28/1/2020",
      "ra": 92.23611341572087
    }
  ],
  "inputs": {
    "incomeYearOfLoan": 2018,
    "fullTermOfAmalgamatedLoan": 7,
    "incomeYearOfEnquiring": 2020,
    "amalgamatedLoanNotPaidByEOIY": 92.2361134157211,
    "repayments": null,
    "lodgement_date": null
  },
  "idx": 741
}