{
  "id": "2023-10-31T20:41:06.236Z0.8696388053727191",
  "alert": "Start of result\nResult\n\nAmalgamated loan fully repaid.\n\nThe amalgamated loan has been paid in full.\u000bThe private company is not taken under Division 7A to pay a dividend to the shareholder or shareholder's associate.\n\nInterest received by the private company must be included in the income tax return for 2001-02.\n\nMinimum yearly repayment\n\n$22.00\n\nBenchmark interest rate\n\n6.8%\n\nOpening balance:\n\nDate: 30/06/2001\n\nBalance: $90.71\n\nDays: 318\n\nInterest: $5.37\n\nPayments\n\nDate: 15/05/2002\n\nAmount: $865.00\n\nBalance: $0\n\nDays: 47\n\nInterest: $0\n\n\n\n\nTotal repayments\n\n$865.00\n\nTotal interest\n\n$5.37\n\nTotal principal\n\n$859.63\n\nClosing balance\n\nDate: 30/06/2002\n\nBalance: $0",
  "outputs": {
    "enquiryRateFormatted": "6.8%",
    "enquiryYearEndMinusOneDisplay": "30/06/2001",
    "amalgamatedLoanNotPaidByEOIYFormatted": "$90.71",
    "openingBalancePayDays": "318",
    "openingBalanceInterestFormatted": "$5.37",
    "totalAmountOfRepaymentFormatted": "$865.00",
    "totalInterestFormatted": "$5.37",
    "principalFormatted": "$859.63",
    "enquiryYearEndDisplay": "30/06/2002",
    "minimumYearRepaymentFormatted": "$22.00",
    "loanAmountFormatted": "$0"
  },
  "repayments": [
    {
      "rd": "15/5/2002",
      "ra": 865
    }
  ],
  "inputs": {
    "incomeYearOfLoan": 2000,
    "fullTermOfAmalgamatedLoan": 6,
    "incomeYearOfEnquiring": 2002,
    "amalgamatedLoanNotPaidByEOIY": 90.71096010083315,
    "repayments": null,
    "lodgement_date": null
  },
  "idx": 6683
}