{
  "id": "2023-10-31T20:41:03.509Z0.2721895834421799",
  "alert": "Start of result\nResult\n\nMinimum yearly repayment not met.\n\nThe amount of the loan not repaid at the end of income year 2001-02 is $90.71.\n\nThe private company may be taken to pay a dividend under Division 7A to the shareholder or shareholder's associate because the amount repaid during income year 2001-02 in relation to the amalgamated loan is less than the minimum yearly repayment required.\n\nInterest received by the private company must be included in the income tax return for 2001-02.\n\nMinimum yearly repayment\n\n$22.00\n\nBenchmark interest rate\n\n6.8%\n\nOpening balance:\n\nDate: 30/06/2001\n\nBalance: $90.71\n\nDays: 365\n\nInterest: $6.17\n\nTotal repayments\n\n$0\n\nTotal interest\n\n$6.17\n\nTotal principal\n\n$0\n\nClosing balance\n\nDate: 30/06/2002\n\nBalance: $90.71",
  "outputs": {
    "enquiryRateFormatted": "6.8%",
    "enquiryYearEndMinusOneDisplay": "30/06/2001",
    "amalgamatedLoanNotPaidByEOIYFormatted": "$90.71",
    "openingBalancePayDays": "365",
    "openingBalanceInterestFormatted": "$6.17",
    "totalAmountOfRepaymentFormatted": "$0",
    "totalInterestFormatted": "$6.17",
    "principalFormatted": "$0",
    "enquiryYearEndDisplay": "30/06/2002",
    "minimumYearRepaymentFormatted": "$22.00",
    "loanAmountFormatted": "$90.71"
  },
  "repayments": [],
  "inputs": {
    "incomeYearOfLoan": 2000,
    "fullTermOfAmalgamatedLoan": 6,
    "incomeYearOfEnquiring": 2002,
    "amalgamatedLoanNotPaidByEOIY": 90.71096010083315,
    "repayments": null,
    "lodgement_date": null
  },
  "idx": 6682
}