{
  "id": "2023-10-31T17:20:02.732Z0.4238342052977314",
  "alert": "Start of result\nResult\n\nMinimum yearly repayment not met.\n\nThe amount of the loan not repaid at the end of income year 2021-22 is $7.21.\n\nThe private company may be taken to pay a dividend under Division 7A to the shareholder or shareholder's associate because the amount repaid during income year 2021-22 in relation to the amalgamated loan is less than the minimum yearly repayment required.\n\nInterest received by the private company must be included in the income tax return for 2021-22.\n\nMinimum yearly repayment\n\n$4.00\n\nBenchmark interest rate\n\n4.52%\n\nOpening balance:\n\nDate: 30/06/2021\n\nBalance: $7.21\n\nDays: 365\n\nInterest: $0.33\n\nTotal repayments\n\n$0\n\nTotal interest\n\n$0.33\n\nTotal principal\n\n$0\n\nClosing balance\n\nDate: 30/06/2022\n\nBalance: $7.21",
  "outputs": {
    "enquiryRateFormatted": "4.52%",
    "enquiryYearEndMinusOneDisplay": "30/06/2021",
    "amalgamatedLoanNotPaidByEOIYFormatted": "$7.21",
    "openingBalancePayDays": "365",
    "openingBalanceInterestFormatted": "$0.33",
    "totalAmountOfRepaymentFormatted": "$0",
    "totalInterestFormatted": "$0.33",
    "principalFormatted": "$0",
    "enquiryYearEndDisplay": "30/06/2022",
    "minimumYearRepaymentFormatted": "$4.00",
    "loanAmountFormatted": "$7.21"
  },
  "repayments": [],
  "inputs": {
    "incomeYearOfLoan": 2019,
    "fullTermOfAmalgamatedLoan": 4,
    "incomeYearOfEnquiring": 2022,
    "amalgamatedLoanNotPaidByEOIY": 7.21308012867211,
    "repayments": null,
    "lodgement_date": null
  },
  "idx": 1096
}