{
  "id": "2023-10-31T18:55:36.601Z0.533417245456452",
  "alert": "Start of result\nResult\n\nAmalgamated loan fully repaid.\n\nThe amalgamated loan has been paid in full.\u000bThe private company is not taken under Division 7A to pay a dividend to the shareholder or shareholder's associate.\n\nInterest received by the private company must be included in the income tax return for 2011-12.\n\nMinimum yearly repayment\n\n$10.00\n\nBenchmark interest rate\n\n7.8%\n\nOpening balance:\n\nDate: 30/06/2011\n\nBalance: $26.28\n\nDays: 77\n\nInterest: $0.43\n\nPayments\n\nDate: 16/09/2011\n\nAmount: $262.87\n\nBalance: $0\n\nDays: 289\n\nInterest: $0\n\n\n\n\nTotal repayments\n\n$262.87\n\nTotal interest\n\n$0.43\n\nTotal principal\n\n$262.44\n\nClosing balance\n\nDate: 30/06/2012\n\nBalance: $0",
  "outputs": {
    "enquiryRateFormatted": "7.8%",
    "enquiryYearEndMinusOneDisplay": "30/06/2011",
    "amalgamatedLoanNotPaidByEOIYFormatted": "$26.28",
    "openingBalancePayDays": "77",
    "openingBalanceInterestFormatted": "$0.43",
    "totalAmountOfRepaymentFormatted": "$262.87",
    "totalInterestFormatted": "$0.43",
    "principalFormatted": "$262.44",
    "enquiryYearEndDisplay": "30/06/2012",
    "minimumYearRepaymentFormatted": "$10.00",
    "loanAmountFormatted": "$0"
  },
  "repayments": [
    {
      "rd": "16/9/2011",
      "ra": 262.8796746062617
    }
  ],
  "inputs": {
    "incomeYearOfLoan": 2007,
    "fullTermOfAmalgamatedLoan": 7,
    "incomeYearOfEnquiring": 2012,
    "amalgamatedLoanNotPaidByEOIY": 26.287967460626156,
    "repayments": null,
    "lodgement_date": null
  },
  "idx": 4759
}