{
  "id": "2023-10-31T20:19:24.232Z0.24558290389739457",
  "alert": "Start of result\nResult\n\nMinimum yearly repayment not met.\n\nThe amount of the loan not repaid at the end of income year 2006-07 is $51.90.\n\nThe private company may be taken to pay a dividend under Division 7A to the shareholder or shareholder's associate because the amount repaid during income year 2006-07 in relation to the amalgamated loan is less than the minimum yearly repayment required.\n\nInterest received by the private company must be included in the income tax return for 2006-07.\n\nMinimum yearly repayment\n\n$56.00\n\nBenchmark interest rate\n\n7.55%\n\nOpening balance:\n\nDate: 30/06/2006\n\nBalance: $51.90\n\nDays: 365\n\nInterest: $3.92\n\nTotal repayments\n\n$0\n\nTotal interest\n\n$3.92\n\nTotal principal\n\n$0\n\nClosing balance\n\nDate: 30/06/2007\n\nBalance: $51.90",
  "outputs": {
    "enquiryRateFormatted": "7.55%",
    "enquiryYearEndMinusOneDisplay": "30/06/2006",
    "amalgamatedLoanNotPaidByEOIYFormatted": "$51.90",
    "openingBalancePayDays": "365",
    "openingBalanceInterestFormatted": "$3.92",
    "totalAmountOfRepaymentFormatted": "$0",
    "totalInterestFormatted": "$3.92",
    "principalFormatted": "$0",
    "enquiryYearEndDisplay": "30/06/2007",
    "minimumYearRepaymentFormatted": "$56.00",
    "loanAmountFormatted": "$51.90"
  },
  "repayments": [],
  "inputs": {
    "incomeYearOfLoan": 2001,
    "fullTermOfAmalgamatedLoan": 6,
    "incomeYearOfEnquiring": 2007,
    "amalgamatedLoanNotPaidByEOIY": 51.90379115838271,
    "repayments": null,
    "lodgement_date": null
  },
  "idx": 6370
}