{
  "id": "2023-10-31T17:24:06.831Z0.6849227965248359",
  "alert": "Start of result\nResult\n\nAmalgamated loan fully repaid.\n\nThe amalgamated loan has been paid in full.\u000bThe private company is not taken under Division 7A to pay a dividend to the shareholder or shareholder's associate.\n\nInterest received by the private company must be included in the income tax return for 2021-22.\n\nMinimum yearly repayment\n\n$9,027.00\n\nBenchmark interest rate\n\n4.52%\n\nOpening balance:\n\nDate: 30/06/2021\n\nBalance: $8,637.00\n\nDays: 48\n\nInterest: $51.34\n\nPayments\n\nDate: 18/08/2021\n\nAmount: $7,126.00\n\nBalance: $1,511.00\n\nDays: 74\n\nInterest: $13.85\n\n\n\n\nDate: 31/10/2021\n\nAmount: $8,374.00\n\nBalance: $0\n\nDays: 243\n\nInterest: $0\n\n\n\n\nTotal repayments\n\n$15,500.00\n\nTotal interest\n\n$65.19\n\nTotal principal\n\n$15,434.81\n\nClosing balance\n\nDate: 30/06/2022\n\nBalance: $0",
  "outputs": {
    "enquiryRateFormatted": "4.52%",
    "enquiryYearEndMinusOneDisplay": "30/06/2021",
    "amalgamatedLoanNotPaidByEOIYFormatted": "$8,637.00",
    "openingBalancePayDays": "48",
    "openingBalanceInterestFormatted": "$51.34",
    "totalAmountOfRepaymentFormatted": "$15,500.00",
    "totalInterestFormatted": "$65.19",
    "principalFormatted": "$15,434.81",
    "enquiryYearEndDisplay": "30/06/2022",
    "minimumYearRepaymentFormatted": "$9,027.00",
    "loanAmountFormatted": "$0"
  },
  "repayments": [
    {
      "rd": "18/8/2021",
      "ra": 7126
    },
    {
      "rd": "31/10/2021",
      "ra": 8374
    }
  ],
  "inputs": {
    "incomeYearOfLoan": 2018,
    "fullTermOfAmalgamatedLoan": 4,
    "incomeYearOfEnquiring": 2022,
    "amalgamatedLoanNotPaidByEOIY": 8637,
    "repayments": null,
    "lodgement_date": null
  },
  "idx": 1356
}