{
  "id": "2023-10-31T18:20:38.361Z0.1799738368360082",
  "alert": "Start of result\nResult\n\nMinimum yearly repayment met.\n\nThe amount of the loan not repaid at the end of income year 2012-13 is $3,669.06.\n\n\u000b\n\nThe amalgamated loan will not be taken to be a dividend because the total repayments made are equal to or greater than the minimum yearly repayment required for income year 2012-13.\n\nInterest received by the private company must be included in the income tax return for 2012-13.\n\nMinimum yearly repayment\n\n$5,384.00\n\nBenchmark interest rate\n\n7.05%\n\nOpening balance:\n\nDate: 30/06/2012\n\nBalance: $9,728.00\n\nDays: 175\n\nInterest: $328.82\n\nPayments\n\nDate: 23/12/2012\n\nAmount: $6,506.00\n\nBalance: $3,222.00\n\nDays: 190\n\nInterest: $118.24\n\n\n\n\nTotal repayments\n\n$6,506.00\n\nTotal interest\n\n$447.06\n\nTotal principal\n\n$6,058.94\n\nClosing balance\n\nDate: 30/06/2013\n\nBalance: $3,669.06",
  "outputs": {
    "enquiryRateFormatted": "7.05%",
    "enquiryYearEndMinusOneDisplay": "30/06/2012",
    "amalgamatedLoanNotPaidByEOIYFormatted": "$9,728.00",
    "openingBalancePayDays": "175",
    "openingBalanceInterestFormatted": "$328.82",
    "totalAmountOfRepaymentFormatted": "$6,506.00",
    "totalInterestFormatted": "$447.06",
    "principalFormatted": "$6,058.94",
    "enquiryYearEndDisplay": "30/06/2013",
    "minimumYearRepaymentFormatted": "$5,384.00",
    "loanAmountFormatted": "$3,669.06"
  },
  "repayments": [
    {
      "rd": "23/12/2012",
      "ra": 6506
    }
  ],
  "inputs": {
    "incomeYearOfLoan": 2010,
    "fullTermOfAmalgamatedLoan": 4,
    "incomeYearOfEnquiring": 2013,
    "amalgamatedLoanNotPaidByEOIY": 9728,
    "repayments": null,
    "lodgement_date": null
  },
  "idx": 3812
}