{
  "id": "2023-10-31T17:21:23.973Z0.6606267378586717",
  "alert": "Start of result\nResult\n\nMinimum yearly repayment not met.\n\nThe amount of the loan not repaid at the end of income year 2021-22 is $10,106.00.\n\nThe private company may be taken to pay a dividend under Division 7A to the shareholder or shareholder's associate because the amount repaid during income year 2021-22 in relation to the amalgamated loan is less than the minimum yearly repayment required.\n\nInterest received by the private company must be included in the income tax return for 2021-22.\n\nMinimum yearly repayment\n\n$2,818.00\n\nBenchmark interest rate\n\n4.52%\n\nOpening balance:\n\nDate: 30/06/2021\n\nBalance: $10,106.00\n\nDays: 365\n\nInterest: $456.79\n\nTotal repayments\n\n$0\n\nTotal interest\n\n$456.79\n\nTotal principal\n\n$0\n\nClosing balance\n\nDate: 30/06/2022\n\nBalance: $10,106.00",
  "outputs": {
    "enquiryRateFormatted": "4.52%",
    "enquiryYearEndMinusOneDisplay": "30/06/2021",
    "amalgamatedLoanNotPaidByEOIYFormatted": "$10,106.00",
    "openingBalancePayDays": "365",
    "openingBalanceInterestFormatted": "$456.79",
    "totalAmountOfRepaymentFormatted": "$0",
    "totalInterestFormatted": "$456.79",
    "principalFormatted": "$0",
    "enquiryYearEndDisplay": "30/06/2022",
    "minimumYearRepaymentFormatted": "$2,818.00",
    "loanAmountFormatted": "$10,106.00"
  },
  "repayments": [],
  "inputs": {
    "incomeYearOfLoan": 2019,
    "fullTermOfAmalgamatedLoan": 6,
    "incomeYearOfEnquiring": 2022,
    "amalgamatedLoanNotPaidByEOIY": 10106,
    "repayments": null,
    "lodgement_date": null
  },
  "idx": 1185
}