{
  "id": "2023-09-06T00:14:22.975Z0.3272416176200772",
  "alert": "Start of result\nResult\n\nMinimum yearly repayment met.\n\nThe amount of the loan not repaid at the end of income year 2018-19 is $866.72.\n\nThe amalgamated loan will not be taken to be a dividend because the total repayments made are equal to or greater than the minimum yearly repayment required for income year 2018-19.\n\nInterest received by the private company must be included in the income tax return for 2018-19.\n\nMinimum yearly repayment\n\n$2,679.00\n\nBenchmark interest rate\n\n5.2%\n\nOpening balance:\n\nDate: 30/06/2018\n\nBalance: $9,455.00\n\nDays: 194\n\nInterest: $261.32\n\nPayments\n\nDate: 11/01/2019\n\nAmount: $8,864.00\n\nBalance: $591.00\n\nDays: 171\n\nInterest: $14.40\n\n\n\n\nTotal repayments\n\n$8,864.00\n\nTotal interest\n\n$275.72\n\nTotal principal\n\n$8,588.28\n\nClosing balance\n\nDate: 30/06/2019\n\nBalance: $866.72",
  "outputs": {
    "enquiryRateFormatted": "5.2%",
    "enquiryYearEndMinusOneDisplay": "30/06/2018",
    "amalgamatedLoanNotPaidByEOIYFormatted": "$9,455.00",
    "openingBalancePayDays": "194",
    "openingBalanceInterestFormatted": "$261.32",
    "totalAmountOfRepaymentFormatted": "$8,864.00",
    "totalInterestFormatted": "$275.72",
    "principalFormatted": "$8,588.28",
    "enquiryYearEndDisplay": "30/06/2019",
    "minimumYearRepaymentFormatted": "$2,679.00"
  },
  "repayments": [
    {
      "rd": "11/1/2019",
      "ra": 8864
    }
  ],
  "inputs": {
    "incomeYearOfLoan": 2015,
    "fullTermOfAmalgamatedLoan": 7,
    "incomeYearOfEnquiring": 2019,
    "amalgamatedLoanNotPaidByEOIY": 9455,
    "repayments": null,
    "lodgement_date": null
  },
  "idx": 2229
}