{
  "id": "2023-09-04T22:08:12.261Z0.7990688051514139",
  "alert": "Start of result\nResult\n\nMinimum yearly repayment not met.\n\nThe amount of the loan not repaid at the end of income year 2008-09 is $6,713.66.\n\nThe private company may be taken to pay a dividend under Division 7A to the shareholder or shareholder's associate because the amount repaid during income year 2008-09 in relation to the amalgamated loan is less than the minimum yearly repayment required.\n\nInterest received by the private company must be included in the income tax return for 2008-09.\n\nMinimum yearly repayment\n\n$4,552.00\n\nBenchmark interest rate\n\n9.45%\n\nOpening balance:\n\nDate: 30/06/2008\n\nBalance: $7,958.00\n\nDays: 0\n\nInterest: $0\n\nPayments\n\nDate: 01/07/2008\n\nAmount: $1,824.00\n\nBalance: $6,134.00\n\nDays: 365\n\nInterest: $579.66\n\n\n\n\nTotal repayments\n\n$1,824.00\n\nTotal interest\n\n$579.66\n\nTotal principal\n\n$1,244.34\n\nClosing balance\n\nDate: 30/06/2009\n\nBalance: $6,713.66",
  "outputs": {
    "enquiryRateFormatted": "9.45%",
    "enquiryYearEndMinusOneDisplay": "30/06/2008",
    "amalgamatedLoanNotPaidByEOIYFormatted": "$7,958.00",
    "openingBalancePayDays": "0",
    "openingBalanceInterestFormatted": "$0",
    "totalAmountOfRepaymentFormatted": "$1,824.00",
    "totalInterestFormatted": "$579.66",
    "principalFormatted": "$1,244.34",
    "enquiryYearEndDisplay": "30/06/2009",
    "minimumYearRepaymentFormatted": "$4,552.00"
  },
  "repayments": [
    {
      "rd": "1/7/2008",
      "ra": 1824
    }
  ],
  "inputs": {
    "incomeYearOfLoan": 2003,
    "fullTermOfAmalgamatedLoan": 7,
    "incomeYearOfEnquiring": 2009,
    "amalgamatedLoanNotPaidByEOIY": 7958,
    "repayments": null,
    "lodgement_date": null
  },
  "idx": 292
}