{
  "id": "2023-09-06T02:30:07.110Z0.8345041511829807",
  "alert": "Start of result\nResult\n\nMinimum yearly repayment not met.\n\nThe amount of the loan not repaid at the end of income year 2013-14 is $0.96.\n\nThe private company may be taken to pay a dividend under Division 7A to the shareholder or shareholder's associate because the amount repaid during income year 2013-14 in relation to the amalgamated loan is less than the minimum yearly repayment required.\n\nInterest received by the private company must be included in the income tax return for 2013-14.\n\nMinimum yearly repayment\n\n$64.00\n\nBenchmark interest rate\n\n6.2%\n\nOpening balance:\n\nDate: 30/06/2013\n\nBalance: $60.11\n\nDays: 94\n\nInterest: $0.96\n\nPayments\n\nDate: 03/10/2013\n\nAmount: $60.11\n\nBalance: $0\n\nDays: 271\n\nInterest: $0\n\n\n\n\nTotal repayments\n\n$60.11\n\nTotal interest\n\n$0.96\n\nTotal principal\n\n$59.15\n\nClosing balance\n\nDate: 30/06/2014\n\nBalance: $0.96",
  "outputs": {
    "enquiryRateFormatted": "6.2%",
    "enquiryYearEndMinusOneDisplay": "30/06/2013",
    "amalgamatedLoanNotPaidByEOIYFormatted": "$60.11",
    "openingBalancePayDays": "94",
    "openingBalanceInterestFormatted": "$0.96",
    "totalAmountOfRepaymentFormatted": "$60.11",
    "totalInterestFormatted": "$0.96",
    "principalFormatted": "$59.15",
    "enquiryYearEndDisplay": "30/06/2014",
    "minimumYearRepaymentFormatted": "$64.00"
  },
  "repayments": [
    {
      "rd": "3/10/2013",
      "ra": 60.11548864670294
    }
  ],
  "inputs": {
    "incomeYearOfLoan": 2013,
    "fullTermOfAmalgamatedLoan": 1,
    "incomeYearOfEnquiring": 2014,
    "amalgamatedLoanNotPaidByEOIY": 60.11548864670307,
    "repayments": null,
    "lodgement_date": "3/8/2013"
  },
  "idx": 399
}