{
  "id": "2023-10-31T18:04:57.938Z0.3034253392199704",
  "alert": "Start of result\nResult\n\nMinimum yearly repayment not met.\n\nThe amount of the loan not repaid at the end of income year 2014-15 is $99.67.\n\nThe private company may be taken to pay a dividend under Division 7A to the shareholder or shareholder's associate because the amount repaid during income year 2014-15 in relation to the amalgamated loan is less than the minimum yearly repayment required.\n\nInterest received by the private company must be included in the income tax return for 2014-15.\n\nMinimum yearly repayment\n\n$29.00\n\nBenchmark interest rate\n\n5.95%\n\nOpening balance:\n\nDate: 30/06/2014\n\nBalance: $99.67\n\nDays: 365\n\nInterest: $5.93\n\nTotal repayments\n\n$0\n\nTotal interest\n\n$5.93\n\nTotal principal\n\n$0\n\nClosing balance\n\nDate: 30/06/2015\n\nBalance: $99.67",
  "outputs": {
    "enquiryRateFormatted": "5.95%",
    "enquiryYearEndMinusOneDisplay": "30/06/2014",
    "amalgamatedLoanNotPaidByEOIYFormatted": "$99.67",
    "openingBalancePayDays": "365",
    "openingBalanceInterestFormatted": "$5.93",
    "totalAmountOfRepaymentFormatted": "$0",
    "totalInterestFormatted": "$5.93",
    "principalFormatted": "$0",
    "enquiryYearEndDisplay": "30/06/2015",
    "minimumYearRepaymentFormatted": "$29.00",
    "loanAmountFormatted": "$99.67"
  },
  "repayments": [],
  "inputs": {
    "incomeYearOfLoan": 2012,
    "fullTermOfAmalgamatedLoan": 6,
    "incomeYearOfEnquiring": 2015,
    "amalgamatedLoanNotPaidByEOIY": 99.67194292626418,
    "repayments": null,
    "lodgement_date": null
  },
  "idx": 3271
}