{
  "id": "2023-10-31T17:56:44.048Z0.8060420598442145",
  "alert": "Start of result\nResult\n\nMinimum yearly repayment not met.\n\nThe amount of the loan not repaid at the end of income year 2016-17 is $5,846.00.\n\nThe private company may be taken to pay a dividend under Division 7A to the shareholder or shareholder's associate because the amount repaid during income year 2016-17 in relation to the amalgamated loan is less than the minimum yearly repayment required.\n\nInterest received by the private company must be included in the income tax return for 2016-17.\n\nMinimum yearly repayment\n\n$3,162.00\n\nBenchmark interest rate\n\n5.4%\n\nOpening balance:\n\nDate: 30/06/2016\n\nBalance: $5,846.00\n\nDays: 365\n\nInterest: $315.68\n\nTotal repayments\n\n$0\n\nTotal interest\n\n$315.68\n\nTotal principal\n\n$0\n\nClosing balance\n\nDate: 30/06/2017\n\nBalance: $5,846.00",
  "outputs": {
    "enquiryRateFormatted": "5.4%",
    "enquiryYearEndMinusOneDisplay": "30/06/2016",
    "amalgamatedLoanNotPaidByEOIYFormatted": "$5,846.00",
    "openingBalancePayDays": "365",
    "openingBalanceInterestFormatted": "$315.68",
    "totalAmountOfRepaymentFormatted": "$0",
    "totalInterestFormatted": "$315.68",
    "principalFormatted": "$0",
    "enquiryYearEndDisplay": "30/06/2017",
    "minimumYearRepaymentFormatted": "$3,162.00",
    "loanAmountFormatted": "$5,846.00"
  },
  "repayments": [],
  "inputs": {
    "incomeYearOfLoan": 2013,
    "fullTermOfAmalgamatedLoan": 5,
    "incomeYearOfEnquiring": 2017,
    "amalgamatedLoanNotPaidByEOIY": 5846,
    "repayments": null,
    "lodgement_date": null
  },
  "idx": 2965
}