{
  "id": "2023-10-31T18:20:31.875Z0.9486907633307253",
  "alert": "Start of result\nResult\n\nAmalgamated loan fully repaid.\n\nThe amalgamated loan has been paid in full.\u000bThe private company is not taken under Division 7A to pay a dividend to the shareholder or shareholder's associate.\n\nInterest received by the private company must be included in the income tax return for 2013-14.\n\nMinimum yearly repayment\n\n$9,266.00\n\nBenchmark interest rate\n\n6.2%\n\nOpening balance:\n\nDate: 30/06/2013\n\nBalance: $8,725.00\n\nDays: 269\n\nInterest: $398.67\n\nPayments\n\nDate: 27/03/2014\n\nAmount: $8,585.00\n\nBalance: $140.00\n\nDays: 18\n\nInterest: $0.43\n\n\n\n\nDate: 14/04/2014\n\nAmount: $955.00\n\nBalance: $0\n\nDays: 78\n\nInterest: $0\n\n\n\n\nTotal repayments\n\n$9,540.00\n\nTotal interest\n\n$399.10\n\nTotal principal\n\n$9,140.90\n\nClosing balance\n\nDate: 30/06/2014\n\nBalance: $0",
  "outputs": {
    "enquiryRateFormatted": "6.2%",
    "enquiryYearEndMinusOneDisplay": "30/06/2013",
    "amalgamatedLoanNotPaidByEOIYFormatted": "$8,725.00",
    "openingBalancePayDays": "269",
    "openingBalanceInterestFormatted": "$398.67",
    "totalAmountOfRepaymentFormatted": "$9,540.00",
    "totalInterestFormatted": "$399.10",
    "principalFormatted": "$9,140.90",
    "enquiryYearEndDisplay": "30/06/2014",
    "minimumYearRepaymentFormatted": "$9,266.00",
    "loanAmountFormatted": "$0"
  },
  "repayments": [
    {
      "rd": "27/3/2014",
      "ra": 8585
    },
    {
      "rd": "14/4/2014",
      "ra": 955
    }
  ],
  "inputs": {
    "incomeYearOfLoan": 2010,
    "fullTermOfAmalgamatedLoan": 4,
    "incomeYearOfEnquiring": 2014,
    "amalgamatedLoanNotPaidByEOIY": 8725,
    "repayments": null,
    "lodgement_date": null
  },
  "idx": 3810
}