{
  "id": "2023-09-06T01:36:26.111Z0.11890247683939315",
  "alert": "Start of result\nResult\n\nMinimum yearly repayment not met.\n\nThe amount of the loan not repaid at the end of income year 2019-20 is $41.55.\n\nThe private company may be taken to pay a dividend under Division 7A to the shareholder or shareholder's associate because the amount repaid during income year 2019-20 in relation to the amalgamated loan is less than the minimum yearly repayment required.\n\nInterest received by the private company must be included in the income tax return for 2019-20.\n\nMinimum yearly repayment\n\n$44.00\n\nBenchmark interest rate\n\n5.37%\n\nOpening balance:\n\nDate: 30/06/2019\n\nBalance: $41.55\n\nDays: 366\n\nInterest: $2.23\n\nTotal repayments\n\n$0\n\nTotal interest\n\n$2.23\n\nTotal principal\n\n$0\n\nClosing balance\n\nDate: 30/06/2020\n\nBalance: $41.55",
  "outputs": {
    "enquiryRateFormatted": "5.37%",
    "enquiryYearEndMinusOneDisplay": "30/06/2019",
    "amalgamatedLoanNotPaidByEOIYFormatted": "$41.55",
    "openingBalancePayDays": "366",
    "openingBalanceInterestFormatted": "$2.23",
    "totalAmountOfRepaymentFormatted": "$0",
    "totalInterestFormatted": "$2.23",
    "principalFormatted": "$0",
    "enquiryYearEndDisplay": "30/06/2020",
    "minimumYearRepaymentFormatted": "$44.00"
  },
  "repayments": [],
  "inputs": {
    "incomeYearOfLoan": 2014,
    "fullTermOfAmalgamatedLoan": 6,
    "incomeYearOfEnquiring": 2020,
    "amalgamatedLoanNotPaidByEOIY": 41.550051961051516,
    "repayments": null,
    "lodgement_date": null
  },
  "idx": 7014
}