{
  "id": "2023-09-06T21:45:17.761Z0.32448816987737605",
  "alert": "Start of result\nResult\n\nMinimum yearly repayment not met.\n\nThe amount of the loan not repaid at the end of income year 2008-09 is $134.01.\n\nThe private company may be taken to pay a dividend under Division 7A to the shareholder or shareholder's associate because the amount repaid during income year 2008-09 in relation to the amalgamated loan is less than the minimum yearly repayment required.\n\nInterest received by the private company must be included in the income tax return for 2008-09.\n\nMinimum yearly repayment\n\n$7,081.00\n\nBenchmark interest rate\n\n9.45%\n\nOpening balance:\n\nDate: 30/06/2008\n\nBalance: $6,470.00\n\nDays: 80\n\nInterest: $134.01\n\nPayments\n\nDate: 19/09/2008\n\nAmount: $6,470.00\n\nBalance: $0\n\nDays: 285\n\nInterest: $0\n\n\n\n\nTotal repayments\n\n$6,470.00\n\nTotal interest\n\n$134.01\n\nTotal principal\n\n$6,335.99\n\nClosing balance\n\nDate: 30/06/2009\n\nBalance: $134.01",
  "outputs": {
    "enquiryRateFormatted": "9.45%",
    "enquiryYearEndMinusOneDisplay": "30/06/2008",
    "amalgamatedLoanNotPaidByEOIYFormatted": "$6,470.00",
    "openingBalancePayDays": "80",
    "openingBalanceInterestFormatted": "$134.01",
    "totalAmountOfRepaymentFormatted": "$6,470.00",
    "totalInterestFormatted": "$134.01",
    "principalFormatted": "$6,335.99",
    "enquiryYearEndDisplay": "30/06/2009",
    "minimumYearRepaymentFormatted": "$7,081.00"
  },
  "repayments": [
    {
      "rd": "19/9/2008",
      "ra": 6470
    }
  ],
  "inputs": {
    "incomeYearOfLoan": 2002,
    "fullTermOfAmalgamatedLoan": 7,
    "incomeYearOfEnquiring": 2009,
    "amalgamatedLoanNotPaidByEOIY": 6470,
    "repayments": null,
    "lodgement_date": null
  },
  "idx": 6653
}