{
  "id": "2023-10-31T18:39:50.335Z0.6056422524999499",
  "alert": "Start of result\nResult\n\nMinimum yearly repayment not met.\n\nThe amount of the loan not repaid at the end of income year 2008-09 is $26.41.\n\nThe private company may be taken to pay a dividend under Division 7A to the shareholder or shareholder's associate because the amount repaid during income year 2008-09 in relation to the amalgamated loan is less than the minimum yearly repayment required.\n\nInterest received by the private company must be included in the income tax return for 2008-09.\n\nMinimum yearly repayment\n\n$7.00\n\nBenchmark interest rate\n\n9.45%\n\nOpening balance:\n\nDate: 30/06/2008\n\nBalance: $26.41\n\nDays: 365\n\nInterest: $2.50\n\nTotal repayments\n\n$0\n\nTotal interest\n\n$2.50\n\nTotal principal\n\n$0\n\nClosing balance\n\nDate: 30/06/2009\n\nBalance: $26.41",
  "outputs": {
    "enquiryRateFormatted": "9.45%",
    "enquiryYearEndMinusOneDisplay": "30/06/2008",
    "amalgamatedLoanNotPaidByEOIYFormatted": "$26.41",
    "openingBalancePayDays": "365",
    "openingBalanceInterestFormatted": "$2.50",
    "totalAmountOfRepaymentFormatted": "$0",
    "totalInterestFormatted": "$2.50",
    "principalFormatted": "$0",
    "enquiryYearEndDisplay": "30/06/2009",
    "minimumYearRepaymentFormatted": "$7.00",
    "loanAmountFormatted": "$26.41"
  },
  "repayments": [],
  "inputs": {
    "incomeYearOfLoan": 2008,
    "fullTermOfAmalgamatedLoan": 5,
    "incomeYearOfEnquiring": 2009,
    "amalgamatedLoanNotPaidByEOIY": 26.41194455754984,
    "repayments": null,
    "lodgement_date": "1/7/2008"
  },
  "idx": 4347
}