{
  "id": "2023-10-31T20:14:53.811Z0.8429248884437986",
  "alert": "Start of result\nResult\n\nMinimum yearly repayment met.\n\nThe amount of the loan not repaid at the end of income year 2002-03 is $1,539.34.\n\n\u000b\n\nThe amalgamated loan will not be taken to be a dividend because the total repayments made are equal to or greater than the minimum yearly repayment required for income year 2002-03.\n\nInterest received by the private company must be included in the income tax return for 2002-03.\n\nMinimum yearly repayment\n\n$3,152.00\n\nBenchmark interest rate\n\n6.3%\n\nOpening balance:\n\nDate: 30/06/2002\n\nBalance: $8,379.00\n\nDays: 128\n\nInterest: $185.12\n\nPayments\n\nDate: 06/11/2002\n\nAmount: $7,078.00\n\nBalance: $1,301.00\n\nDays: 237\n\nInterest: $53.22\n\n\n\n\nTotal repayments\n\n$7,078.00\n\nTotal interest\n\n$238.34\n\nTotal principal\n\n$6,839.66\n\nClosing balance\n\nDate: 30/06/2003\n\nBalance: $1,539.34",
  "outputs": {
    "enquiryRateFormatted": "6.3%",
    "enquiryYearEndMinusOneDisplay": "30/06/2002",
    "amalgamatedLoanNotPaidByEOIYFormatted": "$8,379.00",
    "openingBalancePayDays": "128",
    "openingBalanceInterestFormatted": "$185.12",
    "totalAmountOfRepaymentFormatted": "$7,078.00",
    "totalInterestFormatted": "$238.34",
    "principalFormatted": "$6,839.66",
    "enquiryYearEndDisplay": "30/06/2003",
    "minimumYearRepaymentFormatted": "$3,152.00",
    "loanAmountFormatted": "$1,539.34"
  },
  "repayments": [
    {
      "rd": "6/11/2002",
      "ra": 7078
    }
  ],
  "inputs": {
    "incomeYearOfLoan": 2001,
    "fullTermOfAmalgamatedLoan": 4,
    "incomeYearOfEnquiring": 2003,
    "amalgamatedLoanNotPaidByEOIY": 8379,
    "repayments": null,
    "lodgement_date": null
  },
  "idx": 6304
}