{
  "id": "2023-11-01T00:34:36.327Z0.6323012779764531",
  "alert": "Start of result\nResult\n\nAmalgamated loan fully repaid.\n\nThe amalgamated loan has been paid in full.\u000bThe private company is not taken under Division 7A to pay a dividend to the shareholder or shareholder's associate.\n\nInterest received by the private company must be included in the income tax return for 1999-00.\n\nMinimum yearly repayment\n\n$11.00\n\nBenchmark interest rate\n\n6.5%\n\nOpening balance:\n\nDate: 30/06/1999\n\nBalance: $38.09\n\nDays: 85\n\nInterest: $0.57\n\nPayments\n\nDate: 24/09/1999\n\nAmount: $380.93\n\nBalance: $0\n\nDays: 281\n\nInterest: $0\n\n\n\n\nTotal repayments\n\n$380.93\n\nTotal interest\n\n$0.57\n\nTotal principal\n\n$380.36\n\nClosing balance\n\nDate: 30/06/2000\n\nBalance: $0",
  "outputs": {
    "enquiryRateFormatted": "6.5%",
    "enquiryYearEndMinusOneDisplay": "30/06/1999",
    "amalgamatedLoanNotPaidByEOIYFormatted": "$38.09",
    "openingBalancePayDays": "85",
    "openingBalanceInterestFormatted": "$0.57",
    "totalAmountOfRepaymentFormatted": "$380.93",
    "totalInterestFormatted": "$0.57",
    "principalFormatted": "$380.36",
    "enquiryYearEndDisplay": "30/06/2000",
    "minimumYearRepaymentFormatted": "$11.00",
    "loanAmountFormatted": "$0"
  },
  "repayments": [
    {
      "rd": "24/9/1999",
      "ra": 380.93250075579624
    }
  ],
  "inputs": {
    "incomeYearOfLoan": 1998,
    "fullTermOfAmalgamatedLoan": 5,
    "incomeYearOfEnquiring": 2000,
    "amalgamatedLoanNotPaidByEOIY": 38.093250075579626,
    "repayments": null,
    "lodgement_date": null
  },
  "idx": 1
}