{
  "id": "2023-09-04T16:43:35.942Z0.14608668394971258",
  "alert": "Start of result\nResult\n\nMinimum yearly repayment not met.\n\nThe amount of the loan not repaid at the end of income year 2019-20 is $659.62.\n\nThe private company may be taken to pay a dividend under Division 7A to the shareholder or shareholder's associate because the amount repaid during income year 2019-20 in relation to the amalgamated loan is less than the minimum yearly repayment required.\n\nInterest received by the private company must be included in the income tax return for 2019-20.\n\nMinimum yearly repayment\n\n$9,984.00\n\nBenchmark interest rate\n\n5.37%\n\nOpening balance:\n\nDate: 30/06/2019\n\nBalance: $9,475.00\n\nDays: 0\n\nInterest: $0\n\nPayments\n\nDate: 01/07/2019\n\nAmount: $8,849.00\n\nBalance: $626.00\n\nDays: 366\n\nInterest: $33.62\n\n\n\n\nTotal repayments\n\n$8,849.00\n\nTotal interest\n\n$33.62\n\nTotal principal\n\n$8,815.38\n\nClosing balance\n\nDate: 30/06/2020\n\nBalance: $659.62",
  "outputs": {
    "enquiryRateFormatted": "5.37%",
    "enquiryYearEndMinusOneDisplay": "30/06/2019",
    "amalgamatedLoanNotPaidByEOIYFormatted": "$9,475.00",
    "openingBalancePayDays": "0",
    "openingBalanceInterestFormatted": "$0",
    "totalAmountOfRepaymentFormatted": "$8,849.00",
    "totalInterestFormatted": "$33.62",
    "principalFormatted": "$8,815.38",
    "enquiryYearEndDisplay": "30/06/2020",
    "minimumYearRepaymentFormatted": "$9,984.00"
  },
  "repayments": [
    {
      "rd": "1/7/2019",
      "ra": 8849
    }
  ],
  "inputs": {
    "incomeYearOfLoan": 2016,
    "fullTermOfAmalgamatedLoan": 4,
    "incomeYearOfEnquiring": 2020,
    "amalgamatedLoanNotPaidByEOIY": 9475,
    "repayments": null,
    "lodgement_date": null
  },
  "idx": 1070
}