{
  "id": "2023-10-31T19:09:29.863Z0.9069718898920177",
  "alert": "Start of result\nResult\n\nAmalgamated loan fully repaid.\n\nThe amalgamated loan has been paid in full.\u000bThe private company is not taken under Division 7A to pay a dividend to the shareholder or shareholder's associate.\n\nInterest received by the private company must be included in the income tax return for 2007-08.\n\nMinimum yearly repayment\n\n$12.00\n\nBenchmark interest rate\n\n8.05%\n\nOpening balance:\n\nDate: 30/06/2007\n\nBalance: $54.89\n\nDays: 6\n\nInterest: $0.07\n\nPayments\n\nDate: 07/07/2007\n\nAmount: $548.93\n\nBalance: $0\n\nDays: 360\n\nInterest: $0\n\n\n\n\nTotal repayments\n\n$548.93\n\nTotal interest\n\n$0.07\n\nTotal principal\n\n$548.86\n\nClosing balance\n\nDate: 30/06/2008\n\nBalance: $0",
  "outputs": {
    "enquiryRateFormatted": "8.05%",
    "enquiryYearEndMinusOneDisplay": "30/06/2007",
    "amalgamatedLoanNotPaidByEOIYFormatted": "$54.89",
    "openingBalancePayDays": "6",
    "openingBalanceInterestFormatted": "$0.07",
    "totalAmountOfRepaymentFormatted": "$548.93",
    "totalInterestFormatted": "$0.07",
    "principalFormatted": "$548.86",
    "enquiryYearEndDisplay": "30/06/2008",
    "minimumYearRepaymentFormatted": "$12.00",
    "loanAmountFormatted": "$0"
  },
  "repayments": [
    {
      "rd": "7/7/2007",
      "ra": 548.9324573493705
    }
  ],
  "inputs": {
    "incomeYearOfLoan": 2006,
    "fullTermOfAmalgamatedLoan": 7,
    "incomeYearOfEnquiring": 2008,
    "amalgamatedLoanNotPaidByEOIY": 54.89324573493705,
    "repayments": null,
    "lodgement_date": null
  },
  "idx": 5090
}