{
  "id": "2023-10-31T20:06:44.995Z0.5647926727945235",
  "alert": "Start of result\nResult\n\nAmalgamated loan fully repaid.\n\nThe amalgamated loan has been paid in full.\u000bThe private company is not taken under Division 7A to pay a dividend to the shareholder or shareholder's associate.\n\nInterest received by the private company must be included in the income tax return for 2003-04.\n\nMinimum yearly repayment\n\n$1,223.00\n\nBenchmark interest rate\n\n6.55%\n\nOpening balance:\n\nDate: 30/06/2003\n\nBalance: $5,913.00\n\nDays: 51\n\nInterest: $53.97\n\nPayments\n\nDate: 21/08/2003\n\nAmount: $6,755.00\n\nBalance: $0\n\nDays: 315\n\nInterest: $0\n\n\n\n\nTotal repayments\n\n$6,755.00\n\nTotal interest\n\n$53.97\n\nTotal principal\n\n$6,701.03\n\nClosing balance\n\nDate: 30/06/2004\n\nBalance: $0",
  "outputs": {
    "enquiryRateFormatted": "6.55%",
    "enquiryYearEndMinusOneDisplay": "30/06/2003",
    "amalgamatedLoanNotPaidByEOIYFormatted": "$5,913.00",
    "openingBalancePayDays": "51",
    "openingBalanceInterestFormatted": "$53.97",
    "totalAmountOfRepaymentFormatted": "$6,755.00",
    "totalInterestFormatted": "$53.97",
    "principalFormatted": "$6,701.03",
    "enquiryYearEndDisplay": "30/06/2004",
    "minimumYearRepaymentFormatted": "$1,223.00",
    "loanAmountFormatted": "$0"
  },
  "repayments": [
    {
      "rd": "21/8/2003",
      "ra": 6755
    }
  ],
  "inputs": {
    "incomeYearOfLoan": 2002,
    "fullTermOfAmalgamatedLoan": 7,
    "incomeYearOfEnquiring": 2004,
    "amalgamatedLoanNotPaidByEOIY": 5913,
    "repayments": null,
    "lodgement_date": null
  },
  "idx": 6178
}