{
  "id": "2023-10-31T18:54:10.063Z0.40389577444826597",
  "alert": "Start of result\nResult\n\nMinimum yearly repayment not met.\n\nThe amount of the loan not repaid at the end of income year 2008-09 is $100.31.\n\nThe private company may be taken to pay a dividend under Division 7A to the shareholder or shareholder's associate because the amount repaid during income year 2008-09 in relation to the amalgamated loan is less than the minimum yearly repayment required.\n\nInterest received by the private company must be included in the income tax return for 2008-09.\n\nMinimum yearly repayment\n\n$26.00\n\nBenchmark interest rate\n\n9.45%\n\nOpening balance:\n\nDate: 30/06/2008\n\nBalance: $100.31\n\nDays: 365\n\nInterest: $9.48\n\nTotal repayments\n\n$0\n\nTotal interest\n\n$9.48\n\nTotal principal\n\n$0\n\nClosing balance\n\nDate: 30/06/2009\n\nBalance: $100.31",
  "outputs": {
    "enquiryRateFormatted": "9.45%",
    "enquiryYearEndMinusOneDisplay": "30/06/2008",
    "amalgamatedLoanNotPaidByEOIYFormatted": "$100.31",
    "openingBalancePayDays": "365",
    "openingBalanceInterestFormatted": "$9.48",
    "totalAmountOfRepaymentFormatted": "$0",
    "totalInterestFormatted": "$9.48",
    "principalFormatted": "$0",
    "enquiryYearEndDisplay": "30/06/2009",
    "minimumYearRepaymentFormatted": "$26.00",
    "loanAmountFormatted": "$100.31"
  },
  "repayments": [],
  "inputs": {
    "incomeYearOfLoan": 2007,
    "fullTermOfAmalgamatedLoan": 6,
    "incomeYearOfEnquiring": 2009,
    "amalgamatedLoanNotPaidByEOIY": 100.31407649529207,
    "repayments": null,
    "lodgement_date": null
  },
  "idx": 4724
}