{
  "id": "2023-10-31T17:35:32.668Z0.8417908617482445",
  "alert": "Start of result\nResult\n\nMinimum yearly repayment met.\n\nThe amount of the loan not repaid at the end of income year 2016-17 is $7,093.80.\n\n\u000b\n\nThe amalgamated loan will not be taken to be a dividend because the total repayments made are equal to or greater than the minimum yearly repayment required for income year 2016-17.\n\nInterest received by the private company must be included in the income tax return for 2016-17.\n\nMinimum yearly repayment\n\n$2,387.00\n\nBenchmark interest rate\n\n5.4%\n\nOpening balance:\n\nDate: 30/06/2016\n\nBalance: $10,222.00\n\nDays: 324\n\nInterest: $489.98\n\nPayments\n\nDate: 21/05/2017\n\nAmount: $3,658.00\n\nBalance: $6,564.00\n\nDays: 41\n\nInterest: $39.82\n\n\n\n\nTotal repayments\n\n$3,658.00\n\nTotal interest\n\n$529.80\n\nTotal principal\n\n$3,128.20\n\nClosing balance\n\nDate: 30/06/2017\n\nBalance: $7,093.80",
  "outputs": {
    "enquiryRateFormatted": "5.4%",
    "enquiryYearEndMinusOneDisplay": "30/06/2016",
    "amalgamatedLoanNotPaidByEOIYFormatted": "$10,222.00",
    "openingBalancePayDays": "324",
    "openingBalanceInterestFormatted": "$489.98",
    "totalAmountOfRepaymentFormatted": "$3,658.00",
    "totalInterestFormatted": "$529.80",
    "principalFormatted": "$3,128.20",
    "enquiryYearEndDisplay": "30/06/2017",
    "minimumYearRepaymentFormatted": "$2,387.00",
    "loanAmountFormatted": "$7,093.80"
  },
  "repayments": [
    {
      "rd": "21/5/2017",
      "ra": 3658
    }
  ],
  "inputs": {
    "incomeYearOfLoan": 2016,
    "fullTermOfAmalgamatedLoan": 5,
    "incomeYearOfEnquiring": 2017,
    "amalgamatedLoanNotPaidByEOIY": 10222,
    "repayments": null,
    "lodgement_date": "28/12/2016"
  },
  "idx": 2002
}