{
  "id": "2023-09-06T21:45:26.229Z0.9612620899422006",
  "alert": "Start of result\nResult\n\nMinimum yearly repayment met.\n\nThe amount of the loan not repaid at the end of income year 2006-07 is $2.53.\n\nThe amalgamated loan will not be taken to be a dividend because the total repayments made are equal to or greater than the minimum yearly repayment required for income year 2006-07.\n\nInterest received by the private company must be included in the income tax return for 2006-07.\n\nMinimum yearly repayment\n\n$17.00\n\nBenchmark interest rate\n\n7.55%\n\nOpening balance:\n\nDate: 30/06/2006\n\nBalance: $43.00\n\nDays: 284\n\nInterest: $2.53\n\nPayments\n\nDate: 11/04/2007\n\nAmount: $43.00\n\nBalance: $0\n\nDays: 81\n\nInterest: $0\n\n\n\n\nTotal repayments\n\n$43.00\n\nTotal interest\n\n$2.53\n\nTotal principal\n\n$40.47\n\nClosing balance\n\nDate: 30/06/2007\n\nBalance: $2.53",
  "outputs": {
    "enquiryRateFormatted": "7.55%",
    "enquiryYearEndMinusOneDisplay": "30/06/2006",
    "amalgamatedLoanNotPaidByEOIYFormatted": "$43.00",
    "openingBalancePayDays": "284",
    "openingBalanceInterestFormatted": "$2.53",
    "totalAmountOfRepaymentFormatted": "$43.00",
    "totalInterestFormatted": "$2.53",
    "principalFormatted": "$40.47",
    "enquiryYearEndDisplay": "30/06/2007",
    "minimumYearRepaymentFormatted": "$17.00"
  },
  "repayments": [
    {
      "rd": "11/4/2007",
      "ra": 43
    }
  ],
  "inputs": {
    "incomeYearOfLoan": 2002,
    "fullTermOfAmalgamatedLoan": 7,
    "incomeYearOfEnquiring": 2007,
    "amalgamatedLoanNotPaidByEOIY": 43,
    "repayments": null,
    "lodgement_date": null
  },
  "idx": 6657
}