{
  "id": "2023-10-31T19:49:32.493Z0.3052387734115599",
  "alert": "Start of result\nResult\n\nMinimum yearly repayment not met.\n\nThe amount of the loan not repaid at the end of income year 2007-08 is $6,129.00.\n\nThe private company may be taken to pay a dividend under Division 7A to the shareholder or shareholder's associate because the amount repaid during income year 2007-08 in relation to the amalgamated loan is less than the minimum yearly repayment required.\n\nInterest received by the private company must be included in the income tax return for 2007-08.\n\nMinimum yearly repayment\n\n$2,380.00\n\nBenchmark interest rate\n\n8.05%\n\nOpening balance:\n\nDate: 30/06/2007\n\nBalance: $6,129.00\n\nDays: 366\n\nInterest: $493.38\n\nTotal repayments\n\n$0\n\nTotal interest\n\n$493.38\n\nTotal principal\n\n$0\n\nClosing balance\n\nDate: 30/06/2008\n\nBalance: $6,129.00",
  "outputs": {
    "enquiryRateFormatted": "8.05%",
    "enquiryYearEndMinusOneDisplay": "30/06/2007",
    "amalgamatedLoanNotPaidByEOIYFormatted": "$6,129.00",
    "openingBalancePayDays": "366",
    "openingBalanceInterestFormatted": "$493.38",
    "totalAmountOfRepaymentFormatted": "$0",
    "totalInterestFormatted": "$493.38",
    "principalFormatted": "$0",
    "enquiryYearEndDisplay": "30/06/2008",
    "minimumYearRepaymentFormatted": "$2,380.00",
    "loanAmountFormatted": "$6,129.00"
  },
  "repayments": [],
  "inputs": {
    "incomeYearOfLoan": 2003,
    "fullTermOfAmalgamatedLoan": 7,
    "incomeYearOfEnquiring": 2008,
    "amalgamatedLoanNotPaidByEOIY": 6129,
    "repayments": null,
    "lodgement_date": null
  },
  "idx": 5887
}