{
  "id": "2023-09-05T11:48:25.367Z0.9947658974644855",
  "alert": "Start of result\nResult\n\nMinimum yearly repayment met.\n\nThe amount of the loan not repaid at the end of income year 2023-24 is $0.64.\n\nThe amalgamated loan will not be taken to be a dividend because the total repayments made are equal to or greater than the minimum yearly repayment required for income year 2023-24.\n\nInterest received by the private company must be included in the income tax return for 2023-24.\n\nMinimum yearly repayment\n\n$3.00\n\nBenchmark interest rate\n\n8.27%\n\nOpening balance:\n\nDate: 30/06/2023\n\nBalance: $8.34\n\nDays: 341\n\nInterest: $0.64\n\nPayments\n\nDate: 06/06/2024\n\nAmount: $8.34\n\nBalance: $0\n\nDays: 25\n\nInterest: $0\n\n\n\n\nTotal repayments\n\n$8.34\n\nTotal interest\n\n$0.64\n\nTotal principal\n\n$7.70\n\nClosing balance\n\nDate: 30/06/2024\n\nBalance: $0.64",
  "outputs": {
    "enquiryRateFormatted": "8.27%",
    "enquiryYearEndMinusOneDisplay": "30/06/2023",
    "amalgamatedLoanNotPaidByEOIYFormatted": "$8.34",
    "openingBalancePayDays": "341",
    "openingBalanceInterestFormatted": "$0.64",
    "totalAmountOfRepaymentFormatted": "$8.34",
    "totalInterestFormatted": "$0.64",
    "principalFormatted": "$7.70",
    "enquiryYearEndDisplay": "30/06/2024",
    "minimumYearRepaymentFormatted": "$3.00"
  },
  "repayments": [
    {
      "rd": "6/6/2024",
      "ra": 8.340403799068397
    }
  ],
  "inputs": {
    "incomeYearOfLoan": 2022,
    "fullTermOfAmalgamatedLoan": 4,
    "incomeYearOfEnquiring": 2024,
    "amalgamatedLoanNotPaidByEOIY": 8.340403799068394,
    "repayments": null,
    "lodgement_date": null
  },
  "idx": 2201
}