{
  "id": "2023-10-31T17:57:45.455Z0.9736550990379459",
  "alert": "Start of result\nResult\n\nAmalgamated loan fully repaid.\n\nThe amalgamated loan has been paid in full.\u000bThe private company is not taken under Division 7A to pay a dividend to the shareholder or shareholder's associate.\n\nInterest received by the private company must be included in the income tax return for 2016-17.\n\nMinimum yearly repayment\n\n$3.00\n\nBenchmark interest rate\n\n5.4%\n\nOpening balance:\n\nDate: 30/06/2016\n\nBalance: $9.21\n\nDays: 238\n\nInterest: $0.32\n\nPayments\n\nDate: 24/02/2017\n\nAmount: $92.19\n\nBalance: $0\n\nDays: 127\n\nInterest: $0\n\n\n\n\nTotal repayments\n\n$92.19\n\nTotal interest\n\n$0.32\n\nTotal principal\n\n$91.87\n\nClosing balance\n\nDate: 30/06/2017\n\nBalance: $0",
  "outputs": {
    "enquiryRateFormatted": "5.4%",
    "enquiryYearEndMinusOneDisplay": "30/06/2016",
    "amalgamatedLoanNotPaidByEOIYFormatted": "$9.21",
    "openingBalancePayDays": "238",
    "openingBalanceInterestFormatted": "$0.32",
    "totalAmountOfRepaymentFormatted": "$92.19",
    "totalInterestFormatted": "$0.32",
    "principalFormatted": "$91.87",
    "enquiryYearEndDisplay": "30/06/2017",
    "minimumYearRepaymentFormatted": "$3.00",
    "loanAmountFormatted": "$0"
  },
  "repayments": [
    {
      "rd": "24/2/2017",
      "ra": 92.19933773763228
    }
  ],
  "inputs": {
    "incomeYearOfLoan": 2013,
    "fullTermOfAmalgamatedLoan": 6,
    "incomeYearOfEnquiring": 2017,
    "amalgamatedLoanNotPaidByEOIY": 9.219933773763227,
    "repayments": null,
    "lodgement_date": null
  },
  "idx": 3004
}