{
  "id": "2023-09-04T22:19:40.060Z0.8299492720063717",
  "alert": "Start of result\nResult\n\nMinimum yearly repayment met.\n\nThe amount of the loan not repaid at the end of income year 2002-03 is $2,541.63.\n\nThe amalgamated loan will not be taken to be a dividend because the total repayments made are equal to or greater than the minimum yearly repayment required for income year 2002-03.\n\nInterest received by the private company must be included in the income tax return for 2002-03.\n\nMinimum yearly repayment\n\n$1,472.00\n\nBenchmark interest rate\n\n6.3%\n\nOpening balance:\n\nDate: 30/06/2002\n\nBalance: $7,169.00\n\nDays: 0\n\nInterest: $0\n\nPayments\n\nDate: 01/07/2002\n\nAmount: $4,778.00\n\nBalance: $2,391.00\n\nDays: 365\n\nInterest: $150.63\n\n\n\n\nTotal repayments\n\n$4,778.00\n\nTotal interest\n\n$150.63\n\nTotal principal\n\n$4,627.37\n\nClosing balance\n\nDate: 30/06/2003\n\nBalance: $2,541.63",
  "outputs": {
    "enquiryRateFormatted": "6.3%",
    "enquiryYearEndMinusOneDisplay": "30/06/2002",
    "amalgamatedLoanNotPaidByEOIYFormatted": "$7,169.00",
    "openingBalancePayDays": "0",
    "openingBalanceInterestFormatted": "$0",
    "totalAmountOfRepaymentFormatted": "$4,778.00",
    "totalInterestFormatted": "$150.63",
    "principalFormatted": "$4,627.37",
    "enquiryYearEndDisplay": "30/06/2003",
    "minimumYearRepaymentFormatted": "$1,472.00"
  },
  "repayments": [
    {
      "rd": "1/7/2002",
      "ra": 4778
    }
  ],
  "inputs": {
    "incomeYearOfLoan": 2001,
    "fullTermOfAmalgamatedLoan": 7,
    "incomeYearOfEnquiring": 2003,
    "amalgamatedLoanNotPaidByEOIY": 7169,
    "repayments": null,
    "lodgement_date": null
  },
  "idx": 713
}