{
  "id": "2023-09-06T18:37:12.207Z0.8852436365238527",
  "alert": "Start of result\nResult\n\nMinimum yearly repayment met.\n\nThe amount of the loan not repaid at the end of income year 2008-09 is $424.80.\n\nThe amalgamated loan will not be taken to be a dividend because the total repayments made are equal to or greater than the minimum yearly repayment required for income year 2008-09.\n\nInterest received by the private company must be included in the income tax return for 2008-09.\n\nMinimum yearly repayment\n\n$2,238.00\n\nBenchmark interest rate\n\n9.45%\n\nOpening balance:\n\nDate: 30/06/2008\n\nBalance: $5,619.00\n\nDays: 292\n\nInterest: $424.80\n\nPayments\n\nDate: 19/04/2009\n\nAmount: $5,619.00\n\nBalance: $0\n\nDays: 73\n\nInterest: $0\n\n\n\n\nTotal repayments\n\n$5,619.00\n\nTotal interest\n\n$424.80\n\nTotal principal\n\n$5,194.20\n\nClosing balance\n\nDate: 30/06/2009\n\nBalance: $424.80",
  "outputs": {
    "enquiryRateFormatted": "9.45%",
    "enquiryYearEndMinusOneDisplay": "30/06/2008",
    "amalgamatedLoanNotPaidByEOIYFormatted": "$5,619.00",
    "openingBalancePayDays": "292",
    "openingBalanceInterestFormatted": "$424.80",
    "totalAmountOfRepaymentFormatted": "$5,619.00",
    "totalInterestFormatted": "$424.80",
    "principalFormatted": "$5,194.20",
    "enquiryYearEndDisplay": "30/06/2009",
    "minimumYearRepaymentFormatted": "$2,238.00"
  },
  "repayments": [
    {
      "rd": "19/4/2009",
      "ra": 5619
    }
  ],
  "inputs": {
    "incomeYearOfLoan": 2004,
    "fullTermOfAmalgamatedLoan": 7,
    "incomeYearOfEnquiring": 2009,
    "amalgamatedLoanNotPaidByEOIY": 5619,
    "repayments": null,
    "lodgement_date": null
  },
  "idx": 2957
}