{
  "id": "2023-09-06T23:17:31.107Z0.5856506316843348",
  "alert": "Start of result\nResult\n\nMinimum yearly repayment met.\n\nThe amount of the loan not repaid at the end of income year 2003-04 is $0.91.\n\nThe amalgamated loan will not be taken to be a dividend because the total repayments made are equal to or greater than the minimum yearly repayment required for income year 2003-04.\n\nInterest received by the private company must be included in the income tax return for 2003-04.\n\nMinimum yearly repayment\n\n$11.00\n\nBenchmark interest rate\n\n6.55%\n\nOpening balance:\n\nDate: 30/06/2003\n\nBalance: $44.68\n\nDays: 114\n\nInterest: $0.91\n\nPayments\n\nDate: 23/10/2003\n\nAmount: $44.68\n\nBalance: $0\n\nDays: 252\n\nInterest: $0\n\n\n\n\nTotal repayments\n\n$44.68\n\nTotal interest\n\n$0.91\n\nTotal principal\n\n$43.77\n\nClosing balance\n\nDate: 30/06/2004\n\nBalance: $0.91",
  "outputs": {
    "enquiryRateFormatted": "6.55%",
    "enquiryYearEndMinusOneDisplay": "30/06/2003",
    "amalgamatedLoanNotPaidByEOIYFormatted": "$44.68",
    "openingBalancePayDays": "114",
    "openingBalanceInterestFormatted": "$0.91",
    "totalAmountOfRepaymentFormatted": "$44.68",
    "totalInterestFormatted": "$0.91",
    "principalFormatted": "$43.77",
    "enquiryYearEndDisplay": "30/06/2004",
    "minimumYearRepaymentFormatted": "$11.00"
  },
  "repayments": [
    {
      "rd": "23/10/2003",
      "ra": 44.687043464382896
    }
  ],
  "inputs": {
    "incomeYearOfLoan": 2001,
    "fullTermOfAmalgamatedLoan": 7,
    "incomeYearOfEnquiring": 2004,
    "amalgamatedLoanNotPaidByEOIY": 44.68704346438301,
    "repayments": null,
    "lodgement_date": null
  },
  "idx": 2965
}