{
  "id": "2023-09-06T00:37:29.414Z0.6966705632723895",
  "alert": "Start of result\nResult\n\nMinimum yearly repayment not met.\n\nThe amount of the loan not repaid at the end of income year 2015-16 is $1.36.\n\nThe private company may be taken to pay a dividend under Division 7A to the shareholder or shareholder's associate because the amount repaid during income year 2015-16 in relation to the amalgamated loan is less than the minimum yearly repayment required.\n\nInterest received by the private company must be included in the income tax return for 2015-16.\n\nMinimum yearly repayment\n\n$42.00\n\nBenchmark interest rate\n\n5.45%\n\nOpening balance:\n\nDate: 30/06/2015\n\nBalance: $40.13\n\nDays: 228\n\nInterest: $1.36\n\nPayments\n\nDate: 14/02/2016\n\nAmount: $40.13\n\nBalance: $0\n\nDays: 138\n\nInterest: $0\n\n\n\n\nTotal repayments\n\n$40.13\n\nTotal interest\n\n$1.36\n\nTotal principal\n\n$38.77\n\nClosing balance\n\nDate: 30/06/2016\n\nBalance: $1.36",
  "outputs": {
    "enquiryRateFormatted": "5.45%",
    "enquiryYearEndMinusOneDisplay": "30/06/2015",
    "amalgamatedLoanNotPaidByEOIYFormatted": "$40.13",
    "openingBalancePayDays": "228",
    "openingBalanceInterestFormatted": "$1.36",
    "totalAmountOfRepaymentFormatted": "$40.13",
    "totalInterestFormatted": "$1.36",
    "principalFormatted": "$38.77",
    "enquiryYearEndDisplay": "30/06/2016",
    "minimumYearRepaymentFormatted": "$42.00"
  },
  "repayments": [
    {
      "rd": "14/2/2016",
      "ra": 40.13407427360471
    }
  ],
  "inputs": {
    "incomeYearOfLoan": 2014,
    "fullTermOfAmalgamatedLoan": 2,
    "incomeYearOfEnquiring": 2016,
    "amalgamatedLoanNotPaidByEOIY": 40.13407427360505,
    "repayments": null,
    "lodgement_date": null
  },
  "idx": 3701
}