{
  "id": "2023-09-06T18:28:27.149Z0.15319078241893913",
  "alert": "Start of result\nResult\n\nMinimum yearly repayment not met.\n\nThe amount of the loan not repaid at the end of income year 2004-05 is $97.26.\n\nThe private company may be taken to pay a dividend under Division 7A to the shareholder or shareholder's associate because the amount repaid during income year 2004-05 in relation to the amalgamated loan is less than the minimum yearly repayment required.\n\nInterest received by the private company must be included in the income tax return for 2004-05.\n\nMinimum yearly repayment\n\n$20.00\n\nBenchmark interest rate\n\n7.05%\n\nOpening balance:\n\nDate: 30/06/2004\n\nBalance: $97.26\n\nDays: 365\n\nInterest: $6.86\n\nTotal repayments\n\n$0\n\nTotal interest\n\n$6.86\n\nTotal principal\n\n$0\n\nClosing balance\n\nDate: 30/06/2005\n\nBalance: $97.26",
  "outputs": {
    "enquiryRateFormatted": "7.05%",
    "enquiryYearEndMinusOneDisplay": "30/06/2004",
    "amalgamatedLoanNotPaidByEOIYFormatted": "$97.26",
    "openingBalancePayDays": "365",
    "openingBalanceInterestFormatted": "$6.86",
    "totalAmountOfRepaymentFormatted": "$0",
    "totalInterestFormatted": "$6.86",
    "principalFormatted": "$0",
    "enquiryYearEndDisplay": "30/06/2005",
    "minimumYearRepaymentFormatted": "$20.00"
  },
  "repayments": [],
  "inputs": {
    "incomeYearOfLoan": 2004,
    "fullTermOfAmalgamatedLoan": 6,
    "incomeYearOfEnquiring": 2005,
    "amalgamatedLoanNotPaidByEOIY": 97.26786899157679,
    "repayments": null,
    "lodgement_date": "26/12/2004"
  },
  "idx": 2398
}