{
  "id": "2023-10-31T21:09:26.825Z0.7483144166710739",
  "alert": "Start of result\nResult\n\nMinimum yearly repayment not met.\n\nThe amount of the loan not repaid at the end of income year 1999-00 is $61.63.\n\nThe private company may be taken to pay a dividend under Division 7A to the shareholder or shareholder's associate because the amount repaid during income year 1999-00 in relation to the amalgamated loan is less than the minimum yearly repayment required.\n\nInterest received by the private company must be included in the income tax return for 1999-00.\n\nMinimum yearly repayment\n\n$13.00\n\nBenchmark interest rate\n\n6.5%\n\nOpening balance:\n\nDate: 30/06/1999\n\nBalance: $61.63\n\nDays: 366\n\nInterest: $4.01\n\nTotal repayments\n\n$0\n\nTotal interest\n\n$4.01\n\nTotal principal\n\n$0\n\nClosing balance\n\nDate: 30/06/2000\n\nBalance: $61.63",
  "outputs": {
    "enquiryRateFormatted": "6.5%",
    "enquiryYearEndMinusOneDisplay": "30/06/1999",
    "amalgamatedLoanNotPaidByEOIYFormatted": "$61.63",
    "openingBalancePayDays": "366",
    "openingBalanceInterestFormatted": "$4.01",
    "totalAmountOfRepaymentFormatted": "$0",
    "totalInterestFormatted": "$4.01",
    "principalFormatted": "$0",
    "enquiryYearEndDisplay": "30/06/2000",
    "minimumYearRepaymentFormatted": "$13.00",
    "loanAmountFormatted": "$61.63"
  },
  "repayments": [],
  "inputs": {
    "incomeYearOfLoan": 1999,
    "fullTermOfAmalgamatedLoan": 6,
    "incomeYearOfEnquiring": 2000,
    "amalgamatedLoanNotPaidByEOIY": 61.63633481568357,
    "repayments": null,
    "lodgement_date": "30/6/2000"
  },
  "idx": 7057
}