{
  "id": "2023-10-31T20:03:46.675Z0.6460730208683518",
  "alert": "Start of result\nResult\n\nMinimum yearly repayment met.\n\nThe amount of the loan not repaid at the end of income year 2003-04 is $2,497.41.\n\n\u000b\n\nThe amalgamated loan will not be taken to be a dividend because the total repayments made are equal to or greater than the minimum yearly repayment required for income year 2003-04.\n\nInterest received by the private company must be included in the income tax return for 2003-04.\n\nMinimum yearly repayment\n\n$1,885.00\n\nBenchmark interest rate\n\n6.55%\n\nOpening balance:\n\nDate: 30/06/2003\n\nBalance: $7,821.00\n\nDays: 58\n\nInterest: $81.18\n\nPayments\n\nDate: 28/08/2003\n\nAmount: $5,531.00\n\nBalance: $2,290.00\n\nDays: 308\n\nInterest: $126.23\n\n\n\n\nTotal repayments\n\n$5,531.00\n\nTotal interest\n\n$207.41\n\nTotal principal\n\n$5,323.59\n\nClosing balance\n\nDate: 30/06/2004\n\nBalance: $2,497.41",
  "outputs": {
    "enquiryRateFormatted": "6.55%",
    "enquiryYearEndMinusOneDisplay": "30/06/2003",
    "amalgamatedLoanNotPaidByEOIYFormatted": "$7,821.00",
    "openingBalancePayDays": "58",
    "openingBalanceInterestFormatted": "$81.18",
    "totalAmountOfRepaymentFormatted": "$5,531.00",
    "totalInterestFormatted": "$207.41",
    "principalFormatted": "$5,323.59",
    "enquiryYearEndDisplay": "30/06/2004",
    "minimumYearRepaymentFormatted": "$1,885.00",
    "loanAmountFormatted": "$2,497.41"
  },
  "repayments": [
    {
      "rd": "28/8/2003",
      "ra": 5531
    }
  ],
  "inputs": {
    "incomeYearOfLoan": 2002,
    "fullTermOfAmalgamatedLoan": 6,
    "incomeYearOfEnquiring": 2004,
    "amalgamatedLoanNotPaidByEOIY": 7821,
    "repayments": null,
    "lodgement_date": null
  },
  "idx": 6130
}