{
  "id": "2023-10-31T17:47:09.009Z0.8790665291650105",
  "alert": "Start of result\nResult\n\nAmalgamated loan fully repaid.\n\nThe amalgamated loan has been paid in full.\u000bThe private company is not taken under Division 7A to pay a dividend to the shareholder or shareholder's associate.\n\nInterest received by the private company must be included in the income tax return for 2016-17.\n\nMinimum yearly repayment\n\n$36.00\n\nBenchmark interest rate\n\n5.4%\n\nOpening balance:\n\nDate: 30/06/2016\n\nBalance: $66.55\n\nDays: 96\n\nInterest: $0.95\n\nPayments\n\nDate: 05/10/2016\n\nAmount: $665.50\n\nBalance: $0\n\nDays: 269\n\nInterest: $0\n\n\n\n\nTotal repayments\n\n$665.50\n\nTotal interest\n\n$0.95\n\nTotal principal\n\n$664.55\n\nClosing balance\n\nDate: 30/06/2017\n\nBalance: $0",
  "outputs": {
    "enquiryRateFormatted": "5.4%",
    "enquiryYearEndMinusOneDisplay": "30/06/2016",
    "amalgamatedLoanNotPaidByEOIYFormatted": "$66.55",
    "openingBalancePayDays": "96",
    "openingBalanceInterestFormatted": "$0.95",
    "totalAmountOfRepaymentFormatted": "$665.50",
    "totalInterestFormatted": "$0.95",
    "principalFormatted": "$664.55",
    "enquiryYearEndDisplay": "30/06/2017",
    "minimumYearRepaymentFormatted": "$36.00",
    "loanAmountFormatted": "$0"
  },
  "repayments": [
    {
      "rd": "5/10/2016",
      "ra": 665.5043574664205
    }
  ],
  "inputs": {
    "incomeYearOfLoan": 2014,
    "fullTermOfAmalgamatedLoan": 4,
    "incomeYearOfEnquiring": 2017,
    "amalgamatedLoanNotPaidByEOIY": 66.55043574664204,
    "repayments": null,
    "lodgement_date": null
  },
  "idx": 2558
}