{
  "id": "2023-10-31T18:00:27.609Z0.5933913926336717",
  "alert": "Start of result\nResult\n\nMinimum yearly repayment not met.\n\nThe amount of the loan not repaid at the end of income year 2012-13 is $4,386.68.\n\nThe private company may be taken to pay a dividend under Division 7A to the shareholder or shareholder's associate because the amount repaid during income year 2012-13 in relation to the amalgamated loan is less than the minimum yearly repayment required.\n\nInterest received by the private company must be included in the income tax return for 2012-13.\n\nMinimum yearly repayment\n\n$10,018.00\n\nBenchmark interest rate\n\n7.05%\n\nOpening balance:\n\nDate: 30/06/2012\n\nBalance: $9,358.00\n\nDays: 125\n\nInterest: $225.94\n\nPayments\n\nDate: 03/11/2012\n\nAmount: $1,501.00\n\nBalance: $7,857.00\n\nDays: 233\n\nInterest: $353.60\n\n\n\n\nDate: 24/06/2013\n\nAmount: $4,055.00\n\nBalance: $3,802.00\n\nDays: 7\n\nInterest: $5.14\n\n\n\n\nTotal repayments\n\n$5,556.00\n\nTotal interest\n\n$584.68\n\nTotal principal\n\n$4,971.32\n\nClosing balance\n\nDate: 30/06/2013\n\nBalance: $4,386.68",
  "outputs": {
    "enquiryRateFormatted": "7.05%",
    "enquiryYearEndMinusOneDisplay": "30/06/2012",
    "amalgamatedLoanNotPaidByEOIYFormatted": "$9,358.00",
    "openingBalancePayDays": "125",
    "openingBalanceInterestFormatted": "$225.94",
    "totalAmountOfRepaymentFormatted": "$5,556.00",
    "totalInterestFormatted": "$584.68",
    "principalFormatted": "$4,971.32",
    "enquiryYearEndDisplay": "30/06/2013",
    "minimumYearRepaymentFormatted": "$10,018.00",
    "loanAmountFormatted": "$4,386.68"
  },
  "repayments": [
    {
      "rd": "3/11/2012",
      "ra": 1501
    },
    {
      "rd": "24/6/2013",
      "ra": 4055
    }
  ],
  "inputs": {
    "incomeYearOfLoan": 2012,
    "fullTermOfAmalgamatedLoan": 1,
    "incomeYearOfEnquiring": 2013,
    "amalgamatedLoanNotPaidByEOIY": 9358,
    "repayments": null,
    "lodgement_date": "31/7/2012"
  },
  "idx": 3109
}