{
  "id": "2023-09-06T03:25:22.731Z0.4733358867500259",
  "alert": "Start of result\nResult\n\nMinimum yearly repayment met.\n\nThe amount of the loan not repaid at the end of income year 2016-17 is $867.46.\n\nThe amalgamated loan will not be taken to be a dividend because the total repayments made are equal to or greater than the minimum yearly repayment required for income year 2016-17.\n\nInterest received by the private company must be included in the income tax return for 2016-17.\n\nMinimum yearly repayment\n\n$1,434.00\n\nBenchmark interest rate\n\n5.4%\n\nOpening balance:\n\nDate: 30/06/2016\n\nBalance: $3,877.00\n\nDays: 108\n\nInterest: $61.95\n\nPayments\n\nDate: 17/10/2016\n\nAmount: $3,101.00\n\nBalance: $776.00\n\nDays: 257\n\nInterest: $29.51\n\n\n\n\nTotal repayments\n\n$3,101.00\n\nTotal interest\n\n$91.46\n\nTotal principal\n\n$3,009.54\n\nClosing balance\n\nDate: 30/06/2017\n\nBalance: $867.46",
  "outputs": {
    "enquiryRateFormatted": "5.4%",
    "enquiryYearEndMinusOneDisplay": "30/06/2016",
    "amalgamatedLoanNotPaidByEOIYFormatted": "$3,877.00",
    "openingBalancePayDays": "108",
    "openingBalanceInterestFormatted": "$61.95",
    "totalAmountOfRepaymentFormatted": "$3,101.00",
    "totalInterestFormatted": "$91.46",
    "principalFormatted": "$3,009.54",
    "enquiryYearEndDisplay": "30/06/2017",
    "minimumYearRepaymentFormatted": "$1,434.00"
  },
  "repayments": [
    {
      "rd": "17/10/2016",
      "ra": 3101
    }
  ],
  "inputs": {
    "incomeYearOfLoan": 2013,
    "fullTermOfAmalgamatedLoan": 6,
    "incomeYearOfEnquiring": 2017,
    "amalgamatedLoanNotPaidByEOIY": 3877,
    "repayments": null,
    "lodgement_date": null
  },
  "idx": 4053
}