{
  "id": "2023-10-31T18:06:17.193Z0.6919545665489235",
  "alert": "Start of result\nResult\n\nAmalgamated loan fully repaid.\n\nThe amalgamated loan has been paid in full.\u000bThe private company is not taken under Division 7A to pay a dividend to the shareholder or shareholder's associate.\n\nInterest received by the private company must be included in the income tax return for 2017-18.\n\nMinimum yearly repayment\n\n$25.00\n\nBenchmark interest rate\n\n5.3%\n\nOpening balance:\n\nDate: 30/06/2017\n\nBalance: $46.04\n\nDays: 180\n\nInterest: $1.20\n\nPayments\n\nDate: 28/12/2017\n\nAmount: $460.46\n\nBalance: $0\n\nDays: 185\n\nInterest: $0\n\n\n\n\nTotal repayments\n\n$460.46\n\nTotal interest\n\n$1.20\n\nTotal principal\n\n$459.26\n\nClosing balance\n\nDate: 30/06/2018\n\nBalance: $0",
  "outputs": {
    "enquiryRateFormatted": "5.3%",
    "enquiryYearEndMinusOneDisplay": "30/06/2017",
    "amalgamatedLoanNotPaidByEOIYFormatted": "$46.04",
    "openingBalancePayDays": "180",
    "openingBalanceInterestFormatted": "$1.20",
    "totalAmountOfRepaymentFormatted": "$460.46",
    "totalInterestFormatted": "$1.20",
    "principalFormatted": "$459.26",
    "enquiryYearEndDisplay": "30/06/2018",
    "minimumYearRepaymentFormatted": "$25.00",
    "loanAmountFormatted": "$0"
  },
  "repayments": [
    {
      "rd": "28/12/2017",
      "ra": 460.46300195431564
    }
  ],
  "inputs": {
    "incomeYearOfLoan": 2012,
    "fullTermOfAmalgamatedLoan": 7,
    "incomeYearOfEnquiring": 2018,
    "amalgamatedLoanNotPaidByEOIY": 46.04630019543156,
    "repayments": null,
    "lodgement_date": null
  },
  "idx": 3320
}