{
  "id": "2023-10-31T17:28:59.825Z0.7334146486094378",
  "alert": "Start of result\nResult\n\nMinimum yearly repayment met.\n\nThe amount of the loan not repaid at the end of income year 2020-21 is $936.65.\n\n\u000b\n\nThe amalgamated loan will not be taken to be a dividend because the total repayments made are equal to or greater than the minimum yearly repayment required for income year 2020-21.\n\nInterest received by the private company must be included in the income tax return for 2020-21.\n\nMinimum yearly repayment\n\n$4,654.00\n\nBenchmark interest rate\n\n4.52%\n\nOpening balance:\n\nDate: 30/06/2020\n\nBalance: $8,713.00\n\nDays: 306\n\nInterest: $330.17\n\nPayments\n\nDate: 03/05/2021\n\nAmount: $2,185.00\n\nBalance: $6,528.00\n\nDays: 37\n\nInterest: $29.91\n\n\n\n\nDate: 09/06/2021\n\nAmount: $5,953.00\n\nBalance: $575.00\n\nDays: 22\n\nInterest: $1.57\n\n\n\n\nTotal repayments\n\n$8,138.00\n\nTotal interest\n\n$361.65\n\nTotal principal\n\n$7,776.35\n\nClosing balance\n\nDate: 30/06/2021\n\nBalance: $936.65",
  "outputs": {
    "enquiryRateFormatted": "4.52%",
    "enquiryYearEndMinusOneDisplay": "30/06/2020",
    "amalgamatedLoanNotPaidByEOIYFormatted": "$8,713.00",
    "openingBalancePayDays": "306",
    "openingBalanceInterestFormatted": "$330.17",
    "totalAmountOfRepaymentFormatted": "$8,138.00",
    "totalInterestFormatted": "$361.65",
    "principalFormatted": "$7,776.35",
    "enquiryYearEndDisplay": "30/06/2021",
    "minimumYearRepaymentFormatted": "$4,654.00",
    "loanAmountFormatted": "$936.65"
  },
  "repayments": [
    {
      "rd": "3/5/2021",
      "ra": 2185
    },
    {
      "rd": "9/6/2021",
      "ra": 5953
    }
  ],
  "inputs": {
    "incomeYearOfLoan": 2017,
    "fullTermOfAmalgamatedLoan": 5,
    "incomeYearOfEnquiring": 2021,
    "amalgamatedLoanNotPaidByEOIY": 8713,
    "repayments": null,
    "lodgement_date": null
  },
  "idx": 1640
}