{
  "id": "2023-10-31T17:25:47.939Z0.4035292836727906",
  "alert": "Start of result\nResult\n\nAmalgamated loan fully repaid.\n\nThe amalgamated loan has been paid in full.\u000bThe private company is not taken under Division 7A to pay a dividend to the shareholder or shareholder's associate.\n\nInterest received by the private company must be included in the income tax return for 2018-19.\n\nMinimum yearly repayment\n\n$10.00\n\nBenchmark interest rate\n\n5.2%\n\nOpening balance:\n\nDate: 30/06/2018\n\nBalance: $49.70\n\nDays: 331\n\nInterest: $2.34\n\nPayments\n\nDate: 28/05/2019\n\nAmount: $497.09\n\nBalance: $0\n\nDays: 34\n\nInterest: $0\n\n\n\n\nTotal repayments\n\n$497.09\n\nTotal interest\n\n$2.34\n\nTotal principal\n\n$494.75\n\nClosing balance\n\nDate: 30/06/2019\n\nBalance: $0",
  "outputs": {
    "enquiryRateFormatted": "5.2%",
    "enquiryYearEndMinusOneDisplay": "30/06/2018",
    "amalgamatedLoanNotPaidByEOIYFormatted": "$49.70",
    "openingBalancePayDays": "331",
    "openingBalanceInterestFormatted": "$2.34",
    "totalAmountOfRepaymentFormatted": "$497.09",
    "totalInterestFormatted": "$2.34",
    "principalFormatted": "$494.75",
    "enquiryYearEndDisplay": "30/06/2019",
    "minimumYearRepaymentFormatted": "$10.00",
    "loanAmountFormatted": "$0"
  },
  "repayments": [
    {
      "rd": "28/5/2019",
      "ra": 497.0993026679771
    }
  ],
  "inputs": {
    "incomeYearOfLoan": 2018,
    "fullTermOfAmalgamatedLoan": 6,
    "incomeYearOfEnquiring": 2019,
    "amalgamatedLoanNotPaidByEOIY": 49.70993026679768,
    "repayments": null,
    "lodgement_date": "28/11/2018"
  },
  "idx": 1456
}