{
  "id": "2023-10-31T18:42:55.402Z0.9195222866176912",
  "alert": "Start of result\nResult\n\nMinimum yearly repayment met.\n\nThe amount of the loan not repaid at the end of income year 2013-14 is $4,404.97.\n\n\u000b\n\nThe amalgamated loan will not be taken to be a dividend because the total repayments made are equal to or greater than the minimum yearly repayment required for income year 2013-14.\n\nInterest received by the private company must be included in the income tax return for 2013-14.\n\nMinimum yearly repayment\n\n$5,940.00\n\nBenchmark interest rate\n\n6.2%\n\nOpening balance:\n\nDate: 30/06/2013\n\nBalance: $10,860.00\n\nDays: 68\n\nInterest: $125.44\n\nPayments\n\nDate: 07/09/2013\n\nAmount: $6,786.00\n\nBalance: $4,074.00\n\nDays: 297\n\nInterest: $205.53\n\n\n\n\nTotal repayments\n\n$6,786.00\n\nTotal interest\n\n$330.97\n\nTotal principal\n\n$6,455.03\n\nClosing balance\n\nDate: 30/06/2014\n\nBalance: $4,404.97",
  "outputs": {
    "enquiryRateFormatted": "6.2%",
    "enquiryYearEndMinusOneDisplay": "30/06/2013",
    "amalgamatedLoanNotPaidByEOIYFormatted": "$10,860.00",
    "openingBalancePayDays": "68",
    "openingBalanceInterestFormatted": "$125.44",
    "totalAmountOfRepaymentFormatted": "$6,786.00",
    "totalInterestFormatted": "$330.97",
    "principalFormatted": "$6,455.03",
    "enquiryYearEndDisplay": "30/06/2014",
    "minimumYearRepaymentFormatted": "$5,940.00",
    "loanAmountFormatted": "$4,404.97"
  },
  "repayments": [
    {
      "rd": "7/9/2013",
      "ra": 6786
    }
  ],
  "inputs": {
    "incomeYearOfLoan": 2008,
    "fullTermOfAmalgamatedLoan": 7,
    "incomeYearOfEnquiring": 2014,
    "amalgamatedLoanNotPaidByEOIY": 10860,
    "repayments": null,
    "lodgement_date": null
  },
  "idx": 4432
}