{
  "id": "2023-09-05T21:26:19.690Z0.7194352296785684",
  "alert": "Start of result\nResult\n\nMinimum yearly repayment not met.\n\nThe amount of the loan not repaid at the end of income year 2016-17 is $1,531.14.\n\nThe private company may be taken to pay a dividend under Division 7A to the shareholder or shareholder's associate because the amount repaid during income year 2016-17 in relation to the amalgamated loan is less than the minimum yearly repayment required.\n\nInterest received by the private company must be included in the income tax return for 2016-17.\n\nMinimum yearly repayment\n\n$10,574.00\n\nBenchmark interest rate\n\n5.4%\n\nOpening balance:\n\nDate: 30/06/2016\n\nBalance: $10,032.00\n\nDays: 214\n\nInterest: $317.62\n\nPayments\n\nDate: 31/01/2017\n\nAmount: $8,845.00\n\nBalance: $1,187.00\n\nDays: 151\n\nInterest: $26.52\n\n\n\n\nTotal repayments\n\n$8,845.00\n\nTotal interest\n\n$344.14\n\nTotal principal\n\n$8,500.86\n\nClosing balance\n\nDate: 30/06/2017\n\nBalance: $1,531.14",
  "outputs": {
    "enquiryRateFormatted": "5.4%",
    "enquiryYearEndMinusOneDisplay": "30/06/2016",
    "amalgamatedLoanNotPaidByEOIYFormatted": "$10,032.00",
    "openingBalancePayDays": "214",
    "openingBalanceInterestFormatted": "$317.62",
    "totalAmountOfRepaymentFormatted": "$8,845.00",
    "totalInterestFormatted": "$344.14",
    "principalFormatted": "$8,500.86",
    "enquiryYearEndDisplay": "30/06/2017",
    "minimumYearRepaymentFormatted": "$10,574.00"
  },
  "repayments": [
    {
      "rd": "31/1/2017",
      "ra": 8845
    }
  ],
  "inputs": {
    "incomeYearOfLoan": 2016,
    "fullTermOfAmalgamatedLoan": 1,
    "incomeYearOfEnquiring": 2017,
    "amalgamatedLoanNotPaidByEOIY": 10032,
    "repayments": null,
    "lodgement_date": "18/9/2016"
  },
  "idx": 445
}