{
  "id": "2023-09-04T17:41:35.543Z0.9973172342826269",
  "alert": "Start of result\nResult\n\nMinimum yearly repayment not met.\n\nThe amount of the loan not repaid at the end of income year 2013-14 is $56,813,208.02.\n\nThe private company may be taken to pay a dividend under Division 7A to the shareholder or shareholder's associate because the amount repaid during income year 2013-14 in relation to the amalgamated loan is less than the minimum yearly repayment required.\n\nInterest received by the private company must be included in the income tax return for 2013-14.\n\nMinimum yearly repayment\n\n$21,333,073.00\n\nBenchmark interest rate\n\n6.2%\n\nOpening balance:\n\nDate: 30/06/2013\n\nBalance: $56,813,208.02\n\nDays: 365\n\nInterest: $3,522,418.90\n\nTotal repayments\n\n$0\n\nTotal interest\n\n$3,522,418.90\n\nTotal principal\n\n$0\n\nClosing balance\n\nDate: 30/06/2014\n\nBalance: $56,813,208.02",
  "outputs": {
    "enquiryRateFormatted": "6.2%",
    "enquiryYearEndMinusOneDisplay": "30/06/2013",
    "amalgamatedLoanNotPaidByEOIYFormatted": "$56,813,208.02",
    "openingBalancePayDays": "365",
    "openingBalanceInterestFormatted": "$3,522,418.90",
    "totalAmountOfRepaymentFormatted": "$0",
    "totalInterestFormatted": "$3,522,418.90",
    "principalFormatted": "$0",
    "enquiryYearEndDisplay": "30/06/2014",
    "minimumYearRepaymentFormatted": "$21,333,073.00"
  },
  "repayments": [],
  "inputs": {
    "incomeYearOfLoan": 2012,
    "fullTermOfAmalgamatedLoan": 4,
    "incomeYearOfEnquiring": 2014,
    "amalgamatedLoanNotPaidByEOIY": 56813208.02588431,
    "repayments": null,
    "lodgement_date": null
  },
  "idx": 2472
}