{
  "id": "2023-09-05T20:41:23.611Z0.7064978977405514",
  "alert": "Start of result\nResult\n\nMinimum yearly repayment not met.\n\nThe amount of the loan not repaid at the end of income year 2017-18 is $8,540.00.\n\nThe private company may be taken to pay a dividend under Division 7A to the shareholder or shareholder's associate because the amount repaid during income year 2017-18 in relation to the amalgamated loan is less than the minimum yearly repayment required.\n\nInterest received by the private company must be included in the income tax return for 2017-18.\n\nMinimum yearly repayment\n\n$1,492.00\n\nBenchmark interest rate\n\n5.3%\n\nOpening balance:\n\nDate: 30/06/2017\n\nBalance: $8,540.00\n\nDays: 365\n\nInterest: $452.62\n\nTotal repayments\n\n$0\n\nTotal interest\n\n$452.62\n\nTotal principal\n\n$0\n\nClosing balance\n\nDate: 30/06/2018\n\nBalance: $8,540.00",
  "outputs": {
    "enquiryRateFormatted": "5.3%",
    "enquiryYearEndMinusOneDisplay": "30/06/2017",
    "amalgamatedLoanNotPaidByEOIYFormatted": "$8,540.00",
    "openingBalancePayDays": "365",
    "openingBalanceInterestFormatted": "$452.62",
    "totalAmountOfRepaymentFormatted": "$0",
    "totalInterestFormatted": "$452.62",
    "principalFormatted": "$0",
    "enquiryYearEndDisplay": "30/06/2018",
    "minimumYearRepaymentFormatted": "$1,492.00"
  },
  "repayments": [],
  "inputs": {
    "incomeYearOfLoan": 2017,
    "fullTermOfAmalgamatedLoan": 7,
    "incomeYearOfEnquiring": 2018,
    "amalgamatedLoanNotPaidByEOIY": 8540,
    "repayments": null,
    "lodgement_date": "8/4/2018"
  },
  "idx": 6925
}