{
  "id": "2023-10-31T19:21:19.102Z0.1344921394503008",
  "alert": "Start of result\nResult\n\nAmalgamated loan fully repaid.\n\nThe amalgamated loan has been paid in full.\u000bThe private company is not taken under Division 7A to pay a dividend to the shareholder or shareholder's associate.\n\nInterest received by the private company must be included in the income tax return for 2006-07.\n\nMinimum yearly repayment\n\n$635.00\n\nBenchmark interest rate\n\n7.55%\n\nOpening balance:\n\nDate: 30/06/2006\n\nBalance: $2,975.00\n\nDays: 183\n\nInterest: $112.61\n\nPayments\n\nDate: 31/12/2006\n\nAmount: $5,146.00\n\nBalance: $0\n\nDays: 182\n\nInterest: $0\n\n\n\n\nTotal repayments\n\n$5,146.00\n\nTotal interest\n\n$112.61\n\nTotal principal\n\n$5,033.39\n\nClosing balance\n\nDate: 30/06/2007\n\nBalance: $0",
  "outputs": {
    "enquiryRateFormatted": "7.55%",
    "enquiryYearEndMinusOneDisplay": "30/06/2006",
    "amalgamatedLoanNotPaidByEOIYFormatted": "$2,975.00",
    "openingBalancePayDays": "183",
    "openingBalanceInterestFormatted": "$112.61",
    "totalAmountOfRepaymentFormatted": "$5,146.00",
    "totalInterestFormatted": "$112.61",
    "principalFormatted": "$5,033.39",
    "enquiryYearEndDisplay": "30/06/2007",
    "minimumYearRepaymentFormatted": "$635.00",
    "loanAmountFormatted": "$0"
  },
  "repayments": [
    {
      "rd": "31/12/2006",
      "ra": 5146
    }
  ],
  "inputs": {
    "incomeYearOfLoan": 2005,
    "fullTermOfAmalgamatedLoan": 7,
    "incomeYearOfEnquiring": 2007,
    "amalgamatedLoanNotPaidByEOIY": 2975,
    "repayments": null,
    "lodgement_date": null
  },
  "idx": 5347
}