{
  "id": "2023-09-05T00:27:26.809Z0.5317499856130425",
  "alert": "Start of result\nResult\n\nMinimum yearly repayment not met.\n\nThe amount of the loan not repaid at the end of income year 2004-05 is $44.36.\n\nThe private company may be taken to pay a dividend under Division 7A to the shareholder or shareholder's associate because the amount repaid during income year 2004-05 in relation to the amalgamated loan is less than the minimum yearly repayment required.\n\nInterest received by the private company must be included in the income tax return for 2004-05.\n\nMinimum yearly repayment\n\n$25.00\n\nBenchmark interest rate\n\n7.05%\n\nOpening balance:\n\nDate: 30/06/2004\n\nBalance: $44.36\n\nDays: 365\n\nInterest: $3.13\n\nTotal repayments\n\n$0\n\nTotal interest\n\n$3.13\n\nTotal principal\n\n$0\n\nClosing balance\n\nDate: 30/06/2005\n\nBalance: $44.36",
  "outputs": {
    "enquiryRateFormatted": "7.05%",
    "enquiryYearEndMinusOneDisplay": "30/06/2004",
    "amalgamatedLoanNotPaidByEOIYFormatted": "$44.36",
    "openingBalancePayDays": "365",
    "openingBalanceInterestFormatted": "$3.13",
    "totalAmountOfRepaymentFormatted": "$0",
    "totalInterestFormatted": "$3.13",
    "principalFormatted": "$0",
    "enquiryYearEndDisplay": "30/06/2005",
    "minimumYearRepaymentFormatted": "$25.00"
  },
  "repayments": [],
  "inputs": {
    "incomeYearOfLoan": 1999,
    "fullTermOfAmalgamatedLoan": 7,
    "incomeYearOfEnquiring": 2005,
    "amalgamatedLoanNotPaidByEOIY": 44.36476892821034,
    "repayments": null,
    "lodgement_date": null
  },
  "idx": 6641
}