{
  "id": "2023-09-05T22:40:50.608Z0.1562211103799458",
  "alert": "Start of result\nResult\n\nMinimum yearly repayment met.\n\nThe amount of the loan not repaid at the end of income year 2016-17 is $39.67.\n\nThe amalgamated loan will not be taken to be a dividend because the total repayments made are equal to or greater than the minimum yearly repayment required for income year 2016-17.\n\nInterest received by the private company must be included in the income tax return for 2016-17.\n\nMinimum yearly repayment\n\n$351.00\n\nBenchmark interest rate\n\n5.4%\n\nOpening balance:\n\nDate: 30/06/2016\n\nBalance: $2,001.00\n\nDays: 134\n\nInterest: $39.67\n\nPayments\n\nDate: 12/11/2016\n\nAmount: $2,001.00\n\nBalance: $0\n\nDays: 231\n\nInterest: $0\n\n\n\n\nTotal repayments\n\n$2,001.00\n\nTotal interest\n\n$39.67\n\nTotal principal\n\n$1,961.33\n\nClosing balance\n\nDate: 30/06/2017\n\nBalance: $39.67",
  "outputs": {
    "enquiryRateFormatted": "5.4%",
    "enquiryYearEndMinusOneDisplay": "30/06/2016",
    "amalgamatedLoanNotPaidByEOIYFormatted": "$2,001.00",
    "openingBalancePayDays": "134",
    "openingBalanceInterestFormatted": "$39.67",
    "totalAmountOfRepaymentFormatted": "$2,001.00",
    "totalInterestFormatted": "$39.67",
    "principalFormatted": "$1,961.33",
    "enquiryYearEndDisplay": "30/06/2017",
    "minimumYearRepaymentFormatted": "$351.00"
  },
  "repayments": [
    {
      "rd": "12/11/2016",
      "ra": 2001
    }
  ],
  "inputs": {
    "incomeYearOfLoan": 2016,
    "fullTermOfAmalgamatedLoan": 7,
    "incomeYearOfEnquiring": 2017,
    "amalgamatedLoanNotPaidByEOIY": 2001,
    "repayments": null,
    "lodgement_date": "9/8/2016"
  },
  "idx": 5206
}