{
  "id": "2023-10-31T17:20:53.046Z0.07787042856565829",
  "alert": "Start of result\nResult\n\nMinimum yearly repayment met.\n\nThe amount of the loan not repaid at the end of income year 2020-21 is $6,138.21.\n\n\u000b\n\nThe amalgamated loan will not be taken to be a dividend because the total repayments made are equal to or greater than the minimum yearly repayment required for income year 2020-21.\n\nInterest received by the private company must be included in the income tax return for 2020-21.\n\nMinimum yearly repayment\n\n$2,333.00\n\nBenchmark interest rate\n\n4.52%\n\nOpening balance:\n\nDate: 30/06/2020\n\nBalance: $8,366.00\n\nDays: 342\n\nInterest: $354.31\n\nPayments\n\nDate: 08/06/2021\n\nAmount: $946.00\n\nBalance: $7,420.00\n\nDays: 17\n\nInterest: $15.62\n\n\n\n\nDate: 25/06/2021\n\nAmount: $1,656.00\n\nBalance: $5,764.00\n\nDays: 6\n\nInterest: $4.28\n\n\n\n\nTotal repayments\n\n$2,602.00\n\nTotal interest\n\n$374.21\n\nTotal principal\n\n$2,227.79\n\nClosing balance\n\nDate: 30/06/2021\n\nBalance: $6,138.21",
  "outputs": {
    "enquiryRateFormatted": "4.52%",
    "enquiryYearEndMinusOneDisplay": "30/06/2020",
    "amalgamatedLoanNotPaidByEOIYFormatted": "$8,366.00",
    "openingBalancePayDays": "342",
    "openingBalanceInterestFormatted": "$354.31",
    "totalAmountOfRepaymentFormatted": "$2,602.00",
    "totalInterestFormatted": "$374.21",
    "principalFormatted": "$2,227.79",
    "enquiryYearEndDisplay": "30/06/2021",
    "minimumYearRepaymentFormatted": "$2,333.00",
    "loanAmountFormatted": "$6,138.21"
  },
  "repayments": [
    {
      "rd": "8/6/2021",
      "ra": 946
    },
    {
      "rd": "25/6/2021",
      "ra": 1656
    }
  ],
  "inputs": {
    "incomeYearOfLoan": 2019,
    "fullTermOfAmalgamatedLoan": 5,
    "incomeYearOfEnquiring": 2021,
    "amalgamatedLoanNotPaidByEOIY": 8366,
    "repayments": null,
    "lodgement_date": null
  },
  "idx": 1151
}