{
  "id": "2023-09-04T22:18:38.404Z0.7863438503996376",
  "alert": "Start of result\nResult\n\nMinimum yearly repayment not met.\n\nThe amount of the loan not repaid at the end of income year 2004-05 is $5,129,280.35.\n\nThe private company may be taken to pay a dividend under Division 7A to the shareholder or shareholder's associate because the amount repaid during income year 2004-05 in relation to the amalgamated loan is less than the minimum yearly repayment required.\n\nInterest received by the private company must be included in the income tax return for 2004-05.\n\nMinimum yearly repayment\n\n$1,956,307.00\n\nBenchmark interest rate\n\n7.05%\n\nOpening balance:\n\nDate: 30/06/2004\n\nBalance: $5,129,280.35\n\nDays: 365\n\nInterest: $361,614.26\n\nTotal repayments\n\n$0\n\nTotal interest\n\n$361,614.26\n\nTotal principal\n\n$0\n\nClosing balance\n\nDate: 30/06/2005\n\nBalance: $5,129,280.35",
  "outputs": {
    "enquiryRateFormatted": "7.05%",
    "enquiryYearEndMinusOneDisplay": "30/06/2004",
    "amalgamatedLoanNotPaidByEOIYFormatted": "$5,129,280.35",
    "openingBalancePayDays": "365",
    "openingBalanceInterestFormatted": "$361,614.26",
    "totalAmountOfRepaymentFormatted": "$0",
    "totalInterestFormatted": "$361,614.26",
    "principalFormatted": "$0",
    "enquiryYearEndDisplay": "30/06/2005",
    "minimumYearRepaymentFormatted": "$1,956,307.00"
  },
  "repayments": [],
  "inputs": {
    "incomeYearOfLoan": 2001,
    "fullTermOfAmalgamatedLoan": 6,
    "incomeYearOfEnquiring": 2005,
    "amalgamatedLoanNotPaidByEOIY": 5129280.356451312,
    "repayments": null,
    "lodgement_date": null
  },
  "idx": 681
}