{
  "id": "2023-09-04T22:25:05.093Z0.7869545964085221",
  "alert": "Start of result\nResult\n\nMinimum yearly repayment not met.\n\nThe amount of the loan not repaid at the end of income year 2000-01 is $80,010,623.86.\n\nThe private company may be taken to pay a dividend under Division 7A to the shareholder or shareholder's associate because the amount repaid during income year 2000-01 in relation to the amalgamated loan is less than the minimum yearly repayment required.\n\nInterest received by the private company must be included in the income tax return for 2000-01.\n\nMinimum yearly repayment\n\n$19,933,658.00\n\nBenchmark interest rate\n\n7.8%\n\nOpening balance:\n\nDate: 30/06/2000\n\nBalance: $80,010,623.86\n\nDays: 365\n\nInterest: $6,240,828.66\n\nTotal repayments\n\n$0\n\nTotal interest\n\n$6,240,828.66\n\nTotal principal\n\n$0\n\nClosing balance\n\nDate: 30/06/2001\n\nBalance: $80,010,623.86",
  "outputs": {
    "enquiryRateFormatted": "7.8%",
    "enquiryYearEndMinusOneDisplay": "30/06/2000",
    "amalgamatedLoanNotPaidByEOIYFormatted": "$80,010,623.86",
    "openingBalancePayDays": "365",
    "openingBalanceInterestFormatted": "$6,240,828.66",
    "totalAmountOfRepaymentFormatted": "$0",
    "totalInterestFormatted": "$6,240,828.66",
    "principalFormatted": "$0",
    "enquiryYearEndDisplay": "30/06/2001",
    "minimumYearRepaymentFormatted": "$19,933,658.00"
  },
  "repayments": [],
  "inputs": {
    "incomeYearOfLoan": 2000,
    "fullTermOfAmalgamatedLoan": 5,
    "incomeYearOfEnquiring": 2001,
    "amalgamatedLoanNotPaidByEOIY": 80010623.86337084,
    "repayments": null,
    "lodgement_date": "9/10/2000"
  },
  "idx": 894
}