{
  "id": "2023-09-06T11:55:07.712Z0.8580932440348497",
  "alert": "Start of result\nResult\n\nMinimum yearly repayment met.\n\nThe amount of the loan not repaid at the end of income year 2009-10 is $4.33.\n\nThe amalgamated loan will not be taken to be a dividend because the total repayments made are equal to or greater than the minimum yearly repayment required for income year 2009-10.\n\nInterest received by the private company must be included in the income tax return for 2009-10.\n\nMinimum yearly repayment\n\n$25.00\n\nBenchmark interest rate\n\n5.75%\n\nOpening balance:\n\nDate: 30/06/2009\n\nBalance: $123.67\n\nDays: 222\n\nInterest: $4.33\n\nPayments\n\nDate: 08/02/2010\n\nAmount: $123.67\n\nBalance: $0\n\nDays: 143\n\nInterest: $0\n\n\n\n\nTotal repayments\n\n$123.67\n\nTotal interest\n\n$4.33\n\nTotal principal\n\n$119.34\n\nClosing balance\n\nDate: 30/06/2010\n\nBalance: $4.33",
  "outputs": {
    "enquiryRateFormatted": "5.75%",
    "enquiryYearEndMinusOneDisplay": "30/06/2009",
    "amalgamatedLoanNotPaidByEOIYFormatted": "$123.67",
    "openingBalancePayDays": "222",
    "openingBalanceInterestFormatted": "$4.33",
    "totalAmountOfRepaymentFormatted": "$123.67",
    "totalInterestFormatted": "$4.33",
    "principalFormatted": "$119.34",
    "enquiryYearEndDisplay": "30/06/2010",
    "minimumYearRepaymentFormatted": "$25.00"
  },
  "repayments": [
    {
      "rd": "8/2/2010",
      "ra": 123.6772574156887
    }
  ],
  "inputs": {
    "incomeYearOfLoan": 2008,
    "fullTermOfAmalgamatedLoan": 7,
    "incomeYearOfEnquiring": 2010,
    "amalgamatedLoanNotPaidByEOIY": 123.67725741568874,
    "repayments": null,
    "lodgement_date": null
  },
  "idx": 5913
}