{
  "id": "2023-09-04T22:20:36.410Z0.5119272192809261",
  "alert": "Start of result\nResult\n\nMinimum yearly repayment not met.\n\nThe amount of the loan not repaid at the end of income year 2000-01 is $13,534,434.07.\n\nThe private company may be taken to pay a dividend under Division 7A to the shareholder or shareholder's associate because the amount repaid during income year 2000-01 in relation to the amalgamated loan is less than the minimum yearly repayment required.\n\nInterest received by the private company must be included in the income tax return for 2000-01.\n\nMinimum yearly repayment\n\n$7,564,933.00\n\nBenchmark interest rate\n\n7.8%\n\nOpening balance:\n\nDate: 30/06/2000\n\nBalance: $13,534,434.07\n\nDays: 0\n\nInterest: $0\n\nPayments\n\nDate: 01/07/2000\n\nAmount: $7,072.00\n\nBalance: $13,527,362.07\n\nDays: 365\n\nInterest: $1,055,134.24\n\n\n\n\nTotal repayments\n\n$7,072.00\n\nTotal interest\n\n$1,055,134.24\n\nTotal principal\n\n$0\n\nClosing balance\n\nDate: 30/06/2001\n\nBalance: $13,534,434.07",
  "outputs": {
    "enquiryRateFormatted": "7.8%",
    "enquiryYearEndMinusOneDisplay": "30/06/2000",
    "amalgamatedLoanNotPaidByEOIYFormatted": "$13,534,434.07",
    "openingBalancePayDays": "0",
    "openingBalanceInterestFormatted": "$0",
    "totalAmountOfRepaymentFormatted": "$7,072.00",
    "totalInterestFormatted": "$1,055,134.24",
    "principalFormatted": "$0",
    "enquiryYearEndDisplay": "30/06/2001",
    "minimumYearRepaymentFormatted": "$7,564,933.00"
  },
  "repayments": [
    {
      "rd": "1/7/2000",
      "ra": 7072
    }
  ],
  "inputs": {
    "incomeYearOfLoan": 2000,
    "fullTermOfAmalgamatedLoan": 2,
    "incomeYearOfEnquiring": 2001,
    "amalgamatedLoanNotPaidByEOIY": 13534434.072824396,
    "repayments": null,
    "lodgement_date": "17/1/2001"
  },
  "idx": 749
}