{
  "id": "2023-09-06T03:38:05.866Z0.08887403136981797",
  "alert": "Start of result\nResult\n\nMinimum yearly repayment met.\n\nThe amount of the loan not repaid at the end of income year 2017-18 is $0.90.\n\nThe amalgamated loan will not be taken to be a dividend because the total repayments made are equal to or greater than the minimum yearly repayment required for income year 2017-18.\n\nInterest received by the private company must be included in the income tax return for 2017-18.\n\nMinimum yearly repayment\n\n$46.00\n\nBenchmark interest rate\n\n5.3%\n\nOpening balance:\n\nDate: 30/06/2017\n\nBalance: $123.63\n\nDays: 50\n\nInterest: $0.90\n\nPayments\n\nDate: 20/08/2017\n\nAmount: $123.63\n\nBalance: $0\n\nDays: 315\n\nInterest: $0\n\n\n\n\nTotal repayments\n\n$123.63\n\nTotal interest\n\n$0.90\n\nTotal principal\n\n$122.73\n\nClosing balance\n\nDate: 30/06/2018\n\nBalance: $0.90",
  "outputs": {
    "enquiryRateFormatted": "5.3%",
    "enquiryYearEndMinusOneDisplay": "30/06/2017",
    "amalgamatedLoanNotPaidByEOIYFormatted": "$123.63",
    "openingBalancePayDays": "50",
    "openingBalanceInterestFormatted": "$0.90",
    "totalAmountOfRepaymentFormatted": "$123.63",
    "totalInterestFormatted": "$0.90",
    "principalFormatted": "$122.73",
    "enquiryYearEndDisplay": "30/06/2018",
    "minimumYearRepaymentFormatted": "$46.00"
  },
  "repayments": [
    {
      "rd": "20/8/2017",
      "ra": 123.63890067012017
    }
  ],
  "inputs": {
    "incomeYearOfLoan": 2013,
    "fullTermOfAmalgamatedLoan": 7,
    "incomeYearOfEnquiring": 2018,
    "amalgamatedLoanNotPaidByEOIY": 123.63890067012017,
    "repayments": null,
    "lodgement_date": null
  },
  "idx": 4796
}