{
  "id": "2023-09-07T01:37:04.398Z0.850895396711298",
  "alert": "Start of result\nResult\n\nMinimum yearly repayment met.\n\nThe amount of the loan not repaid at the end of income year 2000-01 is $0.36.\n\nThe amalgamated loan will not be taken to be a dividend because the total repayments made are equal to or greater than the minimum yearly repayment required for income year 2000-01.\n\nInterest received by the private company must be included in the income tax return for 2000-01.\n\nMinimum yearly repayment\n\n$52.00\n\nBenchmark interest rate\n\n7.8%\n\nOpening balance:\n\nDate: 30/06/2000\n\nBalance: $92.63\n\nDays: 18\n\nInterest: $0.36\n\nPayments\n\nDate: 19/07/2000\n\nAmount: $92.63\n\nBalance: $0\n\nDays: 347\n\nInterest: $0\n\n\n\n\nTotal repayments\n\n$92.63\n\nTotal interest\n\n$0.36\n\nTotal principal\n\n$92.27\n\nClosing balance\n\nDate: 30/06/2001\n\nBalance: $0.36",
  "outputs": {
    "enquiryRateFormatted": "7.8%",
    "enquiryYearEndMinusOneDisplay": "30/06/2000",
    "amalgamatedLoanNotPaidByEOIYFormatted": "$92.63",
    "openingBalancePayDays": "18",
    "openingBalanceInterestFormatted": "$0.36",
    "totalAmountOfRepaymentFormatted": "$92.63",
    "totalInterestFormatted": "$0.36",
    "principalFormatted": "$92.27",
    "enquiryYearEndDisplay": "30/06/2001",
    "minimumYearRepaymentFormatted": "$52.00"
  },
  "repayments": [
    {
      "rd": "19/7/2000",
      "ra": 92.63102720556617
    }
  ],
  "inputs": {
    "incomeYearOfLoan": 1999,
    "fullTermOfAmalgamatedLoan": 3,
    "incomeYearOfEnquiring": 2001,
    "amalgamatedLoanNotPaidByEOIY": 92.63102720556617,
    "repayments": null,
    "lodgement_date": null
  },
  "idx": 1840
}