{
  "id": "2023-09-07T03:37:18.897Z0.2513844636490081",
  "alert": "Start of result\nResult\n\nMinimum yearly repayment met.\n\nThe amount of the loan not repaid at the end of income year 1999-00 is $1.60.\n\nThe amalgamated loan will not be taken to be a dividend because the total repayments made are equal to or greater than the minimum yearly repayment required for income year 1999-00.\n\nInterest received by the private company must be included in the income tax return for 1999-00.\n\nMinimum yearly repayment\n\n$15.00\n\nBenchmark interest rate\n\n6.5%\n\nOpening balance:\n\nDate: 30/06/1999\n\nBalance: $40.68\n\nDays: 222\n\nInterest: $1.60\n\nPayments\n\nDate: 08/02/2000\n\nAmount: $40.68\n\nBalance: $0\n\nDays: 144\n\nInterest: $0\n\n\n\n\nTotal repayments\n\n$40.68\n\nTotal interest\n\n$1.60\n\nTotal principal\n\n$39.08\n\nClosing balance\n\nDate: 30/06/2000\n\nBalance: $1.60",
  "outputs": {
    "enquiryRateFormatted": "6.5%",
    "enquiryYearEndMinusOneDisplay": "30/06/1999",
    "amalgamatedLoanNotPaidByEOIYFormatted": "$40.68",
    "openingBalancePayDays": "222",
    "openingBalanceInterestFormatted": "$1.60",
    "totalAmountOfRepaymentFormatted": "$40.68",
    "totalInterestFormatted": "$1.60",
    "principalFormatted": "$39.08",
    "enquiryYearEndDisplay": "30/06/2000",
    "minimumYearRepaymentFormatted": "$15.00"
  },
  "repayments": [
    {
      "rd": "8/2/2000",
      "ra": 40.68880771289696
    }
  ],
  "inputs": {
    "incomeYearOfLoan": 1998,
    "fullTermOfAmalgamatedLoan": 4,
    "incomeYearOfEnquiring": 2000,
    "amalgamatedLoanNotPaidByEOIY": 40.68880771289653,
    "repayments": null,
    "lodgement_date": null
  },
  "idx": 737
}