{
  "id": "2023-10-31T20:14:43.619Z0.3720571636686001",
  "alert": "Start of result\nResult\n\nAmalgamated loan fully repaid.\n\nThe amalgamated loan has been paid in full.\u000bThe private company is not taken under Division 7A to pay a dividend to the shareholder or shareholder's associate.\n\nInterest received by the private company must be included in the income tax return for 2003-04.\n\nMinimum yearly repayment\n\n$1,834.00\n\nBenchmark interest rate\n\n6.55%\n\nOpening balance:\n\nDate: 30/06/2003\n\nBalance: $3,337.00\n\nDays: 271\n\nInterest: $161.84\n\nPayments\n\nDate: 28/03/2004\n\nAmount: $5,907.00\n\nBalance: $0\n\nDays: 95\n\nInterest: $0\n\n\n\n\nTotal repayments\n\n$5,907.00\n\nTotal interest\n\n$161.84\n\nTotal principal\n\n$5,745.16\n\nClosing balance\n\nDate: 30/06/2004\n\nBalance: $0",
  "outputs": {
    "enquiryRateFormatted": "6.55%",
    "enquiryYearEndMinusOneDisplay": "30/06/2003",
    "amalgamatedLoanNotPaidByEOIYFormatted": "$3,337.00",
    "openingBalancePayDays": "271",
    "openingBalanceInterestFormatted": "$161.84",
    "totalAmountOfRepaymentFormatted": "$5,907.00",
    "totalInterestFormatted": "$161.84",
    "principalFormatted": "$5,745.16",
    "enquiryYearEndDisplay": "30/06/2004",
    "minimumYearRepaymentFormatted": "$1,834.00",
    "loanAmountFormatted": "$0"
  },
  "repayments": [
    {
      "rd": "28/3/2004",
      "ra": 5907
    }
  ],
  "inputs": {
    "incomeYearOfLoan": 2001,
    "fullTermOfAmalgamatedLoan": 4,
    "incomeYearOfEnquiring": 2004,
    "amalgamatedLoanNotPaidByEOIY": 3337,
    "repayments": null,
    "lodgement_date": null
  },
  "idx": 6302
}