{
  "id": "2023-10-31T18:30:44.881Z0.9984982337898497",
  "alert": "Start of result\nResult\n\nMinimum yearly repayment not met.\n\nThe amount of the loan not repaid at the end of income year 2012-13 is $7,615.79.\n\nThe private company may be taken to pay a dividend under Division 7A to the shareholder or shareholder's associate because the amount repaid during income year 2012-13 in relation to the amalgamated loan is less than the minimum yearly repayment required.\n\nInterest received by the private company must be included in the income tax return for 2012-13.\n\nMinimum yearly repayment\n\n$6,168.00\n\nBenchmark interest rate\n\n7.05%\n\nOpening balance:\n\nDate: 30/06/2012\n\nBalance: $11,144.00\n\nDays: 302\n\nInterest: $650.05\n\nPayments\n\nDate: 29/04/2013\n\nAmount: $4,262.00\n\nBalance: $6,882.00\n\nDays: 63\n\nInterest: $83.74\n\n\n\n\nTotal repayments\n\n$4,262.00\n\nTotal interest\n\n$733.79\n\nTotal principal\n\n$3,528.21\n\nClosing balance\n\nDate: 30/06/2013\n\nBalance: $7,615.79",
  "outputs": {
    "enquiryRateFormatted": "7.05%",
    "enquiryYearEndMinusOneDisplay": "30/06/2012",
    "amalgamatedLoanNotPaidByEOIYFormatted": "$11,144.00",
    "openingBalancePayDays": "302",
    "openingBalanceInterestFormatted": "$650.05",
    "totalAmountOfRepaymentFormatted": "$4,262.00",
    "totalInterestFormatted": "$733.79",
    "principalFormatted": "$3,528.21",
    "enquiryYearEndDisplay": "30/06/2013",
    "minimumYearRepaymentFormatted": "$6,168.00",
    "loanAmountFormatted": "$7,615.79"
  },
  "repayments": [
    {
      "rd": "29/4/2013",
      "ra": 4262
    }
  ],
  "inputs": {
    "incomeYearOfLoan": 2009,
    "fullTermOfAmalgamatedLoan": 5,
    "incomeYearOfEnquiring": 2013,
    "amalgamatedLoanNotPaidByEOIY": 11144,
    "repayments": null,
    "lodgement_date": null
  },
  "idx": 4099
}