{
  "id": "2023-09-04T20:49:21.349Z0.3811271903455111",
  "alert": "Start of result\nResult\n\nMinimum yearly repayment not met.\n\nThe amount of the loan not repaid at the end of income year 2011-12 is $87,787,669.79.\n\nThe private company may be taken to pay a dividend under Division 7A to the shareholder or shareholder's associate because the amount repaid during income year 2011-12 in relation to the amalgamated loan is less than the minimum yearly repayment required.\n\nInterest received by the private company must be included in the income tax return for 2011-12.\n\nMinimum yearly repayment\n\n$49,090,225.00\n\nBenchmark interest rate\n\n7.8%\n\nOpening balance:\n\nDate: 30/06/2011\n\nBalance: $87,787,669.79\n\nDays: 0\n\nInterest: $0\n\nPayments\n\nDate: 01/07/2011\n\nAmount: $6,161.00\n\nBalance: $87,781,508.79\n\nDays: 366\n\nInterest: $6,846,957.69\n\n\n\n\nTotal repayments\n\n$6,161.00\n\nTotal interest\n\n$6,846,957.69\n\nTotal principal\n\n$0\n\nClosing balance\n\nDate: 30/06/2012\n\nBalance: $87,787,669.79",
  "outputs": {
    "enquiryRateFormatted": "7.8%",
    "enquiryYearEndMinusOneDisplay": "30/06/2011",
    "amalgamatedLoanNotPaidByEOIYFormatted": "$87,787,669.79",
    "openingBalancePayDays": "0",
    "openingBalanceInterestFormatted": "$0",
    "totalAmountOfRepaymentFormatted": "$6,161.00",
    "totalInterestFormatted": "$6,846,957.69",
    "principalFormatted": "$0",
    "enquiryYearEndDisplay": "30/06/2012",
    "minimumYearRepaymentFormatted": "$49,090,225.00"
  },
  "repayments": [
    {
      "rd": "1/7/2011",
      "ra": 6161
    }
  ],
  "inputs": {
    "incomeYearOfLoan": 2011,
    "fullTermOfAmalgamatedLoan": 2,
    "incomeYearOfEnquiring": 2012,
    "amalgamatedLoanNotPaidByEOIY": 87787669.79332966,
    "repayments": null,
    "lodgement_date": "30/6/2012"
  },
  "idx": 83
}