{
  "id": "2023-10-31T17:30:03.226Z0.7689501675630683",
  "alert": "Start of result\nResult\n\nMinimum yearly repayment not met.\n\nThe amount of the loan not repaid at the end of income year 2017-18 is $4.51.\n\nThe private company may be taken to pay a dividend under Division 7A to the shareholder or shareholder's associate because the amount repaid during income year 2017-18 in relation to the amalgamated loan is less than the minimum yearly repayment required.\n\nInterest received by the private company must be included in the income tax return for 2017-18.\n\nMinimum yearly repayment\n\n$1.00\n\nBenchmark interest rate\n\n5.3%\n\nOpening balance:\n\nDate: 30/06/2017\n\nBalance: $4.51\n\nDays: 365\n\nInterest: $0.24\n\nTotal repayments\n\n$0\n\nTotal interest\n\n$0.24\n\nTotal principal\n\n$0\n\nClosing balance\n\nDate: 30/06/2018\n\nBalance: $4.51",
  "outputs": {
    "enquiryRateFormatted": "5.3%",
    "enquiryYearEndMinusOneDisplay": "30/06/2017",
    "amalgamatedLoanNotPaidByEOIYFormatted": "$4.51",
    "openingBalancePayDays": "365",
    "openingBalanceInterestFormatted": "$0.24",
    "totalAmountOfRepaymentFormatted": "$0",
    "totalInterestFormatted": "$0.24",
    "principalFormatted": "$0",
    "enquiryYearEndDisplay": "30/06/2018",
    "minimumYearRepaymentFormatted": "$1.00",
    "loanAmountFormatted": "$4.51"
  },
  "repayments": [],
  "inputs": {
    "incomeYearOfLoan": 2017,
    "fullTermOfAmalgamatedLoan": 6,
    "incomeYearOfEnquiring": 2018,
    "amalgamatedLoanNotPaidByEOIY": 4.51487122300039,
    "repayments": null,
    "lodgement_date": "27/5/2018"
  },
  "idx": 1695
}