{
  "id": "2023-09-04T21:40:20.758Z0.6631039811609196",
  "alert": "Start of result\nResult\n\nMinimum yearly repayment not met.\n\nThe amount of the loan not repaid at the end of income year 2005-06 is $5,675.10.\n\nThe private company may be taken to pay a dividend under Division 7A to the shareholder or shareholder's associate because the amount repaid during income year 2005-06 in relation to the amalgamated loan is less than the minimum yearly repayment required.\n\nInterest received by the private company must be included in the income tax return for 2005-06.\n\nMinimum yearly repayment\n\n$4,768.00\n\nBenchmark interest rate\n\n7.3%\n\nOpening balance:\n\nDate: 30/06/2005\n\nBalance: $8,585.00\n\nDays: 0\n\nInterest: $0\n\nPayments\n\nDate: 01/07/2005\n\nAmount: $3,296.00\n\nBalance: $5,289.00\n\nDays: 365\n\nInterest: $386.10\n\n\n\n\nTotal repayments\n\n$3,296.00\n\nTotal interest\n\n$386.10\n\nTotal principal\n\n$2,909.90\n\nClosing balance\n\nDate: 30/06/2006\n\nBalance: $5,675.10",
  "outputs": {
    "enquiryRateFormatted": "7.3%",
    "enquiryYearEndMinusOneDisplay": "30/06/2005",
    "amalgamatedLoanNotPaidByEOIYFormatted": "$8,585.00",
    "openingBalancePayDays": "0",
    "openingBalanceInterestFormatted": "$0",
    "totalAmountOfRepaymentFormatted": "$3,296.00",
    "totalInterestFormatted": "$386.10",
    "principalFormatted": "$2,909.90",
    "enquiryYearEndDisplay": "30/06/2006",
    "minimumYearRepaymentFormatted": "$4,768.00"
  },
  "repayments": [
    {
      "rd": "1/7/2005",
      "ra": 3296
    }
  ],
  "inputs": {
    "incomeYearOfLoan": 2005,
    "fullTermOfAmalgamatedLoan": 2,
    "incomeYearOfEnquiring": 2006,
    "amalgamatedLoanNotPaidByEOIY": 8585,
    "repayments": null,
    "lodgement_date": "1/7/2005"
  },
  "idx": 1544
}