{
  "id": "2023-09-06T05:27:21.896Z0.4573363776087278",
  "alert": "Start of result\nResult\n\nMinimum yearly repayment not met.\n\nThe amount of the loan not repaid at the end of income year 2012-13 is $112.09.\n\nThe private company may be taken to pay a dividend under Division 7A to the shareholder or shareholder's associate because the amount repaid during income year 2012-13 in relation to the amalgamated loan is less than the minimum yearly repayment required.\n\nInterest received by the private company must be included in the income tax return for 2012-13.\n\nMinimum yearly repayment\n\n$21.00\n\nBenchmark interest rate\n\n7.05%\n\nOpening balance:\n\nDate: 30/06/2012\n\nBalance: $112.09\n\nDays: 365\n\nInterest: $7.90\n\nTotal repayments\n\n$0\n\nTotal interest\n\n$7.90\n\nTotal principal\n\n$0\n\nClosing balance\n\nDate: 30/06/2013\n\nBalance: $112.09",
  "outputs": {
    "enquiryRateFormatted": "7.05%",
    "enquiryYearEndMinusOneDisplay": "30/06/2012",
    "amalgamatedLoanNotPaidByEOIYFormatted": "$112.09",
    "openingBalancePayDays": "365",
    "openingBalanceInterestFormatted": "$7.90",
    "totalAmountOfRepaymentFormatted": "$0",
    "totalInterestFormatted": "$7.90",
    "principalFormatted": "$0",
    "enquiryYearEndDisplay": "30/06/2013",
    "minimumYearRepaymentFormatted": "$21.00"
  },
  "repayments": [],
  "inputs": {
    "incomeYearOfLoan": 2012,
    "fullTermOfAmalgamatedLoan": 7,
    "incomeYearOfEnquiring": 2013,
    "amalgamatedLoanNotPaidByEOIY": 112.09706938125912,
    "repayments": null,
    "lodgement_date": "14/7/2012"
  },
  "idx": 2246
}