{
  "id": "2023-09-04T20:54:21.095Z0.627599833229423",
  "alert": "Start of result\nResult\n\nMinimum yearly repayment not met.\n\nThe amount of the loan not repaid at the end of income year 2010-11 is $3,228.44.\n\nThe private company may be taken to pay a dividend under Division 7A to the shareholder or shareholder's associate because the amount repaid during income year 2010-11 in relation to the amalgamated loan is less than the minimum yearly repayment required.\n\nInterest received by the private company must be included in the income tax return for 2010-11.\n\nMinimum yearly repayment\n\n$9,226.00\n\nBenchmark interest rate\n\n7.4%\n\nOpening balance:\n\nDate: 30/06/2010\n\nBalance: $8,590.00\n\nDays: 0\n\nInterest: $0\n\nPayments\n\nDate: 01/07/2010\n\nAmount: $5,584.00\n\nBalance: $3,006.00\n\nDays: 365\n\nInterest: $222.44\n\n\n\n\nTotal repayments\n\n$5,584.00\n\nTotal interest\n\n$222.44\n\nTotal principal\n\n$5,361.56\n\nClosing balance\n\nDate: 30/06/2011\n\nBalance: $3,228.44",
  "outputs": {
    "enquiryRateFormatted": "7.4%",
    "enquiryYearEndMinusOneDisplay": "30/06/2010",
    "amalgamatedLoanNotPaidByEOIYFormatted": "$8,590.00",
    "openingBalancePayDays": "0",
    "openingBalanceInterestFormatted": "$0",
    "totalAmountOfRepaymentFormatted": "$5,584.00",
    "totalInterestFormatted": "$222.44",
    "principalFormatted": "$5,361.56",
    "enquiryYearEndDisplay": "30/06/2011",
    "minimumYearRepaymentFormatted": "$9,226.00"
  },
  "repayments": [
    {
      "rd": "1/7/2010",
      "ra": 5584
    }
  ],
  "inputs": {
    "incomeYearOfLoan": 2010,
    "fullTermOfAmalgamatedLoan": 1,
    "incomeYearOfEnquiring": 2011,
    "amalgamatedLoanNotPaidByEOIY": 8590,
    "repayments": null,
    "lodgement_date": "1/7/2010"
  },
  "idx": 266
}