{
  "id": "2023-09-04T17:13:33.799Z0.6985341082967509",
  "alert": "Start of result\nResult\n\nMinimum yearly repayment met.\n\nThe amount of the loan not repaid at the end of income year 2015-16 is $2,569.82.\n\nThe amalgamated loan will not be taken to be a dividend because the total repayments made are equal to or greater than the minimum yearly repayment required for income year 2015-16.\n\nInterest received by the private company must be included in the income tax return for 2015-16.\n\nMinimum yearly repayment\n\n$3,857.00\n\nBenchmark interest rate\n\n5.45%\n\nOpening balance:\n\nDate: 30/06/2015\n\nBalance: $10,416.00\n\nDays: 0\n\nInterest: $0\n\nPayments\n\nDate: 01/07/2015\n\nAmount: $7,979.00\n\nBalance: $2,437.00\n\nDays: 366\n\nInterest: $132.82\n\n\n\n\nTotal repayments\n\n$7,979.00\n\nTotal interest\n\n$132.82\n\nTotal principal\n\n$7,846.18\n\nClosing balance\n\nDate: 30/06/2016\n\nBalance: $2,569.82",
  "outputs": {
    "enquiryRateFormatted": "5.45%",
    "enquiryYearEndMinusOneDisplay": "30/06/2015",
    "amalgamatedLoanNotPaidByEOIYFormatted": "$10,416.00",
    "openingBalancePayDays": "0",
    "openingBalanceInterestFormatted": "$0",
    "totalAmountOfRepaymentFormatted": "$7,979.00",
    "totalInterestFormatted": "$132.82",
    "principalFormatted": "$7,846.18",
    "enquiryYearEndDisplay": "30/06/2016",
    "minimumYearRepaymentFormatted": "$3,857.00"
  },
  "repayments": [
    {
      "rd": "1/7/2015",
      "ra": 7979
    }
  ],
  "inputs": {
    "incomeYearOfLoan": 2014,
    "fullTermOfAmalgamatedLoan": 4,
    "incomeYearOfEnquiring": 2016,
    "amalgamatedLoanNotPaidByEOIY": 10416,
    "repayments": null,
    "lodgement_date": null
  },
  "idx": 1867
}