{
  "id": "2023-09-04T16:30:58.903Z0.17882399242496771",
  "alert": "Start of result\nResult\n\nMinimum yearly repayment met.\n\nThe amount of the loan not repaid at the end of income year 2022-23 is $91.15.\n\nThe amalgamated loan will not be taken to be a dividend because the total repayments made are equal to or greater than the minimum yearly repayment required for income year 2022-23.\n\nInterest received by the private company must be included in the income tax return for 2022-23.\n\nMinimum yearly repayment\n\n$923.00\n\nBenchmark interest rate\n\n4.77%\n\nOpening balance:\n\nDate: 30/06/2022\n\nBalance: $1,721.00\n\nDays: 0\n\nInterest: $0\n\nPayments\n\nDate: 01/07/2022\n\nAmount: $1,634.00\n\nBalance: $87.00\n\nDays: 365\n\nInterest: $4.15\n\n\n\n\nTotal repayments\n\n$1,634.00\n\nTotal interest\n\n$4.15\n\nTotal principal\n\n$1,629.85\n\nClosing balance\n\nDate: 30/06/2023\n\nBalance: $91.15",
  "outputs": {
    "enquiryRateFormatted": "4.77%",
    "enquiryYearEndMinusOneDisplay": "30/06/2022",
    "amalgamatedLoanNotPaidByEOIYFormatted": "$1,721.00",
    "openingBalancePayDays": "0",
    "openingBalanceInterestFormatted": "$0",
    "totalAmountOfRepaymentFormatted": "$1,634.00",
    "totalInterestFormatted": "$4.15",
    "principalFormatted": "$1,629.85",
    "enquiryYearEndDisplay": "30/06/2023",
    "minimumYearRepaymentFormatted": "$923.00"
  },
  "repayments": [
    {
      "rd": "1/7/2022",
      "ra": 1634
    }
  ],
  "inputs": {
    "incomeYearOfLoan": 2018,
    "fullTermOfAmalgamatedLoan": 6,
    "incomeYearOfEnquiring": 2023,
    "amalgamatedLoanNotPaidByEOIY": 1721,
    "repayments": null,
    "lodgement_date": null
  },
  "idx": 675
}