{
  "id": "2023-09-06T17:23:07.055Z0.2703278499948292",
  "alert": "Start of result\nResult\n\nMinimum yearly repayment not met.\n\nThe amount of the loan not repaid at the end of income year 2005-06 is $93.81.\n\nThe private company may be taken to pay a dividend under Division 7A to the shareholder or shareholder's associate because the amount repaid during income year 2005-06 in relation to the amalgamated loan is less than the minimum yearly repayment required.\n\nInterest received by the private company must be included in the income tax return for 2005-06.\n\nMinimum yearly repayment\n\n$4,575.00\n\nBenchmark interest rate\n\n7.3%\n\nOpening balance:\n\nDate: 30/06/2005\n\nBalance: $4,264.00\n\nDays: 110\n\nInterest: $93.81\n\nPayments\n\nDate: 19/10/2005\n\nAmount: $4,264.00\n\nBalance: $0\n\nDays: 255\n\nInterest: $0\n\n\n\n\nTotal repayments\n\n$4,264.00\n\nTotal interest\n\n$93.81\n\nTotal principal\n\n$4,170.19\n\nClosing balance\n\nDate: 30/06/2006\n\nBalance: $93.81",
  "outputs": {
    "enquiryRateFormatted": "7.3%",
    "enquiryYearEndMinusOneDisplay": "30/06/2005",
    "amalgamatedLoanNotPaidByEOIYFormatted": "$4,264.00",
    "openingBalancePayDays": "110",
    "openingBalanceInterestFormatted": "$93.81",
    "totalAmountOfRepaymentFormatted": "$4,264.00",
    "totalInterestFormatted": "$93.81",
    "principalFormatted": "$4,170.19",
    "enquiryYearEndDisplay": "30/06/2006",
    "minimumYearRepaymentFormatted": "$4,575.00"
  },
  "repayments": [
    {
      "rd": "19/10/2005",
      "ra": 4264
    }
  ],
  "inputs": {
    "incomeYearOfLoan": 2004,
    "fullTermOfAmalgamatedLoan": 2,
    "incomeYearOfEnquiring": 2006,
    "amalgamatedLoanNotPaidByEOIY": 4264,
    "repayments": null,
    "lodgement_date": null
  },
  "idx": 7004
}