{
  "id": "2023-09-04T16:54:29.219Z0.5820494589989937",
  "alert": "Start of result\nResult\n\nMinimum yearly repayment met.\n\nThe amount of the loan not repaid at the end of income year 2015-16 is $3,962.81.\n\nThe amalgamated loan will not be taken to be a dividend because the total repayments made are equal to or greater than the minimum yearly repayment required for income year 2015-16.\n\nInterest received by the private company must be included in the income tax return for 2015-16.\n\nMinimum yearly repayment\n\n$879.00\n\nBenchmark interest rate\n\n5.45%\n\nOpening balance:\n\nDate: 30/06/2015\n\nBalance: $8,645.00\n\nDays: 0\n\nInterest: $0\n\nPayments\n\nDate: 01/07/2015\n\nAmount: $4,887.00\n\nBalance: $3,758.00\n\nDays: 366\n\nInterest: $204.81\n\n\n\n\nTotal repayments\n\n$4,887.00\n\nTotal interest\n\n$204.81\n\nTotal principal\n\n$4,682.19\n\nClosing balance\n\nDate: 30/06/2016\n\nBalance: $3,962.81",
  "outputs": {
    "enquiryRateFormatted": "5.45%",
    "enquiryYearEndMinusOneDisplay": "30/06/2015",
    "amalgamatedLoanNotPaidByEOIYFormatted": "$8,645.00",
    "openingBalancePayDays": "0",
    "openingBalanceInterestFormatted": "$0",
    "totalAmountOfRepaymentFormatted": "$4,887.00",
    "totalInterestFormatted": "$204.81",
    "principalFormatted": "$4,682.19",
    "enquiryYearEndDisplay": "30/06/2016",
    "minimumYearRepaymentFormatted": "$879.00"
  },
  "repayments": [
    {
      "rd": "1/7/2015",
      "ra": 4887
    }
  ],
  "inputs": {
    "incomeYearOfLoan": 2015,
    "fullTermOfAmalgamatedLoan": 5,
    "incomeYearOfEnquiring": 2016,
    "amalgamatedLoanNotPaidByEOIY": 8645,
    "repayments": null,
    "lodgement_date": "26/4/2016"
  },
  "idx": 1385
}