{
  "id": "2023-10-31T20:22:06.688Z0.8552003354449421",
  "alert": "Start of result\nResult\n\nAmalgamated loan fully repaid.\n\nThe amalgamated loan has been paid in full.\u000bThe private company is not taken under Division 7A to pay a dividend to the shareholder or shareholder's associate.\n\nInterest received by the private company must be included in the income tax return for 2007-08.\n\nMinimum yearly repayment\n\n$108.00\n\nBenchmark interest rate\n\n8.05%\n\nOpening balance:\n\nDate: 30/06/2007\n\nBalance: $100.18\n\nDays: 106\n\nInterest: $2.34\n\nPayments\n\nDate: 15/10/2007\n\nAmount: $512.00\n\nBalance: $0\n\nDays: 260\n\nInterest: $0\n\n\n\n\nTotal repayments\n\n$512.00\n\nTotal interest\n\n$2.34\n\nTotal principal\n\n$509.66\n\nClosing balance\n\nDate: 30/06/2008\n\nBalance: $0",
  "outputs": {
    "enquiryRateFormatted": "8.05%",
    "enquiryYearEndMinusOneDisplay": "30/06/2007",
    "amalgamatedLoanNotPaidByEOIYFormatted": "$100.18",
    "openingBalancePayDays": "106",
    "openingBalanceInterestFormatted": "$2.34",
    "totalAmountOfRepaymentFormatted": "$512.00",
    "totalInterestFormatted": "$2.34",
    "principalFormatted": "$509.66",
    "enquiryYearEndDisplay": "30/06/2008",
    "minimumYearRepaymentFormatted": "$108.00",
    "loanAmountFormatted": "$0"
  },
  "repayments": [
    {
      "rd": "15/10/2007",
      "ra": 512
    }
  ],
  "inputs": {
    "incomeYearOfLoan": 2001,
    "fullTermOfAmalgamatedLoan": 7,
    "incomeYearOfEnquiring": 2008,
    "amalgamatedLoanNotPaidByEOIY": 100.18284435904683,
    "repayments": null,
    "lodgement_date": null
  },
  "idx": 6409
}