{
  "id": "2023-10-31T17:23:36.182Z0.5804562940144979",
  "alert": "Start of result\nResult\n\nAmalgamated loan fully repaid.\n\nThe amalgamated loan has been paid in full.\u000bThe private company is not taken under Division 7A to pay a dividend to the shareholder or shareholder's associate.\n\nInterest received by the private company must be included in the income tax return for 2020-21.\n\nMinimum yearly repayment\n\n$55.00\n\nBenchmark interest rate\n\n4.52%\n\nOpening balance:\n\nDate: 30/06/2020\n\nBalance: $52.98\n\nDays: 332\n\nInterest: $2.18\n\nPayments\n\nDate: 29/05/2021\n\nAmount: $529.84\n\nBalance: $0\n\nDays: 33\n\nInterest: $0\n\n\n\n\nTotal repayments\n\n$529.84\n\nTotal interest\n\n$2.18\n\nTotal principal\n\n$527.66\n\nClosing balance\n\nDate: 30/06/2021\n\nBalance: $0",
  "outputs": {
    "enquiryRateFormatted": "4.52%",
    "enquiryYearEndMinusOneDisplay": "30/06/2020",
    "amalgamatedLoanNotPaidByEOIYFormatted": "$52.98",
    "openingBalancePayDays": "332",
    "openingBalanceInterestFormatted": "$2.18",
    "totalAmountOfRepaymentFormatted": "$529.84",
    "totalInterestFormatted": "$2.18",
    "principalFormatted": "$527.66",
    "enquiryYearEndDisplay": "30/06/2021",
    "minimumYearRepaymentFormatted": "$55.00",
    "loanAmountFormatted": "$0"
  },
  "repayments": [
    {
      "rd": "29/5/2021",
      "ra": 529.841963665167
    }
  ],
  "inputs": {
    "incomeYearOfLoan": 2018,
    "fullTermOfAmalgamatedLoan": 3,
    "incomeYearOfEnquiring": 2021,
    "amalgamatedLoanNotPaidByEOIY": 52.98419636651667,
    "repayments": null,
    "lodgement_date": null
  },
  "idx": 1323
}