{
  "id": "2023-10-31T18:01:03.124Z0.737681018985601",
  "alert": "Start of result\nResult\n\nMinimum yearly repayment not met.\n\nThe amount of the loan not repaid at the end of income year 2012-13 is $97.45.\n\nThe private company may be taken to pay a dividend under Division 7A to the shareholder or shareholder's associate because the amount repaid during income year 2012-13 in relation to the amalgamated loan is less than the minimum yearly repayment required.\n\nInterest received by the private company must be included in the income tax return for 2012-13.\n\nMinimum yearly repayment\n\n$54.00\n\nBenchmark interest rate\n\n7.05%\n\nOpening balance:\n\nDate: 30/06/2012\n\nBalance: $97.45\n\nDays: 365\n\nInterest: $6.87\n\nTotal repayments\n\n$0\n\nTotal interest\n\n$6.87\n\nTotal principal\n\n$0\n\nClosing balance\n\nDate: 30/06/2013\n\nBalance: $97.45",
  "outputs": {
    "enquiryRateFormatted": "7.05%",
    "enquiryYearEndMinusOneDisplay": "30/06/2012",
    "amalgamatedLoanNotPaidByEOIYFormatted": "$97.45",
    "openingBalancePayDays": "365",
    "openingBalanceInterestFormatted": "$6.87",
    "totalAmountOfRepaymentFormatted": "$0",
    "totalInterestFormatted": "$6.87",
    "principalFormatted": "$0",
    "enquiryYearEndDisplay": "30/06/2013",
    "minimumYearRepaymentFormatted": "$54.00",
    "loanAmountFormatted": "$97.45"
  },
  "repayments": [],
  "inputs": {
    "incomeYearOfLoan": 2012,
    "fullTermOfAmalgamatedLoan": 2,
    "incomeYearOfEnquiring": 2013,
    "amalgamatedLoanNotPaidByEOIY": 97.45489801244736,
    "repayments": null,
    "lodgement_date": "26/2/2013"
  },
  "idx": 3132
}