{
  "id": "2023-09-05T17:42:07.524Z0.5296760928346231",
  "alert": "Start of result\nResult\n\nMinimum yearly repayment met.\n\nThe amount of the loan not repaid at the end of income year 2018-19 is $7.32.\n\nThe amalgamated loan will not be taken to be a dividend because the total repayments made are equal to or greater than the minimum yearly repayment required for income year 2018-19.\n\nInterest received by the private company must be included in the income tax return for 2018-19.\n\nMinimum yearly repayment\n\n$0\n\nBenchmark interest rate\n\n5.2%\n\nOpening balance:\n\nDate: 30/06/2018\n\nBalance: $3,426.00\n\nDays: 15\n\nInterest: $7.32\n\nPayments\n\nDate: 16/07/2018\n\nAmount: $3,426.00\n\nBalance: $0\n\nDays: 350\n\nInterest: $0\n\n\n\n\nTotal repayments\n\n$3,426.00\n\nTotal interest\n\n$7.32\n\nTotal principal\n\n$3,418.68\n\nClosing balance\n\nDate: 30/06/2019\n\nBalance: $7.32",
  "outputs": {
    "enquiryRateFormatted": "5.2%",
    "enquiryYearEndMinusOneDisplay": "30/06/2018",
    "amalgamatedLoanNotPaidByEOIYFormatted": "$3,426.00",
    "openingBalancePayDays": "15",
    "openingBalanceInterestFormatted": "$7.32",
    "totalAmountOfRepaymentFormatted": "$3,426.00",
    "totalInterestFormatted": "$7.32",
    "principalFormatted": "$3,418.68",
    "enquiryYearEndDisplay": "30/06/2019",
    "minimumYearRepaymentFormatted": "$0"
  },
  "repayments": [
    {
      "rd": "16/7/2018",
      "ra": 3426
    }
  ],
  "inputs": {
    "incomeYearOfLoan": 2018,
    "fullTermOfAmalgamatedLoan": 1,
    "incomeYearOfEnquiring": 2019,
    "amalgamatedLoanNotPaidByEOIY": 3426,
    "repayments": null,
    "lodgement_date": "8/10/2018"
  },
  "idx": 5276
}