{
  "id": "2023-09-04T20:58:53.715Z0.8254204080902094",
  "alert": "Start of result\nResult\n\nMinimum yearly repayment not met.\n\nThe amount of the loan not repaid at the end of income year 2015-16 is $7,766.39.\n\nThe private company may be taken to pay a dividend under Division 7A to the shareholder or shareholder's associate because the amount repaid during income year 2015-16 in relation to the amalgamated loan is less than the minimum yearly repayment required.\n\nInterest received by the private company must be included in the income tax return for 2015-16.\n\nMinimum yearly repayment\n\n$11,450.00\n\nBenchmark interest rate\n\n5.45%\n\nOpening balance:\n\nDate: 30/06/2015\n\nBalance: $10,858.00\n\nDays: 0\n\nInterest: $0\n\nPayments\n\nDate: 01/07/2015\n\nAmount: $3,493.00\n\nBalance: $7,365.00\n\nDays: 366\n\nInterest: $401.39\n\n\n\n\nTotal repayments\n\n$3,493.00\n\nTotal interest\n\n$401.39\n\nTotal principal\n\n$3,091.61\n\nClosing balance\n\nDate: 30/06/2016\n\nBalance: $7,766.39",
  "outputs": {
    "enquiryRateFormatted": "5.45%",
    "enquiryYearEndMinusOneDisplay": "30/06/2015",
    "amalgamatedLoanNotPaidByEOIYFormatted": "$10,858.00",
    "openingBalancePayDays": "0",
    "openingBalanceInterestFormatted": "$0",
    "totalAmountOfRepaymentFormatted": "$3,493.00",
    "totalInterestFormatted": "$401.39",
    "principalFormatted": "$3,091.61",
    "enquiryYearEndDisplay": "30/06/2016",
    "minimumYearRepaymentFormatted": "$11,450.00"
  },
  "repayments": [
    {
      "rd": "1/7/2015",
      "ra": 3493
    }
  ],
  "inputs": {
    "incomeYearOfLoan": 2010,
    "fullTermOfAmalgamatedLoan": 6,
    "incomeYearOfEnquiring": 2016,
    "amalgamatedLoanNotPaidByEOIY": 10858,
    "repayments": null,
    "lodgement_date": null
  },
  "idx": 433
}