{
  "id": "2023-10-31T20:19:56.567Z0.8099449570517879",
  "alert": "Start of result\nResult\n\nAmalgamated loan fully repaid.\n\nThe amalgamated loan has been paid in full.\u000bThe private company is not taken under Division 7A to pay a dividend to the shareholder or shareholder's associate.\n\nInterest received by the private company must be included in the income tax return for 2003-04.\n\nMinimum yearly repayment\n\n$18.00\n\nBenchmark interest rate\n\n6.55%\n\nOpening balance:\n\nDate: 30/06/2003\n\nBalance: $62.06\n\nDays: 48\n\nInterest: $0.53\n\nPayments\n\nDate: 18/08/2003\n\nAmount: $620.67\n\nBalance: $0\n\nDays: 318\n\nInterest: $0\n\n\n\n\nTotal repayments\n\n$620.67\n\nTotal interest\n\n$0.53\n\nTotal principal\n\n$620.14\n\nClosing balance\n\nDate: 30/06/2004\n\nBalance: $0",
  "outputs": {
    "enquiryRateFormatted": "6.55%",
    "enquiryYearEndMinusOneDisplay": "30/06/2003",
    "amalgamatedLoanNotPaidByEOIYFormatted": "$62.06",
    "openingBalancePayDays": "48",
    "openingBalanceInterestFormatted": "$0.53",
    "totalAmountOfRepaymentFormatted": "$620.67",
    "totalInterestFormatted": "$0.53",
    "principalFormatted": "$620.14",
    "enquiryYearEndDisplay": "30/06/2004",
    "minimumYearRepaymentFormatted": "$18.00",
    "loanAmountFormatted": "$0"
  },
  "repayments": [
    {
      "rd": "18/8/2003",
      "ra": 620.672602945544
    }
  ],
  "inputs": {
    "incomeYearOfLoan": 2001,
    "fullTermOfAmalgamatedLoan": 6,
    "incomeYearOfEnquiring": 2004,
    "amalgamatedLoanNotPaidByEOIY": 62.06726029455441,
    "repayments": null,
    "lodgement_date": null
  },
  "idx": 6377
}