{
  "id": "2023-09-05T20:35:48.407Z0.3602002823756245",
  "alert": "Start of result\nResult\n\nMinimum yearly repayment met.\n\nThe amount of the loan not repaid at the end of income year 2021-22 is $2.38.\n\nThe amalgamated loan will not be taken to be a dividend because the total repayments made are equal to or greater than the minimum yearly repayment required for income year 2021-22.\n\nInterest received by the private company must be included in the income tax return for 2021-22.\n\nMinimum yearly repayment\n\n$30.00\n\nBenchmark interest rate\n\n4.52%\n\nOpening balance:\n\nDate: 30/06/2021\n\nBalance: $82.74\n\nDays: 232\n\nInterest: $2.38\n\nPayments\n\nDate: 18/02/2022\n\nAmount: $82.74\n\nBalance: $0\n\nDays: 133\n\nInterest: $0\n\n\n\n\nTotal repayments\n\n$82.74\n\nTotal interest\n\n$2.38\n\nTotal principal\n\n$80.36\n\nClosing balance\n\nDate: 30/06/2022\n\nBalance: $2.38",
  "outputs": {
    "enquiryRateFormatted": "4.52%",
    "enquiryYearEndMinusOneDisplay": "30/06/2021",
    "amalgamatedLoanNotPaidByEOIYFormatted": "$82.74",
    "openingBalancePayDays": "232",
    "openingBalanceInterestFormatted": "$2.38",
    "totalAmountOfRepaymentFormatted": "$82.74",
    "totalInterestFormatted": "$2.38",
    "principalFormatted": "$80.36",
    "enquiryYearEndDisplay": "30/06/2022",
    "minimumYearRepaymentFormatted": "$30.00"
  },
  "repayments": [
    {
      "rd": "18/2/2022",
      "ra": 82.74016016707992
    }
  ],
  "inputs": {
    "incomeYearOfLoan": 2017,
    "fullTermOfAmalgamatedLoan": 7,
    "incomeYearOfEnquiring": 2022,
    "amalgamatedLoanNotPaidByEOIY": 82.74016016707985,
    "repayments": null,
    "lodgement_date": null
  },
  "idx": 6637
}