{
  "id": "2023-09-06T00:49:40.937Z0.12529864039177108",
  "alert": "Start of result\nResult\n\nMinimum yearly repayment not met.\n\nThe amount of the loan not repaid at the end of income year 2016-17 is $0.75.\n\nThe private company may be taken to pay a dividend under Division 7A to the shareholder or shareholder's associate because the amount repaid during income year 2016-17 in relation to the amalgamated loan is less than the minimum yearly repayment required.\n\nInterest received by the private company must be included in the income tax return for 2016-17.\n\nMinimum yearly repayment\n\n$25.00\n\nBenchmark interest rate\n\n5.4%\n\nOpening balance:\n\nDate: 30/06/2016\n\nBalance: $24.02\n\nDays: 212\n\nInterest: $0.75\n\nPayments\n\nDate: 29/01/2017\n\nAmount: $24.02\n\nBalance: $0\n\nDays: 153\n\nInterest: $0\n\n\n\n\nTotal repayments\n\n$24.02\n\nTotal interest\n\n$0.75\n\nTotal principal\n\n$23.27\n\nClosing balance\n\nDate: 30/06/2017\n\nBalance: $0.75",
  "outputs": {
    "enquiryRateFormatted": "5.4%",
    "enquiryYearEndMinusOneDisplay": "30/06/2016",
    "amalgamatedLoanNotPaidByEOIYFormatted": "$24.02",
    "openingBalancePayDays": "212",
    "openingBalanceInterestFormatted": "$0.75",
    "totalAmountOfRepaymentFormatted": "$24.02",
    "totalInterestFormatted": "$0.75",
    "principalFormatted": "$23.27",
    "enquiryYearEndDisplay": "30/06/2017",
    "minimumYearRepaymentFormatted": "$25.00"
  },
  "repayments": [
    {
      "rd": "29/1/2017",
      "ra": 24.024676656962583
    }
  ],
  "inputs": {
    "incomeYearOfLoan": 2014,
    "fullTermOfAmalgamatedLoan": 3,
    "incomeYearOfEnquiring": 2017,
    "amalgamatedLoanNotPaidByEOIY": 24.024676656962598,
    "repayments": null,
    "lodgement_date": null
  },
  "idx": 4435
}