{
  "id": "2023-11-01T00:35:33.515Z0.1399768735124295",
  "alert": "Start of result\nResult\n\nMinimum yearly repayment met.\n\nThe amount of the loan not repaid at the end of income year 2001-02 is $3,617.42.\n\n\u000b\n\nThe amalgamated loan will not be taken to be a dividend because the total repayments made are equal to or greater than the minimum yearly repayment required for income year 2001-02.\n\nInterest received by the private company must be included in the income tax return for 2001-02.\n\nMinimum yearly repayment\n\n$2,496.00\n\nBenchmark interest rate\n\n6.8%\n\nOpening balance:\n\nDate: 30/06/2001\n\nBalance: $8,494.00\n\nDays: 353\n\nInterest: $558.60\n\nPayments\n\nDate: 19/06/2002\n\nAmount: $5,442.00\n\nBalance: $3,052.00\n\nDays: 12\n\nInterest: $6.82\n\n\n\n\nTotal repayments\n\n$5,442.00\n\nTotal interest\n\n$565.42\n\nTotal principal\n\n$4,876.58\n\nClosing balance\n\nDate: 30/06/2002\n\nBalance: $3,617.42",
  "outputs": {
    "enquiryRateFormatted": "6.8%",
    "enquiryYearEndMinusOneDisplay": "30/06/2001",
    "amalgamatedLoanNotPaidByEOIYFormatted": "$8,494.00",
    "openingBalancePayDays": "353",
    "openingBalanceInterestFormatted": "$558.60",
    "totalAmountOfRepaymentFormatted": "$5,442.00",
    "totalInterestFormatted": "$565.42",
    "principalFormatted": "$4,876.58",
    "enquiryYearEndDisplay": "30/06/2002",
    "minimumYearRepaymentFormatted": "$2,496.00",
    "loanAmountFormatted": "$3,617.42"
  },
  "repayments": [
    {
      "rd": "19/6/2002",
      "ra": 5442
    }
  ],
  "inputs": {
    "incomeYearOfLoan": 1998,
    "fullTermOfAmalgamatedLoan": 7,
    "incomeYearOfEnquiring": 2002,
    "amalgamatedLoanNotPaidByEOIY": 8494,
    "repayments": null,
    "lodgement_date": null
  },
  "idx": 81
}