{
  "id": "2023-09-06T22:14:52.330Z0.8988347095575231",
  "alert": "Start of result\nResult\n\nMinimum yearly repayment not met.\n\nThe amount of the loan not repaid at the end of income year 2002-03 is $105.58.\n\nThe private company may be taken to pay a dividend under Division 7A to the shareholder or shareholder's associate because the amount repaid during income year 2002-03 in relation to the amalgamated loan is less than the minimum yearly repayment required.\n\nInterest received by the private company must be included in the income tax return for 2002-03.\n\nMinimum yearly repayment\n\n$2,969.00\n\nBenchmark interest rate\n\n6.3%\n\nOpening balance:\n\nDate: 30/06/2002\n\nBalance: $2,793.00\n\nDays: 219\n\nInterest: $105.58\n\nPayments\n\nDate: 05/02/2003\n\nAmount: $2,793.00\n\nBalance: $0\n\nDays: 146\n\nInterest: $0\n\n\n\n\nTotal repayments\n\n$2,793.00\n\nTotal interest\n\n$105.58\n\nTotal principal\n\n$2,687.42\n\nClosing balance\n\nDate: 30/06/2003\n\nBalance: $105.58",
  "outputs": {
    "enquiryRateFormatted": "6.3%",
    "enquiryYearEndMinusOneDisplay": "30/06/2002",
    "amalgamatedLoanNotPaidByEOIYFormatted": "$2,793.00",
    "openingBalancePayDays": "219",
    "openingBalanceInterestFormatted": "$105.58",
    "totalAmountOfRepaymentFormatted": "$2,793.00",
    "totalInterestFormatted": "$105.58",
    "principalFormatted": "$2,687.42",
    "enquiryYearEndDisplay": "30/06/2003",
    "minimumYearRepaymentFormatted": "$2,969.00"
  },
  "repayments": [
    {
      "rd": "5/2/2003",
      "ra": 2793
    }
  ],
  "inputs": {
    "incomeYearOfLoan": 2001,
    "fullTermOfAmalgamatedLoan": 2,
    "incomeYearOfEnquiring": 2003,
    "amalgamatedLoanNotPaidByEOIY": 2793,
    "repayments": null,
    "lodgement_date": null
  },
  "idx": 8132
}