{
  "id": "2023-10-31T19:55:21.924Z0.35401152795191315",
  "alert": "Start of result\nResult\n\nAmalgamated loan fully repaid.\n\nThe amalgamated loan has been paid in full.\u000bThe private company is not taken under Division 7A to pay a dividend to the shareholder or shareholder's associate.\n\nInterest received by the private company must be included in the income tax return for 2002-03.\n\nMinimum yearly repayment\n\n$4,031.00\n\nBenchmark interest rate\n\n6.3%\n\nOpening balance:\n\nDate: 30/06/2002\n\nBalance: $7,359.00\n\nDays: 346\n\nInterest: $439.48\n\nPayments\n\nDate: 12/06/2003\n\nAmount: $9,771.00\n\nBalance: $0\n\nDays: 19\n\nInterest: $0\n\n\n\n\nTotal repayments\n\n$9,771.00\n\nTotal interest\n\n$439.48\n\nTotal principal\n\n$9,331.52\n\nClosing balance\n\nDate: 30/06/2003\n\nBalance: $0",
  "outputs": {
    "enquiryRateFormatted": "6.3%",
    "enquiryYearEndMinusOneDisplay": "30/06/2002",
    "amalgamatedLoanNotPaidByEOIYFormatted": "$7,359.00",
    "openingBalancePayDays": "346",
    "openingBalanceInterestFormatted": "$439.48",
    "totalAmountOfRepaymentFormatted": "$9,771.00",
    "totalInterestFormatted": "$439.48",
    "principalFormatted": "$9,331.52",
    "enquiryYearEndDisplay": "30/06/2003",
    "minimumYearRepaymentFormatted": "$4,031.00",
    "loanAmountFormatted": "$0"
  },
  "repayments": [
    {
      "rd": "12/6/2003",
      "ra": 9771
    }
  ],
  "inputs": {
    "incomeYearOfLoan": 2002,
    "fullTermOfAmalgamatedLoan": 2,
    "incomeYearOfEnquiring": 2003,
    "amalgamatedLoanNotPaidByEOIY": 7359,
    "repayments": null,
    "lodgement_date": "28/3/2003"
  },
  "idx": 5992
}