{
  "id": "2023-09-06T17:45:23.796Z0.5691625715990796",
  "alert": "Start of result\nResult\n\nMinimum yearly repayment not met.\n\nThe amount of the loan not repaid at the end of income year 2005-06 is $2,861.57.\n\nThe private company may be taken to pay a dividend under Division 7A to the shareholder or shareholder's associate because the amount repaid during income year 2005-06 in relation to the amalgamated loan is less than the minimum yearly repayment required.\n\nInterest received by the private company must be included in the income tax return for 2005-06.\n\nMinimum yearly repayment\n\n$2,174.00\n\nBenchmark interest rate\n\n7.3%\n\nOpening balance:\n\nDate: 30/06/2005\n\nBalance: $3,915.00\n\nDays: 296\n\nInterest: $231.77\n\nPayments\n\nDate: 23/04/2006\n\nAmount: $1,321.00\n\nBalance: $2,594.00\n\nDays: 69\n\nInterest: $35.80\n\n\n\n\nTotal repayments\n\n$1,321.00\n\nTotal interest\n\n$267.57\n\nTotal principal\n\n$1,053.43\n\nClosing balance\n\nDate: 30/06/2006\n\nBalance: $2,861.57",
  "outputs": {
    "enquiryRateFormatted": "7.3%",
    "enquiryYearEndMinusOneDisplay": "30/06/2005",
    "amalgamatedLoanNotPaidByEOIYFormatted": "$3,915.00",
    "openingBalancePayDays": "296",
    "openingBalanceInterestFormatted": "$231.77",
    "totalAmountOfRepaymentFormatted": "$1,321.00",
    "totalInterestFormatted": "$267.57",
    "principalFormatted": "$1,053.43",
    "enquiryYearEndDisplay": "30/06/2006",
    "minimumYearRepaymentFormatted": "$2,174.00"
  },
  "repayments": [
    {
      "rd": "23/4/2006",
      "ra": 1321
    }
  ],
  "inputs": {
    "incomeYearOfLoan": 2004,
    "fullTermOfAmalgamatedLoan": 3,
    "incomeYearOfEnquiring": 2006,
    "amalgamatedLoanNotPaidByEOIY": 3915,
    "repayments": null,
    "lodgement_date": null
  },
  "idx": 8106
}