{
  "id": "2023-10-31T17:59:01.946Z0.1050471028716411",
  "alert": "Start of result\nResult\n\nMinimum yearly repayment not met.\n\nThe amount of the loan not repaid at the end of income year 2014-15 is $88.26.\n\nThe private company may be taken to pay a dividend under Division 7A to the shareholder or shareholder's associate because the amount repaid during income year 2014-15 in relation to the amalgamated loan is less than the minimum yearly repayment required.\n\nInterest received by the private company must be included in the income tax return for 2014-15.\n\nMinimum yearly repayment\n\n$18.00\n\nBenchmark interest rate\n\n5.95%\n\nOpening balance:\n\nDate: 30/06/2014\n\nBalance: $88.26\n\nDays: 365\n\nInterest: $5.25\n\nTotal repayments\n\n$0\n\nTotal interest\n\n$5.25\n\nTotal principal\n\n$0\n\nClosing balance\n\nDate: 30/06/2015\n\nBalance: $88.26",
  "outputs": {
    "enquiryRateFormatted": "5.95%",
    "enquiryYearEndMinusOneDisplay": "30/06/2014",
    "amalgamatedLoanNotPaidByEOIYFormatted": "$88.26",
    "openingBalancePayDays": "365",
    "openingBalanceInterestFormatted": "$5.25",
    "totalAmountOfRepaymentFormatted": "$0",
    "totalInterestFormatted": "$5.25",
    "principalFormatted": "$0",
    "enquiryYearEndDisplay": "30/06/2015",
    "minimumYearRepaymentFormatted": "$18.00",
    "loanAmountFormatted": "$88.26"
  },
  "repayments": [],
  "inputs": {
    "incomeYearOfLoan": 2013,
    "fullTermOfAmalgamatedLoan": 7,
    "incomeYearOfEnquiring": 2015,
    "amalgamatedLoanNotPaidByEOIY": 88.26341456521541,
    "repayments": null,
    "lodgement_date": null
  },
  "idx": 3050
}