{
  "id": "2023-09-04T15:57:19.181Z0.0408601872996579",
  "alert": "Start of result\nResult\n\nMinimum yearly repayment not met.\n\nThe amount of the loan not repaid at the end of income year 2023-24 is $35,684,515.59.\n\nThe private company may be taken to pay a dividend under Division 7A to the shareholder or shareholder's associate because the amount repaid during income year 2023-24 in relation to the amalgamated loan is less than the minimum yearly repayment required.\n\nInterest received by the private company must be included in the income tax return for 2023-24.\n\nMinimum yearly repayment\n\n$38,625,207.00\n\nBenchmark interest rate\n\n8.27%\n\nOpening balance:\n\nDate: 30/06/2023\n\nBalance: $35,684,515.59\n\nDays: 0\n\nInterest: $0\n\nPayments\n\nDate: 01/07/2023\n\nAmount: $854.00\n\nBalance: $35,683,661.59\n\nDays: 2\n\nInterest: $16,125.90\n\n\n\n\nDate: 03/07/2023\n\nAmount: $8,768.00\n\nBalance: $35,674,893.59\n\nDays: 364\n\nInterest: $2,934,191.77\n\n\n\n\nTotal repayments\n\n$9,622.00\n\nTotal interest\n\n$2,950,317.67\n\nTotal principal\n\n$0\n\nClosing balance\n\nDate: 30/06/2024\n\nBalance: $35,684,515.59",
  "outputs": {
    "enquiryRateFormatted": "8.27%",
    "enquiryYearEndMinusOneDisplay": "30/06/2023",
    "amalgamatedLoanNotPaidByEOIYFormatted": "$35,684,515.59",
    "openingBalancePayDays": "0",
    "openingBalanceInterestFormatted": "$0",
    "totalAmountOfRepaymentFormatted": "$9,622.00",
    "totalInterestFormatted": "$2,950,317.67",
    "principalFormatted": "$0",
    "enquiryYearEndDisplay": "30/06/2024",
    "minimumYearRepaymentFormatted": "$38,625,207.00"
  },
  "repayments": [
    {
      "rd": "1/7/2023",
      "ra": 854
    },
    {
      "rd": "3/7/2023",
      "ra": 8768
    }
  ],
  "inputs": {
    "incomeYearOfLoan": 2023,
    "fullTermOfAmalgamatedLoan": 1,
    "incomeYearOfEnquiring": 2024,
    "amalgamatedLoanNotPaidByEOIY": 35684515.59382477,
    "repayments": null,
    "lodgement_date": "30/6/2024"
  },
  "idx": 14
}