{
  "id": "2023-11-01T00:35:07.698Z0.48794317571070256",
  "alert": "Start of result\nResult\n\nAmalgamated loan fully repaid.\n\nThe amalgamated loan has been paid in full.\u000bThe private company is not taken under Division 7A to pay a dividend to the shareholder or shareholder's associate.\n\nInterest received by the private company must be included in the income tax return for 2000-01.\n\nMinimum yearly repayment\n\n$16.00\n\nBenchmark interest rate\n\n7.8%\n\nOpening balance:\n\nDate: 30/06/2000\n\nBalance: $53.74\n\nDays: 26\n\nInterest: $0.30\n\nPayments\n\nDate: 27/07/2000\n\nAmount: $537.44\n\nBalance: $0\n\nDays: 339\n\nInterest: $0\n\n\n\n\nTotal repayments\n\n$537.44\n\nTotal interest\n\n$0.30\n\nTotal principal\n\n$537.14\n\nClosing balance\n\nDate: 30/06/2001\n\nBalance: $0",
  "outputs": {
    "enquiryRateFormatted": "7.8%",
    "enquiryYearEndMinusOneDisplay": "30/06/2000",
    "amalgamatedLoanNotPaidByEOIYFormatted": "$53.74",
    "openingBalancePayDays": "26",
    "openingBalanceInterestFormatted": "$0.30",
    "totalAmountOfRepaymentFormatted": "$537.44",
    "totalInterestFormatted": "$0.30",
    "principalFormatted": "$537.14",
    "enquiryYearEndDisplay": "30/06/2001",
    "minimumYearRepaymentFormatted": "$16.00",
    "loanAmountFormatted": "$0"
  },
  "repayments": [
    {
      "rd": "27/7/2000",
      "ra": 537.4480637894612
    }
  ],
  "inputs": {
    "incomeYearOfLoan": 1998,
    "fullTermOfAmalgamatedLoan": 6,
    "incomeYearOfEnquiring": 2001,
    "amalgamatedLoanNotPaidByEOIY": 53.74480637894616,
    "repayments": null,
    "lodgement_date": null
  },
  "idx": 43
}