{
  "id": "2023-09-04T16:30:09.759Z0.08208416200992041",
  "alert": "Start of result\nResult\n\nMinimum yearly repayment not met.\n\nThe amount of the loan not repaid at the end of income year 2018-19 is $46,365,198.59.\n\nThe private company may be taken to pay a dividend under Division 7A to the shareholder or shareholder's associate because the amount repaid during income year 2018-19 in relation to the amalgamated loan is less than the minimum yearly repayment required.\n\nInterest received by the private company must be included in the income tax return for 2018-19.\n\nMinimum yearly repayment\n\n$10,766,663.00\n\nBenchmark interest rate\n\n5.2%\n\nOpening balance:\n\nDate: 30/06/2018\n\nBalance: $46,365,198.59\n\nDays: 0\n\nInterest: $0\n\nPayments\n\nDate: 01/07/2018\n\nAmount: $7,772.00\n\nBalance: $46,357,426.59\n\nDays: 365\n\nInterest: $2,410,586.18\n\n\n\n\nTotal repayments\n\n$7,772.00\n\nTotal interest\n\n$2,410,586.18\n\nTotal principal\n\n$0\n\nClosing balance\n\nDate: 30/06/2019\n\nBalance: $46,365,198.59",
  "outputs": {
    "enquiryRateFormatted": "5.2%",
    "enquiryYearEndMinusOneDisplay": "30/06/2018",
    "amalgamatedLoanNotPaidByEOIYFormatted": "$46,365,198.59",
    "openingBalancePayDays": "0",
    "openingBalanceInterestFormatted": "$0",
    "totalAmountOfRepaymentFormatted": "$7,772.00",
    "totalInterestFormatted": "$2,410,586.18",
    "principalFormatted": "$0",
    "enquiryYearEndDisplay": "30/06/2019",
    "minimumYearRepaymentFormatted": "$10,766,663.00"
  },
  "repayments": [
    {
      "rd": "1/7/2018",
      "ra": 7772
    }
  ],
  "inputs": {
    "incomeYearOfLoan": 2018,
    "fullTermOfAmalgamatedLoan": 5,
    "incomeYearOfEnquiring": 2019,
    "amalgamatedLoanNotPaidByEOIY": 46365198.598199144,
    "repayments": null,
    "lodgement_date": "27/4/2019"
  },
  "idx": 645
}