{
  "id": "2023-09-04T16:19:13.492Z0.6650913049845517",
  "alert": "Start of result\nResult\n\nMinimum yearly repayment not met.\n\nThe amount of the loan not repaid at the end of income year 2021-22 is $5,649.31.\n\nThe private company may be taken to pay a dividend under Division 7A to the shareholder or shareholder's associate because the amount repaid during income year 2021-22 in relation to the amalgamated loan is less than the minimum yearly repayment required.\n\nInterest received by the private company must be included in the income tax return for 2021-22.\n\nMinimum yearly repayment\n\n$3,021.00\n\nBenchmark interest rate\n\n4.52%\n\nOpening balance:\n\nDate: 30/06/2021\n\nBalance: $8,302.00\n\nDays: 0\n\nInterest: $0\n\nPayments\n\nDate: 01/07/2021\n\nAmount: $2,897.00\n\nBalance: $5,405.00\n\nDays: 365\n\nInterest: $244.31\n\n\n\n\nTotal repayments\n\n$2,897.00\n\nTotal interest\n\n$244.31\n\nTotal principal\n\n$2,652.69\n\nClosing balance\n\nDate: 30/06/2022\n\nBalance: $5,649.31",
  "outputs": {
    "enquiryRateFormatted": "4.52%",
    "enquiryYearEndMinusOneDisplay": "30/06/2021",
    "amalgamatedLoanNotPaidByEOIYFormatted": "$8,302.00",
    "openingBalancePayDays": "0",
    "openingBalanceInterestFormatted": "$0",
    "totalAmountOfRepaymentFormatted": "$2,897.00",
    "totalInterestFormatted": "$244.31",
    "principalFormatted": "$2,652.69",
    "enquiryYearEndDisplay": "30/06/2022",
    "minimumYearRepaymentFormatted": "$3,021.00"
  },
  "repayments": [
    {
      "rd": "1/7/2021",
      "ra": 2897
    }
  ],
  "inputs": {
    "incomeYearOfLoan": 2020,
    "fullTermOfAmalgamatedLoan": 4,
    "incomeYearOfEnquiring": 2022,
    "amalgamatedLoanNotPaidByEOIY": 8302,
    "repayments": null,
    "lodgement_date": null
  },
  "idx": 259
}