{
  "id": "2023-10-31T18:24:48.656Z0.3017039899018814",
  "alert": "Start of result\nResult\n\nMinimum yearly repayment met.\n\nThe amount of the loan not repaid at the end of income year 2013-14 is $1,947.75.\n\n\u000b\n\nThe amalgamated loan will not be taken to be a dividend because the total repayments made are equal to or greater than the minimum yearly repayment required for income year 2013-14.\n\nInterest received by the private company must be included in the income tax return for 2013-14.\n\nMinimum yearly repayment\n\n$2,242.00\n\nBenchmark interest rate\n\n6.2%\n\nOpening balance:\n\nDate: 30/06/2013\n\nBalance: $7,733.00\n\nDays: 63\n\nInterest: $82.75\n\nPayments\n\nDate: 02/09/2013\n\nAmount: $5,959.00\n\nBalance: $1,774.00\n\nDays: 302\n\nInterest: $91.00\n\n\n\n\nTotal repayments\n\n$5,959.00\n\nTotal interest\n\n$173.75\n\nTotal principal\n\n$5,785.25\n\nClosing balance\n\nDate: 30/06/2014\n\nBalance: $1,947.75",
  "outputs": {
    "enquiryRateFormatted": "6.2%",
    "enquiryYearEndMinusOneDisplay": "30/06/2013",
    "amalgamatedLoanNotPaidByEOIYFormatted": "$7,733.00",
    "openingBalancePayDays": "63",
    "openingBalanceInterestFormatted": "$82.75",
    "totalAmountOfRepaymentFormatted": "$5,959.00",
    "totalInterestFormatted": "$173.75",
    "principalFormatted": "$5,785.25",
    "enquiryYearEndDisplay": "30/06/2014",
    "minimumYearRepaymentFormatted": "$2,242.00",
    "loanAmountFormatted": "$1,947.75"
  },
  "repayments": [
    {
      "rd": "2/9/2013",
      "ra": 5959
    }
  ],
  "inputs": {
    "incomeYearOfLoan": 2010,
    "fullTermOfAmalgamatedLoan": 7,
    "incomeYearOfEnquiring": 2014,
    "amalgamatedLoanNotPaidByEOIY": 7733,
    "repayments": null,
    "lodgement_date": null
  },
  "idx": 3931
}