{
  "id": "2023-10-31T17:22:54.469Z0.4879592226781281",
  "alert": "Start of result\nResult\n\nMinimum yearly repayment met.\n\nThe amount of the loan not repaid at the end of income year 2018-19 is $2,668.73.\n\n\u000b\n\nThe amalgamated loan will not be taken to be a dividend because the total repayments made are equal to or greater than the minimum yearly repayment required for income year 2018-19.\n\nInterest received by the private company must be included in the income tax return for 2018-19.\n\nMinimum yearly repayment\n\n$2,632.00\n\nBenchmark interest rate\n\n5.2%\n\nOpening balance:\n\nDate: 30/06/2018\n\nBalance: $6,649.00\n\nDays: 62\n\nInterest: $58.73\n\nPayments\n\nDate: 01/09/2018\n\nAmount: $4,147.00\n\nBalance: $2,502.00\n\nDays: 303\n\nInterest: $108.00\n\n\n\n\nTotal repayments\n\n$4,147.00\n\nTotal interest\n\n$166.73\n\nTotal principal\n\n$3,980.27\n\nClosing balance\n\nDate: 30/06/2019\n\nBalance: $2,668.73",
  "outputs": {
    "enquiryRateFormatted": "5.2%",
    "enquiryYearEndMinusOneDisplay": "30/06/2018",
    "amalgamatedLoanNotPaidByEOIYFormatted": "$6,649.00",
    "openingBalancePayDays": "62",
    "openingBalanceInterestFormatted": "$58.73",
    "totalAmountOfRepaymentFormatted": "$4,147.00",
    "totalInterestFormatted": "$166.73",
    "principalFormatted": "$3,980.27",
    "enquiryYearEndDisplay": "30/06/2019",
    "minimumYearRepaymentFormatted": "$2,632.00",
    "loanAmountFormatted": "$2,668.73"
  },
  "repayments": [
    {
      "rd": "1/9/2018",
      "ra": 4147
    }
  ],
  "inputs": {
    "incomeYearOfLoan": 2018,
    "fullTermOfAmalgamatedLoan": 1,
    "incomeYearOfEnquiring": 2019,
    "amalgamatedLoanNotPaidByEOIY": 6649,
    "repayments": null,
    "lodgement_date": "27/4/2019"
  },
  "idx": 1282
}