{
  "id": "2023-09-06T18:14:31.490Z0.7054077185011978",
  "alert": "Start of result\nResult\n\nMinimum yearly repayment met.\n\nThe amount of the loan not repaid at the end of income year 2005-06 is $34.06.\n\nThe amalgamated loan will not be taken to be a dividend because the total repayments made are equal to or greater than the minimum yearly repayment required for income year 2005-06.\n\nInterest received by the private company must be included in the income tax return for 2005-06.\n\nMinimum yearly repayment\n\n$296.00\n\nBenchmark interest rate\n\n7.3%\n\nOpening balance:\n\nDate: 30/06/2005\n\nBalance: $996.00\n\nDays: 171\n\nInterest: $34.06\n\nPayments\n\nDate: 19/12/2005\n\nAmount: $996.00\n\nBalance: $0\n\nDays: 194\n\nInterest: $0\n\n\n\n\nTotal repayments\n\n$996.00\n\nTotal interest\n\n$34.06\n\nTotal principal\n\n$961.94\n\nClosing balance\n\nDate: 30/06/2006\n\nBalance: $34.06",
  "outputs": {
    "enquiryRateFormatted": "7.3%",
    "enquiryYearEndMinusOneDisplay": "30/06/2005",
    "amalgamatedLoanNotPaidByEOIYFormatted": "$996.00",
    "openingBalancePayDays": "171",
    "openingBalanceInterestFormatted": "$34.06",
    "totalAmountOfRepaymentFormatted": "$996.00",
    "totalInterestFormatted": "$34.06",
    "principalFormatted": "$961.94",
    "enquiryYearEndDisplay": "30/06/2006",
    "minimumYearRepaymentFormatted": "$296.00"
  },
  "repayments": [
    {
      "rd": "19/12/2005",
      "ra": 996
    }
  ],
  "inputs": {
    "incomeYearOfLoan": 2004,
    "fullTermOfAmalgamatedLoan": 5,
    "incomeYearOfEnquiring": 2006,
    "amalgamatedLoanNotPaidByEOIY": 996,
    "repayments": null,
    "lodgement_date": null
  },
  "idx": 1477
}