{
  "id": "2023-10-31T17:21:25.135Z0.3533343688792624",
  "alert": "Start of result\nResult\n\nMinimum yearly repayment not met.\n\nThe amount of the loan not repaid at the end of income year 2021-22 is $8,953.21.\n\nThe private company may be taken to pay a dividend under Division 7A to the shareholder or shareholder's associate because the amount repaid during income year 2021-22 in relation to the amalgamated loan is less than the minimum yearly repayment required.\n\nInterest received by the private company must be included in the income tax return for 2021-22.\n\nMinimum yearly repayment\n\n$2,818.00\n\nBenchmark interest rate\n\n4.52%\n\nOpening balance:\n\nDate: 30/06/2021\n\nBalance: $10,106.00\n\nDays: 103\n\nInterest: $128.90\n\nPayments\n\nDate: 12/10/2021\n\nAmount: $1,559.00\n\nBalance: $8,547.00\n\nDays: 262\n\nInterest: $277.31\n\n\n\n\nTotal repayments\n\n$1,559.00\n\nTotal interest\n\n$406.21\n\nTotal principal\n\n$1,152.79\n\nClosing balance\n\nDate: 30/06/2022\n\nBalance: $8,953.21",
  "outputs": {
    "enquiryRateFormatted": "4.52%",
    "enquiryYearEndMinusOneDisplay": "30/06/2021",
    "amalgamatedLoanNotPaidByEOIYFormatted": "$10,106.00",
    "openingBalancePayDays": "103",
    "openingBalanceInterestFormatted": "$128.90",
    "totalAmountOfRepaymentFormatted": "$1,559.00",
    "totalInterestFormatted": "$406.21",
    "principalFormatted": "$1,152.79",
    "enquiryYearEndDisplay": "30/06/2022",
    "minimumYearRepaymentFormatted": "$2,818.00",
    "loanAmountFormatted": "$8,953.21"
  },
  "repayments": [
    {
      "rd": "12/10/2021",
      "ra": 1559
    }
  ],
  "inputs": {
    "incomeYearOfLoan": 2019,
    "fullTermOfAmalgamatedLoan": 6,
    "incomeYearOfEnquiring": 2022,
    "amalgamatedLoanNotPaidByEOIY": 10106,
    "repayments": null,
    "lodgement_date": null
  },
  "idx": 1186
}