{
  "id": "2023-09-04T22:27:08.196Z0.5040818703831873",
  "alert": "Start of result\nResult\n\nMinimum yearly repayment not met.\n\nThe amount of the loan not repaid at the end of income year 1999-00 is $101,681,396.86.\n\nThe private company may be taken to pay a dividend under Division 7A to the shareholder or shareholder's associate because the amount repaid during income year 1999-00 in relation to the amalgamated loan is less than the minimum yearly repayment required.\n\nInterest received by the private company must be included in the income tax return for 1999-00.\n\nMinimum yearly repayment\n\n$108,285,234.00\n\nBenchmark interest rate\n\n6.5%\n\nOpening balance:\n\nDate: 30/06/1999\n\nBalance: $101,681,396.86\n\nDays: 0\n\nInterest: $0\n\nPayments\n\nDate: 01/07/1999\n\nAmount: $5,121.00\n\nBalance: $101,676,275.86\n\nDays: 366\n\nInterest: $6,608,957.93\n\n\n\n\nTotal repayments\n\n$5,121.00\n\nTotal interest\n\n$6,608,957.93\n\nTotal principal\n\n$0\n\nClosing balance\n\nDate: 30/06/2000\n\nBalance: $101,681,396.86",
  "outputs": {
    "enquiryRateFormatted": "6.5%",
    "enquiryYearEndMinusOneDisplay": "30/06/1999",
    "amalgamatedLoanNotPaidByEOIYFormatted": "$101,681,396.86",
    "openingBalancePayDays": "0",
    "openingBalanceInterestFormatted": "$0",
    "totalAmountOfRepaymentFormatted": "$5,121.00",
    "totalInterestFormatted": "$6,608,957.93",
    "principalFormatted": "$0",
    "enquiryYearEndDisplay": "30/06/2000",
    "minimumYearRepaymentFormatted": "$108,285,234.00"
  },
  "repayments": [
    {
      "rd": "1/7/1999",
      "ra": 5121
    }
  ],
  "inputs": {
    "incomeYearOfLoan": 1999,
    "fullTermOfAmalgamatedLoan": 1,
    "incomeYearOfEnquiring": 2000,
    "amalgamatedLoanNotPaidByEOIY": 101681396.86831822,
    "repayments": null,
    "lodgement_date": "17/1/2000"
  },
  "idx": 960
}