{
  "id": "2023-10-31T17:18:24.648Z0.4528312271192554",
  "alert": "Start of result\nResult\n\nAmalgamated loan fully repaid.\n\nThe amalgamated loan has been paid in full.\u000bThe private company is not taken under Division 7A to pay a dividend to the shareholder or shareholder's associate.\n\nInterest received by the private company must be included in the income tax return for 2021-22.\n\nMinimum yearly repayment\n\n$20.00\n\nBenchmark interest rate\n\n4.52%\n\nOpening balance:\n\nDate: 30/06/2021\n\nBalance: $104.95\n\nDays: 342\n\nInterest: $4.44\n\nPayments\n\nDate: 08/06/2022\n\nAmount: $323.00\n\nBalance: $0\n\nDays: 23\n\nInterest: $0\n\n\n\n\nTotal repayments\n\n$323.00\n\nTotal interest\n\n$4.44\n\nTotal principal\n\n$318.56\n\nClosing balance\n\nDate: 30/06/2022\n\nBalance: $0",
  "outputs": {
    "enquiryRateFormatted": "4.52%",
    "enquiryYearEndMinusOneDisplay": "30/06/2021",
    "amalgamatedLoanNotPaidByEOIYFormatted": "$104.95",
    "openingBalancePayDays": "342",
    "openingBalanceInterestFormatted": "$4.44",
    "totalAmountOfRepaymentFormatted": "$323.00",
    "totalInterestFormatted": "$4.44",
    "principalFormatted": "$318.56",
    "enquiryYearEndDisplay": "30/06/2022",
    "minimumYearRepaymentFormatted": "$20.00",
    "loanAmountFormatted": "$0"
  },
  "repayments": [
    {
      "rd": "8/6/2022",
      "ra": 323
    }
  ],
  "inputs": {
    "incomeYearOfLoan": 2020,
    "fullTermOfAmalgamatedLoan": 7,
    "incomeYearOfEnquiring": 2022,
    "amalgamatedLoanNotPaidByEOIY": 104.95990875234571,
    "repayments": null,
    "lodgement_date": null
  },
  "idx": 975
}