{
  "id": "2023-10-31T18:06:49.061Z0.7700307034181512",
  "alert": "Start of result\nResult\n\nMinimum yearly repayment not met.\n\nThe amount of the loan not repaid at the end of income year 2012-13 is $123.32.\n\nThe private company may be taken to pay a dividend under Division 7A to the shareholder or shareholder's associate because the amount repaid during income year 2012-13 in relation to the amalgamated loan is less than the minimum yearly repayment required.\n\nInterest received by the private company must be included in the income tax return for 2012-13.\n\nMinimum yearly repayment\n\n$23.00\n\nBenchmark interest rate\n\n7.05%\n\nOpening balance:\n\nDate: 30/06/2012\n\nBalance: $123.32\n\nDays: 365\n\nInterest: $8.69\n\nTotal repayments\n\n$0\n\nTotal interest\n\n$8.69\n\nTotal principal\n\n$0\n\nClosing balance\n\nDate: 30/06/2013\n\nBalance: $123.32",
  "outputs": {
    "enquiryRateFormatted": "7.05%",
    "enquiryYearEndMinusOneDisplay": "30/06/2012",
    "amalgamatedLoanNotPaidByEOIYFormatted": "$123.32",
    "openingBalancePayDays": "365",
    "openingBalanceInterestFormatted": "$8.69",
    "totalAmountOfRepaymentFormatted": "$0",
    "totalInterestFormatted": "$8.69",
    "principalFormatted": "$0",
    "enquiryYearEndDisplay": "30/06/2013",
    "minimumYearRepaymentFormatted": "$23.00",
    "loanAmountFormatted": "$123.32"
  },
  "repayments": [],
  "inputs": {
    "incomeYearOfLoan": 2012,
    "fullTermOfAmalgamatedLoan": 7,
    "incomeYearOfEnquiring": 2013,
    "amalgamatedLoanNotPaidByEOIY": 123.32672003447463,
    "repayments": null,
    "lodgement_date": "28/11/2012"
  },
  "idx": 3335
}