{
  "id": "2023-10-31T18:24:44.790Z0.9710977275203683",
  "alert": "Start of result\nResult\n\nAmalgamated loan fully repaid.\n\nThe amalgamated loan has been paid in full.\u000bThe private company is not taken under Division 7A to pay a dividend to the shareholder or shareholder's associate.\n\nInterest received by the private company must be included in the income tax return for 2014-15.\n\nMinimum yearly repayment\n\n$2,462.00\n\nBenchmark interest rate\n\n5.95%\n\nOpening balance:\n\nDate: 30/06/2014\n\nBalance: $6,588.00\n\nDays: 238\n\nInterest: $255.60\n\nPayments\n\nDate: 24/02/2015\n\nAmount: $9,176.00\n\nBalance: $0\n\nDays: 127\n\nInterest: $0\n\n\n\n\nTotal repayments\n\n$9,176.00\n\nTotal interest\n\n$255.60\n\nTotal principal\n\n$8,920.40\n\nClosing balance\n\nDate: 30/06/2015\n\nBalance: $0",
  "outputs": {
    "enquiryRateFormatted": "5.95%",
    "enquiryYearEndMinusOneDisplay": "30/06/2014",
    "amalgamatedLoanNotPaidByEOIYFormatted": "$6,588.00",
    "openingBalancePayDays": "238",
    "openingBalanceInterestFormatted": "$255.60",
    "totalAmountOfRepaymentFormatted": "$9,176.00",
    "totalInterestFormatted": "$255.60",
    "principalFormatted": "$8,920.40",
    "enquiryYearEndDisplay": "30/06/2015",
    "minimumYearRepaymentFormatted": "$2,462.00",
    "loanAmountFormatted": "$0"
  },
  "repayments": [
    {
      "rd": "24/2/2015",
      "ra": 9176
    }
  ],
  "inputs": {
    "incomeYearOfLoan": 2010,
    "fullTermOfAmalgamatedLoan": 7,
    "incomeYearOfEnquiring": 2015,
    "amalgamatedLoanNotPaidByEOIY": 6588,
    "repayments": null,
    "lodgement_date": null
  },
  "idx": 3929
}