{
  "id": "2023-10-31T18:40:53.086Z0.4025051145828368",
  "alert": "Start of result\nResult\n\nMinimum yearly repayment not met.\n\nThe amount of the loan not repaid at the end of income year 2012-13 is $8,183.00.\n\nThe private company may be taken to pay a dividend under Division 7A to the shareholder or shareholder's associate because the amount repaid during income year 2012-13 in relation to the amalgamated loan is less than the minimum yearly repayment required.\n\nInterest received by the private company must be included in the income tax return for 2012-13.\n\nMinimum yearly repayment\n\n$4,529.00\n\nBenchmark interest rate\n\n7.05%\n\nOpening balance:\n\nDate: 30/06/2012\n\nBalance: $8,183.00\n\nDays: 365\n\nInterest: $576.90\n\nTotal repayments\n\n$0\n\nTotal interest\n\n$576.90\n\nTotal principal\n\n$0\n\nClosing balance\n\nDate: 30/06/2013\n\nBalance: $8,183.00",
  "outputs": {
    "enquiryRateFormatted": "7.05%",
    "enquiryYearEndMinusOneDisplay": "30/06/2012",
    "amalgamatedLoanNotPaidByEOIYFormatted": "$8,183.00",
    "openingBalancePayDays": "365",
    "openingBalanceInterestFormatted": "$576.90",
    "totalAmountOfRepaymentFormatted": "$0",
    "totalInterestFormatted": "$576.90",
    "principalFormatted": "$0",
    "enquiryYearEndDisplay": "30/06/2013",
    "minimumYearRepaymentFormatted": "$4,529.00",
    "loanAmountFormatted": "$8,183.00"
  },
  "repayments": [],
  "inputs": {
    "incomeYearOfLoan": 2008,
    "fullTermOfAmalgamatedLoan": 6,
    "incomeYearOfEnquiring": 2013,
    "amalgamatedLoanNotPaidByEOIY": 8183,
    "repayments": null,
    "lodgement_date": null
  },
  "idx": 4377
}