{
  "id": "2023-10-31T18:10:17.161Z0.8018398723829668",
  "alert": "Start of result\nResult\n\nAmalgamated loan fully repaid.\n\nThe amalgamated loan has been paid in full.\u000bThe private company is not taken under Division 7A to pay a dividend to the shareholder or shareholder's associate.\n\nInterest received by the private company must be included in the income tax return for 2014-15.\n\nMinimum yearly repayment\n\n$20.00\n\nBenchmark interest rate\n\n5.95%\n\nOpening balance:\n\nDate: 30/06/2014\n\nBalance: $18.97\n\nDays: 58\n\nInterest: $0.18\n\nPayments\n\nDate: 28/08/2014\n\nAmount: $189.73\n\nBalance: $0\n\nDays: 307\n\nInterest: $0\n\n\n\n\nTotal repayments\n\n$189.73\n\nTotal interest\n\n$0.18\n\nTotal principal\n\n$189.55\n\nClosing balance\n\nDate: 30/06/2015\n\nBalance: $0",
  "outputs": {
    "enquiryRateFormatted": "5.95%",
    "enquiryYearEndMinusOneDisplay": "30/06/2014",
    "amalgamatedLoanNotPaidByEOIYFormatted": "$18.97",
    "openingBalancePayDays": "58",
    "openingBalanceInterestFormatted": "$0.18",
    "totalAmountOfRepaymentFormatted": "$189.73",
    "totalInterestFormatted": "$0.18",
    "principalFormatted": "$189.55",
    "enquiryYearEndDisplay": "30/06/2015",
    "minimumYearRepaymentFormatted": "$20.00",
    "loanAmountFormatted": "$0"
  },
  "repayments": [
    {
      "rd": "28/8/2014",
      "ra": 189.7365343001129
    }
  ],
  "inputs": {
    "incomeYearOfLoan": 2011,
    "fullTermOfAmalgamatedLoan": 4,
    "incomeYearOfEnquiring": 2015,
    "amalgamatedLoanNotPaidByEOIY": 18.97365343001128,
    "repayments": null,
    "lodgement_date": null
  },
  "idx": 3463
}