{
  "id": "2023-10-31T18:54:23.451Z0.27625828725275114",
  "alert": "Start of result\nResult\n\nMinimum yearly repayment not met.\n\nThe amount of the loan not repaid at the end of income year 2007-08 is $86.28.\n\nThe private company may be taken to pay a dividend under Division 7A to the shareholder or shareholder's associate because the amount repaid during income year 2007-08 in relation to the amalgamated loan is less than the minimum yearly repayment required.\n\nInterest received by the private company must be included in the income tax return for 2007-08.\n\nMinimum yearly repayment\n\n$19.00\n\nBenchmark interest rate\n\n8.05%\n\nOpening balance:\n\nDate: 30/06/2007\n\nBalance: $86.28\n\nDays: 366\n\nInterest: $6.95\n\nTotal repayments\n\n$0\n\nTotal interest\n\n$6.95\n\nTotal principal\n\n$0\n\nClosing balance\n\nDate: 30/06/2008\n\nBalance: $86.28",
  "outputs": {
    "enquiryRateFormatted": "8.05%",
    "enquiryYearEndMinusOneDisplay": "30/06/2007",
    "amalgamatedLoanNotPaidByEOIYFormatted": "$86.28",
    "openingBalancePayDays": "366",
    "openingBalanceInterestFormatted": "$6.95",
    "totalAmountOfRepaymentFormatted": "$0",
    "totalInterestFormatted": "$6.95",
    "principalFormatted": "$0",
    "enquiryYearEndDisplay": "30/06/2008",
    "minimumYearRepaymentFormatted": "$19.00",
    "loanAmountFormatted": "$86.28"
  },
  "repayments": [],
  "inputs": {
    "incomeYearOfLoan": 2007,
    "fullTermOfAmalgamatedLoan": 6,
    "incomeYearOfEnquiring": 2008,
    "amalgamatedLoanNotPaidByEOIY": 86.28130186054621,
    "repayments": null,
    "lodgement_date": "29/9/2007"
  },
  "idx": 4729
}