{
  "id": "2023-09-05T18:27:56.441Z0.44779309439565207",
  "alert": "Start of result\nResult\n\nMinimum yearly repayment not met.\n\nThe amount of the loan not repaid at the end of income year 2022-23 is $371.08.\n\nThe private company may be taken to pay a dividend under Division 7A to the shareholder or shareholder's associate because the amount repaid during income year 2022-23 in relation to the amalgamated loan is less than the minimum yearly repayment required.\n\nInterest received by the private company must be included in the income tax return for 2022-23.\n\nMinimum yearly repayment\n\n$4,296.00\n\nBenchmark interest rate\n\n4.77%\n\nOpening balance:\n\nDate: 30/06/2022\n\nBalance: $4,100.00\n\nDays: 221\n\nInterest: $118.41\n\nPayments\n\nDate: 07/02/2023\n\nAmount: $3,852.00\n\nBalance: $248.00\n\nDays: 144\n\nInterest: $4.67\n\n\n\n\nTotal repayments\n\n$3,852.00\n\nTotal interest\n\n$123.08\n\nTotal principal\n\n$3,728.92\n\nClosing balance\n\nDate: 30/06/2023\n\nBalance: $371.08",
  "outputs": {
    "enquiryRateFormatted": "4.77%",
    "enquiryYearEndMinusOneDisplay": "30/06/2022",
    "amalgamatedLoanNotPaidByEOIYFormatted": "$4,100.00",
    "openingBalancePayDays": "221",
    "openingBalanceInterestFormatted": "$118.41",
    "totalAmountOfRepaymentFormatted": "$3,852.00",
    "totalInterestFormatted": "$123.08",
    "principalFormatted": "$3,728.92",
    "enquiryYearEndDisplay": "30/06/2023",
    "minimumYearRepaymentFormatted": "$4,296.00"
  },
  "repayments": [
    {
      "rd": "7/2/2023",
      "ra": 3852
    }
  ],
  "inputs": {
    "incomeYearOfLoan": 2018,
    "fullTermOfAmalgamatedLoan": 5,
    "incomeYearOfEnquiring": 2023,
    "amalgamatedLoanNotPaidByEOIY": 4100,
    "repayments": null,
    "lodgement_date": null
  },
  "idx": 7752
}