{
  "id": "2023-10-31T18:29:33.651Z0.78192916713032",
  "alert": "Start of result\nResult\n\nMinimum yearly repayment not met.\n\nThe amount of the loan not repaid at the end of income year 2010-11 is $7,028.00.\n\nThe private company may be taken to pay a dividend under Division 7A to the shareholder or shareholder's associate because the amount repaid during income year 2010-11 in relation to the amalgamated loan is less than the minimum yearly repayment required.\n\nInterest received by the private company must be included in the income tax return for 2010-11.\n\nMinimum yearly repayment\n\n$2,698.00\n\nBenchmark interest rate\n\n7.4%\n\nOpening balance:\n\nDate: 30/06/2010\n\nBalance: $7,028.00\n\nDays: 365\n\nInterest: $520.07\n\nTotal repayments\n\n$0\n\nTotal interest\n\n$520.07\n\nTotal principal\n\n$0\n\nClosing balance\n\nDate: 30/06/2011\n\nBalance: $7,028.00",
  "outputs": {
    "enquiryRateFormatted": "7.4%",
    "enquiryYearEndMinusOneDisplay": "30/06/2010",
    "amalgamatedLoanNotPaidByEOIYFormatted": "$7,028.00",
    "openingBalancePayDays": "365",
    "openingBalanceInterestFormatted": "$520.07",
    "totalAmountOfRepaymentFormatted": "$0",
    "totalInterestFormatted": "$520.07",
    "principalFormatted": "$0",
    "enquiryYearEndDisplay": "30/06/2011",
    "minimumYearRepaymentFormatted": "$2,698.00",
    "loanAmountFormatted": "$7,028.00"
  },
  "repayments": [],
  "inputs": {
    "incomeYearOfLoan": 2009,
    "fullTermOfAmalgamatedLoan": 4,
    "incomeYearOfEnquiring": 2011,
    "amalgamatedLoanNotPaidByEOIY": 7028,
    "repayments": null,
    "lodgement_date": null
  },
  "idx": 4066
}