{
  "id": "2023-10-31T17:43:09.773Z0.22190644738072007",
  "alert": "Start of result\nResult\n\nAmalgamated loan fully repaid.\n\nThe amalgamated loan has been paid in full.\u000bThe private company is not taken under Division 7A to pay a dividend to the shareholder or shareholder's associate.\n\nInterest received by the private company must be included in the income tax return for 2020-21.\n\nMinimum yearly repayment\n\n$55.00\n\nBenchmark interest rate\n\n4.52%\n\nOpening balance:\n\nDate: 30/06/2020\n\nBalance: $103.38\n\nDays: 57\n\nInterest: $0.73\n\nPayments\n\nDate: 27/08/2020\n\nAmount: $1,033.86\n\nBalance: $0\n\nDays: 308\n\nInterest: $0\n\n\n\n\nTotal repayments\n\n$1,033.86\n\nTotal interest\n\n$0.73\n\nTotal principal\n\n$1,033.13\n\nClosing balance\n\nDate: 30/06/2021\n\nBalance: $0",
  "outputs": {
    "enquiryRateFormatted": "4.52%",
    "enquiryYearEndMinusOneDisplay": "30/06/2020",
    "amalgamatedLoanNotPaidByEOIYFormatted": "$103.38",
    "openingBalancePayDays": "57",
    "openingBalanceInterestFormatted": "$0.73",
    "totalAmountOfRepaymentFormatted": "$1,033.86",
    "totalInterestFormatted": "$0.73",
    "principalFormatted": "$1,033.13",
    "enquiryYearEndDisplay": "30/06/2021",
    "minimumYearRepaymentFormatted": "$55.00",
    "loanAmountFormatted": "$0"
  },
  "repayments": [
    {
      "rd": "27/8/2020",
      "ra": 1033.86741007618
    }
  ],
  "inputs": {
    "incomeYearOfLoan": 2015,
    "fullTermOfAmalgamatedLoan": 7,
    "incomeYearOfEnquiring": 2021,
    "amalgamatedLoanNotPaidByEOIY": 103.38674100761801,
    "repayments": null,
    "lodgement_date": null
  },
  "idx": 2372
}