{
  "id": "2023-10-31T16:56:15.583Z0.6152963299186",
  "alert": "Start of result\nResult\n\nMinimum yearly repayment not met.\n\nThe amount of the loan not repaid at the end of income year 2023-24 is $106.60.\n\nThe private company may be taken to pay a dividend under Division 7A to the shareholder or shareholder's associate because the amount repaid during income year 2023-24 in relation to the amalgamated loan is less than the minimum yearly repayment required.\n\nInterest received by the private company must be included in the income tax return for 2023-24.\n\nMinimum yearly repayment\n\n$60.00\n\nBenchmark interest rate\n\n8.27%\n\nOpening balance:\n\nDate: 30/06/2023\n\nBalance: $106.60\n\nDays: 366\n\nInterest: $8.82\n\nTotal repayments\n\n$0\n\nTotal interest\n\n$8.82\n\nTotal principal\n\n$0\n\nClosing balance\n\nDate: 30/06/2024\n\nBalance: $106.60",
  "outputs": {
    "enquiryRateFormatted": "8.27%",
    "enquiryYearEndMinusOneDisplay": "30/06/2023",
    "amalgamatedLoanNotPaidByEOIYFormatted": "$106.60",
    "openingBalancePayDays": "366",
    "openingBalanceInterestFormatted": "$8.82",
    "totalAmountOfRepaymentFormatted": "$0",
    "totalInterestFormatted": "$8.82",
    "principalFormatted": "$0",
    "enquiryYearEndDisplay": "30/06/2024",
    "minimumYearRepaymentFormatted": "$60.00",
    "loanAmountFormatted": "$106.60"
  },
  "repayments": [],
  "inputs": {
    "incomeYearOfLoan": 2023,
    "fullTermOfAmalgamatedLoan": 2,
    "incomeYearOfEnquiring": 2024,
    "amalgamatedLoanNotPaidByEOIY": 106.60123078016794,
    "repayments": null,
    "lodgement_date": "5/7/2023"
  },
  "idx": 4
}