{
  "id": "2023-10-31T17:28:07.899Z0.6757485907144682",
  "alert": "Start of result\nResult\n\nMinimum yearly repayment not met.\n\nThe amount of the loan not repaid at the end of income year 2020-21 is $1,244.00.\n\nThe private company may be taken to pay a dividend under Division 7A to the shareholder or shareholder's associate because the amount repaid during income year 2020-21 in relation to the amalgamated loan is less than the minimum yearly repayment required.\n\nInterest received by the private company must be included in the income tax return for 2020-21.\n\nMinimum yearly repayment\n\n$1,300.00\n\nBenchmark interest rate\n\n4.52%\n\nOpening balance:\n\nDate: 30/06/2020\n\nBalance: $1,244.00\n\nDays: 365\n\nInterest: $56.23\n\nTotal repayments\n\n$0\n\nTotal interest\n\n$56.23\n\nTotal principal\n\n$0\n\nClosing balance\n\nDate: 30/06/2021\n\nBalance: $1,244.00",
  "outputs": {
    "enquiryRateFormatted": "4.52%",
    "enquiryYearEndMinusOneDisplay": "30/06/2020",
    "amalgamatedLoanNotPaidByEOIYFormatted": "$1,244.00",
    "openingBalancePayDays": "365",
    "openingBalanceInterestFormatted": "$56.23",
    "totalAmountOfRepaymentFormatted": "$0",
    "totalInterestFormatted": "$56.23",
    "principalFormatted": "$0",
    "enquiryYearEndDisplay": "30/06/2021",
    "minimumYearRepaymentFormatted": "$1,300.00",
    "loanAmountFormatted": "$1,244.00"
  },
  "repayments": [],
  "inputs": {
    "incomeYearOfLoan": 2017,
    "fullTermOfAmalgamatedLoan": 4,
    "incomeYearOfEnquiring": 2021,
    "amalgamatedLoanNotPaidByEOIY": 1244,
    "repayments": null,
    "lodgement_date": null
  },
  "idx": 1595
}