{
  "id": "2023-09-04T17:39:35.373Z0.6861178182309864",
  "alert": "Start of result\nResult\n\nMinimum yearly repayment not met.\n\nThe amount of the loan not repaid at the end of income year 2012-13 is $86,334,315.22.\n\nThe private company may be taken to pay a dividend under Division 7A to the shareholder or shareholder's associate because the amount repaid during income year 2012-13 in relation to the amalgamated loan is less than the minimum yearly repayment required.\n\nInterest received by the private company must be included in the income tax return for 2012-13.\n\nMinimum yearly repayment\n\n$47,783,896.00\n\nBenchmark interest rate\n\n7.05%\n\nOpening balance:\n\nDate: 30/06/2012\n\nBalance: $86,334,315.22\n\nDays: 365\n\nInterest: $6,086,569.22\n\nTotal repayments\n\n$0\n\nTotal interest\n\n$6,086,569.22\n\nTotal principal\n\n$0\n\nClosing balance\n\nDate: 30/06/2013\n\nBalance: $86,334,315.22",
  "outputs": {
    "enquiryRateFormatted": "7.05%",
    "enquiryYearEndMinusOneDisplay": "30/06/2012",
    "amalgamatedLoanNotPaidByEOIYFormatted": "$86,334,315.22",
    "openingBalancePayDays": "365",
    "openingBalanceInterestFormatted": "$6,086,569.22",
    "totalAmountOfRepaymentFormatted": "$0",
    "totalInterestFormatted": "$6,086,569.22",
    "principalFormatted": "$0",
    "enquiryYearEndDisplay": "30/06/2013",
    "minimumYearRepaymentFormatted": "$47,783,896.00"
  },
  "repayments": [],
  "inputs": {
    "incomeYearOfLoan": 2012,
    "fullTermOfAmalgamatedLoan": 2,
    "incomeYearOfEnquiring": 2013,
    "amalgamatedLoanNotPaidByEOIY": 86334315.2203923,
    "repayments": null,
    "lodgement_date": "27/4/2013"
  },
  "idx": 2434
}