{
  "id": "2023-09-05T11:58:47.588Z0.8985815463693891",
  "alert": "Start of result\nResult\n\nMinimum yearly repayment met.\n\nThe amount of the loan not repaid at the end of income year 2022-23 is $5.26.\n\nThe amalgamated loan will not be taken to be a dividend because the total repayments made are equal to or greater than the minimum yearly repayment required for income year 2022-23.\n\nInterest received by the private company must be included in the income tax return for 2022-23.\n\nMinimum yearly repayment\n\n$34.00\n\nBenchmark interest rate\n\n4.77%\n\nOpening balance:\n\nDate: 30/06/2022\n\nBalance: $122.32\n\nDays: 329\n\nInterest: $5.26\n\nPayments\n\nDate: 26/05/2023\n\nAmount: $122.32\n\nBalance: $0\n\nDays: 36\n\nInterest: $0\n\n\n\n\nTotal repayments\n\n$122.32\n\nTotal interest\n\n$5.26\n\nTotal principal\n\n$117.06\n\nClosing balance\n\nDate: 30/06/2023\n\nBalance: $5.26",
  "outputs": {
    "enquiryRateFormatted": "4.77%",
    "enquiryYearEndMinusOneDisplay": "30/06/2022",
    "amalgamatedLoanNotPaidByEOIYFormatted": "$122.32",
    "openingBalancePayDays": "329",
    "openingBalanceInterestFormatted": "$5.26",
    "totalAmountOfRepaymentFormatted": "$122.32",
    "totalInterestFormatted": "$5.26",
    "principalFormatted": "$117.06",
    "enquiryYearEndDisplay": "30/06/2023",
    "minimumYearRepaymentFormatted": "$34.00"
  },
  "repayments": [
    {
      "rd": "26/5/2023",
      "ra": 122.32772100722013
    }
  ],
  "inputs": {
    "incomeYearOfLoan": 2022,
    "fullTermOfAmalgamatedLoan": 4,
    "incomeYearOfEnquiring": 2023,
    "amalgamatedLoanNotPaidByEOIY": 122.32772100722012,
    "repayments": null,
    "lodgement_date": "14/5/2023"
  },
  "idx": 2885
}