{
  "id": "2023-10-31T17:43:06.596Z0.048496859108219215",
  "alert": "Start of result\nResult\n\nAmalgamated loan fully repaid.\n\nThe amalgamated loan has been paid in full.\u000bThe private company is not taken under Division 7A to pay a dividend to the shareholder or shareholder's associate.\n\nInterest received by the private company must be included in the income tax return for 2021-22.\n\nMinimum yearly repayment\n\n$47.00\n\nBenchmark interest rate\n\n4.52%\n\nOpening balance:\n\nDate: 30/06/2021\n\nBalance: $44.74\n\nDays: 261\n\nInterest: $1.45\n\nPayments\n\nDate: 19/03/2022\n\nAmount: $447.41\n\nBalance: $0\n\nDays: 104\n\nInterest: $0\n\n\n\n\nTotal repayments\n\n$447.41\n\nTotal interest\n\n$1.45\n\nTotal principal\n\n$445.96\n\nClosing balance\n\nDate: 30/06/2022\n\nBalance: $0",
  "outputs": {
    "enquiryRateFormatted": "4.52%",
    "enquiryYearEndMinusOneDisplay": "30/06/2021",
    "amalgamatedLoanNotPaidByEOIYFormatted": "$44.74",
    "openingBalancePayDays": "261",
    "openingBalanceInterestFormatted": "$1.45",
    "totalAmountOfRepaymentFormatted": "$447.41",
    "totalInterestFormatted": "$1.45",
    "principalFormatted": "$445.96",
    "enquiryYearEndDisplay": "30/06/2022",
    "minimumYearRepaymentFormatted": "$47.00",
    "loanAmountFormatted": "$0"
  },
  "repayments": [
    {
      "rd": "19/3/2022",
      "ra": 447.41846306643583
    }
  ],
  "inputs": {
    "incomeYearOfLoan": 2015,
    "fullTermOfAmalgamatedLoan": 7,
    "incomeYearOfEnquiring": 2022,
    "amalgamatedLoanNotPaidByEOIY": 44.741846306643545,
    "repayments": null,
    "lodgement_date": null
  },
  "idx": 2370
}