{
  "id": "2023-10-31T21:21:12.240Z0.0907693024150652",
  "alert": "Start of result\nResult\n\nAmalgamated loan fully repaid.\n\nThe amalgamated loan has been paid in full.\u000bThe private company is not taken under Division 7A to pay a dividend to the shareholder or shareholder's associate.\n\nInterest received by the private company must be included in the income tax return for 2000-01.\n\nMinimum yearly repayment\n\n$68.00\n\nBenchmark interest rate\n\n7.8%\n\nOpening balance:\n\nDate: 30/06/2000\n\nBalance: $122.21\n\nDays: 301\n\nInterest: $7.86\n\nPayments\n\nDate: 28/04/2001\n\nAmount: $1,222.17\n\nBalance: $0\n\nDays: 64\n\nInterest: $0\n\n\n\n\nTotal repayments\n\n$1,222.17\n\nTotal interest\n\n$7.86\n\nTotal principal\n\n$1,214.31\n\nClosing balance\n\nDate: 30/06/2001\n\nBalance: $0",
  "outputs": {
    "enquiryRateFormatted": "7.8%",
    "enquiryYearEndMinusOneDisplay": "30/06/2000",
    "amalgamatedLoanNotPaidByEOIYFormatted": "$122.21",
    "openingBalancePayDays": "301",
    "openingBalanceInterestFormatted": "$7.86",
    "totalAmountOfRepaymentFormatted": "$1,222.17",
    "totalInterestFormatted": "$7.86",
    "principalFormatted": "$1,214.31",
    "enquiryYearEndDisplay": "30/06/2001",
    "minimumYearRepaymentFormatted": "$68.00",
    "loanAmountFormatted": "$0"
  },
  "repayments": [
    {
      "rd": "28/4/2001",
      "ra": 1222.1710138863393
    }
  ],
  "inputs": {
    "incomeYearOfLoan": 1998,
    "fullTermOfAmalgamatedLoan": 4,
    "incomeYearOfEnquiring": 2001,
    "amalgamatedLoanNotPaidByEOIY": 122.21710138863394,
    "repayments": null,
    "lodgement_date": null
  },
  "idx": 7208
}