{
  "id": "2023-10-31T18:55:34.641Z0.760682678182783",
  "alert": "Start of result\nResult\n\nMinimum yearly repayment not met.\n\nThe amount of the loan not repaid at the end of income year 2011-12 is $26.28.\n\nThe private company may be taken to pay a dividend under Division 7A to the shareholder or shareholder's associate because the amount repaid during income year 2011-12 in relation to the amalgamated loan is less than the minimum yearly repayment required.\n\nInterest received by the private company must be included in the income tax return for 2011-12.\n\nMinimum yearly repayment\n\n$10.00\n\nBenchmark interest rate\n\n7.8%\n\nOpening balance:\n\nDate: 30/06/2011\n\nBalance: $26.28\n\nDays: 366\n\nInterest: $2.05\n\nTotal repayments\n\n$0\n\nTotal interest\n\n$2.05\n\nTotal principal\n\n$0\n\nClosing balance\n\nDate: 30/06/2012\n\nBalance: $26.28",
  "outputs": {
    "enquiryRateFormatted": "7.8%",
    "enquiryYearEndMinusOneDisplay": "30/06/2011",
    "amalgamatedLoanNotPaidByEOIYFormatted": "$26.28",
    "openingBalancePayDays": "366",
    "openingBalanceInterestFormatted": "$2.05",
    "totalAmountOfRepaymentFormatted": "$0",
    "totalInterestFormatted": "$2.05",
    "principalFormatted": "$0",
    "enquiryYearEndDisplay": "30/06/2012",
    "minimumYearRepaymentFormatted": "$10.00",
    "loanAmountFormatted": "$26.28"
  },
  "repayments": [],
  "inputs": {
    "incomeYearOfLoan": 2007,
    "fullTermOfAmalgamatedLoan": 7,
    "incomeYearOfEnquiring": 2012,
    "amalgamatedLoanNotPaidByEOIY": 26.287967460626156,
    "repayments": null,
    "lodgement_date": null
  },
  "idx": 4758
}