{
  "id": "2023-09-04T17:12:02.908Z0.5882494217169925",
  "alert": "Start of result\nResult\n\nMinimum yearly repayment met.\n\nThe amount of the loan not repaid at the end of income year 2014-15 is $2,272.63.\n\nThe amalgamated loan will not be taken to be a dividend because the total repayments made are equal to or greater than the minimum yearly repayment required for income year 2014-15.\n\nInterest received by the private company must be included in the income tax return for 2014-15.\n\nMinimum yearly repayment\n\n$1,169.00\n\nBenchmark interest rate\n\n5.95%\n\nOpening balance:\n\nDate: 30/06/2014\n\nBalance: $7,814.00\n\nDays: 0\n\nInterest: $0\n\nPayments\n\nDate: 01/07/2014\n\nAmount: $5,669.00\n\nBalance: $2,145.00\n\nDays: 365\n\nInterest: $127.63\n\n\n\n\nTotal repayments\n\n$5,669.00\n\nTotal interest\n\n$127.63\n\nTotal principal\n\n$5,541.37\n\nClosing balance\n\nDate: 30/06/2015\n\nBalance: $2,272.63",
  "outputs": {
    "enquiryRateFormatted": "5.95%",
    "enquiryYearEndMinusOneDisplay": "30/06/2014",
    "amalgamatedLoanNotPaidByEOIYFormatted": "$7,814.00",
    "openingBalancePayDays": "0",
    "openingBalanceInterestFormatted": "$0",
    "totalAmountOfRepaymentFormatted": "$5,669.00",
    "totalInterestFormatted": "$127.63",
    "principalFormatted": "$5,541.37",
    "enquiryYearEndDisplay": "30/06/2015",
    "minimumYearRepaymentFormatted": "$1,169.00"
  },
  "repayments": [
    {
      "rd": "1/7/2014",
      "ra": 5669
    }
  ],
  "inputs": {
    "incomeYearOfLoan": 2014,
    "fullTermOfAmalgamatedLoan": 2,
    "incomeYearOfEnquiring": 2015,
    "amalgamatedLoanNotPaidByEOIY": 7814,
    "repayments": null,
    "lodgement_date": "27/4/2015"
  },
  "idx": 1832
}