{
  "id": "2023-09-06T21:45:22.325Z0.5504154078391208",
  "alert": "Start of result\nResult\n\nMinimum yearly repayment met.\n\nThe amount of the loan not repaid at the end of income year 2007-08 is $3.42.\n\nThe amalgamated loan will not be taken to be a dividend because the total repayments made are equal to or greater than the minimum yearly repayment required for income year 2007-08.\n\nInterest received by the private company must be included in the income tax return for 2007-08.\n\nMinimum yearly repayment\n\n$32.00\n\nBenchmark interest rate\n\n8.05%\n\nOpening balance:\n\nDate: 30/06/2007\n\nBalance: $57.76\n\nDays: 269\n\nInterest: $3.42\n\nPayments\n\nDate: 26/03/2008\n\nAmount: $57.76\n\nBalance: $0\n\nDays: 97\n\nInterest: $0\n\n\n\n\nTotal repayments\n\n$57.76\n\nTotal interest\n\n$3.42\n\nTotal principal\n\n$54.34\n\nClosing balance\n\nDate: 30/06/2008\n\nBalance: $3.42",
  "outputs": {
    "enquiryRateFormatted": "8.05%",
    "enquiryYearEndMinusOneDisplay": "30/06/2007",
    "amalgamatedLoanNotPaidByEOIYFormatted": "$57.76",
    "openingBalancePayDays": "269",
    "openingBalanceInterestFormatted": "$3.42",
    "totalAmountOfRepaymentFormatted": "$57.76",
    "totalInterestFormatted": "$3.42",
    "principalFormatted": "$54.34",
    "enquiryYearEndDisplay": "30/06/2008",
    "minimumYearRepaymentFormatted": "$32.00"
  },
  "repayments": [
    {
      "rd": "26/3/2008",
      "ra": 57.764459074822184
    }
  ],
  "inputs": {
    "incomeYearOfLoan": 2002,
    "fullTermOfAmalgamatedLoan": 7,
    "incomeYearOfEnquiring": 2008,
    "amalgamatedLoanNotPaidByEOIY": 57.76445907482219,
    "repayments": null,
    "lodgement_date": null
  },
  "idx": 6655
}