{
  "id": "2023-10-31T17:20:03.838Z0.04449777607237415",
  "alert": "Start of result\nResult\n\nAmalgamated loan fully repaid.\n\nThe amalgamated loan has been paid in full.\u000bThe private company is not taken under Division 7A to pay a dividend to the shareholder or shareholder's associate.\n\nInterest received by the private company must be included in the income tax return for 2021-22.\n\nMinimum yearly repayment\n\n$4.00\n\nBenchmark interest rate\n\n4.52%\n\nOpening balance:\n\nDate: 30/06/2021\n\nBalance: $7.21\n\nDays: 339\n\nInterest: $0.30\n\nPayments\n\nDate: 05/06/2022\n\nAmount: $72.13\n\nBalance: $0\n\nDays: 26\n\nInterest: $0\n\n\n\n\nTotal repayments\n\n$72.13\n\nTotal interest\n\n$0.30\n\nTotal principal\n\n$71.83\n\nClosing balance\n\nDate: 30/06/2022\n\nBalance: $0",
  "outputs": {
    "enquiryRateFormatted": "4.52%",
    "enquiryYearEndMinusOneDisplay": "30/06/2021",
    "amalgamatedLoanNotPaidByEOIYFormatted": "$7.21",
    "openingBalancePayDays": "339",
    "openingBalanceInterestFormatted": "$0.30",
    "totalAmountOfRepaymentFormatted": "$72.13",
    "totalInterestFormatted": "$0.30",
    "principalFormatted": "$71.83",
    "enquiryYearEndDisplay": "30/06/2022",
    "minimumYearRepaymentFormatted": "$4.00",
    "loanAmountFormatted": "$0"
  },
  "repayments": [
    {
      "rd": "5/6/2022",
      "ra": 72.13080128672118
    }
  ],
  "inputs": {
    "incomeYearOfLoan": 2019,
    "fullTermOfAmalgamatedLoan": 4,
    "incomeYearOfEnquiring": 2022,
    "amalgamatedLoanNotPaidByEOIY": 7.21308012867211,
    "repayments": null,
    "lodgement_date": null
  },
  "idx": 1097
}