{
  "id": "2023-09-06T03:07:49.492Z0.7615416362733989",
  "alert": "Start of result\nResult\n\nMinimum yearly repayment met.\n\nThe amount of the loan not repaid at the end of income year 2013-14 is $2,539.72.\n\nThe amalgamated loan will not be taken to be a dividend because the total repayments made are equal to or greater than the minimum yearly repayment required for income year 2013-14.\n\nInterest received by the private company must be included in the income tax return for 2013-14.\n\nMinimum yearly repayment\n\n$3,439.00\n\nBenchmark interest rate\n\n6.2%\n\nOpening balance:\n\nDate: 30/06/2013\n\nBalance: $11,863.00\n\nDays: 309\n\nInterest: $622.66\n\nPayments\n\nDate: 06/05/2014\n\nAmount: $9,964.00\n\nBalance: $1,899.00\n\nDays: 56\n\nInterest: $18.06\n\n\n\n\nTotal repayments\n\n$9,964.00\n\nTotal interest\n\n$640.72\n\nTotal principal\n\n$9,323.28\n\nClosing balance\n\nDate: 30/06/2014\n\nBalance: $2,539.72",
  "outputs": {
    "enquiryRateFormatted": "6.2%",
    "enquiryYearEndMinusOneDisplay": "30/06/2013",
    "amalgamatedLoanNotPaidByEOIYFormatted": "$11,863.00",
    "openingBalancePayDays": "309",
    "openingBalanceInterestFormatted": "$622.66",
    "totalAmountOfRepaymentFormatted": "$9,964.00",
    "totalInterestFormatted": "$640.72",
    "principalFormatted": "$9,323.28",
    "enquiryYearEndDisplay": "30/06/2014",
    "minimumYearRepaymentFormatted": "$3,439.00"
  },
  "repayments": [
    {
      "rd": "6/5/2014",
      "ra": 9964
    }
  ],
  "inputs": {
    "incomeYearOfLoan": 2013,
    "fullTermOfAmalgamatedLoan": 4,
    "incomeYearOfEnquiring": 2014,
    "amalgamatedLoanNotPaidByEOIY": 11863,
    "repayments": null,
    "lodgement_date": "6/8/2013"
  },
  "idx": 2976
}