{
  "id": "2023-10-31T17:27:32.067Z0.5904897538792832",
  "alert": "Start of result\nResult\n\nMinimum yearly repayment not met.\n\nThe amount of the loan not repaid at the end of income year 2019-20 is $9,182.00.\n\nThe private company may be taken to pay a dividend under Division 7A to the shareholder or shareholder's associate because the amount repaid during income year 2019-20 in relation to the amalgamated loan is less than the minimum yearly repayment required.\n\nInterest received by the private company must be included in the income tax return for 2019-20.\n\nMinimum yearly repayment\n\n$9,675.00\n\nBenchmark interest rate\n\n5.37%\n\nOpening balance:\n\nDate: 30/06/2019\n\nBalance: $9,182.00\n\nDays: 366\n\nInterest: $493.07\n\nTotal repayments\n\n$0\n\nTotal interest\n\n$493.07\n\nTotal principal\n\n$0\n\nClosing balance\n\nDate: 30/06/2020\n\nBalance: $9,182.00",
  "outputs": {
    "enquiryRateFormatted": "5.37%",
    "enquiryYearEndMinusOneDisplay": "30/06/2019",
    "amalgamatedLoanNotPaidByEOIYFormatted": "$9,182.00",
    "openingBalancePayDays": "366",
    "openingBalanceInterestFormatted": "$493.07",
    "totalAmountOfRepaymentFormatted": "$0",
    "totalInterestFormatted": "$493.07",
    "principalFormatted": "$0",
    "enquiryYearEndDisplay": "30/06/2020",
    "minimumYearRepaymentFormatted": "$9,675.00",
    "loanAmountFormatted": "$9,182.00"
  },
  "repayments": [],
  "inputs": {
    "incomeYearOfLoan": 2017,
    "fullTermOfAmalgamatedLoan": 3,
    "incomeYearOfEnquiring": 2020,
    "amalgamatedLoanNotPaidByEOIY": 9182,
    "repayments": null,
    "lodgement_date": null
  },
  "idx": 1561
}