{
  "id": "2023-09-05T18:00:00.897Z0.9549258401649445",
  "alert": "Start of result\nResult\n\nMinimum yearly repayment not met.\n\nThe amount of the loan not repaid at the end of income year 2020-21 is $6,630.24.\n\nThe private company may be taken to pay a dividend under Division 7A to the shareholder or shareholder's associate because the amount repaid during income year 2020-21 in relation to the amalgamated loan is less than the minimum yearly repayment required.\n\nInterest received by the private company must be included in the income tax return for 2020-21.\n\nMinimum yearly repayment\n\n$11,937.00\n\nBenchmark interest rate\n\n4.52%\n\nOpening balance:\n\nDate: 30/06/2020\n\nBalance: $11,421.00\n\nDays: 243\n\nInterest: $343.68\n\nPayments\n\nDate: 01/03/2021\n\nAmount: $5,228.00\n\nBalance: $6,193.00\n\nDays: 122\n\nInterest: $93.56\n\n\n\n\nTotal repayments\n\n$5,228.00\n\nTotal interest\n\n$437.24\n\nTotal principal\n\n$4,790.76\n\nClosing balance\n\nDate: 30/06/2021\n\nBalance: $6,630.24",
  "outputs": {
    "enquiryRateFormatted": "4.52%",
    "enquiryYearEndMinusOneDisplay": "30/06/2020",
    "amalgamatedLoanNotPaidByEOIYFormatted": "$11,421.00",
    "openingBalancePayDays": "243",
    "openingBalanceInterestFormatted": "$343.68",
    "totalAmountOfRepaymentFormatted": "$5,228.00",
    "totalInterestFormatted": "$437.24",
    "principalFormatted": "$4,790.76",
    "enquiryYearEndDisplay": "30/06/2021",
    "minimumYearRepaymentFormatted": "$11,937.00"
  },
  "repayments": [
    {
      "rd": "1/3/2021",
      "ra": 5228
    }
  ],
  "inputs": {
    "incomeYearOfLoan": 2018,
    "fullTermOfAmalgamatedLoan": 3,
    "incomeYearOfEnquiring": 2021,
    "amalgamatedLoanNotPaidByEOIY": 11421,
    "repayments": null,
    "lodgement_date": null
  },
  "idx": 6278
}