{
  "id": "2023-09-06T06:59:00.304Z0.016229860957269082",
  "alert": "Start of result\nResult\n\nMinimum yearly repayment met.\n\nThe amount of the loan not repaid at the end of income year 2013-14 is $1.34.\n\nThe amalgamated loan will not be taken to be a dividend because the total repayments made are equal to or greater than the minimum yearly repayment required for income year 2013-14.\n\nInterest received by the private company must be included in the income tax return for 2013-14.\n\nMinimum yearly repayment\n\n$14.00\n\nBenchmark interest rate\n\n6.2%\n\nOpening balance:\n\nDate: 30/06/2013\n\nBalance: $59.27\n\nDays: 133\n\nInterest: $1.34\n\nPayments\n\nDate: 11/11/2013\n\nAmount: $59.27\n\nBalance: $0\n\nDays: 232\n\nInterest: $0\n\n\n\n\nTotal repayments\n\n$59.27\n\nTotal interest\n\n$1.34\n\nTotal principal\n\n$57.93\n\nClosing balance\n\nDate: 30/06/2014\n\nBalance: $1.34",
  "outputs": {
    "enquiryRateFormatted": "6.2%",
    "enquiryYearEndMinusOneDisplay": "30/06/2013",
    "amalgamatedLoanNotPaidByEOIYFormatted": "$59.27",
    "openingBalancePayDays": "133",
    "openingBalanceInterestFormatted": "$1.34",
    "totalAmountOfRepaymentFormatted": "$59.27",
    "totalInterestFormatted": "$1.34",
    "principalFormatted": "$57.93",
    "enquiryYearEndDisplay": "30/06/2014",
    "minimumYearRepaymentFormatted": "$14.00"
  },
  "repayments": [
    {
      "rd": "11/11/2013",
      "ra": 59.27813158916251
    }
  ],
  "inputs": {
    "incomeYearOfLoan": 2011,
    "fullTermOfAmalgamatedLoan": 7,
    "incomeYearOfEnquiring": 2014,
    "amalgamatedLoanNotPaidByEOIY": 59.2781315891628,
    "repayments": null,
    "lodgement_date": null
  },
  "idx": 7416
}