{
  "id": "2023-10-31T18:24:23.846Z0.11455718375567703",
  "alert": "Start of result\nResult\n\nAmalgamated loan fully repaid.\n\nThe amalgamated loan has been paid in full.\u000bThe private company is not taken under Division 7A to pay a dividend to the shareholder or shareholder's associate.\n\nInterest received by the private company must be included in the income tax return for 2016-17.\n\nMinimum yearly repayment\n\n$9,481.00\n\nBenchmark interest rate\n\n5.4%\n\nOpening balance:\n\nDate: 30/06/2016\n\nBalance: $8,995.00\n\nDays: 137\n\nInterest: $182.32\n\nPayments\n\nDate: 15/11/2016\n\nAmount: $6,805.00\n\nBalance: $2,190.00\n\nDays: 92\n\nInterest: $29.81\n\n\n\n\nDate: 15/02/2017\n\nAmount: $623.00\n\nBalance: $1,567.00\n\nDays: 15\n\nInterest: $3.48\n\n\n\n\nDate: 02/03/2017\n\nAmount: $4,691.00\n\nBalance: $0\n\nDays: 121\n\nInterest: $0\n\n\n\n\nTotal repayments\n\n$12,119.00\n\nTotal interest\n\n$215.61\n\nTotal principal\n\n$11,903.39\n\nClosing balance\n\nDate: 30/06/2017\n\nBalance: $0",
  "outputs": {
    "enquiryRateFormatted": "5.4%",
    "enquiryYearEndMinusOneDisplay": "30/06/2016",
    "amalgamatedLoanNotPaidByEOIYFormatted": "$8,995.00",
    "openingBalancePayDays": "137",
    "openingBalanceInterestFormatted": "$182.32",
    "totalAmountOfRepaymentFormatted": "$12,119.00",
    "totalInterestFormatted": "$215.61",
    "principalFormatted": "$11,903.39",
    "enquiryYearEndDisplay": "30/06/2017",
    "minimumYearRepaymentFormatted": "$9,481.00",
    "loanAmountFormatted": "$0"
  },
  "repayments": [
    {
      "rd": "15/11/2016",
      "ra": 6805
    },
    {
      "rd": "15/2/2017",
      "ra": 623
    },
    {
      "rd": "2/3/2017",
      "ra": 4691
    }
  ],
  "inputs": {
    "incomeYearOfLoan": 2010,
    "fullTermOfAmalgamatedLoan": 7,
    "incomeYearOfEnquiring": 2017,
    "amalgamatedLoanNotPaidByEOIY": 8995,
    "repayments": null,
    "lodgement_date": null
  },
  "idx": 3922
}