{
  "id": "2023-10-31T19:16:44.553Z0.0886778818925894",
  "alert": "Start of result\nResult\n\nAmalgamated loan fully repaid.\n\nThe amalgamated loan has been paid in full.\u000bThe private company is not taken under Division 7A to pay a dividend to the shareholder or shareholder's associate.\n\nInterest received by the private company must be included in the income tax return for 2006-07.\n\nMinimum yearly repayment\n\n$7.00\n\nBenchmark interest rate\n\n7.55%\n\nOpening balance:\n\nDate: 30/06/2006\n\nBalance: $23.47\n\nDays: 176\n\nInterest: $0.85\n\nPayments\n\nDate: 24/12/2006\n\nAmount: $234.78\n\nBalance: $0\n\nDays: 189\n\nInterest: $0\n\n\n\n\nTotal repayments\n\n$234.78\n\nTotal interest\n\n$0.85\n\nTotal principal\n\n$233.93\n\nClosing balance\n\nDate: 30/06/2007\n\nBalance: $0",
  "outputs": {
    "enquiryRateFormatted": "7.55%",
    "enquiryYearEndMinusOneDisplay": "30/06/2006",
    "amalgamatedLoanNotPaidByEOIYFormatted": "$23.47",
    "openingBalancePayDays": "176",
    "openingBalanceInterestFormatted": "$0.85",
    "totalAmountOfRepaymentFormatted": "$234.78",
    "totalInterestFormatted": "$0.85",
    "principalFormatted": "$233.93",
    "enquiryYearEndDisplay": "30/06/2007",
    "minimumYearRepaymentFormatted": "$7.00",
    "loanAmountFormatted": "$0"
  },
  "repayments": [
    {
      "rd": "24/12/2006",
      "ra": 234.78247465804998
    }
  ],
  "inputs": {
    "incomeYearOfLoan": 2005,
    "fullTermOfAmalgamatedLoan": 5,
    "incomeYearOfEnquiring": 2007,
    "amalgamatedLoanNotPaidByEOIY": 23.478247465805026,
    "repayments": null,
    "lodgement_date": null
  },
  "idx": 5257
}