{
  "id": "2023-09-04T21:38:56.472Z0.36144955448510463",
  "alert": "Start of result\nResult\n\nMinimum yearly repayment met.\n\nThe amount of the loan not repaid at the end of income year 2008-09 is $366.66.\n\nThe amalgamated loan will not be taken to be a dividend because the total repayments made are equal to or greater than the minimum yearly repayment required for income year 2008-09.\n\nInterest received by the private company must be included in the income tax return for 2008-09.\n\nMinimum yearly repayment\n\n$322.00\n\nBenchmark interest rate\n\n9.45%\n\nOpening balance:\n\nDate: 30/06/2008\n\nBalance: $1,237.00\n\nDays: 0\n\nInterest: $0\n\nPayments\n\nDate: 01/07/2008\n\nAmount: $902.00\n\nBalance: $335.00\n\nDays: 365\n\nInterest: $31.66\n\n\n\n\nTotal repayments\n\n$902.00\n\nTotal interest\n\n$31.66\n\nTotal principal\n\n$870.34\n\nClosing balance\n\nDate: 30/06/2009\n\nBalance: $366.66",
  "outputs": {
    "enquiryRateFormatted": "9.45%",
    "enquiryYearEndMinusOneDisplay": "30/06/2008",
    "amalgamatedLoanNotPaidByEOIYFormatted": "$1,237.00",
    "openingBalancePayDays": "0",
    "openingBalanceInterestFormatted": "$0",
    "totalAmountOfRepaymentFormatted": "$902.00",
    "totalInterestFormatted": "$31.66",
    "principalFormatted": "$870.34",
    "enquiryYearEndDisplay": "30/06/2009",
    "minimumYearRepaymentFormatted": "$322.00"
  },
  "repayments": [
    {
      "rd": "1/7/2008",
      "ra": 902
    }
  ],
  "inputs": {
    "incomeYearOfLoan": 2006,
    "fullTermOfAmalgamatedLoan": 7,
    "incomeYearOfEnquiring": 2009,
    "amalgamatedLoanNotPaidByEOIY": 1237,
    "repayments": null,
    "lodgement_date": null
  },
  "idx": 1511
}