{
  "id": "2023-09-06T06:29:36.495Z0.3498631896347175",
  "alert": "Start of result\nResult\n\nMinimum yearly repayment met.\n\nThe amount of the loan not repaid at the end of income year 2014-15 is $0.96.\n\nThe amalgamated loan will not be taken to be a dividend because the total repayments made are equal to or greater than the minimum yearly repayment required for income year 2014-15.\n\nInterest received by the private company must be included in the income tax return for 2014-15.\n\nMinimum yearly repayment\n\n$51.00\n\nBenchmark interest rate\n\n5.95%\n\nOpening balance:\n\nDate: 30/06/2014\n\nBalance: $93.46\n\nDays: 63\n\nInterest: $0.96\n\nPayments\n\nDate: 02/09/2014\n\nAmount: $93.46\n\nBalance: $0\n\nDays: 302\n\nInterest: $0\n\n\n\n\nTotal repayments\n\n$93.46\n\nTotal interest\n\n$0.96\n\nTotal principal\n\n$92.50\n\nClosing balance\n\nDate: 30/06/2015\n\nBalance: $0.96",
  "outputs": {
    "enquiryRateFormatted": "5.95%",
    "enquiryYearEndMinusOneDisplay": "30/06/2014",
    "amalgamatedLoanNotPaidByEOIYFormatted": "$93.46",
    "openingBalancePayDays": "63",
    "openingBalanceInterestFormatted": "$0.96",
    "totalAmountOfRepaymentFormatted": "$93.46",
    "totalInterestFormatted": "$0.96",
    "principalFormatted": "$92.50",
    "enquiryYearEndDisplay": "30/06/2015",
    "minimumYearRepaymentFormatted": "$51.00"
  },
  "repayments": [
    {
      "rd": "2/9/2014",
      "ra": 93.46942428667717
    }
  ],
  "inputs": {
    "incomeYearOfLoan": 2011,
    "fullTermOfAmalgamatedLoan": 5,
    "incomeYearOfEnquiring": 2015,
    "amalgamatedLoanNotPaidByEOIY": 93.46942428667717,
    "repayments": null,
    "lodgement_date": null
  },
  "idx": 5921
}