{
  "id": "2023-10-31T20:27:07.501Z0.13300961449894166",
  "alert": "Start of result\nResult\n\nAmalgamated loan fully repaid.\n\nThe amalgamated loan has been paid in full.\u000bThe private company is not taken under Division 7A to pay a dividend to the shareholder or shareholder's associate.\n\nInterest received by the private company must be included in the income tax return for 2001-02.\n\nMinimum yearly repayment\n\n$1,609.00\n\nBenchmark interest rate\n\n6.8%\n\nOpening balance:\n\nDate: 30/06/2001\n\nBalance: $1,507.00\n\nDays: 180\n\nInterest: $50.54\n\nPayments\n\nDate: 28/12/2001\n\nAmount: $6,768.00\n\nBalance: $0\n\nDays: 109\n\nInterest: $0\n\n\n\n\nDate: 16/04/2002\n\nAmount: $869.00\n\nBalance: $0\n\nDays: 32\n\nInterest: $0\n\n\n\n\nDate: 18/05/2002\n\nAmount: $3,944.00\n\nBalance: $0\n\nDays: 44\n\nInterest: $0\n\n\n\n\nTotal repayments\n\n$11,581.00\n\nTotal interest\n\n$50.54\n\nTotal principal\n\n$11,530.46\n\nClosing balance\n\nDate: 30/06/2002\n\nBalance: $0",
  "outputs": {
    "enquiryRateFormatted": "6.8%",
    "enquiryYearEndMinusOneDisplay": "30/06/2001",
    "amalgamatedLoanNotPaidByEOIYFormatted": "$1,507.00",
    "openingBalancePayDays": "180",
    "openingBalanceInterestFormatted": "$50.54",
    "totalAmountOfRepaymentFormatted": "$11,581.00",
    "totalInterestFormatted": "$50.54",
    "principalFormatted": "$11,530.46",
    "enquiryYearEndDisplay": "30/06/2002",
    "minimumYearRepaymentFormatted": "$1,609.00",
    "loanAmountFormatted": "$0"
  },
  "repayments": [
    {
      "rd": "28/12/2001",
      "ra": 6768
    },
    {
      "rd": "16/4/2002",
      "ra": 869
    },
    {
      "rd": "18/5/2002",
      "ra": 3944
    }
  ],
  "inputs": {
    "incomeYearOfLoan": 2000,
    "fullTermOfAmalgamatedLoan": 2,
    "incomeYearOfEnquiring": 2002,
    "amalgamatedLoanNotPaidByEOIY": 1507,
    "repayments": null,
    "lodgement_date": null
  },
  "idx": 6480
}