{
  "id": "2023-09-05T13:02:08.062Z0.4464785811729224",
  "alert": "Start of result\nResult\n\nMinimum yearly repayment not met.\n\nThe amount of the loan not repaid at the end of income year 2023-24 is $159.13.\n\nThe private company may be taken to pay a dividend under Division 7A to the shareholder or shareholder's associate because the amount repaid during income year 2023-24 in relation to the amalgamated loan is less than the minimum yearly repayment required.\n\nInterest received by the private company must be included in the income tax return for 2023-24.\n\nMinimum yearly repayment\n\n$2,979.00\n\nBenchmark interest rate\n\n8.27%\n\nOpening balance:\n\nDate: 30/06/2023\n\nBalance: $2,751.00\n\nDays: 256\n\nInterest: $159.13\n\nPayments\n\nDate: 13/03/2024\n\nAmount: $2,751.00\n\nBalance: $0\n\nDays: 110\n\nInterest: $0\n\n\n\n\nTotal repayments\n\n$2,751.00\n\nTotal interest\n\n$159.13\n\nTotal principal\n\n$2,591.87\n\nClosing balance\n\nDate: 30/06/2024\n\nBalance: $159.13",
  "outputs": {
    "enquiryRateFormatted": "8.27%",
    "enquiryYearEndMinusOneDisplay": "30/06/2023",
    "amalgamatedLoanNotPaidByEOIYFormatted": "$2,751.00",
    "openingBalancePayDays": "256",
    "openingBalanceInterestFormatted": "$159.13",
    "totalAmountOfRepaymentFormatted": "$2,751.00",
    "totalInterestFormatted": "$159.13",
    "principalFormatted": "$2,591.87",
    "enquiryYearEndDisplay": "30/06/2024",
    "minimumYearRepaymentFormatted": "$2,979.00"
  },
  "repayments": [
    {
      "rd": "13/3/2024",
      "ra": 2751
    }
  ],
  "inputs": {
    "incomeYearOfLoan": 2021,
    "fullTermOfAmalgamatedLoan": 3,
    "incomeYearOfEnquiring": 2024,
    "amalgamatedLoanNotPaidByEOIY": 2751,
    "repayments": null,
    "lodgement_date": null
  },
  "idx": 6604
}