{
  "id": "2023-10-31T19:30:15.919Z0.7467504338996581",
  "alert": "Start of result\nResult\n\nAmalgamated loan fully repaid.\n\nThe amalgamated loan has been paid in full.\u000bThe private company is not taken under Division 7A to pay a dividend to the shareholder or shareholder's associate.\n\nInterest received by the private company must be included in the income tax return for 2004-05.\n\nMinimum yearly repayment\n\n$549.00\n\nBenchmark interest rate\n\n7.05%\n\nOpening balance:\n\nDate: 30/06/2004\n\nBalance: $2,250.00\n\nDays: 183\n\nInterest: $79.53\n\nPayments\n\nDate: 31/12/2004\n\nAmount: $8,418.00\n\nBalance: $0\n\nDays: 182\n\nInterest: $0\n\n\n\n\nTotal repayments\n\n$8,418.00\n\nTotal interest\n\n$79.53\n\nTotal principal\n\n$8,338.47\n\nClosing balance\n\nDate: 30/06/2005\n\nBalance: $0",
  "outputs": {
    "enquiryRateFormatted": "7.05%",
    "enquiryYearEndMinusOneDisplay": "30/06/2004",
    "amalgamatedLoanNotPaidByEOIYFormatted": "$2,250.00",
    "openingBalancePayDays": "183",
    "openingBalanceInterestFormatted": "$79.53",
    "totalAmountOfRepaymentFormatted": "$8,418.00",
    "totalInterestFormatted": "$79.53",
    "principalFormatted": "$8,338.47",
    "enquiryYearEndDisplay": "30/06/2005",
    "minimumYearRepaymentFormatted": "$549.00",
    "loanAmountFormatted": "$0"
  },
  "repayments": [
    {
      "rd": "31/12/2004",
      "ra": 8418
    }
  ],
  "inputs": {
    "incomeYearOfLoan": 2004,
    "fullTermOfAmalgamatedLoan": 5,
    "incomeYearOfEnquiring": 2005,
    "amalgamatedLoanNotPaidByEOIY": 2250,
    "repayments": null,
    "lodgement_date": "29/10/2004"
  },
  "idx": 5534
}