{
  "id": "2023-10-31T17:57:14.025Z0.6599278484877792",
  "alert": "Start of result\nResult\n\nMinimum yearly repayment not met.\n\nThe amount of the loan not repaid at the end of income year 2013-14 is $90.11.\n\nThe private company may be taken to pay a dividend under Division 7A to the shareholder or shareholder's associate because the amount repaid during income year 2013-14 in relation to the amalgamated loan is less than the minimum yearly repayment required.\n\nInterest received by the private company must be included in the income tax return for 2013-14.\n\nMinimum yearly repayment\n\n$22.00\n\nBenchmark interest rate\n\n6.2%\n\nOpening balance:\n\nDate: 30/06/2013\n\nBalance: $90.11\n\nDays: 365\n\nInterest: $5.59\n\nTotal repayments\n\n$0\n\nTotal interest\n\n$5.59\n\nTotal principal\n\n$0\n\nClosing balance\n\nDate: 30/06/2014\n\nBalance: $90.11",
  "outputs": {
    "enquiryRateFormatted": "6.2%",
    "enquiryYearEndMinusOneDisplay": "30/06/2013",
    "amalgamatedLoanNotPaidByEOIYFormatted": "$90.11",
    "openingBalancePayDays": "365",
    "openingBalanceInterestFormatted": "$5.59",
    "totalAmountOfRepaymentFormatted": "$0",
    "totalInterestFormatted": "$5.59",
    "principalFormatted": "$0",
    "enquiryYearEndDisplay": "30/06/2014",
    "minimumYearRepaymentFormatted": "$22.00",
    "loanAmountFormatted": "$90.11"
  },
  "repayments": [],
  "inputs": {
    "incomeYearOfLoan": 2013,
    "fullTermOfAmalgamatedLoan": 5,
    "incomeYearOfEnquiring": 2014,
    "amalgamatedLoanNotPaidByEOIY": 90.11346901515316,
    "repayments": null,
    "lodgement_date": "30/6/2014"
  },
  "idx": 2984
}