{
  "id": "2023-09-04T20:59:58.987Z0.307187941518015",
  "alert": "Start of result\nResult\n\nMinimum yearly repayment not met.\n\nThe amount of the loan not repaid at the end of income year 2014-15 is $81,023,583.84.\n\nThe private company may be taken to pay a dividend under Division 7A to the shareholder or shareholder's associate because the amount repaid during income year 2014-15 in relation to the amalgamated loan is less than the minimum yearly repayment required.\n\nInterest received by the private company must be included in the income tax return for 2014-15.\n\nMinimum yearly repayment\n\n$30,283,681.00\n\nBenchmark interest rate\n\n5.95%\n\nOpening balance:\n\nDate: 30/06/2014\n\nBalance: $81,023,583.84\n\nDays: 365\n\nInterest: $4,820,903.24\n\nTotal repayments\n\n$0\n\nTotal interest\n\n$4,820,903.24\n\nTotal principal\n\n$0\n\nClosing balance\n\nDate: 30/06/2015\n\nBalance: $81,023,583.84",
  "outputs": {
    "enquiryRateFormatted": "5.95%",
    "enquiryYearEndMinusOneDisplay": "30/06/2014",
    "amalgamatedLoanNotPaidByEOIYFormatted": "$81,023,583.84",
    "openingBalancePayDays": "365",
    "openingBalanceInterestFormatted": "$4,820,903.24",
    "totalAmountOfRepaymentFormatted": "$0",
    "totalInterestFormatted": "$4,820,903.24",
    "principalFormatted": "$0",
    "enquiryYearEndDisplay": "30/06/2015",
    "minimumYearRepaymentFormatted": "$30,283,681.00"
  },
  "repayments": [],
  "inputs": {
    "incomeYearOfLoan": 2010,
    "fullTermOfAmalgamatedLoan": 7,
    "incomeYearOfEnquiring": 2015,
    "amalgamatedLoanNotPaidByEOIY": 81023583.84376888,
    "repayments": null,
    "lodgement_date": null
  },
  "idx": 468
}