{
  "id": "2023-09-05T15:19:48.858Z0.054508936056839596",
  "alert": "Start of result\nResult\n\nMinimum yearly repayment met.\n\nThe amount of the loan not repaid at the end of income year 2023-24 is $2.01.\n\nThe amalgamated loan will not be taken to be a dividend because the total repayments made are equal to or greater than the minimum yearly repayment required for income year 2023-24.\n\nInterest received by the private company must be included in the income tax return for 2023-24.\n\nMinimum yearly repayment\n\n$19.00\n\nBenchmark interest rate\n\n8.27%\n\nOpening balance:\n\nDate: 30/06/2023\n\nBalance: $33.50\n\nDays: 265\n\nInterest: $2.01\n\nPayments\n\nDate: 22/03/2024\n\nAmount: $33.50\n\nBalance: $0\n\nDays: 101\n\nInterest: $0\n\n\n\n\nTotal repayments\n\n$33.50\n\nTotal interest\n\n$2.01\n\nTotal principal\n\n$31.49\n\nClosing balance\n\nDate: 30/06/2024\n\nBalance: $2.01",
  "outputs": {
    "enquiryRateFormatted": "8.27%",
    "enquiryYearEndMinusOneDisplay": "30/06/2023",
    "amalgamatedLoanNotPaidByEOIYFormatted": "$33.50",
    "openingBalancePayDays": "265",
    "openingBalanceInterestFormatted": "$2.01",
    "totalAmountOfRepaymentFormatted": "$33.50",
    "totalInterestFormatted": "$2.01",
    "principalFormatted": "$31.49",
    "enquiryYearEndDisplay": "30/06/2024",
    "minimumYearRepaymentFormatted": "$19.00"
  },
  "repayments": [
    {
      "rd": "22/3/2024",
      "ra": 33.50643794278753
    }
  ],
  "inputs": {
    "incomeYearOfLoan": 2020,
    "fullTermOfAmalgamatedLoan": 5,
    "incomeYearOfEnquiring": 2024,
    "amalgamatedLoanNotPaidByEOIY": 33.50643794278753,
    "repayments": null,
    "lodgement_date": null
  },
  "idx": 5881
}