{
  "id": "2023-09-04T20:55:48.566Z0.41972968653976017",
  "alert": "Start of result\nResult\n\nMinimum yearly repayment not met.\n\nThe amount of the loan not repaid at the end of income year 2011-12 is $10,531.00.\n\nThe private company may be taken to pay a dividend under Division 7A to the shareholder or shareholder's associate because the amount repaid during income year 2011-12 in relation to the amalgamated loan is less than the minimum yearly repayment required.\n\nInterest received by the private company must be included in the income tax return for 2011-12.\n\nMinimum yearly repayment\n\n$4,072.00\n\nBenchmark interest rate\n\n7.8%\n\nOpening balance:\n\nDate: 30/06/2011\n\nBalance: $10,531.00\n\nDays: 0\n\nInterest: $0\n\nPayments\n\nDate: 01/07/2011\n\nAmount: $49.00\n\nBalance: $10,482.00\n\nDays: 366\n\nInterest: $817.60\n\n\n\n\nTotal repayments\n\n$49.00\n\nTotal interest\n\n$817.60\n\nTotal principal\n\n$0\n\nClosing balance\n\nDate: 30/06/2012\n\nBalance: $10,531.00",
  "outputs": {
    "enquiryRateFormatted": "7.8%",
    "enquiryYearEndMinusOneDisplay": "30/06/2011",
    "amalgamatedLoanNotPaidByEOIYFormatted": "$10,531.00",
    "openingBalancePayDays": "0",
    "openingBalanceInterestFormatted": "$0",
    "totalAmountOfRepaymentFormatted": "$49.00",
    "totalInterestFormatted": "$817.60",
    "principalFormatted": "$0",
    "enquiryYearEndDisplay": "30/06/2012",
    "minimumYearRepaymentFormatted": "$4,072.00"
  },
  "repayments": [
    {
      "rd": "1/7/2011",
      "ra": 49
    }
  ],
  "inputs": {
    "incomeYearOfLoan": 2010,
    "fullTermOfAmalgamatedLoan": 4,
    "incomeYearOfEnquiring": 2012,
    "amalgamatedLoanNotPaidByEOIY": 10531,
    "repayments": null,
    "lodgement_date": null
  },
  "idx": 321
}