{
  "id": "2023-10-31T18:55:43.449Z0.36906630882462976",
  "alert": "Start of result\nResult\n\nMinimum yearly repayment met.\n\nThe amount of the loan not repaid at the end of income year 2010-11 is $3,976.67.\n\n\u000b\n\nThe amalgamated loan will not be taken to be a dividend because the total repayments made are equal to or greater than the minimum yearly repayment required for income year 2010-11.\n\nInterest received by the private company must be included in the income tax return for 2010-11.\n\nMinimum yearly repayment\n\n$3,593.00\n\nBenchmark interest rate\n\n7.4%\n\nOpening balance:\n\nDate: 30/06/2010\n\nBalance: $12,061.00\n\nDays: 162\n\nInterest: $396.13\n\nPayments\n\nDate: 10/12/2010\n\nAmount: $8,622.00\n\nBalance: $3,439.00\n\nDays: 203\n\nInterest: $141.54\n\n\n\n\nTotal repayments\n\n$8,622.00\n\nTotal interest\n\n$537.67\n\nTotal principal\n\n$8,084.33\n\nClosing balance\n\nDate: 30/06/2011\n\nBalance: $3,976.67",
  "outputs": {
    "enquiryRateFormatted": "7.4%",
    "enquiryYearEndMinusOneDisplay": "30/06/2010",
    "amalgamatedLoanNotPaidByEOIYFormatted": "$12,061.00",
    "openingBalancePayDays": "162",
    "openingBalanceInterestFormatted": "$396.13",
    "totalAmountOfRepaymentFormatted": "$8,622.00",
    "totalInterestFormatted": "$537.67",
    "principalFormatted": "$8,084.33",
    "enquiryYearEndDisplay": "30/06/2011",
    "minimumYearRepaymentFormatted": "$3,593.00",
    "loanAmountFormatted": "$3,976.67"
  },
  "repayments": [
    {
      "rd": "10/12/2010",
      "ra": 8622
    }
  ],
  "inputs": {
    "incomeYearOfLoan": 2007,
    "fullTermOfAmalgamatedLoan": 7,
    "incomeYearOfEnquiring": 2011,
    "amalgamatedLoanNotPaidByEOIY": 12061,
    "repayments": null,
    "lodgement_date": null
  },
  "idx": 4761
}