{
  "id": "2023-09-06T01:39:53.341Z0.9108495506411609",
  "alert": "Start of result\nResult\n\nMinimum yearly repayment not met.\n\nThe amount of the loan not repaid at the end of income year 2014-15 is $66.94.\n\nThe private company may be taken to pay a dividend under Division 7A to the shareholder or shareholder's associate because the amount repaid during income year 2014-15 in relation to the amalgamated loan is less than the minimum yearly repayment required.\n\nInterest received by the private company must be included in the income tax return for 2014-15.\n\nMinimum yearly repayment\n\n$14.00\n\nBenchmark interest rate\n\n5.95%\n\nOpening balance:\n\nDate: 30/06/2014\n\nBalance: $66.94\n\nDays: 365\n\nInterest: $3.98\n\nTotal repayments\n\n$0\n\nTotal interest\n\n$3.98\n\nTotal principal\n\n$0\n\nClosing balance\n\nDate: 30/06/2015\n\nBalance: $66.94",
  "outputs": {
    "enquiryRateFormatted": "5.95%",
    "enquiryYearEndMinusOneDisplay": "30/06/2014",
    "amalgamatedLoanNotPaidByEOIYFormatted": "$66.94",
    "openingBalancePayDays": "365",
    "openingBalanceInterestFormatted": "$3.98",
    "totalAmountOfRepaymentFormatted": "$0",
    "totalInterestFormatted": "$3.98",
    "principalFormatted": "$0",
    "enquiryYearEndDisplay": "30/06/2015",
    "minimumYearRepaymentFormatted": "$14.00"
  },
  "repayments": [],
  "inputs": {
    "incomeYearOfLoan": 2014,
    "fullTermOfAmalgamatedLoan": 6,
    "incomeYearOfEnquiring": 2015,
    "amalgamatedLoanNotPaidByEOIY": 66.94315864775838,
    "repayments": null,
    "lodgement_date": "7/12/2014"
  },
  "idx": 7183
}