{
  "id": "2023-09-04T16:13:40.792Z0.31804038961374825",
  "alert": "Start of result\nResult\n\nMinimum yearly repayment met.\n\nThe amount of the loan not repaid at the end of income year 2022-23 is $156.11.\n\nThe amalgamated loan will not be taken to be a dividend because the total repayments made are equal to or greater than the minimum yearly repayment required for income year 2022-23.\n\nInterest received by the private company must be included in the income tax return for 2022-23.\n\nMinimum yearly repayment\n\n$29.00\n\nBenchmark interest rate\n\n4.77%\n\nOpening balance:\n\nDate: 30/06/2022\n\nBalance: $823.00\n\nDays: 0\n\nInterest: $0\n\nPayments\n\nDate: 01/07/2022\n\nAmount: $674.00\n\nBalance: $149.00\n\nDays: 365\n\nInterest: $7.11\n\n\n\n\nTotal repayments\n\n$674.00\n\nTotal interest\n\n$7.11\n\nTotal principal\n\n$666.89\n\nClosing balance\n\nDate: 30/06/2023\n\nBalance: $156.11",
  "outputs": {
    "enquiryRateFormatted": "4.77%",
    "enquiryYearEndMinusOneDisplay": "30/06/2022",
    "amalgamatedLoanNotPaidByEOIYFormatted": "$823.00",
    "openingBalancePayDays": "0",
    "openingBalanceInterestFormatted": "$0",
    "totalAmountOfRepaymentFormatted": "$674.00",
    "totalInterestFormatted": "$7.11",
    "principalFormatted": "$666.89",
    "enquiryYearEndDisplay": "30/06/2023",
    "minimumYearRepaymentFormatted": "$29.00"
  },
  "repayments": [
    {
      "rd": "1/7/2022",
      "ra": 674
    }
  ],
  "inputs": {
    "incomeYearOfLoan": 2022,
    "fullTermOfAmalgamatedLoan": 6,
    "incomeYearOfEnquiring": 2023,
    "amalgamatedLoanNotPaidByEOIY": 823,
    "repayments": null,
    "lodgement_date": "17/1/2023"
  },
  "idx": 33
}