{
  "id": "2023-09-04T16:35:08.601Z0.11415925491165257",
  "alert": "Start of result\nResult\n\nMinimum yearly repayment not met.\n\nThe amount of the loan not repaid at the end of income year 2020-21 is $120,959,525.38.\n\nThe private company may be taken to pay a dividend under Division 7A to the shareholder or shareholder's associate because the amount repaid during income year 2020-21 in relation to the amalgamated loan is less than the minimum yearly repayment required.\n\nInterest received by the private company must be included in the income tax return for 2020-21.\n\nMinimum yearly repayment\n\n$64,610,499.00\n\nBenchmark interest rate\n\n4.52%\n\nOpening balance:\n\nDate: 30/06/2020\n\nBalance: $120,959,525.38\n\nDays: 365\n\nInterest: $5,467,370.55\n\nTotal repayments\n\n$0\n\nTotal interest\n\n$5,467,370.55\n\nTotal principal\n\n$0\n\nClosing balance\n\nDate: 30/06/2021\n\nBalance: $120,959,525.38",
  "outputs": {
    "enquiryRateFormatted": "4.52%",
    "enquiryYearEndMinusOneDisplay": "30/06/2020",
    "amalgamatedLoanNotPaidByEOIYFormatted": "$120,959,525.38",
    "openingBalancePayDays": "365",
    "openingBalanceInterestFormatted": "$5,467,370.55",
    "totalAmountOfRepaymentFormatted": "$0",
    "totalInterestFormatted": "$5,467,370.55",
    "principalFormatted": "$0",
    "enquiryYearEndDisplay": "30/06/2021",
    "minimumYearRepaymentFormatted": "$64,610,499.00"
  },
  "repayments": [],
  "inputs": {
    "incomeYearOfLoan": 2017,
    "fullTermOfAmalgamatedLoan": 5,
    "incomeYearOfEnquiring": 2021,
    "amalgamatedLoanNotPaidByEOIY": 120959525.38134839,
    "repayments": null,
    "lodgement_date": null
  },
  "idx": 809
}