{
  "id": "2023-09-04T22:17:59.657Z0.05095628247107964",
  "alert": "Start of result\nResult\n\nMinimum yearly repayment not met.\n\nThe amount of the loan not repaid at the end of income year 2003-04 is $69,301,806.57.\n\nThe private company may be taken to pay a dividend under Division 7A to the shareholder or shareholder's associate because the amount repaid during income year 2003-04 in relation to the amalgamated loan is less than the minimum yearly repayment required.\n\nInterest received by the private company must be included in the income tax return for 2003-04.\n\nMinimum yearly repayment\n\n$26,190,736.00\n\nBenchmark interest rate\n\n6.55%\n\nOpening balance:\n\nDate: 30/06/2003\n\nBalance: $69,301,806.57\n\nDays: 366\n\nInterest: $4,539,268.33\n\nTotal repayments\n\n$0\n\nTotal interest\n\n$4,539,268.33\n\nTotal principal\n\n$0\n\nClosing balance\n\nDate: 30/06/2004\n\nBalance: $69,301,806.57",
  "outputs": {
    "enquiryRateFormatted": "6.55%",
    "enquiryYearEndMinusOneDisplay": "30/06/2003",
    "amalgamatedLoanNotPaidByEOIYFormatted": "$69,301,806.57",
    "openingBalancePayDays": "366",
    "openingBalanceInterestFormatted": "$4,539,268.33",
    "totalAmountOfRepaymentFormatted": "$0",
    "totalInterestFormatted": "$4,539,268.33",
    "principalFormatted": "$0",
    "enquiryYearEndDisplay": "30/06/2004",
    "minimumYearRepaymentFormatted": "$26,190,736.00"
  },
  "repayments": [],
  "inputs": {
    "incomeYearOfLoan": 2001,
    "fullTermOfAmalgamatedLoan": 5,
    "incomeYearOfEnquiring": 2004,
    "amalgamatedLoanNotPaidByEOIY": 69301806.57044885,
    "repayments": null,
    "lodgement_date": null
  },
  "idx": 660
}