{
  "id": "2023-09-07T03:47:52.657Z0.37151362507129715",
  "alert": "Start of result\nResult\n\nMinimum yearly repayment met.\n\nThe amount of the loan not repaid at the end of income year 1999-00 is $3.55.\n\nThe amalgamated loan will not be taken to be a dividend because the total repayments made are equal to or greater than the minimum yearly repayment required for income year 1999-00.\n\nInterest received by the private company must be included in the income tax return for 1999-00.\n\nMinimum yearly repayment\n\n$29.00\n\nBenchmark interest rate\n\n6.5%\n\nOpening balance:\n\nDate: 30/06/1999\n\nBalance: $100.37\n\nDays: 199\n\nInterest: $3.55\n\nPayments\n\nDate: 16/01/2000\n\nAmount: $100.37\n\nBalance: $0\n\nDays: 167\n\nInterest: $0\n\n\n\n\nTotal repayments\n\n$100.37\n\nTotal interest\n\n$3.55\n\nTotal principal\n\n$96.82\n\nClosing balance\n\nDate: 30/06/2000\n\nBalance: $3.55",
  "outputs": {
    "enquiryRateFormatted": "6.5%",
    "enquiryYearEndMinusOneDisplay": "30/06/1999",
    "amalgamatedLoanNotPaidByEOIYFormatted": "$100.37",
    "openingBalancePayDays": "199",
    "openingBalanceInterestFormatted": "$3.55",
    "totalAmountOfRepaymentFormatted": "$100.37",
    "totalInterestFormatted": "$3.55",
    "principalFormatted": "$96.82",
    "enquiryYearEndDisplay": "30/06/2000",
    "minimumYearRepaymentFormatted": "$29.00"
  },
  "repayments": [
    {
      "rd": "16/1/2000",
      "ra": 100.37120696614738
    }
  ],
  "inputs": {
    "incomeYearOfLoan": 1998,
    "fullTermOfAmalgamatedLoan": 5,
    "incomeYearOfEnquiring": 2000,
    "amalgamatedLoanNotPaidByEOIY": 100.3712069661475,
    "repayments": null,
    "lodgement_date": null
  },
  "idx": 1477
}