{
  "id": "2023-09-06T18:03:55.807Z0.6229851820185626",
  "alert": "Start of result\nResult\n\nMinimum yearly repayment met.\n\nThe amount of the loan not repaid at the end of income year 2005-06 is $7.30.\n\nThe amalgamated loan will not be taken to be a dividend because the total repayments made are equal to or greater than the minimum yearly repayment required for income year 2005-06.\n\nInterest received by the private company must be included in the income tax return for 2005-06.\n\nMinimum yearly repayment\n\n$42.00\n\nBenchmark interest rate\n\n7.3%\n\nOpening balance:\n\nDate: 30/06/2005\n\nBalance: $109.95\n\nDays: 332\n\nInterest: $7.30\n\nPayments\n\nDate: 29/05/2006\n\nAmount: $109.95\n\nBalance: $0\n\nDays: 33\n\nInterest: $0\n\n\n\n\nTotal repayments\n\n$109.95\n\nTotal interest\n\n$7.30\n\nTotal principal\n\n$102.65\n\nClosing balance\n\nDate: 30/06/2006\n\nBalance: $7.30",
  "outputs": {
    "enquiryRateFormatted": "7.3%",
    "enquiryYearEndMinusOneDisplay": "30/06/2005",
    "amalgamatedLoanNotPaidByEOIYFormatted": "$109.95",
    "openingBalancePayDays": "332",
    "openingBalanceInterestFormatted": "$7.30",
    "totalAmountOfRepaymentFormatted": "$109.95",
    "totalInterestFormatted": "$7.30",
    "principalFormatted": "$102.65",
    "enquiryYearEndDisplay": "30/06/2006",
    "minimumYearRepaymentFormatted": "$42.00"
  },
  "repayments": [
    {
      "rd": "29/5/2006",
      "ra": 109.9535171916632
    }
  ],
  "inputs": {
    "incomeYearOfLoan": 2004,
    "fullTermOfAmalgamatedLoan": 4,
    "incomeYearOfEnquiring": 2006,
    "amalgamatedLoanNotPaidByEOIY": 109.95351719166335,
    "repayments": null,
    "lodgement_date": null
  },
  "idx": 737
}