{
  "id": "2023-09-06T11:09:27.655Z0.16689971958804772",
  "alert": "Start of result\nResult\n\nMinimum yearly repayment not met.\n\nThe amount of the loan not repaid at the end of income year 2008-09 is $31.19.\n\nThe private company may be taken to pay a dividend under Division 7A to the shareholder or shareholder's associate because the amount repaid during income year 2008-09 in relation to the amalgamated loan is less than the minimum yearly repayment required.\n\nInterest received by the private company must be included in the income tax return for 2008-09.\n\nMinimum yearly repayment\n\n$12.00\n\nBenchmark interest rate\n\n9.45%\n\nOpening balance:\n\nDate: 30/06/2008\n\nBalance: $31.19\n\nDays: 365\n\nInterest: $2.95\n\nTotal repayments\n\n$0\n\nTotal interest\n\n$2.95\n\nTotal principal\n\n$0\n\nClosing balance\n\nDate: 30/06/2009\n\nBalance: $31.19",
  "outputs": {
    "enquiryRateFormatted": "9.45%",
    "enquiryYearEndMinusOneDisplay": "30/06/2008",
    "amalgamatedLoanNotPaidByEOIYFormatted": "$31.19",
    "openingBalancePayDays": "365",
    "openingBalanceInterestFormatted": "$2.95",
    "totalAmountOfRepaymentFormatted": "$0",
    "totalInterestFormatted": "$2.95",
    "principalFormatted": "$0",
    "enquiryYearEndDisplay": "30/06/2009",
    "minimumYearRepaymentFormatted": "$12.00"
  },
  "repayments": [],
  "inputs": {
    "incomeYearOfLoan": 2008,
    "fullTermOfAmalgamatedLoan": 3,
    "incomeYearOfEnquiring": 2009,
    "amalgamatedLoanNotPaidByEOIY": 31.191250006619885,
    "repayments": null,
    "lodgement_date": "10/5/2009"
  },
  "idx": 3259
}