{
  "id": "2023-09-04T16:42:33.940Z0.14981387475596408",
  "alert": "Start of result\nResult\n\nMinimum yearly repayment not met.\n\nThe amount of the loan not repaid at the end of income year 2018-19 is $8,803.14.\n\nThe private company may be taken to pay a dividend under Division 7A to the shareholder or shareholder's associate because the amount repaid during income year 2018-19 in relation to the amalgamated loan is less than the minimum yearly repayment required.\n\nInterest received by the private company must be included in the income tax return for 2018-19.\n\nMinimum yearly repayment\n\n$12,887.00\n\nBenchmark interest rate\n\n5.2%\n\nOpening balance:\n\nDate: 30/06/2018\n\nBalance: $12,250.00\n\nDays: 0\n\nInterest: $0\n\nPayments\n\nDate: 01/07/2018\n\nAmount: $3,882.00\n\nBalance: $8,368.00\n\nDays: 365\n\nInterest: $435.14\n\n\n\n\nTotal repayments\n\n$3,882.00\n\nTotal interest\n\n$435.14\n\nTotal principal\n\n$3,446.86\n\nClosing balance\n\nDate: 30/06/2019\n\nBalance: $8,803.14",
  "outputs": {
    "enquiryRateFormatted": "5.2%",
    "enquiryYearEndMinusOneDisplay": "30/06/2018",
    "amalgamatedLoanNotPaidByEOIYFormatted": "$12,250.00",
    "openingBalancePayDays": "0",
    "openingBalanceInterestFormatted": "$0",
    "totalAmountOfRepaymentFormatted": "$3,882.00",
    "totalInterestFormatted": "$435.14",
    "principalFormatted": "$3,446.86",
    "enquiryYearEndDisplay": "30/06/2019",
    "minimumYearRepaymentFormatted": "$12,887.00"
  },
  "repayments": [
    {
      "rd": "1/7/2018",
      "ra": 3882
    }
  ],
  "inputs": {
    "incomeYearOfLoan": 2016,
    "fullTermOfAmalgamatedLoan": 3,
    "incomeYearOfEnquiring": 2019,
    "amalgamatedLoanNotPaidByEOIY": 12250,
    "repayments": null,
    "lodgement_date": null
  },
  "idx": 1040
}