{
  "id": "2023-09-05T18:27:54.736Z0.36206529979556534",
  "alert": "Start of result\nResult\n\nMinimum yearly repayment not met.\n\nThe amount of the loan not repaid at the end of income year 2022-23 is $4,100.00.\n\nThe private company may be taken to pay a dividend under Division 7A to the shareholder or shareholder's associate because the amount repaid during income year 2022-23 in relation to the amalgamated loan is less than the minimum yearly repayment required.\n\nInterest received by the private company must be included in the income tax return for 2022-23.\n\nMinimum yearly repayment\n\n$4,296.00\n\nBenchmark interest rate\n\n4.77%\n\nOpening balance:\n\nDate: 30/06/2022\n\nBalance: $4,100.00\n\nDays: 365\n\nInterest: $195.57\n\nTotal repayments\n\n$0\n\nTotal interest\n\n$195.57\n\nTotal principal\n\n$0\n\nClosing balance\n\nDate: 30/06/2023\n\nBalance: $4,100.00",
  "outputs": {
    "enquiryRateFormatted": "4.77%",
    "enquiryYearEndMinusOneDisplay": "30/06/2022",
    "amalgamatedLoanNotPaidByEOIYFormatted": "$4,100.00",
    "openingBalancePayDays": "365",
    "openingBalanceInterestFormatted": "$195.57",
    "totalAmountOfRepaymentFormatted": "$0",
    "totalInterestFormatted": "$195.57",
    "principalFormatted": "$0",
    "enquiryYearEndDisplay": "30/06/2023",
    "minimumYearRepaymentFormatted": "$4,296.00"
  },
  "repayments": [],
  "inputs": {
    "incomeYearOfLoan": 2018,
    "fullTermOfAmalgamatedLoan": 5,
    "incomeYearOfEnquiring": 2023,
    "amalgamatedLoanNotPaidByEOIY": 4100,
    "repayments": null,
    "lodgement_date": null
  },
  "idx": 7751
}