{
  "id": "2023-09-07T00:06:58.098Z0.32875201966320633",
  "alert": "Start of result\nResult\n\nMinimum yearly repayment not met.\n\nThe amount of the loan not repaid at the end of income year 2003-04 is $6,606.44.\n\nThe private company may be taken to pay a dividend under Division 7A to the shareholder or shareholder's associate because the amount repaid during income year 2003-04 in relation to the amalgamated loan is less than the minimum yearly repayment required.\n\nInterest received by the private company must be included in the income tax return for 2003-04.\n\nMinimum yearly repayment\n\n$11,937.00\n\nBenchmark interest rate\n\n6.55%\n\nOpening balance:\n\nDate: 30/06/2003\n\nBalance: $11,203.00\n\nDays: 86\n\nInterest: $172.42\n\nPayments\n\nDate: 25/09/2003\n\nAmount: $5,076.00\n\nBalance: $6,127.00\n\nDays: 280\n\nInterest: $307.02\n\n\n\n\nTotal repayments\n\n$5,076.00\n\nTotal interest\n\n$479.44\n\nTotal principal\n\n$4,596.56\n\nClosing balance\n\nDate: 30/06/2004\n\nBalance: $6,606.44",
  "outputs": {
    "enquiryRateFormatted": "6.55%",
    "enquiryYearEndMinusOneDisplay": "30/06/2003",
    "amalgamatedLoanNotPaidByEOIYFormatted": "$11,203.00",
    "openingBalancePayDays": "86",
    "openingBalanceInterestFormatted": "$172.42",
    "totalAmountOfRepaymentFormatted": "$5,076.00",
    "totalInterestFormatted": "$479.44",
    "principalFormatted": "$4,596.56",
    "enquiryYearEndDisplay": "30/06/2004",
    "minimumYearRepaymentFormatted": "$11,937.00"
  },
  "repayments": [
    {
      "rd": "25/9/2003",
      "ra": 5076
    }
  ],
  "inputs": {
    "incomeYearOfLoan": 2000,
    "fullTermOfAmalgamatedLoan": 4,
    "incomeYearOfEnquiring": 2004,
    "amalgamatedLoanNotPaidByEOIY": 11203,
    "repayments": null,
    "lodgement_date": null
  },
  "idx": 5903
}