{
  "id": "2023-10-31T17:55:56.674Z0.34840221653622205",
  "alert": "Start of result\nResult\n\nAmalgamated loan fully repaid.\n\nThe amalgamated loan has been paid in full.\u000bThe private company is not taken under Division 7A to pay a dividend to the shareholder or shareholder's associate.\n\nInterest received by the private company must be included in the income tax return for 2014-15.\n\nMinimum yearly repayment\n\n$40.00\n\nBenchmark interest rate\n\n5.95%\n\nOpening balance:\n\nDate: 30/06/2014\n\nBalance: $107.14\n\nDays: 164\n\nInterest: $2.86\n\nPayments\n\nDate: 12/12/2014\n\nAmount: $1,071.43\n\nBalance: $0\n\nDays: 201\n\nInterest: $0\n\n\n\n\nTotal repayments\n\n$1,071.43\n\nTotal interest\n\n$2.86\n\nTotal principal\n\n$1,068.57\n\nClosing balance\n\nDate: 30/06/2015\n\nBalance: $0",
  "outputs": {
    "enquiryRateFormatted": "5.95%",
    "enquiryYearEndMinusOneDisplay": "30/06/2014",
    "amalgamatedLoanNotPaidByEOIYFormatted": "$107.14",
    "openingBalancePayDays": "164",
    "openingBalanceInterestFormatted": "$2.86",
    "totalAmountOfRepaymentFormatted": "$1,071.43",
    "totalInterestFormatted": "$2.86",
    "principalFormatted": "$1,068.57",
    "enquiryYearEndDisplay": "30/06/2015",
    "minimumYearRepaymentFormatted": "$40.00",
    "loanAmountFormatted": "$0"
  },
  "repayments": [
    {
      "rd": "12/12/2014",
      "ra": 1071.430222486817
    }
  ],
  "inputs": {
    "incomeYearOfLoan": 2013,
    "fullTermOfAmalgamatedLoan": 4,
    "incomeYearOfEnquiring": 2015,
    "amalgamatedLoanNotPaidByEOIY": 107.1430222486817,
    "repayments": null,
    "lodgement_date": null
  },
  "idx": 2933
}