{
  "id": "2023-10-31T17:21:20.075Z0.22999421330559988",
  "alert": "Start of result\nResult\n\nMinimum yearly repayment not met.\n\nThe amount of the loan not repaid at the end of income year 2023-24 is $4,105.60.\n\nThe private company may be taken to pay a dividend under Division 7A to the shareholder or shareholder's associate because the amount repaid during income year 2023-24 in relation to the amalgamated loan is less than the minimum yearly repayment required.\n\nInterest received by the private company must be included in the income tax return for 2023-24.\n\nMinimum yearly repayment\n\n$3,963.00\n\nBenchmark interest rate\n\n8.27%\n\nOpening balance:\n\nDate: 30/06/2023\n\nBalance: $7,041.00\n\nDays: 336\n\nInterest: $534.56\n\nPayments\n\nDate: 01/06/2024\n\nAmount: $3,494.00\n\nBalance: $3,547.00\n\nDays: 30\n\nInterest: $24.04\n\n\n\n\nTotal repayments\n\n$3,494.00\n\nTotal interest\n\n$558.60\n\nTotal principal\n\n$2,935.40\n\nClosing balance\n\nDate: 30/06/2024\n\nBalance: $4,105.60",
  "outputs": {
    "enquiryRateFormatted": "8.27%",
    "enquiryYearEndMinusOneDisplay": "30/06/2023",
    "amalgamatedLoanNotPaidByEOIYFormatted": "$7,041.00",
    "openingBalancePayDays": "336",
    "openingBalanceInterestFormatted": "$534.56",
    "totalAmountOfRepaymentFormatted": "$3,494.00",
    "totalInterestFormatted": "$558.60",
    "principalFormatted": "$2,935.40",
    "enquiryYearEndDisplay": "30/06/2024",
    "minimumYearRepaymentFormatted": "$3,963.00",
    "loanAmountFormatted": "$4,105.60"
  },
  "repayments": [
    {
      "rd": "1/6/2024",
      "ra": 3494
    }
  ],
  "inputs": {
    "incomeYearOfLoan": 2019,
    "fullTermOfAmalgamatedLoan": 6,
    "incomeYearOfEnquiring": 2024,
    "amalgamatedLoanNotPaidByEOIY": 7041,
    "repayments": null,
    "lodgement_date": null
  },
  "idx": 1182
}