{
  "id": "2023-09-04T23:12:54.368Z0.4557011586726305",
  "alert": "Start of result\nResult\n\nMinimum yearly repayment not met.\n\nThe amount of the loan not repaid at the end of income year 1999-00 is $10,227.20.\n\nThe private company may be taken to pay a dividend under Division 7A to the shareholder or shareholder's associate because the amount repaid during income year 1999-00 in relation to the amalgamated loan is less than the minimum yearly repayment required.\n\nInterest received by the private company must be included in the income tax return for 1999-00.\n\nMinimum yearly repayment\n\n$3,626.00\n\nBenchmark interest rate\n\n6.5%\n\nOpening balance:\n\nDate: 30/06/1999\n\nBalance: $12,280.00\n\nDays: 0\n\nInterest: $0\n\nPayments\n\nDate: 01/07/1999\n\nAmount: $2,677.00\n\nBalance: $9,603.00\n\nDays: 366\n\nInterest: $624.20\n\n\n\n\nTotal repayments\n\n$2,677.00\n\nTotal interest\n\n$624.20\n\nTotal principal\n\n$2,052.80\n\nClosing balance\n\nDate: 30/06/2000\n\nBalance: $10,227.20",
  "outputs": {
    "enquiryRateFormatted": "6.5%",
    "enquiryYearEndMinusOneDisplay": "30/06/1999",
    "amalgamatedLoanNotPaidByEOIYFormatted": "$12,280.00",
    "openingBalancePayDays": "0",
    "openingBalanceInterestFormatted": "$0",
    "totalAmountOfRepaymentFormatted": "$2,677.00",
    "totalInterestFormatted": "$624.20",
    "principalFormatted": "$2,052.80",
    "enquiryYearEndDisplay": "30/06/2000",
    "minimumYearRepaymentFormatted": "$3,626.00"
  },
  "repayments": [
    {
      "rd": "1/7/1999",
      "ra": 2677
    }
  ],
  "inputs": {
    "incomeYearOfLoan": 1999,
    "fullTermOfAmalgamatedLoan": 3,
    "incomeYearOfEnquiring": 2000,
    "amalgamatedLoanNotPaidByEOIY": 12280,
    "repayments": null,
    "lodgement_date": "23/10/1999"
  },
  "idx": 2323
}