{
  "id": "2023-09-04T22:01:30.652Z0.006644043065807237",
  "alert": "Start of result\nResult\n\nMinimum yearly repayment met.\n\nThe amount of the loan not repaid at the end of income year 2004-05 is $6,961.46.\n\nThe amalgamated loan will not be taken to be a dividend because the total repayments made are equal to or greater than the minimum yearly repayment required for income year 2004-05.\n\nInterest received by the private company must be included in the income tax return for 2004-05.\n\nMinimum yearly repayment\n\n$3,599.00\n\nBenchmark interest rate\n\n7.05%\n\nOpening balance:\n\nDate: 30/06/2004\n\nBalance: $10,316.00\n\nDays: 0\n\nInterest: $0\n\nPayments\n\nDate: 01/07/2004\n\nAmount: $3,813.00\n\nBalance: $6,503.00\n\nDays: 365\n\nInterest: $458.46\n\n\n\n\nTotal repayments\n\n$3,813.00\n\nTotal interest\n\n$458.46\n\nTotal principal\n\n$3,354.54\n\nClosing balance\n\nDate: 30/06/2005\n\nBalance: $6,961.46",
  "outputs": {
    "enquiryRateFormatted": "7.05%",
    "enquiryYearEndMinusOneDisplay": "30/06/2004",
    "amalgamatedLoanNotPaidByEOIYFormatted": "$10,316.00",
    "openingBalancePayDays": "0",
    "openingBalanceInterestFormatted": "$0",
    "totalAmountOfRepaymentFormatted": "$3,813.00",
    "totalInterestFormatted": "$458.46",
    "principalFormatted": "$3,354.54",
    "enquiryYearEndDisplay": "30/06/2005",
    "minimumYearRepaymentFormatted": "$3,599.00"
  },
  "repayments": [
    {
      "rd": "1/7/2004",
      "ra": 3813
    }
  ],
  "inputs": {
    "incomeYearOfLoan": 2004,
    "fullTermOfAmalgamatedLoan": 2,
    "incomeYearOfEnquiring": 2005,
    "amalgamatedLoanNotPaidByEOIY": 10316,
    "repayments": null,
    "lodgement_date": "17/1/2005"
  },
  "idx": 21
}