{
  "id": "2023-10-31T18:29:31.354Z0.8941597155143808",
  "alert": "Start of result\nResult\n\nMinimum yearly repayment not met.\n\nThe amount of the loan not repaid at the end of income year 2011-12 is $6,101.56.\n\nThe private company may be taken to pay a dividend under Division 7A to the shareholder or shareholder's associate because the amount repaid during income year 2011-12 in relation to the amalgamated loan is less than the minimum yearly repayment required.\n\nInterest received by the private company must be included in the income tax return for 2011-12.\n\nMinimum yearly repayment\n\n$4,153.00\n\nBenchmark interest rate\n\n7.8%\n\nOpening balance:\n\nDate: 30/06/2011\n\nBalance: $7,426.00\n\nDays: 104\n\nInterest: $164.59\n\nPayments\n\nDate: 13/10/2011\n\nAmount: $1,803.00\n\nBalance: $5,623.00\n\nDays: 262\n\nInterest: $313.97\n\n\n\n\nTotal repayments\n\n$1,803.00\n\nTotal interest\n\n$478.56\n\nTotal principal\n\n$1,324.44\n\nClosing balance\n\nDate: 30/06/2012\n\nBalance: $6,101.56",
  "outputs": {
    "enquiryRateFormatted": "7.8%",
    "enquiryYearEndMinusOneDisplay": "30/06/2011",
    "amalgamatedLoanNotPaidByEOIYFormatted": "$7,426.00",
    "openingBalancePayDays": "104",
    "openingBalanceInterestFormatted": "$164.59",
    "totalAmountOfRepaymentFormatted": "$1,803.00",
    "totalInterestFormatted": "$478.56",
    "principalFormatted": "$1,324.44",
    "enquiryYearEndDisplay": "30/06/2012",
    "minimumYearRepaymentFormatted": "$4,153.00",
    "loanAmountFormatted": "$6,101.56"
  },
  "repayments": [
    {
      "rd": "13/10/2011",
      "ra": 1803
    }
  ],
  "inputs": {
    "incomeYearOfLoan": 2009,
    "fullTermOfAmalgamatedLoan": 4,
    "incomeYearOfEnquiring": 2012,
    "amalgamatedLoanNotPaidByEOIY": 7426,
    "repayments": null,
    "lodgement_date": null
  },
  "idx": 4065
}