{
  "id": "2023-09-06T14:20:59.572Z0.10654173329191141",
  "alert": "Start of result\nResult\n\nMinimum yearly repayment met.\n\nThe amount of the loan not repaid at the end of income year 2006-07 is $13.76.\n\nThe amalgamated loan will not be taken to be a dividend because the total repayments made are equal to or greater than the minimum yearly repayment required for income year 2006-07.\n\nInterest received by the private company must be included in the income tax return for 2006-07.\n\nMinimum yearly repayment\n\n$4.00\n\nBenchmark interest rate\n\n7.55%\n\nOpening balance:\n\nDate: 30/06/2006\n\nBalance: $111.00\n\nDays: 93\n\nInterest: $2.14\n\nPayments\n\nDate: 02/10/2006\n\nAmount: $100.00\n\nBalance: $11.00\n\nDays: 272\n\nInterest: $0.62\n\n\n\n\nTotal repayments\n\n$100.00\n\nTotal interest\n\n$2.76\n\nTotal principal\n\n$97.24\n\nClosing balance\n\nDate: 30/06/2007\n\nBalance: $13.76",
  "outputs": {
    "enquiryRateFormatted": "7.55%",
    "enquiryYearEndMinusOneDisplay": "30/06/2006",
    "amalgamatedLoanNotPaidByEOIYFormatted": "$111.00",
    "openingBalancePayDays": "93",
    "openingBalanceInterestFormatted": "$2.14",
    "totalAmountOfRepaymentFormatted": "$100.00",
    "totalInterestFormatted": "$2.76",
    "principalFormatted": "$97.24",
    "enquiryYearEndDisplay": "30/06/2007",
    "minimumYearRepaymentFormatted": "$4.00"
  },
  "repayments": [
    {
      "rd": "2/10/2006",
      "ra": 100
    }
  ],
  "inputs": {
    "incomeYearOfLoan": 2006,
    "fullTermOfAmalgamatedLoan": 3,
    "incomeYearOfEnquiring": 2007,
    "amalgamatedLoanNotPaidByEOIY": 111,
    "repayments": null,
    "lodgement_date": "19/6/2007"
  },
  "idx": 5157
}