{
  "id": "2023-10-31T17:09:36.170Z0.8740456871634371",
  "alert": "Start of result\nResult\n\nMinimum yearly repayment not met.\n\nThe amount of the loan not repaid at the end of income year 2022-23 is $93.13.\n\nThe private company may be taken to pay a dividend under Division 7A to the shareholder or shareholder's associate because the amount repaid during income year 2022-23 in relation to the amalgamated loan is less than the minimum yearly repayment required.\n\nInterest received by the private company must be included in the income tax return for 2022-23.\n\nMinimum yearly repayment\n\n$26.00\n\nBenchmark interest rate\n\n4.77%\n\nOpening balance:\n\nDate: 30/06/2022\n\nBalance: $93.13\n\nDays: 365\n\nInterest: $4.44\n\nTotal repayments\n\n$0\n\nTotal interest\n\n$4.44\n\nTotal principal\n\n$0\n\nClosing balance\n\nDate: 30/06/2023\n\nBalance: $93.13",
  "outputs": {
    "enquiryRateFormatted": "4.77%",
    "enquiryYearEndMinusOneDisplay": "30/06/2022",
    "amalgamatedLoanNotPaidByEOIYFormatted": "$93.13",
    "openingBalancePayDays": "365",
    "openingBalanceInterestFormatted": "$4.44",
    "totalAmountOfRepaymentFormatted": "$0",
    "totalInterestFormatted": "$4.44",
    "principalFormatted": "$0",
    "enquiryYearEndDisplay": "30/06/2023",
    "minimumYearRepaymentFormatted": "$26.00",
    "loanAmountFormatted": "$93.13"
  },
  "repayments": [],
  "inputs": {
    "incomeYearOfLoan": 2022,
    "fullTermOfAmalgamatedLoan": 4,
    "incomeYearOfEnquiring": 2023,
    "amalgamatedLoanNotPaidByEOIY": 93.13024988393774,
    "repayments": null,
    "lodgement_date": "27/1/2023"
  },
  "idx": 266
}