{
  "id": "2023-10-31T20:53:01.174Z0.2892589586311294",
  "alert": "Start of result\nResult\n\nAmalgamated loan fully repaid.\n\nThe amalgamated loan has been paid in full.\u000bThe private company is not taken under Division 7A to pay a dividend to the shareholder or shareholder's associate.\n\nInterest received by the private company must be included in the income tax return for 1999-00.\n\nMinimum yearly repayment\n\n-$2,026.00\n\nBenchmark interest rate\n\n6.5%\n\nOpening balance:\n\nDate: 30/06/1999\n\nBalance: $1,692.00\n\nDays: 58\n\nInterest: $17.43\n\nPayments\n\nDate: 28/08/1999\n\nAmount: $4,585.00\n\nBalance: $0\n\nDays: 181\n\nInterest: $0\n\n\n\n\nDate: 25/02/2000\n\nAmount: $795.00\n\nBalance: $0\n\nDays: 127\n\nInterest: $0\n\n\n\n\nTotal repayments\n\n$5,380.00\n\nTotal interest\n\n$17.43\n\nTotal principal\n\n$5,362.57\n\nClosing balance\n\nDate: 30/06/2000\n\nBalance: $0",
  "outputs": {
    "enquiryRateFormatted": "6.5%",
    "enquiryYearEndMinusOneDisplay": "30/06/1999",
    "amalgamatedLoanNotPaidByEOIYFormatted": "$1,692.00",
    "openingBalancePayDays": "58",
    "openingBalanceInterestFormatted": "$17.43",
    "totalAmountOfRepaymentFormatted": "$5,380.00",
    "totalInterestFormatted": "$17.43",
    "principalFormatted": "$5,362.57",
    "enquiryYearEndDisplay": "30/06/2000",
    "minimumYearRepaymentFormatted": "-$2,026.00",
    "loanAmountFormatted": "$0"
  },
  "repayments": [
    {
      "rd": "28/8/1999",
      "ra": 4585
    },
    {
      "rd": "25/2/2000",
      "ra": 795
    }
  ],
  "inputs": {
    "incomeYearOfLoan": 1999,
    "fullTermOfAmalgamatedLoan": 2,
    "incomeYearOfEnquiring": 2000,
    "amalgamatedLoanNotPaidByEOIY": 1692,
    "repayments": null,
    "lodgement_date": "27/3/2000"
  },
  "idx": 6839
}