{
  "id": "2023-10-31T20:02:46.181Z0.9806865132845727",
  "alert": "Start of result\nResult\n\nMinimum yearly repayment met.\n\nThe amount of the loan not repaid at the end of income year 2002-03 is $7,172.47.\n\n\u000b\n\nThe amalgamated loan will not be taken to be a dividend because the total repayments made are equal to or greater than the minimum yearly repayment required for income year 2002-03.\n\nInterest received by the private company must be included in the income tax return for 2002-03.\n\nMinimum yearly repayment\n\n$1,597.00\n\nBenchmark interest rate\n\n6.3%\n\nOpening balance:\n\nDate: 30/06/2002\n\nBalance: $8,543.00\n\nDays: 245\n\nInterest: $361.26\n\nPayments\n\nDate: 03/03/2003\n\nAmount: $1,870.00\n\nBalance: $6,673.00\n\nDays: 120\n\nInterest: $138.21\n\n\n\n\nTotal repayments\n\n$1,870.00\n\nTotal interest\n\n$499.47\n\nTotal principal\n\n$1,370.53\n\nClosing balance\n\nDate: 30/06/2003\n\nBalance: $7,172.47",
  "outputs": {
    "enquiryRateFormatted": "6.3%",
    "enquiryYearEndMinusOneDisplay": "30/06/2002",
    "amalgamatedLoanNotPaidByEOIYFormatted": "$8,543.00",
    "openingBalancePayDays": "245",
    "openingBalanceInterestFormatted": "$361.26",
    "totalAmountOfRepaymentFormatted": "$1,870.00",
    "totalInterestFormatted": "$499.47",
    "principalFormatted": "$1,370.53",
    "enquiryYearEndDisplay": "30/06/2003",
    "minimumYearRepaymentFormatted": "$1,597.00",
    "loanAmountFormatted": "$7,172.47"
  },
  "repayments": [
    {
      "rd": "3/3/2003",
      "ra": 1870
    }
  ],
  "inputs": {
    "incomeYearOfLoan": 2002,
    "fullTermOfAmalgamatedLoan": 5,
    "incomeYearOfEnquiring": 2003,
    "amalgamatedLoanNotPaidByEOIY": 8543,
    "repayments": null,
    "lodgement_date": "27/4/2003"
  },
  "idx": 6117
}