{
  "id": "2023-10-31T18:04:48.859Z0.2219103172397423",
  "alert": "Start of result\nResult\n\nAmalgamated loan fully repaid.\n\nThe amalgamated loan has been paid in full.\u000bThe private company is not taken under Division 7A to pay a dividend to the shareholder or shareholder's associate.\n\nInterest received by the private company must be included in the income tax return for 2016-17.\n\nMinimum yearly repayment\n\n$9.00\n\nBenchmark interest rate\n\n5.4%\n\nOpening balance:\n\nDate: 30/06/2016\n\nBalance: $16.06\n\nDays: 133\n\nInterest: $0.32\n\nPayments\n\nDate: 11/11/2016\n\nAmount: $160.60\n\nBalance: $0\n\nDays: 232\n\nInterest: $0\n\n\n\n\nTotal repayments\n\n$160.60\n\nTotal interest\n\n$0.32\n\nTotal principal\n\n$160.28\n\nClosing balance\n\nDate: 30/06/2017\n\nBalance: $0",
  "outputs": {
    "enquiryRateFormatted": "5.4%",
    "enquiryYearEndMinusOneDisplay": "30/06/2016",
    "amalgamatedLoanNotPaidByEOIYFormatted": "$16.06",
    "openingBalancePayDays": "133",
    "openingBalanceInterestFormatted": "$0.32",
    "totalAmountOfRepaymentFormatted": "$160.60",
    "totalInterestFormatted": "$0.32",
    "principalFormatted": "$160.28",
    "enquiryYearEndDisplay": "30/06/2017",
    "minimumYearRepaymentFormatted": "$9.00",
    "loanAmountFormatted": "$0"
  },
  "repayments": [
    {
      "rd": "11/11/2016",
      "ra": 160.60963657998946
    }
  ],
  "inputs": {
    "incomeYearOfLoan": 2012,
    "fullTermOfAmalgamatedLoan": 6,
    "incomeYearOfEnquiring": 2017,
    "amalgamatedLoanNotPaidByEOIY": 16.06096365799891,
    "repayments": null,
    "lodgement_date": null
  },
  "idx": 3267
}