{
  "id": "2023-10-31T20:56:38.630Z0.4630840304928896",
  "alert": "Start of result\nResult\n\nAmalgamated loan fully repaid.\n\nThe amalgamated loan has been paid in full.\u000bThe private company is not taken under Division 7A to pay a dividend to the shareholder or shareholder's associate.\n\nInterest received by the private company must be included in the income tax return for 2000-01.\n\nMinimum yearly repayment\n\n$1,651.00\n\nBenchmark interest rate\n\n7.8%\n\nOpening balance:\n\nDate: 30/06/2000\n\nBalance: $4,270.00\n\nDays: 207\n\nInterest: $188.89\n\nPayments\n\nDate: 24/01/2001\n\nAmount: $7,105.00\n\nBalance: $0\n\nDays: 158\n\nInterest: $0\n\n\n\n\nTotal repayments\n\n$7,105.00\n\nTotal interest\n\n$188.89\n\nTotal principal\n\n$6,916.11\n\nClosing balance\n\nDate: 30/06/2001\n\nBalance: $0",
  "outputs": {
    "enquiryRateFormatted": "7.8%",
    "enquiryYearEndMinusOneDisplay": "30/06/2000",
    "amalgamatedLoanNotPaidByEOIYFormatted": "$4,270.00",
    "openingBalancePayDays": "207",
    "openingBalanceInterestFormatted": "$188.89",
    "totalAmountOfRepaymentFormatted": "$7,105.00",
    "totalInterestFormatted": "$188.89",
    "principalFormatted": "$6,916.11",
    "enquiryYearEndDisplay": "30/06/2001",
    "minimumYearRepaymentFormatted": "$1,651.00",
    "loanAmountFormatted": "$0"
  },
  "repayments": [
    {
      "rd": "24/1/2001",
      "ra": 7105
    }
  ],
  "inputs": {
    "incomeYearOfLoan": 1999,
    "fullTermOfAmalgamatedLoan": 4,
    "incomeYearOfEnquiring": 2001,
    "amalgamatedLoanNotPaidByEOIY": 4270,
    "repayments": null,
    "lodgement_date": null
  },
  "idx": 6885
}