{
  "id": "2023-09-04T17:24:13.957Z0.43792350436231464",
  "alert": "Start of result\nResult\n\nMinimum yearly repayment met.\n\nThe amount of the loan not repaid at the end of income year 2016-17 is $15.38.\n\nThe amalgamated loan will not be taken to be a dividend because the total repayments made are equal to or greater than the minimum yearly repayment required for income year 2016-17.\n\nInterest received by the private company must be included in the income tax return for 2016-17.\n\nMinimum yearly repayment\n\n$3,285.00\n\nBenchmark interest rate\n\n5.4%\n\nOpening balance:\n\nDate: 30/06/2016\n\nBalance: $8,878.00\n\nDays: 0\n\nInterest: $0\n\nPayments\n\nDate: 01/07/2016\n\nAmount: $8,220.00\n\nBalance: $658.00\n\nDays: 158\n\nInterest: $15.38\n\n\n\n\nDate: 06/12/2016\n\nAmount: $658.00\n\nBalance: $0\n\nDays: 207\n\nInterest: $0\n\n\n\n\nTotal repayments\n\n$8,878.00\n\nTotal interest\n\n$15.38\n\nTotal principal\n\n$8,862.62\n\nClosing balance\n\nDate: 30/06/2017\n\nBalance: $15.38",
  "outputs": {
    "enquiryRateFormatted": "5.4%",
    "enquiryYearEndMinusOneDisplay": "30/06/2016",
    "amalgamatedLoanNotPaidByEOIYFormatted": "$8,878.00",
    "openingBalancePayDays": "0",
    "openingBalanceInterestFormatted": "$0",
    "totalAmountOfRepaymentFormatted": "$8,878.00",
    "totalInterestFormatted": "$15.38",
    "principalFormatted": "$8,862.62",
    "enquiryYearEndDisplay": "30/06/2017",
    "minimumYearRepaymentFormatted": "$3,285.00"
  },
  "repayments": [
    {
      "rd": "1/7/2016",
      "ra": 8220
    },
    {
      "rd": "6/12/2016",
      "ra": 658
    }
  ],
  "inputs": {
    "incomeYearOfLoan": 2013,
    "fullTermOfAmalgamatedLoan": 6,
    "incomeYearOfEnquiring": 2017,
    "amalgamatedLoanNotPaidByEOIY": 8878,
    "repayments": null,
    "lodgement_date": null
  },
  "idx": 2095
}