{
  "id": "2023-09-05T13:00:13.755Z0.935518633760011",
  "alert": "Start of result\nResult\n\nMinimum yearly repayment met.\n\nThe amount of the loan not repaid at the end of income year 2021-22 is $10.72.\n\nThe amalgamated loan will not be taken to be a dividend because the total repayments made are equal to or greater than the minimum yearly repayment required for income year 2021-22.\n\nInterest received by the private company must be included in the income tax return for 2021-22.\n\nMinimum yearly repayment\n\n$0\n\nBenchmark interest rate\n\n4.52%\n\nOpening balance:\n\nDate: 30/06/2021\n\nBalance: $746.00\n\nDays: 116\n\nInterest: $10.72\n\nPayments\n\nDate: 25/10/2021\n\nAmount: $746.00\n\nBalance: $0\n\nDays: 249\n\nInterest: $0\n\n\n\n\nTotal repayments\n\n$746.00\n\nTotal interest\n\n$10.72\n\nTotal principal\n\n$735.28\n\nClosing balance\n\nDate: 30/06/2022\n\nBalance: $10.72",
  "outputs": {
    "enquiryRateFormatted": "4.52%",
    "enquiryYearEndMinusOneDisplay": "30/06/2021",
    "amalgamatedLoanNotPaidByEOIYFormatted": "$746.00",
    "openingBalancePayDays": "116",
    "openingBalanceInterestFormatted": "$10.72",
    "totalAmountOfRepaymentFormatted": "$746.00",
    "totalInterestFormatted": "$10.72",
    "principalFormatted": "$735.28",
    "enquiryYearEndDisplay": "30/06/2022",
    "minimumYearRepaymentFormatted": "$0"
  },
  "repayments": [
    {
      "rd": "25/10/2021",
      "ra": 746
    }
  ],
  "inputs": {
    "incomeYearOfLoan": 2021,
    "fullTermOfAmalgamatedLoan": 2,
    "incomeYearOfEnquiring": 2022,
    "amalgamatedLoanNotPaidByEOIY": 746,
    "repayments": null,
    "lodgement_date": "26/3/2022"
  },
  "idx": 6505
}