{
  "id": "2023-10-31T18:20:40.228Z0.4517354477376565",
  "alert": "Start of result\nResult\n\nMinimum yearly repayment not met.\n\nThe amount of the loan not repaid at the end of income year 2011-12 is $11,865.00.\n\nThe private company may be taken to pay a dividend under Division 7A to the shareholder or shareholder's associate because the amount repaid during income year 2011-12 in relation to the amalgamated loan is less than the minimum yearly repayment required.\n\nInterest received by the private company must be included in the income tax return for 2011-12.\n\nMinimum yearly repayment\n\n$4,587.00\n\nBenchmark interest rate\n\n7.8%\n\nOpening balance:\n\nDate: 30/06/2011\n\nBalance: $11,865.00\n\nDays: 366\n\nInterest: $925.47\n\nTotal repayments\n\n$0\n\nTotal interest\n\n$925.47\n\nTotal principal\n\n$0\n\nClosing balance\n\nDate: 30/06/2012\n\nBalance: $11,865.00",
  "outputs": {
    "enquiryRateFormatted": "7.8%",
    "enquiryYearEndMinusOneDisplay": "30/06/2011",
    "amalgamatedLoanNotPaidByEOIYFormatted": "$11,865.00",
    "openingBalancePayDays": "366",
    "openingBalanceInterestFormatted": "$925.47",
    "totalAmountOfRepaymentFormatted": "$0",
    "totalInterestFormatted": "$925.47",
    "principalFormatted": "$0",
    "enquiryYearEndDisplay": "30/06/2012",
    "minimumYearRepaymentFormatted": "$4,587.00",
    "loanAmountFormatted": "$11,865.00"
  },
  "repayments": [],
  "inputs": {
    "incomeYearOfLoan": 2010,
    "fullTermOfAmalgamatedLoan": 4,
    "incomeYearOfEnquiring": 2012,
    "amalgamatedLoanNotPaidByEOIY": 11865,
    "repayments": null,
    "lodgement_date": null
  },
  "idx": 3813
}