{
  "id": "2023-10-31T17:58:45.198Z0.8935268121767247",
  "alert": "Start of result\nResult\n\nAmalgamated loan fully repaid.\n\nThe amalgamated loan has been paid in full.\u000bThe private company is not taken under Division 7A to pay a dividend to the shareholder or shareholder's associate.\n\nInterest received by the private company must be included in the income tax return for 2018-19.\n\nMinimum yearly repayment\n\n$51.00\n\nBenchmark interest rate\n\n5.2%\n\nOpening balance:\n\nDate: 30/06/2018\n\nBalance: $95.46\n\nDays: 302\n\nInterest: $4.11\n\nPayments\n\nDate: 29/04/2019\n\nAmount: $954.68\n\nBalance: $0\n\nDays: 63\n\nInterest: $0\n\n\n\n\nTotal repayments\n\n$954.68\n\nTotal interest\n\n$4.11\n\nTotal principal\n\n$950.57\n\nClosing balance\n\nDate: 30/06/2019\n\nBalance: $0",
  "outputs": {
    "enquiryRateFormatted": "5.2%",
    "enquiryYearEndMinusOneDisplay": "30/06/2018",
    "amalgamatedLoanNotPaidByEOIYFormatted": "$95.46",
    "openingBalancePayDays": "302",
    "openingBalanceInterestFormatted": "$4.11",
    "totalAmountOfRepaymentFormatted": "$954.68",
    "totalInterestFormatted": "$4.11",
    "principalFormatted": "$950.57",
    "enquiryYearEndDisplay": "30/06/2019",
    "minimumYearRepaymentFormatted": "$51.00",
    "loanAmountFormatted": "$0"
  },
  "repayments": [
    {
      "rd": "29/4/2019",
      "ra": 954.6805332099575
    }
  ],
  "inputs": {
    "incomeYearOfLoan": 2013,
    "fullTermOfAmalgamatedLoan": 7,
    "incomeYearOfEnquiring": 2019,
    "amalgamatedLoanNotPaidByEOIY": 95.46805332099571,
    "repayments": null,
    "lodgement_date": null
  },
  "idx": 3042
}