{
  "id": "2023-09-04T20:48:29.759Z0.9518219222035191",
  "alert": "Start of result\nResult\n\nMinimum yearly repayment met.\n\nThe amount of the loan not repaid at the end of income year 2013-14 is $643.57.\n\nThe amalgamated loan will not be taken to be a dividend because the total repayments made are equal to or greater than the minimum yearly repayment required for income year 2013-14.\n\nInterest received by the private company must be included in the income tax return for 2013-14.\n\nMinimum yearly repayment\n\n$1,936.00\n\nBenchmark interest rate\n\n6.2%\n\nOpening balance:\n\nDate: 30/06/2013\n\nBalance: $9,459.00\n\nDays: 0\n\nInterest: $0\n\nPayments\n\nDate: 01/07/2013\n\nAmount: $8,853.00\n\nBalance: $606.00\n\nDays: 365\n\nInterest: $37.57\n\n\n\n\nTotal repayments\n\n$8,853.00\n\nTotal interest\n\n$37.57\n\nTotal principal\n\n$8,815.43\n\nClosing balance\n\nDate: 30/06/2014\n\nBalance: $643.57",
  "outputs": {
    "enquiryRateFormatted": "6.2%",
    "enquiryYearEndMinusOneDisplay": "30/06/2013",
    "amalgamatedLoanNotPaidByEOIYFormatted": "$9,459.00",
    "openingBalancePayDays": "0",
    "openingBalanceInterestFormatted": "$0",
    "totalAmountOfRepaymentFormatted": "$8,853.00",
    "totalInterestFormatted": "$37.57",
    "principalFormatted": "$8,815.43",
    "enquiryYearEndDisplay": "30/06/2014",
    "minimumYearRepaymentFormatted": "$1,936.00"
  },
  "repayments": [
    {
      "rd": "1/7/2013",
      "ra": 8853
    }
  ],
  "inputs": {
    "incomeYearOfLoan": 2012,
    "fullTermOfAmalgamatedLoan": 7,
    "incomeYearOfEnquiring": 2014,
    "amalgamatedLoanNotPaidByEOIY": 9459,
    "repayments": null,
    "lodgement_date": null
  },
  "idx": 40
}