{
  "id": "2023-10-31T18:19:29.249Z0.1578568783997948",
  "alert": "Start of result\nResult\n\nMinimum yearly repayment not met.\n\nThe amount of the loan not repaid at the end of income year 2011-12 is $2,689.87.\n\nThe private company may be taken to pay a dividend under Division 7A to the shareholder or shareholder's associate because the amount repaid during income year 2011-12 in relation to the amalgamated loan is less than the minimum yearly repayment required.\n\nInterest received by the private company must be included in the income tax return for 2011-12.\n\nMinimum yearly repayment\n\n$2,597.00\n\nBenchmark interest rate\n\n7.8%\n\nOpening balance:\n\nDate: 30/06/2011\n\nBalance: $4,644.00\n\nDays: 17\n\nInterest: $16.82\n\nPayments\n\nDate: 18/07/2011\n\nAmount: $2,156.00\n\nBalance: $2,488.00\n\nDays: 349\n\nInterest: $185.05\n\n\n\n\nTotal repayments\n\n$2,156.00\n\nTotal interest\n\n$201.87\n\nTotal principal\n\n$1,954.13\n\nClosing balance\n\nDate: 30/06/2012\n\nBalance: $2,689.87",
  "outputs": {
    "enquiryRateFormatted": "7.8%",
    "enquiryYearEndMinusOneDisplay": "30/06/2011",
    "amalgamatedLoanNotPaidByEOIYFormatted": "$4,644.00",
    "openingBalancePayDays": "17",
    "openingBalanceInterestFormatted": "$16.82",
    "totalAmountOfRepaymentFormatted": "$2,156.00",
    "totalInterestFormatted": "$201.87",
    "principalFormatted": "$1,954.13",
    "enquiryYearEndDisplay": "30/06/2012",
    "minimumYearRepaymentFormatted": "$2,597.00",
    "loanAmountFormatted": "$2,689.87"
  },
  "repayments": [
    {
      "rd": "18/7/2011",
      "ra": 2156
    }
  ],
  "inputs": {
    "incomeYearOfLoan": 2010,
    "fullTermOfAmalgamatedLoan": 3,
    "incomeYearOfEnquiring": 2012,
    "amalgamatedLoanNotPaidByEOIY": 4644,
    "repayments": null,
    "lodgement_date": null
  },
  "idx": 3778
}