{
  "id": "2023-10-31T17:42:15.592Z0.7508849466737523",
  "alert": "Start of result\nResult\n\nAmalgamated loan fully repaid.\n\nThe amalgamated loan has been paid in full.\u000bThe private company is not taken under Division 7A to pay a dividend to the shareholder or shareholder's associate.\n\nInterest received by the private company must be included in the income tax return for 2018-19.\n\nMinimum yearly repayment\n\n$900.00\n\nBenchmark interest rate\n\n5.2%\n\nOpening balance:\n\nDate: 30/06/2018\n\nBalance: $2,442.00\n\nDays: 58\n\nInterest: $20.18\n\nPayments\n\nDate: 28/08/2018\n\nAmount: $853.00\n\nBalance: $1,589.00\n\nDays: 54\n\nInterest: $12.22\n\n\n\n\nDate: 21/10/2018\n\nAmount: $766.00\n\nBalance: $823.00\n\nDays: 10\n\nInterest: $1.17\n\n\n\n\nDate: 31/10/2018\n\nAmount: $5,056.00\n\nBalance: $0\n\nDays: 34\n\nInterest: $0\n\n\n\n\nDate: 04/12/2018\n\nAmount: $3,987.00\n\nBalance: $0\n\nDays: 209\n\nInterest: $0\n\n\n\n\nTotal repayments\n\n$10,662.00\n\nTotal interest\n\n$33.57\n\nTotal principal\n\n$10,628.43\n\nClosing balance\n\nDate: 30/06/2019\n\nBalance: $0",
  "outputs": {
    "enquiryRateFormatted": "5.2%",
    "enquiryYearEndMinusOneDisplay": "30/06/2018",
    "amalgamatedLoanNotPaidByEOIYFormatted": "$2,442.00",
    "openingBalancePayDays": "58",
    "openingBalanceInterestFormatted": "$20.18",
    "totalAmountOfRepaymentFormatted": "$10,662.00",
    "totalInterestFormatted": "$33.57",
    "principalFormatted": "$10,628.43",
    "enquiryYearEndDisplay": "30/06/2019",
    "minimumYearRepaymentFormatted": "$900.00",
    "loanAmountFormatted": "$0"
  },
  "repayments": [
    {
      "rd": "28/8/2018",
      "ra": 853
    },
    {
      "rd": "21/10/2018",
      "ra": 766
    },
    {
      "rd": "31/10/2018",
      "ra": 5056
    },
    {
      "rd": "4/12/2018",
      "ra": 3987
    }
  ],
  "inputs": {
    "incomeYearOfLoan": 2015,
    "fullTermOfAmalgamatedLoan": 6,
    "incomeYearOfEnquiring": 2019,
    "amalgamatedLoanNotPaidByEOIY": 2442,
    "repayments": null,
    "lodgement_date": null
  },
  "idx": 2333
}