{
  "id": "2023-09-05T22:08:48.434Z0.5665082048713641",
  "alert": "Start of result\nResult\n\nMinimum yearly repayment not met.\n\nThe amount of the loan not repaid at the end of income year 2020-21 is $1.89.\n\nThe private company may be taken to pay a dividend under Division 7A to the shareholder or shareholder's associate because the amount repaid during income year 2020-21 in relation to the amalgamated loan is less than the minimum yearly repayment required.\n\nInterest received by the private company must be included in the income tax return for 2020-21.\n\nMinimum yearly repayment\n\n$117.00\n\nBenchmark interest rate\n\n4.52%\n\nOpening balance:\n\nDate: 30/06/2020\n\nBalance: $111.63\n\nDays: 137\n\nInterest: $1.89\n\nPayments\n\nDate: 15/11/2020\n\nAmount: $111.63\n\nBalance: $0\n\nDays: 228\n\nInterest: $0\n\n\n\n\nTotal repayments\n\n$111.63\n\nTotal interest\n\n$1.89\n\nTotal principal\n\n$109.74\n\nClosing balance\n\nDate: 30/06/2021\n\nBalance: $1.89",
  "outputs": {
    "enquiryRateFormatted": "4.52%",
    "enquiryYearEndMinusOneDisplay": "30/06/2020",
    "amalgamatedLoanNotPaidByEOIYFormatted": "$111.63",
    "openingBalancePayDays": "137",
    "openingBalanceInterestFormatted": "$1.89",
    "totalAmountOfRepaymentFormatted": "$111.63",
    "totalInterestFormatted": "$1.89",
    "principalFormatted": "$109.74",
    "enquiryYearEndDisplay": "30/06/2021",
    "minimumYearRepaymentFormatted": "$117.00"
  },
  "repayments": [
    {
      "rd": "15/11/2020",
      "ra": 111.63885081322587
    }
  ],
  "inputs": {
    "incomeYearOfLoan": 2016,
    "fullTermOfAmalgamatedLoan": 5,
    "incomeYearOfEnquiring": 2021,
    "amalgamatedLoanNotPaidByEOIY": 111.63885081322647,
    "repayments": null,
    "lodgement_date": null
  },
  "idx": 3307
}