{
  "id": "2023-09-04T16:15:27.137Z0.781457167312547",
  "alert": "Start of result\nResult\n\nMinimum yearly repayment not met.\n\nThe amount of the loan not repaid at the end of income year 2021-22 is $91,865,718.79.\n\nThe private company may be taken to pay a dividend under Division 7A to the shareholder or shareholder's associate because the amount repaid during income year 2021-22 in relation to the amalgamated loan is less than the minimum yearly repayment required.\n\nInterest received by the private company must be included in the income tax return for 2021-22.\n\nMinimum yearly repayment\n\n$25,618,968.00\n\nBenchmark interest rate\n\n4.52%\n\nOpening balance:\n\nDate: 30/06/2021\n\nBalance: $91,865,718.79\n\nDays: 0\n\nInterest: $0\n\nPayments\n\nDate: 01/07/2021\n\nAmount: $5.00\n\nBalance: $91,865,713.79\n\nDays: 365\n\nInterest: $4,152,330.26\n\n\n\n\nTotal repayments\n\n$5.00\n\nTotal interest\n\n$4,152,330.26\n\nTotal principal\n\n$0\n\nClosing balance\n\nDate: 30/06/2022\n\nBalance: $91,865,718.79",
  "outputs": {
    "enquiryRateFormatted": "4.52%",
    "enquiryYearEndMinusOneDisplay": "30/06/2021",
    "amalgamatedLoanNotPaidByEOIYFormatted": "$91,865,718.79",
    "openingBalancePayDays": "0",
    "openingBalanceInterestFormatted": "$0",
    "totalAmountOfRepaymentFormatted": "$5.00",
    "totalInterestFormatted": "$4,152,330.26",
    "principalFormatted": "$0",
    "enquiryYearEndDisplay": "30/06/2022",
    "minimumYearRepaymentFormatted": "$25,618,968.00"
  },
  "repayments": [
    {
      "rd": "1/7/2021",
      "ra": 5
    }
  ],
  "inputs": {
    "incomeYearOfLoan": 2021,
    "fullTermOfAmalgamatedLoan": 4,
    "incomeYearOfEnquiring": 2022,
    "amalgamatedLoanNotPaidByEOIY": 91865718.79879904,
    "repayments": null,
    "lodgement_date": "30/6/2022"
  },
  "idx": 118
}