{
  "id": "2023-09-07T01:37:01.101Z0.39162691884950207",
  "alert": "Start of result\nResult\n\nMinimum yearly repayment not met.\n\nThe amount of the loan not repaid at the end of income year 2001-02 is $7,380.63.\n\nThe private company may be taken to pay a dividend under Division 7A to the shareholder or shareholder's associate because the amount repaid during income year 2001-02 in relation to the amalgamated loan is less than the minimum yearly repayment required.\n\nInterest received by the private company must be included in the income tax return for 2001-02.\n\nMinimum yearly repayment\n\n$8,667.00\n\nBenchmark interest rate\n\n6.8%\n\nOpening balance:\n\nDate: 30/06/2001\n\nBalance: $8,115.00\n\nDays: 288\n\nInterest: $435.41\n\nPayments\n\nDate: 15/04/2002\n\nAmount: $1,268.00\n\nBalance: $6,847.00\n\nDays: 77\n\nInterest: $98.22\n\n\n\n\nTotal repayments\n\n$1,268.00\n\nTotal interest\n\n$533.63\n\nTotal principal\n\n$734.37\n\nClosing balance\n\nDate: 30/06/2002\n\nBalance: $7,380.63",
  "outputs": {
    "enquiryRateFormatted": "6.8%",
    "enquiryYearEndMinusOneDisplay": "30/06/2001",
    "amalgamatedLoanNotPaidByEOIYFormatted": "$8,115.00",
    "openingBalancePayDays": "288",
    "openingBalanceInterestFormatted": "$435.41",
    "totalAmountOfRepaymentFormatted": "$1,268.00",
    "totalInterestFormatted": "$533.63",
    "principalFormatted": "$734.37",
    "enquiryYearEndDisplay": "30/06/2002",
    "minimumYearRepaymentFormatted": "$8,667.00"
  },
  "repayments": [
    {
      "rd": "15/4/2002",
      "ra": 1268
    }
  ],
  "inputs": {
    "incomeYearOfLoan": 1999,
    "fullTermOfAmalgamatedLoan": 3,
    "incomeYearOfEnquiring": 2002,
    "amalgamatedLoanNotPaidByEOIY": 8115,
    "repayments": null,
    "lodgement_date": null
  },
  "idx": 1838
}