{
  "id": "2023-10-31T21:07:47.970Z0.9138360194714729",
  "alert": "Start of result\nResult\n\nAmalgamated loan fully repaid.\n\nThe amalgamated loan has been paid in full.\u000bThe private company is not taken under Division 7A to pay a dividend to the shareholder or shareholder's associate.\n\nInterest received by the private company must be included in the income tax return for 2003-04.\n\nMinimum yearly repayment\n\n$30.00\n\nBenchmark interest rate\n\n6.55%\n\nOpening balance:\n\nDate: 30/06/2003\n\nBalance: $54.88\n\nDays: 18\n\nInterest: $0.18\n\nPayments\n\nDate: 19/07/2003\n\nAmount: $548.81\n\nBalance: $0\n\nDays: 348\n\nInterest: $0\n\n\n\n\nTotal repayments\n\n$548.81\n\nTotal interest\n\n$0.18\n\nTotal principal\n\n$548.63\n\nClosing balance\n\nDate: 30/06/2004\n\nBalance: $0",
  "outputs": {
    "enquiryRateFormatted": "6.55%",
    "enquiryYearEndMinusOneDisplay": "30/06/2003",
    "amalgamatedLoanNotPaidByEOIYFormatted": "$54.88",
    "openingBalancePayDays": "18",
    "openingBalanceInterestFormatted": "$0.18",
    "totalAmountOfRepaymentFormatted": "$548.81",
    "totalInterestFormatted": "$0.18",
    "principalFormatted": "$548.63",
    "enquiryYearEndDisplay": "30/06/2004",
    "minimumYearRepaymentFormatted": "$30.00",
    "loanAmountFormatted": "$0"
  },
  "repayments": [
    {
      "rd": "19/7/2003",
      "ra": 548.8180799529009
    }
  ],
  "inputs": {
    "incomeYearOfLoan": 1999,
    "fullTermOfAmalgamatedLoan": 6,
    "incomeYearOfEnquiring": 2004,
    "amalgamatedLoanNotPaidByEOIY": 54.88180799529007,
    "repayments": null,
    "lodgement_date": null
  },
  "idx": 7037
}