{
  "id": "2023-10-31T19:58:55.377Z0.9787505914863699",
  "alert": "Start of result\nResult\n\nAmalgamated loan fully repaid.\n\nThe amalgamated loan has been paid in full.\u000bThe private company is not taken under Division 7A to pay a dividend to the shareholder or shareholder's associate.\n\nInterest received by the private company must be included in the income tax return for 2004-05.\n\nMinimum yearly repayment\n\n$22.00\n\nBenchmark interest rate\n\n7.05%\n\nOpening balance:\n\nDate: 30/06/2004\n\nBalance: $39.20\n\nDays: 252\n\nInterest: $1.91\n\nPayments\n\nDate: 10/03/2005\n\nAmount: $392.09\n\nBalance: $0\n\nDays: 113\n\nInterest: $0\n\n\n\n\nTotal repayments\n\n$392.09\n\nTotal interest\n\n$1.91\n\nTotal principal\n\n$390.18\n\nClosing balance\n\nDate: 30/06/2005\n\nBalance: $0",
  "outputs": {
    "enquiryRateFormatted": "7.05%",
    "enquiryYearEndMinusOneDisplay": "30/06/2004",
    "amalgamatedLoanNotPaidByEOIYFormatted": "$39.20",
    "openingBalancePayDays": "252",
    "openingBalanceInterestFormatted": "$1.91",
    "totalAmountOfRepaymentFormatted": "$392.09",
    "totalInterestFormatted": "$1.91",
    "principalFormatted": "$390.18",
    "enquiryYearEndDisplay": "30/06/2005",
    "minimumYearRepaymentFormatted": "$22.00",
    "loanAmountFormatted": "$0"
  },
  "repayments": [
    {
      "rd": "10/3/2005",
      "ra": 392.09308360652017
    }
  ],
  "inputs": {
    "incomeYearOfLoan": 2002,
    "fullTermOfAmalgamatedLoan": 4,
    "incomeYearOfEnquiring": 2005,
    "amalgamatedLoanNotPaidByEOIY": 39.20930836065202,
    "repayments": null,
    "lodgement_date": null
  },
  "idx": 6052
}