{
  "id": "2023-09-04T20:54:31.545Z0.21105004050694576",
  "alert": "Start of result\nResult\n\nMinimum yearly repayment not met.\n\nThe amount of the loan not repaid at the end of income year 2010-11 is $59,251,649.31.\n\nThe private company may be taken to pay a dividend under Division 7A to the shareholder or shareholder's associate because the amount repaid during income year 2010-11 in relation to the amalgamated loan is less than the minimum yearly repayment required.\n\nInterest received by the private company must be included in the income tax return for 2010-11.\n\nMinimum yearly repayment\n\n$32,953,402.00\n\nBenchmark interest rate\n\n7.4%\n\nOpening balance:\n\nDate: 30/06/2010\n\nBalance: $59,251,649.31\n\nDays: 365\n\nInterest: $4,384,622.05\n\nTotal repayments\n\n$0\n\nTotal interest\n\n$4,384,622.05\n\nTotal principal\n\n$0\n\nClosing balance\n\nDate: 30/06/2011\n\nBalance: $59,251,649.31",
  "outputs": {
    "enquiryRateFormatted": "7.4%",
    "enquiryYearEndMinusOneDisplay": "30/06/2010",
    "amalgamatedLoanNotPaidByEOIYFormatted": "$59,251,649.31",
    "openingBalancePayDays": "365",
    "openingBalanceInterestFormatted": "$4,384,622.05",
    "totalAmountOfRepaymentFormatted": "$0",
    "totalInterestFormatted": "$4,384,622.05",
    "principalFormatted": "$0",
    "enquiryYearEndDisplay": "30/06/2011",
    "minimumYearRepaymentFormatted": "$32,953,402.00"
  },
  "repayments": [],
  "inputs": {
    "incomeYearOfLoan": 2010,
    "fullTermOfAmalgamatedLoan": 2,
    "incomeYearOfEnquiring": 2011,
    "amalgamatedLoanNotPaidByEOIY": 59251649.310073785,
    "repayments": null,
    "lodgement_date": "1/7/2010"
  },
  "idx": 273
}