{
  "id": "2023-09-05T16:30:22.247Z0.23970632147532656",
  "alert": "Start of result\nResult\n\nMinimum yearly repayment not met.\n\nThe amount of the loan not repaid at the end of income year 2021-22 is $4,627.72.\n\nThe private company may be taken to pay a dividend under Division 7A to the shareholder or shareholder's associate because the amount repaid during income year 2021-22 in relation to the amalgamated loan is less than the minimum yearly repayment required.\n\nInterest received by the private company must be included in the income tax return for 2021-22.\n\nMinimum yearly repayment\n\n$5,223.00\n\nBenchmark interest rate\n\n4.52%\n\nOpening balance:\n\nDate: 30/06/2021\n\nBalance: $4,997.00\n\nDays: 225\n\nInterest: $139.23\n\nPayments\n\nDate: 11/02/2022\n\nAmount: $585.00\n\nBalance: $4,412.00\n\nDays: 140\n\nInterest: $76.49\n\n\n\n\nTotal repayments\n\n$585.00\n\nTotal interest\n\n$215.72\n\nTotal principal\n\n$369.28\n\nClosing balance\n\nDate: 30/06/2022\n\nBalance: $4,627.72",
  "outputs": {
    "enquiryRateFormatted": "4.52%",
    "enquiryYearEndMinusOneDisplay": "30/06/2021",
    "amalgamatedLoanNotPaidByEOIYFormatted": "$4,997.00",
    "openingBalancePayDays": "225",
    "openingBalanceInterestFormatted": "$139.23",
    "totalAmountOfRepaymentFormatted": "$585.00",
    "totalInterestFormatted": "$215.72",
    "principalFormatted": "$369.28",
    "enquiryYearEndDisplay": "30/06/2022",
    "minimumYearRepaymentFormatted": "$5,223.00"
  },
  "repayments": [
    {
      "rd": "11/2/2022",
      "ra": 585
    }
  ],
  "inputs": {
    "incomeYearOfLoan": 2019,
    "fullTermOfAmalgamatedLoan": 3,
    "incomeYearOfEnquiring": 2022,
    "amalgamatedLoanNotPaidByEOIY": 4997,
    "repayments": null,
    "lodgement_date": null
  },
  "idx": 737
}