{
  "id": "2023-09-05T16:17:15.591Z0.7959475737007757",
  "alert": "Start of result\nResult\n\nMinimum yearly repayment met.\n\nThe amount of the loan not repaid at the end of income year 2019-20 is $2.30.\n\nThe amalgamated loan will not be taken to be a dividend because the total repayments made are equal to or greater than the minimum yearly repayment required for income year 2019-20.\n\nInterest received by the private company must be included in the income tax return for 2019-20.\n\nMinimum yearly repayment\n\n$0\n\nBenchmark interest rate\n\n5.37%\n\nOpening balance:\n\nDate: 30/06/2019\n\nBalance: $68.47\n\nDays: 229\n\nInterest: $2.30\n\nPayments\n\nDate: 15/02/2020\n\nAmount: $68.47\n\nBalance: $0\n\nDays: 137\n\nInterest: $0\n\n\n\n\nTotal repayments\n\n$68.47\n\nTotal interest\n\n$2.30\n\nTotal principal\n\n$66.17\n\nClosing balance\n\nDate: 30/06/2020\n\nBalance: $2.30",
  "outputs": {
    "enquiryRateFormatted": "5.37%",
    "enquiryYearEndMinusOneDisplay": "30/06/2019",
    "amalgamatedLoanNotPaidByEOIYFormatted": "$68.47",
    "openingBalancePayDays": "229",
    "openingBalanceInterestFormatted": "$2.30",
    "totalAmountOfRepaymentFormatted": "$68.47",
    "totalInterestFormatted": "$2.30",
    "principalFormatted": "$66.17",
    "enquiryYearEndDisplay": "30/06/2020",
    "minimumYearRepaymentFormatted": "$0"
  },
  "repayments": [
    {
      "rd": "15/2/2020",
      "ra": 68.47773594280716
    }
  ],
  "inputs": {
    "incomeYearOfLoan": 2019,
    "fullTermOfAmalgamatedLoan": 1,
    "incomeYearOfEnquiring": 2020,
    "amalgamatedLoanNotPaidByEOIY": 68.47773594280736,
    "repayments": null,
    "lodgement_date": "31/5/2020"
  },
  "idx": 8797
}