{
  "id": "2023-10-31T17:52:06.825Z0.8850602369992222",
  "alert": "Start of result\nResult\n\nMinimum yearly repayment met.\n\nThe amount of the loan not repaid at the end of income year 2016-17 is $3,304.66.\n\n\u000b\n\nThe amalgamated loan will not be taken to be a dividend because the total repayments made are equal to or greater than the minimum yearly repayment required for income year 2016-17.\n\nInterest received by the private company must be included in the income tax return for 2016-17.\n\nMinimum yearly repayment\n\n$1,144.00\n\nBenchmark interest rate\n\n5.4%\n\nOpening balance:\n\nDate: 30/06/2016\n\nBalance: $4,899.00\n\nDays: 213\n\nInterest: $154.38\n\nPayments\n\nDate: 30/01/2017\n\nAmount: $1,818.00\n\nBalance: $3,081.00\n\nDays: 152\n\nInterest: $69.28\n\n\n\n\nTotal repayments\n\n$1,818.00\n\nTotal interest\n\n$223.66\n\nTotal principal\n\n$1,594.34\n\nClosing balance\n\nDate: 30/06/2017\n\nBalance: $3,304.66",
  "outputs": {
    "enquiryRateFormatted": "5.4%",
    "enquiryYearEndMinusOneDisplay": "30/06/2016",
    "amalgamatedLoanNotPaidByEOIYFormatted": "$4,899.00",
    "openingBalancePayDays": "213",
    "openingBalanceInterestFormatted": "$154.38",
    "totalAmountOfRepaymentFormatted": "$1,818.00",
    "totalInterestFormatted": "$223.66",
    "principalFormatted": "$1,594.34",
    "enquiryYearEndDisplay": "30/06/2017",
    "minimumYearRepaymentFormatted": "$1,144.00",
    "loanAmountFormatted": "$3,304.66"
  },
  "repayments": [
    {
      "rd": "30/1/2017",
      "ra": 1818
    }
  ],
  "inputs": {
    "incomeYearOfLoan": 2014,
    "fullTermOfAmalgamatedLoan": 7,
    "incomeYearOfEnquiring": 2017,
    "amalgamatedLoanNotPaidByEOIY": 4899,
    "repayments": null,
    "lodgement_date": null
  },
  "idx": 2774
}