{
  "id": "2023-11-01T00:34:54.270Z0.9284002853187968",
  "alert": "Start of result\nResult\n\nMinimum yearly repayment not met.\n\nThe amount of the loan not repaid at the end of income year 2003-04 is $1,125.11.\n\nThe private company may be taken to pay a dividend under Division 7A to the shareholder or shareholder's associate because the amount repaid during income year 2003-04 in relation to the amalgamated loan is less than the minimum yearly repayment required.\n\nInterest received by the private company must be included in the income tax return for 2003-04.\n\nMinimum yearly repayment\n\n$9,335.00\n\nBenchmark interest rate\n\n6.55%\n\nOpening balance:\n\nDate: 30/06/2003\n\nBalance: $8,761.00\n\nDays: 291\n\nInterest: $456.25\n\nPayments\n\nDate: 17/04/2004\n\nAmount: $8,101.00\n\nBalance: $660.00\n\nDays: 75\n\nInterest: $8.86\n\n\n\n\nTotal repayments\n\n$8,101.00\n\nTotal interest\n\n$465.11\n\nTotal principal\n\n$7,635.89\n\nClosing balance\n\nDate: 30/06/2004\n\nBalance: $1,125.11",
  "outputs": {
    "enquiryRateFormatted": "6.55%",
    "enquiryYearEndMinusOneDisplay": "30/06/2003",
    "amalgamatedLoanNotPaidByEOIYFormatted": "$8,761.00",
    "openingBalancePayDays": "291",
    "openingBalanceInterestFormatted": "$456.25",
    "totalAmountOfRepaymentFormatted": "$8,101.00",
    "totalInterestFormatted": "$465.11",
    "principalFormatted": "$7,635.89",
    "enquiryYearEndDisplay": "30/06/2004",
    "minimumYearRepaymentFormatted": "$9,335.00",
    "loanAmountFormatted": "$1,125.11"
  },
  "repayments": [
    {
      "rd": "17/4/2004",
      "ra": 8101
    }
  ],
  "inputs": {
    "incomeYearOfLoan": 1998,
    "fullTermOfAmalgamatedLoan": 6,
    "incomeYearOfEnquiring": 2004,
    "amalgamatedLoanNotPaidByEOIY": 8761,
    "repayments": null,
    "lodgement_date": null
  },
  "idx": 31
}