{
  "id": "2023-10-31T17:28:13.531Z0.7526777671387308",
  "alert": "Start of result\nResult\n\nAmalgamated loan fully repaid.\n\nThe amalgamated loan has been paid in full.\u000bThe private company is not taken under Division 7A to pay a dividend to the shareholder or shareholder's associate.\n\nInterest received by the private company must be included in the income tax return for 2019-20.\n\nMinimum yearly repayment\n\n$29.00\n\nBenchmark interest rate\n\n5.37%\n\nOpening balance:\n\nDate: 30/06/2019\n\nBalance: $53.97\n\nDays: 362\n\nInterest: $2.87\n\nPayments\n\nDate: 27/06/2020\n\nAmount: $539.77\n\nBalance: $0\n\nDays: 4\n\nInterest: $0\n\n\n\n\nTotal repayments\n\n$539.77\n\nTotal interest\n\n$2.87\n\nTotal principal\n\n$536.90\n\nClosing balance\n\nDate: 30/06/2020\n\nBalance: $0",
  "outputs": {
    "enquiryRateFormatted": "5.37%",
    "enquiryYearEndMinusOneDisplay": "30/06/2019",
    "amalgamatedLoanNotPaidByEOIYFormatted": "$53.97",
    "openingBalancePayDays": "362",
    "openingBalanceInterestFormatted": "$2.87",
    "totalAmountOfRepaymentFormatted": "$539.77",
    "totalInterestFormatted": "$2.87",
    "principalFormatted": "$536.90",
    "enquiryYearEndDisplay": "30/06/2020",
    "minimumYearRepaymentFormatted": "$29.00",
    "loanAmountFormatted": "$0"
  },
  "repayments": [
    {
      "rd": "27/6/2020",
      "ra": 539.7719819075737
    }
  ],
  "inputs": {
    "incomeYearOfLoan": 2017,
    "fullTermOfAmalgamatedLoan": 4,
    "incomeYearOfEnquiring": 2020,
    "amalgamatedLoanNotPaidByEOIY": 53.97719819075739,
    "repayments": null,
    "lodgement_date": null
  },
  "idx": 1599
}