{
  "id": "2023-09-06T00:14:26.593Z0.095848830732856",
  "alert": "Start of result\nResult\n\nMinimum yearly repayment met.\n\nThe amount of the loan not repaid at the end of income year 2017-18 is $2.75.\n\nThe amalgamated loan will not be taken to be a dividend because the total repayments made are equal to or greater than the minimum yearly repayment required for income year 2017-18.\n\nInterest received by the private company must be included in the income tax return for 2017-18.\n\nMinimum yearly repayment\n\n$19.00\n\nBenchmark interest rate\n\n5.3%\n\nOpening balance:\n\nDate: 30/06/2017\n\nBalance: $79.67\n\nDays: 238\n\nInterest: $2.75\n\nPayments\n\nDate: 24/02/2018\n\nAmount: $79.67\n\nBalance: $0\n\nDays: 127\n\nInterest: $0\n\n\n\n\nTotal repayments\n\n$79.67\n\nTotal interest\n\n$2.75\n\nTotal principal\n\n$76.92\n\nClosing balance\n\nDate: 30/06/2018\n\nBalance: $2.75",
  "outputs": {
    "enquiryRateFormatted": "5.3%",
    "enquiryYearEndMinusOneDisplay": "30/06/2017",
    "amalgamatedLoanNotPaidByEOIYFormatted": "$79.67",
    "openingBalancePayDays": "238",
    "openingBalanceInterestFormatted": "$2.75",
    "totalAmountOfRepaymentFormatted": "$79.67",
    "totalInterestFormatted": "$2.75",
    "principalFormatted": "$76.92",
    "enquiryYearEndDisplay": "30/06/2018",
    "minimumYearRepaymentFormatted": "$19.00"
  },
  "repayments": [
    {
      "rd": "24/2/2018",
      "ra": 79.67278564431854
    }
  ],
  "inputs": {
    "incomeYearOfLoan": 2015,
    "fullTermOfAmalgamatedLoan": 7,
    "incomeYearOfEnquiring": 2018,
    "amalgamatedLoanNotPaidByEOIY": 79.67278564431868,
    "repayments": null,
    "lodgement_date": null
  },
  "idx": 2231
}