{
  "id": "2023-10-31T17:23:00.985Z0.10761094276774308",
  "alert": "Start of result\nResult\n\nAmalgamated loan fully repaid.\n\nThe amalgamated loan has been paid in full.\u000bThe private company is not taken under Division 7A to pay a dividend to the shareholder or shareholder's associate.\n\nInterest received by the private company must be included in the income tax return for 2019-20.\n\nMinimum yearly repayment\n\n$3,580.00\n\nBenchmark interest rate\n\n5.37%\n\nOpening balance:\n\nDate: 30/06/2019\n\nBalance: $3,398.00\n\nDays: 157\n\nInterest: $78.27\n\nPayments\n\nDate: 05/12/2019\n\nAmount: $449.00\n\nBalance: $2,949.00\n\nDays: 7\n\nInterest: $3.03\n\n\n\n\nDate: 12/12/2019\n\nAmount: $8,670.00\n\nBalance: $0\n\nDays: 202\n\nInterest: $0\n\n\n\n\nTotal repayments\n\n$9,119.00\n\nTotal interest\n\n$81.30\n\nTotal principal\n\n$9,037.70\n\nClosing balance\n\nDate: 30/06/2020\n\nBalance: $0",
  "outputs": {
    "enquiryRateFormatted": "5.37%",
    "enquiryYearEndMinusOneDisplay": "30/06/2019",
    "amalgamatedLoanNotPaidByEOIYFormatted": "$3,398.00",
    "openingBalancePayDays": "157",
    "openingBalanceInterestFormatted": "$78.27",
    "totalAmountOfRepaymentFormatted": "$9,119.00",
    "totalInterestFormatted": "$81.30",
    "principalFormatted": "$9,037.70",
    "enquiryYearEndDisplay": "30/06/2020",
    "minimumYearRepaymentFormatted": "$3,580.00",
    "loanAmountFormatted": "$0"
  },
  "repayments": [
    {
      "rd": "5/12/2019",
      "ra": 449
    },
    {
      "rd": "12/12/2019",
      "ra": 8670
    }
  ],
  "inputs": {
    "incomeYearOfLoan": 2018,
    "fullTermOfAmalgamatedLoan": 2,
    "incomeYearOfEnquiring": 2020,
    "amalgamatedLoanNotPaidByEOIY": 3398,
    "repayments": null,
    "lodgement_date": null
  },
  "idx": 1288
}