{
  "id": "2023-09-05T21:13:42.348Z0.31536921053641676",
  "alert": "Start of result\nResult\n\nMinimum yearly repayment not met.\n\nThe amount of the loan not repaid at the end of income year 2016-17 is $27.90.\n\nThe private company may be taken to pay a dividend under Division 7A to the shareholder or shareholder's associate because the amount repaid during income year 2016-17 in relation to the amalgamated loan is less than the minimum yearly repayment required.\n\nInterest received by the private company must be included in the income tax return for 2016-17.\n\nMinimum yearly repayment\n\n$4,417.00\n\nBenchmark interest rate\n\n5.4%\n\nOpening balance:\n\nDate: 30/06/2016\n\nBalance: $4,191.00\n\nDays: 45\n\nInterest: $27.90\n\nPayments\n\nDate: 15/08/2016\n\nAmount: $4,191.00\n\nBalance: $0\n\nDays: 320\n\nInterest: $0\n\n\n\n\nTotal repayments\n\n$4,191.00\n\nTotal interest\n\n$27.90\n\nTotal principal\n\n$4,163.10\n\nClosing balance\n\nDate: 30/06/2017\n\nBalance: $27.90",
  "outputs": {
    "enquiryRateFormatted": "5.4%",
    "enquiryYearEndMinusOneDisplay": "30/06/2016",
    "amalgamatedLoanNotPaidByEOIYFormatted": "$4,191.00",
    "openingBalancePayDays": "45",
    "openingBalanceInterestFormatted": "$27.90",
    "totalAmountOfRepaymentFormatted": "$4,191.00",
    "totalInterestFormatted": "$27.90",
    "principalFormatted": "$4,163.10",
    "enquiryYearEndDisplay": "30/06/2017",
    "minimumYearRepaymentFormatted": "$4,417.00"
  },
  "repayments": [
    {
      "rd": "15/8/2016",
      "ra": 4191
    }
  ],
  "inputs": {
    "incomeYearOfLoan": 2016,
    "fullTermOfAmalgamatedLoan": 1,
    "incomeYearOfEnquiring": 2017,
    "amalgamatedLoanNotPaidByEOIY": 4191,
    "repayments": null,
    "lodgement_date": "14/8/2016"
  },
  "idx": 8518
}