{
  "id": "2023-10-31T17:41:11.113Z0.6073697141367923",
  "alert": "Start of result\nResult\n\nMinimum yearly repayment not met.\n\nThe amount of the loan not repaid at the end of income year 2019-20 is $27.57.\n\nThe private company may be taken to pay a dividend under Division 7A to the shareholder or shareholder's associate because the amount repaid during income year 2019-20 in relation to the amalgamated loan is less than the minimum yearly repayment required.\n\nInterest received by the private company must be included in the income tax return for 2019-20.\n\nMinimum yearly repayment\n\n$29.00\n\nBenchmark interest rate\n\n5.37%\n\nOpening balance:\n\nDate: 30/06/2019\n\nBalance: $27.57\n\nDays: 366\n\nInterest: $1.48\n\nTotal repayments\n\n$0\n\nTotal interest\n\n$1.48\n\nTotal principal\n\n$0\n\nClosing balance\n\nDate: 30/06/2020\n\nBalance: $27.57",
  "outputs": {
    "enquiryRateFormatted": "5.37%",
    "enquiryYearEndMinusOneDisplay": "30/06/2019",
    "amalgamatedLoanNotPaidByEOIYFormatted": "$27.57",
    "openingBalancePayDays": "366",
    "openingBalanceInterestFormatted": "$1.48",
    "totalAmountOfRepaymentFormatted": "$0",
    "totalInterestFormatted": "$1.48",
    "principalFormatted": "$0",
    "enquiryYearEndDisplay": "30/06/2020",
    "minimumYearRepaymentFormatted": "$29.00",
    "loanAmountFormatted": "$27.57"
  },
  "repayments": [],
  "inputs": {
    "incomeYearOfLoan": 2015,
    "fullTermOfAmalgamatedLoan": 5,
    "incomeYearOfEnquiring": 2020,
    "amalgamatedLoanNotPaidByEOIY": 27.57202712222223,
    "repayments": null,
    "lodgement_date": null
  },
  "idx": 2287
}