{
  "id": "2023-10-31T17:55:55.198Z0.8161813098720142",
  "alert": "Start of result\nResult\n\nMinimum yearly repayment not met.\n\nThe amount of the loan not repaid at the end of income year 2014-15 is $107.14.\n\nThe private company may be taken to pay a dividend under Division 7A to the shareholder or shareholder's associate because the amount repaid during income year 2014-15 in relation to the amalgamated loan is less than the minimum yearly repayment required.\n\nInterest received by the private company must be included in the income tax return for 2014-15.\n\nMinimum yearly repayment\n\n$40.00\n\nBenchmark interest rate\n\n5.95%\n\nOpening balance:\n\nDate: 30/06/2014\n\nBalance: $107.14\n\nDays: 365\n\nInterest: $6.37\n\nTotal repayments\n\n$0\n\nTotal interest\n\n$6.37\n\nTotal principal\n\n$0\n\nClosing balance\n\nDate: 30/06/2015\n\nBalance: $107.14",
  "outputs": {
    "enquiryRateFormatted": "5.95%",
    "enquiryYearEndMinusOneDisplay": "30/06/2014",
    "amalgamatedLoanNotPaidByEOIYFormatted": "$107.14",
    "openingBalancePayDays": "365",
    "openingBalanceInterestFormatted": "$6.37",
    "totalAmountOfRepaymentFormatted": "$0",
    "totalInterestFormatted": "$6.37",
    "principalFormatted": "$0",
    "enquiryYearEndDisplay": "30/06/2015",
    "minimumYearRepaymentFormatted": "$40.00",
    "loanAmountFormatted": "$107.14"
  },
  "repayments": [],
  "inputs": {
    "incomeYearOfLoan": 2013,
    "fullTermOfAmalgamatedLoan": 4,
    "incomeYearOfEnquiring": 2015,
    "amalgamatedLoanNotPaidByEOIY": 107.1430222486817,
    "repayments": null,
    "lodgement_date": null
  },
  "idx": 2932
}