{
  "id": "2023-10-31T21:14:28.143Z0.14046281894147294",
  "alert": "Start of result\nResult\n\nMinimum yearly repayment not met.\n\nThe amount of the loan not repaid at the end of income year 1998-99 is $11,594.00.\n\nThe private company may be taken to pay a dividend under Division 7A to the shareholder or shareholder's associate because the amount repaid during income year 1998-99 in relation to the amalgamated loan is less than the minimum yearly repayment required.\n\nInterest received by the private company must be included in the income tax return for 1998-99.\n\nMinimum yearly repayment\n\n$12,371.00\n\nBenchmark interest rate\n\n6.7%\n\nOpening balance:\n\nDate: 30/06/1998\n\nBalance: $11,594.00\n\nDays: 365\n\nInterest: $776.80\n\nTotal repayments\n\n$0\n\nTotal interest\n\n$776.80\n\nTotal principal\n\n$0\n\nClosing balance\n\nDate: 30/06/1999\n\nBalance: $11,594.00",
  "outputs": {
    "enquiryRateFormatted": "6.7%",
    "enquiryYearEndMinusOneDisplay": "30/06/1998",
    "amalgamatedLoanNotPaidByEOIYFormatted": "$11,594.00",
    "openingBalancePayDays": "365",
    "openingBalanceInterestFormatted": "$776.80",
    "totalAmountOfRepaymentFormatted": "$0",
    "totalInterestFormatted": "$776.80",
    "principalFormatted": "$0",
    "enquiryYearEndDisplay": "30/06/1999",
    "minimumYearRepaymentFormatted": "$12,371.00",
    "loanAmountFormatted": "$11,594.00"
  },
  "repayments": [],
  "inputs": {
    "incomeYearOfLoan": 1998,
    "fullTermOfAmalgamatedLoan": 1,
    "incomeYearOfEnquiring": 1999,
    "amalgamatedLoanNotPaidByEOIY": 11594,
    "repayments": null,
    "lodgement_date": "28/11/1998"
  },
  "idx": 7120
}