{
  "id": "2023-10-31T17:24:04.053Z0.9409173347172052",
  "alert": "Start of result\nResult\n\nMinimum yearly repayment not met.\n\nThe amount of the loan not repaid at the end of income year 2021-22 is $8,637.00.\n\nThe private company may be taken to pay a dividend under Division 7A to the shareholder or shareholder's associate because the amount repaid during income year 2021-22 in relation to the amalgamated loan is less than the minimum yearly repayment required.\n\nInterest received by the private company must be included in the income tax return for 2021-22.\n\nMinimum yearly repayment\n\n$9,027.00\n\nBenchmark interest rate\n\n4.52%\n\nOpening balance:\n\nDate: 30/06/2021\n\nBalance: $8,637.00\n\nDays: 365\n\nInterest: $390.39\n\nTotal repayments\n\n$0\n\nTotal interest\n\n$390.39\n\nTotal principal\n\n$0\n\nClosing balance\n\nDate: 30/06/2022\n\nBalance: $8,637.00",
  "outputs": {
    "enquiryRateFormatted": "4.52%",
    "enquiryYearEndMinusOneDisplay": "30/06/2021",
    "amalgamatedLoanNotPaidByEOIYFormatted": "$8,637.00",
    "openingBalancePayDays": "365",
    "openingBalanceInterestFormatted": "$390.39",
    "totalAmountOfRepaymentFormatted": "$0",
    "totalInterestFormatted": "$390.39",
    "principalFormatted": "$0",
    "enquiryYearEndDisplay": "30/06/2022",
    "minimumYearRepaymentFormatted": "$9,027.00",
    "loanAmountFormatted": "$8,637.00"
  },
  "repayments": [],
  "inputs": {
    "incomeYearOfLoan": 2018,
    "fullTermOfAmalgamatedLoan": 4,
    "incomeYearOfEnquiring": 2022,
    "amalgamatedLoanNotPaidByEOIY": 8637,
    "repayments": null,
    "lodgement_date": null
  },
  "idx": 1354
}