{
  "id": "2023-10-31T19:58:29.483Z0.8070606569025075",
  "alert": "Start of result\nResult\n\nAmalgamated loan fully repaid.\n\nThe amalgamated loan has been paid in full.\u000bThe private company is not taken under Division 7A to pay a dividend to the shareholder or shareholder's associate.\n\nInterest received by the private company must be included in the income tax return for 2002-03.\n\nMinimum yearly repayment\n\n-$2,581.00\n\nBenchmark interest rate\n\n6.3%\n\nOpening balance:\n\nDate: 30/06/2002\n\nBalance: $2,932.00\n\nDays: 13\n\nInterest: $6.58\n\nPayments\n\nDate: 14/07/2002\n\nAmount: $410.00\n\nBalance: $2,522.00\n\nDays: 350\n\nInterest: $152.36\n\n\n\n\nDate: 29/06/2003\n\nAmount: $9,384.00\n\nBalance: $0\n\nDays: 2\n\nInterest: $0\n\n\n\n\nTotal repayments\n\n$9,794.00\n\nTotal interest\n\n$158.94\n\nTotal principal\n\n$9,635.06\n\nClosing balance\n\nDate: 30/06/2003\n\nBalance: $0",
  "outputs": {
    "enquiryRateFormatted": "6.3%",
    "enquiryYearEndMinusOneDisplay": "30/06/2002",
    "amalgamatedLoanNotPaidByEOIYFormatted": "$2,932.00",
    "openingBalancePayDays": "13",
    "openingBalanceInterestFormatted": "$6.58",
    "totalAmountOfRepaymentFormatted": "$9,794.00",
    "totalInterestFormatted": "$158.94",
    "principalFormatted": "$9,635.06",
    "enquiryYearEndDisplay": "30/06/2003",
    "minimumYearRepaymentFormatted": "-$2,581.00",
    "loanAmountFormatted": "$0"
  },
  "repayments": [
    {
      "rd": "14/7/2002",
      "ra": 410
    },
    {
      "rd": "29/6/2003",
      "ra": 9384
    }
  ],
  "inputs": {
    "incomeYearOfLoan": 2002,
    "fullTermOfAmalgamatedLoan": 3,
    "incomeYearOfEnquiring": 2003,
    "amalgamatedLoanNotPaidByEOIY": 2932,
    "repayments": null,
    "lodgement_date": "30/6/2003"
  },
  "idx": 6048
}