{
  "id": "2023-09-04T16:45:34.674Z0.6107711463471046",
  "alert": "Start of result\nResult\n\nMinimum yearly repayment met.\n\nThe amount of the loan not repaid at the end of income year 2018-19 is $4,591.98.\n\nThe amalgamated loan will not be taken to be a dividend because the total repayments made are equal to or greater than the minimum yearly repayment required for income year 2018-19.\n\nInterest received by the private company must be included in the income tax return for 2018-19.\n\nMinimum yearly repayment\n\n$1,769.00\n\nBenchmark interest rate\n\n5.2%\n\nOpening balance:\n\nDate: 30/06/2018\n\nBalance: $6,242.00\n\nDays: 0\n\nInterest: $0\n\nPayments\n\nDate: 01/07/2018\n\nAmount: $1,877.00\n\nBalance: $4,365.00\n\nDays: 365\n\nInterest: $226.98\n\n\n\n\nTotal repayments\n\n$1,877.00\n\nTotal interest\n\n$226.98\n\nTotal principal\n\n$1,650.02\n\nClosing balance\n\nDate: 30/06/2019\n\nBalance: $4,591.98",
  "outputs": {
    "enquiryRateFormatted": "5.2%",
    "enquiryYearEndMinusOneDisplay": "30/06/2018",
    "amalgamatedLoanNotPaidByEOIYFormatted": "$6,242.00",
    "openingBalancePayDays": "0",
    "openingBalanceInterestFormatted": "$0",
    "totalAmountOfRepaymentFormatted": "$1,877.00",
    "totalInterestFormatted": "$226.98",
    "principalFormatted": "$1,650.02",
    "enquiryYearEndDisplay": "30/06/2019",
    "minimumYearRepaymentFormatted": "$1,769.00"
  },
  "repayments": [
    {
      "rd": "1/7/2018",
      "ra": 1877
    }
  ],
  "inputs": {
    "incomeYearOfLoan": 2016,
    "fullTermOfAmalgamatedLoan": 6,
    "incomeYearOfEnquiring": 2019,
    "amalgamatedLoanNotPaidByEOIY": 6242,
    "repayments": null,
    "lodgement_date": null
  },
  "idx": 1126
}