{
  "id": "2023-09-05T19:09:26.293Z0.4923603235784495",
  "alert": "Start of result\nResult\n\nMinimum yearly repayment met.\n\nThe amount of the loan not repaid at the end of income year 2018-19 is $30.23.\n\nThe amalgamated loan will not be taken to be a dividend because the total repayments made are equal to or greater than the minimum yearly repayment required for income year 2018-19.\n\nInterest received by the private company must be included in the income tax return for 2018-19.\n\nMinimum yearly repayment\n\n$0\n\nBenchmark interest rate\n\n5.2%\n\nOpening balance:\n\nDate: 30/06/2018\n\nBalance: $780.00\n\nDays: 272\n\nInterest: $30.23\n\nPayments\n\nDate: 30/03/2019\n\nAmount: $780.00\n\nBalance: $0\n\nDays: 93\n\nInterest: $0\n\n\n\n\nTotal repayments\n\n$780.00\n\nTotal interest\n\n$30.23\n\nTotal principal\n\n$749.77\n\nClosing balance\n\nDate: 30/06/2019\n\nBalance: $30.23",
  "outputs": {
    "enquiryRateFormatted": "5.2%",
    "enquiryYearEndMinusOneDisplay": "30/06/2018",
    "amalgamatedLoanNotPaidByEOIYFormatted": "$780.00",
    "openingBalancePayDays": "272",
    "openingBalanceInterestFormatted": "$30.23",
    "totalAmountOfRepaymentFormatted": "$780.00",
    "totalInterestFormatted": "$30.23",
    "principalFormatted": "$749.77",
    "enquiryYearEndDisplay": "30/06/2019",
    "minimumYearRepaymentFormatted": "$0"
  },
  "repayments": [
    {
      "rd": "30/3/2019",
      "ra": 780
    }
  ],
  "inputs": {
    "incomeYearOfLoan": 2018,
    "fullTermOfAmalgamatedLoan": 7,
    "incomeYearOfEnquiring": 2019,
    "amalgamatedLoanNotPaidByEOIY": 780,
    "repayments": null,
    "lodgement_date": "15/6/2019"
  },
  "idx": 1457
}