{
  "id": "2023-10-31T20:20:05.679Z0.9136479106463249",
  "alert": "Start of result\nResult\n\nAmalgamated loan fully repaid.\n\nThe amalgamated loan has been paid in full.\u000bThe private company is not taken under Division 7A to pay a dividend to the shareholder or shareholder's associate.\n\nInterest received by the private company must be included in the income tax return for 2002-03.\n\nMinimum yearly repayment\n\n$27.00\n\nBenchmark interest rate\n\n6.3%\n\nOpening balance:\n\nDate: 30/06/2002\n\nBalance: $112.14\n\nDays: 153\n\nInterest: $2.96\n\nPayments\n\nDate: 01/12/2002\n\nAmount: $1,121.41\n\nBalance: $0\n\nDays: 212\n\nInterest: $0\n\n\n\n\nTotal repayments\n\n$1,121.41\n\nTotal interest\n\n$2.96\n\nTotal principal\n\n$1,118.45\n\nClosing balance\n\nDate: 30/06/2003\n\nBalance: $0",
  "outputs": {
    "enquiryRateFormatted": "6.3%",
    "enquiryYearEndMinusOneDisplay": "30/06/2002",
    "amalgamatedLoanNotPaidByEOIYFormatted": "$112.14",
    "openingBalancePayDays": "153",
    "openingBalanceInterestFormatted": "$2.96",
    "totalAmountOfRepaymentFormatted": "$1,121.41",
    "totalInterestFormatted": "$2.96",
    "principalFormatted": "$1,118.45",
    "enquiryYearEndDisplay": "30/06/2003",
    "minimumYearRepaymentFormatted": "$27.00",
    "loanAmountFormatted": "$0"
  },
  "repayments": [
    {
      "rd": "1/12/2002",
      "ra": 1121.4148548865596
    }
  ],
  "inputs": {
    "incomeYearOfLoan": 2001,
    "fullTermOfAmalgamatedLoan": 6,
    "incomeYearOfEnquiring": 2003,
    "amalgamatedLoanNotPaidByEOIY": 112.14148548865596,
    "repayments": null,
    "lodgement_date": null
  },
  "idx": 6379
}