{
  "id": "2023-09-04T21:50:23.661Z0.2305878977506448",
  "alert": "Start of result\nResult\n\nMinimum yearly repayment met.\n\nThe amount of the loan not repaid at the end of income year 2005-06 is $3,264.07.\n\nThe amalgamated loan will not be taken to be a dividend because the total repayments made are equal to or greater than the minimum yearly repayment required for income year 2005-06.\n\nInterest received by the private company must be included in the income tax return for 2005-06.\n\nMinimum yearly repayment\n\n$904.00\n\nBenchmark interest rate\n\n7.3%\n\nOpening balance:\n\nDate: 30/06/2005\n\nBalance: $5,208.00\n\nDays: 0\n\nInterest: $0\n\nPayments\n\nDate: 01/07/2005\n\nAmount: $2,166.00\n\nBalance: $3,042.00\n\nDays: 365\n\nInterest: $222.07\n\n\n\n\nTotal repayments\n\n$2,166.00\n\nTotal interest\n\n$222.07\n\nTotal principal\n\n$1,943.93\n\nClosing balance\n\nDate: 30/06/2006\n\nBalance: $3,264.07",
  "outputs": {
    "enquiryRateFormatted": "7.3%",
    "enquiryYearEndMinusOneDisplay": "30/06/2005",
    "amalgamatedLoanNotPaidByEOIYFormatted": "$5,208.00",
    "openingBalancePayDays": "0",
    "openingBalanceInterestFormatted": "$0",
    "totalAmountOfRepaymentFormatted": "$2,166.00",
    "totalInterestFormatted": "$222.07",
    "principalFormatted": "$1,943.93",
    "enquiryYearEndDisplay": "30/06/2006",
    "minimumYearRepaymentFormatted": "$904.00"
  },
  "repayments": [
    {
      "rd": "1/7/2005",
      "ra": 2166
    }
  ],
  "inputs": {
    "incomeYearOfLoan": 2005,
    "fullTermOfAmalgamatedLoan": 4,
    "incomeYearOfEnquiring": 2006,
    "amalgamatedLoanNotPaidByEOIY": 5208,
    "repayments": null,
    "lodgement_date": "30/6/2006"
  },
  "idx": 1712
}