{
  "id": "2023-09-06T22:30:27.607Z0.7687491410412091",
  "alert": "Start of result\nResult\n\nMinimum yearly repayment not met.\n\nThe amount of the loan not repaid at the end of income year 2002-03 is $11,982.00.\n\nThe private company may be taken to pay a dividend under Division 7A to the shareholder or shareholder's associate because the amount repaid during income year 2002-03 in relation to the amalgamated loan is less than the minimum yearly repayment required.\n\nInterest received by the private company must be included in the income tax return for 2002-03.\n\nMinimum yearly repayment\n\n$6,563.00\n\nBenchmark interest rate\n\n6.3%\n\nOpening balance:\n\nDate: 30/06/2002\n\nBalance: $11,982.00\n\nDays: 179\n\nInterest: $370.19\n\nPayments\n\nDate: 27/12/2002\n\nAmount: $48.00\n\nBalance: $11,934.00\n\nDays: 186\n\nInterest: $383.13\n\n\n\n\nTotal repayments\n\n$48.00\n\nTotal interest\n\n$753.32\n\nTotal principal\n\n$0\n\nClosing balance\n\nDate: 30/06/2003\n\nBalance: $11,982.00",
  "outputs": {
    "enquiryRateFormatted": "6.3%",
    "enquiryYearEndMinusOneDisplay": "30/06/2002",
    "amalgamatedLoanNotPaidByEOIYFormatted": "$11,982.00",
    "openingBalancePayDays": "179",
    "openingBalanceInterestFormatted": "$370.19",
    "totalAmountOfRepaymentFormatted": "$48.00",
    "totalInterestFormatted": "$753.32",
    "principalFormatted": "$0",
    "enquiryYearEndDisplay": "30/06/2003",
    "minimumYearRepaymentFormatted": "$6,563.00"
  },
  "repayments": [
    {
      "rd": "27/12/2002",
      "ra": 48
    }
  ],
  "inputs": {
    "incomeYearOfLoan": 2001,
    "fullTermOfAmalgamatedLoan": 3,
    "incomeYearOfEnquiring": 2003,
    "amalgamatedLoanNotPaidByEOIY": 11982,
    "repayments": null,
    "lodgement_date": null
  },
  "idx": 8868
}