{
  "id": "2023-09-04T22:25:15.203Z0.659545142647735",
  "alert": "Start of result\nResult\n\nMinimum yearly repayment not met.\n\nThe amount of the loan not repaid at the end of income year 2000-01 is $80,010,623.86.\n\nThe private company may be taken to pay a dividend under Division 7A to the shareholder or shareholder's associate because the amount repaid during income year 2000-01 in relation to the amalgamated loan is less than the minimum yearly repayment required.\n\nInterest received by the private company must be included in the income tax return for 2000-01.\n\nMinimum yearly repayment\n\n$19,931,822.00\n\nBenchmark interest rate\n\n7.8%\n\nOpening balance:\n\nDate: 30/06/2000\n\nBalance: $80,010,623.86\n\nDays: 0\n\nInterest: $0\n\nPayments\n\nDate: 01/07/2000\n\nAmount: $7,370.00\n\nBalance: $80,003,253.86\n\nDays: 365\n\nInterest: $6,240,253.80\n\n\n\n\nTotal repayments\n\n$7,370.00\n\nTotal interest\n\n$6,240,253.80\n\nTotal principal\n\n$0\n\nClosing balance\n\nDate: 30/06/2001\n\nBalance: $80,010,623.86",
  "outputs": {
    "enquiryRateFormatted": "7.8%",
    "enquiryYearEndMinusOneDisplay": "30/06/2000",
    "amalgamatedLoanNotPaidByEOIYFormatted": "$80,010,623.86",
    "openingBalancePayDays": "0",
    "openingBalanceInterestFormatted": "$0",
    "totalAmountOfRepaymentFormatted": "$7,370.00",
    "totalInterestFormatted": "$6,240,253.80",
    "principalFormatted": "$0",
    "enquiryYearEndDisplay": "30/06/2001",
    "minimumYearRepaymentFormatted": "$19,931,822.00"
  },
  "repayments": [
    {
      "rd": "1/7/2000",
      "ra": 7370
    }
  ],
  "inputs": {
    "incomeYearOfLoan": 2000,
    "fullTermOfAmalgamatedLoan": 5,
    "incomeYearOfEnquiring": 2001,
    "amalgamatedLoanNotPaidByEOIY": 80010623.86337084,
    "repayments": null,
    "lodgement_date": "27/4/2001"
  },
  "idx": 901
}