{
  "id": "2023-09-04T22:09:42.315Z0.14558992377146374",
  "alert": "Start of result\nResult\n\nMinimum yearly repayment not met.\n\nThe amount of the loan not repaid at the end of income year 2004-05 is $72,010,289.11.\n\nThe private company may be taken to pay a dividend under Division 7A to the shareholder or shareholder's associate because the amount repaid during income year 2004-05 in relation to the amalgamated loan is less than the minimum yearly repayment required.\n\nInterest received by the private company must be included in the income tax return for 2004-05.\n\nMinimum yearly repayment\n\n$77,087,014.00\n\nBenchmark interest rate\n\n7.05%\n\nOpening balance:\n\nDate: 30/06/2004\n\nBalance: $72,010,289.11\n\nDays: 365\n\nInterest: $5,076,725.38\n\nTotal repayments\n\n$0\n\nTotal interest\n\n$5,076,725.38\n\nTotal principal\n\n$0\n\nClosing balance\n\nDate: 30/06/2005\n\nBalance: $72,010,289.11",
  "outputs": {
    "enquiryRateFormatted": "7.05%",
    "enquiryYearEndMinusOneDisplay": "30/06/2004",
    "amalgamatedLoanNotPaidByEOIYFormatted": "$72,010,289.11",
    "openingBalancePayDays": "365",
    "openingBalanceInterestFormatted": "$5,076,725.38",
    "totalAmountOfRepaymentFormatted": "$0",
    "totalInterestFormatted": "$5,076,725.38",
    "principalFormatted": "$0",
    "enquiryYearEndDisplay": "30/06/2005",
    "minimumYearRepaymentFormatted": "$77,087,014.00"
  },
  "repayments": [],
  "inputs": {
    "incomeYearOfLoan": 2002,
    "fullTermOfAmalgamatedLoan": 3,
    "incomeYearOfEnquiring": 2005,
    "amalgamatedLoanNotPaidByEOIY": 72010289.1191439,
    "repayments": null,
    "lodgement_date": null
  },
  "idx": 353
}