{
  "id": "2023-10-31T17:37:29.246Z0.4148789759781123",
  "alert": "Start of result\nResult\n\nAmalgamated loan fully repaid.\n\nThe amalgamated loan has been paid in full.\u000bThe private company is not taken under Division 7A to pay a dividend to the shareholder or shareholder's associate.\n\nInterest received by the private company must be included in the income tax return for 2016-17.\n\nMinimum yearly repayment\n\n-$776.00\n\nBenchmark interest rate\n\n5.4%\n\nOpening balance:\n\nDate: 30/06/2016\n\nBalance: $4,831.00\n\nDays: 79\n\nInterest: $56.46\n\nPayments\n\nDate: 18/09/2016\n\nAmount: $8,391.00\n\nBalance: $0\n\nDays: 24\n\nInterest: $0\n\n\n\n\nDate: 12/10/2016\n\nAmount: $867.00\n\nBalance: $0\n\nDays: 262\n\nInterest: $0\n\n\n\n\nTotal repayments\n\n$9,258.00\n\nTotal interest\n\n$56.46\n\nTotal principal\n\n$9,201.54\n\nClosing balance\n\nDate: 30/06/2017\n\nBalance: $0",
  "outputs": {
    "enquiryRateFormatted": "5.4%",
    "enquiryYearEndMinusOneDisplay": "30/06/2016",
    "amalgamatedLoanNotPaidByEOIYFormatted": "$4,831.00",
    "openingBalancePayDays": "79",
    "openingBalanceInterestFormatted": "$56.46",
    "totalAmountOfRepaymentFormatted": "$9,258.00",
    "totalInterestFormatted": "$56.46",
    "principalFormatted": "$9,201.54",
    "enquiryYearEndDisplay": "30/06/2017",
    "minimumYearRepaymentFormatted": "-$776.00",
    "loanAmountFormatted": "$0"
  },
  "repayments": [
    {
      "rd": "18/9/2016",
      "ra": 8391
    },
    {
      "rd": "12/10/2016",
      "ra": 867
    }
  ],
  "inputs": {
    "incomeYearOfLoan": 2016,
    "fullTermOfAmalgamatedLoan": 7,
    "incomeYearOfEnquiring": 2017,
    "amalgamatedLoanNotPaidByEOIY": 4831,
    "repayments": null,
    "lodgement_date": "27/1/2017"
  },
  "idx": 2099
}