{
  "id": "2023-09-06T18:00:11.783Z0.9181661384194832",
  "alert": "Start of result\nResult\n\nMinimum yearly repayment met.\n\nThe amount of the loan not repaid at the end of income year 2004-05 is $148.81.\n\nThe amalgamated loan will not be taken to be a dividend because the total repayments made are equal to or greater than the minimum yearly repayment required for income year 2004-05.\n\nInterest received by the private company must be included in the income tax return for 2004-05.\n\nMinimum yearly repayment\n\n$2,099.00\n\nBenchmark interest rate\n\n7.05%\n\nOpening balance:\n\nDate: 30/06/2004\n\nBalance: $5,503.00\n\nDays: 140\n\nInterest: $148.81\n\nPayments\n\nDate: 18/11/2004\n\nAmount: $5,503.00\n\nBalance: $0\n\nDays: 225\n\nInterest: $0\n\n\n\n\nTotal repayments\n\n$5,503.00\n\nTotal interest\n\n$148.81\n\nTotal principal\n\n$5,354.19\n\nClosing balance\n\nDate: 30/06/2005\n\nBalance: $148.81",
  "outputs": {
    "enquiryRateFormatted": "7.05%",
    "enquiryYearEndMinusOneDisplay": "30/06/2004",
    "amalgamatedLoanNotPaidByEOIYFormatted": "$5,503.00",
    "openingBalancePayDays": "140",
    "openingBalanceInterestFormatted": "$148.81",
    "totalAmountOfRepaymentFormatted": "$5,503.00",
    "totalInterestFormatted": "$148.81",
    "principalFormatted": "$5,354.19",
    "enquiryYearEndDisplay": "30/06/2005",
    "minimumYearRepaymentFormatted": "$2,099.00"
  },
  "repayments": [
    {
      "rd": "18/11/2004",
      "ra": 5503
    }
  ],
  "inputs": {
    "incomeYearOfLoan": 2004,
    "fullTermOfAmalgamatedLoan": 3,
    "incomeYearOfEnquiring": 2005,
    "amalgamatedLoanNotPaidByEOIY": 5503,
    "repayments": null,
    "lodgement_date": "15/10/2004"
  },
  "idx": 472
}