{
  "id": "2023-11-01T00:35:09.504Z0.38565135402909845",
  "alert": "Start of result\nResult\n\nAmalgamated loan fully repaid.\n\nThe amalgamated loan has been paid in full.\u000bThe private company is not taken under Division 7A to pay a dividend to the shareholder or shareholder's associate.\n\nInterest received by the private company must be included in the income tax return for 1999-00.\n\nMinimum yearly repayment\n\n$2.00\n\nBenchmark interest rate\n\n6.5%\n\nOpening balance:\n\nDate: 30/06/1999\n\nBalance: $8.08\n\nDays: 89\n\nInterest: $0.13\n\nPayments\n\nDate: 28/09/1999\n\nAmount: $80.85\n\nBalance: $0\n\nDays: 277\n\nInterest: $0\n\n\n\n\nTotal repayments\n\n$80.85\n\nTotal interest\n\n$0.13\n\nTotal principal\n\n$80.72\n\nClosing balance\n\nDate: 30/06/2000\n\nBalance: $0",
  "outputs": {
    "enquiryRateFormatted": "6.5%",
    "enquiryYearEndMinusOneDisplay": "30/06/1999",
    "amalgamatedLoanNotPaidByEOIYFormatted": "$8.08",
    "openingBalancePayDays": "89",
    "openingBalanceInterestFormatted": "$0.13",
    "totalAmountOfRepaymentFormatted": "$80.85",
    "totalInterestFormatted": "$0.13",
    "principalFormatted": "$80.72",
    "enquiryYearEndDisplay": "30/06/2000",
    "minimumYearRepaymentFormatted": "$2.00",
    "loanAmountFormatted": "$0"
  },
  "repayments": [
    {
      "rd": "28/9/1999",
      "ra": 80.8524189321779
    }
  ],
  "inputs": {
    "incomeYearOfLoan": 1998,
    "fullTermOfAmalgamatedLoan": 6,
    "incomeYearOfEnquiring": 2000,
    "amalgamatedLoanNotPaidByEOIY": 8.085241893217749,
    "repayments": null,
    "lodgement_date": null
  },
  "idx": 45
}