{
  "id": "2023-10-31T17:24:39.539Z0.8316624291353589",
  "alert": "Start of result\nResult\n\nMinimum yearly repayment not met.\n\nThe amount of the loan not repaid at the end of income year 2022-23 is $1,262.75.\n\nThe private company may be taken to pay a dividend under Division 7A to the shareholder or shareholder's associate because the amount repaid during income year 2022-23 in relation to the amalgamated loan is less than the minimum yearly repayment required.\n\nInterest received by the private company must be included in the income tax return for 2022-23.\n\nMinimum yearly repayment\n\n$5,765.00\n\nBenchmark interest rate\n\n4.77%\n\nOpening balance:\n\nDate: 30/06/2022\n\nBalance: $5,503.00\n\nDays: 197\n\nInterest: $141.67\n\nPayments\n\nDate: 14/01/2023\n\nAmount: $4,406.00\n\nBalance: $1,097.00\n\nDays: 168\n\nInterest: $24.08\n\n\n\n\nTotal repayments\n\n$4,406.00\n\nTotal interest\n\n$165.75\n\nTotal principal\n\n$4,240.25\n\nClosing balance\n\nDate: 30/06/2023\n\nBalance: $1,262.75",
  "outputs": {
    "enquiryRateFormatted": "4.77%",
    "enquiryYearEndMinusOneDisplay": "30/06/2022",
    "amalgamatedLoanNotPaidByEOIYFormatted": "$5,503.00",
    "openingBalancePayDays": "197",
    "openingBalanceInterestFormatted": "$141.67",
    "totalAmountOfRepaymentFormatted": "$4,406.00",
    "totalInterestFormatted": "$165.75",
    "principalFormatted": "$4,240.25",
    "enquiryYearEndDisplay": "30/06/2023",
    "minimumYearRepaymentFormatted": "$5,765.00",
    "loanAmountFormatted": "$1,262.75"
  },
  "repayments": [
    {
      "rd": "14/1/2023",
      "ra": 4406
    }
  ],
  "inputs": {
    "incomeYearOfLoan": 2018,
    "fullTermOfAmalgamatedLoan": 5,
    "incomeYearOfEnquiring": 2023,
    "amalgamatedLoanNotPaidByEOIY": 5503,
    "repayments": null,
    "lodgement_date": null
  },
  "idx": 1390
}