{
  "id": "2023-10-31T18:55:31.793Z0.23079133179648226",
  "alert": "Start of result\nResult\n\nAmalgamated loan fully repaid.\n\nThe amalgamated loan has been paid in full.\u000bThe private company is not taken under Division 7A to pay a dividend to the shareholder or shareholder's associate.\n\nInterest received by the private company must be included in the income tax return for 2012-13.\n\nMinimum yearly repayment\n\n$37.00\n\nBenchmark interest rate\n\n7.05%\n\nOpening balance:\n\nDate: 30/06/2012\n\nBalance: $66.24\n\nDays: 222\n\nInterest: $2.84\n\nPayments\n\nDate: 08/02/2013\n\nAmount: $662.49\n\nBalance: $0\n\nDays: 143\n\nInterest: $0\n\n\n\n\nTotal repayments\n\n$662.49\n\nTotal interest\n\n$2.84\n\nTotal principal\n\n$659.65\n\nClosing balance\n\nDate: 30/06/2013\n\nBalance: $0",
  "outputs": {
    "enquiryRateFormatted": "7.05%",
    "enquiryYearEndMinusOneDisplay": "30/06/2012",
    "amalgamatedLoanNotPaidByEOIYFormatted": "$66.24",
    "openingBalancePayDays": "222",
    "openingBalanceInterestFormatted": "$2.84",
    "totalAmountOfRepaymentFormatted": "$662.49",
    "totalInterestFormatted": "$2.84",
    "principalFormatted": "$659.65",
    "enquiryYearEndDisplay": "30/06/2013",
    "minimumYearRepaymentFormatted": "$37.00",
    "loanAmountFormatted": "$0"
  },
  "repayments": [
    {
      "rd": "8/2/2013",
      "ra": 662.4937192717016
    }
  ],
  "inputs": {
    "incomeYearOfLoan": 2007,
    "fullTermOfAmalgamatedLoan": 7,
    "incomeYearOfEnquiring": 2013,
    "amalgamatedLoanNotPaidByEOIY": 66.24937192717019,
    "repayments": null,
    "lodgement_date": null
  },
  "idx": 4757
}