{
  "id": "2023-09-04T21:32:25.281Z0.366536240731794",
  "alert": "Start of result\nResult\n\nMinimum yearly repayment not met.\n\nThe amount of the loan not repaid at the end of income year 2007-08 is $107,433,004.11.\n\nThe private company may be taken to pay a dividend under Division 7A to the shareholder or shareholder's associate because the amount repaid during income year 2007-08 in relation to the amalgamated loan is less than the minimum yearly repayment required.\n\nInterest received by the private company must be included in the income tax return for 2007-08.\n\nMinimum yearly repayment\n\n$116,081,361.00\n\nBenchmark interest rate\n\n8.05%\n\nOpening balance:\n\nDate: 30/06/2007\n\nBalance: $107,433,004.11\n\nDays: 366\n\nInterest: $8,648,356.83\n\nTotal repayments\n\n$0\n\nTotal interest\n\n$8,648,356.83\n\nTotal principal\n\n$0\n\nClosing balance\n\nDate: 30/06/2008\n\nBalance: $107,433,004.11",
  "outputs": {
    "enquiryRateFormatted": "8.05%",
    "enquiryYearEndMinusOneDisplay": "30/06/2007",
    "amalgamatedLoanNotPaidByEOIYFormatted": "$107,433,004.11",
    "openingBalancePayDays": "366",
    "openingBalanceInterestFormatted": "$8,648,356.83",
    "totalAmountOfRepaymentFormatted": "$0",
    "totalInterestFormatted": "$8,648,356.83",
    "principalFormatted": "$0",
    "enquiryYearEndDisplay": "30/06/2008",
    "minimumYearRepaymentFormatted": "$116,081,361.00"
  },
  "repayments": [],
  "inputs": {
    "incomeYearOfLoan": 2006,
    "fullTermOfAmalgamatedLoan": 2,
    "incomeYearOfEnquiring": 2008,
    "amalgamatedLoanNotPaidByEOIY": 107433004.11883341,
    "repayments": null,
    "lodgement_date": null
  },
  "idx": 1371
}