{
  "id": "2023-09-05T15:19:52.638Z0.7289126557573404",
  "alert": "Start of result\nResult\n\nMinimum yearly repayment not met.\n\nThe amount of the loan not repaid at the end of income year 2022-23 is $5,156.71.\n\nThe private company may be taken to pay a dividend under Division 7A to the shareholder or shareholder's associate because the amount repaid during income year 2022-23 in relation to the amalgamated loan is less than the minimum yearly repayment required.\n\nInterest received by the private company must be included in the income tax return for 2022-23.\n\nMinimum yearly repayment\n\n$2,348.00\n\nBenchmark interest rate\n\n4.77%\n\nOpening balance:\n\nDate: 30/06/2022\n\nBalance: $6,423.00\n\nDays: 131\n\nInterest: $109.96\n\nPayments\n\nDate: 09/11/2022\n\nAmount: $1,526.00\n\nBalance: $4,897.00\n\nDays: 234\n\nInterest: $149.75\n\n\n\n\nTotal repayments\n\n$1,526.00\n\nTotal interest\n\n$259.71\n\nTotal principal\n\n$1,266.29\n\nClosing balance\n\nDate: 30/06/2023\n\nBalance: $5,156.71",
  "outputs": {
    "enquiryRateFormatted": "4.77%",
    "enquiryYearEndMinusOneDisplay": "30/06/2022",
    "amalgamatedLoanNotPaidByEOIYFormatted": "$6,423.00",
    "openingBalancePayDays": "131",
    "openingBalanceInterestFormatted": "$109.96",
    "totalAmountOfRepaymentFormatted": "$1,526.00",
    "totalInterestFormatted": "$259.71",
    "principalFormatted": "$1,266.29",
    "enquiryYearEndDisplay": "30/06/2023",
    "minimumYearRepaymentFormatted": "$2,348.00"
  },
  "repayments": [
    {
      "rd": "9/11/2022",
      "ra": 1526
    }
  ],
  "inputs": {
    "incomeYearOfLoan": 2020,
    "fullTermOfAmalgamatedLoan": 5,
    "incomeYearOfEnquiring": 2023,
    "amalgamatedLoanNotPaidByEOIY": 6423,
    "repayments": null,
    "lodgement_date": null
  },
  "idx": 5883
}