{
  "id": "2023-10-31T17:29:25.559Z0.31001428999727365",
  "alert": "Start of result\nResult\n\nMinimum yearly repayment not met.\n\nThe amount of the loan not repaid at the end of income year 2017-18 is $12,284.00.\n\nThe private company may be taken to pay a dividend under Division 7A to the shareholder or shareholder's associate because the amount repaid during income year 2017-18 in relation to the amalgamated loan is less than the minimum yearly repayment required.\n\nInterest received by the private company must be included in the income tax return for 2017-18.\n\nMinimum yearly repayment\n\n$2,861.00\n\nBenchmark interest rate\n\n5.3%\n\nOpening balance:\n\nDate: 30/06/2017\n\nBalance: $12,284.00\n\nDays: 349\n\nInterest: $622.51\n\nPayments\n\nDate: 15/06/2018\n\nAmount: $47.00\n\nBalance: $12,237.00\n\nDays: 16\n\nInterest: $28.43\n\n\n\n\nTotal repayments\n\n$47.00\n\nTotal interest\n\n$650.94\n\nTotal principal\n\n$0\n\nClosing balance\n\nDate: 30/06/2018\n\nBalance: $12,284.00",
  "outputs": {
    "enquiryRateFormatted": "5.3%",
    "enquiryYearEndMinusOneDisplay": "30/06/2017",
    "amalgamatedLoanNotPaidByEOIYFormatted": "$12,284.00",
    "openingBalancePayDays": "349",
    "openingBalanceInterestFormatted": "$622.51",
    "totalAmountOfRepaymentFormatted": "$47.00",
    "totalInterestFormatted": "$650.94",
    "principalFormatted": "$0",
    "enquiryYearEndDisplay": "30/06/2018",
    "minimumYearRepaymentFormatted": "$2,861.00",
    "loanAmountFormatted": "$12,284.00"
  },
  "repayments": [
    {
      "rd": "15/6/2018",
      "ra": 47
    }
  ],
  "inputs": {
    "incomeYearOfLoan": 2017,
    "fullTermOfAmalgamatedLoan": 5,
    "incomeYearOfEnquiring": 2018,
    "amalgamatedLoanNotPaidByEOIY": 12284,
    "repayments": null,
    "lodgement_date": "29/10/2017"
  },
  "idx": 1663
}