{
  "id": "2023-09-05T22:20:55.635Z0.24873679202552124",
  "alert": "Start of result\nResult\n\nMinimum yearly repayment met.\n\nThe amount of the loan not repaid at the end of income year 2020-21 is $1.53.\n\nThe amalgamated loan will not be taken to be a dividend because the total repayments made are equal to or greater than the minimum yearly repayment required for income year 2020-21.\n\nInterest received by the private company must be included in the income tax return for 2020-21.\n\nMinimum yearly repayment\n\n$36.00\n\nBenchmark interest rate\n\n4.52%\n\nOpening balance:\n\nDate: 30/06/2020\n\nBalance: $66.93\n\nDays: 184\n\nInterest: $1.53\n\nPayments\n\nDate: 01/01/2021\n\nAmount: $66.93\n\nBalance: $0\n\nDays: 181\n\nInterest: $0\n\n\n\n\nTotal repayments\n\n$66.93\n\nTotal interest\n\n$1.53\n\nTotal principal\n\n$65.40\n\nClosing balance\n\nDate: 30/06/2021\n\nBalance: $1.53",
  "outputs": {
    "enquiryRateFormatted": "4.52%",
    "enquiryYearEndMinusOneDisplay": "30/06/2020",
    "amalgamatedLoanNotPaidByEOIYFormatted": "$66.93",
    "openingBalancePayDays": "184",
    "openingBalanceInterestFormatted": "$1.53",
    "totalAmountOfRepaymentFormatted": "$66.93",
    "totalInterestFormatted": "$1.53",
    "principalFormatted": "$65.40",
    "enquiryYearEndDisplay": "30/06/2021",
    "minimumYearRepaymentFormatted": "$36.00"
  },
  "repayments": [
    {
      "rd": "1/1/2021",
      "ra": 66.93686561013601
    }
  ],
  "inputs": {
    "incomeYearOfLoan": 2016,
    "fullTermOfAmalgamatedLoan": 6,
    "incomeYearOfEnquiring": 2021,
    "amalgamatedLoanNotPaidByEOIY": 66.93686561013583,
    "repayments": null,
    "lodgement_date": null
  },
  "idx": 4049
}