{
  "id": "2023-10-31T17:29:35.325Z0.24997157024314898",
  "alert": "Start of result\nResult\n\nMinimum yearly repayment not met.\n\nThe amount of the loan not repaid at the end of income year 2022-23 is $78.90.\n\nThe private company may be taken to pay a dividend under Division 7A to the shareholder or shareholder's associate because the amount repaid during income year 2022-23 in relation to the amalgamated loan is less than the minimum yearly repayment required.\n\nInterest received by the private company must be included in the income tax return for 2022-23.\n\nMinimum yearly repayment\n\n$83.00\n\nBenchmark interest rate\n\n4.77%\n\nOpening balance:\n\nDate: 30/06/2022\n\nBalance: $78.90\n\nDays: 365\n\nInterest: $3.76\n\nTotal repayments\n\n$0\n\nTotal interest\n\n$3.76\n\nTotal principal\n\n$0\n\nClosing balance\n\nDate: 30/06/2023\n\nBalance: $78.90",
  "outputs": {
    "enquiryRateFormatted": "4.77%",
    "enquiryYearEndMinusOneDisplay": "30/06/2022",
    "amalgamatedLoanNotPaidByEOIYFormatted": "$78.90",
    "openingBalancePayDays": "365",
    "openingBalanceInterestFormatted": "$3.76",
    "totalAmountOfRepaymentFormatted": "$0",
    "totalInterestFormatted": "$3.76",
    "principalFormatted": "$0",
    "enquiryYearEndDisplay": "30/06/2023",
    "minimumYearRepaymentFormatted": "$83.00",
    "loanAmountFormatted": "$78.90"
  },
  "repayments": [],
  "inputs": {
    "incomeYearOfLoan": 2017,
    "fullTermOfAmalgamatedLoan": 6,
    "incomeYearOfEnquiring": 2023,
    "amalgamatedLoanNotPaidByEOIY": 78.90009791133384,
    "repayments": null,
    "lodgement_date": null
  },
  "idx": 1673
}