{
  "id": "2023-09-04T22:03:12.779Z0.5996356502719826",
  "alert": "Start of result\nResult\n\nMinimum yearly repayment not met.\n\nThe amount of the loan not repaid at the end of income year 2008-09 is $77,051,294.28.\n\nThe private company may be taken to pay a dividend under Division 7A to the shareholder or shareholder's associate because the amount repaid during income year 2008-09 in relation to the amalgamated loan is less than the minimum yearly repayment required.\n\nInterest received by the private company must be included in the income tax return for 2008-09.\n\nMinimum yearly repayment\n\n$44,068,788.00\n\nBenchmark interest rate\n\n9.45%\n\nOpening balance:\n\nDate: 30/06/2008\n\nBalance: $77,051,294.28\n\nDays: 365\n\nInterest: $7,281,347.31\n\nTotal repayments\n\n$0\n\nTotal interest\n\n$7,281,347.31\n\nTotal principal\n\n$0\n\nClosing balance\n\nDate: 30/06/2009\n\nBalance: $77,051,294.28",
  "outputs": {
    "enquiryRateFormatted": "9.45%",
    "enquiryYearEndMinusOneDisplay": "30/06/2008",
    "amalgamatedLoanNotPaidByEOIYFormatted": "$77,051,294.28",
    "openingBalancePayDays": "365",
    "openingBalanceInterestFormatted": "$7,281,347.31",
    "totalAmountOfRepaymentFormatted": "$0",
    "totalInterestFormatted": "$7,281,347.31",
    "principalFormatted": "$0",
    "enquiryYearEndDisplay": "30/06/2009",
    "minimumYearRepaymentFormatted": "$44,068,788.00"
  },
  "repayments": [],
  "inputs": {
    "incomeYearOfLoan": 2004,
    "fullTermOfAmalgamatedLoan": 6,
    "incomeYearOfEnquiring": 2009,
    "amalgamatedLoanNotPaidByEOIY": 77051294.28320676,
    "repayments": null,
    "lodgement_date": null
  },
  "idx": 96
}