{
  "id": "2023-09-05T17:09:31.235Z0.6506966946749291",
  "alert": "Start of result\nResult\n\nMinimum yearly repayment met.\n\nThe amount of the loan not repaid at the end of income year 2020-21 is $39.24.\n\nThe amalgamated loan will not be taken to be a dividend because the total repayments made are equal to or greater than the minimum yearly repayment required for income year 2020-21.\n\nInterest received by the private company must be included in the income tax return for 2020-21.\n\nMinimum yearly repayment\n\n$589.00\n\nBenchmark interest rate\n\n4.52%\n\nOpening balance:\n\nDate: 30/06/2020\n\nBalance: $2,584.00\n\nDays: 27\n\nInterest: $8.64\n\nPayments\n\nDate: 28/07/2020\n\nAmount: $378.00\n\nBalance: $2,206.00\n\nDays: 112\n\nInterest: $30.60\n\n\n\n\nDate: 17/11/2020\n\nAmount: $2,206.00\n\nBalance: $0\n\nDays: 226\n\nInterest: $0\n\n\n\n\nTotal repayments\n\n$2,584.00\n\nTotal interest\n\n$39.24\n\nTotal principal\n\n$2,544.76\n\nClosing balance\n\nDate: 30/06/2021\n\nBalance: $39.24",
  "outputs": {
    "enquiryRateFormatted": "4.52%",
    "enquiryYearEndMinusOneDisplay": "30/06/2020",
    "amalgamatedLoanNotPaidByEOIYFormatted": "$2,584.00",
    "openingBalancePayDays": "27",
    "openingBalanceInterestFormatted": "$8.64",
    "totalAmountOfRepaymentFormatted": "$2,584.00",
    "totalInterestFormatted": "$39.24",
    "principalFormatted": "$2,544.76",
    "enquiryYearEndDisplay": "30/06/2021",
    "minimumYearRepaymentFormatted": "$589.00"
  },
  "repayments": [
    {
      "rd": "28/7/2020",
      "ra": 378
    },
    {
      "rd": "17/11/2020",
      "ra": 2206
    }
  ],
  "inputs": {
    "incomeYearOfLoan": 2019,
    "fullTermOfAmalgamatedLoan": 6,
    "incomeYearOfEnquiring": 2021,
    "amalgamatedLoanNotPaidByEOIY": 2584,
    "repayments": null,
    "lodgement_date": null
  },
  "idx": 3334
}