{
  "id": "2023-09-06T23:05:50.994Z0.35209905578543665",
  "alert": "Start of result\nResult\n\nMinimum yearly repayment met.\n\nThe amount of the loan not repaid at the end of income year 2005-06 is $4.57.\n\nThe amalgamated loan will not be taken to be a dividend because the total repayments made are equal to or greater than the minimum yearly repayment required for income year 2005-06.\n\nInterest received by the private company must be included in the income tax return for 2005-06.\n\nMinimum yearly repayment\n\n$59.00\n\nBenchmark interest rate\n\n7.3%\n\nOpening balance:\n\nDate: 30/06/2005\n\nBalance: $106.34\n\nDays: 215\n\nInterest: $4.57\n\nPayments\n\nDate: 01/02/2006\n\nAmount: $106.34\n\nBalance: $0\n\nDays: 150\n\nInterest: $0\n\n\n\n\nTotal repayments\n\n$106.34\n\nTotal interest\n\n$4.57\n\nTotal principal\n\n$101.77\n\nClosing balance\n\nDate: 30/06/2006\n\nBalance: $4.57",
  "outputs": {
    "enquiryRateFormatted": "7.3%",
    "enquiryYearEndMinusOneDisplay": "30/06/2005",
    "amalgamatedLoanNotPaidByEOIYFormatted": "$106.34",
    "openingBalancePayDays": "215",
    "openingBalanceInterestFormatted": "$4.57",
    "totalAmountOfRepaymentFormatted": "$106.34",
    "totalInterestFormatted": "$4.57",
    "principalFormatted": "$101.77",
    "enquiryYearEndDisplay": "30/06/2006",
    "minimumYearRepaymentFormatted": "$59.00"
  },
  "repayments": [
    {
      "rd": "1/2/2006",
      "ra": 106.34246824966613
    }
  ],
  "inputs": {
    "incomeYearOfLoan": 2001,
    "fullTermOfAmalgamatedLoan": 6,
    "incomeYearOfEnquiring": 2006,
    "amalgamatedLoanNotPaidByEOIY": 106.34246824966637,
    "repayments": null,
    "lodgement_date": null
  },
  "idx": 2214
}