{
  "id": "2023-10-31T19:24:05.841Z0.06555774736337427",
  "alert": "Start of result\nResult\n\nAmalgamated loan fully repaid.\n\nThe amalgamated loan has been paid in full.\u000bThe private company is not taken under Division 7A to pay a dividend to the shareholder or shareholder's associate.\n\nInterest received by the private company must be included in the income tax return for 2005-06.\n\nMinimum yearly repayment\n\n$53.00\n\nBenchmark interest rate\n\n7.3%\n\nOpening balance:\n\nDate: 30/06/2005\n\nBalance: $49.76\n\nDays: 25\n\nInterest: $0.25\n\nPayments\n\nDate: 26/07/2005\n\nAmount: $497.66\n\nBalance: $0\n\nDays: 340\n\nInterest: $0\n\n\n\n\nTotal repayments\n\n$497.66\n\nTotal interest\n\n$0.25\n\nTotal principal\n\n$497.41\n\nClosing balance\n\nDate: 30/06/2006\n\nBalance: $0",
  "outputs": {
    "enquiryRateFormatted": "7.3%",
    "enquiryYearEndMinusOneDisplay": "30/06/2005",
    "amalgamatedLoanNotPaidByEOIYFormatted": "$49.76",
    "openingBalancePayDays": "25",
    "openingBalanceInterestFormatted": "$0.25",
    "totalAmountOfRepaymentFormatted": "$497.66",
    "totalInterestFormatted": "$0.25",
    "principalFormatted": "$497.41",
    "enquiryYearEndDisplay": "30/06/2006",
    "minimumYearRepaymentFormatted": "$53.00",
    "loanAmountFormatted": "$0"
  },
  "repayments": [
    {
      "rd": "26/7/2005",
      "ra": 497.66625430612294
    }
  ],
  "inputs": {
    "incomeYearOfLoan": 2004,
    "fullTermOfAmalgamatedLoan": 2,
    "incomeYearOfEnquiring": 2006,
    "amalgamatedLoanNotPaidByEOIY": 49.766625430612294,
    "repayments": null,
    "lodgement_date": null
  },
  "idx": 5405
}