{
  "id": "2023-09-06T06:58:47.492Z0.9610709662501049",
  "alert": "Start of result\nResult\n\nMinimum yearly repayment not met.\n\nThe amount of the loan not repaid at the end of income year 2015-16 is $103.80.\n\nThe private company may be taken to pay a dividend under Division 7A to the shareholder or shareholder's associate because the amount repaid during income year 2015-16 in relation to the amalgamated loan is less than the minimum yearly repayment required.\n\nInterest received by the private company must be included in the income tax return for 2015-16.\n\nMinimum yearly repayment\n\n$38.00\n\nBenchmark interest rate\n\n5.45%\n\nOpening balance:\n\nDate: 30/06/2015\n\nBalance: $103.80\n\nDays: 366\n\nInterest: $5.66\n\nTotal repayments\n\n$0\n\nTotal interest\n\n$5.66\n\nTotal principal\n\n$0\n\nClosing balance\n\nDate: 30/06/2016\n\nBalance: $103.80",
  "outputs": {
    "enquiryRateFormatted": "5.45%",
    "enquiryYearEndMinusOneDisplay": "30/06/2015",
    "amalgamatedLoanNotPaidByEOIYFormatted": "$103.80",
    "openingBalancePayDays": "366",
    "openingBalanceInterestFormatted": "$5.66",
    "totalAmountOfRepaymentFormatted": "$0",
    "totalInterestFormatted": "$5.66",
    "principalFormatted": "$0",
    "enquiryYearEndDisplay": "30/06/2016",
    "minimumYearRepaymentFormatted": "$38.00"
  },
  "repayments": [],
  "inputs": {
    "incomeYearOfLoan": 2011,
    "fullTermOfAmalgamatedLoan": 7,
    "incomeYearOfEnquiring": 2016,
    "amalgamatedLoanNotPaidByEOIY": 103.80681981769425,
    "repayments": null,
    "lodgement_date": null
  },
  "idx": 7410
}