{
  "id": "2023-09-04T22:01:43.414Z0.02105154773790674",
  "alert": "Start of result\nResult\n\nMinimum yearly repayment not met.\n\nThe amount of the loan not repaid at the end of income year 2005-06 is $116,825,455.58.\n\nThe private company may be taken to pay a dividend under Division 7A to the shareholder or shareholder's associate because the amount repaid during income year 2005-06 in relation to the amalgamated loan is less than the minimum yearly repayment required.\n\nInterest received by the private company must be included in the income tax return for 2005-06.\n\nMinimum yearly repayment\n\n$64,884,001.00\n\nBenchmark interest rate\n\n7.3%\n\nOpening balance:\n\nDate: 30/06/2005\n\nBalance: $116,825,455.58\n\nDays: 365\n\nInterest: $8,528,258.26\n\nTotal repayments\n\n$0\n\nTotal interest\n\n$8,528,258.26\n\nTotal principal\n\n$0\n\nClosing balance\n\nDate: 30/06/2006\n\nBalance: $116,825,455.58",
  "outputs": {
    "enquiryRateFormatted": "7.3%",
    "enquiryYearEndMinusOneDisplay": "30/06/2005",
    "amalgamatedLoanNotPaidByEOIYFormatted": "$116,825,455.58",
    "openingBalancePayDays": "365",
    "openingBalanceInterestFormatted": "$8,528,258.26",
    "totalAmountOfRepaymentFormatted": "$0",
    "totalInterestFormatted": "$8,528,258.26",
    "principalFormatted": "$0",
    "enquiryYearEndDisplay": "30/06/2006",
    "minimumYearRepaymentFormatted": "$64,884,001.00"
  },
  "repayments": [],
  "inputs": {
    "incomeYearOfLoan": 2004,
    "fullTermOfAmalgamatedLoan": 3,
    "incomeYearOfEnquiring": 2006,
    "amalgamatedLoanNotPaidByEOIY": 116825455.5842459,
    "repayments": null,
    "lodgement_date": null
  },
  "idx": 31
}