{
  "id": "2023-09-06T10:28:16.118Z0.5290950555104685",
  "alert": "Start of result\nResult\n\nMinimum yearly repayment met.\n\nThe amount of the loan not repaid at the end of income year 2009-10 is $4,659.90.\n\nThe amalgamated loan will not be taken to be a dividend because the total repayments made are equal to or greater than the minimum yearly repayment required for income year 2009-10.\n\nInterest received by the private company must be included in the income tax return for 2009-10.\n\nMinimum yearly repayment\n\n$1,900.00\n\nBenchmark interest rate\n\n5.75%\n\nOpening balance:\n\nDate: 30/06/2009\n\nBalance: $9,415.00\n\nDays: 344\n\nInterest: $510.22\n\nPayments\n\nDate: 10/06/2010\n\nAmount: $5,279.00\n\nBalance: $4,136.00\n\nDays: 21\n\nInterest: $13.68\n\n\n\n\nTotal repayments\n\n$5,279.00\n\nTotal interest\n\n$523.90\n\nTotal principal\n\n$4,755.10\n\nClosing balance\n\nDate: 30/06/2010\n\nBalance: $4,659.90",
  "outputs": {
    "enquiryRateFormatted": "5.75%",
    "enquiryYearEndMinusOneDisplay": "30/06/2009",
    "amalgamatedLoanNotPaidByEOIYFormatted": "$9,415.00",
    "openingBalancePayDays": "344",
    "openingBalanceInterestFormatted": "$510.22",
    "totalAmountOfRepaymentFormatted": "$5,279.00",
    "totalInterestFormatted": "$523.90",
    "principalFormatted": "$4,755.10",
    "enquiryYearEndDisplay": "30/06/2010",
    "minimumYearRepaymentFormatted": "$1,900.00"
  },
  "repayments": [
    {
      "rd": "10/6/2010",
      "ra": 5279
    }
  ],
  "inputs": {
    "incomeYearOfLoan": 2009,
    "fullTermOfAmalgamatedLoan": 6,
    "incomeYearOfEnquiring": 2010,
    "amalgamatedLoanNotPaidByEOIY": 9415,
    "repayments": null,
    "lodgement_date": "18/10/2009"
  },
  "idx": 475
}