{
  "id": "2023-09-06T03:01:37.890Z0.3498552892758917",
  "alert": "Start of result\nResult\n\nMinimum yearly repayment met.\n\nThe amount of the loan not repaid at the end of income year 2014-15 is $0.54.\n\nThe amalgamated loan will not be taken to be a dividend because the total repayments made are equal to or greater than the minimum yearly repayment required for income year 2014-15.\n\nInterest received by the private company must be included in the income tax return for 2014-15.\n\nMinimum yearly repayment\n\n$3.00\n\nBenchmark interest rate\n\n5.95%\n\nOpening balance:\n\nDate: 30/06/2014\n\nBalance: $9.33\n\nDays: 352\n\nInterest: $0.54\n\nPayments\n\nDate: 18/06/2015\n\nAmount: $9.33\n\nBalance: $0\n\nDays: 13\n\nInterest: $0\n\n\n\n\nTotal repayments\n\n$9.33\n\nTotal interest\n\n$0.54\n\nTotal principal\n\n$8.79\n\nClosing balance\n\nDate: 30/06/2015\n\nBalance: $0.54",
  "outputs": {
    "enquiryRateFormatted": "5.95%",
    "enquiryYearEndMinusOneDisplay": "30/06/2014",
    "amalgamatedLoanNotPaidByEOIYFormatted": "$9.33",
    "openingBalancePayDays": "352",
    "openingBalanceInterestFormatted": "$0.54",
    "totalAmountOfRepaymentFormatted": "$9.33",
    "totalInterestFormatted": "$0.54",
    "principalFormatted": "$8.79",
    "enquiryYearEndDisplay": "30/06/2015",
    "minimumYearRepaymentFormatted": "$3.00"
  },
  "repayments": [
    {
      "rd": "18/6/2015",
      "ra": 9.33032378300959
    }
  ],
  "inputs": {
    "incomeYearOfLoan": 2013,
    "fullTermOfAmalgamatedLoan": 4,
    "incomeYearOfEnquiring": 2015,
    "amalgamatedLoanNotPaidByEOIY": 9.33032378300925,
    "repayments": null,
    "lodgement_date": null
  },
  "idx": 2573
}