{
  "id": "2023-09-06T22:54:55.075Z0.06616293261154049",
  "alert": "Start of result\nResult\n\nMinimum yearly repayment met.\n\nThe amount of the loan not repaid at the end of income year 2004-05 is $188.97.\n\nThe amalgamated loan will not be taken to be a dividend because the total repayments made are equal to or greater than the minimum yearly repayment required for income year 2004-05.\n\nInterest received by the private company must be included in the income tax return for 2004-05.\n\nMinimum yearly repayment\n\n$3,760.00\n\nBenchmark interest rate\n\n7.05%\n\nOpening balance:\n\nDate: 30/06/2004\n\nBalance: $6,794.00\n\nDays: 144\n\nInterest: $188.97\n\nPayments\n\nDate: 22/11/2004\n\nAmount: $6,794.00\n\nBalance: $0\n\nDays: 221\n\nInterest: $0\n\n\n\n\nTotal repayments\n\n$6,794.00\n\nTotal interest\n\n$188.97\n\nTotal principal\n\n$6,605.03\n\nClosing balance\n\nDate: 30/06/2005\n\nBalance: $188.97",
  "outputs": {
    "enquiryRateFormatted": "7.05%",
    "enquiryYearEndMinusOneDisplay": "30/06/2004",
    "amalgamatedLoanNotPaidByEOIYFormatted": "$6,794.00",
    "openingBalancePayDays": "144",
    "openingBalanceInterestFormatted": "$188.97",
    "totalAmountOfRepaymentFormatted": "$6,794.00",
    "totalInterestFormatted": "$188.97",
    "principalFormatted": "$6,605.03",
    "enquiryYearEndDisplay": "30/06/2005",
    "minimumYearRepaymentFormatted": "$3,760.00"
  },
  "repayments": [
    {
      "rd": "22/11/2004",
      "ra": 6794
    }
  ],
  "inputs": {
    "incomeYearOfLoan": 2001,
    "fullTermOfAmalgamatedLoan": 5,
    "incomeYearOfEnquiring": 2005,
    "amalgamatedLoanNotPaidByEOIY": 6794,
    "repayments": null,
    "lodgement_date": null
  },
  "idx": 1473
}