{
  "id": "2023-10-31T20:28:00.544Z0.13542104378728914",
  "alert": "Start of result\nResult\n\nMinimum yearly repayment not met.\n\nThe amount of the loan not repaid at the end of income year 2000-01 is $105.59.\n\nThe private company may be taken to pay a dividend under Division 7A to the shareholder or shareholder's associate because the amount repaid during income year 2000-01 in relation to the amalgamated loan is less than the minimum yearly repayment required.\n\nInterest received by the private company must be included in the income tax return for 2000-01.\n\nMinimum yearly repayment\n\n$59.00\n\nBenchmark interest rate\n\n7.8%\n\nOpening balance:\n\nDate: 30/06/2000\n\nBalance: $105.59\n\nDays: 365\n\nInterest: $8.24\n\nTotal repayments\n\n$0\n\nTotal interest\n\n$8.24\n\nTotal principal\n\n$0\n\nClosing balance\n\nDate: 30/06/2001\n\nBalance: $105.59",
  "outputs": {
    "enquiryRateFormatted": "7.8%",
    "enquiryYearEndMinusOneDisplay": "30/06/2000",
    "amalgamatedLoanNotPaidByEOIYFormatted": "$105.59",
    "openingBalancePayDays": "365",
    "openingBalanceInterestFormatted": "$8.24",
    "totalAmountOfRepaymentFormatted": "$0",
    "totalInterestFormatted": "$8.24",
    "principalFormatted": "$0",
    "enquiryYearEndDisplay": "30/06/2001",
    "minimumYearRepaymentFormatted": "$59.00",
    "loanAmountFormatted": "$105.59"
  },
  "repayments": [],
  "inputs": {
    "incomeYearOfLoan": 2000,
    "fullTermOfAmalgamatedLoan": 2,
    "incomeYearOfEnquiring": 2001,
    "amalgamatedLoanNotPaidByEOIY": 105.5943931906181,
    "repayments": null,
    "lodgement_date": "27/5/2001"
  },
  "idx": 6492
}