{
  "id": "2023-10-31T18:38:11.794Z0.7809791808805039",
  "alert": "Start of result\nResult\n\nMinimum yearly repayment not met.\n\nThe amount of the loan not repaid at the end of income year 2011-12 is $11,358.00.\n\nThe private company may be taken to pay a dividend under Division 7A to the shareholder or shareholder's associate because the amount repaid during income year 2011-12 in relation to the amalgamated loan is less than the minimum yearly repayment required.\n\nInterest received by the private company must be included in the income tax return for 2011-12.\n\nMinimum yearly repayment\n\n$12,244.00\n\nBenchmark interest rate\n\n7.8%\n\nOpening balance:\n\nDate: 30/06/2011\n\nBalance: $11,358.00\n\nDays: 277\n\nInterest: $670.49\n\nPayments\n\nDate: 03/04/2012\n\nAmount: $706.00\n\nBalance: $10,652.00\n\nDays: 89\n\nInterest: $202.04\n\n\n\n\nTotal repayments\n\n$706.00\n\nTotal interest\n\n$872.53\n\nTotal principal\n\n$0\n\nClosing balance\n\nDate: 30/06/2012\n\nBalance: $11,358.00",
  "outputs": {
    "enquiryRateFormatted": "7.8%",
    "enquiryYearEndMinusOneDisplay": "30/06/2011",
    "amalgamatedLoanNotPaidByEOIYFormatted": "$11,358.00",
    "openingBalancePayDays": "277",
    "openingBalanceInterestFormatted": "$670.49",
    "totalAmountOfRepaymentFormatted": "$706.00",
    "totalInterestFormatted": "$872.53",
    "principalFormatted": "$0",
    "enquiryYearEndDisplay": "30/06/2012",
    "minimumYearRepaymentFormatted": "$12,244.00",
    "loanAmountFormatted": "$11,358.00"
  },
  "repayments": [
    {
      "rd": "3/4/2012",
      "ra": 706
    }
  ],
  "inputs": {
    "incomeYearOfLoan": 2008,
    "fullTermOfAmalgamatedLoan": 4,
    "incomeYearOfEnquiring": 2012,
    "amalgamatedLoanNotPaidByEOIY": 11358,
    "repayments": null,
    "lodgement_date": null
  },
  "idx": 4306
}