{
  "id": "2023-09-06T15:10:36.697Z0.4589430176572571",
  "alert": "Start of result\nResult\n\nMinimum yearly repayment met.\n\nThe amount of the loan not repaid at the end of income year 2008-09 is $148.81.\n\nThe amalgamated loan will not be taken to be a dividend because the total repayments made are equal to or greater than the minimum yearly repayment required for income year 2008-09.\n\nInterest received by the private company must be included in the income tax return for 2008-09.\n\nMinimum yearly repayment\n\n$1,267.00\n\nBenchmark interest rate\n\n9.45%\n\nOpening balance:\n\nDate: 30/06/2008\n\nBalance: $4,871.00\n\nDays: 118\n\nInterest: $148.81\n\nPayments\n\nDate: 27/10/2008\n\nAmount: $4,871.00\n\nBalance: $0\n\nDays: 247\n\nInterest: $0\n\n\n\n\nTotal repayments\n\n$4,871.00\n\nTotal interest\n\n$148.81\n\nTotal principal\n\n$4,722.19\n\nClosing balance\n\nDate: 30/06/2009\n\nBalance: $148.81",
  "outputs": {
    "enquiryRateFormatted": "9.45%",
    "enquiryYearEndMinusOneDisplay": "30/06/2008",
    "amalgamatedLoanNotPaidByEOIYFormatted": "$4,871.00",
    "openingBalancePayDays": "118",
    "openingBalanceInterestFormatted": "$148.81",
    "totalAmountOfRepaymentFormatted": "$4,871.00",
    "totalInterestFormatted": "$148.81",
    "principalFormatted": "$4,722.19",
    "enquiryYearEndDisplay": "30/06/2009",
    "minimumYearRepaymentFormatted": "$1,267.00"
  },
  "repayments": [
    {
      "rd": "27/10/2008",
      "ra": 4871
    }
  ],
  "inputs": {
    "incomeYearOfLoan": 2006,
    "fullTermOfAmalgamatedLoan": 7,
    "incomeYearOfEnquiring": 2009,
    "amalgamatedLoanNotPaidByEOIY": 4871,
    "repayments": null,
    "lodgement_date": null
  },
  "idx": 7768
}