{
  "id": "2023-10-31T17:32:39.118Z0.4730243071603514",
  "alert": "Start of result\nResult\n\nMinimum yearly repayment not met.\n\nThe amount of the loan not repaid at the end of income year 2016-17 is $41.32.\n\nThe private company may be taken to pay a dividend under Division 7A to the shareholder or shareholder's associate because the amount repaid during income year 2016-17 in relation to the amalgamated loan is less than the minimum yearly repayment required.\n\nInterest received by the private company must be included in the income tax return for 2016-17.\n\nMinimum yearly repayment\n\n$44.00\n\nBenchmark interest rate\n\n5.4%\n\nOpening balance:\n\nDate: 30/06/2016\n\nBalance: $41.32\n\nDays: 365\n\nInterest: $2.23\n\nTotal repayments\n\n$0\n\nTotal interest\n\n$2.23\n\nTotal principal\n\n$0\n\nClosing balance\n\nDate: 30/06/2017\n\nBalance: $41.32",
  "outputs": {
    "enquiryRateFormatted": "5.4%",
    "enquiryYearEndMinusOneDisplay": "30/06/2016",
    "amalgamatedLoanNotPaidByEOIYFormatted": "$41.32",
    "openingBalancePayDays": "365",
    "openingBalanceInterestFormatted": "$2.23",
    "totalAmountOfRepaymentFormatted": "$0",
    "totalInterestFormatted": "$2.23",
    "principalFormatted": "$0",
    "enquiryYearEndDisplay": "30/06/2017",
    "minimumYearRepaymentFormatted": "$44.00",
    "loanAmountFormatted": "$41.32"
  },
  "repayments": [],
  "inputs": {
    "incomeYearOfLoan": 2016,
    "fullTermOfAmalgamatedLoan": 1,
    "incomeYearOfEnquiring": 2017,
    "amalgamatedLoanNotPaidByEOIY": 41.32823677233935,
    "repayments": null,
    "lodgement_date": "28/3/2017"
  },
  "idx": 1845
}