{
  "id": "2023-10-31T17:19:50.365Z0.22956901427087473",
  "alert": "Start of result\nResult\n\nAmalgamated loan fully repaid.\n\nThe amalgamated loan has been paid in full.\u000bThe private company is not taken under Division 7A to pay a dividend to the shareholder or shareholder's associate.\n\nInterest received by the private company must be included in the income tax return for 2019-20.\n\nMinimum yearly repayment\n\n$176.00\n\nBenchmark interest rate\n\n5.37%\n\nOpening balance:\n\nDate: 30/06/2019\n\nBalance: $476.00\n\nDays: 249\n\nInterest: $17.39\n\nPayments\n\nDate: 06/03/2020\n\nAmount: $4,760.00\n\nBalance: $0\n\nDays: 117\n\nInterest: $0\n\n\n\n\nTotal repayments\n\n$4,760.00\n\nTotal interest\n\n$17.39\n\nTotal principal\n\n$4,742.61\n\nClosing balance\n\nDate: 30/06/2020\n\nBalance: $0",
  "outputs": {
    "enquiryRateFormatted": "5.37%",
    "enquiryYearEndMinusOneDisplay": "30/06/2019",
    "amalgamatedLoanNotPaidByEOIYFormatted": "$476.00",
    "openingBalancePayDays": "249",
    "openingBalanceInterestFormatted": "$17.39",
    "totalAmountOfRepaymentFormatted": "$4,760.00",
    "totalInterestFormatted": "$17.39",
    "principalFormatted": "$4,742.61",
    "enquiryYearEndDisplay": "30/06/2020",
    "minimumYearRepaymentFormatted": "$176.00",
    "loanAmountFormatted": "$0"
  },
  "repayments": [
    {
      "rd": "6/3/2020",
      "ra": 4760
    }
  ],
  "inputs": {
    "incomeYearOfLoan": 2019,
    "fullTermOfAmalgamatedLoan": 3,
    "incomeYearOfEnquiring": 2020,
    "amalgamatedLoanNotPaidByEOIY": 476,
    "repayments": null,
    "lodgement_date": "30/8/2019"
  },
  "idx": 1082
}