{
  "id": "2023-09-04T16:34:13.232Z0.6530610184694658",
  "alert": "Start of result\nResult\n\nMinimum yearly repayment not met.\n\nThe amount of the loan not repaid at the end of income year 2018-19 is $27,832,809.52.\n\nThe private company may be taken to pay a dividend under Division 7A to the shareholder or shareholder's associate because the amount repaid during income year 2018-19 in relation to the amalgamated loan is less than the minimum yearly repayment required.\n\nInterest received by the private company must be included in the income tax return for 2018-19.\n\nMinimum yearly repayment\n\n$15,011,053.00\n\nBenchmark interest rate\n\n5.2%\n\nOpening balance:\n\nDate: 30/06/2018\n\nBalance: $27,832,809.52\n\nDays: 365\n\nInterest: $1,447,306.10\n\nTotal repayments\n\n$0\n\nTotal interest\n\n$1,447,306.10\n\nTotal principal\n\n$0\n\nClosing balance\n\nDate: 30/06/2019\n\nBalance: $27,832,809.52",
  "outputs": {
    "enquiryRateFormatted": "5.2%",
    "enquiryYearEndMinusOneDisplay": "30/06/2018",
    "amalgamatedLoanNotPaidByEOIYFormatted": "$27,832,809.52",
    "openingBalancePayDays": "365",
    "openingBalanceInterestFormatted": "$1,447,306.10",
    "totalAmountOfRepaymentFormatted": "$0",
    "totalInterestFormatted": "$1,447,306.10",
    "principalFormatted": "$0",
    "enquiryYearEndDisplay": "30/06/2019",
    "minimumYearRepaymentFormatted": "$15,011,053.00"
  },
  "repayments": [],
  "inputs": {
    "incomeYearOfLoan": 2017,
    "fullTermOfAmalgamatedLoan": 3,
    "incomeYearOfEnquiring": 2019,
    "amalgamatedLoanNotPaidByEOIY": 27832809.524075635,
    "repayments": null,
    "lodgement_date": null
  },
  "idx": 778
}