{
  "id": "2023-10-31T17:08:38.169Z0.8502404689303813",
  "alert": "Start of result\nResult\n\nMinimum yearly repayment not met.\n\nThe amount of the loan not repaid at the end of income year 2022-23 is $6,828.00.\n\nThe private company may be taken to pay a dividend under Division 7A to the shareholder or shareholder's associate because the amount repaid during income year 2022-23 in relation to the amalgamated loan is less than the minimum yearly repayment required.\n\nInterest received by the private company must be included in the income tax return for 2022-23.\n\nMinimum yearly repayment\n\n$7,154.00\n\nBenchmark interest rate\n\n4.77%\n\nOpening balance:\n\nDate: 30/06/2022\n\nBalance: $6,828.00\n\nDays: 365\n\nInterest: $325.70\n\nTotal repayments\n\n$0\n\nTotal interest\n\n$325.70\n\nTotal principal\n\n$0\n\nClosing balance\n\nDate: 30/06/2023\n\nBalance: $6,828.00",
  "outputs": {
    "enquiryRateFormatted": "4.77%",
    "enquiryYearEndMinusOneDisplay": "30/06/2022",
    "amalgamatedLoanNotPaidByEOIYFormatted": "$6,828.00",
    "openingBalancePayDays": "365",
    "openingBalanceInterestFormatted": "$325.70",
    "totalAmountOfRepaymentFormatted": "$0",
    "totalInterestFormatted": "$325.70",
    "principalFormatted": "$0",
    "enquiryYearEndDisplay": "30/06/2023",
    "minimumYearRepaymentFormatted": "$7,154.00",
    "loanAmountFormatted": "$6,828.00"
  },
  "repayments": [],
  "inputs": {
    "incomeYearOfLoan": 2022,
    "fullTermOfAmalgamatedLoan": 1,
    "incomeYearOfEnquiring": 2023,
    "amalgamatedLoanNotPaidByEOIY": 6828,
    "repayments": null,
    "lodgement_date": "26/2/2023"
  },
  "idx": 176
}