{
  "id": "2023-10-31T19:16:36.395Z0.8297609665062023",
  "alert": "Start of result\nResult\n\nMinimum yearly repayment met.\n\nThe amount of the loan not repaid at the end of income year 2007-08 is $549.62.\n\n\u000b\n\nThe amalgamated loan will not be taken to be a dividend because the total repayments made are equal to or greater than the minimum yearly repayment required for income year 2007-08.\n\nInterest received by the private company must be included in the income tax return for 2007-08.\n\nMinimum yearly repayment\n\n$2,841.00\n\nBenchmark interest rate\n\n8.05%\n\nOpening balance:\n\nDate: 30/06/2007\n\nBalance: $7,314.00\n\nDays: 66\n\nInterest: $106.17\n\nPayments\n\nDate: 05/09/2007\n\nAmount: $6,898.00\n\nBalance: $416.00\n\nDays: 300\n\nInterest: $27.45\n\n\n\n\nTotal repayments\n\n$6,898.00\n\nTotal interest\n\n$133.62\n\nTotal principal\n\n$6,764.38\n\nClosing balance\n\nDate: 30/06/2008\n\nBalance: $549.62",
  "outputs": {
    "enquiryRateFormatted": "8.05%",
    "enquiryYearEndMinusOneDisplay": "30/06/2007",
    "amalgamatedLoanNotPaidByEOIYFormatted": "$7,314.00",
    "openingBalancePayDays": "66",
    "openingBalanceInterestFormatted": "$106.17",
    "totalAmountOfRepaymentFormatted": "$6,898.00",
    "totalInterestFormatted": "$133.62",
    "principalFormatted": "$6,764.38",
    "enquiryYearEndDisplay": "30/06/2008",
    "minimumYearRepaymentFormatted": "$2,841.00",
    "loanAmountFormatted": "$549.62"
  },
  "repayments": [
    {
      "rd": "5/9/2007",
      "ra": 6898
    }
  ],
  "inputs": {
    "incomeYearOfLoan": 2005,
    "fullTermOfAmalgamatedLoan": 5,
    "incomeYearOfEnquiring": 2008,
    "amalgamatedLoanNotPaidByEOIY": 7314,
    "repayments": null,
    "lodgement_date": null
  },
  "idx": 5255
}