{
  "id": "2023-10-31T17:52:02.417Z0.6442514861463396",
  "alert": "Start of result\nResult\n\nAmalgamated loan fully repaid.\n\nThe amalgamated loan has been paid in full.\u000bThe private company is not taken under Division 7A to pay a dividend to the shareholder or shareholder's associate.\n\nInterest received by the private company must be included in the income tax return for 2017-18.\n\nMinimum yearly repayment\n\n$6.00\n\nBenchmark interest rate\n\n5.3%\n\nOpening balance:\n\nDate: 30/06/2017\n\nBalance: $20.27\n\nDays: 221\n\nInterest: $0.65\n\nPayments\n\nDate: 07/02/2018\n\nAmount: $202.73\n\nBalance: $0\n\nDays: 144\n\nInterest: $0\n\n\n\n\nTotal repayments\n\n$202.73\n\nTotal interest\n\n$0.65\n\nTotal principal\n\n$202.08\n\nClosing balance\n\nDate: 30/06/2018\n\nBalance: $0",
  "outputs": {
    "enquiryRateFormatted": "5.3%",
    "enquiryYearEndMinusOneDisplay": "30/06/2017",
    "amalgamatedLoanNotPaidByEOIYFormatted": "$20.27",
    "openingBalancePayDays": "221",
    "openingBalanceInterestFormatted": "$0.65",
    "totalAmountOfRepaymentFormatted": "$202.73",
    "totalInterestFormatted": "$0.65",
    "principalFormatted": "$202.08",
    "enquiryYearEndDisplay": "30/06/2018",
    "minimumYearRepaymentFormatted": "$6.00",
    "loanAmountFormatted": "$0"
  },
  "repayments": [
    {
      "rd": "7/2/2018",
      "ra": 202.73841514415471
    }
  ],
  "inputs": {
    "incomeYearOfLoan": 2014,
    "fullTermOfAmalgamatedLoan": 7,
    "incomeYearOfEnquiring": 2018,
    "amalgamatedLoanNotPaidByEOIY": 20.27384151441545,
    "repayments": null,
    "lodgement_date": null
  },
  "idx": 2772
}