{
  "id": "2023-10-31T16:28:25.574Z0.38634988298663986",
  "alert": "Start of result\nResult\n\nMinimum yearly repayment not met.\n\nThe amount of the loan not repaid at the end of income year 2023-24 is $2,879.03.\n\nThe private company may be taken to pay a dividend under Division 7A to the shareholder or shareholder's associate because the amount repaid during income year 2023-24 in relation to the amalgamated loan is less than the minimum yearly repayment required.\n\nInterest received by the private company must be included in the income tax return for 2023-24.\n\nMinimum yearly repayment\n\n$11,435.00\n\nBenchmark interest rate\n\n8.27%\n\nOpening balance:\n\nDate: 30/06/2023\n\nBalance: $10,562.00\n\nDays: 255\n\nInterest: $608.57\n\nPayments\n\nDate: 12/03/2024\n\nAmount: $364.00\n\nBalance: $10,198.00\n\nDays: 94\n\nInterest: $216.60\n\n\n\n\nDate: 14/06/2024\n\nAmount: $8,152.00\n\nBalance: $2,046.00\n\nDays: 17\n\nInterest: $7.86\n\n\n\n\nTotal repayments\n\n$8,516.00\n\nTotal interest\n\n$833.03\n\nTotal principal\n\n$7,682.97\n\nClosing balance\n\nDate: 30/06/2024\n\nBalance: $2,879.03",
  "outputs": {
    "enquiryRateFormatted": "8.27%",
    "enquiryYearEndMinusOneDisplay": "30/06/2023",
    "amalgamatedLoanNotPaidByEOIYFormatted": "$10,562.00",
    "openingBalancePayDays": "255",
    "openingBalanceInterestFormatted": "$608.57",
    "totalAmountOfRepaymentFormatted": "$8,516.00",
    "totalInterestFormatted": "$833.03",
    "principalFormatted": "$7,682.97",
    "enquiryYearEndDisplay": "30/06/2024",
    "minimumYearRepaymentFormatted": "$11,435.00",
    "loanAmountFormatted": "$2,879.03"
  },
  "repayments": [
    {
      "rd": "12/3/2024",
      "ra": 364
    },
    {
      "rd": "14/6/2024",
      "ra": 8152
    }
  ],
  "inputs": {
    "incomeYearOfLoan": 2023,
    "fullTermOfAmalgamatedLoan": 1,
    "incomeYearOfEnquiring": 2024,
    "amalgamatedLoanNotPaidByEOIY": 10562,
    "repayments": null,
    "lodgement_date": "12/10/2023"
  },
  "idx": 837
}