{
  "id": "2023-09-05T02:04:09.572Z0.5692049447086074",
  "alert": "Start of result\nResult\n\nMinimum yearly repayment met.\n\nThe amount of the loan not repaid at the end of income year 2002-03 is $2,249.31.\n\nThe amalgamated loan will not be taken to be a dividend because the total repayments made are equal to or greater than the minimum yearly repayment required for income year 2002-03.\n\nInterest received by the private company must be included in the income tax return for 2002-03.\n\nMinimum yearly repayment\n\n$4,436.00\n\nBenchmark interest rate\n\n6.3%\n\nOpening balance:\n\nDate: 30/06/2002\n\nBalance: $8,098.00\n\nDays: 0\n\nInterest: $0\n\nPayments\n\nDate: 01/07/2002\n\nAmount: $5,982.00\n\nBalance: $2,116.00\n\nDays: 365\n\nInterest: $133.31\n\n\n\n\nTotal repayments\n\n$5,982.00\n\nTotal interest\n\n$133.31\n\nTotal principal\n\n$5,848.69\n\nClosing balance\n\nDate: 30/06/2003\n\nBalance: $2,249.31",
  "outputs": {
    "enquiryRateFormatted": "6.3%",
    "enquiryYearEndMinusOneDisplay": "30/06/2002",
    "amalgamatedLoanNotPaidByEOIYFormatted": "$8,098.00",
    "openingBalancePayDays": "0",
    "openingBalanceInterestFormatted": "$0",
    "totalAmountOfRepaymentFormatted": "$5,982.00",
    "totalInterestFormatted": "$133.31",
    "principalFormatted": "$5,848.69",
    "enquiryYearEndDisplay": "30/06/2003",
    "minimumYearRepaymentFormatted": "$4,436.00"
  },
  "repayments": [
    {
      "rd": "1/7/2002",
      "ra": 5982
    }
  ],
  "inputs": {
    "incomeYearOfLoan": 1998,
    "fullTermOfAmalgamatedLoan": 6,
    "incomeYearOfEnquiring": 2003,
    "amalgamatedLoanNotPaidByEOIY": 8098,
    "repayments": null,
    "lodgement_date": null
  },
  "idx": 4421
}