{
  "id": "2023-09-06T12:49:33.637Z0.769554291780866",
  "alert": "Start of result\nResult\n\nMinimum yearly repayment met.\n\nThe amount of the loan not repaid at the end of income year 2007-08 is $1.55.\n\nThe amalgamated loan will not be taken to be a dividend because the total repayments made are equal to or greater than the minimum yearly repayment required for income year 2007-08.\n\nInterest received by the private company must be included in the income tax return for 2007-08.\n\nMinimum yearly repayment\n\n$11.00\n\nBenchmark interest rate\n\n8.05%\n\nOpening balance:\n\nDate: 30/06/2007\n\nBalance: $27.15\n\nDays: 259\n\nInterest: $1.55\n\nPayments\n\nDate: 16/03/2008\n\nAmount: $27.15\n\nBalance: $0\n\nDays: 107\n\nInterest: $0\n\n\n\n\nTotal repayments\n\n$27.15\n\nTotal interest\n\n$1.55\n\nTotal principal\n\n$25.60\n\nClosing balance\n\nDate: 30/06/2008\n\nBalance: $1.55",
  "outputs": {
    "enquiryRateFormatted": "8.05%",
    "enquiryYearEndMinusOneDisplay": "30/06/2007",
    "amalgamatedLoanNotPaidByEOIYFormatted": "$27.15",
    "openingBalancePayDays": "259",
    "openingBalanceInterestFormatted": "$1.55",
    "totalAmountOfRepaymentFormatted": "$27.15",
    "totalInterestFormatted": "$1.55",
    "principalFormatted": "$25.60",
    "enquiryYearEndDisplay": "30/06/2008",
    "minimumYearRepaymentFormatted": "$11.00"
  },
  "repayments": [
    {
      "rd": "16/3/2008",
      "ra": 27.156666097323523
    }
  ],
  "inputs": {
    "incomeYearOfLoan": 2007,
    "fullTermOfAmalgamatedLoan": 3,
    "incomeYearOfEnquiring": 2008,
    "amalgamatedLoanNotPaidByEOIY": 27.15666609732373,
    "repayments": null,
    "lodgement_date": "1/1/2008"
  },
  "idx": 8673
}