{
  "id": "2023-10-31T19:39:25.888Z0.2713057987599816",
  "alert": "Start of result\nResult\n\nMinimum yearly repayment not met.\n\nThe amount of the loan not repaid at the end of income year 2003-04 is $5,832.32.\n\nThe private company may be taken to pay a dividend under Division 7A to the shareholder or shareholder's associate because the amount repaid during income year 2003-04 in relation to the amalgamated loan is less than the minimum yearly repayment required.\n\nInterest received by the private company must be included in the income tax return for 2003-04.\n\nMinimum yearly repayment\n\n$3,014.00\n\nBenchmark interest rate\n\n6.55%\n\nOpening balance:\n\nDate: 30/06/2003\n\nBalance: $7,975.00\n\nDays: 224\n\nInterest: $319.70\n\nPayments\n\nDate: 10/02/2004\n\nAmount: $2,599.00\n\nBalance: $5,376.00\n\nDays: 142\n\nInterest: $136.62\n\n\n\n\nTotal repayments\n\n$2,599.00\n\nTotal interest\n\n$456.32\n\nTotal principal\n\n$2,142.68\n\nClosing balance\n\nDate: 30/06/2004\n\nBalance: $5,832.32",
  "outputs": {
    "enquiryRateFormatted": "6.55%",
    "enquiryYearEndMinusOneDisplay": "30/06/2003",
    "amalgamatedLoanNotPaidByEOIYFormatted": "$7,975.00",
    "openingBalancePayDays": "224",
    "openingBalanceInterestFormatted": "$319.70",
    "totalAmountOfRepaymentFormatted": "$2,599.00",
    "totalInterestFormatted": "$456.32",
    "principalFormatted": "$2,142.68",
    "enquiryYearEndDisplay": "30/06/2004",
    "minimumYearRepaymentFormatted": "$3,014.00",
    "loanAmountFormatted": "$5,832.32"
  },
  "repayments": [
    {
      "rd": "10/2/2004",
      "ra": 2599
    }
  ],
  "inputs": {
    "incomeYearOfLoan": 2003,
    "fullTermOfAmalgamatedLoan": 3,
    "incomeYearOfEnquiring": 2004,
    "amalgamatedLoanNotPaidByEOIY": 7975,
    "repayments": null,
    "lodgement_date": "28/11/2003"
  },
  "idx": 5710
}