{
  "incomeYearOfLoan": 2023,
  "fullTermOfAmalgamatedLoan": 8,
  "incomeYearOfEnquiring": 2024,
  "amalgamatedLoanNotPaidByEOIY": 82839043.40152363,
  "repayments": [
    {
      "rd": "1/7/2023",
      "ra": 604
    },
    {
      "rd": "30/3/2024",
      "ra": 4964
    },
    {
      "rd": "16/4/2024",
      "ra": 707
    }
  ],
  "lodgement_date_string": "1/7/2023",
  "id": "2023-09-03T22:01:39.149Z0.8050240623307393",
  "alert": "Start of result\nResult\n\nMinimum yearly repayment not met.\n\nThe amount of the loan not repaid at the end of income year 2023-24 is $82,839,043.40.\n\nThe private company may be taken to pay a dividend under Division 7A to the shareholder or shareholder's associate because the amount repaid during income year 2023-24 in relation to the amalgamated loan is less than the minimum yearly repayment required.\n\nInterest received by the private company must be included in the income tax return for 2023-24.\n\nMinimum yearly repayment\n\n$20,895,428.00\n\nBenchmark interest rate\n\n8.27%\n\nOpening balance:\n\nDate: 30/06/2023\n\nBalance: $82,839,043.40\n\nDays: 0\n\nInterest: $0\n\nPayments\n\nDate: 01/07/2023\n\nAmount: $604.00\n\nBalance: $82,838,439.40\n\nDays: 273\n\nInterest: $5,109,977.40\n\n\n\n\nDate: 30/03/2024\n\nAmount: $4,964.00\n\nBalance: $82,833,475.40\n\nDays: 17\n\nInterest: $318,184.65\n\n\n\n\nDate: 16/04/2024\n\nAmount: $707.00\n\nBalance: $82,832,768.40\n\nDays: 76\n\nInterest: $1,422,460.43\n\n\n\n\nTotal repayments\n\n$6,275.00\n\nTotal interest\n\n$6,850,622.48\n\nTotal principal\n\n$0\n\nClosing balance\n\nDate: 30/06/2024\n\nBalance: $82,839,043.40",
  "enquiryRateFormatted": "8.27%",
  "enquiryYearEndMinusOneDisplay": "30/06/2023",
  "amalgamatedLoanNotPaidByEOIYFormatted": "$82,839,043.40",
  "openingBalancePayDays": "0",
  "openingBalanceInterestFormatted": "$0",
  "totalAmountOfRepaymentFormatted": "$6,275.00",
  "totalInterestFormatted": "$6,850,622.48",
  "principalFormatted": "$0",
  "enquiryYearEndDisplay": "30/06/2024",
  "minimumYearRepaymentFormatted": "$20,895,428.00"
}