{
  "id": "2023-10-31T17:43:16.774Z0.19944503366988775",
  "alert": "Start of result\nResult\n\nAmalgamated loan fully repaid.\n\nThe amalgamated loan has been paid in full.\u000bThe private company is not taken under Division 7A to pay a dividend to the shareholder or shareholder's associate.\n\nInterest received by the private company must be included in the income tax return for 2018-19.\n\nMinimum yearly repayment\n\n$0\n\nBenchmark interest rate\n\n5.2%\n\nOpening balance:\n\nDate: 30/06/2018\n\nBalance: $1.36\n\nDays: 350\n\nInterest: $0.07\n\nPayments\n\nDate: 16/06/2019\n\nAmount: $13.60\n\nBalance: $0\n\nDays: 15\n\nInterest: $0\n\n\n\n\nTotal repayments\n\n$13.60\n\nTotal interest\n\n$0.07\n\nTotal principal\n\n$13.53\n\nClosing balance\n\nDate: 30/06/2019\n\nBalance: $0",
  "outputs": {
    "enquiryRateFormatted": "5.2%",
    "enquiryYearEndMinusOneDisplay": "30/06/2018",
    "amalgamatedLoanNotPaidByEOIYFormatted": "$1.36",
    "openingBalancePayDays": "350",
    "openingBalanceInterestFormatted": "$0.07",
    "totalAmountOfRepaymentFormatted": "$13.60",
    "totalInterestFormatted": "$0.07",
    "principalFormatted": "$13.53",
    "enquiryYearEndDisplay": "30/06/2019",
    "minimumYearRepaymentFormatted": "$0",
    "loanAmountFormatted": "$0"
  },
  "repayments": [
    {
      "rd": "16/6/2019",
      "ra": 13.607200446077513
    }
  ],
  "inputs": {
    "incomeYearOfLoan": 2015,
    "fullTermOfAmalgamatedLoan": 7,
    "incomeYearOfEnquiring": 2019,
    "amalgamatedLoanNotPaidByEOIY": 1.3607200446077523,
    "repayments": null,
    "lodgement_date": null
  },
  "idx": 2376
}