{
  "id": "2023-10-31T20:22:43.539Z0.668555840774665",
  "alert": "Start of result\nResult\n\nMinimum yearly repayment not met.\n\nThe amount of the loan not repaid at the end of income year 2003-04 is $1,189.28.\n\nThe private company may be taken to pay a dividend under Division 7A to the shareholder or shareholder's associate because the amount repaid during income year 2003-04 in relation to the amalgamated loan is less than the minimum yearly repayment required.\n\nInterest received by the private company must be included in the income tax return for 2003-04.\n\nMinimum yearly repayment\n\n$318.00\n\nBenchmark interest rate\n\n6.55%\n\nOpening balance:\n\nDate: 30/06/2003\n\nBalance: $1,320.00\n\nDays: 5\n\nInterest: $1.18\n\nPayments\n\nDate: 06/07/2003\n\nAmount: $204.00\n\nBalance: $1,116.00\n\nDays: 361\n\nInterest: $72.10\n\n\n\n\nTotal repayments\n\n$204.00\n\nTotal interest\n\n$73.28\n\nTotal principal\n\n$130.72\n\nClosing balance\n\nDate: 30/06/2004\n\nBalance: $1,189.28",
  "outputs": {
    "enquiryRateFormatted": "6.55%",
    "enquiryYearEndMinusOneDisplay": "30/06/2003",
    "amalgamatedLoanNotPaidByEOIYFormatted": "$1,320.00",
    "openingBalancePayDays": "5",
    "openingBalanceInterestFormatted": "$1.18",
    "totalAmountOfRepaymentFormatted": "$204.00",
    "totalInterestFormatted": "$73.28",
    "principalFormatted": "$130.72",
    "enquiryYearEndDisplay": "30/06/2004",
    "minimumYearRepaymentFormatted": "$318.00",
    "loanAmountFormatted": "$1,189.28"
  },
  "repayments": [
    {
      "rd": "6/7/2003",
      "ra": 204
    }
  ],
  "inputs": {
    "incomeYearOfLoan": 2001,
    "fullTermOfAmalgamatedLoan": 7,
    "incomeYearOfEnquiring": 2004,
    "amalgamatedLoanNotPaidByEOIY": 1320,
    "repayments": null,
    "lodgement_date": null
  },
  "idx": 6417
}