{
  "id": "2023-09-04T20:55:22.262Z0.1394959139544576",
  "alert": "Start of result\nResult\n\nMinimum yearly repayment not met.\n\nThe amount of the loan not repaid at the end of income year 2013-14 is $88,127,496.31.\n\nThe private company may be taken to pay a dividend under Division 7A to the shareholder or shareholder's associate because the amount repaid during income year 2013-14 in relation to the amalgamated loan is less than the minimum yearly repayment required.\n\nInterest received by the private company must be included in the income tax return for 2013-14.\n\nMinimum yearly repayment\n\n$93,591,401.00\n\nBenchmark interest rate\n\n6.2%\n\nOpening balance:\n\nDate: 30/06/2013\n\nBalance: $88,127,496.31\n\nDays: 365\n\nInterest: $5,463,904.77\n\nTotal repayments\n\n$0\n\nTotal interest\n\n$5,463,904.77\n\nTotal principal\n\n$0\n\nClosing balance\n\nDate: 30/06/2014\n\nBalance: $88,127,496.31",
  "outputs": {
    "enquiryRateFormatted": "6.2%",
    "enquiryYearEndMinusOneDisplay": "30/06/2013",
    "amalgamatedLoanNotPaidByEOIYFormatted": "$88,127,496.31",
    "openingBalancePayDays": "365",
    "openingBalanceInterestFormatted": "$5,463,904.77",
    "totalAmountOfRepaymentFormatted": "$0",
    "totalInterestFormatted": "$5,463,904.77",
    "principalFormatted": "$0",
    "enquiryYearEndDisplay": "30/06/2014",
    "minimumYearRepaymentFormatted": "$93,591,401.00"
  },
  "repayments": [],
  "inputs": {
    "incomeYearOfLoan": 2010,
    "fullTermOfAmalgamatedLoan": 4,
    "incomeYearOfEnquiring": 2014,
    "amalgamatedLoanNotPaidByEOIY": 88127496.31442595,
    "repayments": null,
    "lodgement_date": null
  },
  "idx": 309
}