{
  "id": "2023-09-05T22:51:45.434Z0.2462221159669229",
  "alert": "Start of result\nResult\n\nMinimum yearly repayment not met.\n\nThe amount of the loan not repaid at the end of income year 2015-16 is $110.85.\n\nThe private company may be taken to pay a dividend under Division 7A to the shareholder or shareholder's associate because the amount repaid during income year 2015-16 in relation to the amalgamated loan is less than the minimum yearly repayment required.\n\nInterest received by the private company must be included in the income tax return for 2015-16.\n\nMinimum yearly repayment\n\n$117.00\n\nBenchmark interest rate\n\n5.45%\n\nOpening balance:\n\nDate: 30/06/2015\n\nBalance: $110.85\n\nDays: 366\n\nInterest: $6.04\n\nTotal repayments\n\n$0\n\nTotal interest\n\n$6.04\n\nTotal principal\n\n$0\n\nClosing balance\n\nDate: 30/06/2016\n\nBalance: $110.85",
  "outputs": {
    "enquiryRateFormatted": "5.45%",
    "enquiryYearEndMinusOneDisplay": "30/06/2015",
    "amalgamatedLoanNotPaidByEOIYFormatted": "$110.85",
    "openingBalancePayDays": "366",
    "openingBalanceInterestFormatted": "$6.04",
    "totalAmountOfRepaymentFormatted": "$0",
    "totalInterestFormatted": "$6.04",
    "principalFormatted": "$0",
    "enquiryYearEndDisplay": "30/06/2016",
    "minimumYearRepaymentFormatted": "$117.00"
  },
  "repayments": [],
  "inputs": {
    "incomeYearOfLoan": 2015,
    "fullTermOfAmalgamatedLoan": 1,
    "incomeYearOfEnquiring": 2016,
    "amalgamatedLoanNotPaidByEOIY": 110.8590569185037,
    "repayments": null,
    "lodgement_date": "15/4/2016"
  },
  "idx": 5822
}