{
  "id": "2023-10-31T20:17:12.767Z0.3302452339605294",
  "alert": "Start of result\nResult\n\nAmalgamated loan fully repaid.\n\nThe amalgamated loan has been paid in full.\u000bThe private company is not taken under Division 7A to pay a dividend to the shareholder or shareholder's associate.\n\nInterest received by the private company must be included in the income tax return for 2003-04.\n\nMinimum yearly repayment\n\n$42.00\n\nBenchmark interest rate\n\n6.55%\n\nOpening balance:\n\nDate: 30/06/2003\n\nBalance: $110.76\n\nDays: 80\n\nInterest: $1.59\n\nPayments\n\nDate: 19/09/2003\n\nAmount: $1,107.61\n\nBalance: $0\n\nDays: 286\n\nInterest: $0\n\n\n\n\nTotal repayments\n\n$1,107.61\n\nTotal interest\n\n$1.59\n\nTotal principal\n\n$1,106.02\n\nClosing balance\n\nDate: 30/06/2004\n\nBalance: $0",
  "outputs": {
    "enquiryRateFormatted": "6.55%",
    "enquiryYearEndMinusOneDisplay": "30/06/2003",
    "amalgamatedLoanNotPaidByEOIYFormatted": "$110.76",
    "openingBalancePayDays": "80",
    "openingBalanceInterestFormatted": "$1.59",
    "totalAmountOfRepaymentFormatted": "$1,107.61",
    "totalInterestFormatted": "$1.59",
    "principalFormatted": "$1,106.02",
    "enquiryYearEndDisplay": "30/06/2004",
    "minimumYearRepaymentFormatted": "$42.00",
    "loanAmountFormatted": "$0"
  },
  "repayments": [
    {
      "rd": "19/9/2003",
      "ra": 1107.6160155211564
    }
  ],
  "inputs": {
    "incomeYearOfLoan": 2001,
    "fullTermOfAmalgamatedLoan": 5,
    "incomeYearOfEnquiring": 2004,
    "amalgamatedLoanNotPaidByEOIY": 110.7616015521157,
    "repayments": null,
    "lodgement_date": null
  },
  "idx": 6339
}