{
  "id": "2023-09-04T16:38:11.388Z0.7372072115339805",
  "alert": "Start of result\nResult\n\nMinimum yearly repayment not met.\n\nThe amount of the loan not repaid at the end of income year 2016-17 is $30,994,979.14.\n\nThe private company may be taken to pay a dividend under Division 7A to the shareholder or shareholder's associate because the amount repaid during income year 2016-17 in relation to the amalgamated loan is less than the minimum yearly repayment required.\n\nInterest received by the private company must be included in the income tax return for 2016-17.\n\nMinimum yearly repayment\n\n$32,660,329.00\n\nBenchmark interest rate\n\n5.4%\n\nOpening balance:\n\nDate: 30/06/2016\n\nBalance: $30,994,979.14\n\nDays: 0\n\nInterest: $0\n\nPayments\n\nDate: 01/07/2016\n\nAmount: $7,950.00\n\nBalance: $30,987,029.14\n\nDays: 365\n\nInterest: $1,673,299.57\n\n\n\n\nTotal repayments\n\n$7,950.00\n\nTotal interest\n\n$1,673,299.57\n\nTotal principal\n\n$0\n\nClosing balance\n\nDate: 30/06/2017\n\nBalance: $30,994,979.14",
  "outputs": {
    "enquiryRateFormatted": "5.4%",
    "enquiryYearEndMinusOneDisplay": "30/06/2016",
    "amalgamatedLoanNotPaidByEOIYFormatted": "$30,994,979.14",
    "openingBalancePayDays": "0",
    "openingBalanceInterestFormatted": "$0",
    "totalAmountOfRepaymentFormatted": "$7,950.00",
    "totalInterestFormatted": "$1,673,299.57",
    "principalFormatted": "$0",
    "enquiryYearEndDisplay": "30/06/2017",
    "minimumYearRepaymentFormatted": "$32,660,329.00"
  },
  "repayments": [
    {
      "rd": "1/7/2016",
      "ra": 7950
    }
  ],
  "inputs": {
    "incomeYearOfLoan": 2016,
    "fullTermOfAmalgamatedLoan": 1,
    "incomeYearOfEnquiring": 2017,
    "amalgamatedLoanNotPaidByEOIY": 30994979.14028745,
    "repayments": null,
    "lodgement_date": "17/1/2017"
  },
  "idx": 900
}