{
  "id": "2023-09-05T18:24:23.516Z0.8966311162420815",
  "alert": "Start of result\nResult\n\nMinimum yearly repayment met.\n\nThe amount of the loan not repaid at the end of income year 2018-19 is $2.65.\n\nThe amalgamated loan will not be taken to be a dividend because the total repayments made are equal to or greater than the minimum yearly repayment required for income year 2018-19.\n\nInterest received by the private company must be included in the income tax return for 2018-19.\n\nMinimum yearly repayment\n\n$18.00\n\nBenchmark interest rate\n\n5.2%\n\nOpening balance:\n\nDate: 30/06/2018\n\nBalance: $64.53\n\nDays: 288\n\nInterest: $2.65\n\nPayments\n\nDate: 15/04/2019\n\nAmount: $64.53\n\nBalance: $0\n\nDays: 77\n\nInterest: $0\n\n\n\n\nTotal repayments\n\n$64.53\n\nTotal interest\n\n$2.65\n\nTotal principal\n\n$61.88\n\nClosing balance\n\nDate: 30/06/2019\n\nBalance: $2.65",
  "outputs": {
    "enquiryRateFormatted": "5.2%",
    "enquiryYearEndMinusOneDisplay": "30/06/2018",
    "amalgamatedLoanNotPaidByEOIYFormatted": "$64.53",
    "openingBalancePayDays": "288",
    "openingBalanceInterestFormatted": "$2.65",
    "totalAmountOfRepaymentFormatted": "$64.53",
    "totalInterestFormatted": "$2.65",
    "principalFormatted": "$61.88",
    "enquiryYearEndDisplay": "30/06/2019",
    "minimumYearRepaymentFormatted": "$18.00"
  },
  "repayments": [
    {
      "rd": "15/4/2019",
      "ra": 64.53913860296007
    }
  ],
  "inputs": {
    "incomeYearOfLoan": 2018,
    "fullTermOfAmalgamatedLoan": 4,
    "incomeYearOfEnquiring": 2019,
    "amalgamatedLoanNotPaidByEOIY": 64.53913860296008,
    "repayments": null,
    "lodgement_date": "4/1/2019"
  },
  "idx": 7572
}