{
  "id": "2023-10-31T18:03:48.917Z0.9145835977507221",
  "alert": "Start of result\nResult\n\nMinimum yearly repayment met.\n\nThe amount of the loan not repaid at the end of income year 2014-15 is $1,566.58.\n\n\u000b\n\nThe amalgamated loan will not be taken to be a dividend because the total repayments made are equal to or greater than the minimum yearly repayment required for income year 2014-15.\n\nInterest received by the private company must be included in the income tax return for 2014-15.\n\nMinimum yearly repayment\n\n$2,170.00\n\nBenchmark interest rate\n\n5.95%\n\nOpening balance:\n\nDate: 30/06/2014\n\nBalance: $5,805.00\n\nDays: 81\n\nInterest: $76.65\n\nPayments\n\nDate: 20/09/2014\n\nAmount: $4,381.00\n\nBalance: $1,424.00\n\nDays: 284\n\nInterest: $65.93\n\n\n\n\nTotal repayments\n\n$4,381.00\n\nTotal interest\n\n$142.58\n\nTotal principal\n\n$4,238.42\n\nClosing balance\n\nDate: 30/06/2015\n\nBalance: $1,566.58",
  "outputs": {
    "enquiryRateFormatted": "5.95%",
    "enquiryYearEndMinusOneDisplay": "30/06/2014",
    "amalgamatedLoanNotPaidByEOIYFormatted": "$5,805.00",
    "openingBalancePayDays": "81",
    "openingBalanceInterestFormatted": "$76.65",
    "totalAmountOfRepaymentFormatted": "$4,381.00",
    "totalInterestFormatted": "$142.58",
    "principalFormatted": "$4,238.42",
    "enquiryYearEndDisplay": "30/06/2015",
    "minimumYearRepaymentFormatted": "$2,170.00",
    "loanAmountFormatted": "$1,566.58"
  },
  "repayments": [
    {
      "rd": "20/9/2014",
      "ra": 4381
    }
  ],
  "inputs": {
    "incomeYearOfLoan": 2012,
    "fullTermOfAmalgamatedLoan": 5,
    "incomeYearOfEnquiring": 2015,
    "amalgamatedLoanNotPaidByEOIY": 5805,
    "repayments": null,
    "lodgement_date": null
  },
  "idx": 3232
}