{
  "id": "2023-09-06T22:44:31.091Z0.6133340322441201",
  "alert": "Start of result\nResult\n\nMinimum yearly repayment met.\n\nThe amount of the loan not repaid at the end of income year 2002-03 is $328.15.\n\nThe amalgamated loan will not be taken to be a dividend because the total repayments made are equal to or greater than the minimum yearly repayment required for income year 2002-03.\n\nInterest received by the private company must be included in the income tax return for 2002-03.\n\nMinimum yearly repayment\n\n$2,449.00\n\nBenchmark interest rate\n\n6.3%\n\nOpening balance:\n\nDate: 30/06/2002\n\nBalance: $6,511.00\n\nDays: 292\n\nInterest: $328.15\n\nPayments\n\nDate: 19/04/2003\n\nAmount: $6,511.00\n\nBalance: $0\n\nDays: 73\n\nInterest: $0\n\n\n\n\nTotal repayments\n\n$6,511.00\n\nTotal interest\n\n$328.15\n\nTotal principal\n\n$6,182.85\n\nClosing balance\n\nDate: 30/06/2003\n\nBalance: $328.15",
  "outputs": {
    "enquiryRateFormatted": "6.3%",
    "enquiryYearEndMinusOneDisplay": "30/06/2002",
    "amalgamatedLoanNotPaidByEOIYFormatted": "$6,511.00",
    "openingBalancePayDays": "292",
    "openingBalanceInterestFormatted": "$328.15",
    "totalAmountOfRepaymentFormatted": "$6,511.00",
    "totalInterestFormatted": "$328.15",
    "principalFormatted": "$6,182.85",
    "enquiryYearEndDisplay": "30/06/2003",
    "minimumYearRepaymentFormatted": "$2,449.00"
  },
  "repayments": [
    {
      "rd": "19/4/2003",
      "ra": 6511
    }
  ],
  "inputs": {
    "incomeYearOfLoan": 2001,
    "fullTermOfAmalgamatedLoan": 4,
    "incomeYearOfEnquiring": 2003,
    "amalgamatedLoanNotPaidByEOIY": 6511,
    "repayments": null,
    "lodgement_date": null
  },
  "idx": 737
}