{
  "id": "2023-10-31T19:29:06.658Z0.7186624699020345",
  "alert": "Start of result\nResult\n\nAmalgamated loan fully repaid.\n\nThe amalgamated loan has been paid in full.\u000bThe private company is not taken under Division 7A to pay a dividend to the shareholder or shareholder's associate.\n\nInterest received by the private company must be included in the income tax return for 2007-08.\n\nMinimum yearly repayment\n\n$21.00\n\nBenchmark interest rate\n\n8.05%\n\nOpening balance:\n\nDate: 30/06/2007\n\nBalance: $37.02\n\nDays: 141\n\nInterest: $1.15\n\nPayments\n\nDate: 19/11/2007\n\nAmount: $370.29\n\nBalance: $0\n\nDays: 225\n\nInterest: $0\n\n\n\n\nTotal repayments\n\n$370.29\n\nTotal interest\n\n$1.15\n\nTotal principal\n\n$369.14\n\nClosing balance\n\nDate: 30/06/2008\n\nBalance: $0",
  "outputs": {
    "enquiryRateFormatted": "8.05%",
    "enquiryYearEndMinusOneDisplay": "30/06/2007",
    "amalgamatedLoanNotPaidByEOIYFormatted": "$37.02",
    "openingBalancePayDays": "141",
    "openingBalanceInterestFormatted": "$1.15",
    "totalAmountOfRepaymentFormatted": "$370.29",
    "totalInterestFormatted": "$1.15",
    "principalFormatted": "$369.14",
    "enquiryYearEndDisplay": "30/06/2008",
    "minimumYearRepaymentFormatted": "$21.00",
    "loanAmountFormatted": "$0"
  },
  "repayments": [
    {
      "rd": "19/11/2007",
      "ra": 370.29629213047224
    }
  ],
  "inputs": {
    "incomeYearOfLoan": 2004,
    "fullTermOfAmalgamatedLoan": 5,
    "incomeYearOfEnquiring": 2008,
    "amalgamatedLoanNotPaidByEOIY": 37.02962921304722,
    "repayments": null,
    "lodgement_date": null
  },
  "idx": 5510
}