{
  "id": "2023-09-05T13:58:02.043Z0.5158595087243112",
  "alert": "Start of result\nResult\n\nMinimum yearly repayment not met.\n\nThe amount of the loan not repaid at the end of income year 2022-23 is $111.57.\n\nThe private company may be taken to pay a dividend under Division 7A to the shareholder or shareholder's associate because the amount repaid during income year 2022-23 in relation to the amalgamated loan is less than the minimum yearly repayment required.\n\nInterest received by the private company must be included in the income tax return for 2022-23.\n\nMinimum yearly repayment\n\n$31.00\n\nBenchmark interest rate\n\n4.77%\n\nOpening balance:\n\nDate: 30/06/2022\n\nBalance: $111.57\n\nDays: 365\n\nInterest: $5.32\n\nTotal repayments\n\n$0\n\nTotal interest\n\n$5.32\n\nTotal principal\n\n$0\n\nClosing balance\n\nDate: 30/06/2023\n\nBalance: $111.57",
  "outputs": {
    "enquiryRateFormatted": "4.77%",
    "enquiryYearEndMinusOneDisplay": "30/06/2022",
    "amalgamatedLoanNotPaidByEOIYFormatted": "$111.57",
    "openingBalancePayDays": "365",
    "openingBalanceInterestFormatted": "$5.32",
    "totalAmountOfRepaymentFormatted": "$0",
    "totalInterestFormatted": "$5.32",
    "principalFormatted": "$0",
    "enquiryYearEndDisplay": "30/06/2023",
    "minimumYearRepaymentFormatted": "$31.00"
  },
  "repayments": [],
  "inputs": {
    "incomeYearOfLoan": 2021,
    "fullTermOfAmalgamatedLoan": 5,
    "incomeYearOfEnquiring": 2023,
    "amalgamatedLoanNotPaidByEOIY": 111.57768280498655,
    "repayments": null,
    "lodgement_date": null
  },
  "idx": 734
}