{
  "id": "2023-10-31T19:03:19.315Z0.8872855946720952",
  "alert": "Start of result\nResult\n\nMinimum yearly repayment not met.\n\nThe amount of the loan not repaid at the end of income year 2007-08 is $9,994.00.\n\nThe private company may be taken to pay a dividend under Division 7A to the shareholder or shareholder's associate because the amount repaid during income year 2007-08 in relation to the amalgamated loan is less than the minimum yearly repayment required.\n\nInterest received by the private company must be included in the income tax return for 2007-08.\n\nMinimum yearly repayment\n\n$3,882.00\n\nBenchmark interest rate\n\n8.05%\n\nOpening balance:\n\nDate: 30/06/2007\n\nBalance: $9,994.00\n\nDays: 366\n\nInterest: $804.52\n\nTotal repayments\n\n$0\n\nTotal interest\n\n$804.52\n\nTotal principal\n\n$0\n\nClosing balance\n\nDate: 30/06/2008\n\nBalance: $9,994.00",
  "outputs": {
    "enquiryRateFormatted": "8.05%",
    "enquiryYearEndMinusOneDisplay": "30/06/2007",
    "amalgamatedLoanNotPaidByEOIYFormatted": "$9,994.00",
    "openingBalancePayDays": "366",
    "openingBalanceInterestFormatted": "$804.52",
    "totalAmountOfRepaymentFormatted": "$0",
    "totalInterestFormatted": "$804.52",
    "principalFormatted": "$0",
    "enquiryYearEndDisplay": "30/06/2008",
    "minimumYearRepaymentFormatted": "$3,882.00",
    "loanAmountFormatted": "$9,994.00"
  },
  "repayments": [],
  "inputs": {
    "incomeYearOfLoan": 2006,
    "fullTermOfAmalgamatedLoan": 4,
    "incomeYearOfEnquiring": 2008,
    "amalgamatedLoanNotPaidByEOIY": 9994,
    "repayments": null,
    "lodgement_date": null
  },
  "idx": 4949
}