{
  "id": "2023-09-07T04:10:11.822Z0.7525009813732986",
  "alert": "Start of result\nResult\n\nMinimum yearly repayment met.\n\nThe amount of the loan not repaid at the end of income year 2002-03 is $93.46.\n\nThe amalgamated loan will not be taken to be a dividend because the total repayments made are equal to or greater than the minimum yearly repayment required for income year 2002-03.\n\nInterest received by the private company must be included in the income tax return for 2002-03.\n\nMinimum yearly repayment\n\n$2,315.00\n\nBenchmark interest rate\n\n6.3%\n\nOpening balance:\n\nDate: 30/06/2002\n\nBalance: $6,153.00\n\nDays: 88\n\nInterest: $93.46\n\nPayments\n\nDate: 27/09/2002\n\nAmount: $6,153.00\n\nBalance: $0\n\nDays: 277\n\nInterest: $0\n\n\n\n\nTotal repayments\n\n$6,153.00\n\nTotal interest\n\n$93.46\n\nTotal principal\n\n$6,059.54\n\nClosing balance\n\nDate: 30/06/2003\n\nBalance: $93.46",
  "outputs": {
    "enquiryRateFormatted": "6.3%",
    "enquiryYearEndMinusOneDisplay": "30/06/2002",
    "amalgamatedLoanNotPaidByEOIYFormatted": "$6,153.00",
    "openingBalancePayDays": "88",
    "openingBalanceInterestFormatted": "$93.46",
    "totalAmountOfRepaymentFormatted": "$6,153.00",
    "totalInterestFormatted": "$93.46",
    "principalFormatted": "$6,059.54",
    "enquiryYearEndDisplay": "30/06/2003",
    "minimumYearRepaymentFormatted": "$2,315.00"
  },
  "repayments": [
    {
      "rd": "27/9/2002",
      "ra": 6153
    }
  ],
  "inputs": {
    "incomeYearOfLoan": 1998,
    "fullTermOfAmalgamatedLoan": 7,
    "incomeYearOfEnquiring": 2003,
    "amalgamatedLoanNotPaidByEOIY": 6153,
    "repayments": null,
    "lodgement_date": null
  },
  "idx": 2957
}