{
  "id": "2023-09-04T20:53:50.886Z0.4245594375954833",
  "alert": "Start of result\nResult\n\nMinimum yearly repayment met.\n\nThe amount of the loan not repaid at the end of income year 2013-14 is $3,338.93.\n\nThe amalgamated loan will not be taken to be a dividend because the total repayments made are equal to or greater than the minimum yearly repayment required for income year 2013-14.\n\nInterest received by the private company must be included in the income tax return for 2013-14.\n\nMinimum yearly repayment\n\n$2,283.00\n\nBenchmark interest rate\n\n6.2%\n\nOpening balance:\n\nDate: 30/06/2013\n\nBalance: $9,565.00\n\nDays: 0\n\nInterest: $0\n\nPayments\n\nDate: 01/07/2013\n\nAmount: $6,421.00\n\nBalance: $3,144.00\n\nDays: 365\n\nInterest: $194.93\n\n\n\n\nTotal repayments\n\n$6,421.00\n\nTotal interest\n\n$194.93\n\nTotal principal\n\n$6,226.07\n\nClosing balance\n\nDate: 30/06/2014\n\nBalance: $3,338.93",
  "outputs": {
    "enquiryRateFormatted": "6.2%",
    "enquiryYearEndMinusOneDisplay": "30/06/2013",
    "amalgamatedLoanNotPaidByEOIYFormatted": "$9,565.00",
    "openingBalancePayDays": "0",
    "openingBalanceInterestFormatted": "$0",
    "totalAmountOfRepaymentFormatted": "$6,421.00",
    "totalInterestFormatted": "$194.93",
    "principalFormatted": "$6,226.07",
    "enquiryYearEndDisplay": "30/06/2014",
    "minimumYearRepaymentFormatted": "$2,283.00"
  },
  "repayments": [
    {
      "rd": "1/7/2013",
      "ra": 6421
    }
  ],
  "inputs": {
    "incomeYearOfLoan": 2011,
    "fullTermOfAmalgamatedLoan": 7,
    "incomeYearOfEnquiring": 2014,
    "amalgamatedLoanNotPaidByEOIY": 9565,
    "repayments": null,
    "lodgement_date": null
  },
  "idx": 246
}