{
  "id": "2023-09-04T22:25:29.646Z0.28435776808775026",
  "alert": "Start of result\nResult\n\nMinimum yearly repayment not met.\n\nThe amount of the loan not repaid at the end of income year 2005-06 is $9,571.00.\n\nThe private company may be taken to pay a dividend under Division 7A to the shareholder or shareholder's associate because the amount repaid during income year 2005-06 in relation to the amalgamated loan is less than the minimum yearly repayment required.\n\nInterest received by the private company must be included in the income tax return for 2005-06.\n\nMinimum yearly repayment\n\n$10,270.00\n\nBenchmark interest rate\n\n7.3%\n\nOpening balance:\n\nDate: 30/06/2005\n\nBalance: $9,571.00\n\nDays: 0\n\nInterest: $0\n\nPayments\n\nDate: 01/07/2005\n\nAmount: $407.00\n\nBalance: $9,164.00\n\nDays: 365\n\nInterest: $668.97\n\n\n\n\nTotal repayments\n\n$407.00\n\nTotal interest\n\n$668.97\n\nTotal principal\n\n$0\n\nClosing balance\n\nDate: 30/06/2006\n\nBalance: $9,571.00",
  "outputs": {
    "enquiryRateFormatted": "7.3%",
    "enquiryYearEndMinusOneDisplay": "30/06/2005",
    "amalgamatedLoanNotPaidByEOIYFormatted": "$9,571.00",
    "openingBalancePayDays": "0",
    "openingBalanceInterestFormatted": "$0",
    "totalAmountOfRepaymentFormatted": "$407.00",
    "totalInterestFormatted": "$668.97",
    "principalFormatted": "$0",
    "enquiryYearEndDisplay": "30/06/2006",
    "minimumYearRepaymentFormatted": "$10,270.00"
  },
  "repayments": [
    {
      "rd": "1/7/2005",
      "ra": 407
    }
  ],
  "inputs": {
    "incomeYearOfLoan": 2000,
    "fullTermOfAmalgamatedLoan": 6,
    "incomeYearOfEnquiring": 2006,
    "amalgamatedLoanNotPaidByEOIY": 9571,
    "repayments": null,
    "lodgement_date": null
  },
  "idx": 909
}