{
  "id": "2023-10-31T19:08:44.553Z0.7055712350315532",
  "alert": "Start of result\nResult\n\nMinimum yearly repayment met.\n\nThe amount of the loan not repaid at the end of income year 2011-12 is $3,745.61.\n\n\u000b\n\nThe amalgamated loan will not be taken to be a dividend because the total repayments made are equal to or greater than the minimum yearly repayment required for income year 2011-12.\n\nInterest received by the private company must be included in the income tax return for 2011-12.\n\nMinimum yearly repayment\n\n$6,804.00\n\nBenchmark interest rate\n\n7.8%\n\nOpening balance:\n\nDate: 30/06/2011\n\nBalance: $12,167.00\n\nDays: 59\n\nInterest: $152.99\n\nPayments\n\nDate: 29/08/2011\n\nAmount: $8,795.00\n\nBalance: $3,372.00\n\nDays: 307\n\nInterest: $220.62\n\n\n\n\nTotal repayments\n\n$8,795.00\n\nTotal interest\n\n$373.61\n\nTotal principal\n\n$8,421.39\n\nClosing balance\n\nDate: 30/06/2012\n\nBalance: $3,745.61",
  "outputs": {
    "enquiryRateFormatted": "7.8%",
    "enquiryYearEndMinusOneDisplay": "30/06/2011",
    "amalgamatedLoanNotPaidByEOIYFormatted": "$12,167.00",
    "openingBalancePayDays": "59",
    "openingBalanceInterestFormatted": "$152.99",
    "totalAmountOfRepaymentFormatted": "$8,795.00",
    "totalInterestFormatted": "$373.61",
    "principalFormatted": "$8,421.39",
    "enquiryYearEndDisplay": "30/06/2012",
    "minimumYearRepaymentFormatted": "$6,804.00",
    "loanAmountFormatted": "$3,745.61"
  },
  "repayments": [
    {
      "rd": "29/8/2011",
      "ra": 8795
    }
  ],
  "inputs": {
    "incomeYearOfLoan": 2006,
    "fullTermOfAmalgamatedLoan": 7,
    "incomeYearOfEnquiring": 2012,
    "amalgamatedLoanNotPaidByEOIY": 12167,
    "repayments": null,
    "lodgement_date": null
  },
  "idx": 5076
}