{
  "id": "2023-09-04T16:17:20.246Z0.2788553338898776",
  "alert": "Start of result\nResult\n\nMinimum yearly repayment not met.\n\nThe amount of the loan not repaid at the end of income year 2021-22 is $120,649,486.74.\n\nThe private company may be taken to pay a dividend under Division 7A to the shareholder or shareholder's associate because the amount repaid during income year 2021-22 in relation to the amalgamated loan is less than the minimum yearly repayment required.\n\nInterest received by the private company must be included in the income tax return for 2021-22.\n\nMinimum yearly repayment\n\n$23,405,830.00\n\nBenchmark interest rate\n\n4.52%\n\nOpening balance:\n\nDate: 30/06/2021\n\nBalance: $120,649,486.74\n\nDays: 0\n\nInterest: $0\n\nPayments\n\nDate: 01/07/2021\n\nAmount: $3,069.00\n\nBalance: $120,646,417.74\n\nDays: 365\n\nInterest: $5,453,218.08\n\n\n\n\nTotal repayments\n\n$3,069.00\n\nTotal interest\n\n$5,453,218.08\n\nTotal principal\n\n$0\n\nClosing balance\n\nDate: 30/06/2022\n\nBalance: $120,649,486.74",
  "outputs": {
    "enquiryRateFormatted": "4.52%",
    "enquiryYearEndMinusOneDisplay": "30/06/2021",
    "amalgamatedLoanNotPaidByEOIYFormatted": "$120,649,486.74",
    "openingBalancePayDays": "0",
    "openingBalanceInterestFormatted": "$0",
    "totalAmountOfRepaymentFormatted": "$3,069.00",
    "totalInterestFormatted": "$5,453,218.08",
    "principalFormatted": "$0",
    "enquiryYearEndDisplay": "30/06/2022",
    "minimumYearRepaymentFormatted": "$23,405,830.00"
  },
  "repayments": [
    {
      "rd": "1/7/2021",
      "ra": 3069
    }
  ],
  "inputs": {
    "incomeYearOfLoan": 2021,
    "fullTermOfAmalgamatedLoan": 6,
    "incomeYearOfEnquiring": 2022,
    "amalgamatedLoanNotPaidByEOIY": 120649486.74859253,
    "repayments": null,
    "lodgement_date": "27/4/2022"
  },
  "idx": 182
}