{
  "id": "2023-09-06T06:43:47.561Z0.6454882852675192",
  "alert": "Start of result\nResult\n\nMinimum yearly repayment met.\n\nThe amount of the loan not repaid at the end of income year 2015-16 is $140.08.\n\nThe amalgamated loan will not be taken to be a dividend because the total repayments made are equal to or greater than the minimum yearly repayment required for income year 2015-16.\n\nInterest received by the private company must be included in the income tax return for 2015-16.\n\nMinimum yearly repayment\n\n$1,611.00\n\nBenchmark interest rate\n\n5.45%\n\nOpening balance:\n\nDate: 30/06/2015\n\nBalance: $2,977.00\n\nDays: 316\n\nInterest: $140.08\n\nPayments\n\nDate: 12/05/2016\n\nAmount: $2,977.00\n\nBalance: $0\n\nDays: 50\n\nInterest: $0\n\n\n\n\nTotal repayments\n\n$2,977.00\n\nTotal interest\n\n$140.08\n\nTotal principal\n\n$2,836.92\n\nClosing balance\n\nDate: 30/06/2016\n\nBalance: $140.08",
  "outputs": {
    "enquiryRateFormatted": "5.45%",
    "enquiryYearEndMinusOneDisplay": "30/06/2015",
    "amalgamatedLoanNotPaidByEOIYFormatted": "$2,977.00",
    "openingBalancePayDays": "316",
    "openingBalanceInterestFormatted": "$140.08",
    "totalAmountOfRepaymentFormatted": "$2,977.00",
    "totalInterestFormatted": "$140.08",
    "principalFormatted": "$2,836.92",
    "enquiryYearEndDisplay": "30/06/2016",
    "minimumYearRepaymentFormatted": "$1,611.00"
  },
  "repayments": [
    {
      "rd": "12/5/2016",
      "ra": 2977
    }
  ],
  "inputs": {
    "incomeYearOfLoan": 2011,
    "fullTermOfAmalgamatedLoan": 6,
    "incomeYearOfEnquiring": 2016,
    "amalgamatedLoanNotPaidByEOIY": 2977,
    "repayments": null,
    "lodgement_date": null
  },
  "idx": 6663
}