{
  "id": "2023-09-05T01:45:43.201Z0.661462427993134",
  "alert": "Start of result\nResult\n\nMinimum yearly repayment not met.\n\nThe amount of the loan not repaid at the end of income year 2001-02 is $111.93.\n\nThe private company may be taken to pay a dividend under Division 7A to the shareholder or shareholder's associate because the amount repaid during income year 2001-02 in relation to the amalgamated loan is less than the minimum yearly repayment required.\n\nInterest received by the private company must be included in the income tax return for 2001-02.\n\nMinimum yearly repayment\n\n$62.00\n\nBenchmark interest rate\n\n6.8%\n\nOpening balance:\n\nDate: 30/06/2001\n\nBalance: $111.93\n\nDays: 365\n\nInterest: $7.61\n\nTotal repayments\n\n$0\n\nTotal interest\n\n$7.61\n\nTotal principal\n\n$0\n\nClosing balance\n\nDate: 30/06/2002\n\nBalance: $111.93",
  "outputs": {
    "enquiryRateFormatted": "6.8%",
    "enquiryYearEndMinusOneDisplay": "30/06/2001",
    "amalgamatedLoanNotPaidByEOIYFormatted": "$111.93",
    "openingBalancePayDays": "365",
    "openingBalanceInterestFormatted": "$7.61",
    "totalAmountOfRepaymentFormatted": "$0",
    "totalInterestFormatted": "$7.61",
    "principalFormatted": "$0",
    "enquiryYearEndDisplay": "30/06/2002",
    "minimumYearRepaymentFormatted": "$62.00"
  },
  "repayments": [],
  "inputs": {
    "incomeYearOfLoan": 1998,
    "fullTermOfAmalgamatedLoan": 5,
    "incomeYearOfEnquiring": 2002,
    "amalgamatedLoanNotPaidByEOIY": 111.93348654982546,
    "repayments": null,
    "lodgement_date": null
  },
  "idx": 3313
}