{
  "id": "2023-10-31T17:43:22.603Z0.9175512327473743",
  "alert": "Start of result\nResult\n\nMinimum yearly repayment not met.\n\nThe amount of the loan not repaid at the end of income year 2016-17 is $2,785.00.\n\nThe private company may be taken to pay a dividend under Division 7A to the shareholder or shareholder's associate because the amount repaid during income year 2016-17 in relation to the amalgamated loan is less than the minimum yearly repayment required.\n\nInterest received by the private company must be included in the income tax return for 2016-17.\n\nMinimum yearly repayment\n\n$556.00\n\nBenchmark interest rate\n\n5.4%\n\nOpening balance:\n\nDate: 30/06/2016\n\nBalance: $2,785.00\n\nDays: 365\n\nInterest: $150.39\n\nTotal repayments\n\n$0\n\nTotal interest\n\n$150.39\n\nTotal principal\n\n$0\n\nClosing balance\n\nDate: 30/06/2017\n\nBalance: $2,785.00",
  "outputs": {
    "enquiryRateFormatted": "5.4%",
    "enquiryYearEndMinusOneDisplay": "30/06/2016",
    "amalgamatedLoanNotPaidByEOIYFormatted": "$2,785.00",
    "openingBalancePayDays": "365",
    "openingBalanceInterestFormatted": "$150.39",
    "totalAmountOfRepaymentFormatted": "$0",
    "totalInterestFormatted": "$150.39",
    "principalFormatted": "$0",
    "enquiryYearEndDisplay": "30/06/2017",
    "minimumYearRepaymentFormatted": "$556.00",
    "loanAmountFormatted": "$2,785.00"
  },
  "repayments": [],
  "inputs": {
    "incomeYearOfLoan": 2015,
    "fullTermOfAmalgamatedLoan": 7,
    "incomeYearOfEnquiring": 2017,
    "amalgamatedLoanNotPaidByEOIY": 2785,
    "repayments": null,
    "lodgement_date": null
  },
  "idx": 2379
}