{
  "id": "2023-09-04T21:54:40.476Z0.07344445178154224",
  "alert": "Start of result\nResult\n\nMinimum yearly repayment met.\n\nThe amount of the loan not repaid at the end of income year 2005-06 is $8,321.12.\n\nThe amalgamated loan will not be taken to be a dividend because the total repayments made are equal to or greater than the minimum yearly repayment required for income year 2005-06.\n\nInterest received by the private company must be included in the income tax return for 2005-06.\n\nMinimum yearly repayment\n\n$1,642.00\n\nBenchmark interest rate\n\n7.3%\n\nOpening balance:\n\nDate: 30/06/2005\n\nBalance: $11,457.00\n\nDays: 0\n\nInterest: $0\n\nPayments\n\nDate: 01/07/2005\n\nAmount: $3,702.00\n\nBalance: $7,755.00\n\nDays: 365\n\nInterest: $566.12\n\n\n\n\nTotal repayments\n\n$3,702.00\n\nTotal interest\n\n$566.12\n\nTotal principal\n\n$3,135.88\n\nClosing balance\n\nDate: 30/06/2006\n\nBalance: $8,321.12",
  "outputs": {
    "enquiryRateFormatted": "7.3%",
    "enquiryYearEndMinusOneDisplay": "30/06/2005",
    "amalgamatedLoanNotPaidByEOIYFormatted": "$11,457.00",
    "openingBalancePayDays": "0",
    "openingBalanceInterestFormatted": "$0",
    "totalAmountOfRepaymentFormatted": "$3,702.00",
    "totalInterestFormatted": "$566.12",
    "principalFormatted": "$3,135.88",
    "enquiryYearEndDisplay": "30/06/2006",
    "minimumYearRepaymentFormatted": "$1,642.00"
  },
  "repayments": [
    {
      "rd": "1/7/2005",
      "ra": 3702
    }
  ],
  "inputs": {
    "incomeYearOfLoan": 2005,
    "fullTermOfAmalgamatedLoan": 6,
    "incomeYearOfEnquiring": 2006,
    "amalgamatedLoanNotPaidByEOIY": 11457,
    "repayments": null,
    "lodgement_date": "9/10/2005"
  },
  "idx": 1787
}