{
  "id": "2023-09-04T22:10:28.147Z0.22846579811569123",
  "alert": "Start of result\nResult\n\nMinimum yearly repayment not met.\n\nThe amount of the loan not repaid at the end of income year 2002-03 is $90,177,962.34.\n\nThe private company may be taken to pay a dividend under Division 7A to the shareholder or shareholder's associate because the amount repaid during income year 2002-03 in relation to the amalgamated loan is less than the minimum yearly repayment required.\n\nInterest received by the private company must be included in the income tax return for 2002-03.\n\nMinimum yearly repayment\n\n$26,203,482.00\n\nBenchmark interest rate\n\n6.3%\n\nOpening balance:\n\nDate: 30/06/2002\n\nBalance: $90,177,962.34\n\nDays: 0\n\nInterest: $0\n\nPayments\n\nDate: 01/07/2002\n\nAmount: $407.00\n\nBalance: $90,177,555.34\n\nDays: 365\n\nInterest: $5,681,185.99\n\n\n\n\nTotal repayments\n\n$407.00\n\nTotal interest\n\n$5,681,185.99\n\nTotal principal\n\n$0\n\nClosing balance\n\nDate: 30/06/2003\n\nBalance: $90,177,962.34",
  "outputs": {
    "enquiryRateFormatted": "6.3%",
    "enquiryYearEndMinusOneDisplay": "30/06/2002",
    "amalgamatedLoanNotPaidByEOIYFormatted": "$90,177,962.34",
    "openingBalancePayDays": "0",
    "openingBalanceInterestFormatted": "$0",
    "totalAmountOfRepaymentFormatted": "$407.00",
    "totalInterestFormatted": "$5,681,185.99",
    "principalFormatted": "$0",
    "enquiryYearEndDisplay": "30/06/2003",
    "minimumYearRepaymentFormatted": "$26,203,482.00"
  },
  "repayments": [
    {
      "rd": "1/7/2002",
      "ra": 407
    }
  ],
  "inputs": {
    "incomeYearOfLoan": 2002,
    "fullTermOfAmalgamatedLoan": 4,
    "incomeYearOfEnquiring": 2003,
    "amalgamatedLoanNotPaidByEOIY": 90177962.34500042,
    "repayments": null,
    "lodgement_date": "30/6/2003"
  },
  "idx": 384
}