{
  "id": "2023-10-31T17:36:16.500Z0.5115319431955049",
  "alert": "Start of result\nResult\n\nMinimum yearly repayment met.\n\nThe amount of the loan not repaid at the end of income year 2016-17 is $6,873.90.\n\n\u000b\n\nThe amalgamated loan will not be taken to be a dividend because the total repayments made are equal to or greater than the minimum yearly repayment required for income year 2016-17.\n\nInterest received by the private company must be included in the income tax return for 2016-17.\n\nMinimum yearly repayment\n\n$1,295.00\n\nBenchmark interest rate\n\n5.4%\n\nOpening balance:\n\nDate: 30/06/2016\n\nBalance: $12,175.00\n\nDays: 41\n\nInterest: $73.85\n\nPayments\n\nDate: 11/08/2016\n\nAmount: $5,686.00\n\nBalance: $6,489.00\n\nDays: 324\n\nInterest: $311.05\n\n\n\n\nTotal repayments\n\n$5,686.00\n\nTotal interest\n\n$384.90\n\nTotal principal\n\n$5,301.10\n\nClosing balance\n\nDate: 30/06/2017\n\nBalance: $6,873.90",
  "outputs": {
    "enquiryRateFormatted": "5.4%",
    "enquiryYearEndMinusOneDisplay": "30/06/2016",
    "amalgamatedLoanNotPaidByEOIYFormatted": "$12,175.00",
    "openingBalancePayDays": "41",
    "openingBalanceInterestFormatted": "$73.85",
    "totalAmountOfRepaymentFormatted": "$5,686.00",
    "totalInterestFormatted": "$384.90",
    "principalFormatted": "$5,301.10",
    "enquiryYearEndDisplay": "30/06/2017",
    "minimumYearRepaymentFormatted": "$1,295.00",
    "loanAmountFormatted": "$6,873.90"
  },
  "repayments": [
    {
      "rd": "11/8/2016",
      "ra": 5686
    }
  ],
  "inputs": {
    "incomeYearOfLoan": 2016,
    "fullTermOfAmalgamatedLoan": 6,
    "incomeYearOfEnquiring": 2017,
    "amalgamatedLoanNotPaidByEOIY": 12175,
    "repayments": null,
    "lodgement_date": "29/10/2016"
  },
  "idx": 2038
}