{
  "id": "2023-10-31T18:34:58.227Z0.28541777460917084",
  "alert": "Start of result\nResult\n\nAmalgamated loan fully repaid.\n\nThe amalgamated loan has been paid in full.\u000bThe private company is not taken under Division 7A to pay a dividend to the shareholder or shareholder's associate.\n\nInterest received by the private company must be included in the income tax return for 2009-10.\n\nMinimum yearly repayment\n\n-$62.00\n\nBenchmark interest rate\n\n5.75%\n\nOpening balance:\n\nDate: 30/06/2009\n\nBalance: $39.09\n\nDays: 62\n\nInterest: $0.38\n\nPayments\n\nDate: 01/09/2009\n\nAmount: $390.90\n\nBalance: $0\n\nDays: 303\n\nInterest: $0\n\n\n\n\nTotal repayments\n\n$390.90\n\nTotal interest\n\n$0.38\n\nTotal principal\n\n$390.52\n\nClosing balance\n\nDate: 30/06/2010\n\nBalance: $0",
  "outputs": {
    "enquiryRateFormatted": "5.75%",
    "enquiryYearEndMinusOneDisplay": "30/06/2009",
    "amalgamatedLoanNotPaidByEOIYFormatted": "$39.09",
    "openingBalancePayDays": "62",
    "openingBalanceInterestFormatted": "$0.38",
    "totalAmountOfRepaymentFormatted": "$390.90",
    "totalInterestFormatted": "$0.38",
    "principalFormatted": "$390.52",
    "enquiryYearEndDisplay": "30/06/2010",
    "minimumYearRepaymentFormatted": "-$62.00",
    "loanAmountFormatted": "$0"
  },
  "repayments": [
    {
      "rd": "1/9/2009",
      "ra": 390.90777317451466
    }
  ],
  "inputs": {
    "incomeYearOfLoan": 2009,
    "fullTermOfAmalgamatedLoan": 7,
    "incomeYearOfEnquiring": 2010,
    "amalgamatedLoanNotPaidByEOIY": 39.09077731745153,
    "repayments": null,
    "lodgement_date": "30/6/2010"
  },
  "idx": 4213
}