{
  "id": "2023-10-31T19:06:55.325Z0.130745142688504",
  "alert": "Start of result\nResult\n\nMinimum yearly repayment not met.\n\nThe amount of the loan not repaid at the end of income year 2009-10 is $86.64.\n\nThe private company may be taken to pay a dividend under Division 7A to the shareholder or shareholder's associate because the amount repaid during income year 2009-10 in relation to the amalgamated loan is less than the minimum yearly repayment required.\n\nInterest received by the private company must be included in the income tax return for 2009-10.\n\nMinimum yearly repayment\n\n$32.00\n\nBenchmark interest rate\n\n5.75%\n\nOpening balance:\n\nDate: 30/06/2009\n\nBalance: $86.64\n\nDays: 365\n\nInterest: $4.98\n\nTotal repayments\n\n$0\n\nTotal interest\n\n$4.98\n\nTotal principal\n\n$0\n\nClosing balance\n\nDate: 30/06/2010\n\nBalance: $86.64",
  "outputs": {
    "enquiryRateFormatted": "5.75%",
    "enquiryYearEndMinusOneDisplay": "30/06/2009",
    "amalgamatedLoanNotPaidByEOIYFormatted": "$86.64",
    "openingBalancePayDays": "365",
    "openingBalanceInterestFormatted": "$4.98",
    "totalAmountOfRepaymentFormatted": "$0",
    "totalInterestFormatted": "$4.98",
    "principalFormatted": "$0",
    "enquiryYearEndDisplay": "30/06/2010",
    "minimumYearRepaymentFormatted": "$32.00",
    "loanAmountFormatted": "$86.64"
  },
  "repayments": [],
  "inputs": {
    "incomeYearOfLoan": 2006,
    "fullTermOfAmalgamatedLoan": 6,
    "incomeYearOfEnquiring": 2010,
    "amalgamatedLoanNotPaidByEOIY": 86.64198588906159,
    "repayments": null,
    "lodgement_date": null
  },
  "idx": 5034
}