{
  "id": "2023-10-31T18:06:25.461Z0.1120595099965278",
  "alert": "Start of result\nResult\n\nMinimum yearly repayment met.\n\nThe amount of the loan not repaid at the end of income year 2015-16 is $7,256.83.\n\n\u000b\n\nThe amalgamated loan will not be taken to be a dividend because the total repayments made are equal to or greater than the minimum yearly repayment required for income year 2015-16.\n\nInterest received by the private company must be included in the income tax return for 2015-16.\n\nMinimum yearly repayment\n\n$2,890.00\n\nBenchmark interest rate\n\n5.45%\n\nOpening balance:\n\nDate: 30/06/2015\n\nBalance: $10,141.00\n\nDays: 138\n\nInterest: $208.39\n\nPayments\n\nDate: 16/11/2015\n\nAmount: $3,324.00\n\nBalance: $6,817.00\n\nDays: 228\n\nInterest: $231.44\n\n\n\n\nTotal repayments\n\n$3,324.00\n\nTotal interest\n\n$439.83\n\nTotal principal\n\n$2,884.17\n\nClosing balance\n\nDate: 30/06/2016\n\nBalance: $7,256.83",
  "outputs": {
    "enquiryRateFormatted": "5.45%",
    "enquiryYearEndMinusOneDisplay": "30/06/2015",
    "amalgamatedLoanNotPaidByEOIYFormatted": "$10,141.00",
    "openingBalancePayDays": "138",
    "openingBalanceInterestFormatted": "$208.39",
    "totalAmountOfRepaymentFormatted": "$3,324.00",
    "totalInterestFormatted": "$439.83",
    "principalFormatted": "$2,884.17",
    "enquiryYearEndDisplay": "30/06/2016",
    "minimumYearRepaymentFormatted": "$2,890.00",
    "loanAmountFormatted": "$7,256.83"
  },
  "repayments": [
    {
      "rd": "16/11/2015",
      "ra": 3324
    }
  ],
  "inputs": {
    "incomeYearOfLoan": 2012,
    "fullTermOfAmalgamatedLoan": 7,
    "incomeYearOfEnquiring": 2016,
    "amalgamatedLoanNotPaidByEOIY": 10141,
    "repayments": null,
    "lodgement_date": null
  },
  "idx": 3324
}