{
  "id": "2023-09-04T16:20:22.303Z0.8278989035969837",
  "alert": "Start of result\nResult\n\nMinimum yearly repayment not met.\n\nThe amount of the loan not repaid at the end of income year 2022-23 is $114,237,910.37.\n\nThe private company may be taken to pay a dividend under Division 7A to the shareholder or shareholder's associate because the amount repaid during income year 2022-23 in relation to the amalgamated loan is less than the minimum yearly repayment required.\n\nInterest received by the private company must be included in the income tax return for 2022-23.\n\nMinimum yearly repayment\n\n$32,044,495.00\n\nBenchmark interest rate\n\n4.77%\n\nOpening balance:\n\nDate: 30/06/2022\n\nBalance: $114,237,910.37\n\nDays: 365\n\nInterest: $5,449,148.32\n\nTotal repayments\n\n$0\n\nTotal interest\n\n$5,449,148.32\n\nTotal principal\n\n$0\n\nClosing balance\n\nDate: 30/06/2023\n\nBalance: $114,237,910.37",
  "outputs": {
    "enquiryRateFormatted": "4.77%",
    "enquiryYearEndMinusOneDisplay": "30/06/2022",
    "amalgamatedLoanNotPaidByEOIYFormatted": "$114,237,910.37",
    "openingBalancePayDays": "365",
    "openingBalanceInterestFormatted": "$5,449,148.32",
    "totalAmountOfRepaymentFormatted": "$0",
    "totalInterestFormatted": "$5,449,148.32",
    "principalFormatted": "$0",
    "enquiryYearEndDisplay": "30/06/2023",
    "minimumYearRepaymentFormatted": "$32,044,495.00"
  },
  "repayments": [],
  "inputs": {
    "incomeYearOfLoan": 2020,
    "fullTermOfAmalgamatedLoan": 6,
    "incomeYearOfEnquiring": 2023,
    "amalgamatedLoanNotPaidByEOIY": 114237910.3783266,
    "repayments": null,
    "lodgement_date": null
  },
  "idx": 304
}