{
  "id": "2023-10-31T19:44:47.428Z0.23556953765031385",
  "alert": "Start of result\nResult\n\nAmalgamated loan fully repaid.\n\nThe amalgamated loan has been paid in full.\u000bThe private company is not taken under Division 7A to pay a dividend to the shareholder or shareholder's associate.\n\nInterest received by the private company must be included in the income tax return for 2006-07.\n\nMinimum yearly repayment\n\n$27.00\n\nBenchmark interest rate\n\n7.55%\n\nOpening balance:\n\nDate: 30/06/2006\n\nBalance: $69.11\n\nDays: 139\n\nInterest: $1.99\n\nPayments\n\nDate: 17/11/2006\n\nAmount: $691.16\n\nBalance: $0\n\nDays: 226\n\nInterest: $0\n\n\n\n\nTotal repayments\n\n$691.16\n\nTotal interest\n\n$1.99\n\nTotal principal\n\n$689.17\n\nClosing balance\n\nDate: 30/06/2007\n\nBalance: $0",
  "outputs": {
    "enquiryRateFormatted": "7.55%",
    "enquiryYearEndMinusOneDisplay": "30/06/2006",
    "amalgamatedLoanNotPaidByEOIYFormatted": "$69.11",
    "openingBalancePayDays": "139",
    "openingBalanceInterestFormatted": "$1.99",
    "totalAmountOfRepaymentFormatted": "$691.16",
    "totalInterestFormatted": "$1.99",
    "principalFormatted": "$689.17",
    "enquiryYearEndDisplay": "30/06/2007",
    "minimumYearRepaymentFormatted": "$27.00",
    "loanAmountFormatted": "$0"
  },
  "repayments": [
    {
      "rd": "17/11/2006",
      "ra": 691.162373524377
    }
  ],
  "inputs": {
    "incomeYearOfLoan": 2003,
    "fullTermOfAmalgamatedLoan": 6,
    "incomeYearOfEnquiring": 2007,
    "amalgamatedLoanNotPaidByEOIY": 69.11623735243771,
    "repayments": null,
    "lodgement_date": null
  },
  "idx": 5801
}