{
  "id": "2023-09-04T21:55:06.921Z0.4534758231398135",
  "alert": "Start of result\nResult\n\nMinimum yearly repayment not met.\n\nThe amount of the loan not repaid at the end of income year 2011-12 is $75,773,805.64.\n\nThe private company may be taken to pay a dividend under Division 7A to the shareholder or shareholder's associate because the amount repaid during income year 2011-12 in relation to the amalgamated loan is less than the minimum yearly repayment required.\n\nInterest received by the private company must be included in the income tax return for 2011-12.\n\nMinimum yearly repayment\n\n$81,684,162.00\n\nBenchmark interest rate\n\n7.8%\n\nOpening balance:\n\nDate: 30/06/2011\n\nBalance: $75,773,805.64\n\nDays: 366\n\nInterest: $5,910,356.84\n\nTotal repayments\n\n$0\n\nTotal interest\n\n$5,910,356.84\n\nTotal principal\n\n$0\n\nClosing balance\n\nDate: 30/06/2012\n\nBalance: $75,773,805.64",
  "outputs": {
    "enquiryRateFormatted": "7.8%",
    "enquiryYearEndMinusOneDisplay": "30/06/2011",
    "amalgamatedLoanNotPaidByEOIYFormatted": "$75,773,805.64",
    "openingBalancePayDays": "366",
    "openingBalanceInterestFormatted": "$5,910,356.84",
    "totalAmountOfRepaymentFormatted": "$0",
    "totalInterestFormatted": "$5,910,356.84",
    "principalFormatted": "$0",
    "enquiryYearEndDisplay": "30/06/2012",
    "minimumYearRepaymentFormatted": "$81,684,162.00"
  },
  "repayments": [],
  "inputs": {
    "incomeYearOfLoan": 2005,
    "fullTermOfAmalgamatedLoan": 7,
    "incomeYearOfEnquiring": 2012,
    "amalgamatedLoanNotPaidByEOIY": 75773805.64075157,
    "repayments": null,
    "lodgement_date": null
  },
  "idx": 1796
}