{
  "id": "2023-09-04T21:09:24.934Z0.8341541943122401",
  "alert": "Start of result\nResult\n\nMinimum yearly repayment not met.\n\nThe amount of the loan not repaid at the end of income year 2009-10 is $83,645,202.33.\n\nThe private company may be taken to pay a dividend under Division 7A to the shareholder or shareholder's associate because the amount repaid during income year 2009-10 in relation to the amalgamated loan is less than the minimum yearly repayment required.\n\nInterest received by the private company must be included in the income tax return for 2009-10.\n\nMinimum yearly repayment\n\n$14,849,259.00\n\nBenchmark interest rate\n\n5.75%\n\nOpening balance:\n\nDate: 30/06/2009\n\nBalance: $83,645,202.33\n\nDays: 0\n\nInterest: $0\n\nPayments\n\nDate: 01/07/2009\n\nAmount: $9,309.00\n\nBalance: $83,635,893.33\n\nDays: 365\n\nInterest: $4,809,063.87\n\n\n\n\nTotal repayments\n\n$9,309.00\n\nTotal interest\n\n$4,809,063.87\n\nTotal principal\n\n$0\n\nClosing balance\n\nDate: 30/06/2010\n\nBalance: $83,645,202.33",
  "outputs": {
    "enquiryRateFormatted": "5.75%",
    "enquiryYearEndMinusOneDisplay": "30/06/2009",
    "amalgamatedLoanNotPaidByEOIYFormatted": "$83,645,202.33",
    "openingBalancePayDays": "0",
    "openingBalanceInterestFormatted": "$0",
    "totalAmountOfRepaymentFormatted": "$9,309.00",
    "totalInterestFormatted": "$4,809,063.87",
    "principalFormatted": "$0",
    "enquiryYearEndDisplay": "30/06/2010",
    "minimumYearRepaymentFormatted": "$14,849,259.00"
  },
  "repayments": [
    {
      "rd": "1/7/2009",
      "ra": 9309
    }
  ],
  "inputs": {
    "incomeYearOfLoan": 2009,
    "fullTermOfAmalgamatedLoan": 7,
    "incomeYearOfEnquiring": 2010,
    "amalgamatedLoanNotPaidByEOIY": 83645202.33509362,
    "repayments": null,
    "lodgement_date": "30/6/2010"
  },
  "idx": 749
}