{
  "id": "2023-10-31T17:34:56.648Z0.9002221205584215",
  "alert": "Start of result\nResult\n\nAmalgamated loan fully repaid.\n\nThe amalgamated loan has been paid in full.\u000bThe private company is not taken under Division 7A to pay a dividend to the shareholder or shareholder's associate.\n\nInterest received by the private company must be included in the income tax return for 2016-17.\n\nMinimum yearly repayment\n\n-$214.00\n\nBenchmark interest rate\n\n5.4%\n\nOpening balance:\n\nDate: 30/06/2016\n\nBalance: $83.40\n\nDays: 59\n\nInterest: $0.73\n\nPayments\n\nDate: 29/08/2016\n\nAmount: $834.06\n\nBalance: $0\n\nDays: 306\n\nInterest: $0\n\n\n\n\nTotal repayments\n\n$834.06\n\nTotal interest\n\n$0.73\n\nTotal principal\n\n$833.33\n\nClosing balance\n\nDate: 30/06/2017\n\nBalance: $0",
  "outputs": {
    "enquiryRateFormatted": "5.4%",
    "enquiryYearEndMinusOneDisplay": "30/06/2016",
    "amalgamatedLoanNotPaidByEOIYFormatted": "$83.40",
    "openingBalancePayDays": "59",
    "openingBalanceInterestFormatted": "$0.73",
    "totalAmountOfRepaymentFormatted": "$834.06",
    "totalInterestFormatted": "$0.73",
    "principalFormatted": "$833.33",
    "enquiryYearEndDisplay": "30/06/2017",
    "minimumYearRepaymentFormatted": "-$214.00",
    "loanAmountFormatted": "$0"
  },
  "repayments": [
    {
      "rd": "29/8/2016",
      "ra": 834.0652725828968
    }
  ],
  "inputs": {
    "incomeYearOfLoan": 2016,
    "fullTermOfAmalgamatedLoan": 4,
    "incomeYearOfEnquiring": 2017,
    "amalgamatedLoanNotPaidByEOIY": 83.40652725828964,
    "repayments": null,
    "lodgement_date": "30/6/2017"
  },
  "idx": 1973
}