{
  "id": "2023-10-31T17:35:52.860Z0.6227861915635393",
  "alert": "Start of result\nResult\n\nAmalgamated loan fully repaid.\n\nThe amalgamated loan has been paid in full.\u000bThe private company is not taken under Division 7A to pay a dividend to the shareholder or shareholder's associate.\n\nInterest received by the private company must be included in the income tax return for 2018-19.\n\nMinimum yearly repayment\n\n$17.00\n\nBenchmark interest rate\n\n5.2%\n\nOpening balance:\n\nDate: 30/06/2018\n\nBalance: $61.28\n\nDays: 61\n\nInterest: $0.53\n\nPayments\n\nDate: 31/08/2018\n\nAmount: $612.87\n\nBalance: $0\n\nDays: 304\n\nInterest: $0\n\n\n\n\nTotal repayments\n\n$612.87\n\nTotal interest\n\n$0.53\n\nTotal principal\n\n$612.34\n\nClosing balance\n\nDate: 30/06/2019\n\nBalance: $0",
  "outputs": {
    "enquiryRateFormatted": "5.2%",
    "enquiryYearEndMinusOneDisplay": "30/06/2018",
    "amalgamatedLoanNotPaidByEOIYFormatted": "$61.28",
    "openingBalancePayDays": "61",
    "openingBalanceInterestFormatted": "$0.53",
    "totalAmountOfRepaymentFormatted": "$612.87",
    "totalInterestFormatted": "$0.53",
    "principalFormatted": "$612.34",
    "enquiryYearEndDisplay": "30/06/2019",
    "minimumYearRepaymentFormatted": "$17.00",
    "loanAmountFormatted": "$0"
  },
  "repayments": [
    {
      "rd": "31/8/2018",
      "ra": 612.8702787980142
    }
  ],
  "inputs": {
    "incomeYearOfLoan": 2016,
    "fullTermOfAmalgamatedLoan": 6,
    "incomeYearOfEnquiring": 2019,
    "amalgamatedLoanNotPaidByEOIY": 61.287027879801414,
    "repayments": null,
    "lodgement_date": null
  },
  "idx": 2017
}