{
  "id": "2023-09-04T21:29:16.787Z0.7453231039105206",
  "alert": "Start of result\nResult\n\nMinimum yearly repayment met.\n\nThe amount of the loan not repaid at the end of income year 2007-08 is $3,144.26.\n\nThe amalgamated loan will not be taken to be a dividend because the total repayments made are equal to or greater than the minimum yearly repayment required for income year 2007-08.\n\nInterest received by the private company must be included in the income tax return for 2007-08.\n\nMinimum yearly repayment\n\n$730.00\n\nBenchmark interest rate\n\n8.05%\n\nOpening balance:\n\nDate: 30/06/2007\n\nBalance: $8,490.00\n\nDays: 0\n\nInterest: $0\n\nPayments\n\nDate: 01/07/2007\n\nAmount: $5,580.00\n\nBalance: $2,910.00\n\nDays: 366\n\nInterest: $234.26\n\n\n\n\nTotal repayments\n\n$5,580.00\n\nTotal interest\n\n$234.26\n\nTotal principal\n\n$5,345.74\n\nClosing balance\n\nDate: 30/06/2008\n\nBalance: $3,144.26",
  "outputs": {
    "enquiryRateFormatted": "8.05%",
    "enquiryYearEndMinusOneDisplay": "30/06/2007",
    "amalgamatedLoanNotPaidByEOIYFormatted": "$8,490.00",
    "openingBalancePayDays": "0",
    "openingBalanceInterestFormatted": "$0",
    "totalAmountOfRepaymentFormatted": "$5,580.00",
    "totalInterestFormatted": "$234.26",
    "principalFormatted": "$5,345.74",
    "enquiryYearEndDisplay": "30/06/2008",
    "minimumYearRepaymentFormatted": "$730.00"
  },
  "repayments": [
    {
      "rd": "1/7/2007",
      "ra": 5580
    }
  ],
  "inputs": {
    "incomeYearOfLoan": 2007,
    "fullTermOfAmalgamatedLoan": 5,
    "incomeYearOfEnquiring": 2008,
    "amalgamatedLoanNotPaidByEOIY": 8490,
    "repayments": null,
    "lodgement_date": "17/1/2008"
  },
  "idx": 1294
}