{
  "id": "2023-10-31T19:09:21.274Z0.25711527469001383",
  "alert": "Start of result\nResult\n\nMinimum yearly repayment not met.\n\nThe amount of the loan not repaid at the end of income year 2008-09 is $89.03.\n\nThe private company may be taken to pay a dividend under Division 7A to the shareholder or shareholder's associate because the amount repaid during income year 2008-09 in relation to the amalgamated loan is less than the minimum yearly repayment required.\n\nInterest received by the private company must be included in the income tax return for 2008-09.\n\nMinimum yearly repayment\n\n$23.00\n\nBenchmark interest rate\n\n9.45%\n\nOpening balance:\n\nDate: 30/06/2008\n\nBalance: $89.03\n\nDays: 365\n\nInterest: $8.41\n\nTotal repayments\n\n$0\n\nTotal interest\n\n$8.41\n\nTotal principal\n\n$0\n\nClosing balance\n\nDate: 30/06/2009\n\nBalance: $89.03",
  "outputs": {
    "enquiryRateFormatted": "9.45%",
    "enquiryYearEndMinusOneDisplay": "30/06/2008",
    "amalgamatedLoanNotPaidByEOIYFormatted": "$89.03",
    "openingBalancePayDays": "365",
    "openingBalanceInterestFormatted": "$8.41",
    "totalAmountOfRepaymentFormatted": "$0",
    "totalInterestFormatted": "$8.41",
    "principalFormatted": "$0",
    "enquiryYearEndDisplay": "30/06/2009",
    "minimumYearRepaymentFormatted": "$23.00",
    "loanAmountFormatted": "$89.03"
  },
  "repayments": [],
  "inputs": {
    "incomeYearOfLoan": 2006,
    "fullTermOfAmalgamatedLoan": 7,
    "incomeYearOfEnquiring": 2009,
    "amalgamatedLoanNotPaidByEOIY": 89.03320432615034,
    "repayments": null,
    "lodgement_date": null
  },
  "idx": 5087
}