{
  "id": "2023-10-31T19:21:26.029Z0.3107276273218331",
  "alert": "Start of result\nResult\n\nMinimum yearly repayment not met.\n\nThe amount of the loan not repaid at the end of income year 2005-06 is $37.98.\n\nThe private company may be taken to pay a dividend under Division 7A to the shareholder or shareholder's associate because the amount repaid during income year 2005-06 in relation to the amalgamated loan is less than the minimum yearly repayment required.\n\nInterest received by the private company must be included in the income tax return for 2005-06.\n\nMinimum yearly repayment\n\n$7.00\n\nBenchmark interest rate\n\n7.3%\n\nOpening balance:\n\nDate: 30/06/2005\n\nBalance: $37.98\n\nDays: 365\n\nInterest: $2.77\n\nTotal repayments\n\n$0\n\nTotal interest\n\n$2.77\n\nTotal principal\n\n$0\n\nClosing balance\n\nDate: 30/06/2006\n\nBalance: $37.98",
  "outputs": {
    "enquiryRateFormatted": "7.3%",
    "enquiryYearEndMinusOneDisplay": "30/06/2005",
    "amalgamatedLoanNotPaidByEOIYFormatted": "$37.98",
    "openingBalancePayDays": "365",
    "openingBalanceInterestFormatted": "$2.77",
    "totalAmountOfRepaymentFormatted": "$0",
    "totalInterestFormatted": "$2.77",
    "principalFormatted": "$0",
    "enquiryYearEndDisplay": "30/06/2006",
    "minimumYearRepaymentFormatted": "$7.00",
    "loanAmountFormatted": "$37.98"
  },
  "repayments": [],
  "inputs": {
    "incomeYearOfLoan": 2005,
    "fullTermOfAmalgamatedLoan": 7,
    "incomeYearOfEnquiring": 2006,
    "amalgamatedLoanNotPaidByEOIY": 37.98935635587309,
    "repayments": null,
    "lodgement_date": "1/7/2005"
  },
  "idx": 5348
}