{
  "id": "2023-09-06T16:55:22.442Z0.6695193312957333",
  "alert": "Start of result\nResult\n\nMinimum yearly repayment met.\n\nThe amount of the loan not repaid at the end of income year 2009-10 is $7,393.56.\n\nThe amalgamated loan will not be taken to be a dividend because the total repayments made are equal to or greater than the minimum yearly repayment required for income year 2009-10.\n\nInterest received by the private company must be included in the income tax return for 2009-10.\n\nMinimum yearly repayment\n\n$4,524.00\n\nBenchmark interest rate\n\n5.75%\n\nOpening balance:\n\nDate: 30/06/2009\n\nBalance: $12,150.00\n\nDays: 331\n\nInterest: $633.55\n\nPayments\n\nDate: 28/05/2010\n\nAmount: $5,426.00\n\nBalance: $6,724.00\n\nDays: 34\n\nInterest: $36.01\n\n\n\n\nTotal repayments\n\n$5,426.00\n\nTotal interest\n\n$669.56\n\nTotal principal\n\n$4,756.44\n\nClosing balance\n\nDate: 30/06/2010\n\nBalance: $7,393.56",
  "outputs": {
    "enquiryRateFormatted": "5.75%",
    "enquiryYearEndMinusOneDisplay": "30/06/2009",
    "amalgamatedLoanNotPaidByEOIYFormatted": "$12,150.00",
    "openingBalancePayDays": "331",
    "openingBalanceInterestFormatted": "$633.55",
    "totalAmountOfRepaymentFormatted": "$5,426.00",
    "totalInterestFormatted": "$669.56",
    "principalFormatted": "$4,756.44",
    "enquiryYearEndDisplay": "30/06/2010",
    "minimumYearRepaymentFormatted": "$4,524.00"
  },
  "repayments": [
    {
      "rd": "28/5/2010",
      "ra": 5426
    }
  ],
  "inputs": {
    "incomeYearOfLoan": 2005,
    "fullTermOfAmalgamatedLoan": 7,
    "incomeYearOfEnquiring": 2010,
    "amalgamatedLoanNotPaidByEOIY": 12150,
    "repayments": null,
    "lodgement_date": null
  },
  "idx": 5532
}