{
  "id": "2023-10-31T19:04:17.149Z0.5453440393207309",
  "alert": "Start of result\nResult\n\nMinimum yearly repayment met.\n\nThe amount of the loan not repaid at the end of income year 2006-07 is $6,026.80.\n\n\u000b\n\nThe amalgamated loan will not be taken to be a dividend because the total repayments made are equal to or greater than the minimum yearly repayment required for income year 2006-07.\n\nInterest received by the private company must be included in the income tax return for 2006-07.\n\nMinimum yearly repayment\n\n$1,656.00\n\nBenchmark interest rate\n\n7.55%\n\nOpening balance:\n\nDate: 30/06/2006\n\nBalance: $12,166.00\n\nDays: 50\n\nInterest: $125.83\n\nPayments\n\nDate: 20/08/2006\n\nAmount: $6,626.00\n\nBalance: $5,540.00\n\nDays: 315\n\nInterest: $360.97\n\n\n\n\nTotal repayments\n\n$6,626.00\n\nTotal interest\n\n$486.80\n\nTotal principal\n\n$6,139.20\n\nClosing balance\n\nDate: 30/06/2007\n\nBalance: $6,026.80",
  "outputs": {
    "enquiryRateFormatted": "7.55%",
    "enquiryYearEndMinusOneDisplay": "30/06/2006",
    "amalgamatedLoanNotPaidByEOIYFormatted": "$12,166.00",
    "openingBalancePayDays": "50",
    "openingBalanceInterestFormatted": "$125.83",
    "totalAmountOfRepaymentFormatted": "$6,626.00",
    "totalInterestFormatted": "$486.80",
    "principalFormatted": "$6,139.20",
    "enquiryYearEndDisplay": "30/06/2007",
    "minimumYearRepaymentFormatted": "$1,656.00",
    "loanAmountFormatted": "$6,026.80"
  },
  "repayments": [
    {
      "rd": "20/8/2006",
      "ra": 6626
    }
  ],
  "inputs": {
    "incomeYearOfLoan": 2006,
    "fullTermOfAmalgamatedLoan": 4,
    "incomeYearOfEnquiring": 2007,
    "amalgamatedLoanNotPaidByEOIY": 12166,
    "repayments": null,
    "lodgement_date": "28/3/2007"
  },
  "idx": 4974
}