{
  "id": "2023-09-06T06:03:01.008Z0.9349746921556734",
  "alert": "Start of result\nResult\n\nMinimum yearly repayment met.\n\nThe amount of the loan not repaid at the end of income year 2012-13 is $1.86.\n\nThe amalgamated loan will not be taken to be a dividend because the total repayments made are equal to or greater than the minimum yearly repayment required for income year 2012-13.\n\nInterest received by the private company must be included in the income tax return for 2012-13.\n\nMinimum yearly repayment\n\n$15.00\n\nBenchmark interest rate\n\n7.05%\n\nOpening balance:\n\nDate: 30/06/2012\n\nBalance: $26.74\n\nDays: 361\n\nInterest: $1.86\n\nPayments\n\nDate: 27/06/2013\n\nAmount: $26.74\n\nBalance: $0\n\nDays: 4\n\nInterest: $0\n\n\n\n\nTotal repayments\n\n$26.74\n\nTotal interest\n\n$1.86\n\nTotal principal\n\n$24.88\n\nClosing balance\n\nDate: 30/06/2013\n\nBalance: $1.86",
  "outputs": {
    "enquiryRateFormatted": "7.05%",
    "enquiryYearEndMinusOneDisplay": "30/06/2012",
    "amalgamatedLoanNotPaidByEOIYFormatted": "$26.74",
    "openingBalancePayDays": "361",
    "openingBalanceInterestFormatted": "$1.86",
    "totalAmountOfRepaymentFormatted": "$26.74",
    "totalInterestFormatted": "$1.86",
    "principalFormatted": "$24.88",
    "enquiryYearEndDisplay": "30/06/2013",
    "minimumYearRepaymentFormatted": "$15.00"
  },
  "repayments": [
    {
      "rd": "27/6/2013",
      "ra": 26.741640914922755
    }
  ],
  "inputs": {
    "incomeYearOfLoan": 2011,
    "fullTermOfAmalgamatedLoan": 3,
    "incomeYearOfEnquiring": 2013,
    "amalgamatedLoanNotPaidByEOIY": 26.74164091492273,
    "repayments": null,
    "lodgement_date": null
  },
  "idx": 4440
}