{
  "id": "2023-09-05T01:34:09.911Z0.7326687356833399",
  "alert": "Start of result\nResult\n\nMinimum yearly repayment not met.\n\nThe amount of the loan not repaid at the end of income year 1999-00 is $12,286.00.\n\nThe private company may be taken to pay a dividend under Division 7A to the shareholder or shareholder's associate because the amount repaid during income year 1999-00 in relation to the amalgamated loan is less than the minimum yearly repayment required.\n\nInterest received by the private company must be included in the income tax return for 1999-00.\n\nMinimum yearly repayment\n\n$4,639.00\n\nBenchmark interest rate\n\n6.5%\n\nOpening balance:\n\nDate: 30/06/1999\n\nBalance: $12,286.00\n\nDays: 0\n\nInterest: $0\n\nPayments\n\nDate: 01/07/1999\n\nAmount: $292.00\n\nBalance: $11,994.00\n\nDays: 366\n\nInterest: $779.61\n\n\n\n\nTotal repayments\n\n$292.00\n\nTotal interest\n\n$779.61\n\nTotal principal\n\n$0\n\nClosing balance\n\nDate: 30/06/2000\n\nBalance: $12,286.00",
  "outputs": {
    "enquiryRateFormatted": "6.5%",
    "enquiryYearEndMinusOneDisplay": "30/06/1999",
    "amalgamatedLoanNotPaidByEOIYFormatted": "$12,286.00",
    "openingBalancePayDays": "0",
    "openingBalanceInterestFormatted": "$0",
    "totalAmountOfRepaymentFormatted": "$292.00",
    "totalInterestFormatted": "$779.61",
    "principalFormatted": "$0",
    "enquiryYearEndDisplay": "30/06/2000",
    "minimumYearRepaymentFormatted": "$4,639.00"
  },
  "repayments": [
    {
      "rd": "1/7/1999",
      "ra": 292
    }
  ],
  "inputs": {
    "incomeYearOfLoan": 1998,
    "fullTermOfAmalgamatedLoan": 4,
    "incomeYearOfEnquiring": 2000,
    "amalgamatedLoanNotPaidByEOIY": 12286,
    "repayments": null,
    "lodgement_date": null
  },
  "idx": 2577
}