{
  "id": "2023-10-31T18:28:03.586Z0.45431244285659556",
  "alert": "Start of result\nResult\n\nAmalgamated loan fully repaid.\n\nThe amalgamated loan has been paid in full.\u000bThe private company is not taken under Division 7A to pay a dividend to the shareholder or shareholder's associate.\n\nInterest received by the private company must be included in the income tax return for 2009-10.\n\nMinimum yearly repayment\n\n-$597.00\n\nBenchmark interest rate\n\n5.75%\n\nOpening balance:\n\nDate: 30/06/2009\n\nBalance: $122.02\n\nDays: 135\n\nInterest: $2.60\n\nPayments\n\nDate: 13/11/2009\n\nAmount: $1,220.27\n\nBalance: $0\n\nDays: 230\n\nInterest: $0\n\n\n\n\nTotal repayments\n\n$1,220.27\n\nTotal interest\n\n$2.60\n\nTotal principal\n\n$1,217.67\n\nClosing balance\n\nDate: 30/06/2010\n\nBalance: $0",
  "outputs": {
    "enquiryRateFormatted": "5.75%",
    "enquiryYearEndMinusOneDisplay": "30/06/2009",
    "amalgamatedLoanNotPaidByEOIYFormatted": "$122.02",
    "openingBalancePayDays": "135",
    "openingBalanceInterestFormatted": "$2.60",
    "totalAmountOfRepaymentFormatted": "$1,220.27",
    "totalInterestFormatted": "$2.60",
    "principalFormatted": "$1,217.67",
    "enquiryYearEndDisplay": "30/06/2010",
    "minimumYearRepaymentFormatted": "-$597.00",
    "loanAmountFormatted": "$0"
  },
  "repayments": [
    {
      "rd": "13/11/2009",
      "ra": 1220.2717703392755
    }
  ],
  "inputs": {
    "incomeYearOfLoan": 2009,
    "fullTermOfAmalgamatedLoan": 2,
    "incomeYearOfEnquiring": 2010,
    "amalgamatedLoanNotPaidByEOIY": 122.02717703392749,
    "repayments": null,
    "lodgement_date": "27/4/2010"
  },
  "idx": 4025
}