{
  "id": "2023-10-31T17:28:58.201Z0.11867275794788901",
  "alert": "Start of result\nResult\n\nMinimum yearly repayment not met.\n\nThe amount of the loan not repaid at the end of income year 2020-21 is $6,905.87.\n\nThe private company may be taken to pay a dividend under Division 7A to the shareholder or shareholder's associate because the amount repaid during income year 2020-21 in relation to the amalgamated loan is less than the minimum yearly repayment required.\n\nInterest received by the private company must be included in the income tax return for 2020-21.\n\nMinimum yearly repayment\n\n$4,654.00\n\nBenchmark interest rate\n\n4.52%\n\nOpening balance:\n\nDate: 30/06/2020\n\nBalance: $8,713.00\n\nDays: 306\n\nInterest: $330.17\n\nPayments\n\nDate: 03/05/2021\n\nAmount: $2,185.00\n\nBalance: $6,528.00\n\nDays: 59\n\nInterest: $47.70\n\n\n\n\nTotal repayments\n\n$2,185.00\n\nTotal interest\n\n$377.87\n\nTotal principal\n\n$1,807.13\n\nClosing balance\n\nDate: 30/06/2021\n\nBalance: $6,905.87",
  "outputs": {
    "enquiryRateFormatted": "4.52%",
    "enquiryYearEndMinusOneDisplay": "30/06/2020",
    "amalgamatedLoanNotPaidByEOIYFormatted": "$8,713.00",
    "openingBalancePayDays": "306",
    "openingBalanceInterestFormatted": "$330.17",
    "totalAmountOfRepaymentFormatted": "$2,185.00",
    "totalInterestFormatted": "$377.87",
    "principalFormatted": "$1,807.13",
    "enquiryYearEndDisplay": "30/06/2021",
    "minimumYearRepaymentFormatted": "$4,654.00",
    "loanAmountFormatted": "$6,905.87"
  },
  "repayments": [
    {
      "rd": "3/5/2021",
      "ra": 2185
    }
  ],
  "inputs": {
    "incomeYearOfLoan": 2017,
    "fullTermOfAmalgamatedLoan": 5,
    "incomeYearOfEnquiring": 2021,
    "amalgamatedLoanNotPaidByEOIY": 8713,
    "repayments": null,
    "lodgement_date": null
  },
  "idx": 1639
}