{
  "id": "2023-10-31T19:27:12.473Z0.22833271309721204",
  "alert": "Start of result\nResult\n\nAmalgamated loan fully repaid.\n\nThe amalgamated loan has been paid in full.\u000bThe private company is not taken under Division 7A to pay a dividend to the shareholder or shareholder's associate.\n\nInterest received by the private company must be included in the income tax return for 2006-07.\n\nMinimum yearly repayment\n\n$4,091.00\n\nBenchmark interest rate\n\n7.55%\n\nOpening balance:\n\nDate: 30/06/2006\n\nBalance: $7,340.00\n\nDays: 92\n\nInterest: $139.68\n\nPayments\n\nDate: 01/10/2006\n\nAmount: $4,552.00\n\nBalance: $2,788.00\n\nDays: 15\n\nInterest: $8.65\n\n\n\n\nDate: 16/10/2006\n\nAmount: $4,279.00\n\nBalance: $0\n\nDays: 4\n\nInterest: $0\n\n\n\n\nDate: 20/10/2006\n\nAmount: $3,491.00\n\nBalance: $0\n\nDays: 5\n\nInterest: $0\n\n\n\n\nDate: 25/10/2006\n\nAmount: $7,141.00\n\nBalance: $0\n\nDays: 249\n\nInterest: $0\n\n\n\n\nTotal repayments\n\n$19,463.00\n\nTotal interest\n\n$148.33\n\nTotal principal\n\n$19,314.67\n\nClosing balance\n\nDate: 30/06/2007\n\nBalance: $0",
  "outputs": {
    "enquiryRateFormatted": "7.55%",
    "enquiryYearEndMinusOneDisplay": "30/06/2006",
    "amalgamatedLoanNotPaidByEOIYFormatted": "$7,340.00",
    "openingBalancePayDays": "92",
    "openingBalanceInterestFormatted": "$139.68",
    "totalAmountOfRepaymentFormatted": "$19,463.00",
    "totalInterestFormatted": "$148.33",
    "principalFormatted": "$19,314.67",
    "enquiryYearEndDisplay": "30/06/2007",
    "minimumYearRepaymentFormatted": "$4,091.00",
    "loanAmountFormatted": "$0"
  },
  "repayments": [
    {
      "rd": "1/10/2006",
      "ra": 4552
    },
    {
      "rd": "16/10/2006",
      "ra": 4279
    },
    {
      "rd": "20/10/2006",
      "ra": 3491
    },
    {
      "rd": "25/10/2006",
      "ra": 7141
    }
  ],
  "inputs": {
    "incomeYearOfLoan": 2004,
    "fullTermOfAmalgamatedLoan": 4,
    "incomeYearOfEnquiring": 2007,
    "amalgamatedLoanNotPaidByEOIY": 7340,
    "repayments": null,
    "lodgement_date": null
  },
  "idx": 5473
}