{
  "id": "2023-09-06T15:10:17.497Z0.23078115747981354",
  "alert": "Start of result\nResult\n\nMinimum yearly repayment not met.\n\nThe amount of the loan not repaid at the end of income year 2012-13 is $131.01.\n\nThe private company may be taken to pay a dividend under Division 7A to the shareholder or shareholder's associate because the amount repaid during income year 2012-13 in relation to the amalgamated loan is less than the minimum yearly repayment required.\n\nInterest received by the private company must be included in the income tax return for 2012-13.\n\nMinimum yearly repayment\n\n$3,822.00\n\nBenchmark interest rate\n\n7.05%\n\nOpening balance:\n\nDate: 30/06/2012\n\nBalance: $3,570.00\n\nDays: 190\n\nInterest: $131.01\n\nPayments\n\nDate: 07/01/2013\n\nAmount: $3,570.00\n\nBalance: $0\n\nDays: 175\n\nInterest: $0\n\n\n\n\nTotal repayments\n\n$3,570.00\n\nTotal interest\n\n$131.01\n\nTotal principal\n\n$3,438.99\n\nClosing balance\n\nDate: 30/06/2013\n\nBalance: $131.01",
  "outputs": {
    "enquiryRateFormatted": "7.05%",
    "enquiryYearEndMinusOneDisplay": "30/06/2012",
    "amalgamatedLoanNotPaidByEOIYFormatted": "$3,570.00",
    "openingBalancePayDays": "190",
    "openingBalanceInterestFormatted": "$131.01",
    "totalAmountOfRepaymentFormatted": "$3,570.00",
    "totalInterestFormatted": "$131.01",
    "principalFormatted": "$3,438.99",
    "enquiryYearEndDisplay": "30/06/2013",
    "minimumYearRepaymentFormatted": "$3,822.00"
  },
  "repayments": [
    {
      "rd": "7/1/2013",
      "ra": 3570
    }
  ],
  "inputs": {
    "incomeYearOfLoan": 2006,
    "fullTermOfAmalgamatedLoan": 7,
    "incomeYearOfEnquiring": 2013,
    "amalgamatedLoanNotPaidByEOIY": 3570,
    "repayments": null,
    "lodgement_date": null
  },
  "idx": 7759
}