{
  "id": "2023-09-04T16:29:19.188Z0.9632497358640824",
  "alert": "Start of result\nResult\n\nMinimum yearly repayment not met.\n\nThe amount of the loan not repaid at the end of income year 2018-19 is $11,006,853.80.\n\nThe private company may be taken to pay a dividend under Division 7A to the shareholder or shareholder's associate because the amount repaid during income year 2018-19 in relation to the amalgamated loan is less than the minimum yearly repayment required.\n\nInterest received by the private company must be included in the income tax return for 2018-19.\n\nMinimum yearly repayment\n\n$3,118,497.00\n\nBenchmark interest rate\n\n5.2%\n\nOpening balance:\n\nDate: 30/06/2018\n\nBalance: $11,006,853.80\n\nDays: 365\n\nInterest: $572,356.40\n\nTotal repayments\n\n$0\n\nTotal interest\n\n$572,356.40\n\nTotal principal\n\n$0\n\nClosing balance\n\nDate: 30/06/2019\n\nBalance: $11,006,853.80",
  "outputs": {
    "enquiryRateFormatted": "5.2%",
    "enquiryYearEndMinusOneDisplay": "30/06/2018",
    "amalgamatedLoanNotPaidByEOIYFormatted": "$11,006,853.80",
    "openingBalancePayDays": "365",
    "openingBalanceInterestFormatted": "$572,356.40",
    "totalAmountOfRepaymentFormatted": "$0",
    "totalInterestFormatted": "$572,356.40",
    "principalFormatted": "$0",
    "enquiryYearEndDisplay": "30/06/2019",
    "minimumYearRepaymentFormatted": "$3,118,497.00"
  },
  "repayments": [],
  "inputs": {
    "incomeYearOfLoan": 2018,
    "fullTermOfAmalgamatedLoan": 4,
    "incomeYearOfEnquiring": 2019,
    "amalgamatedLoanNotPaidByEOIY": 11006853.801509619,
    "repayments": null,
    "lodgement_date": "9/10/2018"
  },
  "idx": 616
}