{
  "id": "2023-09-05T20:36:01.010Z0.6589228235374913",
  "alert": "Start of result\nResult\n\nMinimum yearly repayment not met.\n\nThe amount of the loan not repaid at the end of income year 2018-19 is $9,994.54.\n\nThe private company may be taken to pay a dividend under Division 7A to the shareholder or shareholder's associate because the amount repaid during income year 2018-19 in relation to the amalgamated loan is less than the minimum yearly repayment required.\n\nInterest received by the private company must be included in the income tax return for 2018-19.\n\nMinimum yearly repayment\n\n$2,070.00\n\nBenchmark interest rate\n\n5.2%\n\nOpening balance:\n\nDate: 30/06/2018\n\nBalance: $10,441.00\n\nDays: 135\n\nInterest: $200.81\n\nPayments\n\nDate: 13/11/2018\n\nAmount: $958.00\n\nBalance: $9,483.00\n\nDays: 230\n\nInterest: $310.73\n\n\n\n\nTotal repayments\n\n$958.00\n\nTotal interest\n\n$511.54\n\nTotal principal\n\n$446.46\n\nClosing balance\n\nDate: 30/06/2019\n\nBalance: $9,994.54",
  "outputs": {
    "enquiryRateFormatted": "5.2%",
    "enquiryYearEndMinusOneDisplay": "30/06/2018",
    "amalgamatedLoanNotPaidByEOIYFormatted": "$10,441.00",
    "openingBalancePayDays": "135",
    "openingBalanceInterestFormatted": "$200.81",
    "totalAmountOfRepaymentFormatted": "$958.00",
    "totalInterestFormatted": "$511.54",
    "principalFormatted": "$446.46",
    "enquiryYearEndDisplay": "30/06/2019",
    "minimumYearRepaymentFormatted": "$2,070.00"
  },
  "repayments": [
    {
      "rd": "13/11/2018",
      "ra": 958
    }
  ],
  "inputs": {
    "incomeYearOfLoan": 2017,
    "fullTermOfAmalgamatedLoan": 7,
    "incomeYearOfEnquiring": 2019,
    "amalgamatedLoanNotPaidByEOIY": 10441,
    "repayments": null,
    "lodgement_date": null
  },
  "idx": 6643
}