{
  "id": "2023-09-05T22:08:20.200Z0.8934351487825167",
  "alert": "Start of result\nResult\n\nMinimum yearly repayment met.\n\nThe amount of the loan not repaid at the end of income year 2016-17 is $33.76.\n\nThe amalgamated loan will not be taken to be a dividend because the total repayments made are equal to or greater than the minimum yearly repayment required for income year 2016-17.\n\nInterest received by the private company must be included in the income tax return for 2016-17.\n\nMinimum yearly repayment\n\n$9.00\n\nBenchmark interest rate\n\n5.4%\n\nOpening balance:\n\nDate: 30/06/2016\n\nBalance: $93.31\n\nDays: 195\n\nInterest: $2.69\n\nPayments\n\nDate: 12/01/2017\n\nAmount: $63.00\n\nBalance: $30.31\n\nDays: 170\n\nInterest: $0.76\n\n\n\n\nTotal repayments\n\n$63.00\n\nTotal interest\n\n$3.45\n\nTotal principal\n\n$59.55\n\nClosing balance\n\nDate: 30/06/2017\n\nBalance: $33.76",
  "outputs": {
    "enquiryRateFormatted": "5.4%",
    "enquiryYearEndMinusOneDisplay": "30/06/2016",
    "amalgamatedLoanNotPaidByEOIYFormatted": "$93.31",
    "openingBalancePayDays": "195",
    "openingBalanceInterestFormatted": "$2.69",
    "totalAmountOfRepaymentFormatted": "$63.00",
    "totalInterestFormatted": "$3.45",
    "principalFormatted": "$59.55",
    "enquiryYearEndDisplay": "30/06/2017",
    "minimumYearRepaymentFormatted": "$9.00"
  },
  "repayments": [
    {
      "rd": "12/1/2017",
      "ra": 63
    }
  ],
  "inputs": {
    "incomeYearOfLoan": 2016,
    "fullTermOfAmalgamatedLoan": 4,
    "incomeYearOfEnquiring": 2017,
    "amalgamatedLoanNotPaidByEOIY": 93.31193060577698,
    "repayments": null,
    "lodgement_date": "6/6/2017"
  },
  "idx": 3280
}