{
  "id": "2023-10-31T17:49:40.002Z0.0519774256757084",
  "alert": "Start of result\nResult\n\nMinimum yearly repayment met.\n\nThe amount of the loan not repaid at the end of income year 2017-18 is $4,146.58.\n\n\u000b\n\nThe amalgamated loan will not be taken to be a dividend because the total repayments made are equal to or greater than the minimum yearly repayment required for income year 2017-18.\n\nInterest received by the private company must be included in the income tax return for 2017-18.\n\nMinimum yearly repayment\n\n$6,304.00\n\nBenchmark interest rate\n\n5.3%\n\nOpening balance:\n\nDate: 30/06/2017\n\nBalance: $11,672.00\n\nDays: 241\n\nInterest: $408.46\n\nPayments\n\nDate: 27/02/2018\n\nAmount: $8,000.00\n\nBalance: $3,672.00\n\nDays: 124\n\nInterest: $66.12\n\n\n\n\nTotal repayments\n\n$8,000.00\n\nTotal interest\n\n$474.58\n\nTotal principal\n\n$7,525.42\n\nClosing balance\n\nDate: 30/06/2018\n\nBalance: $4,146.58",
  "outputs": {
    "enquiryRateFormatted": "5.3%",
    "enquiryYearEndMinusOneDisplay": "30/06/2017",
    "amalgamatedLoanNotPaidByEOIYFormatted": "$11,672.00",
    "openingBalancePayDays": "241",
    "openingBalanceInterestFormatted": "$408.46",
    "totalAmountOfRepaymentFormatted": "$8,000.00",
    "totalInterestFormatted": "$474.58",
    "principalFormatted": "$7,525.42",
    "enquiryYearEndDisplay": "30/06/2018",
    "minimumYearRepaymentFormatted": "$6,304.00",
    "loanAmountFormatted": "$4,146.58"
  },
  "repayments": [
    {
      "rd": "27/2/2018",
      "ra": 8000
    }
  ],
  "inputs": {
    "incomeYearOfLoan": 2014,
    "fullTermOfAmalgamatedLoan": 5,
    "incomeYearOfEnquiring": 2018,
    "amalgamatedLoanNotPaidByEOIY": 11672,
    "repayments": null,
    "lodgement_date": null
  },
  "idx": 2676
}