{
  "id": "2023-10-31T17:47:11.992Z0.26637498543859617",
  "alert": "Start of result\nResult\n\nMinimum yearly repayment not met.\n\nThe amount of the loan not repaid at the end of income year 2015-16 is $7,524.36.\n\nThe private company may be taken to pay a dividend under Division 7A to the shareholder or shareholder's associate because the amount repaid during income year 2015-16 in relation to the amalgamated loan is less than the minimum yearly repayment required.\n\nInterest received by the private company must be included in the income tax return for 2015-16.\n\nMinimum yearly repayment\n\n$3,192.00\n\nBenchmark interest rate\n\n5.45%\n\nOpening balance:\n\nDate: 30/06/2015\n\nBalance: $8,621.00\n\nDays: 87\n\nInterest: $111.68\n\nPayments\n\nDate: 26/09/2015\n\nAmount: $1,504.00\n\nBalance: $7,117.00\n\nDays: 279\n\nInterest: $295.68\n\n\n\n\nTotal repayments\n\n$1,504.00\n\nTotal interest\n\n$407.36\n\nTotal principal\n\n$1,096.64\n\nClosing balance\n\nDate: 30/06/2016\n\nBalance: $7,524.36",
  "outputs": {
    "enquiryRateFormatted": "5.45%",
    "enquiryYearEndMinusOneDisplay": "30/06/2015",
    "amalgamatedLoanNotPaidByEOIYFormatted": "$8,621.00",
    "openingBalancePayDays": "87",
    "openingBalanceInterestFormatted": "$111.68",
    "totalAmountOfRepaymentFormatted": "$1,504.00",
    "totalInterestFormatted": "$407.36",
    "principalFormatted": "$1,096.64",
    "enquiryYearEndDisplay": "30/06/2016",
    "minimumYearRepaymentFormatted": "$3,192.00",
    "loanAmountFormatted": "$7,524.36"
  },
  "repayments": [
    {
      "rd": "26/9/2015",
      "ra": 1504
    }
  ],
  "inputs": {
    "incomeYearOfLoan": 2014,
    "fullTermOfAmalgamatedLoan": 4,
    "incomeYearOfEnquiring": 2016,
    "amalgamatedLoanNotPaidByEOIY": 8621,
    "repayments": null,
    "lodgement_date": null
  },
  "idx": 2560
}