{
  "id": "2023-10-31T17:51:53.644Z0.14112412743762726",
  "alert": "Start of result\nResult\n\nMinimum yearly repayment not met.\n\nThe amount of the loan not repaid at the end of income year 2019-20 is $12,094.00.\n\nThe private company may be taken to pay a dividend under Division 7A to the shareholder or shareholder's associate because the amount repaid during income year 2019-20 in relation to the amalgamated loan is less than the minimum yearly repayment required.\n\nInterest received by the private company must be included in the income tax return for 2019-20.\n\nMinimum yearly repayment\n\n$6,538.00\n\nBenchmark interest rate\n\n5.37%\n\nOpening balance:\n\nDate: 30/06/2019\n\nBalance: $12,094.00\n\nDays: 366\n\nInterest: $649.45\n\nTotal repayments\n\n$0\n\nTotal interest\n\n$649.45\n\nTotal principal\n\n$0\n\nClosing balance\n\nDate: 30/06/2020\n\nBalance: $12,094.00",
  "outputs": {
    "enquiryRateFormatted": "5.37%",
    "enquiryYearEndMinusOneDisplay": "30/06/2019",
    "amalgamatedLoanNotPaidByEOIYFormatted": "$12,094.00",
    "openingBalancePayDays": "366",
    "openingBalanceInterestFormatted": "$649.45",
    "totalAmountOfRepaymentFormatted": "$0",
    "totalInterestFormatted": "$649.45",
    "principalFormatted": "$0",
    "enquiryYearEndDisplay": "30/06/2020",
    "minimumYearRepaymentFormatted": "$6,538.00",
    "loanAmountFormatted": "$12,094.00"
  },
  "repayments": [],
  "inputs": {
    "incomeYearOfLoan": 2014,
    "fullTermOfAmalgamatedLoan": 7,
    "incomeYearOfEnquiring": 2020,
    "amalgamatedLoanNotPaidByEOIY": 12094,
    "repayments": null,
    "lodgement_date": null
  },
  "idx": 2767
}