{
  "id": "2023-09-04T23:27:29.259Z0.2422185685928211",
  "alert": "Start of result\nResult\n\nMinimum yearly repayment not met.\n\nThe amount of the loan not repaid at the end of income year 1999-00 is $5,917.00.\n\nThe private company may be taken to pay a dividend under Division 7A to the shareholder or shareholder's associate because the amount repaid during income year 1999-00 in relation to the amalgamated loan is less than the minimum yearly repayment required.\n\nInterest received by the private company must be included in the income tax return for 1999-00.\n\nMinimum yearly repayment\n\n$1,727.00\n\nBenchmark interest rate\n\n6.5%\n\nOpening balance:\n\nDate: 30/06/1999\n\nBalance: $5,917.00\n\nDays: 366\n\nInterest: $384.61\n\nTotal repayments\n\n$0\n\nTotal interest\n\n$384.61\n\nTotal principal\n\n$0\n\nClosing balance\n\nDate: 30/06/2000\n\nBalance: $5,917.00",
  "outputs": {
    "enquiryRateFormatted": "6.5%",
    "enquiryYearEndMinusOneDisplay": "30/06/1999",
    "amalgamatedLoanNotPaidByEOIYFormatted": "$5,917.00",
    "openingBalancePayDays": "366",
    "openingBalanceInterestFormatted": "$384.61",
    "totalAmountOfRepaymentFormatted": "$0",
    "totalInterestFormatted": "$384.61",
    "principalFormatted": "$0",
    "enquiryYearEndDisplay": "30/06/2000",
    "minimumYearRepaymentFormatted": "$1,727.00"
  },
  "repayments": [],
  "inputs": {
    "incomeYearOfLoan": 1999,
    "fullTermOfAmalgamatedLoan": 4,
    "incomeYearOfEnquiring": 2000,
    "amalgamatedLoanNotPaidByEOIY": 5917,
    "repayments": null,
    "lodgement_date": "25/4/2000"
  },
  "idx": 3250
}