{
  "id": "2023-10-31T20:17:04.166Z0.5821953475801889",
  "alert": "Start of result\nResult\n\nAmalgamated loan fully repaid.\n\nThe amalgamated loan has been paid in full.\u000bThe private company is not taken under Division 7A to pay a dividend to the shareholder or shareholder's associate.\n\nInterest received by the private company must be included in the income tax return for 2004-05.\n\nMinimum yearly repayment\n\n$19.00\n\nBenchmark interest rate\n\n7.05%\n\nOpening balance:\n\nDate: 30/06/2004\n\nBalance: $34.02\n\nDays: 276\n\nInterest: $1.81\n\nPayments\n\nDate: 03/04/2005\n\nAmount: $340.24\n\nBalance: $0\n\nDays: 89\n\nInterest: $0\n\n\n\n\nTotal repayments\n\n$340.24\n\nTotal interest\n\n$1.81\n\nTotal principal\n\n$338.43\n\nClosing balance\n\nDate: 30/06/2005\n\nBalance: $0",
  "outputs": {
    "enquiryRateFormatted": "7.05%",
    "enquiryYearEndMinusOneDisplay": "30/06/2004",
    "amalgamatedLoanNotPaidByEOIYFormatted": "$34.02",
    "openingBalancePayDays": "276",
    "openingBalanceInterestFormatted": "$1.81",
    "totalAmountOfRepaymentFormatted": "$340.24",
    "totalInterestFormatted": "$1.81",
    "principalFormatted": "$338.43",
    "enquiryYearEndDisplay": "30/06/2005",
    "minimumYearRepaymentFormatted": "$19.00",
    "loanAmountFormatted": "$0"
  },
  "repayments": [
    {
      "rd": "3/4/2005",
      "ra": 340.24383777484127
    }
  ],
  "inputs": {
    "incomeYearOfLoan": 2001,
    "fullTermOfAmalgamatedLoan": 5,
    "incomeYearOfEnquiring": 2005,
    "amalgamatedLoanNotPaidByEOIY": 34.02438377748413,
    "repayments": null,
    "lodgement_date": null
  },
  "idx": 6337
}