{
  "id": "2023-10-31T18:12:43.730Z0.035632023156425885",
  "alert": "Start of result\nResult\n\nAmalgamated loan fully repaid.\n\nThe amalgamated loan has been paid in full.\u000bThe private company is not taken under Division 7A to pay a dividend to the shareholder or shareholder's associate.\n\nInterest received by the private company must be included in the income tax return for 2012-13.\n\nMinimum yearly repayment\n\n$680.00\n\nBenchmark interest rate\n\n7.05%\n\nOpening balance:\n\nDate: 30/06/2012\n\nBalance: $2,784.00\n\nDays: 30\n\nInterest: $16.13\n\nPayments\n\nDate: 31/07/2012\n\nAmount: $6,042.00\n\nBalance: $0\n\nDays: 335\n\nInterest: $0\n\n\n\n\nTotal repayments\n\n$6,042.00\n\nTotal interest\n\n$16.13\n\nTotal principal\n\n$6,025.87\n\nClosing balance\n\nDate: 30/06/2013\n\nBalance: $0",
  "outputs": {
    "enquiryRateFormatted": "7.05%",
    "enquiryYearEndMinusOneDisplay": "30/06/2012",
    "amalgamatedLoanNotPaidByEOIYFormatted": "$2,784.00",
    "openingBalancePayDays": "30",
    "openingBalanceInterestFormatted": "$16.13",
    "totalAmountOfRepaymentFormatted": "$6,042.00",
    "totalInterestFormatted": "$16.13",
    "principalFormatted": "$6,025.87",
    "enquiryYearEndDisplay": "30/06/2013",
    "minimumYearRepaymentFormatted": "$680.00",
    "loanAmountFormatted": "$0"
  },
  "repayments": [
    {
      "rd": "31/7/2012",
      "ra": 6042
    }
  ],
  "inputs": {
    "incomeYearOfLoan": 2011,
    "fullTermOfAmalgamatedLoan": 6,
    "incomeYearOfEnquiring": 2013,
    "amalgamatedLoanNotPaidByEOIY": 2784,
    "repayments": null,
    "lodgement_date": null
  },
  "idx": 3545
}