{
  "id": "2023-10-31T18:30:29.229Z0.4764913600175711",
  "alert": "Start of result\nResult\n\nAmalgamated loan fully repaid.\n\nThe amalgamated loan has been paid in full.\u000bThe private company is not taken under Division 7A to pay a dividend to the shareholder or shareholder's associate.\n\nInterest received by the private company must be included in the income tax return for 2009-10.\n\nMinimum yearly repayment\n\n-$57.00\n\nBenchmark interest rate\n\n5.75%\n\nOpening balance:\n\nDate: 30/06/2009\n\nBalance: $21.95\n\nDays: 274\n\nInterest: $0.95\n\nPayments\n\nDate: 01/04/2010\n\nAmount: $219.57\n\nBalance: $0\n\nDays: 91\n\nInterest: $0\n\n\n\n\nTotal repayments\n\n$219.57\n\nTotal interest\n\n$0.95\n\nTotal principal\n\n$218.62\n\nClosing balance\n\nDate: 30/06/2010\n\nBalance: $0",
  "outputs": {
    "enquiryRateFormatted": "5.75%",
    "enquiryYearEndMinusOneDisplay": "30/06/2009",
    "amalgamatedLoanNotPaidByEOIYFormatted": "$21.95",
    "openingBalancePayDays": "274",
    "openingBalanceInterestFormatted": "$0.95",
    "totalAmountOfRepaymentFormatted": "$219.57",
    "totalInterestFormatted": "$0.95",
    "principalFormatted": "$218.62",
    "enquiryYearEndDisplay": "30/06/2010",
    "minimumYearRepaymentFormatted": "-$57.00",
    "loanAmountFormatted": "$0"
  },
  "repayments": [
    {
      "rd": "1/4/2010",
      "ra": 219.5773687068579
    }
  ],
  "inputs": {
    "incomeYearOfLoan": 2009,
    "fullTermOfAmalgamatedLoan": 4,
    "incomeYearOfEnquiring": 2010,
    "amalgamatedLoanNotPaidByEOIY": 21.95773687068579,
    "repayments": null,
    "lodgement_date": "30/6/2010"
  },
  "idx": 4095
}