{
  "id": "2023-10-31T18:28:17.185Z0.7960837147323958",
  "alert": "Start of result\nResult\n\nAmalgamated loan fully repaid.\n\nThe amalgamated loan has been paid in full.\u000bThe private company is not taken under Division 7A to pay a dividend to the shareholder or shareholder's associate.\n\nInterest received by the private company must be included in the income tax return for 2011-12.\n\nMinimum yearly repayment\n\n$89.00\n\nBenchmark interest rate\n\n7.8%\n\nOpening balance:\n\nDate: 30/06/2011\n\nBalance: $82.65\n\nDays: 60\n\nInterest: $1.06\n\nPayments\n\nDate: 30/08/2011\n\nAmount: $826.52\n\nBalance: $0\n\nDays: 306\n\nInterest: $0\n\n\n\n\nTotal repayments\n\n$826.52\n\nTotal interest\n\n$1.06\n\nTotal principal\n\n$825.46\n\nClosing balance\n\nDate: 30/06/2012\n\nBalance: $0",
  "outputs": {
    "enquiryRateFormatted": "7.8%",
    "enquiryYearEndMinusOneDisplay": "30/06/2011",
    "amalgamatedLoanNotPaidByEOIYFormatted": "$82.65",
    "openingBalancePayDays": "60",
    "openingBalanceInterestFormatted": "$1.06",
    "totalAmountOfRepaymentFormatted": "$826.52",
    "totalInterestFormatted": "$1.06",
    "principalFormatted": "$825.46",
    "enquiryYearEndDisplay": "30/06/2012",
    "minimumYearRepaymentFormatted": "$89.00",
    "loanAmountFormatted": "$0"
  },
  "repayments": [
    {
      "rd": "30/8/2011",
      "ra": 826.5266527923704
    }
  ],
  "inputs": {
    "incomeYearOfLoan": 2009,
    "fullTermOfAmalgamatedLoan": 3,
    "incomeYearOfEnquiring": 2012,
    "amalgamatedLoanNotPaidByEOIY": 82.65266527923708,
    "repayments": null,
    "lodgement_date": null
  },
  "idx": 4030
}