{
  "id": "2023-10-31T18:23:15.202Z0.4099683175206713",
  "alert": "Start of result\nResult\n\nAmalgamated loan fully repaid.\n\nThe amalgamated loan has been paid in full.\u000bThe private company is not taken under Division 7A to pay a dividend to the shareholder or shareholder's associate.\n\nInterest received by the private company must be included in the income tax return for 2012-13.\n\nMinimum yearly repayment\n\n$31.00\n\nBenchmark interest rate\n\n7.05%\n\nOpening balance:\n\nDate: 30/06/2012\n\nBalance: $104.90\n\nDays: 93\n\nInterest: $1.88\n\nPayments\n\nDate: 02/10/2012\n\nAmount: $1,049.02\n\nBalance: $0\n\nDays: 272\n\nInterest: $0\n\n\n\n\nTotal repayments\n\n$1,049.02\n\nTotal interest\n\n$1.88\n\nTotal principal\n\n$1,047.14\n\nClosing balance\n\nDate: 30/06/2013\n\nBalance: $0",
  "outputs": {
    "enquiryRateFormatted": "7.05%",
    "enquiryYearEndMinusOneDisplay": "30/06/2012",
    "amalgamatedLoanNotPaidByEOIYFormatted": "$104.90",
    "openingBalancePayDays": "93",
    "openingBalanceInterestFormatted": "$1.88",
    "totalAmountOfRepaymentFormatted": "$1,049.02",
    "totalInterestFormatted": "$1.88",
    "principalFormatted": "$1,047.14",
    "enquiryYearEndDisplay": "30/06/2013",
    "minimumYearRepaymentFormatted": "$31.00",
    "loanAmountFormatted": "$0"
  },
  "repayments": [
    {
      "rd": "2/10/2012",
      "ra": 1049.0211112389443
    }
  ],
  "inputs": {
    "incomeYearOfLoan": 2010,
    "fullTermOfAmalgamatedLoan": 6,
    "incomeYearOfEnquiring": 2013,
    "amalgamatedLoanNotPaidByEOIY": 104.90211112389439,
    "repayments": null,
    "lodgement_date": null
  },
  "idx": 3888
}