{
  "id": "2023-09-06T00:03:16.173Z0.3577715909188053",
  "alert": "Start of result\nResult\n\nMinimum yearly repayment met.\n\nThe amount of the loan not repaid at the end of income year 2017-18 is $4.99.\n\nThe amalgamated loan will not be taken to be a dividend because the total repayments made are equal to or greater than the minimum yearly repayment required for income year 2017-18.\n\nInterest received by the private company must be included in the income tax return for 2017-18.\n\nMinimum yearly repayment\n\n$28.00\n\nBenchmark interest rate\n\n5.3%\n\nOpening balance:\n\nDate: 30/06/2017\n\nBalance: $97.44\n\nDays: 353\n\nInterest: $4.99\n\nPayments\n\nDate: 19/06/2018\n\nAmount: $97.44\n\nBalance: $0\n\nDays: 12\n\nInterest: $0\n\n\n\n\nTotal repayments\n\n$97.44\n\nTotal interest\n\n$4.99\n\nTotal principal\n\n$92.45\n\nClosing balance\n\nDate: 30/06/2018\n\nBalance: $4.99",
  "outputs": {
    "enquiryRateFormatted": "5.3%",
    "enquiryYearEndMinusOneDisplay": "30/06/2017",
    "amalgamatedLoanNotPaidByEOIYFormatted": "$97.44",
    "openingBalancePayDays": "353",
    "openingBalanceInterestFormatted": "$4.99",
    "totalAmountOfRepaymentFormatted": "$97.44",
    "totalInterestFormatted": "$4.99",
    "principalFormatted": "$92.45",
    "enquiryYearEndDisplay": "30/06/2018",
    "minimumYearRepaymentFormatted": "$28.00"
  },
  "repayments": [
    {
      "rd": "19/6/2018",
      "ra": 97.44127602577464
    }
  ],
  "inputs": {
    "incomeYearOfLoan": 2015,
    "fullTermOfAmalgamatedLoan": 6,
    "incomeYearOfEnquiring": 2018,
    "amalgamatedLoanNotPaidByEOIY": 97.44127602577446,
    "repayments": null,
    "lodgement_date": null
  },
  "idx": 1485
}