{
  "id": "2023-10-31T20:43:52.902Z0.5302707153735084",
  "alert": "Start of result\nResult\n\nMinimum yearly repayment met.\n\nThe amount of the loan not repaid at the end of income year 2003-04 is $2,741.85.\n\n\u000b\n\nThe amalgamated loan will not be taken to be a dividend because the total repayments made are equal to or greater than the minimum yearly repayment required for income year 2003-04.\n\nInterest received by the private company must be included in the income tax return for 2003-04.\n\nMinimum yearly repayment\n\n$1,327.00\n\nBenchmark interest rate\n\n6.55%\n\nOpening balance:\n\nDate: 30/06/2003\n\nBalance: $4,541.00\n\nDays: 264\n\nInterest: $214.54\n\nPayments\n\nDate: 21/03/2004\n\nAmount: $2,059.00\n\nBalance: $2,482.00\n\nDays: 102\n\nInterest: $45.31\n\n\n\n\nTotal repayments\n\n$2,059.00\n\nTotal interest\n\n$259.85\n\nTotal principal\n\n$1,799.15\n\nClosing balance\n\nDate: 30/06/2004\n\nBalance: $2,741.85",
  "outputs": {
    "enquiryRateFormatted": "6.55%",
    "enquiryYearEndMinusOneDisplay": "30/06/2003",
    "amalgamatedLoanNotPaidByEOIYFormatted": "$4,541.00",
    "openingBalancePayDays": "264",
    "openingBalanceInterestFormatted": "$214.54",
    "totalAmountOfRepaymentFormatted": "$2,059.00",
    "totalInterestFormatted": "$259.85",
    "principalFormatted": "$1,799.15",
    "enquiryYearEndDisplay": "30/06/2004",
    "minimumYearRepaymentFormatted": "$1,327.00",
    "loanAmountFormatted": "$2,741.85"
  },
  "repayments": [
    {
      "rd": "21/3/2004",
      "ra": 2059
    }
  ],
  "inputs": {
    "incomeYearOfLoan": 2000,
    "fullTermOfAmalgamatedLoan": 7,
    "incomeYearOfEnquiring": 2004,
    "amalgamatedLoanNotPaidByEOIY": 4541,
    "repayments": null,
    "lodgement_date": null
  },
  "idx": 6719
}