{
  "id": "2023-09-06T09:19:42.135Z0.25809558197433",
  "alert": "Start of result\nResult\n\nMinimum yearly repayment met.\n\nThe amount of the loan not repaid at the end of income year 2010-11 is $282.71.\n\nThe amalgamated loan will not be taken to be a dividend because the total repayments made are equal to or greater than the minimum yearly repayment required for income year 2010-11.\n\nInterest received by the private company must be included in the income tax return for 2010-11.\n\nMinimum yearly repayment\n\n$3,993.00\n\nBenchmark interest rate\n\n7.4%\n\nOpening balance:\n\nDate: 30/06/2010\n\nBalance: $7,179.00\n\nDays: 133\n\nInterest: $193.58\n\nPayments\n\nDate: 11/11/2010\n\nAmount: $6,931.00\n\nBalance: $248.00\n\nDays: 4\n\nInterest: $0.20\n\n\n\n\nDate: 15/11/2010\n\nAmount: $163.00\n\nBalance: $85.00\n\nDays: 228\n\nInterest: $3.93\n\n\n\n\nTotal repayments\n\n$7,094.00\n\nTotal interest\n\n$197.71\n\nTotal principal\n\n$6,896.29\n\nClosing balance\n\nDate: 30/06/2011\n\nBalance: $282.71",
  "outputs": {
    "enquiryRateFormatted": "7.4%",
    "enquiryYearEndMinusOneDisplay": "30/06/2010",
    "amalgamatedLoanNotPaidByEOIYFormatted": "$7,179.00",
    "openingBalancePayDays": "133",
    "openingBalanceInterestFormatted": "$193.58",
    "totalAmountOfRepaymentFormatted": "$7,094.00",
    "totalInterestFormatted": "$197.71",
    "principalFormatted": "$6,896.29",
    "enquiryYearEndDisplay": "30/06/2011",
    "minimumYearRepaymentFormatted": "$3,993.00"
  },
  "repayments": [
    {
      "rd": "11/11/2010",
      "ra": 6931
    },
    {
      "rd": "15/11/2010",
      "ra": 163
    }
  ],
  "inputs": {
    "incomeYearOfLoan": 2009,
    "fullTermOfAmalgamatedLoan": 3,
    "incomeYearOfEnquiring": 2011,
    "amalgamatedLoanNotPaidByEOIY": 7179,
    "repayments": null,
    "lodgement_date": null
  },
  "idx": 6271
}