{
  "id": "2023-09-04T21:31:52.138Z0.8934494116099987",
  "alert": "Start of result\nResult\n\nMinimum yearly repayment not met.\n\nThe amount of the loan not repaid at the end of income year 2006-07 is $107,733,739.11.\n\nThe private company may be taken to pay a dividend under Division 7A to the shareholder or shareholder's associate because the amount repaid during income year 2006-07 in relation to the amalgamated loan is less than the minimum yearly repayment required.\n\nInterest received by the private company must be included in the income tax return for 2006-07.\n\nMinimum yearly repayment\n\n$115,867,636.00\n\nBenchmark interest rate\n\n7.55%\n\nOpening balance:\n\nDate: 30/06/2006\n\nBalance: $107,733,739.11\n\nDays: 0\n\nInterest: $0\n\nPayments\n\nDate: 01/07/2006\n\nAmount: $9,396.00\n\nBalance: $107,724,343.11\n\nDays: 365\n\nInterest: $8,133,187.90\n\n\n\n\nTotal repayments\n\n$9,396.00\n\nTotal interest\n\n$8,133,187.90\n\nTotal principal\n\n$0\n\nClosing balance\n\nDate: 30/06/2007\n\nBalance: $107,733,739.11",
  "outputs": {
    "enquiryRateFormatted": "7.55%",
    "enquiryYearEndMinusOneDisplay": "30/06/2006",
    "amalgamatedLoanNotPaidByEOIYFormatted": "$107,733,739.11",
    "openingBalancePayDays": "0",
    "openingBalanceInterestFormatted": "$0",
    "totalAmountOfRepaymentFormatted": "$9,396.00",
    "totalInterestFormatted": "$8,133,187.90",
    "principalFormatted": "$0",
    "enquiryYearEndDisplay": "30/06/2007",
    "minimumYearRepaymentFormatted": "$115,867,636.00"
  },
  "repayments": [
    {
      "rd": "1/7/2006",
      "ra": 9396
    }
  ],
  "inputs": {
    "incomeYearOfLoan": 2006,
    "fullTermOfAmalgamatedLoan": 1,
    "incomeYearOfEnquiring": 2007,
    "amalgamatedLoanNotPaidByEOIY": 107733739.11489004,
    "repayments": null,
    "lodgement_date": "1/7/2006"
  },
  "idx": 1356
}