{
  "id": "2023-10-31T18:11:32.214Z0.8793752293813402",
  "alert": "Start of result\nResult\n\nAmalgamated loan fully repaid.\n\nThe amalgamated loan has been paid in full.\u000bThe private company is not taken under Division 7A to pay a dividend to the shareholder or shareholder's associate.\n\nInterest received by the private company must be included in the income tax return for 2012-13.\n\nMinimum yearly repayment\n\n$0\n\nBenchmark interest rate\n\n7.05%\n\nOpening balance:\n\nDate: 30/06/2012\n\nBalance: $1.53\n\nDays: 166\n\nInterest: $0.05\n\nPayments\n\nDate: 14/12/2012\n\nAmount: $15.37\n\nBalance: $0\n\nDays: 199\n\nInterest: $0\n\n\n\n\nTotal repayments\n\n$15.37\n\nTotal interest\n\n$0.05\n\nTotal principal\n\n$15.32\n\nClosing balance\n\nDate: 30/06/2013\n\nBalance: $0",
  "outputs": {
    "enquiryRateFormatted": "7.05%",
    "enquiryYearEndMinusOneDisplay": "30/06/2012",
    "amalgamatedLoanNotPaidByEOIYFormatted": "$1.53",
    "openingBalancePayDays": "166",
    "openingBalanceInterestFormatted": "$0.05",
    "totalAmountOfRepaymentFormatted": "$15.37",
    "totalInterestFormatted": "$0.05",
    "principalFormatted": "$15.32",
    "enquiryYearEndDisplay": "30/06/2013",
    "minimumYearRepaymentFormatted": "$0",
    "loanAmountFormatted": "$0"
  },
  "repayments": [
    {
      "rd": "14/12/2012",
      "ra": 15.370623360571699
    }
  ],
  "inputs": {
    "incomeYearOfLoan": 2011,
    "fullTermOfAmalgamatedLoan": 5,
    "incomeYearOfEnquiring": 2013,
    "amalgamatedLoanNotPaidByEOIY": 1.537062336057128,
    "repayments": null,
    "lodgement_date": null
  },
  "idx": 3505
}