{
  "id": "2023-10-31T18:03:54.390Z0.10908091410846232",
  "alert": "Start of result\nResult\n\nAmalgamated loan fully repaid.\n\nThe amalgamated loan has been paid in full.\u000bThe private company is not taken under Division 7A to pay a dividend to the shareholder or shareholder's associate.\n\nInterest received by the private company must be included in the income tax return for 2013-14.\n\nMinimum yearly repayment\n\n$7.00\n\nBenchmark interest rate\n\n6.2%\n\nOpening balance:\n\nDate: 30/06/2013\n\nBalance: $25.66\n\nDays: 226\n\nInterest: $0.99\n\nPayments\n\nDate: 12/02/2014\n\nAmount: $256.63\n\nBalance: $0\n\nDays: 139\n\nInterest: $0\n\n\n\n\nTotal repayments\n\n$256.63\n\nTotal interest\n\n$0.99\n\nTotal principal\n\n$255.64\n\nClosing balance\n\nDate: 30/06/2014\n\nBalance: $0",
  "outputs": {
    "enquiryRateFormatted": "6.2%",
    "enquiryYearEndMinusOneDisplay": "30/06/2013",
    "amalgamatedLoanNotPaidByEOIYFormatted": "$25.66",
    "openingBalancePayDays": "226",
    "openingBalanceInterestFormatted": "$0.99",
    "totalAmountOfRepaymentFormatted": "$256.63",
    "totalInterestFormatted": "$0.99",
    "principalFormatted": "$255.64",
    "enquiryYearEndDisplay": "30/06/2014",
    "minimumYearRepaymentFormatted": "$7.00",
    "loanAmountFormatted": "$0"
  },
  "repayments": [
    {
      "rd": "12/2/2014",
      "ra": 256.63520829788285
    }
  ],
  "inputs": {
    "incomeYearOfLoan": 2012,
    "fullTermOfAmalgamatedLoan": 5,
    "incomeYearOfEnquiring": 2014,
    "amalgamatedLoanNotPaidByEOIY": 25.663520829788286,
    "repayments": null,
    "lodgement_date": null
  },
  "idx": 3234
}