{
  "id": "2023-10-31T18:40:36.568Z0.5841206571494674",
  "alert": "Start of result\nResult\n\nAmalgamated loan fully repaid.\n\nThe amalgamated loan has been paid in full.\u000bThe private company is not taken under Division 7A to pay a dividend to the shareholder or shareholder's associate.\n\nInterest received by the private company must be included in the income tax return for 2008-09.\n\nMinimum yearly repayment\n\n-$62.00\n\nBenchmark interest rate\n\n9.45%\n\nOpening balance:\n\nDate: 30/06/2008\n\nBalance: $26.41\n\nDays: 88\n\nInterest: $0.60\n\nPayments\n\nDate: 27/09/2008\n\nAmount: $264.11\n\nBalance: $0\n\nDays: 277\n\nInterest: $0\n\n\n\n\nTotal repayments\n\n$264.11\n\nTotal interest\n\n$0.60\n\nTotal principal\n\n$263.51\n\nClosing balance\n\nDate: 30/06/2009\n\nBalance: $0",
  "outputs": {
    "enquiryRateFormatted": "9.45%",
    "enquiryYearEndMinusOneDisplay": "30/06/2008",
    "amalgamatedLoanNotPaidByEOIYFormatted": "$26.41",
    "openingBalancePayDays": "88",
    "openingBalanceInterestFormatted": "$0.60",
    "totalAmountOfRepaymentFormatted": "$264.11",
    "totalInterestFormatted": "$0.60",
    "principalFormatted": "$263.51",
    "enquiryYearEndDisplay": "30/06/2009",
    "minimumYearRepaymentFormatted": "-$62.00",
    "loanAmountFormatted": "$0"
  },
  "repayments": [
    {
      "rd": "27/9/2008",
      "ra": 264.1194455754985
    }
  ],
  "inputs": {
    "incomeYearOfLoan": 2008,
    "fullTermOfAmalgamatedLoan": 5,
    "incomeYearOfEnquiring": 2009,
    "amalgamatedLoanNotPaidByEOIY": 26.41194455754984,
    "repayments": null,
    "lodgement_date": "27/5/2009"
  },
  "idx": 4372
}