{
  "id": "2023-10-31T19:29:00.192Z0.6800928987708612",
  "alert": "Start of result\nResult\n\nMinimum yearly repayment not met.\n\nThe amount of the loan not repaid at the end of income year 2008-09 is $6,226.40.\n\nThe private company may be taken to pay a dividend under Division 7A to the shareholder or shareholder's associate because the amount repaid during income year 2008-09 in relation to the amalgamated loan is less than the minimum yearly repayment required.\n\nInterest received by the private company must be included in the income tax return for 2008-09.\n\nMinimum yearly repayment\n\n$8,956.00\n\nBenchmark interest rate\n\n9.45%\n\nOpening balance:\n\nDate: 30/06/2008\n\nBalance: $8,183.00\n\nDays: 235\n\nInterest: $497.87\n\nPayments\n\nDate: 21/02/2009\n\nAmount: $2,641.00\n\nBalance: $5,542.00\n\nDays: 130\n\nInterest: $186.53\n\n\n\n\nTotal repayments\n\n$2,641.00\n\nTotal interest\n\n$684.40\n\nTotal principal\n\n$1,956.60\n\nClosing balance\n\nDate: 30/06/2009\n\nBalance: $6,226.40",
  "outputs": {
    "enquiryRateFormatted": "9.45%",
    "enquiryYearEndMinusOneDisplay": "30/06/2008",
    "amalgamatedLoanNotPaidByEOIYFormatted": "$8,183.00",
    "openingBalancePayDays": "235",
    "openingBalanceInterestFormatted": "$497.87",
    "totalAmountOfRepaymentFormatted": "$2,641.00",
    "totalInterestFormatted": "$684.40",
    "principalFormatted": "$1,956.60",
    "enquiryYearEndDisplay": "30/06/2009",
    "minimumYearRepaymentFormatted": "$8,956.00",
    "loanAmountFormatted": "$6,226.40"
  },
  "repayments": [
    {
      "rd": "21/2/2009",
      "ra": 2641
    }
  ],
  "inputs": {
    "incomeYearOfLoan": 2004,
    "fullTermOfAmalgamatedLoan": 5,
    "incomeYearOfEnquiring": 2009,
    "amalgamatedLoanNotPaidByEOIY": 8183,
    "repayments": null,
    "lodgement_date": null
  },
  "idx": 5508
}