{
  "id": "2023-10-31T18:12:32.465Z0.33931960050731114",
  "alert": "Start of result\nResult\n\nAmalgamated loan fully repaid.\n\nThe amalgamated loan has been paid in full.\u000bThe private company is not taken under Division 7A to pay a dividend to the shareholder or shareholder's associate.\n\nInterest received by the private company must be included in the income tax return for 2014-15.\n\nMinimum yearly repayment\n\n$156.00\n\nBenchmark interest rate\n\n5.95%\n\nOpening balance:\n\nDate: 30/06/2014\n\nBalance: $418.00\n\nDays: 184\n\nInterest: $12.54\n\nPayments\n\nDate: 01/01/2015\n\nAmount: $2,469.00\n\nBalance: $0\n\nDays: 181\n\nInterest: $0\n\n\n\n\nTotal repayments\n\n$2,469.00\n\nTotal interest\n\n$12.54\n\nTotal principal\n\n$2,456.46\n\nClosing balance\n\nDate: 30/06/2015\n\nBalance: $0",
  "outputs": {
    "enquiryRateFormatted": "5.95%",
    "enquiryYearEndMinusOneDisplay": "30/06/2014",
    "amalgamatedLoanNotPaidByEOIYFormatted": "$418.00",
    "openingBalancePayDays": "184",
    "openingBalanceInterestFormatted": "$12.54",
    "totalAmountOfRepaymentFormatted": "$2,469.00",
    "totalInterestFormatted": "$12.54",
    "principalFormatted": "$2,456.46",
    "enquiryYearEndDisplay": "30/06/2015",
    "minimumYearRepaymentFormatted": "$156.00",
    "loanAmountFormatted": "$0"
  },
  "repayments": [
    {
      "rd": "1/1/2015",
      "ra": 2469
    }
  ],
  "inputs": {
    "incomeYearOfLoan": 2011,
    "fullTermOfAmalgamatedLoan": 6,
    "incomeYearOfEnquiring": 2015,
    "amalgamatedLoanNotPaidByEOIY": 418,
    "repayments": null,
    "lodgement_date": null
  },
  "idx": 3540
}