{
  "id": "2023-10-31T20:19:41.825Z0.8304500311349532",
  "alert": "Start of result\nResult\n\nMinimum yearly repayment not met.\n\nThe amount of the loan not repaid at the end of income year 2004-05 is $7,552.23.\n\nThe private company may be taken to pay a dividend under Division 7A to the shareholder or shareholder's associate because the amount repaid during income year 2004-05 in relation to the amalgamated loan is less than the minimum yearly repayment required.\n\nInterest received by the private company must be included in the income tax return for 2004-05.\n\nMinimum yearly repayment\n\n$3,870.00\n\nBenchmark interest rate\n\n7.05%\n\nOpening balance:\n\nDate: 30/06/2004\n\nBalance: $10,146.00\n\nDays: 335\n\nInterest: $656.50\n\nPayments\n\nDate: 01/06/2005\n\nAmount: $3,290.00\n\nBalance: $6,856.00\n\nDays: 30\n\nInterest: $39.73\n\n\n\n\nTotal repayments\n\n$3,290.00\n\nTotal interest\n\n$696.23\n\nTotal principal\n\n$2,593.77\n\nClosing balance\n\nDate: 30/06/2005\n\nBalance: $7,552.23",
  "outputs": {
    "enquiryRateFormatted": "7.05%",
    "enquiryYearEndMinusOneDisplay": "30/06/2004",
    "amalgamatedLoanNotPaidByEOIYFormatted": "$10,146.00",
    "openingBalancePayDays": "335",
    "openingBalanceInterestFormatted": "$656.50",
    "totalAmountOfRepaymentFormatted": "$3,290.00",
    "totalInterestFormatted": "$696.23",
    "principalFormatted": "$2,593.77",
    "enquiryYearEndDisplay": "30/06/2005",
    "minimumYearRepaymentFormatted": "$3,870.00",
    "loanAmountFormatted": "$7,552.23"
  },
  "repayments": [
    {
      "rd": "1/6/2005",
      "ra": 3290
    }
  ],
  "inputs": {
    "incomeYearOfLoan": 2001,
    "fullTermOfAmalgamatedLoan": 6,
    "incomeYearOfEnquiring": 2005,
    "amalgamatedLoanNotPaidByEOIY": 10146,
    "repayments": null,
    "lodgement_date": null
  },
  "idx": 6375
}