{
  "id": "2023-10-31T20:40:51.117Z0.38387928300689234",
  "alert": "Start of result\nResult\n\nMinimum yearly repayment not met.\n\nThe amount of the loan not repaid at the end of income year 2002-03 is $76.45.\n\nThe private company may be taken to pay a dividend under Division 7A to the shareholder or shareholder's associate because the amount repaid during income year 2002-03 in relation to the amalgamated loan is less than the minimum yearly repayment required.\n\nInterest received by the private company must be included in the income tax return for 2002-03.\n\nMinimum yearly repayment\n\n$22.00\n\nBenchmark interest rate\n\n6.3%\n\nOpening balance:\n\nDate: 30/06/2002\n\nBalance: $76.45\n\nDays: 365\n\nInterest: $4.82\n\nTotal repayments\n\n$0\n\nTotal interest\n\n$4.82\n\nTotal principal\n\n$0\n\nClosing balance\n\nDate: 30/06/2003\n\nBalance: $76.45",
  "outputs": {
    "enquiryRateFormatted": "6.3%",
    "enquiryYearEndMinusOneDisplay": "30/06/2002",
    "amalgamatedLoanNotPaidByEOIYFormatted": "$76.45",
    "openingBalancePayDays": "365",
    "openingBalanceInterestFormatted": "$4.82",
    "totalAmountOfRepaymentFormatted": "$0",
    "totalInterestFormatted": "$4.82",
    "principalFormatted": "$0",
    "enquiryYearEndDisplay": "30/06/2003",
    "minimumYearRepaymentFormatted": "$22.00",
    "loanAmountFormatted": "$76.45"
  },
  "repayments": [],
  "inputs": {
    "incomeYearOfLoan": 2000,
    "fullTermOfAmalgamatedLoan": 6,
    "incomeYearOfEnquiring": 2003,
    "amalgamatedLoanNotPaidByEOIY": 76.45316443266954,
    "repayments": null,
    "lodgement_date": null
  },
  "idx": 6680
}