{
  "id": "2023-09-06T11:41:25.154Z0.851232047045474",
  "alert": "Start of result\nResult\n\nMinimum yearly repayment met.\n\nThe amount of the loan not repaid at the end of income year 2012-13 is $3.82.\n\nThe amalgamated loan will not be taken to be a dividend because the total repayments made are equal to or greater than the minimum yearly repayment required for income year 2012-13.\n\nInterest received by the private company must be included in the income tax return for 2012-13.\n\nMinimum yearly repayment\n\n$36.00\n\nBenchmark interest rate\n\n7.05%\n\nOpening balance:\n\nDate: 30/06/2012\n\nBalance: $65.22\n\nDays: 303\n\nInterest: $3.82\n\nPayments\n\nDate: 30/04/2013\n\nAmount: $65.22\n\nBalance: $0\n\nDays: 62\n\nInterest: $0\n\n\n\n\nTotal repayments\n\n$65.22\n\nTotal interest\n\n$3.82\n\nTotal principal\n\n$61.40\n\nClosing balance\n\nDate: 30/06/2013\n\nBalance: $3.82",
  "outputs": {
    "enquiryRateFormatted": "7.05%",
    "enquiryYearEndMinusOneDisplay": "30/06/2012",
    "amalgamatedLoanNotPaidByEOIYFormatted": "$65.22",
    "openingBalancePayDays": "303",
    "openingBalanceInterestFormatted": "$3.82",
    "totalAmountOfRepaymentFormatted": "$65.22",
    "totalInterestFormatted": "$3.82",
    "principalFormatted": "$61.40",
    "enquiryYearEndDisplay": "30/06/2013",
    "minimumYearRepaymentFormatted": "$36.00"
  },
  "repayments": [
    {
      "rd": "30/4/2013",
      "ra": 65.22909633983409
    }
  ],
  "inputs": {
    "incomeYearOfLoan": 2008,
    "fullTermOfAmalgamatedLoan": 6,
    "incomeYearOfEnquiring": 2013,
    "amalgamatedLoanNotPaidByEOIY": 65.22909633983403,
    "repayments": null,
    "lodgement_date": null
  },
  "idx": 5161
}