{
  "id": "2023-09-04T17:13:44.527Z0.47709540821275387",
  "alert": "Start of result\nResult\n\nMinimum yearly repayment not met.\n\nThe amount of the loan not repaid at the end of income year 2014-15 is $63,966,556.14.\n\nThe private company may be taken to pay a dividend under Division 7A to the shareholder or shareholder's associate because the amount repaid during income year 2014-15 in relation to the amalgamated loan is less than the minimum yearly repayment required.\n\nInterest received by the private company must be included in the income tax return for 2014-15.\n\nMinimum yearly repayment\n\n$18,439,073.00\n\nBenchmark interest rate\n\n5.95%\n\nOpening balance:\n\nDate: 30/06/2014\n\nBalance: $63,966,556.14\n\nDays: 365\n\nInterest: $3,806,010.09\n\nTotal repayments\n\n$0\n\nTotal interest\n\n$3,806,010.09\n\nTotal principal\n\n$0\n\nClosing balance\n\nDate: 30/06/2015\n\nBalance: $63,966,556.14",
  "outputs": {
    "enquiryRateFormatted": "5.95%",
    "enquiryYearEndMinusOneDisplay": "30/06/2014",
    "amalgamatedLoanNotPaidByEOIYFormatted": "$63,966,556.14",
    "openingBalancePayDays": "365",
    "openingBalanceInterestFormatted": "$3,806,010.09",
    "totalAmountOfRepaymentFormatted": "$0",
    "totalInterestFormatted": "$3,806,010.09",
    "principalFormatted": "$0",
    "enquiryYearEndDisplay": "30/06/2015",
    "minimumYearRepaymentFormatted": "$18,439,073.00"
  },
  "repayments": [],
  "inputs": {
    "incomeYearOfLoan": 2014,
    "fullTermOfAmalgamatedLoan": 4,
    "incomeYearOfEnquiring": 2015,
    "amalgamatedLoanNotPaidByEOIY": 63966556.143400274,
    "repayments": null,
    "lodgement_date": "1/7/2014"
  },
  "idx": 1870
}