{
  "id": "2023-09-05T16:41:01.514Z0.31378426306257756",
  "alert": "Start of result\nResult\n\nMinimum yearly repayment met.\n\nThe amount of the loan not repaid at the end of income year 2021-22 is $0.87.\n\nThe amalgamated loan will not be taken to be a dividend because the total repayments made are equal to or greater than the minimum yearly repayment required for income year 2021-22.\n\nInterest received by the private company must be included in the income tax return for 2021-22.\n\nMinimum yearly repayment\n\n$36.00\n\nBenchmark interest rate\n\n4.52%\n\nOpening balance:\n\nDate: 30/06/2021\n\nBalance: $66.65\n\nDays: 105\n\nInterest: $0.87\n\nPayments\n\nDate: 14/10/2021\n\nAmount: $66.65\n\nBalance: $0\n\nDays: 260\n\nInterest: $0\n\n\n\n\nTotal repayments\n\n$66.65\n\nTotal interest\n\n$0.87\n\nTotal principal\n\n$65.78\n\nClosing balance\n\nDate: 30/06/2022\n\nBalance: $0.87",
  "outputs": {
    "enquiryRateFormatted": "4.52%",
    "enquiryYearEndMinusOneDisplay": "30/06/2021",
    "amalgamatedLoanNotPaidByEOIYFormatted": "$66.65",
    "openingBalancePayDays": "105",
    "openingBalanceInterestFormatted": "$0.87",
    "totalAmountOfRepaymentFormatted": "$66.65",
    "totalInterestFormatted": "$0.87",
    "principalFormatted": "$65.78",
    "enquiryYearEndDisplay": "30/06/2022",
    "minimumYearRepaymentFormatted": "$36.00"
  },
  "repayments": [
    {
      "rd": "14/10/2021",
      "ra": 66.65407486818549
    }
  ],
  "inputs": {
    "incomeYearOfLoan": 2019,
    "fullTermOfAmalgamatedLoan": 4,
    "incomeYearOfEnquiring": 2022,
    "amalgamatedLoanNotPaidByEOIY": 66.6540748681856,
    "repayments": null,
    "lodgement_date": null
  },
  "idx": 1478
}