{
  "id": "2023-09-06T09:33:42.766Z0.11332966359313779",
  "alert": "Start of result\nResult\n\nMinimum yearly repayment not met.\n\nThe amount of the loan not repaid at the end of income year 2012-13 is $0.96.\n\nThe private company may be taken to pay a dividend under Division 7A to the shareholder or shareholder's associate because the amount repaid during income year 2012-13 in relation to the amalgamated loan is less than the minimum yearly repayment required.\n\nInterest received by the private company must be included in the income tax return for 2012-13.\n\nMinimum yearly repayment\n\n$22.00\n\nBenchmark interest rate\n\n7.05%\n\nOpening balance:\n\nDate: 30/06/2012\n\nBalance: $20.97\n\nDays: 238\n\nInterest: $0.96\n\nPayments\n\nDate: 24/02/2013\n\nAmount: $20.97\n\nBalance: $0\n\nDays: 127\n\nInterest: $0\n\n\n\n\nTotal repayments\n\n$20.97\n\nTotal interest\n\n$0.96\n\nTotal principal\n\n$20.01\n\nClosing balance\n\nDate: 30/06/2013\n\nBalance: $0.96",
  "outputs": {
    "enquiryRateFormatted": "7.05%",
    "enquiryYearEndMinusOneDisplay": "30/06/2012",
    "amalgamatedLoanNotPaidByEOIYFormatted": "$20.97",
    "openingBalancePayDays": "238",
    "openingBalanceInterestFormatted": "$0.96",
    "totalAmountOfRepaymentFormatted": "$20.97",
    "totalInterestFormatted": "$0.96",
    "principalFormatted": "$20.01",
    "enquiryYearEndDisplay": "30/06/2013",
    "minimumYearRepaymentFormatted": "$22.00"
  },
  "repayments": [
    {
      "rd": "24/2/2013",
      "ra": 20.9762627262061
    }
  ],
  "inputs": {
    "incomeYearOfLoan": 2009,
    "fullTermOfAmalgamatedLoan": 4,
    "incomeYearOfEnquiring": 2013,
    "amalgamatedLoanNotPaidByEOIY": 20.976262726206098,
    "repayments": null,
    "lodgement_date": null
  },
  "idx": 7006
}