{
  "id": "2023-10-31T19:18:55.625Z0.8107575338697881",
  "alert": "Start of result\nResult\n\nMinimum yearly repayment not met.\n\nThe amount of the loan not repaid at the end of income year 2006-07 is $43.80.\n\nThe private company may be taken to pay a dividend under Division 7A to the shareholder or shareholder's associate because the amount repaid during income year 2006-07 in relation to the amalgamated loan is less than the minimum yearly repayment required.\n\nInterest received by the private company must be included in the income tax return for 2006-07.\n\nMinimum yearly repayment\n\n$11.00\n\nBenchmark interest rate\n\n7.55%\n\nOpening balance:\n\nDate: 30/06/2006\n\nBalance: $43.80\n\nDays: 365\n\nInterest: $3.31\n\nTotal repayments\n\n$0\n\nTotal interest\n\n$3.31\n\nTotal principal\n\n$0\n\nClosing balance\n\nDate: 30/06/2007\n\nBalance: $43.80",
  "outputs": {
    "enquiryRateFormatted": "7.55%",
    "enquiryYearEndMinusOneDisplay": "30/06/2006",
    "amalgamatedLoanNotPaidByEOIYFormatted": "$43.80",
    "openingBalancePayDays": "365",
    "openingBalanceInterestFormatted": "$3.31",
    "totalAmountOfRepaymentFormatted": "$0",
    "totalInterestFormatted": "$3.31",
    "principalFormatted": "$0",
    "enquiryYearEndDisplay": "30/06/2007",
    "minimumYearRepaymentFormatted": "$11.00",
    "loanAmountFormatted": "$43.80"
  },
  "repayments": [],
  "inputs": {
    "incomeYearOfLoan": 2005,
    "fullTermOfAmalgamatedLoan": 6,
    "incomeYearOfEnquiring": 2007,
    "amalgamatedLoanNotPaidByEOIY": 43.80764079896291,
    "repayments": null,
    "lodgement_date": null
  },
  "idx": 5300
}