{
  "id": "2023-09-04T20:49:10.158Z0.19058886728431612",
  "alert": "Start of result\nResult\n\nMinimum yearly repayment not met.\n\nThe amount of the loan not repaid at the end of income year 2012-13 is $1,997.55.\n\nThe private company may be taken to pay a dividend under Division 7A to the shareholder or shareholder's associate because the amount repaid during income year 2012-13 in relation to the amalgamated loan is less than the minimum yearly repayment required.\n\nInterest received by the private company must be included in the income tax return for 2012-13.\n\nMinimum yearly repayment\n\n$2,148.00\n\nBenchmark interest rate\n\n7.05%\n\nOpening balance:\n\nDate: 30/06/2012\n\nBalance: $2,007.00\n\nDays: 0\n\nInterest: $0\n\nPayments\n\nDate: 01/07/2012\n\nAmount: $141.00\n\nBalance: $1,866.00\n\nDays: 365\n\nInterest: $131.55\n\n\n\n\nTotal repayments\n\n$141.00\n\nTotal interest\n\n$131.55\n\nTotal principal\n\n$9.45\n\nClosing balance\n\nDate: 30/06/2013\n\nBalance: $1,997.55",
  "outputs": {
    "enquiryRateFormatted": "7.05%",
    "enquiryYearEndMinusOneDisplay": "30/06/2012",
    "amalgamatedLoanNotPaidByEOIYFormatted": "$2,007.00",
    "openingBalancePayDays": "0",
    "openingBalanceInterestFormatted": "$0",
    "totalAmountOfRepaymentFormatted": "$141.00",
    "totalInterestFormatted": "$131.55",
    "principalFormatted": "$9.45",
    "enquiryYearEndDisplay": "30/06/2013",
    "minimumYearRepaymentFormatted": "$2,148.00"
  },
  "repayments": [
    {
      "rd": "1/7/2012",
      "ra": 141
    }
  ],
  "inputs": {
    "incomeYearOfLoan": 2011,
    "fullTermOfAmalgamatedLoan": 2,
    "incomeYearOfEnquiring": 2013,
    "amalgamatedLoanNotPaidByEOIY": 2007,
    "repayments": null,
    "lodgement_date": null
  },
  "idx": 73
}