{
  "id": "2023-09-06T04:25:28.154Z0.3165787790220649",
  "alert": "Start of result\nResult\n\nMinimum yearly repayment not met.\n\nThe amount of the loan not repaid at the end of income year 2014-15 is $73.53.\n\nThe private company may be taken to pay a dividend under Division 7A to the shareholder or shareholder's associate because the amount repaid during income year 2014-15 in relation to the amalgamated loan is less than the minimum yearly repayment required.\n\nInterest received by the private company must be included in the income tax return for 2014-15.\n\nMinimum yearly repayment\n\n$78.00\n\nBenchmark interest rate\n\n5.95%\n\nOpening balance:\n\nDate: 30/06/2014\n\nBalance: $73.53\n\nDays: 365\n\nInterest: $4.38\n\nTotal repayments\n\n$0\n\nTotal interest\n\n$4.38\n\nTotal principal\n\n$0\n\nClosing balance\n\nDate: 30/06/2015\n\nBalance: $73.53",
  "outputs": {
    "enquiryRateFormatted": "5.95%",
    "enquiryYearEndMinusOneDisplay": "30/06/2014",
    "amalgamatedLoanNotPaidByEOIYFormatted": "$73.53",
    "openingBalancePayDays": "365",
    "openingBalanceInterestFormatted": "$4.38",
    "totalAmountOfRepaymentFormatted": "$0",
    "totalInterestFormatted": "$4.38",
    "principalFormatted": "$0",
    "enquiryYearEndDisplay": "30/06/2015",
    "minimumYearRepaymentFormatted": "$78.00"
  },
  "repayments": [],
  "inputs": {
    "incomeYearOfLoan": 2012,
    "fullTermOfAmalgamatedLoan": 3,
    "incomeYearOfEnquiring": 2015,
    "amalgamatedLoanNotPaidByEOIY": 73.53823976855224,
    "repayments": null,
    "lodgement_date": null
  },
  "idx": 7367
}