{
  "id": "2023-10-31T18:51:25.419Z0.5704208919174765",
  "alert": "Start of result\nResult\n\nAmalgamated loan fully repaid.\n\nThe amalgamated loan has been paid in full.\u000bThe private company is not taken under Division 7A to pay a dividend to the shareholder or shareholder's associate.\n\nInterest received by the private company must be included in the income tax return for 2009-10.\n\nMinimum yearly repayment\n\n$16.00\n\nBenchmark interest rate\n\n5.75%\n\nOpening balance:\n\nDate: 30/06/2009\n\nBalance: $42.10\n\nDays: 302\n\nInterest: $2.00\n\nPayments\n\nDate: 29/04/2010\n\nAmount: $421.06\n\nBalance: $0\n\nDays: 63\n\nInterest: $0\n\n\n\n\nTotal repayments\n\n$421.06\n\nTotal interest\n\n$2.00\n\nTotal principal\n\n$419.06\n\nClosing balance\n\nDate: 30/06/2010\n\nBalance: $0",
  "outputs": {
    "enquiryRateFormatted": "5.75%",
    "enquiryYearEndMinusOneDisplay": "30/06/2009",
    "amalgamatedLoanNotPaidByEOIYFormatted": "$42.10",
    "openingBalancePayDays": "302",
    "openingBalanceInterestFormatted": "$2.00",
    "totalAmountOfRepaymentFormatted": "$421.06",
    "totalInterestFormatted": "$2.00",
    "principalFormatted": "$419.06",
    "enquiryYearEndDisplay": "30/06/2010",
    "minimumYearRepaymentFormatted": "$16.00",
    "loanAmountFormatted": "$0"
  },
  "repayments": [
    {
      "rd": "29/4/2010",
      "ra": 421.0619079795756
    }
  ],
  "inputs": {
    "incomeYearOfLoan": 2007,
    "fullTermOfAmalgamatedLoan": 5,
    "incomeYearOfEnquiring": 2010,
    "amalgamatedLoanNotPaidByEOIY": 42.106190797957545,
    "repayments": null,
    "lodgement_date": null
  },
  "idx": 4656
}