{
  "id": "2023-09-05T19:43:31.658Z0.7684051502650491",
  "alert": "Start of result\nResult\n\nMinimum yearly repayment met.\n\nThe amount of the loan not repaid at the end of income year 2018-19 is $75.41.\n\nThe amalgamated loan will not be taken to be a dividend because the total repayments made are equal to or greater than the minimum yearly repayment required for income year 2018-19.\n\nInterest received by the private company must be included in the income tax return for 2018-19.\n\nMinimum yearly repayment\n\n$1,404.00\n\nBenchmark interest rate\n\n5.2%\n\nOpening balance:\n\nDate: 30/06/2018\n\nBalance: $3,808.00\n\nDays: 139\n\nInterest: $75.41\n\nPayments\n\nDate: 17/11/2018\n\nAmount: $3,808.00\n\nBalance: $0\n\nDays: 226\n\nInterest: $0\n\n\n\n\nTotal repayments\n\n$3,808.00\n\nTotal interest\n\n$75.41\n\nTotal principal\n\n$3,732.59\n\nClosing balance\n\nDate: 30/06/2019\n\nBalance: $75.41",
  "outputs": {
    "enquiryRateFormatted": "5.2%",
    "enquiryYearEndMinusOneDisplay": "30/06/2018",
    "amalgamatedLoanNotPaidByEOIYFormatted": "$3,808.00",
    "openingBalancePayDays": "139",
    "openingBalanceInterestFormatted": "$75.41",
    "totalAmountOfRepaymentFormatted": "$3,808.00",
    "totalInterestFormatted": "$75.41",
    "principalFormatted": "$3,732.59",
    "enquiryYearEndDisplay": "30/06/2019",
    "minimumYearRepaymentFormatted": "$1,404.00"
  },
  "repayments": [
    {
      "rd": "17/11/2018",
      "ra": 3808
    }
  ],
  "inputs": {
    "incomeYearOfLoan": 2017,
    "fullTermOfAmalgamatedLoan": 4,
    "incomeYearOfEnquiring": 2019,
    "amalgamatedLoanNotPaidByEOIY": 3808,
    "repayments": null,
    "lodgement_date": null
  },
  "idx": 3683
}