{
  "id": "2023-10-31T18:30:47.123Z0.43617656932491655",
  "alert": "Start of result\nResult\n\nMinimum yearly repayment not met.\n\nThe amount of the loan not repaid at the end of income year 2011-12 is $5,349.00.\n\nThe private company may be taken to pay a dividend under Division 7A to the shareholder or shareholder's associate because the amount repaid during income year 2011-12 in relation to the amalgamated loan is less than the minimum yearly repayment required.\n\nInterest received by the private company must be included in the income tax return for 2011-12.\n\nMinimum yearly repayment\n\n$2,068.00\n\nBenchmark interest rate\n\n7.8%\n\nOpening balance:\n\nDate: 30/06/2011\n\nBalance: $5,349.00\n\nDays: 366\n\nInterest: $417.22\n\nTotal repayments\n\n$0\n\nTotal interest\n\n$417.22\n\nTotal principal\n\n$0\n\nClosing balance\n\nDate: 30/06/2012\n\nBalance: $5,349.00",
  "outputs": {
    "enquiryRateFormatted": "7.8%",
    "enquiryYearEndMinusOneDisplay": "30/06/2011",
    "amalgamatedLoanNotPaidByEOIYFormatted": "$5,349.00",
    "openingBalancePayDays": "366",
    "openingBalanceInterestFormatted": "$417.22",
    "totalAmountOfRepaymentFormatted": "$0",
    "totalInterestFormatted": "$417.22",
    "principalFormatted": "$0",
    "enquiryYearEndDisplay": "30/06/2012",
    "minimumYearRepaymentFormatted": "$2,068.00",
    "loanAmountFormatted": "$5,349.00"
  },
  "repayments": [],
  "inputs": {
    "incomeYearOfLoan": 2009,
    "fullTermOfAmalgamatedLoan": 5,
    "incomeYearOfEnquiring": 2012,
    "amalgamatedLoanNotPaidByEOIY": 5349,
    "repayments": null,
    "lodgement_date": null
  },
  "idx": 4100
}