{
  "id": "2023-10-31T18:04:47.128Z0.6895410163471802",
  "alert": "Start of result\nResult\n\nMinimum yearly repayment not met.\n\nThe amount of the loan not repaid at the end of income year 2016-17 is $16.06.\n\nThe private company may be taken to pay a dividend under Division 7A to the shareholder or shareholder's associate because the amount repaid during income year 2016-17 in relation to the amalgamated loan is less than the minimum yearly repayment required.\n\nInterest received by the private company must be included in the income tax return for 2016-17.\n\nMinimum yearly repayment\n\n$9.00\n\nBenchmark interest rate\n\n5.4%\n\nOpening balance:\n\nDate: 30/06/2016\n\nBalance: $16.06\n\nDays: 365\n\nInterest: $0.87\n\nTotal repayments\n\n$0\n\nTotal interest\n\n$0.87\n\nTotal principal\n\n$0\n\nClosing balance\n\nDate: 30/06/2017\n\nBalance: $16.06",
  "outputs": {
    "enquiryRateFormatted": "5.4%",
    "enquiryYearEndMinusOneDisplay": "30/06/2016",
    "amalgamatedLoanNotPaidByEOIYFormatted": "$16.06",
    "openingBalancePayDays": "365",
    "openingBalanceInterestFormatted": "$0.87",
    "totalAmountOfRepaymentFormatted": "$0",
    "totalInterestFormatted": "$0.87",
    "principalFormatted": "$0",
    "enquiryYearEndDisplay": "30/06/2017",
    "minimumYearRepaymentFormatted": "$9.00",
    "loanAmountFormatted": "$16.06"
  },
  "repayments": [],
  "inputs": {
    "incomeYearOfLoan": 2012,
    "fullTermOfAmalgamatedLoan": 6,
    "incomeYearOfEnquiring": 2017,
    "amalgamatedLoanNotPaidByEOIY": 16.06096365799891,
    "repayments": null,
    "lodgement_date": null
  },
  "idx": 3266
}