{
  "id": "2023-09-05T18:59:16.976Z0.15896663356831842",
  "alert": "Start of result\nResult\n\nMinimum yearly repayment not met.\n\nThe amount of the loan not repaid at the end of income year 2019-20 is $92.23.\n\nThe private company may be taken to pay a dividend under Division 7A to the shareholder or shareholder's associate because the amount repaid during income year 2019-20 in relation to the amalgamated loan is less than the minimum yearly repayment required.\n\nInterest received by the private company must be included in the income tax return for 2019-20.\n\nMinimum yearly repayment\n\n$18.00\n\nBenchmark interest rate\n\n5.37%\n\nOpening balance:\n\nDate: 30/06/2019\n\nBalance: $92.23\n\nDays: 366\n\nInterest: $4.95\n\nTotal repayments\n\n$0\n\nTotal interest\n\n$4.95\n\nTotal principal\n\n$0\n\nClosing balance\n\nDate: 30/06/2020\n\nBalance: $92.23",
  "outputs": {
    "enquiryRateFormatted": "5.37%",
    "enquiryYearEndMinusOneDisplay": "30/06/2019",
    "amalgamatedLoanNotPaidByEOIYFormatted": "$92.23",
    "openingBalancePayDays": "366",
    "openingBalanceInterestFormatted": "$4.95",
    "totalAmountOfRepaymentFormatted": "$0",
    "totalInterestFormatted": "$4.95",
    "principalFormatted": "$0",
    "enquiryYearEndDisplay": "30/06/2020",
    "minimumYearRepaymentFormatted": "$18.00"
  },
  "repayments": [],
  "inputs": {
    "incomeYearOfLoan": 2018,
    "fullTermOfAmalgamatedLoan": 7,
    "incomeYearOfEnquiring": 2020,
    "amalgamatedLoanNotPaidByEOIY": 92.2361134157211,
    "repayments": null,
    "lodgement_date": null
  },
  "idx": 740
}