{
  "id": "2023-09-04T16:56:51.553Z0.7255105317272712",
  "alert": "Start of result\nResult\n\nMinimum yearly repayment not met.\n\nThe amount of the loan not repaid at the end of income year 2018-19 is $104,095,926.08.\n\nThe private company may be taken to pay a dividend under Division 7A to the shareholder or shareholder's associate because the amount repaid during income year 2018-19 in relation to the amalgamated loan is less than the minimum yearly repayment required.\n\nInterest received by the private company must be included in the income tax return for 2018-19.\n\nMinimum yearly repayment\n\n$29,492,787.00\n\nBenchmark interest rate\n\n5.2%\n\nOpening balance:\n\nDate: 30/06/2018\n\nBalance: $104,095,926.08\n\nDays: 0\n\nInterest: $0\n\nPayments\n\nDate: 01/07/2018\n\nAmount: $254.00\n\nBalance: $104,095,672.08\n\nDays: 365\n\nInterest: $5,412,974.95\n\n\n\n\nTotal repayments\n\n$254.00\n\nTotal interest\n\n$5,412,974.95\n\nTotal principal\n\n$0\n\nClosing balance\n\nDate: 30/06/2019\n\nBalance: $104,095,926.08",
  "outputs": {
    "enquiryRateFormatted": "5.2%",
    "enquiryYearEndMinusOneDisplay": "30/06/2018",
    "amalgamatedLoanNotPaidByEOIYFormatted": "$104,095,926.08",
    "openingBalancePayDays": "0",
    "openingBalanceInterestFormatted": "$0",
    "totalAmountOfRepaymentFormatted": "$254.00",
    "totalInterestFormatted": "$5,412,974.95",
    "principalFormatted": "$0",
    "enquiryYearEndDisplay": "30/06/2019",
    "minimumYearRepaymentFormatted": "$29,492,787.00"
  },
  "repayments": [
    {
      "rd": "1/7/2018",
      "ra": 254
    }
  ],
  "inputs": {
    "incomeYearOfLoan": 2015,
    "fullTermOfAmalgamatedLoan": 7,
    "incomeYearOfEnquiring": 2019,
    "amalgamatedLoanNotPaidByEOIY": 104095926.08395314,
    "repayments": null,
    "lodgement_date": null
  },
  "idx": 1441
}