{
  "id": "2023-09-06T08:11:13.582Z0.06033832504327408",
  "alert": "Start of result\nResult\n\nMinimum yearly repayment met.\n\nThe amount of the loan not repaid at the end of income year 2011-12 is $169.44.\n\nThe amalgamated loan will not be taken to be a dividend because the total repayments made are equal to or greater than the minimum yearly repayment required for income year 2011-12.\n\nInterest received by the private company must be included in the income tax return for 2011-12.\n\nMinimum yearly repayment\n\n$768.00\n\nBenchmark interest rate\n\n7.8%\n\nOpening balance:\n\nDate: 30/06/2011\n\nBalance: $2,556.00\n\nDays: 69\n\nInterest: $37.59\n\nPayments\n\nDate: 08/09/2011\n\nAmount: $2,432.00\n\nBalance: $124.00\n\nDays: 297\n\nInterest: $7.85\n\n\n\n\nTotal repayments\n\n$2,432.00\n\nTotal interest\n\n$45.44\n\nTotal principal\n\n$2,386.56\n\nClosing balance\n\nDate: 30/06/2012\n\nBalance: $169.44",
  "outputs": {
    "enquiryRateFormatted": "7.8%",
    "enquiryYearEndMinusOneDisplay": "30/06/2011",
    "amalgamatedLoanNotPaidByEOIYFormatted": "$2,556.00",
    "openingBalancePayDays": "69",
    "openingBalanceInterestFormatted": "$37.59",
    "totalAmountOfRepaymentFormatted": "$2,432.00",
    "totalInterestFormatted": "$45.44",
    "principalFormatted": "$2,386.56",
    "enquiryYearEndDisplay": "30/06/2012",
    "minimumYearRepaymentFormatted": "$768.00"
  },
  "repayments": [
    {
      "rd": "8/9/2011",
      "ra": 2432
    }
  ],
  "inputs": {
    "incomeYearOfLoan": 2010,
    "fullTermOfAmalgamatedLoan": 5,
    "incomeYearOfEnquiring": 2012,
    "amalgamatedLoanNotPaidByEOIY": 2556,
    "repayments": null,
    "lodgement_date": null
  },
  "idx": 2213
}