{
  "id": "2023-09-06T05:00:41.878Z0.5564122783881178",
  "alert": "Start of result\nResult\n\nMinimum yearly repayment met.\n\nThe amount of the loan not repaid at the end of income year 2012-13 is $34.76.\n\nThe amalgamated loan will not be taken to be a dividend because the total repayments made are equal to or greater than the minimum yearly repayment required for income year 2012-13.\n\nInterest received by the private company must be included in the income tax return for 2012-13.\n\nMinimum yearly repayment\n\n$0\n\nBenchmark interest rate\n\n7.05%\n\nOpening balance:\n\nDate: 30/06/2012\n\nBalance: $3,912.00\n\nDays: 46\n\nInterest: $34.76\n\nPayments\n\nDate: 16/08/2012\n\nAmount: $3,912.00\n\nBalance: $0\n\nDays: 319\n\nInterest: $0\n\n\n\n\nTotal repayments\n\n$3,912.00\n\nTotal interest\n\n$34.76\n\nTotal principal\n\n$3,877.24\n\nClosing balance\n\nDate: 30/06/2013\n\nBalance: $34.76",
  "outputs": {
    "enquiryRateFormatted": "7.05%",
    "enquiryYearEndMinusOneDisplay": "30/06/2012",
    "amalgamatedLoanNotPaidByEOIYFormatted": "$3,912.00",
    "openingBalancePayDays": "46",
    "openingBalanceInterestFormatted": "$34.76",
    "totalAmountOfRepaymentFormatted": "$3,912.00",
    "totalInterestFormatted": "$34.76",
    "principalFormatted": "$3,877.24",
    "enquiryYearEndDisplay": "30/06/2013",
    "minimumYearRepaymentFormatted": "$0"
  },
  "repayments": [
    {
      "rd": "16/8/2012",
      "ra": 3912
    }
  ],
  "inputs": {
    "incomeYearOfLoan": 2012,
    "fullTermOfAmalgamatedLoan": 4,
    "incomeYearOfEnquiring": 2013,
    "amalgamatedLoanNotPaidByEOIY": 3912,
    "repayments": null,
    "lodgement_date": "12/9/2012"
  },
  "idx": 439
}