{
  "id": "2023-10-31T18:46:40.778Z0.6150464778946735",
  "alert": "Start of result\nResult\n\nAmalgamated loan fully repaid.\n\nThe amalgamated loan has been paid in full.\u000bThe private company is not taken under Division 7A to pay a dividend to the shareholder or shareholder's associate.\n\nInterest received by the private company must be included in the income tax return for 2007-08.\n\nMinimum yearly repayment\n\n-$151.00\n\nBenchmark interest rate\n\n8.05%\n\nOpening balance:\n\nDate: 30/06/2007\n\nBalance: $15.50\n\nDays: 25\n\nInterest: $0.09\n\nPayments\n\nDate: 26/07/2007\n\nAmount: $155.01\n\nBalance: $0\n\nDays: 341\n\nInterest: $0\n\n\n\n\nTotal repayments\n\n$155.01\n\nTotal interest\n\n$0.09\n\nTotal principal\n\n$154.92\n\nClosing balance\n\nDate: 30/06/2008\n\nBalance: $0",
  "outputs": {
    "enquiryRateFormatted": "8.05%",
    "enquiryYearEndMinusOneDisplay": "30/06/2007",
    "amalgamatedLoanNotPaidByEOIYFormatted": "$15.50",
    "openingBalancePayDays": "25",
    "openingBalanceInterestFormatted": "$0.09",
    "totalAmountOfRepaymentFormatted": "$155.01",
    "totalInterestFormatted": "$0.09",
    "principalFormatted": "$154.92",
    "enquiryYearEndDisplay": "30/06/2008",
    "minimumYearRepaymentFormatted": "-$151.00",
    "loanAmountFormatted": "$0"
  },
  "repayments": [
    {
      "rd": "26/7/2007",
      "ra": 155.01631579171908
    }
  ],
  "inputs": {
    "incomeYearOfLoan": 2007,
    "fullTermOfAmalgamatedLoan": 1,
    "incomeYearOfEnquiring": 2008,
    "amalgamatedLoanNotPaidByEOIY": 15.501631579171917,
    "repayments": null,
    "lodgement_date": "27/3/2008"
  },
  "idx": 4535
}