{
  "id": "2023-10-31T17:51:06.007Z0.8382437501026824",
  "alert": "Start of result\nResult\n\nAmalgamated loan fully repaid.\n\nThe amalgamated loan has been paid in full.\u000bThe private company is not taken under Division 7A to pay a dividend to the shareholder or shareholder's associate.\n\nInterest received by the private company must be included in the income tax return for 2015-16.\n\nMinimum yearly repayment\n\n$2.00\n\nBenchmark interest rate\n\n5.45%\n\nOpening balance:\n\nDate: 30/06/2015\n\nBalance: $10.46\n\nDays: 227\n\nInterest: $0.35\n\nPayments\n\nDate: 13/02/2016\n\nAmount: $104.60\n\nBalance: $0\n\nDays: 139\n\nInterest: $0\n\n\n\n\nTotal repayments\n\n$104.60\n\nTotal interest\n\n$0.35\n\nTotal principal\n\n$104.25\n\nClosing balance\n\nDate: 30/06/2016\n\nBalance: $0",
  "outputs": {
    "enquiryRateFormatted": "5.45%",
    "enquiryYearEndMinusOneDisplay": "30/06/2015",
    "amalgamatedLoanNotPaidByEOIYFormatted": "$10.46",
    "openingBalancePayDays": "227",
    "openingBalanceInterestFormatted": "$0.35",
    "totalAmountOfRepaymentFormatted": "$104.60",
    "totalInterestFormatted": "$0.35",
    "principalFormatted": "$104.25",
    "enquiryYearEndDisplay": "30/06/2016",
    "minimumYearRepaymentFormatted": "$2.00",
    "loanAmountFormatted": "$0"
  },
  "repayments": [
    {
      "rd": "13/2/2016",
      "ra": 104.60278487430651
    }
  ],
  "inputs": {
    "incomeYearOfLoan": 2014,
    "fullTermOfAmalgamatedLoan": 6,
    "incomeYearOfEnquiring": 2016,
    "amalgamatedLoanNotPaidByEOIY": 10.460278487430651,
    "repayments": null,
    "lodgement_date": null
  },
  "idx": 2735
}