{
  "id": "2023-09-05T18:28:13.367Z0.7125359745565965",
  "alert": "Start of result\nResult\n\nMinimum yearly repayment met.\n\nThe amount of the loan not repaid at the end of income year 2019-20 is $0.68.\n\nThe amalgamated loan will not be taken to be a dividend because the total repayments made are equal to or greater than the minimum yearly repayment required for income year 2019-20.\n\nInterest received by the private company must be included in the income tax return for 2019-20.\n\nMinimum yearly repayment\n\n$7.00\n\nBenchmark interest rate\n\n5.37%\n\nOpening balance:\n\nDate: 30/06/2019\n\nBalance: $25.15\n\nDays: 184\n\nInterest: $0.68\n\nPayments\n\nDate: 01/01/2020\n\nAmount: $25.15\n\nBalance: $0\n\nDays: 182\n\nInterest: $0\n\n\n\n\nTotal repayments\n\n$25.15\n\nTotal interest\n\n$0.68\n\nTotal principal\n\n$24.47\n\nClosing balance\n\nDate: 30/06/2020\n\nBalance: $0.68",
  "outputs": {
    "enquiryRateFormatted": "5.37%",
    "enquiryYearEndMinusOneDisplay": "30/06/2019",
    "amalgamatedLoanNotPaidByEOIYFormatted": "$25.15",
    "openingBalancePayDays": "184",
    "openingBalanceInterestFormatted": "$0.68",
    "totalAmountOfRepaymentFormatted": "$25.15",
    "totalInterestFormatted": "$0.68",
    "principalFormatted": "$24.47",
    "enquiryYearEndDisplay": "30/06/2020",
    "minimumYearRepaymentFormatted": "$7.00"
  },
  "repayments": [
    {
      "rd": "1/1/2020",
      "ra": 25.155119477950393
    }
  ],
  "inputs": {
    "incomeYearOfLoan": 2018,
    "fullTermOfAmalgamatedLoan": 5,
    "incomeYearOfEnquiring": 2020,
    "amalgamatedLoanNotPaidByEOIY": 25.15511947795076,
    "repayments": null,
    "lodgement_date": null
  },
  "idx": 7759
}