{
  "id": "2023-09-05T19:55:56.005Z0.6350914142207789",
  "alert": "Start of result\nResult\n\nMinimum yearly repayment met.\n\nThe amount of the loan not repaid at the end of income year 2018-19 is $3.62.\n\nThe amalgamated loan will not be taken to be a dividend because the total repayments made are equal to or greater than the minimum yearly repayment required for income year 2018-19.\n\nInterest received by the private company must be included in the income tax return for 2018-19.\n\nMinimum yearly repayment\n\n$25.00\n\nBenchmark interest rate\n\n5.2%\n\nOpening balance:\n\nDate: 30/06/2018\n\nBalance: $86.79\n\nDays: 293\n\nInterest: $3.62\n\nPayments\n\nDate: 20/04/2019\n\nAmount: $86.79\n\nBalance: $0\n\nDays: 72\n\nInterest: $0\n\n\n\n\nTotal repayments\n\n$86.79\n\nTotal interest\n\n$3.62\n\nTotal principal\n\n$83.17\n\nClosing balance\n\nDate: 30/06/2019\n\nBalance: $3.62",
  "outputs": {
    "enquiryRateFormatted": "5.2%",
    "enquiryYearEndMinusOneDisplay": "30/06/2018",
    "amalgamatedLoanNotPaidByEOIYFormatted": "$86.79",
    "openingBalancePayDays": "293",
    "openingBalanceInterestFormatted": "$3.62",
    "totalAmountOfRepaymentFormatted": "$86.79",
    "totalInterestFormatted": "$3.62",
    "principalFormatted": "$83.17",
    "enquiryYearEndDisplay": "30/06/2019",
    "minimumYearRepaymentFormatted": "$25.00"
  },
  "repayments": [
    {
      "rd": "20/4/2019",
      "ra": 86.79839190107668
    }
  ],
  "inputs": {
    "incomeYearOfLoan": 2017,
    "fullTermOfAmalgamatedLoan": 5,
    "incomeYearOfEnquiring": 2019,
    "amalgamatedLoanNotPaidByEOIY": 86.79839190107677,
    "repayments": null,
    "lodgement_date": null
  },
  "idx": 4423
}