{
  "id": "2023-09-06T00:14:13.156Z0.09394447470335154",
  "alert": "Start of result\nResult\n\nMinimum yearly repayment not met.\n\nThe amount of the loan not repaid at the end of income year 2021-22 is $12.35.\n\nThe private company may be taken to pay a dividend under Division 7A to the shareholder or shareholder's associate because the amount repaid during income year 2021-22 in relation to the amalgamated loan is less than the minimum yearly repayment required.\n\nInterest received by the private company must be included in the income tax return for 2021-22.\n\nMinimum yearly repayment\n\n$3,067.00\n\nBenchmark interest rate\n\n4.52%\n\nOpening balance:\n\nDate: 30/06/2021\n\nBalance: $2,934.00\n\nDays: 34\n\nInterest: $12.35\n\nPayments\n\nDate: 04/08/2021\n\nAmount: $2,934.00\n\nBalance: $0\n\nDays: 331\n\nInterest: $0\n\n\n\n\nTotal repayments\n\n$2,934.00\n\nTotal interest\n\n$12.35\n\nTotal principal\n\n$2,921.65\n\nClosing balance\n\nDate: 30/06/2022\n\nBalance: $12.35",
  "outputs": {
    "enquiryRateFormatted": "4.52%",
    "enquiryYearEndMinusOneDisplay": "30/06/2021",
    "amalgamatedLoanNotPaidByEOIYFormatted": "$2,934.00",
    "openingBalancePayDays": "34",
    "openingBalanceInterestFormatted": "$12.35",
    "totalAmountOfRepaymentFormatted": "$2,934.00",
    "totalInterestFormatted": "$12.35",
    "principalFormatted": "$2,921.65",
    "enquiryYearEndDisplay": "30/06/2022",
    "minimumYearRepaymentFormatted": "$3,067.00"
  },
  "repayments": [
    {
      "rd": "4/8/2021",
      "ra": 2934
    }
  ],
  "inputs": {
    "incomeYearOfLoan": 2015,
    "fullTermOfAmalgamatedLoan": 7,
    "incomeYearOfEnquiring": 2022,
    "amalgamatedLoanNotPaidByEOIY": 2934,
    "repayments": null,
    "lodgement_date": null
  },
  "idx": 2223
}