{
  "id": "2023-10-31T18:13:49.361Z0.8028306180242459",
  "alert": "Start of result\nResult\n\nAmalgamated loan fully repaid.\n\nThe amalgamated loan has been paid in full.\u000bThe private company is not taken under Division 7A to pay a dividend to the shareholder or shareholder's associate.\n\nInterest received by the private company must be included in the income tax return for 2014-15.\n\nMinimum yearly repayment\n\n$30.00\n\nBenchmark interest rate\n\n5.95%\n\nOpening balance:\n\nDate: 30/06/2014\n\nBalance: $104.70\n\nDays: 236\n\nInterest: $4.03\n\nPayments\n\nDate: 22/02/2015\n\nAmount: $1,047.07\n\nBalance: $0\n\nDays: 129\n\nInterest: $0\n\n\n\n\nTotal repayments\n\n$1,047.07\n\nTotal interest\n\n$4.03\n\nTotal principal\n\n$1,043.04\n\nClosing balance\n\nDate: 30/06/2015\n\nBalance: $0",
  "outputs": {
    "enquiryRateFormatted": "5.95%",
    "enquiryYearEndMinusOneDisplay": "30/06/2014",
    "amalgamatedLoanNotPaidByEOIYFormatted": "$104.70",
    "openingBalancePayDays": "236",
    "openingBalanceInterestFormatted": "$4.03",
    "totalAmountOfRepaymentFormatted": "$1,047.07",
    "totalInterestFormatted": "$4.03",
    "principalFormatted": "$1,043.04",
    "enquiryYearEndDisplay": "30/06/2015",
    "minimumYearRepaymentFormatted": "$30.00",
    "loanAmountFormatted": "$0"
  },
  "repayments": [
    {
      "rd": "22/2/2015",
      "ra": 1047.0750023571836
    }
  ],
  "inputs": {
    "incomeYearOfLoan": 2011,
    "fullTermOfAmalgamatedLoan": 7,
    "incomeYearOfEnquiring": 2015,
    "amalgamatedLoanNotPaidByEOIY": 104.70750023571837,
    "repayments": null,
    "lodgement_date": null
  },
  "idx": 3581
}