{
  "id": "2023-10-31T20:11:44.972Z0.7996607324726624",
  "alert": "Start of result\nResult\n\nAmalgamated loan fully repaid.\n\nThe amalgamated loan has been paid in full.\u000bThe private company is not taken under Division 7A to pay a dividend to the shareholder or shareholder's associate.\n\nInterest received by the private company must be included in the income tax return for 2001-02.\n\nMinimum yearly repayment\n\n$63.00\n\nBenchmark interest rate\n\n6.8%\n\nOpening balance:\n\nDate: 30/06/2001\n\nBalance: $113.32\n\nDays: 353\n\nInterest: $7.45\n\nPayments\n\nDate: 19/06/2002\n\nAmount: $1,133.20\n\nBalance: $0\n\nDays: 12\n\nInterest: $0\n\n\n\n\nTotal repayments\n\n$1,133.20\n\nTotal interest\n\n$7.45\n\nTotal principal\n\n$1,125.75\n\nClosing balance\n\nDate: 30/06/2002\n\nBalance: $0",
  "outputs": {
    "enquiryRateFormatted": "6.8%",
    "enquiryYearEndMinusOneDisplay": "30/06/2001",
    "amalgamatedLoanNotPaidByEOIYFormatted": "$113.32",
    "openingBalancePayDays": "353",
    "openingBalanceInterestFormatted": "$7.45",
    "totalAmountOfRepaymentFormatted": "$1,133.20",
    "totalInterestFormatted": "$7.45",
    "principalFormatted": "$1,125.75",
    "enquiryYearEndDisplay": "30/06/2002",
    "minimumYearRepaymentFormatted": "$63.00",
    "loanAmountFormatted": "$0"
  },
  "repayments": [
    {
      "rd": "19/6/2002",
      "ra": 1133.2062723681129
    }
  ],
  "inputs": {
    "incomeYearOfLoan": 2001,
    "fullTermOfAmalgamatedLoan": 2,
    "incomeYearOfEnquiring": 2002,
    "amalgamatedLoanNotPaidByEOIY": 113.32062723681126,
    "repayments": null,
    "lodgement_date": "28/11/2001"
  },
  "idx": 6257
}