{
  "id": "2023-10-31T18:33:34.833Z0.30339098846928514",
  "alert": "Start of result\nResult\n\nAmalgamated loan fully repaid.\n\nThe amalgamated loan has been paid in full.\u000bThe private company is not taken under Division 7A to pay a dividend to the shareholder or shareholder's associate.\n\nInterest received by the private company must be included in the income tax return for 2014-15.\n\nMinimum yearly repayment\n\n$30.00\n\nBenchmark interest rate\n\n5.95%\n\nOpening balance:\n\nDate: 30/06/2014\n\nBalance: $55.29\n\nDays: 200\n\nInterest: $1.80\n\nPayments\n\nDate: 17/01/2015\n\nAmount: $552.94\n\nBalance: $0\n\nDays: 165\n\nInterest: $0\n\n\n\n\nTotal repayments\n\n$552.94\n\nTotal interest\n\n$1.80\n\nTotal principal\n\n$551.14\n\nClosing balance\n\nDate: 30/06/2015\n\nBalance: $0",
  "outputs": {
    "enquiryRateFormatted": "5.95%",
    "enquiryYearEndMinusOneDisplay": "30/06/2014",
    "amalgamatedLoanNotPaidByEOIYFormatted": "$55.29",
    "openingBalancePayDays": "200",
    "openingBalanceInterestFormatted": "$1.80",
    "totalAmountOfRepaymentFormatted": "$552.94",
    "totalInterestFormatted": "$1.80",
    "principalFormatted": "$551.14",
    "enquiryYearEndDisplay": "30/06/2015",
    "minimumYearRepaymentFormatted": "$30.00",
    "loanAmountFormatted": "$0"
  },
  "repayments": [
    {
      "rd": "17/1/2015",
      "ra": 552.9471395466381
    }
  ],
  "inputs": {
    "incomeYearOfLoan": 2009,
    "fullTermOfAmalgamatedLoan": 7,
    "incomeYearOfEnquiring": 2015,
    "amalgamatedLoanNotPaidByEOIY": 55.29471395466381,
    "repayments": null,
    "lodgement_date": null
  },
  "idx": 4175
}