{
  "id": "2023-10-31T17:15:30.778Z0.47800443130723835",
  "alert": "Start of result\nResult\n\nMinimum yearly repayment met.\n\nThe amount of the loan not repaid at the end of income year 2021-22 is $2,573.36.\n\n\u000b\n\nThe amalgamated loan will not be taken to be a dividend because the total repayments made are equal to or greater than the minimum yearly repayment required for income year 2021-22.\n\nInterest received by the private company must be included in the income tax return for 2021-22.\n\nMinimum yearly repayment\n\n$5,662.00\n\nBenchmark interest rate\n\n4.52%\n\nOpening balance:\n\nDate: 30/06/2021\n\nBalance: $10,600.00\n\nDays: 329\n\nInterest: $431.86\n\nPayments\n\nDate: 26/05/2022\n\nAmount: $8,468.00\n\nBalance: $2,132.00\n\nDays: 36\n\nInterest: $9.50\n\n\n\n\nTotal repayments\n\n$8,468.00\n\nTotal interest\n\n$441.36\n\nTotal principal\n\n$8,026.64\n\nClosing balance\n\nDate: 30/06/2022\n\nBalance: $2,573.36",
  "outputs": {
    "enquiryRateFormatted": "4.52%",
    "enquiryYearEndMinusOneDisplay": "30/06/2021",
    "amalgamatedLoanNotPaidByEOIYFormatted": "$10,600.00",
    "openingBalancePayDays": "329",
    "openingBalanceInterestFormatted": "$431.86",
    "totalAmountOfRepaymentFormatted": "$8,468.00",
    "totalInterestFormatted": "$441.36",
    "principalFormatted": "$8,026.64",
    "enquiryYearEndDisplay": "30/06/2022",
    "minimumYearRepaymentFormatted": "$5,662.00",
    "loanAmountFormatted": "$2,573.36"
  },
  "repayments": [
    {
      "rd": "26/5/2022",
      "ra": 8468
    }
  ],
  "inputs": {
    "incomeYearOfLoan": 2020,
    "fullTermOfAmalgamatedLoan": 3,
    "incomeYearOfEnquiring": 2022,
    "amalgamatedLoanNotPaidByEOIY": 10600,
    "repayments": null,
    "lodgement_date": null
  },
  "idx": 764
}