{
  "id": "2023-09-06T03:57:03.148Z0.05890473258505624",
  "alert": "Start of result\nResult\n\nMinimum yearly repayment not met.\n\nThe amount of the loan not repaid at the end of income year 2012-13 is $3,586.00.\n\nThe private company may be taken to pay a dividend under Division 7A to the shareholder or shareholder's associate because the amount repaid during income year 2012-13 in relation to the amalgamated loan is less than the minimum yearly repayment required.\n\nInterest received by the private company must be included in the income tax return for 2012-13.\n\nMinimum yearly repayment\n\n$3,839.00\n\nBenchmark interest rate\n\n7.05%\n\nOpening balance:\n\nDate: 30/06/2012\n\nBalance: $3,586.00\n\nDays: 365\n\nInterest: $252.81\n\nTotal repayments\n\n$0\n\nTotal interest\n\n$252.81\n\nTotal principal\n\n$0\n\nClosing balance\n\nDate: 30/06/2013\n\nBalance: $3,586.00",
  "outputs": {
    "enquiryRateFormatted": "7.05%",
    "enquiryYearEndMinusOneDisplay": "30/06/2012",
    "amalgamatedLoanNotPaidByEOIYFormatted": "$3,586.00",
    "openingBalancePayDays": "365",
    "openingBalanceInterestFormatted": "$252.81",
    "totalAmountOfRepaymentFormatted": "$0",
    "totalInterestFormatted": "$252.81",
    "principalFormatted": "$0",
    "enquiryYearEndDisplay": "30/06/2013",
    "minimumYearRepaymentFormatted": "$3,839.00"
  },
  "repayments": [],
  "inputs": {
    "incomeYearOfLoan": 2012,
    "fullTermOfAmalgamatedLoan": 1,
    "incomeYearOfEnquiring": 2013,
    "amalgamatedLoanNotPaidByEOIY": 3586,
    "repayments": null,
    "lodgement_date": "30/5/2013"
  },
  "idx": 5868
}