{
  "id": "2023-09-04T20:48:15.443Z0.20763133292428404",
  "alert": "Start of result\nResult\n\nMinimum yearly repayment not met.\n\nThe amount of the loan not repaid at the end of income year 2016-17 is $2,357.80.\n\nThe private company may be taken to pay a dividend under Division 7A to the shareholder or shareholder's associate because the amount repaid during income year 2016-17 in relation to the amalgamated loan is less than the minimum yearly repayment required.\n\nInterest received by the private company must be included in the income tax return for 2016-17.\n\nMinimum yearly repayment\n\n$987.00\n\nBenchmark interest rate\n\n5.4%\n\nOpening balance:\n\nDate: 30/06/2016\n\nBalance: $2,669.00\n\nDays: 0\n\nInterest: $0\n\nPayments\n\nDate: 01/07/2016\n\nAmount: $432.00\n\nBalance: $2,237.00\n\nDays: 365\n\nInterest: $120.80\n\n\n\n\nTotal repayments\n\n$432.00\n\nTotal interest\n\n$120.80\n\nTotal principal\n\n$311.20\n\nClosing balance\n\nDate: 30/06/2017\n\nBalance: $2,357.80",
  "outputs": {
    "enquiryRateFormatted": "5.4%",
    "enquiryYearEndMinusOneDisplay": "30/06/2016",
    "amalgamatedLoanNotPaidByEOIYFormatted": "$2,669.00",
    "openingBalancePayDays": "0",
    "openingBalanceInterestFormatted": "$0",
    "totalAmountOfRepaymentFormatted": "$432.00",
    "totalInterestFormatted": "$120.80",
    "principalFormatted": "$311.20",
    "enquiryYearEndDisplay": "30/06/2017",
    "minimumYearRepaymentFormatted": "$987.00"
  },
  "repayments": [
    {
      "rd": "1/7/2016",
      "ra": 432
    }
  ],
  "inputs": {
    "incomeYearOfLoan": 2012,
    "fullTermOfAmalgamatedLoan": 7,
    "incomeYearOfEnquiring": 2017,
    "amalgamatedLoanNotPaidByEOIY": 2669,
    "repayments": null,
    "lodgement_date": null
  },
  "idx": 32
}