{
  "id": "2023-10-31T19:23:00.805Z0.995752218861708",
  "alert": "Start of result\nResult\n\nMinimum yearly repayment not met.\n\nThe amount of the loan not repaid at the end of income year 2004-05 is $65.80.\n\nThe private company may be taken to pay a dividend under Division 7A to the shareholder or shareholder's associate because the amount repaid during income year 2004-05 in relation to the amalgamated loan is less than the minimum yearly repayment required.\n\nInterest received by the private company must be included in the income tax return for 2004-05.\n\nMinimum yearly repayment\n\n$70.00\n\nBenchmark interest rate\n\n7.05%\n\nOpening balance:\n\nDate: 30/06/2004\n\nBalance: $65.80\n\nDays: 365\n\nInterest: $4.64\n\nTotal repayments\n\n$0\n\nTotal interest\n\n$4.64\n\nTotal principal\n\n$0\n\nClosing balance\n\nDate: 30/06/2005\n\nBalance: $65.80",
  "outputs": {
    "enquiryRateFormatted": "7.05%",
    "enquiryYearEndMinusOneDisplay": "30/06/2004",
    "amalgamatedLoanNotPaidByEOIYFormatted": "$65.80",
    "openingBalancePayDays": "365",
    "openingBalanceInterestFormatted": "$4.64",
    "totalAmountOfRepaymentFormatted": "$0",
    "totalInterestFormatted": "$4.64",
    "principalFormatted": "$0",
    "enquiryYearEndDisplay": "30/06/2005",
    "minimumYearRepaymentFormatted": "$70.00",
    "loanAmountFormatted": "$65.80"
  },
  "repayments": [],
  "inputs": {
    "incomeYearOfLoan": 2004,
    "fullTermOfAmalgamatedLoan": 1,
    "incomeYearOfEnquiring": 2005,
    "amalgamatedLoanNotPaidByEOIY": 65.80832418952322,
    "repayments": null,
    "lodgement_date": "28/11/2004"
  },
  "idx": 5381
}