{
  "id": "2023-10-31T18:30:38.590Z0.25249986322759543",
  "alert": "Start of result\nResult\n\nAmalgamated loan fully repaid.\n\nThe amalgamated loan has been paid in full.\u000bThe private company is not taken under Division 7A to pay a dividend to the shareholder or shareholder's associate.\n\nInterest received by the private company must be included in the income tax return for 2013-14.\n\nMinimum yearly repayment\n\n$33.00\n\nBenchmark interest rate\n\n6.2%\n\nOpening balance:\n\nDate: 30/06/2013\n\nBalance: $31.09\n\nDays: 59\n\nInterest: $0.31\n\nPayments\n\nDate: 29/08/2013\n\nAmount: $310.91\n\nBalance: $0\n\nDays: 306\n\nInterest: $0\n\n\n\n\nTotal repayments\n\n$310.91\n\nTotal interest\n\n$0.31\n\nTotal principal\n\n$310.60\n\nClosing balance\n\nDate: 30/06/2014\n\nBalance: $0",
  "outputs": {
    "enquiryRateFormatted": "6.2%",
    "enquiryYearEndMinusOneDisplay": "30/06/2013",
    "amalgamatedLoanNotPaidByEOIYFormatted": "$31.09",
    "openingBalancePayDays": "59",
    "openingBalanceInterestFormatted": "$0.31",
    "totalAmountOfRepaymentFormatted": "$310.91",
    "totalInterestFormatted": "$0.31",
    "principalFormatted": "$310.60",
    "enquiryYearEndDisplay": "30/06/2014",
    "minimumYearRepaymentFormatted": "$33.00",
    "loanAmountFormatted": "$0"
  },
  "repayments": [
    {
      "rd": "29/8/2013",
      "ra": 310.9122163144084
    }
  ],
  "inputs": {
    "incomeYearOfLoan": 2009,
    "fullTermOfAmalgamatedLoan": 5,
    "incomeYearOfEnquiring": 2014,
    "amalgamatedLoanNotPaidByEOIY": 31.091221631440824,
    "repayments": null,
    "lodgement_date": null
  },
  "idx": 4097
}