{
  "id": "2023-09-04T22:19:12.136Z0.9803930903260574",
  "alert": "Start of result\nResult\n\nMinimum yearly repayment not met.\n\nThe amount of the loan not repaid at the end of income year 2007-08 is $68,573,669.06.\n\nThe private company may be taken to pay a dividend under Division 7A to the shareholder or shareholder's associate because the amount repaid during income year 2007-08 in relation to the amalgamated loan is less than the minimum yearly repayment required.\n\nInterest received by the private company must be included in the income tax return for 2007-08.\n\nMinimum yearly repayment\n\n$74,093,849.00\n\nBenchmark interest rate\n\n8.05%\n\nOpening balance:\n\nDate: 30/06/2007\n\nBalance: $68,573,669.06\n\nDays: 0\n\nInterest: $0\n\nPayments\n\nDate: 01/07/2007\n\nAmount: $356.00\n\nBalance: $68,573,313.06\n\nDays: 366\n\nInterest: $5,520,151.70\n\n\n\n\nTotal repayments\n\n$356.00\n\nTotal interest\n\n$5,520,151.70\n\nTotal principal\n\n$0\n\nClosing balance\n\nDate: 30/06/2008\n\nBalance: $68,573,669.06",
  "outputs": {
    "enquiryRateFormatted": "8.05%",
    "enquiryYearEndMinusOneDisplay": "30/06/2007",
    "amalgamatedLoanNotPaidByEOIYFormatted": "$68,573,669.06",
    "openingBalancePayDays": "0",
    "openingBalanceInterestFormatted": "$0",
    "totalAmountOfRepaymentFormatted": "$356.00",
    "totalInterestFormatted": "$5,520,151.70",
    "principalFormatted": "$0",
    "enquiryYearEndDisplay": "30/06/2008",
    "minimumYearRepaymentFormatted": "$74,093,849.00"
  },
  "repayments": [
    {
      "rd": "1/7/2007",
      "ra": 356
    }
  ],
  "inputs": {
    "incomeYearOfLoan": 2001,
    "fullTermOfAmalgamatedLoan": 7,
    "incomeYearOfEnquiring": 2008,
    "amalgamatedLoanNotPaidByEOIY": 68573669.06603718,
    "repayments": null,
    "lodgement_date": null
  },
  "idx": 700
}