{
  "id": "2023-09-04T20:51:59.989Z0.0819573339540911",
  "alert": "Start of result\nResult\n\nMinimum yearly repayment not met.\n\nThe amount of the loan not repaid at the end of income year 2015-16 is $68,451,111.60.\n\nThe private company may be taken to pay a dividend under Division 7A to the shareholder or shareholder's associate because the amount repaid during income year 2015-16 in relation to the amalgamated loan is less than the minimum yearly repayment required.\n\nInterest received by the private company must be included in the income tax return for 2015-16.\n\nMinimum yearly repayment\n\n$37,048,235.00\n\nBenchmark interest rate\n\n5.45%\n\nOpening balance:\n\nDate: 30/06/2015\n\nBalance: $68,451,111.60\n\nDays: 366\n\nInterest: $3,730,585.58\n\nTotal repayments\n\n$0\n\nTotal interest\n\n$3,730,585.58\n\nTotal principal\n\n$0\n\nClosing balance\n\nDate: 30/06/2016\n\nBalance: $68,451,111.60",
  "outputs": {
    "enquiryRateFormatted": "5.45%",
    "enquiryYearEndMinusOneDisplay": "30/06/2015",
    "amalgamatedLoanNotPaidByEOIYFormatted": "$68,451,111.60",
    "openingBalancePayDays": "366",
    "openingBalanceInterestFormatted": "$3,730,585.58",
    "totalAmountOfRepaymentFormatted": "$0",
    "totalInterestFormatted": "$3,730,585.58",
    "principalFormatted": "$0",
    "enquiryYearEndDisplay": "30/06/2016",
    "minimumYearRepaymentFormatted": "$37,048,235.00"
  },
  "repayments": [],
  "inputs": {
    "incomeYearOfLoan": 2011,
    "fullTermOfAmalgamatedLoan": 6,
    "incomeYearOfEnquiring": 2016,
    "amalgamatedLoanNotPaidByEOIY": 68451111.6039868,
    "repayments": null,
    "lodgement_date": null
  },
  "idx": 192
}