{
  "id": "2023-09-05T18:59:10.541Z0.5859733790355985",
  "alert": "Start of result\nResult\n\nMinimum yearly repayment not met.\n\nThe amount of the loan not repaid at the end of income year 2021-22 is $3,530.00.\n\nThe private company may be taken to pay a dividend under Division 7A to the shareholder or shareholder's associate because the amount repaid during income year 2021-22 in relation to the amalgamated loan is less than the minimum yearly repayment required.\n\nInterest received by the private company must be included in the income tax return for 2021-22.\n\nMinimum yearly repayment\n\n$984.00\n\nBenchmark interest rate\n\n4.52%\n\nOpening balance:\n\nDate: 30/06/2021\n\nBalance: $3,530.00\n\nDays: 365\n\nInterest: $159.56\n\nTotal repayments\n\n$0\n\nTotal interest\n\n$159.56\n\nTotal principal\n\n$0\n\nClosing balance\n\nDate: 30/06/2022\n\nBalance: $3,530.00",
  "outputs": {
    "enquiryRateFormatted": "4.52%",
    "enquiryYearEndMinusOneDisplay": "30/06/2021",
    "amalgamatedLoanNotPaidByEOIYFormatted": "$3,530.00",
    "openingBalancePayDays": "365",
    "openingBalanceInterestFormatted": "$159.56",
    "totalAmountOfRepaymentFormatted": "$0",
    "totalInterestFormatted": "$159.56",
    "principalFormatted": "$0",
    "enquiryYearEndDisplay": "30/06/2022",
    "minimumYearRepaymentFormatted": "$984.00"
  },
  "repayments": [],
  "inputs": {
    "incomeYearOfLoan": 2018,
    "fullTermOfAmalgamatedLoan": 7,
    "incomeYearOfEnquiring": 2022,
    "amalgamatedLoanNotPaidByEOIY": 3530,
    "repayments": null,
    "lodgement_date": null
  },
  "idx": 736
}