{
  "id": "2023-10-31T18:12:02.592Z0.6203820314243484",
  "alert": "Start of result\nResult\n\nAmalgamated loan fully repaid.\n\nThe amalgamated loan has been paid in full.\u000bThe private company is not taken under Division 7A to pay a dividend to the shareholder or shareholder's associate.\n\nInterest received by the private company must be included in the income tax return for 2011-12.\n\nMinimum yearly repayment\n\n$1.00\n\nBenchmark interest rate\n\n7.8%\n\nOpening balance:\n\nDate: 30/06/2011\n\nBalance: $3.39\n\nDays: 249\n\nInterest: $0.18\n\nPayments\n\nDate: 06/03/2012\n\nAmount: $33.94\n\nBalance: $0\n\nDays: 117\n\nInterest: $0\n\n\n\n\nTotal repayments\n\n$33.94\n\nTotal interest\n\n$0.18\n\nTotal principal\n\n$33.76\n\nClosing balance\n\nDate: 30/06/2012\n\nBalance: $0",
  "outputs": {
    "enquiryRateFormatted": "7.8%",
    "enquiryYearEndMinusOneDisplay": "30/06/2011",
    "amalgamatedLoanNotPaidByEOIYFormatted": "$3.39",
    "openingBalancePayDays": "249",
    "openingBalanceInterestFormatted": "$0.18",
    "totalAmountOfRepaymentFormatted": "$33.94",
    "totalInterestFormatted": "$0.18",
    "principalFormatted": "$33.76",
    "enquiryYearEndDisplay": "30/06/2012",
    "minimumYearRepaymentFormatted": "$1.00",
    "loanAmountFormatted": "$0"
  },
  "repayments": [
    {
      "rd": "6/3/2012",
      "ra": 33.94509944494712
    }
  ],
  "inputs": {
    "incomeYearOfLoan": 2011,
    "fullTermOfAmalgamatedLoan": 5,
    "incomeYearOfEnquiring": 2012,
    "amalgamatedLoanNotPaidByEOIY": 3.3945099444946747,
    "repayments": null,
    "lodgement_date": "29/10/2011"
  },
  "idx": 3524
}