{
  "id": "2023-10-31T18:02:54.770Z0.3151372764234225",
  "alert": "Start of result\nResult\n\nMinimum yearly repayment not met.\n\nThe amount of the loan not repaid at the end of income year 2012-13 is $4,483.00.\n\nThe private company may be taken to pay a dividend under Division 7A to the shareholder or shareholder's associate because the amount repaid during income year 2012-13 in relation to the amalgamated loan is less than the minimum yearly repayment required.\n\nInterest received by the private company must be included in the income tax return for 2012-13.\n\nMinimum yearly repayment\n\n$1,325.00\n\nBenchmark interest rate\n\n7.05%\n\nOpening balance:\n\nDate: 30/06/2012\n\nBalance: $4,483.00\n\nDays: 365\n\nInterest: $316.05\n\nTotal repayments\n\n$0\n\nTotal interest\n\n$316.05\n\nTotal principal\n\n$0\n\nClosing balance\n\nDate: 30/06/2013\n\nBalance: $4,483.00",
  "outputs": {
    "enquiryRateFormatted": "7.05%",
    "enquiryYearEndMinusOneDisplay": "30/06/2012",
    "amalgamatedLoanNotPaidByEOIYFormatted": "$4,483.00",
    "openingBalancePayDays": "365",
    "openingBalanceInterestFormatted": "$316.05",
    "totalAmountOfRepaymentFormatted": "$0",
    "totalInterestFormatted": "$316.05",
    "principalFormatted": "$0",
    "enquiryYearEndDisplay": "30/06/2013",
    "minimumYearRepaymentFormatted": "$1,325.00",
    "loanAmountFormatted": "$4,483.00"
  },
  "repayments": [],
  "inputs": {
    "incomeYearOfLoan": 2012,
    "fullTermOfAmalgamatedLoan": 4,
    "incomeYearOfEnquiring": 2013,
    "amalgamatedLoanNotPaidByEOIY": 4483,
    "repayments": null,
    "lodgement_date": "28/3/2013"
  },
  "idx": 3201
}