{
  "id": "2023-09-04T17:23:20.042Z0.6762689671653515",
  "alert": "Start of result\nResult\n\nMinimum yearly repayment met.\n\nThe amount of the loan not repaid at the end of income year 2014-15 is $1.54.\n\nThe amalgamated loan will not be taken to be a dividend because the total repayments made are equal to or greater than the minimum yearly repayment required for income year 2014-15.\n\nInterest received by the private company must be included in the income tax return for 2014-15.\n\nMinimum yearly repayment\n\n$668.00\n\nBenchmark interest rate\n\n5.95%\n\nOpening balance:\n\nDate: 30/06/2014\n\nBalance: $2,318.00\n\nDays: 0\n\nInterest: $0\n\nPayments\n\nDate: 01/07/2014\n\nAmount: $2,014.00\n\nBalance: $304.00\n\nDays: 31\n\nInterest: $1.54\n\n\n\n\nDate: 01/08/2014\n\nAmount: $304.00\n\nBalance: $0\n\nDays: 334\n\nInterest: $0\n\n\n\n\nTotal repayments\n\n$2,318.00\n\nTotal interest\n\n$1.54\n\nTotal principal\n\n$2,316.46\n\nClosing balance\n\nDate: 30/06/2015\n\nBalance: $1.54",
  "outputs": {
    "enquiryRateFormatted": "5.95%",
    "enquiryYearEndMinusOneDisplay": "30/06/2014",
    "amalgamatedLoanNotPaidByEOIYFormatted": "$2,318.00",
    "openingBalancePayDays": "0",
    "openingBalanceInterestFormatted": "$0",
    "totalAmountOfRepaymentFormatted": "$2,318.00",
    "totalInterestFormatted": "$1.54",
    "principalFormatted": "$2,316.46",
    "enquiryYearEndDisplay": "30/06/2015",
    "minimumYearRepaymentFormatted": "$668.00"
  },
  "repayments": [
    {
      "rd": "1/7/2014",
      "ra": 2014
    },
    {
      "rd": "1/8/2014",
      "ra": 304
    }
  ],
  "inputs": {
    "incomeYearOfLoan": 2013,
    "fullTermOfAmalgamatedLoan": 5,
    "incomeYearOfEnquiring": 2015,
    "amalgamatedLoanNotPaidByEOIY": 2318,
    "repayments": null,
    "lodgement_date": null
  },
  "idx": 2076
}