{
  "id": "2023-10-31T17:26:37.497Z0.6874018808590501",
  "alert": "Start of result\nResult\n\nMinimum yearly repayment not met.\n\nThe amount of the loan not repaid at the end of income year 2017-18 is $105.55.\n\nThe private company may be taken to pay a dividend under Division 7A to the shareholder or shareholder's associate because the amount repaid during income year 2017-18 in relation to the amalgamated loan is less than the minimum yearly repayment required.\n\nInterest received by the private company must be included in the income tax return for 2017-18.\n\nMinimum yearly repayment\n\n$111.00\n\nBenchmark interest rate\n\n5.3%\n\nOpening balance:\n\nDate: 30/06/2017\n\nBalance: $105.55\n\nDays: 365\n\nInterest: $5.59\n\nTotal repayments\n\n$0\n\nTotal interest\n\n$5.59\n\nTotal principal\n\n$0\n\nClosing balance\n\nDate: 30/06/2018\n\nBalance: $105.55",
  "outputs": {
    "enquiryRateFormatted": "5.3%",
    "enquiryYearEndMinusOneDisplay": "30/06/2017",
    "amalgamatedLoanNotPaidByEOIYFormatted": "$105.55",
    "openingBalancePayDays": "365",
    "openingBalanceInterestFormatted": "$5.59",
    "totalAmountOfRepaymentFormatted": "$0",
    "totalInterestFormatted": "$5.59",
    "principalFormatted": "$0",
    "enquiryYearEndDisplay": "30/06/2018",
    "minimumYearRepaymentFormatted": "$111.00",
    "loanAmountFormatted": "$105.55"
  },
  "repayments": [],
  "inputs": {
    "incomeYearOfLoan": 2017,
    "fullTermOfAmalgamatedLoan": 1,
    "incomeYearOfEnquiring": 2018,
    "amalgamatedLoanNotPaidByEOIY": 105.55443925384006,
    "repayments": null,
    "lodgement_date": "1/7/2017"
  },
  "idx": 1503
}