{
  "id": "2023-10-31T20:16:54.949Z0.42883973765769845",
  "alert": "Start of result\nResult\n\nAmalgamated loan fully repaid.\n\nThe amalgamated loan has been paid in full.\u000bThe private company is not taken under Division 7A to pay a dividend to the shareholder or shareholder's associate.\n\nInterest received by the private company must be included in the income tax return for 2005-06.\n\nMinimum yearly repayment\n\n$70.00\n\nBenchmark interest rate\n\n7.3%\n\nOpening balance:\n\nDate: 30/06/2005\n\nBalance: $65.62\n\nDays: 44\n\nInterest: $0.58\n\nPayments\n\nDate: 14/08/2005\n\nAmount: $656.20\n\nBalance: $0\n\nDays: 321\n\nInterest: $0\n\n\n\n\nTotal repayments\n\n$656.20\n\nTotal interest\n\n$0.58\n\nTotal principal\n\n$655.62\n\nClosing balance\n\nDate: 30/06/2006\n\nBalance: $0",
  "outputs": {
    "enquiryRateFormatted": "7.3%",
    "enquiryYearEndMinusOneDisplay": "30/06/2005",
    "amalgamatedLoanNotPaidByEOIYFormatted": "$65.62",
    "openingBalancePayDays": "44",
    "openingBalanceInterestFormatted": "$0.58",
    "totalAmountOfRepaymentFormatted": "$656.20",
    "totalInterestFormatted": "$0.58",
    "principalFormatted": "$655.62",
    "enquiryYearEndDisplay": "30/06/2006",
    "minimumYearRepaymentFormatted": "$70.00",
    "loanAmountFormatted": "$0"
  },
  "repayments": [
    {
      "rd": "14/8/2005",
      "ra": 656.2050273524428
    }
  ],
  "inputs": {
    "incomeYearOfLoan": 2001,
    "fullTermOfAmalgamatedLoan": 5,
    "incomeYearOfEnquiring": 2006,
    "amalgamatedLoanNotPaidByEOIY": 65.62050273524427,
    "repayments": null,
    "lodgement_date": null
  },
  "idx": 6335
}