{
  "id": "2023-10-31T17:26:06.835Z0.5383170189027761",
  "alert": "Start of result\nResult\n\nAmalgamated loan fully repaid.\n\nThe amalgamated loan has been paid in full.\u000bThe private company is not taken under Division 7A to pay a dividend to the shareholder or shareholder's associate.\n\nInterest received by the private company must be included in the income tax return for 2020-21.\n\nMinimum yearly repayment\n\n$175.00\n\nBenchmark interest rate\n\n4.52%\n\nOpening balance:\n\nDate: 30/06/2020\n\nBalance: $767.00\n\nDays: 280\n\nInterest: $26.59\n\nPayments\n\nDate: 07/04/2021\n\nAmount: $5,401.00\n\nBalance: $0\n\nDays: 85\n\nInterest: $0\n\n\n\n\nTotal repayments\n\n$5,401.00\n\nTotal interest\n\n$26.59\n\nTotal principal\n\n$5,374.41\n\nClosing balance\n\nDate: 30/06/2021\n\nBalance: $0",
  "outputs": {
    "enquiryRateFormatted": "4.52%",
    "enquiryYearEndMinusOneDisplay": "30/06/2020",
    "amalgamatedLoanNotPaidByEOIYFormatted": "$767.00",
    "openingBalancePayDays": "280",
    "openingBalanceInterestFormatted": "$26.59",
    "totalAmountOfRepaymentFormatted": "$5,401.00",
    "totalInterestFormatted": "$26.59",
    "principalFormatted": "$5,374.41",
    "enquiryYearEndDisplay": "30/06/2021",
    "minimumYearRepaymentFormatted": "$175.00",
    "loanAmountFormatted": "$0"
  },
  "repayments": [
    {
      "rd": "7/4/2021",
      "ra": 5401
    }
  ],
  "inputs": {
    "incomeYearOfLoan": 2018,
    "fullTermOfAmalgamatedLoan": 7,
    "incomeYearOfEnquiring": 2021,
    "amalgamatedLoanNotPaidByEOIY": 767,
    "repayments": null,
    "lodgement_date": null
  },
  "idx": 1472
}