{
  "id": "2023-09-06T20:23:59.368Z0.8891059569828672",
  "alert": "Start of result\nResult\n\nMinimum yearly repayment not met.\n\nThe amount of the loan not repaid at the end of income year 2003-04 is $11.56.\n\nThe private company may be taken to pay a dividend under Division 7A to the shareholder or shareholder's associate because the amount repaid during income year 2003-04 in relation to the amalgamated loan is less than the minimum yearly repayment required.\n\nInterest received by the private company must be included in the income tax return for 2003-04.\n\nMinimum yearly repayment\n\n$2.00\n\nBenchmark interest rate\n\n6.55%\n\nOpening balance:\n\nDate: 30/06/2003\n\nBalance: $11.56\n\nDays: 366\n\nInterest: $0.76\n\nTotal repayments\n\n$0\n\nTotal interest\n\n$0.76\n\nTotal principal\n\n$0\n\nClosing balance\n\nDate: 30/06/2004\n\nBalance: $11.56",
  "outputs": {
    "enquiryRateFormatted": "6.55%",
    "enquiryYearEndMinusOneDisplay": "30/06/2003",
    "amalgamatedLoanNotPaidByEOIYFormatted": "$11.56",
    "openingBalancePayDays": "366",
    "openingBalanceInterestFormatted": "$0.76",
    "totalAmountOfRepaymentFormatted": "$0",
    "totalInterestFormatted": "$0.76",
    "principalFormatted": "$0",
    "enquiryYearEndDisplay": "30/06/2004",
    "minimumYearRepaymentFormatted": "$2.00"
  },
  "repayments": [],
  "inputs": {
    "incomeYearOfLoan": 2003,
    "fullTermOfAmalgamatedLoan": 7,
    "incomeYearOfEnquiring": 2004,
    "amalgamatedLoanNotPaidByEOIY": 11.566526978629438,
    "repayments": null,
    "lodgement_date": "24/4/2004"
  },
  "idx": 1791
}