{
  "id": "2023-10-31T19:03:09.237Z0.669968748278731",
  "alert": "Start of result\nResult\n\nMinimum yearly repayment not met.\n\nThe amount of the loan not repaid at the end of income year 2009-10 is $7,761.19.\n\nThe private company may be taken to pay a dividend under Division 7A to the shareholder or shareholder's associate because the amount repaid during income year 2009-10 in relation to the amalgamated loan is less than the minimum yearly repayment required.\n\nInterest received by the private company must be included in the income tax return for 2009-10.\n\nMinimum yearly repayment\n\n$11,171.00\n\nBenchmark interest rate\n\n5.75%\n\nOpening balance:\n\nDate: 30/06/2009\n\nBalance: $10,564.00\n\nDays: 135\n\nInterest: $224.67\n\nPayments\n\nDate: 13/11/2009\n\nAmount: $3,291.00\n\nBalance: $7,273.00\n\nDays: 230\n\nInterest: $263.52\n\n\n\n\nTotal repayments\n\n$3,291.00\n\nTotal interest\n\n$488.19\n\nTotal principal\n\n$2,802.81\n\nClosing balance\n\nDate: 30/06/2010\n\nBalance: $7,761.19",
  "outputs": {
    "enquiryRateFormatted": "5.75%",
    "enquiryYearEndMinusOneDisplay": "30/06/2009",
    "amalgamatedLoanNotPaidByEOIYFormatted": "$10,564.00",
    "openingBalancePayDays": "135",
    "openingBalanceInterestFormatted": "$224.67",
    "totalAmountOfRepaymentFormatted": "$3,291.00",
    "totalInterestFormatted": "$488.19",
    "principalFormatted": "$2,802.81",
    "enquiryYearEndDisplay": "30/06/2010",
    "minimumYearRepaymentFormatted": "$11,171.00",
    "loanAmountFormatted": "$7,761.19"
  },
  "repayments": [
    {
      "rd": "13/11/2009",
      "ra": 3291
    }
  ],
  "inputs": {
    "incomeYearOfLoan": 2006,
    "fullTermOfAmalgamatedLoan": 4,
    "incomeYearOfEnquiring": 2010,
    "amalgamatedLoanNotPaidByEOIY": 10564,
    "repayments": null,
    "lodgement_date": null
  },
  "idx": 4946
}