{
  "id": "2023-09-04T16:06:27.464Z0.18574591982185806",
  "alert": "Start of result\nResult\n\nMinimum yearly repayment not met.\n\nThe amount of the loan not repaid at the end of income year 2022-23 is $5,697.39.\n\nThe private company may be taken to pay a dividend under Division 7A to the shareholder or shareholder's associate because the amount repaid during income year 2022-23 in relation to the amalgamated loan is less than the minimum yearly repayment required.\n\nInterest received by the private company must be included in the income tax return for 2022-23.\n\nMinimum yearly repayment\n\n$6,067.00\n\nBenchmark interest rate\n\n4.77%\n\nOpening balance:\n\nDate: 30/06/2022\n\nBalance: $11,318.00\n\nDays: 0\n\nInterest: $0\n\nPayments\n\nDate: 01/07/2022\n\nAmount: $5,880.00\n\nBalance: $5,438.00\n\nDays: 365\n\nInterest: $259.39\n\n\n\n\nTotal repayments\n\n$5,880.00\n\nTotal interest\n\n$259.39\n\nTotal principal\n\n$5,620.61\n\nClosing balance\n\nDate: 30/06/2023\n\nBalance: $5,697.39",
  "outputs": {
    "enquiryRateFormatted": "4.77%",
    "enquiryYearEndMinusOneDisplay": "30/06/2022",
    "amalgamatedLoanNotPaidByEOIYFormatted": "$11,318.00",
    "openingBalancePayDays": "0",
    "openingBalanceInterestFormatted": "$0",
    "totalAmountOfRepaymentFormatted": "$5,880.00",
    "totalInterestFormatted": "$259.39",
    "principalFormatted": "$5,620.61",
    "enquiryYearEndDisplay": "30/06/2023",
    "minimumYearRepaymentFormatted": "$6,067.00"
  },
  "repayments": [
    {
      "rd": "1/7/2022",
      "ra": 5880
    }
  ],
  "inputs": {
    "incomeYearOfLoan": 2022,
    "fullTermOfAmalgamatedLoan": 2,
    "incomeYearOfEnquiring": 2023,
    "amalgamatedLoanNotPaidByEOIY": 11318,
    "repayments": null,
    "lodgement_date": "1/7/2022"
  },
  "idx": 72
}