{
  "id": "2023-10-31T19:09:12.833Z0.8523481522997196",
  "alert": "Start of result\nResult\n\nAmalgamated loan fully repaid.\n\nThe amalgamated loan has been paid in full.\u000bThe private company is not taken under Division 7A to pay a dividend to the shareholder or shareholder's associate.\n\nInterest received by the private company must be included in the income tax return for 2009-10.\n\nMinimum yearly repayment\n\n$1,194.00\n\nBenchmark interest rate\n\n5.75%\n\nOpening balance:\n\nDate: 30/06/2009\n\nBalance: $4,162.00\n\nDays: 256\n\nInterest: $167.85\n\nPayments\n\nDate: 14/03/2010\n\nAmount: $9,367.00\n\nBalance: $0\n\nDays: 109\n\nInterest: $0\n\n\n\n\nTotal repayments\n\n$9,367.00\n\nTotal interest\n\n$167.85\n\nTotal principal\n\n$9,199.15\n\nClosing balance\n\nDate: 30/06/2010\n\nBalance: $0",
  "outputs": {
    "enquiryRateFormatted": "5.75%",
    "enquiryYearEndMinusOneDisplay": "30/06/2009",
    "amalgamatedLoanNotPaidByEOIYFormatted": "$4,162.00",
    "openingBalancePayDays": "256",
    "openingBalanceInterestFormatted": "$167.85",
    "totalAmountOfRepaymentFormatted": "$9,367.00",
    "totalInterestFormatted": "$167.85",
    "principalFormatted": "$9,199.15",
    "enquiryYearEndDisplay": "30/06/2010",
    "minimumYearRepaymentFormatted": "$1,194.00",
    "loanAmountFormatted": "$0"
  },
  "repayments": [
    {
      "rd": "14/3/2010",
      "ra": 9367
    }
  ],
  "inputs": {
    "incomeYearOfLoan": 2006,
    "fullTermOfAmalgamatedLoan": 7,
    "incomeYearOfEnquiring": 2010,
    "amalgamatedLoanNotPaidByEOIY": 4162,
    "repayments": null,
    "lodgement_date": null
  },
  "idx": 5085
}