{
  "id": "2023-09-06T15:10:21.573Z0.8039856758123483",
  "alert": "Start of result\nResult\n\nMinimum yearly repayment met.\n\nThe amount of the loan not repaid at the end of income year 2011-12 is $170.77.\n\nThe amalgamated loan will not be taken to be a dividend because the total repayments made are equal to or greater than the minimum yearly repayment required for income year 2011-12.\n\nInterest received by the private company must be included in the income tax return for 2011-12.\n\nMinimum yearly repayment\n\n$2,409.00\n\nBenchmark interest rate\n\n7.8%\n\nOpening balance:\n\nDate: 30/06/2011\n\nBalance: $4,308.00\n\nDays: 186\n\nInterest: $170.77\n\nPayments\n\nDate: 03/01/2012\n\nAmount: $4,308.00\n\nBalance: $0\n\nDays: 180\n\nInterest: $0\n\n\n\n\nTotal repayments\n\n$4,308.00\n\nTotal interest\n\n$170.77\n\nTotal principal\n\n$4,137.23\n\nClosing balance\n\nDate: 30/06/2012\n\nBalance: $170.77",
  "outputs": {
    "enquiryRateFormatted": "7.8%",
    "enquiryYearEndMinusOneDisplay": "30/06/2011",
    "amalgamatedLoanNotPaidByEOIYFormatted": "$4,308.00",
    "openingBalancePayDays": "186",
    "openingBalanceInterestFormatted": "$170.77",
    "totalAmountOfRepaymentFormatted": "$4,308.00",
    "totalInterestFormatted": "$170.77",
    "principalFormatted": "$4,137.23",
    "enquiryYearEndDisplay": "30/06/2012",
    "minimumYearRepaymentFormatted": "$2,409.00"
  },
  "repayments": [
    {
      "rd": "3/1/2012",
      "ra": 4308
    }
  ],
  "inputs": {
    "incomeYearOfLoan": 2006,
    "fullTermOfAmalgamatedLoan": 7,
    "incomeYearOfEnquiring": 2012,
    "amalgamatedLoanNotPaidByEOIY": 4308,
    "repayments": null,
    "lodgement_date": null
  },
  "idx": 7761
}