{
  "id": "2023-10-31T18:13:42.538Z0.8761859022292672",
  "alert": "Start of result\nResult\n\nMinimum yearly repayment not met.\n\nThe amount of the loan not repaid at the end of income year 2015-16 is $12,204.00.\n\nThe private company may be taken to pay a dividend under Division 7A to the shareholder or shareholder's associate because the amount repaid during income year 2015-16 in relation to the amalgamated loan is less than the minimum yearly repayment required.\n\nInterest received by the private company must be included in the income tax return for 2015-16.\n\nMinimum yearly repayment\n\n$4,519.00\n\nBenchmark interest rate\n\n5.45%\n\nOpening balance:\n\nDate: 30/06/2015\n\nBalance: $12,204.00\n\nDays: 366\n\nInterest: $665.12\n\nTotal repayments\n\n$0\n\nTotal interest\n\n$665.12\n\nTotal principal\n\n$0\n\nClosing balance\n\nDate: 30/06/2016\n\nBalance: $12,204.00",
  "outputs": {
    "enquiryRateFormatted": "5.45%",
    "enquiryYearEndMinusOneDisplay": "30/06/2015",
    "amalgamatedLoanNotPaidByEOIYFormatted": "$12,204.00",
    "openingBalancePayDays": "366",
    "openingBalanceInterestFormatted": "$665.12",
    "totalAmountOfRepaymentFormatted": "$0",
    "totalInterestFormatted": "$665.12",
    "principalFormatted": "$0",
    "enquiryYearEndDisplay": "30/06/2016",
    "minimumYearRepaymentFormatted": "$4,519.00",
    "loanAmountFormatted": "$12,204.00"
  },
  "repayments": [],
  "inputs": {
    "incomeYearOfLoan": 2011,
    "fullTermOfAmalgamatedLoan": 7,
    "incomeYearOfEnquiring": 2016,
    "amalgamatedLoanNotPaidByEOIY": 12204,
    "repayments": null,
    "lodgement_date": null
  },
  "idx": 3578
}