{
  "id": "2023-10-31T19:08:40.233Z0.2679769217021376",
  "alert": "Start of result\nResult\n\nAmalgamated loan fully repaid.\n\nThe amalgamated loan has been paid in full.\u000bThe private company is not taken under Division 7A to pay a dividend to the shareholder or shareholder's associate.\n\nInterest received by the private company must be included in the income tax return for 2012-13.\n\nMinimum yearly repayment\n\n$2,790.00\n\nBenchmark interest rate\n\n7.05%\n\nOpening balance:\n\nDate: 30/06/2012\n\nBalance: $2,606.00\n\nDays: 213\n\nInterest: $107.21\n\nPayments\n\nDate: 30/01/2013\n\nAmount: $7,224.00\n\nBalance: $0\n\nDays: 152\n\nInterest: $0\n\n\n\n\nTotal repayments\n\n$7,224.00\n\nTotal interest\n\n$107.21\n\nTotal principal\n\n$7,116.79\n\nClosing balance\n\nDate: 30/06/2013\n\nBalance: $0",
  "outputs": {
    "enquiryRateFormatted": "7.05%",
    "enquiryYearEndMinusOneDisplay": "30/06/2012",
    "amalgamatedLoanNotPaidByEOIYFormatted": "$2,606.00",
    "openingBalancePayDays": "213",
    "openingBalanceInterestFormatted": "$107.21",
    "totalAmountOfRepaymentFormatted": "$7,224.00",
    "totalInterestFormatted": "$107.21",
    "principalFormatted": "$7,116.79",
    "enquiryYearEndDisplay": "30/06/2013",
    "minimumYearRepaymentFormatted": "$2,790.00",
    "loanAmountFormatted": "$0"
  },
  "repayments": [
    {
      "rd": "30/1/2013",
      "ra": 7224
    }
  ],
  "inputs": {
    "incomeYearOfLoan": 2006,
    "fullTermOfAmalgamatedLoan": 7,
    "incomeYearOfEnquiring": 2013,
    "amalgamatedLoanNotPaidByEOIY": 2606,
    "repayments": null,
    "lodgement_date": null
  },
  "idx": 5074
}