{
  "id": "2023-10-31T18:08:05.134Z0.417285559359193",
  "alert": "Start of result\nResult\n\nMinimum yearly repayment not met.\n\nThe amount of the loan not repaid at the end of income year 2011-12 is $1,879.26.\n\nThe private company may be taken to pay a dividend under Division 7A to the shareholder or shareholder's associate because the amount repaid during income year 2011-12 in relation to the amalgamated loan is less than the minimum yearly repayment required.\n\nInterest received by the private company must be included in the income tax return for 2011-12.\n\nMinimum yearly repayment\n\n$1,832.00\n\nBenchmark interest rate\n\n7.8%\n\nOpening balance:\n\nDate: 30/06/2011\n\nBalance: $2,872.00\n\nDays: 191\n\nInterest: $116.90\n\nPayments\n\nDate: 08/01/2012\n\nAmount: $1,173.00\n\nBalance: $1,699.00\n\nDays: 175\n\nInterest: $63.36\n\n\n\n\nTotal repayments\n\n$1,173.00\n\nTotal interest\n\n$180.26\n\nTotal principal\n\n$992.74\n\nClosing balance\n\nDate: 30/06/2012\n\nBalance: $1,879.26",
  "outputs": {
    "enquiryRateFormatted": "7.8%",
    "enquiryYearEndMinusOneDisplay": "30/06/2011",
    "amalgamatedLoanNotPaidByEOIYFormatted": "$2,872.00",
    "openingBalancePayDays": "191",
    "openingBalanceInterestFormatted": "$116.90",
    "totalAmountOfRepaymentFormatted": "$1,173.00",
    "totalInterestFormatted": "$180.26",
    "principalFormatted": "$992.74",
    "enquiryYearEndDisplay": "30/06/2012",
    "minimumYearRepaymentFormatted": "$1,832.00",
    "loanAmountFormatted": "$1,879.26"
  },
  "repayments": [
    {
      "rd": "8/1/2012",
      "ra": 1173
    }
  ],
  "inputs": {
    "incomeYearOfLoan": 2011,
    "fullTermOfAmalgamatedLoan": 1,
    "incomeYearOfEnquiring": 2012,
    "amalgamatedLoanNotPaidByEOIY": 2872,
    "repayments": null,
    "lodgement_date": "30/6/2012"
  },
  "idx": 3385
}