{
  "id": "2023-10-31T17:35:41.923Z0.40669644958365114",
  "alert": "Start of result\nResult\n\nMinimum yearly repayment not met.\n\nThe amount of the loan not repaid at the end of income year 2021-22 is $95.57.\n\nThe private company may be taken to pay a dividend under Division 7A to the shareholder or shareholder's associate because the amount repaid during income year 2021-22 in relation to the amalgamated loan is less than the minimum yearly repayment required.\n\nInterest received by the private company must be included in the income tax return for 2021-22.\n\nMinimum yearly repayment\n\n$100.00\n\nBenchmark interest rate\n\n4.52%\n\nOpening balance:\n\nDate: 30/06/2021\n\nBalance: $95.57\n\nDays: 365\n\nInterest: $4.32\n\nTotal repayments\n\n$0\n\nTotal interest\n\n$4.32\n\nTotal principal\n\n$0\n\nClosing balance\n\nDate: 30/06/2022\n\nBalance: $95.57",
  "outputs": {
    "enquiryRateFormatted": "4.52%",
    "enquiryYearEndMinusOneDisplay": "30/06/2021",
    "amalgamatedLoanNotPaidByEOIYFormatted": "$95.57",
    "openingBalancePayDays": "365",
    "openingBalanceInterestFormatted": "$4.32",
    "totalAmountOfRepaymentFormatted": "$0",
    "totalInterestFormatted": "$4.32",
    "principalFormatted": "$0",
    "enquiryYearEndDisplay": "30/06/2022",
    "minimumYearRepaymentFormatted": "$100.00",
    "loanAmountFormatted": "$95.57"
  },
  "repayments": [],
  "inputs": {
    "incomeYearOfLoan": 2016,
    "fullTermOfAmalgamatedLoan": 6,
    "incomeYearOfEnquiring": 2022,
    "amalgamatedLoanNotPaidByEOIY": 95.57153200607331,
    "repayments": null,
    "lodgement_date": null
  },
  "idx": 2010
}