{
  "id": "2023-09-05T18:43:16.938Z0.9378353022945647",
  "alert": "Start of result\nResult\n\nMinimum yearly repayment not met.\n\nThe amount of the loan not repaid at the end of income year 2020-21 is $4,349.29.\n\nThe private company may be taken to pay a dividend under Division 7A to the shareholder or shareholder's associate because the amount repaid during income year 2020-21 in relation to the amalgamated loan is less than the minimum yearly repayment required.\n\nInterest received by the private company must be included in the income tax return for 2020-21.\n\nMinimum yearly repayment\n\n$1,498.00\n\nBenchmark interest rate\n\n4.52%\n\nOpening balance:\n\nDate: 30/06/2020\n\nBalance: $5,372.00\n\nDays: 125\n\nInterest: $83.16\n\nPayments\n\nDate: 03/11/2020\n\nAmount: $1,229.00\n\nBalance: $4,143.00\n\nDays: 240\n\nInterest: $123.13\n\n\n\n\nTotal repayments\n\n$1,229.00\n\nTotal interest\n\n$206.29\n\nTotal principal\n\n$1,022.71\n\nClosing balance\n\nDate: 30/06/2021\n\nBalance: $4,349.29",
  "outputs": {
    "enquiryRateFormatted": "4.52%",
    "enquiryYearEndMinusOneDisplay": "30/06/2020",
    "amalgamatedLoanNotPaidByEOIYFormatted": "$5,372.00",
    "openingBalancePayDays": "125",
    "openingBalanceInterestFormatted": "$83.16",
    "totalAmountOfRepaymentFormatted": "$1,229.00",
    "totalInterestFormatted": "$206.29",
    "principalFormatted": "$1,022.71",
    "enquiryYearEndDisplay": "30/06/2021",
    "minimumYearRepaymentFormatted": "$1,498.00"
  },
  "repayments": [
    {
      "rd": "3/11/2020",
      "ra": 1229
    }
  ],
  "inputs": {
    "incomeYearOfLoan": 2018,
    "fullTermOfAmalgamatedLoan": 6,
    "incomeYearOfEnquiring": 2021,
    "amalgamatedLoanNotPaidByEOIY": 5372,
    "repayments": null,
    "lodgement_date": null
  },
  "idx": 8502
}