{
  "id": "2023-10-31T17:39:52.431Z0.4296368982211347",
  "alert": "Start of result\nResult\n\nMinimum yearly repayment not met.\n\nThe amount of the loan not repaid at the end of income year 2016-17 is $7,921.87.\n\nThe private company may be taken to pay a dividend under Division 7A to the shareholder or shareholder's associate because the amount repaid during income year 2016-17 in relation to the amalgamated loan is less than the minimum yearly repayment required.\n\nInterest received by the private company must be included in the income tax return for 2016-17.\n\nMinimum yearly repayment\n\n$4,581.00\n\nBenchmark interest rate\n\n5.4%\n\nOpening balance:\n\nDate: 30/06/2016\n\nBalance: $8,469.00\n\nDays: 287\n\nInterest: $359.60\n\nPayments\n\nDate: 14/04/2017\n\nAmount: $993.00\n\nBalance: $7,476.00\n\nDays: 78\n\nInterest: $86.27\n\n\n\n\nTotal repayments\n\n$993.00\n\nTotal interest\n\n$445.87\n\nTotal principal\n\n$547.13\n\nClosing balance\n\nDate: 30/06/2017\n\nBalance: $7,921.87",
  "outputs": {
    "enquiryRateFormatted": "5.4%",
    "enquiryYearEndMinusOneDisplay": "30/06/2016",
    "amalgamatedLoanNotPaidByEOIYFormatted": "$8,469.00",
    "openingBalancePayDays": "287",
    "openingBalanceInterestFormatted": "$359.60",
    "totalAmountOfRepaymentFormatted": "$993.00",
    "totalInterestFormatted": "$445.87",
    "principalFormatted": "$547.13",
    "enquiryYearEndDisplay": "30/06/2017",
    "minimumYearRepaymentFormatted": "$4,581.00",
    "loanAmountFormatted": "$7,921.87"
  },
  "repayments": [
    {
      "rd": "14/4/2017",
      "ra": 993
    }
  ],
  "inputs": {
    "incomeYearOfLoan": 2015,
    "fullTermOfAmalgamatedLoan": 3,
    "incomeYearOfEnquiring": 2017,
    "amalgamatedLoanNotPaidByEOIY": 8469,
    "repayments": null,
    "lodgement_date": null
  },
  "idx": 2223
}