{
  "id": "2023-09-06T05:35:57.977Z0.7700893609869319",
  "alert": "Start of result\nResult\n\nMinimum yearly repayment met.\n\nThe amount of the loan not repaid at the end of income year 2012-13 is $3.62.\n\nThe amalgamated loan will not be taken to be a dividend because the total repayments made are equal to or greater than the minimum yearly repayment required for income year 2012-13.\n\nInterest received by the private company must be included in the income tax return for 2012-13.\n\nMinimum yearly repayment\n\n$0\n\nBenchmark interest rate\n\n7.05%\n\nOpening balance:\n\nDate: 30/06/2012\n\nBalance: $112.09\n\nDays: 167\n\nInterest: $3.62\n\nPayments\n\nDate: 15/12/2012\n\nAmount: $112.09\n\nBalance: $0\n\nDays: 198\n\nInterest: $0\n\n\n\n\nTotal repayments\n\n$112.09\n\nTotal interest\n\n$3.62\n\nTotal principal\n\n$108.47\n\nClosing balance\n\nDate: 30/06/2013\n\nBalance: $3.62",
  "outputs": {
    "enquiryRateFormatted": "7.05%",
    "enquiryYearEndMinusOneDisplay": "30/06/2012",
    "amalgamatedLoanNotPaidByEOIYFormatted": "$112.09",
    "openingBalancePayDays": "167",
    "openingBalanceInterestFormatted": "$3.62",
    "totalAmountOfRepaymentFormatted": "$112.09",
    "totalInterestFormatted": "$3.62",
    "principalFormatted": "$108.47",
    "enquiryYearEndDisplay": "30/06/2013",
    "minimumYearRepaymentFormatted": "$0"
  },
  "repayments": [
    {
      "rd": "15/12/2012",
      "ra": 112.09706938125964
    }
  ],
  "inputs": {
    "incomeYearOfLoan": 2012,
    "fullTermOfAmalgamatedLoan": 7,
    "incomeYearOfEnquiring": 2013,
    "amalgamatedLoanNotPaidByEOIY": 112.09706938125912,
    "repayments": null,
    "lodgement_date": "22/1/2013"
  },
  "idx": 2804
}