{
  "id": "2023-09-06T17:22:04.256Z0.6280717292335283",
  "alert": "Start of result\nResult\n\nMinimum yearly repayment not met.\n\nThe amount of the loan not repaid at the end of income year 2004-05 is $8,046.82.\n\nThe private company may be taken to pay a dividend under Division 7A to the shareholder or shareholder's associate because the amount repaid during income year 2004-05 in relation to the amalgamated loan is less than the minimum yearly repayment required.\n\nInterest received by the private company must be included in the income tax return for 2004-05.\n\nMinimum yearly repayment\n\n$7,835.00\n\nBenchmark interest rate\n\n7.05%\n\nOpening balance:\n\nDate: 30/06/2004\n\nBalance: $11,927.00\n\nDays: 238\n\nInterest: $548.28\n\nPayments\n\nDate: 24/02/2005\n\nAmount: $4,608.00\n\nBalance: $7,319.00\n\nDays: 127\n\nInterest: $179.54\n\n\n\n\nTotal repayments\n\n$4,608.00\n\nTotal interest\n\n$727.82\n\nTotal principal\n\n$3,880.18\n\nClosing balance\n\nDate: 30/06/2005\n\nBalance: $8,046.82",
  "outputs": {
    "enquiryRateFormatted": "7.05%",
    "enquiryYearEndMinusOneDisplay": "30/06/2004",
    "amalgamatedLoanNotPaidByEOIYFormatted": "$11,927.00",
    "openingBalancePayDays": "238",
    "openingBalanceInterestFormatted": "$548.28",
    "totalAmountOfRepaymentFormatted": "$4,608.00",
    "totalInterestFormatted": "$727.82",
    "principalFormatted": "$3,880.18",
    "enquiryYearEndDisplay": "30/06/2005",
    "minimumYearRepaymentFormatted": "$7,835.00"
  },
  "repayments": [
    {
      "rd": "24/2/2005",
      "ra": 4608
    }
  ],
  "inputs": {
    "incomeYearOfLoan": 2004,
    "fullTermOfAmalgamatedLoan": 1,
    "incomeYearOfEnquiring": 2005,
    "amalgamatedLoanNotPaidByEOIY": 11927,
    "repayments": null,
    "lodgement_date": "14/5/2005"
  },
  "idx": 6954
}