{
  "id": "2023-09-04T17:17:35.224Z0.2289016571716327",
  "alert": "Start of result\nResult\n\nMinimum yearly repayment not met.\n\nThe amount of the loan not repaid at the end of income year 2019-20 is $18,522,242.02.\n\nThe private company may be taken to pay a dividend under Division 7A to the shareholder or shareholder's associate because the amount repaid during income year 2019-20 in relation to the amalgamated loan is less than the minimum yearly repayment required.\n\nInterest received by the private company must be included in the income tax return for 2019-20.\n\nMinimum yearly repayment\n\n$10,013,606.00\n\nBenchmark interest rate\n\n5.37%\n\nOpening balance:\n\nDate: 30/06/2019\n\nBalance: $18,522,242.02\n\nDays: 0\n\nInterest: $0\n\nPayments\n\nDate: 01/07/2019\n\nAmount: $578.00\n\nBalance: $18,521,664.02\n\nDays: 366\n\nInterest: $994,613.36\n\n\n\n\nTotal repayments\n\n$578.00\n\nTotal interest\n\n$994,613.36\n\nTotal principal\n\n$0\n\nClosing balance\n\nDate: 30/06/2020\n\nBalance: $18,522,242.02",
  "outputs": {
    "enquiryRateFormatted": "5.37%",
    "enquiryYearEndMinusOneDisplay": "30/06/2019",
    "amalgamatedLoanNotPaidByEOIYFormatted": "$18,522,242.02",
    "openingBalancePayDays": "0",
    "openingBalanceInterestFormatted": "$0",
    "totalAmountOfRepaymentFormatted": "$578.00",
    "totalInterestFormatted": "$994,613.36",
    "principalFormatted": "$0",
    "enquiryYearEndDisplay": "30/06/2020",
    "minimumYearRepaymentFormatted": "$10,013,606.00"
  },
  "repayments": [
    {
      "rd": "1/7/2019",
      "ra": 578
    }
  ],
  "inputs": {
    "incomeYearOfLoan": 2014,
    "fullTermOfAmalgamatedLoan": 7,
    "incomeYearOfEnquiring": 2020,
    "amalgamatedLoanNotPaidByEOIY": 18522242.026810084,
    "repayments": null,
    "lodgement_date": null
  },
  "idx": 1956
}