{
  "id": "2023-09-04T16:13:13.282Z0.4875920326125893",
  "alert": "Start of result\nResult\n\nMinimum yearly repayment not met.\n\nThe amount of the loan not repaid at the end of income year 2023-24 is $5,299.82.\n\nThe private company may be taken to pay a dividend under Division 7A to the shareholder or shareholder's associate because the amount repaid during income year 2023-24 in relation to the amalgamated loan is less than the minimum yearly repayment required.\n\nInterest received by the private company must be included in the income tax return for 2023-24.\n\nMinimum yearly repayment\n\n$1,743.00\n\nBenchmark interest rate\n\n8.27%\n\nOpening balance:\n\nDate: 30/06/2023\n\nBalance: $5,739.00\n\nDays: 0\n\nInterest: $0\n\nPayments\n\nDate: 01/07/2023\n\nAmount: $844.00\n\nBalance: $4,895.00\n\nDays: 366\n\nInterest: $404.82\n\n\n\n\nTotal repayments\n\n$844.00\n\nTotal interest\n\n$404.82\n\nTotal principal\n\n$439.18\n\nClosing balance\n\nDate: 30/06/2024\n\nBalance: $5,299.82",
  "outputs": {
    "enquiryRateFormatted": "8.27%",
    "enquiryYearEndMinusOneDisplay": "30/06/2023",
    "amalgamatedLoanNotPaidByEOIYFormatted": "$5,739.00",
    "openingBalancePayDays": "0",
    "openingBalanceInterestFormatted": "$0",
    "totalAmountOfRepaymentFormatted": "$844.00",
    "totalInterestFormatted": "$404.82",
    "principalFormatted": "$439.18",
    "enquiryYearEndDisplay": "30/06/2024",
    "minimumYearRepaymentFormatted": "$1,743.00"
  },
  "repayments": [
    {
      "rd": "1/7/2023",
      "ra": 844
    }
  ],
  "inputs": {
    "incomeYearOfLoan": 2022,
    "fullTermOfAmalgamatedLoan": 5,
    "incomeYearOfEnquiring": 2024,
    "amalgamatedLoanNotPaidByEOIY": 5739,
    "repayments": null,
    "lodgement_date": null
  },
  "idx": 11
}