{
  "id": "2023-09-05T09:49:29.904Z0.4073842251575317",
  "alert": "Start of result\nResult\n\nMinimum yearly repayment met.\n\nThe amount of the loan not repaid at the end of income year 2023-24 is $1.87.\n\nThe amalgamated loan will not be taken to be a dividend because the total repayments made are equal to or greater than the minimum yearly repayment required for income year 2023-24.\n\nInterest received by the private company must be included in the income tax return for 2023-24.\n\nMinimum yearly repayment\n\n$0\n\nBenchmark interest rate\n\n8.27%\n\nOpening balance:\n\nDate: 30/06/2023\n\nBalance: $49.36\n\nDays: 168\n\nInterest: $1.87\n\nPayments\n\nDate: 16/12/2023\n\nAmount: $49.36\n\nBalance: $0\n\nDays: 198\n\nInterest: $0\n\n\n\n\nTotal repayments\n\n$49.36\n\nTotal interest\n\n$1.87\n\nTotal principal\n\n$47.49\n\nClosing balance\n\nDate: 30/06/2024\n\nBalance: $1.87",
  "outputs": {
    "enquiryRateFormatted": "8.27%",
    "enquiryYearEndMinusOneDisplay": "30/06/2023",
    "amalgamatedLoanNotPaidByEOIYFormatted": "$49.36",
    "openingBalancePayDays": "168",
    "openingBalanceInterestFormatted": "$1.87",
    "totalAmountOfRepaymentFormatted": "$49.36",
    "totalInterestFormatted": "$1.87",
    "principalFormatted": "$47.49",
    "enquiryYearEndDisplay": "30/06/2024",
    "minimumYearRepaymentFormatted": "$0"
  },
  "repayments": [
    {
      "rd": "16/12/2023",
      "ra": 49.36600597377878
    }
  ],
  "inputs": {
    "incomeYearOfLoan": 2023,
    "fullTermOfAmalgamatedLoan": 1,
    "incomeYearOfEnquiring": 2024,
    "amalgamatedLoanNotPaidByEOIY": 49.36600597377884,
    "repayments": null,
    "lodgement_date": "11/1/2024"
  },
  "idx": 561
}