{
  "id": "2023-09-07T03:58:50.975Z0.9591776144389581",
  "alert": "Start of result\nResult\n\nMinimum yearly repayment not met.\n\nThe amount of the loan not repaid at the end of income year 1999-00 is $26.20.\n\nThe private company may be taken to pay a dividend under Division 7A to the shareholder or shareholder's associate because the amount repaid during income year 1999-00 in relation to the amalgamated loan is less than the minimum yearly repayment required.\n\nInterest received by the private company must be included in the income tax return for 1999-00.\n\nMinimum yearly repayment\n\n$6.00\n\nBenchmark interest rate\n\n6.5%\n\nOpening balance:\n\nDate: 30/06/1999\n\nBalance: $26.20\n\nDays: 366\n\nInterest: $1.70\n\nTotal repayments\n\n$0\n\nTotal interest\n\n$1.70\n\nTotal principal\n\n$0\n\nClosing balance\n\nDate: 30/06/2000\n\nBalance: $26.20",
  "outputs": {
    "enquiryRateFormatted": "6.5%",
    "enquiryYearEndMinusOneDisplay": "30/06/1999",
    "amalgamatedLoanNotPaidByEOIYFormatted": "$26.20",
    "openingBalancePayDays": "366",
    "openingBalanceInterestFormatted": "$1.70",
    "totalAmountOfRepaymentFormatted": "$0",
    "totalInterestFormatted": "$1.70",
    "principalFormatted": "$0",
    "enquiryYearEndDisplay": "30/06/2000",
    "minimumYearRepaymentFormatted": "$6.00"
  },
  "repayments": [],
  "inputs": {
    "incomeYearOfLoan": 1998,
    "fullTermOfAmalgamatedLoan": 6,
    "incomeYearOfEnquiring": 2000,
    "amalgamatedLoanNotPaidByEOIY": 26.206627088677134,
    "repayments": null,
    "lodgement_date": null
  },
  "idx": 2218
}