{
  "id": "2023-10-31T20:14:33.997Z0.5297978266211764",
  "alert": "Start of result\nResult\n\nMinimum yearly repayment not met.\n\nThe amount of the loan not repaid at the end of income year 2004-05 is $121.84.\n\nThe private company may be taken to pay a dividend under Division 7A to the shareholder or shareholder's associate because the amount repaid during income year 2004-05 in relation to the amalgamated loan is less than the minimum yearly repayment required.\n\nInterest received by the private company must be included in the income tax return for 2004-05.\n\nMinimum yearly repayment\n\n$130.00\n\nBenchmark interest rate\n\n7.05%\n\nOpening balance:\n\nDate: 30/06/2004\n\nBalance: $121.84\n\nDays: 365\n\nInterest: $8.59\n\nTotal repayments\n\n$0\n\nTotal interest\n\n$8.59\n\nTotal principal\n\n$0\n\nClosing balance\n\nDate: 30/06/2005\n\nBalance: $121.84",
  "outputs": {
    "enquiryRateFormatted": "7.05%",
    "enquiryYearEndMinusOneDisplay": "30/06/2004",
    "amalgamatedLoanNotPaidByEOIYFormatted": "$121.84",
    "openingBalancePayDays": "365",
    "openingBalanceInterestFormatted": "$8.59",
    "totalAmountOfRepaymentFormatted": "$0",
    "totalInterestFormatted": "$8.59",
    "principalFormatted": "$0",
    "enquiryYearEndDisplay": "30/06/2005",
    "minimumYearRepaymentFormatted": "$130.00",
    "loanAmountFormatted": "$121.84"
  },
  "repayments": [],
  "inputs": {
    "incomeYearOfLoan": 2001,
    "fullTermOfAmalgamatedLoan": 4,
    "incomeYearOfEnquiring": 2005,
    "amalgamatedLoanNotPaidByEOIY": 121.8432946932674,
    "repayments": null,
    "lodgement_date": null
  },
  "idx": 6299
}