{
  "id": "2023-10-31T17:10:47.888Z0.016710380389915125",
  "alert": "Start of result\nResult\n\nMinimum yearly repayment met.\n\nThe amount of the loan not repaid at the end of income year 2023-24 is $6,033.26.\n\n\u000b\n\nThe amalgamated loan will not be taken to be a dividend because the total repayments made are equal to or greater than the minimum yearly repayment required for income year 2023-24.\n\nInterest received by the private company must be included in the income tax return for 2023-24.\n\nMinimum yearly repayment\n\n$1,852.00\n\nBenchmark interest rate\n\n8.27%\n\nOpening balance:\n\nDate: 30/06/2023\n\nBalance: $8,490.00\n\nDays: 199\n\nInterest: $381.76\n\nPayments\n\nDate: 16/01/2024\n\nAmount: $3,044.00\n\nBalance: $5,446.00\n\nDays: 167\n\nInterest: $205.50\n\n\n\n\nTotal repayments\n\n$3,044.00\n\nTotal interest\n\n$587.26\n\nTotal principal\n\n$2,456.74\n\nClosing balance\n\nDate: 30/06/2024\n\nBalance: $6,033.26",
  "outputs": {
    "enquiryRateFormatted": "8.27%",
    "enquiryYearEndMinusOneDisplay": "30/06/2023",
    "amalgamatedLoanNotPaidByEOIYFormatted": "$8,490.00",
    "openingBalancePayDays": "199",
    "openingBalanceInterestFormatted": "$381.76",
    "totalAmountOfRepaymentFormatted": "$3,044.00",
    "totalInterestFormatted": "$587.26",
    "principalFormatted": "$2,456.74",
    "enquiryYearEndDisplay": "30/06/2024",
    "minimumYearRepaymentFormatted": "$1,852.00",
    "loanAmountFormatted": "$6,033.26"
  },
  "repayments": [
    {
      "rd": "16/1/2024",
      "ra": 3044
    }
  ],
  "inputs": {
    "incomeYearOfLoan": 2022,
    "fullTermOfAmalgamatedLoan": 7,
    "incomeYearOfEnquiring": 2024,
    "amalgamatedLoanNotPaidByEOIY": 8490,
    "repayments": null,
    "lodgement_date": null
  },
  "idx": 376
}