{
  "id": "2023-10-31T17:40:36.880Z0.693279412176112",
  "alert": "Start of result\nResult\n\nAmalgamated loan fully repaid.\n\nThe amalgamated loan has been paid in full.\u000bThe private company is not taken under Division 7A to pay a dividend to the shareholder or shareholder's associate.\n\nInterest received by the private company must be included in the income tax return for 2016-17.\n\nMinimum yearly repayment\n\n$28.00\n\nBenchmark interest rate\n\n5.4%\n\nOpening balance:\n\nDate: 30/06/2016\n\nBalance: $76.36\n\nDays: 218\n\nInterest: $2.46\n\nPayments\n\nDate: 04/02/2017\n\nAmount: $763.62\n\nBalance: $0\n\nDays: 147\n\nInterest: $0\n\n\n\n\nTotal repayments\n\n$763.62\n\nTotal interest\n\n$2.46\n\nTotal principal\n\n$761.16\n\nClosing balance\n\nDate: 30/06/2017\n\nBalance: $0",
  "outputs": {
    "enquiryRateFormatted": "5.4%",
    "enquiryYearEndMinusOneDisplay": "30/06/2016",
    "amalgamatedLoanNotPaidByEOIYFormatted": "$76.36",
    "openingBalancePayDays": "218",
    "openingBalanceInterestFormatted": "$2.46",
    "totalAmountOfRepaymentFormatted": "$763.62",
    "totalInterestFormatted": "$2.46",
    "principalFormatted": "$761.16",
    "enquiryYearEndDisplay": "30/06/2017",
    "minimumYearRepaymentFormatted": "$28.00",
    "loanAmountFormatted": "$0"
  },
  "repayments": [
    {
      "rd": "4/2/2017",
      "ra": 763.626586960947
    }
  ],
  "inputs": {
    "incomeYearOfLoan": 2015,
    "fullTermOfAmalgamatedLoan": 4,
    "incomeYearOfEnquiring": 2017,
    "amalgamatedLoanNotPaidByEOIY": 76.36265869609474,
    "repayments": null,
    "lodgement_date": null
  },
  "idx": 2258
}