{
  "id": "2023-09-05T11:22:07.922Z0.6011750790664256",
  "alert": "Start of result\nResult\n\nMinimum yearly repayment not met.\n\nThe amount of the loan not repaid at the end of income year 2022-23 is $0.17.\n\nThe private company may be taken to pay a dividend under Division 7A to the shareholder or shareholder's associate because the amount repaid during income year 2022-23 in relation to the amalgamated loan is less than the minimum yearly repayment required.\n\nInterest received by the private company must be included in the income tax return for 2022-23.\n\nMinimum yearly repayment\n\n$80.00\n\nBenchmark interest rate\n\n4.77%\n\nOpening balance:\n\nDate: 30/06/2022\n\nBalance: $76.34\n\nDays: 17\n\nInterest: $0.17\n\nPayments\n\nDate: 18/07/2022\n\nAmount: $76.34\n\nBalance: $0\n\nDays: 348\n\nInterest: $0\n\n\n\n\nTotal repayments\n\n$76.34\n\nTotal interest\n\n$0.17\n\nTotal principal\n\n$76.17\n\nClosing balance\n\nDate: 30/06/2023\n\nBalance: $0.17",
  "outputs": {
    "enquiryRateFormatted": "4.77%",
    "enquiryYearEndMinusOneDisplay": "30/06/2022",
    "amalgamatedLoanNotPaidByEOIYFormatted": "$76.34",
    "openingBalancePayDays": "17",
    "openingBalanceInterestFormatted": "$0.17",
    "totalAmountOfRepaymentFormatted": "$76.34",
    "totalInterestFormatted": "$0.17",
    "principalFormatted": "$76.17",
    "enquiryYearEndDisplay": "30/06/2023",
    "minimumYearRepaymentFormatted": "$80.00"
  },
  "repayments": [
    {
      "rd": "18/7/2022",
      "ra": 76.34021794722844
    }
  ],
  "inputs": {
    "incomeYearOfLoan": 2022,
    "fullTermOfAmalgamatedLoan": 1,
    "incomeYearOfEnquiring": 2023,
    "amalgamatedLoanNotPaidByEOIY": 76.34021794722838,
    "repayments": null,
    "lodgement_date": "3/7/2022"
  },
  "idx": 368
}