{
  "id": "2023-10-31T19:40:02.990Z0.7511374999530048",
  "alert": "Start of result\nResult\n\nMinimum yearly repayment not met.\n\nThe amount of the loan not repaid at the end of income year 2006-07 is $724.36.\n\nThe private company may be taken to pay a dividend under Division 7A to the shareholder or shareholder's associate because the amount repaid during income year 2006-07 in relation to the amalgamated loan is less than the minimum yearly repayment required.\n\nInterest received by the private company must be included in the income tax return for 2006-07.\n\nMinimum yearly repayment\n\n$4,849.00\n\nBenchmark interest rate\n\n7.55%\n\nOpening balance:\n\nDate: 30/06/2006\n\nBalance: $4,509.00\n\nDays: 29\n\nInterest: $27.05\n\nPayments\n\nDate: 30/07/2006\n\nAmount: $3,857.00\n\nBalance: $652.00\n\nDays: 336\n\nInterest: $45.31\n\n\n\n\nTotal repayments\n\n$3,857.00\n\nTotal interest\n\n$72.36\n\nTotal principal\n\n$3,784.64\n\nClosing balance\n\nDate: 30/06/2007\n\nBalance: $724.36",
  "outputs": {
    "enquiryRateFormatted": "7.55%",
    "enquiryYearEndMinusOneDisplay": "30/06/2006",
    "amalgamatedLoanNotPaidByEOIYFormatted": "$4,509.00",
    "openingBalancePayDays": "29",
    "openingBalanceInterestFormatted": "$27.05",
    "totalAmountOfRepaymentFormatted": "$3,857.00",
    "totalInterestFormatted": "$72.36",
    "principalFormatted": "$3,784.64",
    "enquiryYearEndDisplay": "30/06/2007",
    "minimumYearRepaymentFormatted": "$4,849.00",
    "loanAmountFormatted": "$724.36"
  },
  "repayments": [
    {
      "rd": "30/7/2006",
      "ra": 3857
    }
  ],
  "inputs": {
    "incomeYearOfLoan": 2003,
    "fullTermOfAmalgamatedLoan": 4,
    "incomeYearOfEnquiring": 2007,
    "amalgamatedLoanNotPaidByEOIY": 4509,
    "repayments": null,
    "lodgement_date": null
  },
  "idx": 5720
}