{
  "id": "2023-10-31T20:50:48.995Z0.12844632057621086",
  "alert": "Start of result\nResult\n\nMinimum yearly repayment not met.\n\nThe amount of the loan not repaid at the end of income year 1999-00 is $1,692.00.\n\nThe private company may be taken to pay a dividend under Division 7A to the shareholder or shareholder's associate because the amount repaid during income year 1999-00 in relation to the amalgamated loan is less than the minimum yearly repayment required.\n\nInterest received by the private company must be included in the income tax return for 1999-00.\n\nMinimum yearly repayment\n\n$929.00\n\nBenchmark interest rate\n\n6.5%\n\nOpening balance:\n\nDate: 30/06/1999\n\nBalance: $1,692.00\n\nDays: 366\n\nInterest: $109.98\n\nTotal repayments\n\n$0\n\nTotal interest\n\n$109.98\n\nTotal principal\n\n$0\n\nClosing balance\n\nDate: 30/06/2000\n\nBalance: $1,692.00",
  "outputs": {
    "enquiryRateFormatted": "6.5%",
    "enquiryYearEndMinusOneDisplay": "30/06/1999",
    "amalgamatedLoanNotPaidByEOIYFormatted": "$1,692.00",
    "openingBalancePayDays": "366",
    "openingBalanceInterestFormatted": "$109.98",
    "totalAmountOfRepaymentFormatted": "$0",
    "totalInterestFormatted": "$109.98",
    "principalFormatted": "$0",
    "enquiryYearEndDisplay": "30/06/2000",
    "minimumYearRepaymentFormatted": "$929.00",
    "loanAmountFormatted": "$1,692.00"
  },
  "repayments": [],
  "inputs": {
    "incomeYearOfLoan": 1999,
    "fullTermOfAmalgamatedLoan": 2,
    "incomeYearOfEnquiring": 2000,
    "amalgamatedLoanNotPaidByEOIY": 1692,
    "repayments": null,
    "lodgement_date": "28/11/1999"
  },
  "idx": 6807
}