{
  "id": "2023-09-04T22:09:47.472Z0.6607736518579692",
  "alert": "Start of result\nResult\n\nMinimum yearly repayment met.\n\nThe amount of the loan not repaid at the end of income year 2003-04 is $2,779.89.\n\nThe amalgamated loan will not be taken to be a dividend because the total repayments made are equal to or greater than the minimum yearly repayment required for income year 2003-04.\n\nInterest received by the private company must be included in the income tax return for 2003-04.\n\nMinimum yearly repayment\n\n$4,511.00\n\nBenchmark interest rate\n\n6.55%\n\nOpening balance:\n\nDate: 30/06/2003\n\nBalance: $8,207.00\n\nDays: 0\n\nInterest: $0\n\nPayments\n\nDate: 01/07/2003\n\nAmount: $5,598.00\n\nBalance: $2,609.00\n\nDays: 366\n\nInterest: $170.89\n\n\n\n\nTotal repayments\n\n$5,598.00\n\nTotal interest\n\n$170.89\n\nTotal principal\n\n$5,427.11\n\nClosing balance\n\nDate: 30/06/2004\n\nBalance: $2,779.89",
  "outputs": {
    "enquiryRateFormatted": "6.55%",
    "enquiryYearEndMinusOneDisplay": "30/06/2003",
    "amalgamatedLoanNotPaidByEOIYFormatted": "$8,207.00",
    "openingBalancePayDays": "0",
    "openingBalanceInterestFormatted": "$0",
    "totalAmountOfRepaymentFormatted": "$5,598.00",
    "totalInterestFormatted": "$170.89",
    "principalFormatted": "$5,427.11",
    "enquiryYearEndDisplay": "30/06/2004",
    "minimumYearRepaymentFormatted": "$4,511.00"
  },
  "repayments": [
    {
      "rd": "1/7/2003",
      "ra": 5598
    }
  ],
  "inputs": {
    "incomeYearOfLoan": 2002,
    "fullTermOfAmalgamatedLoan": 3,
    "incomeYearOfEnquiring": 2004,
    "amalgamatedLoanNotPaidByEOIY": 8207,
    "repayments": null,
    "lodgement_date": null
  },
  "idx": 356
}