{
  "id": "2023-10-31T20:10:28.072Z0.6481547897781743",
  "alert": "Start of result\nResult\n\nAmalgamated loan fully repaid.\n\nThe amalgamated loan has been paid in full.\u000bThe private company is not taken under Division 7A to pay a dividend to the shareholder or shareholder's associate.\n\nInterest received by the private company must be included in the income tax return for 2002-03.\n\nMinimum yearly repayment\n\n$32.00\n\nBenchmark interest rate\n\n6.3%\n\nOpening balance:\n\nDate: 30/06/2002\n\nBalance: $30.15\n\nDays: 83\n\nInterest: $0.43\n\nPayments\n\nDate: 22/09/2002\n\nAmount: $301.55\n\nBalance: $0\n\nDays: 282\n\nInterest: $0\n\n\n\n\nTotal repayments\n\n$301.55\n\nTotal interest\n\n$0.43\n\nTotal principal\n\n$301.12\n\nClosing balance\n\nDate: 30/06/2003\n\nBalance: $0",
  "outputs": {
    "enquiryRateFormatted": "6.3%",
    "enquiryYearEndMinusOneDisplay": "30/06/2002",
    "amalgamatedLoanNotPaidByEOIYFormatted": "$30.15",
    "openingBalancePayDays": "83",
    "openingBalanceInterestFormatted": "$0.43",
    "totalAmountOfRepaymentFormatted": "$301.55",
    "totalInterestFormatted": "$0.43",
    "principalFormatted": "$301.12",
    "enquiryYearEndDisplay": "30/06/2003",
    "minimumYearRepaymentFormatted": "$32.00",
    "loanAmountFormatted": "$0"
  },
  "repayments": [
    {
      "rd": "22/9/2002",
      "ra": 301.55204076782434
    }
  ],
  "inputs": {
    "incomeYearOfLoan": 2001,
    "fullTermOfAmalgamatedLoan": 2,
    "incomeYearOfEnquiring": 2003,
    "amalgamatedLoanNotPaidByEOIY": 30.15520407678243,
    "repayments": null,
    "lodgement_date": null
  },
  "idx": 6237
}