{
  "id": "2023-09-06T22:54:58.398Z0.1431182738360528",
  "alert": "Start of result\nResult\n\nMinimum yearly repayment met.\n\nThe amount of the loan not repaid at the end of income year 2003-04 is $83.22.\n\nThe amalgamated loan will not be taken to be a dividend because the total repayments made are equal to or greater than the minimum yearly repayment required for income year 2003-04.\n\nInterest received by the private company must be included in the income tax return for 2003-04.\n\nMinimum yearly repayment\n\n$594.00\n\nBenchmark interest rate\n\n6.55%\n\nOpening balance:\n\nDate: 30/06/2003\n\nBalance: $1,571.00\n\nDays: 296\n\nInterest: $83.22\n\nPayments\n\nDate: 22/04/2004\n\nAmount: $1,571.00\n\nBalance: $0\n\nDays: 70\n\nInterest: $0\n\n\n\n\nTotal repayments\n\n$1,571.00\n\nTotal interest\n\n$83.22\n\nTotal principal\n\n$1,487.78\n\nClosing balance\n\nDate: 30/06/2004\n\nBalance: $83.22",
  "outputs": {
    "enquiryRateFormatted": "6.55%",
    "enquiryYearEndMinusOneDisplay": "30/06/2003",
    "amalgamatedLoanNotPaidByEOIYFormatted": "$1,571.00",
    "openingBalancePayDays": "296",
    "openingBalanceInterestFormatted": "$83.22",
    "totalAmountOfRepaymentFormatted": "$1,571.00",
    "totalInterestFormatted": "$83.22",
    "principalFormatted": "$1,487.78",
    "enquiryYearEndDisplay": "30/06/2004",
    "minimumYearRepaymentFormatted": "$594.00"
  },
  "repayments": [
    {
      "rd": "22/4/2004",
      "ra": 1571
    }
  ],
  "inputs": {
    "incomeYearOfLoan": 2001,
    "fullTermOfAmalgamatedLoan": 5,
    "incomeYearOfEnquiring": 2004,
    "amalgamatedLoanNotPaidByEOIY": 1571,
    "repayments": null,
    "lodgement_date": null
  },
  "idx": 1475
}