{
  "id": "2023-10-31T20:06:03.462Z0.034593438033605484",
  "alert": "Start of result\nResult\n\nAmalgamated loan fully repaid.\n\nThe amalgamated loan has been paid in full.\u000bThe private company is not taken under Division 7A to pay a dividend to the shareholder or shareholder's associate.\n\nInterest received by the private company must be included in the income tax return for 2006-07.\n\nMinimum yearly repayment\n\n$37.00\n\nBenchmark interest rate\n\n7.55%\n\nOpening balance:\n\nDate: 30/06/2006\n\nBalance: $95.60\n\nDays: 98\n\nInterest: $1.94\n\nPayments\n\nDate: 07/10/2006\n\nAmount: $956.05\n\nBalance: $0\n\nDays: 267\n\nInterest: $0\n\n\n\n\nTotal repayments\n\n$956.05\n\nTotal interest\n\n$1.94\n\nTotal principal\n\n$954.11\n\nClosing balance\n\nDate: 30/06/2007\n\nBalance: $0",
  "outputs": {
    "enquiryRateFormatted": "7.55%",
    "enquiryYearEndMinusOneDisplay": "30/06/2006",
    "amalgamatedLoanNotPaidByEOIYFormatted": "$95.60",
    "openingBalancePayDays": "98",
    "openingBalanceInterestFormatted": "$1.94",
    "totalAmountOfRepaymentFormatted": "$956.05",
    "totalInterestFormatted": "$1.94",
    "principalFormatted": "$954.11",
    "enquiryYearEndDisplay": "30/06/2007",
    "minimumYearRepaymentFormatted": "$37.00",
    "loanAmountFormatted": "$0"
  },
  "repayments": [
    {
      "rd": "7/10/2006",
      "ra": 956.0590573177847
    }
  ],
  "inputs": {
    "incomeYearOfLoan": 2002,
    "fullTermOfAmalgamatedLoan": 7,
    "incomeYearOfEnquiring": 2007,
    "amalgamatedLoanNotPaidByEOIY": 95.60590573177846,
    "repayments": null,
    "lodgement_date": null
  },
  "idx": 6167
}