{
  "id": "2023-09-07T02:30:35.472Z0.49999955404539276",
  "alert": "Start of result\nResult\n\nMinimum yearly repayment not met.\n\nThe amount of the loan not repaid at the end of income year 2005-06 is $1.40.\n\nThe private company may be taken to pay a dividend under Division 7A to the shareholder or shareholder's associate because the amount repaid during income year 2005-06 in relation to the amalgamated loan is less than the minimum yearly repayment required.\n\nInterest received by the private company must be included in the income tax return for 2005-06.\n\nMinimum yearly repayment\n\n$24.00\n\nBenchmark interest rate\n\n7.3%\n\nOpening balance:\n\nDate: 30/06/2005\n\nBalance: $22.45\n\nDays: 311\n\nInterest: $1.40\n\nPayments\n\nDate: 08/05/2006\n\nAmount: $22.45\n\nBalance: $0\n\nDays: 54\n\nInterest: $0\n\n\n\n\nTotal repayments\n\n$22.45\n\nTotal interest\n\n$1.40\n\nTotal principal\n\n$21.05\n\nClosing balance\n\nDate: 30/06/2006\n\nBalance: $1.40",
  "outputs": {
    "enquiryRateFormatted": "7.3%",
    "enquiryYearEndMinusOneDisplay": "30/06/2005",
    "amalgamatedLoanNotPaidByEOIYFormatted": "$22.45",
    "openingBalancePayDays": "311",
    "openingBalanceInterestFormatted": "$1.40",
    "totalAmountOfRepaymentFormatted": "$22.45",
    "totalInterestFormatted": "$1.40",
    "principalFormatted": "$21.05",
    "enquiryYearEndDisplay": "30/06/2006",
    "minimumYearRepaymentFormatted": "$24.00"
  },
  "repayments": [
    {
      "rd": "8/5/2006",
      "ra": 22.458145899943702
    }
  ],
  "inputs": {
    "incomeYearOfLoan": 1999,
    "fullTermOfAmalgamatedLoan": 7,
    "incomeYearOfEnquiring": 2006,
    "amalgamatedLoanNotPaidByEOIY": 22.45814589994385,
    "repayments": null,
    "lodgement_date": null
  },
  "idx": 5169
}