{
  "id": "2023-10-31T17:58:56.984Z0.03072102177212155",
  "alert": "Start of result\nResult\n\nMinimum yearly repayment not met.\n\nThe amount of the loan not repaid at the end of income year 2015-16 is $70.97.\n\nThe private company may be taken to pay a dividend under Division 7A to the shareholder or shareholder's associate because the amount repaid during income year 2015-16 in relation to the amalgamated loan is less than the minimum yearly repayment required.\n\nInterest received by the private company must be included in the income tax return for 2015-16.\n\nMinimum yearly repayment\n\n$17.00\n\nBenchmark interest rate\n\n5.45%\n\nOpening balance:\n\nDate: 30/06/2015\n\nBalance: $70.97\n\nDays: 366\n\nInterest: $3.87\n\nTotal repayments\n\n$0\n\nTotal interest\n\n$3.87\n\nTotal principal\n\n$0\n\nClosing balance\n\nDate: 30/06/2016\n\nBalance: $70.97",
  "outputs": {
    "enquiryRateFormatted": "5.45%",
    "enquiryYearEndMinusOneDisplay": "30/06/2015",
    "amalgamatedLoanNotPaidByEOIYFormatted": "$70.97",
    "openingBalancePayDays": "366",
    "openingBalanceInterestFormatted": "$3.87",
    "totalAmountOfRepaymentFormatted": "$0",
    "totalInterestFormatted": "$3.87",
    "principalFormatted": "$0",
    "enquiryYearEndDisplay": "30/06/2016",
    "minimumYearRepaymentFormatted": "$17.00",
    "loanAmountFormatted": "$70.97"
  },
  "repayments": [],
  "inputs": {
    "incomeYearOfLoan": 2013,
    "fullTermOfAmalgamatedLoan": 7,
    "incomeYearOfEnquiring": 2016,
    "amalgamatedLoanNotPaidByEOIY": 70.97533595212519,
    "repayments": null,
    "lodgement_date": null
  },
  "idx": 3048
}