{
  "id": "2023-09-04T22:16:43.936Z0.4226259079509891",
  "alert": "Start of result\nResult\n\nMinimum yearly repayment not met.\n\nThe amount of the loan not repaid at the end of income year 2001-02 is $4,230.00.\n\nThe private company may be taken to pay a dividend under Division 7A to the shareholder or shareholder's associate because the amount repaid during income year 2001-02 in relation to the amalgamated loan is less than the minimum yearly repayment required.\n\nInterest received by the private company must be included in the income tax return for 2001-02.\n\nMinimum yearly repayment\n\n$1,606.00\n\nBenchmark interest rate\n\n6.8%\n\nOpening balance:\n\nDate: 30/06/2001\n\nBalance: $4,230.00\n\nDays: 365\n\nInterest: $287.64\n\nTotal repayments\n\n$0\n\nTotal interest\n\n$287.64\n\nTotal principal\n\n$0\n\nClosing balance\n\nDate: 30/06/2002\n\nBalance: $4,230.00",
  "outputs": {
    "enquiryRateFormatted": "6.8%",
    "enquiryYearEndMinusOneDisplay": "30/06/2001",
    "amalgamatedLoanNotPaidByEOIYFormatted": "$4,230.00",
    "openingBalancePayDays": "365",
    "openingBalanceInterestFormatted": "$287.64",
    "totalAmountOfRepaymentFormatted": "$0",
    "totalInterestFormatted": "$287.64",
    "principalFormatted": "$0",
    "enquiryYearEndDisplay": "30/06/2002",
    "minimumYearRepaymentFormatted": "$1,606.00"
  },
  "repayments": [],
  "inputs": {
    "incomeYearOfLoan": 2001,
    "fullTermOfAmalgamatedLoan": 3,
    "incomeYearOfEnquiring": 2002,
    "amalgamatedLoanNotPaidByEOIY": 4230,
    "repayments": null,
    "lodgement_date": "1/7/2001"
  },
  "idx": 617
}