{
  "id": "2023-10-31T19:03:21.175Z0.28163553694796317",
  "alert": "Start of result\nResult\n\nMinimum yearly repayment met.\n\nThe amount of the loan not repaid at the end of income year 2007-08 is $848.86.\n\n\u000b\n\nThe amalgamated loan will not be taken to be a dividend because the total repayments made are equal to or greater than the minimum yearly repayment required for income year 2007-08.\n\nInterest received by the private company must be included in the income tax return for 2007-08.\n\nMinimum yearly repayment\n\n$3,882.00\n\nBenchmark interest rate\n\n8.05%\n\nOpening balance:\n\nDate: 30/06/2007\n\nBalance: $9,994.00\n\nDays: 320\n\nInterest: $703.40\n\nPayments\n\nDate: 16/05/2008\n\nAmount: $9,850.00\n\nBalance: $144.00\n\nDays: 46\n\nInterest: $1.46\n\n\n\n\nTotal repayments\n\n$9,850.00\n\nTotal interest\n\n$704.86\n\nTotal principal\n\n$9,145.14\n\nClosing balance\n\nDate: 30/06/2008\n\nBalance: $848.86",
  "outputs": {
    "enquiryRateFormatted": "8.05%",
    "enquiryYearEndMinusOneDisplay": "30/06/2007",
    "amalgamatedLoanNotPaidByEOIYFormatted": "$9,994.00",
    "openingBalancePayDays": "320",
    "openingBalanceInterestFormatted": "$703.40",
    "totalAmountOfRepaymentFormatted": "$9,850.00",
    "totalInterestFormatted": "$704.86",
    "principalFormatted": "$9,145.14",
    "enquiryYearEndDisplay": "30/06/2008",
    "minimumYearRepaymentFormatted": "$3,882.00",
    "loanAmountFormatted": "$848.86"
  },
  "repayments": [
    {
      "rd": "16/5/2008",
      "ra": 9850
    }
  ],
  "inputs": {
    "incomeYearOfLoan": 2006,
    "fullTermOfAmalgamatedLoan": 4,
    "incomeYearOfEnquiring": 2008,
    "amalgamatedLoanNotPaidByEOIY": 9994,
    "repayments": null,
    "lodgement_date": null
  },
  "idx": 4950
}