{
  "id": "2023-09-06T19:13:59.980Z0.8374156637880197",
  "alert": "Start of result\nResult\n\nMinimum yearly repayment not met.\n\nThe amount of the loan not repaid at the end of income year 2005-06 is $2.39.\n\nThe private company may be taken to pay a dividend under Division 7A to the shareholder or shareholder's associate because the amount repaid during income year 2005-06 in relation to the amalgamated loan is less than the minimum yearly repayment required.\n\nInterest received by the private company must be included in the income tax return for 2005-06.\n\nMinimum yearly repayment\n\n$81.00\n\nBenchmark interest rate\n\n7.3%\n\nOpening balance:\n\nDate: 30/06/2005\n\nBalance: $75.04\n\nDays: 159\n\nInterest: $2.39\n\nPayments\n\nDate: 07/12/2005\n\nAmount: $75.04\n\nBalance: $0\n\nDays: 206\n\nInterest: $0\n\n\n\n\nTotal repayments\n\n$75.04\n\nTotal interest\n\n$2.39\n\nTotal principal\n\n$72.65\n\nClosing balance\n\nDate: 30/06/2006\n\nBalance: $2.39",
  "outputs": {
    "enquiryRateFormatted": "7.3%",
    "enquiryYearEndMinusOneDisplay": "30/06/2005",
    "amalgamatedLoanNotPaidByEOIYFormatted": "$75.04",
    "openingBalancePayDays": "159",
    "openingBalanceInterestFormatted": "$2.39",
    "totalAmountOfRepaymentFormatted": "$75.04",
    "totalInterestFormatted": "$2.39",
    "principalFormatted": "$72.65",
    "enquiryYearEndDisplay": "30/06/2006",
    "minimumYearRepaymentFormatted": "$81.00"
  },
  "repayments": [
    {
      "rd": "7/12/2005",
      "ra": 75.0495654543115
    }
  ],
  "inputs": {
    "incomeYearOfLoan": 2003,
    "fullTermOfAmalgamatedLoan": 3,
    "incomeYearOfEnquiring": 2006,
    "amalgamatedLoanNotPaidByEOIY": 75.0495654543116,
    "repayments": null,
    "lodgement_date": null
  },
  "idx": 5167
}