{
  "id": "2023-09-07T01:00:35.725Z0.3520936434141073",
  "alert": "Start of result\nResult\n\nMinimum yearly repayment met.\n\nThe amount of the loan not repaid at the end of income year 2000-01 is $7,348.06.\n\nThe amalgamated loan will not be taken to be a dividend because the total repayments made are equal to or greater than the minimum yearly repayment required for income year 2000-01.\n\nInterest received by the private company must be included in the income tax return for 2000-01.\n\nMinimum yearly repayment\n\n$1,950.00\n\nBenchmark interest rate\n\n7.8%\n\nOpening balance:\n\nDate: 30/06/2000\n\nBalance: $10,220.00\n\nDays: 325\n\nInterest: $709.80\n\nPayments\n\nDate: 22/05/2001\n\nAmount: $3,638.00\n\nBalance: $6,582.00\n\nDays: 40\n\nInterest: $56.26\n\n\n\n\nTotal repayments\n\n$3,638.00\n\nTotal interest\n\n$766.06\n\nTotal principal\n\n$2,871.94\n\nClosing balance\n\nDate: 30/06/2001\n\nBalance: $7,348.06",
  "outputs": {
    "enquiryRateFormatted": "7.8%",
    "enquiryYearEndMinusOneDisplay": "30/06/2000",
    "amalgamatedLoanNotPaidByEOIYFormatted": "$10,220.00",
    "openingBalancePayDays": "325",
    "openingBalanceInterestFormatted": "$709.80",
    "totalAmountOfRepaymentFormatted": "$3,638.00",
    "totalInterestFormatted": "$766.06",
    "principalFormatted": "$2,871.94",
    "enquiryYearEndDisplay": "30/06/2001",
    "minimumYearRepaymentFormatted": "$1,950.00"
  },
  "repayments": [
    {
      "rd": "22/5/2001",
      "ra": 3638
    }
  ],
  "inputs": {
    "incomeYearOfLoan": 2000,
    "fullTermOfAmalgamatedLoan": 7,
    "incomeYearOfEnquiring": 2001,
    "amalgamatedLoanNotPaidByEOIY": 10220,
    "repayments": null,
    "lodgement_date": "9/11/2000"
  },
  "idx": 8631
}