{
  "id": "2023-09-04T22:24:42.433Z0.8862682444277667",
  "alert": "Start of result\nResult\n\nMinimum yearly repayment not met.\n\nThe amount of the loan not repaid at the end of income year 2003-04 is $89,037,744.60.\n\nThe private company may be taken to pay a dividend under Division 7A to the shareholder or shareholder's associate because the amount repaid during income year 2003-04 in relation to the amalgamated loan is less than the minimum yearly repayment required.\n\nInterest received by the private company must be included in the income tax return for 2003-04.\n\nMinimum yearly repayment\n\n$48,939,087.00\n\nBenchmark interest rate\n\n6.55%\n\nOpening balance:\n\nDate: 30/06/2003\n\nBalance: $89,037,744.60\n\nDays: 366\n\nInterest: $5,831,972.27\n\nTotal repayments\n\n$0\n\nTotal interest\n\n$5,831,972.27\n\nTotal principal\n\n$0\n\nClosing balance\n\nDate: 30/06/2004\n\nBalance: $89,037,744.60",
  "outputs": {
    "enquiryRateFormatted": "6.55%",
    "enquiryYearEndMinusOneDisplay": "30/06/2003",
    "amalgamatedLoanNotPaidByEOIYFormatted": "$89,037,744.60",
    "openingBalancePayDays": "366",
    "openingBalanceInterestFormatted": "$5,831,972.27",
    "totalAmountOfRepaymentFormatted": "$0",
    "totalInterestFormatted": "$5,831,972.27",
    "principalFormatted": "$0",
    "enquiryYearEndDisplay": "30/06/2004",
    "minimumYearRepaymentFormatted": "$48,939,087.00"
  },
  "repayments": [],
  "inputs": {
    "incomeYearOfLoan": 2000,
    "fullTermOfAmalgamatedLoan": 5,
    "incomeYearOfEnquiring": 2004,
    "amalgamatedLoanNotPaidByEOIY": 89037744.60546726,
    "repayments": null,
    "lodgement_date": null
  },
  "idx": 884
}