{
  "id": "2023-10-31T19:46:47.008Z0.6382232677885126",
  "alert": "Start of result\nResult\n\nMinimum yearly repayment met.\n\nThe amount of the loan not repaid at the end of income year 2003-04 is $3,933.03.\n\n\u000b\n\nThe amalgamated loan will not be taken to be a dividend because the total repayments made are equal to or greater than the minimum yearly repayment required for income year 2003-04.\n\nInterest received by the private company must be included in the income tax return for 2003-04.\n\nMinimum yearly repayment\n\n$737.00\n\nBenchmark interest rate\n\n6.55%\n\nOpening balance:\n\nDate: 30/06/2003\n\nBalance: $8,620.00\n\nDays: 151\n\nInterest: $232.94\n\nPayments\n\nDate: 29/11/2003\n\nAmount: $5,057.00\n\nBalance: $3,563.00\n\nDays: 215\n\nInterest: $137.09\n\n\n\n\nTotal repayments\n\n$5,057.00\n\nTotal interest\n\n$370.03\n\nTotal principal\n\n$4,686.97\n\nClosing balance\n\nDate: 30/06/2004\n\nBalance: $3,933.03",
  "outputs": {
    "enquiryRateFormatted": "6.55%",
    "enquiryYearEndMinusOneDisplay": "30/06/2003",
    "amalgamatedLoanNotPaidByEOIYFormatted": "$8,620.00",
    "openingBalancePayDays": "151",
    "openingBalanceInterestFormatted": "$232.94",
    "totalAmountOfRepaymentFormatted": "$5,057.00",
    "totalInterestFormatted": "$370.03",
    "principalFormatted": "$4,686.97",
    "enquiryYearEndDisplay": "30/06/2004",
    "minimumYearRepaymentFormatted": "$737.00",
    "loanAmountFormatted": "$3,933.03"
  },
  "repayments": [
    {
      "rd": "29/11/2003",
      "ra": 5057
    }
  ],
  "inputs": {
    "incomeYearOfLoan": 2003,
    "fullTermOfAmalgamatedLoan": 6,
    "incomeYearOfEnquiring": 2004,
    "amalgamatedLoanNotPaidByEOIY": 8620,
    "repayments": null,
    "lodgement_date": "26/4/2004"
  },
  "idx": 5837
}