{
  "id": "2023-09-06T16:55:20.387Z0.9727422304583511",
  "alert": "Start of result\nResult\n\nMinimum yearly repayment not met.\n\nThe amount of the loan not repaid at the end of income year 2009-10 is $12,150.00.\n\nThe private company may be taken to pay a dividend under Division 7A to the shareholder or shareholder's associate because the amount repaid during income year 2009-10 in relation to the amalgamated loan is less than the minimum yearly repayment required.\n\nInterest received by the private company must be included in the income tax return for 2009-10.\n\nMinimum yearly repayment\n\n$4,524.00\n\nBenchmark interest rate\n\n5.75%\n\nOpening balance:\n\nDate: 30/06/2009\n\nBalance: $12,150.00\n\nDays: 365\n\nInterest: $698.63\n\nTotal repayments\n\n$0\n\nTotal interest\n\n$698.63\n\nTotal principal\n\n$0\n\nClosing balance\n\nDate: 30/06/2010\n\nBalance: $12,150.00",
  "outputs": {
    "enquiryRateFormatted": "5.75%",
    "enquiryYearEndMinusOneDisplay": "30/06/2009",
    "amalgamatedLoanNotPaidByEOIYFormatted": "$12,150.00",
    "openingBalancePayDays": "365",
    "openingBalanceInterestFormatted": "$698.63",
    "totalAmountOfRepaymentFormatted": "$0",
    "totalInterestFormatted": "$698.63",
    "principalFormatted": "$0",
    "enquiryYearEndDisplay": "30/06/2010",
    "minimumYearRepaymentFormatted": "$4,524.00"
  },
  "repayments": [],
  "inputs": {
    "incomeYearOfLoan": 2005,
    "fullTermOfAmalgamatedLoan": 7,
    "incomeYearOfEnquiring": 2010,
    "amalgamatedLoanNotPaidByEOIY": 12150,
    "repayments": null,
    "lodgement_date": null
  },
  "idx": 5531
}