{
  "id": "2023-09-05T00:59:39.696Z0.14912712289486296",
  "alert": "Start of result\nResult\n\nMinimum yearly repayment not met.\n\nThe amount of the loan not repaid at the end of income year 1998-99 is $9,527.00.\n\nThe private company may be taken to pay a dividend under Division 7A to the shareholder or shareholder's associate because the amount repaid during income year 1998-99 in relation to the amalgamated loan is less than the minimum yearly repayment required.\n\nInterest received by the private company must be included in the income tax return for 1998-99.\n\nMinimum yearly repayment\n\n$10,165.00\n\nBenchmark interest rate\n\n6.7%\n\nOpening balance:\n\nDate: 30/06/1998\n\nBalance: $9,527.00\n\nDays: 365\n\nInterest: $638.31\n\nTotal repayments\n\n$0\n\nTotal interest\n\n$638.31\n\nTotal principal\n\n$0\n\nClosing balance\n\nDate: 30/06/1999\n\nBalance: $9,527.00",
  "outputs": {
    "enquiryRateFormatted": "6.7%",
    "enquiryYearEndMinusOneDisplay": "30/06/1998",
    "amalgamatedLoanNotPaidByEOIYFormatted": "$9,527.00",
    "openingBalancePayDays": "365",
    "openingBalanceInterestFormatted": "$638.31",
    "totalAmountOfRepaymentFormatted": "$0",
    "totalInterestFormatted": "$638.31",
    "principalFormatted": "$0",
    "enquiryYearEndDisplay": "30/06/1999",
    "minimumYearRepaymentFormatted": "$10,165.00"
  },
  "repayments": [],
  "inputs": {
    "incomeYearOfLoan": 1998,
    "fullTermOfAmalgamatedLoan": 1,
    "incomeYearOfEnquiring": 1999,
    "amalgamatedLoanNotPaidByEOIY": 9527,
    "repayments": null,
    "lodgement_date": "11/1/1999"
  },
  "idx": 194
}