{
  "id": "2023-09-06T05:15:44.134Z0.6064957245104259",
  "alert": "Start of result\nResult\n\nMinimum yearly repayment not met.\n\nThe amount of the loan not repaid at the end of income year 2013-14 is $8,938.00.\n\nThe private company may be taken to pay a dividend under Division 7A to the shareholder or shareholder's associate because the amount repaid during income year 2013-14 in relation to the amalgamated loan is less than the minimum yearly repayment required.\n\nInterest received by the private company must be included in the income tax return for 2013-14.\n\nMinimum yearly repayment\n\n$2,133.00\n\nBenchmark interest rate\n\n6.2%\n\nOpening balance:\n\nDate: 30/06/2013\n\nBalance: $8,938.00\n\nDays: 365\n\nInterest: $554.16\n\nTotal repayments\n\n$0\n\nTotal interest\n\n$554.16\n\nTotal principal\n\n$0\n\nClosing balance\n\nDate: 30/06/2014\n\nBalance: $8,938.00",
  "outputs": {
    "enquiryRateFormatted": "6.2%",
    "enquiryYearEndMinusOneDisplay": "30/06/2013",
    "amalgamatedLoanNotPaidByEOIYFormatted": "$8,938.00",
    "openingBalancePayDays": "365",
    "openingBalanceInterestFormatted": "$554.16",
    "totalAmountOfRepaymentFormatted": "$0",
    "totalInterestFormatted": "$554.16",
    "principalFormatted": "$0",
    "enquiryYearEndDisplay": "30/06/2014",
    "minimumYearRepaymentFormatted": "$2,133.00"
  },
  "repayments": [],
  "inputs": {
    "incomeYearOfLoan": 2012,
    "fullTermOfAmalgamatedLoan": 6,
    "incomeYearOfEnquiring": 2014,
    "amalgamatedLoanNotPaidByEOIY": 8938,
    "repayments": null,
    "lodgement_date": null
  },
  "idx": 1483
}