{
  "id": "2023-10-31T17:50:56.583Z0.9441622104929015",
  "alert": "Start of result\nResult\n\nMinimum yearly repayment not met.\n\nThe amount of the loan not repaid at the end of income year 2017-18 is $43.56.\n\nThe private company may be taken to pay a dividend under Division 7A to the shareholder or shareholder's associate because the amount repaid during income year 2017-18 in relation to the amalgamated loan is less than the minimum yearly repayment required.\n\nInterest received by the private company must be included in the income tax return for 2017-18.\n\nMinimum yearly repayment\n\n$16.00\n\nBenchmark interest rate\n\n5.3%\n\nOpening balance:\n\nDate: 30/06/2017\n\nBalance: $43.56\n\nDays: 365\n\nInterest: $2.31\n\nTotal repayments\n\n$0\n\nTotal interest\n\n$2.31\n\nTotal principal\n\n$0\n\nClosing balance\n\nDate: 30/06/2018\n\nBalance: $43.56",
  "outputs": {
    "enquiryRateFormatted": "5.3%",
    "enquiryYearEndMinusOneDisplay": "30/06/2017",
    "amalgamatedLoanNotPaidByEOIYFormatted": "$43.56",
    "openingBalancePayDays": "365",
    "openingBalanceInterestFormatted": "$2.31",
    "totalAmountOfRepaymentFormatted": "$0",
    "totalInterestFormatted": "$2.31",
    "principalFormatted": "$0",
    "enquiryYearEndDisplay": "30/06/2018",
    "minimumYearRepaymentFormatted": "$16.00",
    "loanAmountFormatted": "$43.56"
  },
  "repayments": [],
  "inputs": {
    "incomeYearOfLoan": 2014,
    "fullTermOfAmalgamatedLoan": 6,
    "incomeYearOfEnquiring": 2018,
    "amalgamatedLoanNotPaidByEOIY": 43.567484555102446,
    "repayments": null,
    "lodgement_date": null
  },
  "idx": 2730
}