{
  "id": "2023-09-04T16:19:51.022Z0.855663880418658",
  "alert": "Start of result\nResult\n\nMinimum yearly repayment not met.\n\nThe amount of the loan not repaid at the end of income year 2021-22 is $1,629.00.\n\nThe private company may be taken to pay a dividend under Division 7A to the shareholder or shareholder's associate because the amount repaid during income year 2021-22 in relation to the amalgamated loan is less than the minimum yearly repayment required.\n\nInterest received by the private company must be included in the income tax return for 2021-22.\n\nMinimum yearly repayment\n\n$454.00\n\nBenchmark interest rate\n\n4.52%\n\nOpening balance:\n\nDate: 30/06/2021\n\nBalance: $1,629.00\n\nDays: 365\n\nInterest: $73.63\n\nTotal repayments\n\n$0\n\nTotal interest\n\n$73.63\n\nTotal principal\n\n$0\n\nClosing balance\n\nDate: 30/06/2022\n\nBalance: $1,629.00",
  "outputs": {
    "enquiryRateFormatted": "4.52%",
    "enquiryYearEndMinusOneDisplay": "30/06/2021",
    "amalgamatedLoanNotPaidByEOIYFormatted": "$1,629.00",
    "openingBalancePayDays": "365",
    "openingBalanceInterestFormatted": "$73.63",
    "totalAmountOfRepaymentFormatted": "$0",
    "totalInterestFormatted": "$73.63",
    "principalFormatted": "$0",
    "enquiryYearEndDisplay": "30/06/2022",
    "minimumYearRepaymentFormatted": "$454.00"
  },
  "repayments": [],
  "inputs": {
    "incomeYearOfLoan": 2020,
    "fullTermOfAmalgamatedLoan": 5,
    "incomeYearOfEnquiring": 2022,
    "amalgamatedLoanNotPaidByEOIY": 1629,
    "repayments": null,
    "lodgement_date": null
  },
  "idx": 283
}