{
  "id": "2023-10-31T17:16:04.406Z0.7400673226843272",
  "alert": "Start of result\nResult\n\nMinimum yearly repayment not met.\n\nThe amount of the loan not repaid at the end of income year 2021-22 is $19.49.\n\nThe private company may be taken to pay a dividend under Division 7A to the shareholder or shareholder's associate because the amount repaid during income year 2021-22 in relation to the amalgamated loan is less than the minimum yearly repayment required.\n\nInterest received by the private company must be included in the income tax return for 2021-22.\n\nMinimum yearly repayment\n\n$7.00\n\nBenchmark interest rate\n\n4.52%\n\nOpening balance:\n\nDate: 30/06/2021\n\nBalance: $19.49\n\nDays: 365\n\nInterest: $0.88\n\nTotal repayments\n\n$0\n\nTotal interest\n\n$0.88\n\nTotal principal\n\n$0\n\nClosing balance\n\nDate: 30/06/2022\n\nBalance: $19.49",
  "outputs": {
    "enquiryRateFormatted": "4.52%",
    "enquiryYearEndMinusOneDisplay": "30/06/2021",
    "amalgamatedLoanNotPaidByEOIYFormatted": "$19.49",
    "openingBalancePayDays": "365",
    "openingBalanceInterestFormatted": "$0.88",
    "totalAmountOfRepaymentFormatted": "$0",
    "totalInterestFormatted": "$0.88",
    "principalFormatted": "$0",
    "enquiryYearEndDisplay": "30/06/2022",
    "minimumYearRepaymentFormatted": "$7.00",
    "loanAmountFormatted": "$19.49"
  },
  "repayments": [],
  "inputs": {
    "incomeYearOfLoan": 2020,
    "fullTermOfAmalgamatedLoan": 4,
    "incomeYearOfEnquiring": 2022,
    "amalgamatedLoanNotPaidByEOIY": 19.492679337740608,
    "repayments": null,
    "lodgement_date": null
  },
  "idx": 802
}