{
  "id": "2023-10-31T19:32:29.830Z0.6641168390738063",
  "alert": "Start of result\nResult\n\nAmalgamated loan fully repaid.\n\nThe amalgamated loan has been paid in full.\u000bThe private company is not taken under Division 7A to pay a dividend to the shareholder or shareholder's associate.\n\nInterest received by the private company must be included in the income tax return for 2004-05.\n\nMinimum yearly repayment\n\n$111.00\n\nBenchmark interest rate\n\n7.05%\n\nOpening balance:\n\nDate: 30/06/2004\n\nBalance: $526.00\n\nDays: 315\n\nInterest: $32.00\n\nPayments\n\nDate: 12/05/2005\n\nAmount: $5,260.00\n\nBalance: $0\n\nDays: 50\n\nInterest: $0\n\n\n\n\nTotal repayments\n\n$5,260.00\n\nTotal interest\n\n$32.00\n\nTotal principal\n\n$5,228.00\n\nClosing balance\n\nDate: 30/06/2005\n\nBalance: $0",
  "outputs": {
    "enquiryRateFormatted": "7.05%",
    "enquiryYearEndMinusOneDisplay": "30/06/2004",
    "amalgamatedLoanNotPaidByEOIYFormatted": "$526.00",
    "openingBalancePayDays": "315",
    "openingBalanceInterestFormatted": "$32.00",
    "totalAmountOfRepaymentFormatted": "$5,260.00",
    "totalInterestFormatted": "$32.00",
    "principalFormatted": "$5,228.00",
    "enquiryYearEndDisplay": "30/06/2005",
    "minimumYearRepaymentFormatted": "$111.00",
    "loanAmountFormatted": "$0"
  },
  "repayments": [
    {
      "rd": "12/5/2005",
      "ra": 5260
    }
  ],
  "inputs": {
    "incomeYearOfLoan": 2004,
    "fullTermOfAmalgamatedLoan": 6,
    "incomeYearOfEnquiring": 2005,
    "amalgamatedLoanNotPaidByEOIY": 526,
    "repayments": null,
    "lodgement_date": "30/8/2004"
  },
  "idx": 5576
}