{
  "id": "2023-10-31T18:11:21.751Z0.787545279012044",
  "alert": "Start of result\nResult\n\nMinimum yearly repayment not met.\n\nThe amount of the loan not repaid at the end of income year 2014-15 is $12,295.00.\n\nThe private company may be taken to pay a dividend under Division 7A to the shareholder or shareholder's associate because the amount repaid during income year 2014-15 in relation to the amalgamated loan is less than the minimum yearly repayment required.\n\nInterest received by the private company must be included in the income tax return for 2014-15.\n\nMinimum yearly repayment\n\n$6,701.00\n\nBenchmark interest rate\n\n5.95%\n\nOpening balance:\n\nDate: 30/06/2014\n\nBalance: $12,295.00\n\nDays: 365\n\nInterest: $731.55\n\nTotal repayments\n\n$0\n\nTotal interest\n\n$731.55\n\nTotal principal\n\n$0\n\nClosing balance\n\nDate: 30/06/2015\n\nBalance: $12,295.00",
  "outputs": {
    "enquiryRateFormatted": "5.95%",
    "enquiryYearEndMinusOneDisplay": "30/06/2014",
    "amalgamatedLoanNotPaidByEOIYFormatted": "$12,295.00",
    "openingBalancePayDays": "365",
    "openingBalanceInterestFormatted": "$731.55",
    "totalAmountOfRepaymentFormatted": "$0",
    "totalInterestFormatted": "$731.55",
    "principalFormatted": "$0",
    "enquiryYearEndDisplay": "30/06/2015",
    "minimumYearRepaymentFormatted": "$6,701.00",
    "loanAmountFormatted": "$12,295.00"
  },
  "repayments": [],
  "inputs": {
    "incomeYearOfLoan": 2011,
    "fullTermOfAmalgamatedLoan": 5,
    "incomeYearOfEnquiring": 2015,
    "amalgamatedLoanNotPaidByEOIY": 12295,
    "repayments": null,
    "lodgement_date": null
  },
  "idx": 3500
}