{
  "id": "2023-09-04T17:24:37.127Z0.23807361234419822",
  "alert": "Start of result\nResult\n\nMinimum yearly repayment not met.\n\nThe amount of the loan not repaid at the end of income year 2013-14 is $83,759,138.09.\n\nThe private company may be taken to pay a dividend under Division 7A to the shareholder or shareholder's associate because the amount repaid during income year 2013-14 in relation to the amalgamated loan is less than the minimum yearly repayment required.\n\nInterest received by the private company must be included in the income tax return for 2013-14.\n\nMinimum yearly repayment\n\n$17,140,660.00\n\nBenchmark interest rate\n\n6.2%\n\nOpening balance:\n\nDate: 30/06/2013\n\nBalance: $83,759,138.09\n\nDays: 365\n\nInterest: $5,193,066.56\n\nTotal repayments\n\n$0\n\nTotal interest\n\n$5,193,066.56\n\nTotal principal\n\n$0\n\nClosing balance\n\nDate: 30/06/2014\n\nBalance: $83,759,138.09",
  "outputs": {
    "enquiryRateFormatted": "6.2%",
    "enquiryYearEndMinusOneDisplay": "30/06/2013",
    "amalgamatedLoanNotPaidByEOIYFormatted": "$83,759,138.09",
    "openingBalancePayDays": "365",
    "openingBalanceInterestFormatted": "$5,193,066.56",
    "totalAmountOfRepaymentFormatted": "$0",
    "totalInterestFormatted": "$5,193,066.56",
    "principalFormatted": "$0",
    "enquiryYearEndDisplay": "30/06/2014",
    "minimumYearRepaymentFormatted": "$17,140,660.00"
  },
  "repayments": [],
  "inputs": {
    "incomeYearOfLoan": 2013,
    "fullTermOfAmalgamatedLoan": 6,
    "incomeYearOfEnquiring": 2014,
    "amalgamatedLoanNotPaidByEOIY": 83759138.09432231,
    "repayments": null,
    "lodgement_date": "9/10/2013"
  },
  "idx": 2102
}