{
  "id": "2023-09-06T13:21:19.840Z0.1879032094764923",
  "alert": "Start of result\nResult\n\nMinimum yearly repayment met.\n\nThe amount of the loan not repaid at the end of income year 2007-08 is $198.94.\n\nThe amalgamated loan will not be taken to be a dividend because the total repayments made are equal to or greater than the minimum yearly repayment required for income year 2007-08.\n\nInterest received by the private company must be included in the income tax return for 2007-08.\n\nMinimum yearly repayment\n\n$677.00\n\nBenchmark interest rate\n\n8.05%\n\nOpening balance:\n\nDate: 30/06/2007\n\nBalance: $2,700.00\n\nDays: 335\n\nInterest: $198.94\n\nPayments\n\nDate: 31/05/2008\n\nAmount: $2,700.00\n\nBalance: $0\n\nDays: 31\n\nInterest: $0\n\n\n\n\nTotal repayments\n\n$2,700.00\n\nTotal interest\n\n$198.94\n\nTotal principal\n\n$2,501.06\n\nClosing balance\n\nDate: 30/06/2008\n\nBalance: $198.94",
  "outputs": {
    "enquiryRateFormatted": "8.05%",
    "enquiryYearEndMinusOneDisplay": "30/06/2007",
    "amalgamatedLoanNotPaidByEOIYFormatted": "$2,700.00",
    "openingBalancePayDays": "335",
    "openingBalanceInterestFormatted": "$198.94",
    "totalAmountOfRepaymentFormatted": "$2,700.00",
    "totalInterestFormatted": "$198.94",
    "principalFormatted": "$2,501.06",
    "enquiryYearEndDisplay": "30/06/2008",
    "minimumYearRepaymentFormatted": "$677.00"
  },
  "repayments": [
    {
      "rd": "31/5/2008",
      "ra": 2700
    }
  ],
  "inputs": {
    "incomeYearOfLoan": 2007,
    "fullTermOfAmalgamatedLoan": 5,
    "incomeYearOfEnquiring": 2008,
    "amalgamatedLoanNotPaidByEOIY": 2700,
    "repayments": null,
    "lodgement_date": "10/5/2008"
  },
  "idx": 1424
}