{
  "id": "2023-10-31T20:24:25.774Z0.20454785859131097",
  "alert": "Start of result\nResult\n\nAmalgamated loan fully repaid.\n\nThe amalgamated loan has been paid in full.\u000bThe private company is not taken under Division 7A to pay a dividend to the shareholder or shareholder's associate.\n\nInterest received by the private company must be included in the income tax return for 2001-02.\n\nMinimum yearly repayment\n\n-$32.00\n\nBenchmark interest rate\n\n6.8%\n\nOpening balance:\n\nDate: 30/06/2001\n\nBalance: $19.01\n\nDays: 106\n\nInterest: $0.38\n\nPayments\n\nDate: 15/10/2001\n\nAmount: $190.10\n\nBalance: $0\n\nDays: 259\n\nInterest: $0\n\n\n\n\nTotal repayments\n\n$190.10\n\nTotal interest\n\n$0.38\n\nTotal principal\n\n$189.72\n\nClosing balance\n\nDate: 30/06/2002\n\nBalance: $0",
  "outputs": {
    "enquiryRateFormatted": "6.8%",
    "enquiryYearEndMinusOneDisplay": "30/06/2001",
    "amalgamatedLoanNotPaidByEOIYFormatted": "$19.01",
    "openingBalancePayDays": "106",
    "openingBalanceInterestFormatted": "$0.38",
    "totalAmountOfRepaymentFormatted": "$190.10",
    "totalInterestFormatted": "$0.38",
    "principalFormatted": "$189.72",
    "enquiryYearEndDisplay": "30/06/2002",
    "minimumYearRepaymentFormatted": "-$32.00",
    "loanAmountFormatted": "$0"
  },
  "repayments": [
    {
      "rd": "15/10/2001",
      "ra": 190.1053148983492
    }
  ],
  "inputs": {
    "incomeYearOfLoan": 2001,
    "fullTermOfAmalgamatedLoan": 7,
    "incomeYearOfEnquiring": 2002,
    "amalgamatedLoanNotPaidByEOIY": 19.010531489834957,
    "repayments": null,
    "lodgement_date": "27/1/2002"
  },
  "idx": 6442
}