{
  "id": "2023-10-31T17:43:45.191Z0.4216989757606562",
  "alert": "Start of result\nResult\n\nAmalgamated loan fully repaid.\n\nThe amalgamated loan has been paid in full.\u000bThe private company is not taken under Division 7A to pay a dividend to the shareholder or shareholder's associate.\n\nInterest received by the private company must be included in the income tax return for 2015-16.\n\nMinimum yearly repayment\n\n$15.00\n\nBenchmark interest rate\n\n5.45%\n\nOpening balance:\n\nDate: 30/06/2015\n\nBalance: $86.82\n\nDays: 211\n\nInterest: $2.73\n\nPayments\n\nDate: 28/01/2016\n\nAmount: $868.21\n\nBalance: $0\n\nDays: 155\n\nInterest: $0\n\n\n\n\nTotal repayments\n\n$868.21\n\nTotal interest\n\n$2.73\n\nTotal principal\n\n$865.48\n\nClosing balance\n\nDate: 30/06/2016\n\nBalance: $0",
  "outputs": {
    "enquiryRateFormatted": "5.45%",
    "enquiryYearEndMinusOneDisplay": "30/06/2015",
    "amalgamatedLoanNotPaidByEOIYFormatted": "$86.82",
    "openingBalancePayDays": "211",
    "openingBalanceInterestFormatted": "$2.73",
    "totalAmountOfRepaymentFormatted": "$868.21",
    "totalInterestFormatted": "$2.73",
    "principalFormatted": "$865.48",
    "enquiryYearEndDisplay": "30/06/2016",
    "minimumYearRepaymentFormatted": "$15.00",
    "loanAmountFormatted": "$0"
  },
  "repayments": [
    {
      "rd": "28/1/2016",
      "ra": 868.2151230591226
    }
  ],
  "inputs": {
    "incomeYearOfLoan": 2015,
    "fullTermOfAmalgamatedLoan": 7,
    "incomeYearOfEnquiring": 2016,
    "amalgamatedLoanNotPaidByEOIY": 86.82151230591226,
    "repayments": null,
    "lodgement_date": "30/8/2015"
  },
  "idx": 2397
}