{
  "id": "2023-09-04T16:44:18.857Z0.45239922487559814",
  "alert": "Start of result\nResult\n\nMinimum yearly repayment not met.\n\nThe amount of the loan not repaid at the end of income year 2020-21 is $81,437,709.23.\n\nThe private company may be taken to pay a dividend under Division 7A to the shareholder or shareholder's associate because the amount repaid during income year 2020-21 in relation to the amalgamated loan is less than the minimum yearly repayment required.\n\nInterest received by the private company must be included in the income tax return for 2020-21.\n\nMinimum yearly repayment\n\n$85,118,694.00\n\nBenchmark interest rate\n\n4.52%\n\nOpening balance:\n\nDate: 30/06/2020\n\nBalance: $81,437,709.23\n\nDays: 365\n\nInterest: $3,680,984.46\n\nTotal repayments\n\n$0\n\nTotal interest\n\n$3,680,984.46\n\nTotal principal\n\n$0\n\nClosing balance\n\nDate: 30/06/2021\n\nBalance: $81,437,709.23",
  "outputs": {
    "enquiryRateFormatted": "4.52%",
    "enquiryYearEndMinusOneDisplay": "30/06/2020",
    "amalgamatedLoanNotPaidByEOIYFormatted": "$81,437,709.23",
    "openingBalancePayDays": "365",
    "openingBalanceInterestFormatted": "$3,680,984.46",
    "totalAmountOfRepaymentFormatted": "$0",
    "totalInterestFormatted": "$3,680,984.46",
    "principalFormatted": "$0",
    "enquiryYearEndDisplay": "30/06/2021",
    "minimumYearRepaymentFormatted": "$85,118,694.00"
  },
  "repayments": [],
  "inputs": {
    "incomeYearOfLoan": 2016,
    "fullTermOfAmalgamatedLoan": 5,
    "incomeYearOfEnquiring": 2021,
    "amalgamatedLoanNotPaidByEOIY": 81437709.23384292,
    "repayments": null,
    "lodgement_date": null
  },
  "idx": 1091
}