{
  "id": "2023-10-31T19:05:05.597Z0.2727172855604204",
  "alert": "Start of result\nResult\n\nAmalgamated loan fully repaid.\n\nThe amalgamated loan has been paid in full.\u000bThe private company is not taken under Division 7A to pay a dividend to the shareholder or shareholder's associate.\n\nInterest received by the private company must be included in the income tax return for 2010-11.\n\nMinimum yearly repayment\n\n$1,479.00\n\nBenchmark interest rate\n\n7.4%\n\nOpening balance:\n\nDate: 30/06/2010\n\nBalance: $1,377.00\n\nDays: 349\n\nInterest: $97.43\n\nPayments\n\nDate: 15/06/2011\n\nAmount: $4,673.00\n\nBalance: $0\n\nDays: 16\n\nInterest: $0\n\n\n\n\nTotal repayments\n\n$4,673.00\n\nTotal interest\n\n$97.43\n\nTotal principal\n\n$4,575.57\n\nClosing balance\n\nDate: 30/06/2011\n\nBalance: $0",
  "outputs": {
    "enquiryRateFormatted": "7.4%",
    "enquiryYearEndMinusOneDisplay": "30/06/2010",
    "amalgamatedLoanNotPaidByEOIYFormatted": "$1,377.00",
    "openingBalancePayDays": "349",
    "openingBalanceInterestFormatted": "$97.43",
    "totalAmountOfRepaymentFormatted": "$4,673.00",
    "totalInterestFormatted": "$97.43",
    "principalFormatted": "$4,575.57",
    "enquiryYearEndDisplay": "30/06/2011",
    "minimumYearRepaymentFormatted": "$1,479.00",
    "loanAmountFormatted": "$0"
  },
  "repayments": [
    {
      "rd": "15/6/2011",
      "ra": 4673
    }
  ],
  "inputs": {
    "incomeYearOfLoan": 2006,
    "fullTermOfAmalgamatedLoan": 5,
    "incomeYearOfEnquiring": 2011,
    "amalgamatedLoanNotPaidByEOIY": 1377,
    "repayments": null,
    "lodgement_date": null
  },
  "idx": 4994
}