{
  "id": "2023-09-04T21:34:29.032Z0.739568291198601",
  "alert": "Start of result\nResult\n\nMinimum yearly repayment not met.\n\nThe amount of the loan not repaid at the end of income year 2009-10 is $782.55.\n\nThe private company may be taken to pay a dividend under Division 7A to the shareholder or shareholder's associate because the amount repaid during income year 2009-10 in relation to the amalgamated loan is less than the minimum yearly repayment required.\n\nInterest received by the private company must be included in the income tax return for 2009-10.\n\nMinimum yearly repayment\n\n$7,184.00\n\nBenchmark interest rate\n\n5.75%\n\nOpening balance:\n\nDate: 30/06/2009\n\nBalance: $6,793.00\n\nDays: 0\n\nInterest: $0\n\nPayments\n\nDate: 01/07/2009\n\nAmount: $6,053.00\n\nBalance: $740.00\n\nDays: 365\n\nInterest: $42.55\n\n\n\n\nTotal repayments\n\n$6,053.00\n\nTotal interest\n\n$42.55\n\nTotal principal\n\n$6,010.45\n\nClosing balance\n\nDate: 30/06/2010\n\nBalance: $782.55",
  "outputs": {
    "enquiryRateFormatted": "5.75%",
    "enquiryYearEndMinusOneDisplay": "30/06/2009",
    "amalgamatedLoanNotPaidByEOIYFormatted": "$6,793.00",
    "openingBalancePayDays": "0",
    "openingBalanceInterestFormatted": "$0",
    "totalAmountOfRepaymentFormatted": "$6,053.00",
    "totalInterestFormatted": "$42.55",
    "principalFormatted": "$6,010.45",
    "enquiryYearEndDisplay": "30/06/2010",
    "minimumYearRepaymentFormatted": "$7,184.00"
  },
  "repayments": [
    {
      "rd": "1/7/2009",
      "ra": 6053
    }
  ],
  "inputs": {
    "incomeYearOfLoan": 2006,
    "fullTermOfAmalgamatedLoan": 4,
    "incomeYearOfEnquiring": 2010,
    "amalgamatedLoanNotPaidByEOIY": 6793,
    "repayments": null,
    "lodgement_date": null
  },
  "idx": 1417
}