{
  "id": "2023-09-06T23:17:29.384Z0.49205968764744323",
  "alert": "Start of result\nResult\n\nMinimum yearly repayment not met.\n\nThe amount of the loan not repaid at the end of income year 2003-04 is $44.68.\n\nThe private company may be taken to pay a dividend under Division 7A to the shareholder or shareholder's associate because the amount repaid during income year 2003-04 in relation to the amalgamated loan is less than the minimum yearly repayment required.\n\nInterest received by the private company must be included in the income tax return for 2003-04.\n\nMinimum yearly repayment\n\n$11.00\n\nBenchmark interest rate\n\n6.55%\n\nOpening balance:\n\nDate: 30/06/2003\n\nBalance: $44.68\n\nDays: 366\n\nInterest: $2.93\n\nTotal repayments\n\n$0\n\nTotal interest\n\n$2.93\n\nTotal principal\n\n$0\n\nClosing balance\n\nDate: 30/06/2004\n\nBalance: $44.68",
  "outputs": {
    "enquiryRateFormatted": "6.55%",
    "enquiryYearEndMinusOneDisplay": "30/06/2003",
    "amalgamatedLoanNotPaidByEOIYFormatted": "$44.68",
    "openingBalancePayDays": "366",
    "openingBalanceInterestFormatted": "$2.93",
    "totalAmountOfRepaymentFormatted": "$0",
    "totalInterestFormatted": "$2.93",
    "principalFormatted": "$0",
    "enquiryYearEndDisplay": "30/06/2004",
    "minimumYearRepaymentFormatted": "$11.00"
  },
  "repayments": [],
  "inputs": {
    "incomeYearOfLoan": 2001,
    "fullTermOfAmalgamatedLoan": 7,
    "incomeYearOfEnquiring": 2004,
    "amalgamatedLoanNotPaidByEOIY": 44.68704346438301,
    "repayments": null,
    "lodgement_date": null
  },
  "idx": 2964
}