{
  "id": "2023-09-04T22:09:52.703Z0.3571978408811549",
  "alert": "Start of result\nResult\n\nMinimum yearly repayment not met.\n\nThe amount of the loan not repaid at the end of income year 2002-03 is $11,062.00.\n\nThe private company may be taken to pay a dividend under Division 7A to the shareholder or shareholder's associate because the amount repaid during income year 2002-03 in relation to the amalgamated loan is less than the minimum yearly repayment required.\n\nInterest received by the private company must be included in the income tax return for 2002-03.\n\nMinimum yearly repayment\n\n$4,161.00\n\nBenchmark interest rate\n\n6.3%\n\nOpening balance:\n\nDate: 30/06/2002\n\nBalance: $11,062.00\n\nDays: 365\n\nInterest: $696.91\n\nTotal repayments\n\n$0\n\nTotal interest\n\n$696.91\n\nTotal principal\n\n$0\n\nClosing balance\n\nDate: 30/06/2003\n\nBalance: $11,062.00",
  "outputs": {
    "enquiryRateFormatted": "6.3%",
    "enquiryYearEndMinusOneDisplay": "30/06/2002",
    "amalgamatedLoanNotPaidByEOIYFormatted": "$11,062.00",
    "openingBalancePayDays": "365",
    "openingBalanceInterestFormatted": "$696.91",
    "totalAmountOfRepaymentFormatted": "$0",
    "totalInterestFormatted": "$696.91",
    "principalFormatted": "$0",
    "enquiryYearEndDisplay": "30/06/2003",
    "minimumYearRepaymentFormatted": "$4,161.00"
  },
  "repayments": [],
  "inputs": {
    "incomeYearOfLoan": 2002,
    "fullTermOfAmalgamatedLoan": 3,
    "incomeYearOfEnquiring": 2003,
    "amalgamatedLoanNotPaidByEOIY": 11062,
    "repayments": null,
    "lodgement_date": "27/4/2003"
  },
  "idx": 360
}