{
  "id": "2023-10-31T19:20:53.717Z0.6735529910018303",
  "alert": "Start of result\nResult\n\nMinimum yearly repayment met.\n\nThe amount of the loan not repaid at the end of income year 2007-08 is $1,900.86.\n\n\u000b\n\nThe amalgamated loan will not be taken to be a dividend because the total repayments made are equal to or greater than the minimum yearly repayment required for income year 2007-08.\n\nInterest received by the private company must be included in the income tax return for 2007-08.\n\nMinimum yearly repayment\n\n$1,220.00\n\nBenchmark interest rate\n\n8.05%\n\nOpening balance:\n\nDate: 30/06/2007\n\nBalance: $4,865.00\n\nDays: 13\n\nInterest: $13.91\n\nPayments\n\nDate: 14/07/2007\n\nAmount: $3,114.00\n\nBalance: $1,751.00\n\nDays: 353\n\nInterest: $135.95\n\n\n\n\nTotal repayments\n\n$3,114.00\n\nTotal interest\n\n$149.86\n\nTotal principal\n\n$2,964.14\n\nClosing balance\n\nDate: 30/06/2008\n\nBalance: $1,900.86",
  "outputs": {
    "enquiryRateFormatted": "8.05%",
    "enquiryYearEndMinusOneDisplay": "30/06/2007",
    "amalgamatedLoanNotPaidByEOIYFormatted": "$4,865.00",
    "openingBalancePayDays": "13",
    "openingBalanceInterestFormatted": "$13.91",
    "totalAmountOfRepaymentFormatted": "$3,114.00",
    "totalInterestFormatted": "$149.86",
    "principalFormatted": "$2,964.14",
    "enquiryYearEndDisplay": "30/06/2008",
    "minimumYearRepaymentFormatted": "$1,220.00",
    "loanAmountFormatted": "$1,900.86"
  },
  "repayments": [
    {
      "rd": "14/7/2007",
      "ra": 3114
    }
  ],
  "inputs": {
    "incomeYearOfLoan": 2005,
    "fullTermOfAmalgamatedLoan": 7,
    "incomeYearOfEnquiring": 2008,
    "amalgamatedLoanNotPaidByEOIY": 4865,
    "repayments": null,
    "lodgement_date": null
  },
  "idx": 5339
}