{
  "id": "2023-09-06T05:27:00.803Z0.49711083557652347",
  "alert": "Start of result\nResult\n\nMinimum yearly repayment met.\n\nThe amount of the loan not repaid at the end of income year 2015-16 is $198.37.\n\nThe amalgamated loan will not be taken to be a dividend because the total repayments made are equal to or greater than the minimum yearly repayment required for income year 2015-16.\n\nInterest received by the private company must be included in the income tax return for 2015-16.\n\nMinimum yearly repayment\n\n$1,161.00\n\nBenchmark interest rate\n\n5.45%\n\nOpening balance:\n\nDate: 30/06/2015\n\nBalance: $4,074.00\n\nDays: 327\n\nInterest: $198.37\n\nPayments\n\nDate: 23/05/2016\n\nAmount: $4,074.00\n\nBalance: $0\n\nDays: 39\n\nInterest: $0\n\n\n\n\nTotal repayments\n\n$4,074.00\n\nTotal interest\n\n$198.37\n\nTotal principal\n\n$3,875.63\n\nClosing balance\n\nDate: 30/06/2016\n\nBalance: $198.37",
  "outputs": {
    "enquiryRateFormatted": "5.45%",
    "enquiryYearEndMinusOneDisplay": "30/06/2015",
    "amalgamatedLoanNotPaidByEOIYFormatted": "$4,074.00",
    "openingBalancePayDays": "327",
    "openingBalanceInterestFormatted": "$198.37",
    "totalAmountOfRepaymentFormatted": "$4,074.00",
    "totalInterestFormatted": "$198.37",
    "principalFormatted": "$3,875.63",
    "enquiryYearEndDisplay": "30/06/2016",
    "minimumYearRepaymentFormatted": "$1,161.00"
  },
  "repayments": [
    {
      "rd": "23/5/2016",
      "ra": 4074
    }
  ],
  "inputs": {
    "incomeYearOfLoan": 2012,
    "fullTermOfAmalgamatedLoan": 7,
    "incomeYearOfEnquiring": 2016,
    "amalgamatedLoanNotPaidByEOIY": 4074,
    "repayments": null,
    "lodgement_date": null
  },
  "idx": 2228
}