{
  "id": "2023-10-31T18:37:03.873Z0.2826726078490046",
  "alert": "Start of result\nResult\n\nMinimum yearly repayment not met.\n\nThe amount of the loan not repaid at the end of income year 2010-11 is $3,461.97.\n\nThe private company may be taken to pay a dividend under Division 7A to the shareholder or shareholder's associate because the amount repaid during income year 2010-11 in relation to the amalgamated loan is less than the minimum yearly repayment required.\n\nInterest received by the private company must be included in the income tax return for 2010-11.\n\nMinimum yearly repayment\n\n$9,476.00\n\nBenchmark interest rate\n\n7.4%\n\nOpening balance:\n\nDate: 30/06/2010\n\nBalance: $8,823.00\n\nDays: 51\n\nInterest: $91.23\n\nPayments\n\nDate: 21/08/2010\n\nAmount: $5,654.00\n\nBalance: $3,169.00\n\nDays: 314\n\nInterest: $201.74\n\n\n\n\nTotal repayments\n\n$5,654.00\n\nTotal interest\n\n$292.97\n\nTotal principal\n\n$5,361.03\n\nClosing balance\n\nDate: 30/06/2011\n\nBalance: $3,461.97",
  "outputs": {
    "enquiryRateFormatted": "7.4%",
    "enquiryYearEndMinusOneDisplay": "30/06/2010",
    "amalgamatedLoanNotPaidByEOIYFormatted": "$8,823.00",
    "openingBalancePayDays": "51",
    "openingBalanceInterestFormatted": "$91.23",
    "totalAmountOfRepaymentFormatted": "$5,654.00",
    "totalInterestFormatted": "$292.97",
    "principalFormatted": "$5,361.03",
    "enquiryYearEndDisplay": "30/06/2011",
    "minimumYearRepaymentFormatted": "$9,476.00",
    "loanAmountFormatted": "$3,461.97"
  },
  "repayments": [
    {
      "rd": "21/8/2010",
      "ra": 5654
    }
  ],
  "inputs": {
    "incomeYearOfLoan": 2008,
    "fullTermOfAmalgamatedLoan": 3,
    "incomeYearOfEnquiring": 2011,
    "amalgamatedLoanNotPaidByEOIY": 8823,
    "repayments": null,
    "lodgement_date": null
  },
  "idx": 4273
}