{
  "id": "2023-10-31T17:16:03.341Z0.2685850140402801",
  "alert": "Start of result\nResult\n\nAmalgamated loan fully repaid.\n\nThe amalgamated loan has been paid in full.\u000bThe private company is not taken under Division 7A to pay a dividend to the shareholder or shareholder's associate.\n\nInterest received by the private company must be included in the income tax return for 2022-23.\n\nMinimum yearly repayment\n\n$52.00\n\nBenchmark interest rate\n\n4.77%\n\nOpening balance:\n\nDate: 30/06/2022\n\nBalance: $96.17\n\nDays: 204\n\nInterest: $2.56\n\nPayments\n\nDate: 21/01/2023\n\nAmount: $961.70\n\nBalance: $0\n\nDays: 161\n\nInterest: $0\n\n\n\n\nTotal repayments\n\n$961.70\n\nTotal interest\n\n$2.56\n\nTotal principal\n\n$959.14\n\nClosing balance\n\nDate: 30/06/2023\n\nBalance: $0",
  "outputs": {
    "enquiryRateFormatted": "4.77%",
    "enquiryYearEndMinusOneDisplay": "30/06/2022",
    "amalgamatedLoanNotPaidByEOIYFormatted": "$96.17",
    "openingBalancePayDays": "204",
    "openingBalanceInterestFormatted": "$2.56",
    "totalAmountOfRepaymentFormatted": "$961.70",
    "totalInterestFormatted": "$2.56",
    "principalFormatted": "$959.14",
    "enquiryYearEndDisplay": "30/06/2023",
    "minimumYearRepaymentFormatted": "$52.00",
    "loanAmountFormatted": "$0"
  },
  "repayments": [
    {
      "rd": "21/1/2023",
      "ra": 961.7072386536738
    }
  ],
  "inputs": {
    "incomeYearOfLoan": 2020,
    "fullTermOfAmalgamatedLoan": 4,
    "incomeYearOfEnquiring": 2023,
    "amalgamatedLoanNotPaidByEOIY": 96.17072386536738,
    "repayments": null,
    "lodgement_date": null
  },
  "idx": 801
}