{
  "id": "2023-09-04T21:56:49.408Z0.46459146371929094",
  "alert": "Start of result\nResult\n\nMinimum yearly repayment met.\n\nThe amount of the loan not repaid at the end of income year 2005-06 is $209.24.\n\nThe amalgamated loan will not be taken to be a dividend because the total repayments made are equal to or greater than the minimum yearly repayment required for income year 2005-06.\n\nInterest received by the private company must be included in the income tax return for 2005-06.\n\nMinimum yearly repayment\n\n$37.00\n\nBenchmark interest rate\n\n7.3%\n\nOpening balance:\n\nDate: 30/06/2005\n\nBalance: $1,084.00\n\nDays: 0\n\nInterest: $0\n\nPayments\n\nDate: 01/07/2005\n\nAmount: $889.00\n\nBalance: $195.00\n\nDays: 365\n\nInterest: $14.24\n\n\n\n\nTotal repayments\n\n$889.00\n\nTotal interest\n\n$14.24\n\nTotal principal\n\n$874.76\n\nClosing balance\n\nDate: 30/06/2006\n\nBalance: $209.24",
  "outputs": {
    "enquiryRateFormatted": "7.3%",
    "enquiryYearEndMinusOneDisplay": "30/06/2005",
    "amalgamatedLoanNotPaidByEOIYFormatted": "$1,084.00",
    "openingBalancePayDays": "0",
    "openingBalanceInterestFormatted": "$0",
    "totalAmountOfRepaymentFormatted": "$889.00",
    "totalInterestFormatted": "$14.24",
    "principalFormatted": "$874.76",
    "enquiryYearEndDisplay": "30/06/2006",
    "minimumYearRepaymentFormatted": "$37.00"
  },
  "repayments": [
    {
      "rd": "1/7/2005",
      "ra": 889
    }
  ],
  "inputs": {
    "incomeYearOfLoan": 2005,
    "fullTermOfAmalgamatedLoan": 7,
    "incomeYearOfEnquiring": 2006,
    "amalgamatedLoanNotPaidByEOIY": 1084,
    "repayments": null,
    "lodgement_date": "30/6/2006"
  },
  "idx": 1826
}