{
  "id": "2023-10-31T19:10:56.490Z0.508549019202139",
  "alert": "Start of result\nResult\n\nMinimum yearly repayment not met.\n\nThe amount of the loan not repaid at the end of income year 2005-06 is $11,093.00.\n\nThe private company may be taken to pay a dividend under Division 7A to the shareholder or shareholder's associate because the amount repaid during income year 2005-06 in relation to the amalgamated loan is less than the minimum yearly repayment required.\n\nInterest received by the private company must be included in the income tax return for 2005-06.\n\nMinimum yearly repayment\n\n$11,903.00\n\nBenchmark interest rate\n\n7.3%\n\nOpening balance:\n\nDate: 30/06/2005\n\nBalance: $11,093.00\n\nDays: 365\n\nInterest: $809.79\n\nTotal repayments\n\n$0\n\nTotal interest\n\n$809.79\n\nTotal principal\n\n$0\n\nClosing balance\n\nDate: 30/06/2006\n\nBalance: $11,093.00",
  "outputs": {
    "enquiryRateFormatted": "7.3%",
    "enquiryYearEndMinusOneDisplay": "30/06/2005",
    "amalgamatedLoanNotPaidByEOIYFormatted": "$11,093.00",
    "openingBalancePayDays": "365",
    "openingBalanceInterestFormatted": "$809.79",
    "totalAmountOfRepaymentFormatted": "$0",
    "totalInterestFormatted": "$809.79",
    "principalFormatted": "$0",
    "enquiryYearEndDisplay": "30/06/2006",
    "minimumYearRepaymentFormatted": "$11,903.00",
    "loanAmountFormatted": "$11,093.00"
  },
  "repayments": [],
  "inputs": {
    "incomeYearOfLoan": 2005,
    "fullTermOfAmalgamatedLoan": 1,
    "incomeYearOfEnquiring": 2006,
    "amalgamatedLoanNotPaidByEOIY": 11093,
    "repayments": null,
    "lodgement_date": "28/11/2005"
  },
  "idx": 5124
}