{
  "id": "2023-09-04T16:46:04.547Z0.8149136173716782",
  "alert": "Start of result\nResult\n\nMinimum yearly repayment met.\n\nThe amount of the loan not repaid at the end of income year 2016-17 is $4.05.\n\nThe amalgamated loan will not be taken to be a dividend because the total repayments made are equal to or greater than the minimum yearly repayment required for income year 2016-17.\n\nInterest received by the private company must be included in the income tax return for 2016-17.\n\nMinimum yearly repayment\n\n$1,781.00\n\nBenchmark interest rate\n\n5.4%\n\nOpening balance:\n\nDate: 30/06/2016\n\nBalance: $8,924.00\n\nDays: 0\n\nInterest: $0\n\nPayments\n\nDate: 01/07/2016\n\nAmount: $8,515.00\n\nBalance: $409.00\n\nDays: 67\n\nInterest: $4.05\n\n\n\n\nDate: 06/09/2016\n\nAmount: $409.00\n\nBalance: $0\n\nDays: 298\n\nInterest: $0\n\n\n\n\nTotal repayments\n\n$8,924.00\n\nTotal interest\n\n$4.05\n\nTotal principal\n\n$8,919.95\n\nClosing balance\n\nDate: 30/06/2017\n\nBalance: $4.05",
  "outputs": {
    "enquiryRateFormatted": "5.4%",
    "enquiryYearEndMinusOneDisplay": "30/06/2016",
    "amalgamatedLoanNotPaidByEOIYFormatted": "$8,924.00",
    "openingBalancePayDays": "0",
    "openingBalanceInterestFormatted": "$0",
    "totalAmountOfRepaymentFormatted": "$8,924.00",
    "totalInterestFormatted": "$4.05",
    "principalFormatted": "$8,919.95",
    "enquiryYearEndDisplay": "30/06/2017",
    "minimumYearRepaymentFormatted": "$1,781.00"
  },
  "repayments": [
    {
      "rd": "1/7/2016",
      "ra": 8515
    },
    {
      "rd": "6/9/2016",
      "ra": 409
    }
  ],
  "inputs": {
    "incomeYearOfLoan": 2016,
    "fullTermOfAmalgamatedLoan": 6,
    "incomeYearOfEnquiring": 2017,
    "amalgamatedLoanNotPaidByEOIY": 8924,
    "repayments": null,
    "lodgement_date": "1/7/2016"
  },
  "idx": 1141
}