{
  "id": "2023-09-05T16:57:44.991Z0.20415303092328863",
  "alert": "Start of result\nResult\n\nMinimum yearly repayment met.\n\nThe amount of the loan not repaid at the end of income year 2020-21 is $1,608.43.\n\nThe amalgamated loan will not be taken to be a dividend because the total repayments made are equal to or greater than the minimum yearly repayment required for income year 2020-21.\n\nInterest received by the private company must be included in the income tax return for 2020-21.\n\nMinimum yearly repayment\n\n$685.00\n\nBenchmark interest rate\n\n4.52%\n\nOpening balance:\n\nDate: 30/06/2020\n\nBalance: $2,458.00\n\nDays: 161\n\nInterest: $49.01\n\nPayments\n\nDate: 09/12/2020\n\nAmount: $937.00\n\nBalance: $1,521.00\n\nDays: 204\n\nInterest: $38.42\n\n\n\n\nTotal repayments\n\n$937.00\n\nTotal interest\n\n$87.43\n\nTotal principal\n\n$849.57\n\nClosing balance\n\nDate: 30/06/2021\n\nBalance: $1,608.43",
  "outputs": {
    "enquiryRateFormatted": "4.52%",
    "enquiryYearEndMinusOneDisplay": "30/06/2020",
    "amalgamatedLoanNotPaidByEOIYFormatted": "$2,458.00",
    "openingBalancePayDays": "161",
    "openingBalanceInterestFormatted": "$49.01",
    "totalAmountOfRepaymentFormatted": "$937.00",
    "totalInterestFormatted": "$87.43",
    "principalFormatted": "$849.57",
    "enquiryYearEndDisplay": "30/06/2021",
    "minimumYearRepaymentFormatted": "$685.00"
  },
  "repayments": [
    {
      "rd": "9/12/2020",
      "ra": 937
    }
  ],
  "inputs": {
    "incomeYearOfLoan": 2019,
    "fullTermOfAmalgamatedLoan": 5,
    "incomeYearOfEnquiring": 2021,
    "amalgamatedLoanNotPaidByEOIY": 2458,
    "repayments": null,
    "lodgement_date": null
  },
  "idx": 2590
}