{
  "id": "2023-09-04T16:35:29.758Z0.009274936871648931",
  "alert": "Start of result\nResult\n\nMinimum yearly repayment met.\n\nThe amount of the loan not repaid at the end of income year 2018-19 is $14.68.\n\nThe amalgamated loan will not be taken to be a dividend because the total repayments made are equal to or greater than the minimum yearly repayment required for income year 2018-19.\n\nInterest received by the private company must be included in the income tax return for 2018-19.\n\nMinimum yearly repayment\n\n$2,152.00\n\nBenchmark interest rate\n\n5.2%\n\nOpening balance:\n\nDate: 30/06/2018\n\nBalance: $7,596.00\n\nDays: 0\n\nInterest: $0\n\nPayments\n\nDate: 01/07/2018\n\nAmount: $7,004.00\n\nBalance: $592.00\n\nDays: 174\n\nInterest: $14.68\n\n\n\n\nDate: 22/12/2018\n\nAmount: $592.00\n\nBalance: $0\n\nDays: 191\n\nInterest: $0\n\n\n\n\nTotal repayments\n\n$7,596.00\n\nTotal interest\n\n$14.68\n\nTotal principal\n\n$7,581.32\n\nClosing balance\n\nDate: 30/06/2019\n\nBalance: $14.68",
  "outputs": {
    "enquiryRateFormatted": "5.2%",
    "enquiryYearEndMinusOneDisplay": "30/06/2018",
    "amalgamatedLoanNotPaidByEOIYFormatted": "$7,596.00",
    "openingBalancePayDays": "0",
    "openingBalanceInterestFormatted": "$0",
    "totalAmountOfRepaymentFormatted": "$7,596.00",
    "totalInterestFormatted": "$14.68",
    "principalFormatted": "$7,581.32",
    "enquiryYearEndDisplay": "30/06/2019",
    "minimumYearRepaymentFormatted": "$2,152.00"
  },
  "repayments": [
    {
      "rd": "1/7/2018",
      "ra": 7004
    },
    {
      "rd": "22/12/2018",
      "ra": 592
    }
  ],
  "inputs": {
    "incomeYearOfLoan": 2017,
    "fullTermOfAmalgamatedLoan": 5,
    "incomeYearOfEnquiring": 2019,
    "amalgamatedLoanNotPaidByEOIY": 7596,
    "repayments": null,
    "lodgement_date": null
  },
  "idx": 818
}