{
  "id": "2023-10-31T18:22:12.393Z0.842159277463926",
  "alert": "Start of result\nResult\n\nMinimum yearly repayment not met.\n\nThe amount of the loan not repaid at the end of income year 2010-11 is $9,930.00.\n\nThe private company may be taken to pay a dividend under Division 7A to the shareholder or shareholder's associate because the amount repaid during income year 2010-11 in relation to the amalgamated loan is less than the minimum yearly repayment required.\n\nInterest received by the private company must be included in the income tax return for 2010-11.\n\nMinimum yearly repayment\n\n$2,448.00\n\nBenchmark interest rate\n\n7.4%\n\nOpening balance:\n\nDate: 30/06/2010\n\nBalance: $9,930.00\n\nDays: 365\n\nInterest: $734.82\n\nTotal repayments\n\n$0\n\nTotal interest\n\n$734.82\n\nTotal principal\n\n$0\n\nClosing balance\n\nDate: 30/06/2011\n\nBalance: $9,930.00",
  "outputs": {
    "enquiryRateFormatted": "7.4%",
    "enquiryYearEndMinusOneDisplay": "30/06/2010",
    "amalgamatedLoanNotPaidByEOIYFormatted": "$9,930.00",
    "openingBalancePayDays": "365",
    "openingBalanceInterestFormatted": "$734.82",
    "totalAmountOfRepaymentFormatted": "$0",
    "totalInterestFormatted": "$734.82",
    "principalFormatted": "$0",
    "enquiryYearEndDisplay": "30/06/2011",
    "minimumYearRepaymentFormatted": "$2,448.00",
    "loanAmountFormatted": "$9,930.00"
  },
  "repayments": [],
  "inputs": {
    "incomeYearOfLoan": 2010,
    "fullTermOfAmalgamatedLoan": 5,
    "incomeYearOfEnquiring": 2011,
    "amalgamatedLoanNotPaidByEOIY": 9930,
    "repayments": null,
    "lodgement_date": "28/12/2010"
  },
  "idx": 3858
}