{
  "id": "2023-10-31T18:40:55.360Z0.12464114818435557",
  "alert": "Start of result\nResult\n\nMinimum yearly repayment not met.\n\nThe amount of the loan not repaid at the end of income year 2012-13 is $5,420.35.\n\nThe private company may be taken to pay a dividend under Division 7A to the shareholder or shareholder's associate because the amount repaid during income year 2012-13 in relation to the amalgamated loan is less than the minimum yearly repayment required.\n\nInterest received by the private company must be included in the income tax return for 2012-13.\n\nMinimum yearly repayment\n\n$4,529.00\n\nBenchmark interest rate\n\n7.05%\n\nOpening balance:\n\nDate: 30/06/2012\n\nBalance: $8,183.00\n\nDays: 295\n\nInterest: $466.26\n\nPayments\n\nDate: 22/04/2013\n\nAmount: $3,295.00\n\nBalance: $4,888.00\n\nDays: 70\n\nInterest: $66.09\n\n\n\n\nTotal repayments\n\n$3,295.00\n\nTotal interest\n\n$532.35\n\nTotal principal\n\n$2,762.65\n\nClosing balance\n\nDate: 30/06/2013\n\nBalance: $5,420.35",
  "outputs": {
    "enquiryRateFormatted": "7.05%",
    "enquiryYearEndMinusOneDisplay": "30/06/2012",
    "amalgamatedLoanNotPaidByEOIYFormatted": "$8,183.00",
    "openingBalancePayDays": "295",
    "openingBalanceInterestFormatted": "$466.26",
    "totalAmountOfRepaymentFormatted": "$3,295.00",
    "totalInterestFormatted": "$532.35",
    "principalFormatted": "$2,762.65",
    "enquiryYearEndDisplay": "30/06/2013",
    "minimumYearRepaymentFormatted": "$4,529.00",
    "loanAmountFormatted": "$5,420.35"
  },
  "repayments": [
    {
      "rd": "22/4/2013",
      "ra": 3295
    }
  ],
  "inputs": {
    "incomeYearOfLoan": 2008,
    "fullTermOfAmalgamatedLoan": 6,
    "incomeYearOfEnquiring": 2013,
    "amalgamatedLoanNotPaidByEOIY": 8183,
    "repayments": null,
    "lodgement_date": null
  },
  "idx": 4378
}