{
  "id": "2023-10-31T17:30:14.348Z0.5113515653455452",
  "alert": "Start of result\nResult\n\nAmalgamated loan fully repaid.\n\nThe amalgamated loan has been paid in full.\u000bThe private company is not taken under Division 7A to pay a dividend to the shareholder or shareholder's associate.\n\nInterest received by the private company must be included in the income tax return for 2017-18.\n\nMinimum yearly repayment\n\n$1.00\n\nBenchmark interest rate\n\n5.3%\n\nOpening balance:\n\nDate: 30/06/2017\n\nBalance: $4.51\n\nDays: 271\n\nInterest: $0.18\n\nPayments\n\nDate: 29/03/2018\n\nAmount: $45.14\n\nBalance: $0\n\nDays: 94\n\nInterest: $0\n\n\n\n\nTotal repayments\n\n$45.14\n\nTotal interest\n\n$0.18\n\nTotal principal\n\n$44.96\n\nClosing balance\n\nDate: 30/06/2018\n\nBalance: $0",
  "outputs": {
    "enquiryRateFormatted": "5.3%",
    "enquiryYearEndMinusOneDisplay": "30/06/2017",
    "amalgamatedLoanNotPaidByEOIYFormatted": "$4.51",
    "openingBalancePayDays": "271",
    "openingBalanceInterestFormatted": "$0.18",
    "totalAmountOfRepaymentFormatted": "$45.14",
    "totalInterestFormatted": "$0.18",
    "principalFormatted": "$44.96",
    "enquiryYearEndDisplay": "30/06/2018",
    "minimumYearRepaymentFormatted": "$1.00",
    "loanAmountFormatted": "$0"
  },
  "repayments": [
    {
      "rd": "29/3/2018",
      "ra": 45.148712230003866
    }
  ],
  "inputs": {
    "incomeYearOfLoan": 2017,
    "fullTermOfAmalgamatedLoan": 6,
    "incomeYearOfEnquiring": 2018,
    "amalgamatedLoanNotPaidByEOIY": 4.51487122300039,
    "repayments": null,
    "lodgement_date": "28/3/2018"
  },
  "idx": 1707
}