{
  "id": "2023-09-06T11:41:27.712Z0.406879580185904",
  "alert": "Start of result\nResult\n\nMinimum yearly repayment not met.\n\nThe amount of the loan not repaid at the end of income year 2011-12 is $52.25.\n\nThe private company may be taken to pay a dividend under Division 7A to the shareholder or shareholder's associate because the amount repaid during income year 2011-12 in relation to the amalgamated loan is less than the minimum yearly repayment required.\n\nInterest received by the private company must be included in the income tax return for 2011-12.\n\nMinimum yearly repayment\n\n$20.00\n\nBenchmark interest rate\n\n7.8%\n\nOpening balance:\n\nDate: 30/06/2011\n\nBalance: $52.25\n\nDays: 366\n\nInterest: $4.08\n\nTotal repayments\n\n$0\n\nTotal interest\n\n$4.08\n\nTotal principal\n\n$0\n\nClosing balance\n\nDate: 30/06/2012\n\nBalance: $52.25",
  "outputs": {
    "enquiryRateFormatted": "7.8%",
    "enquiryYearEndMinusOneDisplay": "30/06/2011",
    "amalgamatedLoanNotPaidByEOIYFormatted": "$52.25",
    "openingBalancePayDays": "366",
    "openingBalanceInterestFormatted": "$4.08",
    "totalAmountOfRepaymentFormatted": "$0",
    "totalInterestFormatted": "$4.08",
    "principalFormatted": "$0",
    "enquiryYearEndDisplay": "30/06/2012",
    "minimumYearRepaymentFormatted": "$20.00"
  },
  "repayments": [],
  "inputs": {
    "incomeYearOfLoan": 2008,
    "fullTermOfAmalgamatedLoan": 6,
    "incomeYearOfEnquiring": 2012,
    "amalgamatedLoanNotPaidByEOIY": 52.259148063174784,
    "repayments": null,
    "lodgement_date": null
  },
  "idx": 5162
}