{
  "id": "2023-10-31T17:57:40.394Z0.6361209861656794",
  "alert": "Start of result\nResult\n\nMinimum yearly repayment not met.\n\nThe amount of the loan not repaid at the end of income year 2017-18 is $11,335.00.\n\nThe private company may be taken to pay a dividend under Division 7A to the shareholder or shareholder's associate because the amount repaid during income year 2017-18 in relation to the amalgamated loan is less than the minimum yearly repayment required.\n\nInterest received by the private company must be included in the income tax return for 2017-18.\n\nMinimum yearly repayment\n\n$6,122.00\n\nBenchmark interest rate\n\n5.3%\n\nOpening balance:\n\nDate: 30/06/2017\n\nBalance: $11,335.00\n\nDays: 365\n\nInterest: $600.76\n\nTotal repayments\n\n$0\n\nTotal interest\n\n$600.76\n\nTotal principal\n\n$0\n\nClosing balance\n\nDate: 30/06/2018\n\nBalance: $11,335.00",
  "outputs": {
    "enquiryRateFormatted": "5.3%",
    "enquiryYearEndMinusOneDisplay": "30/06/2017",
    "amalgamatedLoanNotPaidByEOIYFormatted": "$11,335.00",
    "openingBalancePayDays": "365",
    "openingBalanceInterestFormatted": "$600.76",
    "totalAmountOfRepaymentFormatted": "$0",
    "totalInterestFormatted": "$600.76",
    "principalFormatted": "$0",
    "enquiryYearEndDisplay": "30/06/2018",
    "minimumYearRepaymentFormatted": "$6,122.00",
    "loanAmountFormatted": "$11,335.00"
  },
  "repayments": [],
  "inputs": {
    "incomeYearOfLoan": 2013,
    "fullTermOfAmalgamatedLoan": 6,
    "incomeYearOfEnquiring": 2018,
    "amalgamatedLoanNotPaidByEOIY": 11335,
    "repayments": null,
    "lodgement_date": null
  },
  "idx": 3001
}