{
  "id": "2023-09-06T10:31:52.835Z0.18902670873742933",
  "alert": "Start of result\nResult\n\nMinimum yearly repayment not met.\n\nThe amount of the loan not repaid at the end of income year 2015-16 is $311.51.\n\nThe private company may be taken to pay a dividend under Division 7A to the shareholder or shareholder's associate because the amount repaid during income year 2015-16 in relation to the amalgamated loan is less than the minimum yearly repayment required.\n\nInterest received by the private company must be included in the income tax return for 2015-16.\n\nMinimum yearly repayment\n\n$6,094.00\n\nBenchmark interest rate\n\n5.45%\n\nOpening balance:\n\nDate: 30/06/2015\n\nBalance: $5,779.00\n\nDays: 362\n\nInterest: $311.51\n\nPayments\n\nDate: 27/06/2016\n\nAmount: $5,779.00\n\nBalance: $0\n\nDays: 4\n\nInterest: $0\n\n\n\n\nTotal repayments\n\n$5,779.00\n\nTotal interest\n\n$311.51\n\nTotal principal\n\n$5,467.49\n\nClosing balance\n\nDate: 30/06/2016\n\nBalance: $311.51",
  "outputs": {
    "enquiryRateFormatted": "5.45%",
    "enquiryYearEndMinusOneDisplay": "30/06/2015",
    "amalgamatedLoanNotPaidByEOIYFormatted": "$5,779.00",
    "openingBalancePayDays": "362",
    "openingBalanceInterestFormatted": "$311.51",
    "totalAmountOfRepaymentFormatted": "$5,779.00",
    "totalInterestFormatted": "$311.51",
    "principalFormatted": "$5,467.49",
    "enquiryYearEndDisplay": "30/06/2016",
    "minimumYearRepaymentFormatted": "$6,094.00"
  },
  "repayments": [
    {
      "rd": "27/6/2016",
      "ra": 5779
    }
  ],
  "inputs": {
    "incomeYearOfLoan": 2009,
    "fullTermOfAmalgamatedLoan": 7,
    "incomeYearOfEnquiring": 2016,
    "amalgamatedLoanNotPaidByEOIY": 5779,
    "repayments": null,
    "lodgement_date": null
  },
  "idx": 733
}