{
  "id": "2023-10-31T17:17:21.895Z0.48833044867688824",
  "alert": "Start of result\nResult\n\nMinimum yearly repayment not met.\n\nThe amount of the loan not repaid at the end of income year 2020-21 is $87.55.\n\nThe private company may be taken to pay a dividend under Division 7A to the shareholder or shareholder's associate because the amount repaid during income year 2020-21 in relation to the amalgamated loan is less than the minimum yearly repayment required.\n\nInterest received by the private company must be included in the income tax return for 2020-21.\n\nMinimum yearly repayment\n\n$20.00\n\nBenchmark interest rate\n\n4.52%\n\nOpening balance:\n\nDate: 30/06/2020\n\nBalance: $87.55\n\nDays: 365\n\nInterest: $3.96\n\nTotal repayments\n\n$0\n\nTotal interest\n\n$3.96\n\nTotal principal\n\n$0\n\nClosing balance\n\nDate: 30/06/2021\n\nBalance: $87.55",
  "outputs": {
    "enquiryRateFormatted": "4.52%",
    "enquiryYearEndMinusOneDisplay": "30/06/2020",
    "amalgamatedLoanNotPaidByEOIYFormatted": "$87.55",
    "openingBalancePayDays": "365",
    "openingBalanceInterestFormatted": "$3.96",
    "totalAmountOfRepaymentFormatted": "$0",
    "totalInterestFormatted": "$3.96",
    "principalFormatted": "$0",
    "enquiryYearEndDisplay": "30/06/2021",
    "minimumYearRepaymentFormatted": "$20.00",
    "loanAmountFormatted": "$87.55"
  },
  "repayments": [],
  "inputs": {
    "incomeYearOfLoan": 2020,
    "fullTermOfAmalgamatedLoan": 5,
    "incomeYearOfEnquiring": 2021,
    "amalgamatedLoanNotPaidByEOIY": 87.55246168804905,
    "repayments": null,
    "lodgement_date": "28/12/2020"
  },
  "idx": 900
}