{
  "id": "2023-09-06T19:48:06.179Z0.9015578143557816",
  "alert": "Start of result\nResult\n\nMinimum yearly repayment not met.\n\nThe amount of the loan not repaid at the end of income year 2007-08 is $1.46.\n\nThe private company may be taken to pay a dividend under Division 7A to the shareholder or shareholder's associate because the amount repaid during income year 2007-08 in relation to the amalgamated loan is less than the minimum yearly repayment required.\n\nInterest received by the private company must be included in the income tax return for 2007-08.\n\nMinimum yearly repayment\n\n$90.00\n\nBenchmark interest rate\n\n8.05%\n\nOpening balance:\n\nDate: 30/06/2007\n\nBalance: $83.22\n\nDays: 80\n\nInterest: $1.46\n\nPayments\n\nDate: 19/09/2007\n\nAmount: $83.22\n\nBalance: $0\n\nDays: 286\n\nInterest: $0\n\n\n\n\nTotal repayments\n\n$83.22\n\nTotal interest\n\n$1.46\n\nTotal principal\n\n$81.76\n\nClosing balance\n\nDate: 30/06/2008\n\nBalance: $1.46",
  "outputs": {
    "enquiryRateFormatted": "8.05%",
    "enquiryYearEndMinusOneDisplay": "30/06/2007",
    "amalgamatedLoanNotPaidByEOIYFormatted": "$83.22",
    "openingBalancePayDays": "80",
    "openingBalanceInterestFormatted": "$1.46",
    "totalAmountOfRepaymentFormatted": "$83.22",
    "totalInterestFormatted": "$1.46",
    "principalFormatted": "$81.76",
    "enquiryYearEndDisplay": "30/06/2008",
    "minimumYearRepaymentFormatted": "$90.00"
  },
  "repayments": [
    {
      "rd": "19/9/2007",
      "ra": 83.2275182931554
    }
  ],
  "inputs": {
    "incomeYearOfLoan": 2003,
    "fullTermOfAmalgamatedLoan": 5,
    "incomeYearOfEnquiring": 2008,
    "amalgamatedLoanNotPaidByEOIY": 83.2275182931554,
    "repayments": null,
    "lodgement_date": null
  },
  "idx": 7012
}