{
  "id": "2023-10-31T20:43:19.175Z0.5774193055866323",
  "alert": "Start of result\nResult\n\nMinimum yearly repayment not met.\n\nThe amount of the loan not repaid at the end of income year 2006-07 is $18.51.\n\nThe private company may be taken to pay a dividend under Division 7A to the shareholder or shareholder's associate because the amount repaid during income year 2006-07 in relation to the amalgamated loan is less than the minimum yearly repayment required.\n\nInterest received by the private company must be included in the income tax return for 2006-07.\n\nMinimum yearly repayment\n\n$20.00\n\nBenchmark interest rate\n\n7.55%\n\nOpening balance:\n\nDate: 30/06/2006\n\nBalance: $18.51\n\nDays: 365\n\nInterest: $1.40\n\nTotal repayments\n\n$0\n\nTotal interest\n\n$1.40\n\nTotal principal\n\n$0\n\nClosing balance\n\nDate: 30/06/2007\n\nBalance: $18.51",
  "outputs": {
    "enquiryRateFormatted": "7.55%",
    "enquiryYearEndMinusOneDisplay": "30/06/2006",
    "amalgamatedLoanNotPaidByEOIYFormatted": "$18.51",
    "openingBalancePayDays": "365",
    "openingBalanceInterestFormatted": "$1.40",
    "totalAmountOfRepaymentFormatted": "$0",
    "totalInterestFormatted": "$1.40",
    "principalFormatted": "$0",
    "enquiryYearEndDisplay": "30/06/2007",
    "minimumYearRepaymentFormatted": "$20.00",
    "loanAmountFormatted": "$18.51"
  },
  "repayments": [],
  "inputs": {
    "incomeYearOfLoan": 2000,
    "fullTermOfAmalgamatedLoan": 7,
    "incomeYearOfEnquiring": 2007,
    "amalgamatedLoanNotPaidByEOIY": 18.516431634589395,
    "repayments": null,
    "lodgement_date": null
  },
  "idx": 6712
}