{
  "id": "2023-09-05T16:57:39.324Z0.2489626506139906",
  "alert": "Start of result\nResult\n\nMinimum yearly repayment met.\n\nThe amount of the loan not repaid at the end of income year 2021-22 is $2,282.21.\n\nThe amalgamated loan will not be taken to be a dividend because the total repayments made are equal to or greater than the minimum yearly repayment required for income year 2021-22.\n\nInterest received by the private company must be included in the income tax return for 2021-22.\n\nMinimum yearly repayment\n\n$4,240.00\n\nBenchmark interest rate\n\n4.52%\n\nOpening balance:\n\nDate: 30/06/2021\n\nBalance: $11,652.00\n\nDays: 58\n\nInterest: $83.69\n\nPayments\n\nDate: 28/08/2021\n\nAmount: $9,534.00\n\nBalance: $2,118.00\n\nDays: 307\n\nInterest: $80.52\n\n\n\n\nTotal repayments\n\n$9,534.00\n\nTotal interest\n\n$164.21\n\nTotal principal\n\n$9,369.79\n\nClosing balance\n\nDate: 30/06/2022\n\nBalance: $2,282.21",
  "outputs": {
    "enquiryRateFormatted": "4.52%",
    "enquiryYearEndMinusOneDisplay": "30/06/2021",
    "amalgamatedLoanNotPaidByEOIYFormatted": "$11,652.00",
    "openingBalancePayDays": "58",
    "openingBalanceInterestFormatted": "$83.69",
    "totalAmountOfRepaymentFormatted": "$9,534.00",
    "totalInterestFormatted": "$164.21",
    "principalFormatted": "$9,369.79",
    "enquiryYearEndDisplay": "30/06/2022",
    "minimumYearRepaymentFormatted": "$4,240.00"
  },
  "repayments": [
    {
      "rd": "28/8/2021",
      "ra": 9534
    }
  ],
  "inputs": {
    "incomeYearOfLoan": 2019,
    "fullTermOfAmalgamatedLoan": 5,
    "incomeYearOfEnquiring": 2022,
    "amalgamatedLoanNotPaidByEOIY": 11652,
    "repayments": null,
    "lodgement_date": null
  },
  "idx": 2587
}