{
  "id": "2023-09-04T17:15:47.046Z0.8696621616877691",
  "alert": "Start of result\nResult\n\nMinimum yearly repayment not met.\n\nThe amount of the loan not repaid at the end of income year 2018-19 is $62,057,499.62.\n\nThe private company may be taken to pay a dividend under Division 7A to the shareholder or shareholder's associate because the amount repaid during income year 2018-19 in relation to the amalgamated loan is less than the minimum yearly repayment required.\n\nInterest received by the private company must be included in the income tax return for 2018-19.\n\nMinimum yearly repayment\n\n$33,469,436.00\n\nBenchmark interest rate\n\n5.2%\n\nOpening balance:\n\nDate: 30/06/2018\n\nBalance: $62,057,499.62\n\nDays: 365\n\nInterest: $3,226,989.98\n\nTotal repayments\n\n$0\n\nTotal interest\n\n$3,226,989.98\n\nTotal principal\n\n$0\n\nClosing balance\n\nDate: 30/06/2019\n\nBalance: $62,057,499.62",
  "outputs": {
    "enquiryRateFormatted": "5.2%",
    "enquiryYearEndMinusOneDisplay": "30/06/2018",
    "amalgamatedLoanNotPaidByEOIYFormatted": "$62,057,499.62",
    "openingBalancePayDays": "365",
    "openingBalanceInterestFormatted": "$3,226,989.98",
    "totalAmountOfRepaymentFormatted": "$0",
    "totalInterestFormatted": "$3,226,989.98",
    "principalFormatted": "$0",
    "enquiryYearEndDisplay": "30/06/2019",
    "minimumYearRepaymentFormatted": "$33,469,436.00"
  },
  "repayments": [],
  "inputs": {
    "incomeYearOfLoan": 2014,
    "fullTermOfAmalgamatedLoan": 6,
    "incomeYearOfEnquiring": 2019,
    "amalgamatedLoanNotPaidByEOIY": 62057499.62028309,
    "repayments": null,
    "lodgement_date": null
  },
  "idx": 1915
}