{
  "id": "2023-09-05T16:40:58.047Z0.21048730278027716",
  "alert": "Start of result\nResult\n\nMinimum yearly repayment not met.\n\nThe amount of the loan not repaid at the end of income year 2022-23 is $2,033.62.\n\nThe private company may be taken to pay a dividend under Division 7A to the shareholder or shareholder's associate because the amount repaid during income year 2022-23 in relation to the amalgamated loan is less than the minimum yearly repayment required.\n\nInterest received by the private company must be included in the income tax return for 2022-23.\n\nMinimum yearly repayment\n\n$8,909.00\n\nBenchmark interest rate\n\n4.77%\n\nOpening balance:\n\nDate: 30/06/2022\n\nBalance: $8,503.00\n\nDays: 355\n\nInterest: $394.48\n\nPayments\n\nDate: 21/06/2023\n\nAmount: $6,866.00\n\nBalance: $1,637.00\n\nDays: 10\n\nInterest: $2.14\n\n\n\n\nTotal repayments\n\n$6,866.00\n\nTotal interest\n\n$396.62\n\nTotal principal\n\n$6,469.38\n\nClosing balance\n\nDate: 30/06/2023\n\nBalance: $2,033.62",
  "outputs": {
    "enquiryRateFormatted": "4.77%",
    "enquiryYearEndMinusOneDisplay": "30/06/2022",
    "amalgamatedLoanNotPaidByEOIYFormatted": "$8,503.00",
    "openingBalancePayDays": "355",
    "openingBalanceInterestFormatted": "$394.48",
    "totalAmountOfRepaymentFormatted": "$6,866.00",
    "totalInterestFormatted": "$396.62",
    "principalFormatted": "$6,469.38",
    "enquiryYearEndDisplay": "30/06/2023",
    "minimumYearRepaymentFormatted": "$8,909.00"
  },
  "repayments": [
    {
      "rd": "21/6/2023",
      "ra": 6866
    }
  ],
  "inputs": {
    "incomeYearOfLoan": 2019,
    "fullTermOfAmalgamatedLoan": 4,
    "incomeYearOfEnquiring": 2023,
    "amalgamatedLoanNotPaidByEOIY": 8503,
    "repayments": null,
    "lodgement_date": null
  },
  "idx": 1476
}