{
  "id": "2023-09-04T21:13:03.046Z0.45305411364130554",
  "alert": "Start of result\nResult\n\nMinimum yearly repayment not met.\n\nThe amount of the loan not repaid at the end of income year 2008-09 is $1,240,499.50.\n\nThe private company may be taken to pay a dividend under Division 7A to the shareholder or shareholder's associate because the amount repaid during income year 2008-09 in relation to the amalgamated loan is less than the minimum yearly repayment required.\n\nInterest received by the private company must be included in the income tax return for 2008-09.\n\nMinimum yearly repayment\n\n$320,124.00\n\nBenchmark interest rate\n\n9.45%\n\nOpening balance:\n\nDate: 30/06/2008\n\nBalance: $1,240,499.50\n\nDays: 0\n\nInterest: $0\n\nPayments\n\nDate: 01/07/2008\n\nAmount: $3,138.00\n\nBalance: $1,237,361.50\n\nDays: 165\n\nInterest: $52,859.07\n\n\n\n\nDate: 13/12/2008\n\nAmount: $6,595.00\n\nBalance: $1,230,766.50\n\nDays: 200\n\nInterest: $63,730.10\n\n\n\n\nTotal repayments\n\n$9,733.00\n\nTotal interest\n\n$116,589.17\n\nTotal principal\n\n$0\n\nClosing balance\n\nDate: 30/06/2009\n\nBalance: $1,240,499.50",
  "outputs": {
    "enquiryRateFormatted": "9.45%",
    "enquiryYearEndMinusOneDisplay": "30/06/2008",
    "amalgamatedLoanNotPaidByEOIYFormatted": "$1,240,499.50",
    "openingBalancePayDays": "0",
    "openingBalanceInterestFormatted": "$0",
    "totalAmountOfRepaymentFormatted": "$9,733.00",
    "totalInterestFormatted": "$116,589.17",
    "principalFormatted": "$0",
    "enquiryYearEndDisplay": "30/06/2009",
    "minimumYearRepaymentFormatted": "$320,124.00"
  },
  "repayments": [
    {
      "rd": "1/7/2008",
      "ra": 3138
    },
    {
      "rd": "13/12/2008",
      "ra": 6595
    }
  ],
  "inputs": {
    "incomeYearOfLoan": 2008,
    "fullTermOfAmalgamatedLoan": 5,
    "incomeYearOfEnquiring": 2009,
    "amalgamatedLoanNotPaidByEOIY": 1240499.5048223303,
    "repayments": null,
    "lodgement_date": "17/1/2009"
  },
  "idx": 859
}