{
  "id": "2023-10-31T21:20:58.801Z0.845731839842714",
  "alert": "Start of result\nResult\n\nMinimum yearly repayment not met.\n\nThe amount of the loan not repaid at the end of income year 2001-02 is $78.72.\n\nThe private company may be taken to pay a dividend under Division 7A to the shareholder or shareholder's associate because the amount repaid during income year 2001-02 in relation to the amalgamated loan is less than the minimum yearly repayment required.\n\nInterest received by the private company must be included in the income tax return for 2001-02.\n\nMinimum yearly repayment\n\n$84.00\n\nBenchmark interest rate\n\n6.8%\n\nOpening balance:\n\nDate: 30/06/2001\n\nBalance: $78.72\n\nDays: 365\n\nInterest: $5.35\n\nTotal repayments\n\n$0\n\nTotal interest\n\n$5.35\n\nTotal principal\n\n$0\n\nClosing balance\n\nDate: 30/06/2002\n\nBalance: $78.72",
  "outputs": {
    "enquiryRateFormatted": "6.8%",
    "enquiryYearEndMinusOneDisplay": "30/06/2001",
    "amalgamatedLoanNotPaidByEOIYFormatted": "$78.72",
    "openingBalancePayDays": "365",
    "openingBalanceInterestFormatted": "$5.35",
    "totalAmountOfRepaymentFormatted": "$0",
    "totalInterestFormatted": "$5.35",
    "principalFormatted": "$0",
    "enquiryYearEndDisplay": "30/06/2002",
    "minimumYearRepaymentFormatted": "$84.00",
    "loanAmountFormatted": "$78.72"
  },
  "repayments": [],
  "inputs": {
    "incomeYearOfLoan": 1998,
    "fullTermOfAmalgamatedLoan": 4,
    "incomeYearOfEnquiring": 2002,
    "amalgamatedLoanNotPaidByEOIY": 78.7220067668578,
    "repayments": null,
    "lodgement_date": null
  },
  "idx": 7205
}