{
  "id": "2023-09-06T21:45:38.999Z0.4004220161034979",
  "alert": "Start of result\nResult\n\nMinimum yearly repayment met.\n\nThe amount of the loan not repaid at the end of income year 2003-04 is $6,705.93.\n\nThe amalgamated loan will not be taken to be a dividend because the total repayments made are equal to or greater than the minimum yearly repayment required for income year 2003-04.\n\nInterest received by the private company must be included in the income tax return for 2003-04.\n\nMinimum yearly repayment\n\n$2,018.00\n\nBenchmark interest rate\n\n6.55%\n\nOpening balance:\n\nDate: 30/06/2003\n\nBalance: $9,753.00\n\nDays: 96\n\nInterest: $167.56\n\nPayments\n\nDate: 05/10/2003\n\nAmount: $3,516.00\n\nBalance: $6,237.00\n\nDays: 270\n\nInterest: $301.37\n\n\n\n\nTotal repayments\n\n$3,516.00\n\nTotal interest\n\n$468.93\n\nTotal principal\n\n$3,047.07\n\nClosing balance\n\nDate: 30/06/2004\n\nBalance: $6,705.93",
  "outputs": {
    "enquiryRateFormatted": "6.55%",
    "enquiryYearEndMinusOneDisplay": "30/06/2003",
    "amalgamatedLoanNotPaidByEOIYFormatted": "$9,753.00",
    "openingBalancePayDays": "96",
    "openingBalanceInterestFormatted": "$167.56",
    "totalAmountOfRepaymentFormatted": "$3,516.00",
    "totalInterestFormatted": "$468.93",
    "principalFormatted": "$3,047.07",
    "enquiryYearEndDisplay": "30/06/2004",
    "minimumYearRepaymentFormatted": "$2,018.00"
  },
  "repayments": [
    {
      "rd": "5/10/2003",
      "ra": 3516
    }
  ],
  "inputs": {
    "incomeYearOfLoan": 2002,
    "fullTermOfAmalgamatedLoan": 7,
    "incomeYearOfEnquiring": 2004,
    "amalgamatedLoanNotPaidByEOIY": 9753,
    "repayments": null,
    "lodgement_date": null
  },
  "idx": 6663
}