{
  "id": "2023-09-06T05:04:48.529Z0.8742045826789258",
  "alert": "Start of result\nResult\n\nMinimum yearly repayment not met.\n\nThe amount of the loan not repaid at the end of income year 2016-17 is $3.59.\n\nThe private company may be taken to pay a dividend under Division 7A to the shareholder or shareholder's associate because the amount repaid during income year 2016-17 in relation to the amalgamated loan is less than the minimum yearly repayment required.\n\nInterest received by the private company must be included in the income tax return for 2016-17.\n\nMinimum yearly repayment\n\n$111.00\n\nBenchmark interest rate\n\n5.4%\n\nOpening balance:\n\nDate: 30/06/2016\n\nBalance: $105.12\n\nDays: 231\n\nInterest: $3.59\n\nPayments\n\nDate: 17/02/2017\n\nAmount: $105.12\n\nBalance: $0\n\nDays: 134\n\nInterest: $0\n\n\n\n\nTotal repayments\n\n$105.12\n\nTotal interest\n\n$3.59\n\nTotal principal\n\n$101.53\n\nClosing balance\n\nDate: 30/06/2017\n\nBalance: $3.59",
  "outputs": {
    "enquiryRateFormatted": "5.4%",
    "enquiryYearEndMinusOneDisplay": "30/06/2016",
    "amalgamatedLoanNotPaidByEOIYFormatted": "$105.12",
    "openingBalancePayDays": "231",
    "openingBalanceInterestFormatted": "$3.59",
    "totalAmountOfRepaymentFormatted": "$105.12",
    "totalInterestFormatted": "$3.59",
    "principalFormatted": "$101.53",
    "enquiryYearEndDisplay": "30/06/2017",
    "minimumYearRepaymentFormatted": "$111.00"
  },
  "repayments": [
    {
      "rd": "17/2/2017",
      "ra": 105.12164630332245
    }
  ],
  "inputs": {
    "incomeYearOfLoan": 2012,
    "fullTermOfAmalgamatedLoan": 5,
    "incomeYearOfEnquiring": 2017,
    "amalgamatedLoanNotPaidByEOIY": 105.12164630332207,
    "repayments": null,
    "lodgement_date": null
  },
  "idx": 733
}