{
  "id": "2023-10-31T17:51:59.051Z0.24661732809415327",
  "alert": "Start of result\nResult\n\nAmalgamated loan fully repaid.\n\nThe amalgamated loan has been paid in full.\u000bThe private company is not taken under Division 7A to pay a dividend to the shareholder or shareholder's associate.\n\nInterest received by the private company must be included in the income tax return for 2018-19.\n\nMinimum yearly repayment\n\n$177.00\n\nBenchmark interest rate\n\n5.2%\n\nOpening balance:\n\nDate: 30/06/2018\n\nBalance: $479.00\n\nDays: 272\n\nInterest: $18.56\n\nPayments\n\nDate: 30/03/2019\n\nAmount: $515.00\n\nBalance: $0\n\nDays: 93\n\nInterest: $0\n\n\n\n\nTotal repayments\n\n$515.00\n\nTotal interest\n\n$18.56\n\nTotal principal\n\n$496.44\n\nClosing balance\n\nDate: 30/06/2019\n\nBalance: $0",
  "outputs": {
    "enquiryRateFormatted": "5.2%",
    "enquiryYearEndMinusOneDisplay": "30/06/2018",
    "amalgamatedLoanNotPaidByEOIYFormatted": "$479.00",
    "openingBalancePayDays": "272",
    "openingBalanceInterestFormatted": "$18.56",
    "totalAmountOfRepaymentFormatted": "$515.00",
    "totalInterestFormatted": "$18.56",
    "principalFormatted": "$496.44",
    "enquiryYearEndDisplay": "30/06/2019",
    "minimumYearRepaymentFormatted": "$177.00",
    "loanAmountFormatted": "$0"
  },
  "repayments": [
    {
      "rd": "30/3/2019",
      "ra": 515
    }
  ],
  "inputs": {
    "incomeYearOfLoan": 2014,
    "fullTermOfAmalgamatedLoan": 7,
    "incomeYearOfEnquiring": 2019,
    "amalgamatedLoanNotPaidByEOIY": 479,
    "repayments": null,
    "lodgement_date": null
  },
  "idx": 2770
}