{
  "id": "2023-10-31T17:22:23.826Z0.20952100159242426",
  "alert": "Start of result\nResult\n\nAmalgamated loan fully repaid.\n\nThe amalgamated loan has been paid in full.\u000bThe private company is not taken under Division 7A to pay a dividend to the shareholder or shareholder's associate.\n\nInterest received by the private company must be included in the income tax return for 2019-20.\n\nMinimum yearly repayment\n\n$11.00\n\nBenchmark interest rate\n\n5.37%\n\nOpening balance:\n\nDate: 30/06/2019\n\nBalance: $61.77\n\nDays: 188\n\nInterest: $1.70\n\nPayments\n\nDate: 05/01/2020\n\nAmount: $617.73\n\nBalance: $0\n\nDays: 178\n\nInterest: $0\n\n\n\n\nTotal repayments\n\n$617.73\n\nTotal interest\n\n$1.70\n\nTotal principal\n\n$616.03\n\nClosing balance\n\nDate: 30/06/2020\n\nBalance: $0",
  "outputs": {
    "enquiryRateFormatted": "5.37%",
    "enquiryYearEndMinusOneDisplay": "30/06/2019",
    "amalgamatedLoanNotPaidByEOIYFormatted": "$61.77",
    "openingBalancePayDays": "188",
    "openingBalanceInterestFormatted": "$1.70",
    "totalAmountOfRepaymentFormatted": "$617.73",
    "totalInterestFormatted": "$1.70",
    "principalFormatted": "$616.03",
    "enquiryYearEndDisplay": "30/06/2020",
    "minimumYearRepaymentFormatted": "$11.00",
    "loanAmountFormatted": "$0"
  },
  "repayments": [
    {
      "rd": "5/1/2020",
      "ra": 617.7363245538336
    }
  ],
  "inputs": {
    "incomeYearOfLoan": 2019,
    "fullTermOfAmalgamatedLoan": 7,
    "incomeYearOfEnquiring": 2020,
    "amalgamatedLoanNotPaidByEOIY": 61.77363245538333,
    "repayments": null,
    "lodgement_date": "30/8/2019"
  },
  "idx": 1246
}