{
  "id": "2023-10-31T21:24:15.269Z0.26346028312873215",
  "alert": "Start of result\nResult\n\nAmalgamated loan fully repaid.\n\nThe amalgamated loan has been paid in full.\u000bThe private company is not taken under Division 7A to pay a dividend to the shareholder or shareholder's associate.\n\nInterest received by the private company must be included in the income tax return for 2000-01.\n\nMinimum yearly repayment\n\n$708.00\n\nBenchmark interest rate\n\n7.8%\n\nOpening balance:\n\nDate: 30/06/2000\n\nBalance: $1,830.00\n\nDays: 28\n\nInterest: $10.95\n\nPayments\n\nDate: 29/07/2000\n\nAmount: $4,447.00\n\nBalance: $0\n\nDays: 337\n\nInterest: $0\n\n\n\n\nTotal repayments\n\n$4,447.00\n\nTotal interest\n\n$10.95\n\nTotal principal\n\n$4,436.05\n\nClosing balance\n\nDate: 30/06/2001\n\nBalance: $0",
  "outputs": {
    "enquiryRateFormatted": "7.8%",
    "enquiryYearEndMinusOneDisplay": "30/06/2000",
    "amalgamatedLoanNotPaidByEOIYFormatted": "$1,830.00",
    "openingBalancePayDays": "28",
    "openingBalanceInterestFormatted": "$10.95",
    "totalAmountOfRepaymentFormatted": "$4,447.00",
    "totalInterestFormatted": "$10.95",
    "principalFormatted": "$4,436.05",
    "enquiryYearEndDisplay": "30/06/2001",
    "minimumYearRepaymentFormatted": "$708.00",
    "loanAmountFormatted": "$0"
  },
  "repayments": [
    {
      "rd": "29/7/2000",
      "ra": 4447
    }
  ],
  "inputs": {
    "incomeYearOfLoan": 1998,
    "fullTermOfAmalgamatedLoan": 5,
    "incomeYearOfEnquiring": 2001,
    "amalgamatedLoanNotPaidByEOIY": 1830,
    "repayments": null,
    "lodgement_date": null
  },
  "idx": 7246
}