{
  "id": "2023-09-07T00:41:34.794Z0.26345816402301603",
  "alert": "Start of result\nResult\n\nMinimum yearly repayment not met.\n\nThe amount of the loan not repaid at the end of income year 2000-01 is $9.77.\n\nThe private company may be taken to pay a dividend under Division 7A to the shareholder or shareholder's associate because the amount repaid during income year 2000-01 in relation to the amalgamated loan is less than the minimum yearly repayment required.\n\nInterest received by the private company must be included in the income tax return for 2000-01.\n\nMinimum yearly repayment\n\n$2.00\n\nBenchmark interest rate\n\n7.8%\n\nOpening balance:\n\nDate: 30/06/2000\n\nBalance: $9.77\n\nDays: 365\n\nInterest: $0.76\n\nTotal repayments\n\n$0\n\nTotal interest\n\n$0.76\n\nTotal principal\n\n$0\n\nClosing balance\n\nDate: 30/06/2001\n\nBalance: $9.77",
  "outputs": {
    "enquiryRateFormatted": "7.8%",
    "enquiryYearEndMinusOneDisplay": "30/06/2000",
    "amalgamatedLoanNotPaidByEOIYFormatted": "$9.77",
    "openingBalancePayDays": "365",
    "openingBalanceInterestFormatted": "$0.76",
    "totalAmountOfRepaymentFormatted": "$0",
    "totalInterestFormatted": "$0.76",
    "principalFormatted": "$0",
    "enquiryYearEndDisplay": "30/06/2001",
    "minimumYearRepaymentFormatted": "$2.00"
  },
  "repayments": [],
  "inputs": {
    "incomeYearOfLoan": 2000,
    "fullTermOfAmalgamatedLoan": 6,
    "incomeYearOfEnquiring": 2001,
    "amalgamatedLoanNotPaidByEOIY": 9.779555653231451,
    "repayments": null,
    "lodgement_date": "20/5/2001"
  },
  "idx": 7713
}