{
  "id": "2023-09-05T01:34:02.751Z0.43008209503021466",
  "alert": "Start of result\nResult\n\nMinimum yearly repayment not met.\n\nThe amount of the loan not repaid at the end of income year 2000-01 is $9,201.00.\n\nThe private company may be taken to pay a dividend under Division 7A to the shareholder or shareholder's associate because the amount repaid during income year 2000-01 in relation to the amalgamated loan is less than the minimum yearly repayment required.\n\nInterest received by the private company must be included in the income tax return for 2000-01.\n\nMinimum yearly repayment\n\n$5,145.00\n\nBenchmark interest rate\n\n7.8%\n\nOpening balance:\n\nDate: 30/06/2000\n\nBalance: $9,201.00\n\nDays: 365\n\nInterest: $717.68\n\nTotal repayments\n\n$0\n\nTotal interest\n\n$717.68\n\nTotal principal\n\n$0\n\nClosing balance\n\nDate: 30/06/2001\n\nBalance: $9,201.00",
  "outputs": {
    "enquiryRateFormatted": "7.8%",
    "enquiryYearEndMinusOneDisplay": "30/06/2000",
    "amalgamatedLoanNotPaidByEOIYFormatted": "$9,201.00",
    "openingBalancePayDays": "365",
    "openingBalanceInterestFormatted": "$717.68",
    "totalAmountOfRepaymentFormatted": "$0",
    "totalInterestFormatted": "$717.68",
    "principalFormatted": "$0",
    "enquiryYearEndDisplay": "30/06/2001",
    "minimumYearRepaymentFormatted": "$5,145.00"
  },
  "repayments": [],
  "inputs": {
    "incomeYearOfLoan": 1998,
    "fullTermOfAmalgamatedLoan": 4,
    "incomeYearOfEnquiring": 2001,
    "amalgamatedLoanNotPaidByEOIY": 9201,
    "repayments": null,
    "lodgement_date": null
  },
  "idx": 2573
}