{
  "id": "2023-10-31T20:05:55.364Z0.8024914449758834",
  "alert": "Start of result\nResult\n\nAmalgamated loan fully repaid.\n\nThe amalgamated loan has been paid in full.\u000bThe private company is not taken under Division 7A to pay a dividend to the shareholder or shareholder's associate.\n\nInterest received by the private company must be included in the income tax return for 2007-08.\n\nMinimum yearly repayment\n\n$53.00\n\nBenchmark interest rate\n\n8.05%\n\nOpening balance:\n\nDate: 30/06/2007\n\nBalance: $95.21\n\nDays: 110\n\nInterest: $2.30\n\nPayments\n\nDate: 19/10/2007\n\nAmount: $952.15\n\nBalance: $0\n\nDays: 256\n\nInterest: $0\n\n\n\n\nTotal repayments\n\n$952.15\n\nTotal interest\n\n$2.30\n\nTotal principal\n\n$949.85\n\nClosing balance\n\nDate: 30/06/2008\n\nBalance: $0",
  "outputs": {
    "enquiryRateFormatted": "8.05%",
    "enquiryYearEndMinusOneDisplay": "30/06/2007",
    "amalgamatedLoanNotPaidByEOIYFormatted": "$95.21",
    "openingBalancePayDays": "110",
    "openingBalanceInterestFormatted": "$2.30",
    "totalAmountOfRepaymentFormatted": "$952.15",
    "totalInterestFormatted": "$2.30",
    "principalFormatted": "$949.85",
    "enquiryYearEndDisplay": "30/06/2008",
    "minimumYearRepaymentFormatted": "$53.00",
    "loanAmountFormatted": "$0"
  },
  "repayments": [
    {
      "rd": "19/10/2007",
      "ra": 952.155526305894
    }
  ],
  "inputs": {
    "incomeYearOfLoan": 2002,
    "fullTermOfAmalgamatedLoan": 7,
    "incomeYearOfEnquiring": 2008,
    "amalgamatedLoanNotPaidByEOIY": 95.2155526305894,
    "repayments": null,
    "lodgement_date": null
  },
  "idx": 6165
}