{
  "id": "2023-09-04T17:43:29.831Z0.6228237549096107",
  "alert": "Start of result\nResult\n\nMinimum yearly repayment not met.\n\nThe amount of the loan not repaid at the end of income year 2016-17 is $7,949.27.\n\nThe private company may be taken to pay a dividend under Division 7A to the shareholder or shareholder's associate because the amount repaid during income year 2016-17 in relation to the amalgamated loan is less than the minimum yearly repayment required.\n\nInterest received by the private company must be included in the income tax return for 2016-17.\n\nMinimum yearly repayment\n\n$5,918.00\n\nBenchmark interest rate\n\n5.4%\n\nOpening balance:\n\nDate: 30/06/2016\n\nBalance: $10,942.00\n\nDays: 0\n\nInterest: $0\n\nPayments\n\nDate: 01/07/2016\n\nAmount: $3,400.00\n\nBalance: $7,542.00\n\nDays: 365\n\nInterest: $407.27\n\n\n\n\nTotal repayments\n\n$3,400.00\n\nTotal interest\n\n$407.27\n\nTotal principal\n\n$2,992.73\n\nClosing balance\n\nDate: 30/06/2017\n\nBalance: $7,949.27",
  "outputs": {
    "enquiryRateFormatted": "5.4%",
    "enquiryYearEndMinusOneDisplay": "30/06/2016",
    "amalgamatedLoanNotPaidByEOIYFormatted": "$10,942.00",
    "openingBalancePayDays": "0",
    "openingBalanceInterestFormatted": "$0",
    "totalAmountOfRepaymentFormatted": "$3,400.00",
    "totalInterestFormatted": "$407.27",
    "principalFormatted": "$2,992.73",
    "enquiryYearEndDisplay": "30/06/2017",
    "minimumYearRepaymentFormatted": "$5,918.00"
  },
  "repayments": [
    {
      "rd": "1/7/2016",
      "ra": 3400
    }
  ],
  "inputs": {
    "incomeYearOfLoan": 2012,
    "fullTermOfAmalgamatedLoan": 6,
    "incomeYearOfEnquiring": 2017,
    "amalgamatedLoanNotPaidByEOIY": 10942,
    "repayments": null,
    "lodgement_date": null
  },
  "idx": 2511
}