{
  "id": "2023-10-31T17:51:11.130Z0.9541683605356359",
  "alert": "Start of result\nResult\n\nMinimum yearly repayment not met.\n\nThe amount of the loan not repaid at the end of income year 2014-15 is $35.91.\n\nThe private company may be taken to pay a dividend under Division 7A to the shareholder or shareholder's associate because the amount repaid during income year 2014-15 in relation to the amalgamated loan is less than the minimum yearly repayment required.\n\nInterest received by the private company must be included in the income tax return for 2014-15.\n\nMinimum yearly repayment\n\n$7.00\n\nBenchmark interest rate\n\n5.95%\n\nOpening balance:\n\nDate: 30/06/2014\n\nBalance: $35.91\n\nDays: 365\n\nInterest: $2.14\n\nTotal repayments\n\n$0\n\nTotal interest\n\n$2.14\n\nTotal principal\n\n$0\n\nClosing balance\n\nDate: 30/06/2015\n\nBalance: $35.91",
  "outputs": {
    "enquiryRateFormatted": "5.95%",
    "enquiryYearEndMinusOneDisplay": "30/06/2014",
    "amalgamatedLoanNotPaidByEOIYFormatted": "$35.91",
    "openingBalancePayDays": "365",
    "openingBalanceInterestFormatted": "$2.14",
    "totalAmountOfRepaymentFormatted": "$0",
    "totalInterestFormatted": "$2.14",
    "principalFormatted": "$0",
    "enquiryYearEndDisplay": "30/06/2015",
    "minimumYearRepaymentFormatted": "$7.00",
    "loanAmountFormatted": "$35.91"
  },
  "repayments": [],
  "inputs": {
    "incomeYearOfLoan": 2014,
    "fullTermOfAmalgamatedLoan": 6,
    "incomeYearOfEnquiring": 2015,
    "amalgamatedLoanNotPaidByEOIY": 35.916357742055304,
    "repayments": null,
    "lodgement_date": "31/7/2014"
  },
  "idx": 2737
}