{
  "id": "2023-09-07T02:17:53.424Z0.5362323898373635",
  "alert": "Start of result\nResult\n\nMinimum yearly repayment met.\n\nThe amount of the loan not repaid at the end of income year 2002-03 is $1.48.\n\nThe amalgamated loan will not be taken to be a dividend because the total repayments made are equal to or greater than the minimum yearly repayment required for income year 2002-03.\n\nInterest received by the private company must be included in the income tax return for 2002-03.\n\nMinimum yearly repayment\n\n$16.00\n\nBenchmark interest rate\n\n6.3%\n\nOpening balance:\n\nDate: 30/06/2002\n\nBalance: $42.75\n\nDays: 200\n\nInterest: $1.48\n\nPayments\n\nDate: 17/01/2003\n\nAmount: $42.75\n\nBalance: $0\n\nDays: 165\n\nInterest: $0\n\n\n\n\nTotal repayments\n\n$42.75\n\nTotal interest\n\n$1.48\n\nTotal principal\n\n$41.27\n\nClosing balance\n\nDate: 30/06/2003\n\nBalance: $1.48",
  "outputs": {
    "enquiryRateFormatted": "6.3%",
    "enquiryYearEndMinusOneDisplay": "30/06/2002",
    "amalgamatedLoanNotPaidByEOIYFormatted": "$42.75",
    "openingBalancePayDays": "200",
    "openingBalanceInterestFormatted": "$1.48",
    "totalAmountOfRepaymentFormatted": "$42.75",
    "totalInterestFormatted": "$1.48",
    "principalFormatted": "$41.27",
    "enquiryYearEndDisplay": "30/06/2003",
    "minimumYearRepaymentFormatted": "$16.00"
  },
  "repayments": [
    {
      "rd": "17/1/2003",
      "ra": 42.754020804893116
    }
  ],
  "inputs": {
    "incomeYearOfLoan": 1999,
    "fullTermOfAmalgamatedLoan": 6,
    "incomeYearOfEnquiring": 2003,
    "amalgamatedLoanNotPaidByEOIY": 42.754020804893074,
    "repayments": null,
    "lodgement_date": null
  },
  "idx": 4429
}