{
  "id": "2023-09-06T01:22:18.514Z0.763641953244891",
  "alert": "Start of result\nResult\n\nMinimum yearly repayment not met.\n\nThe amount of the loan not repaid at the end of income year 2018-19 is $3,760.77.\n\nThe private company may be taken to pay a dividend under Division 7A to the shareholder or shareholder's associate because the amount repaid during income year 2018-19 in relation to the amalgamated loan is less than the minimum yearly repayment required.\n\nInterest received by the private company must be included in the income tax return for 2018-19.\n\nMinimum yearly repayment\n\n$7,699.00\n\nBenchmark interest rate\n\n5.2%\n\nOpening balance:\n\nDate: 30/06/2018\n\nBalance: $7,318.00\n\nDays: 231\n\nInterest: $240.83\n\nPayments\n\nDate: 17/02/2019\n\nAmount: $3,864.00\n\nBalance: $3,454.00\n\nDays: 134\n\nInterest: $65.94\n\n\n\n\nTotal repayments\n\n$3,864.00\n\nTotal interest\n\n$306.77\n\nTotal principal\n\n$3,557.23\n\nClosing balance\n\nDate: 30/06/2019\n\nBalance: $3,760.77",
  "outputs": {
    "enquiryRateFormatted": "5.2%",
    "enquiryYearEndMinusOneDisplay": "30/06/2018",
    "amalgamatedLoanNotPaidByEOIYFormatted": "$7,318.00",
    "openingBalancePayDays": "231",
    "openingBalanceInterestFormatted": "$240.83",
    "totalAmountOfRepaymentFormatted": "$3,864.00",
    "totalInterestFormatted": "$306.77",
    "principalFormatted": "$3,557.23",
    "enquiryYearEndDisplay": "30/06/2019",
    "minimumYearRepaymentFormatted": "$7,699.00"
  },
  "repayments": [
    {
      "rd": "17/2/2019",
      "ra": 3864
    }
  ],
  "inputs": {
    "incomeYearOfLoan": 2014,
    "fullTermOfAmalgamatedLoan": 5,
    "incomeYearOfEnquiring": 2019,
    "amalgamatedLoanNotPaidByEOIY": 7318,
    "repayments": null,
    "lodgement_date": null
  },
  "idx": 6275
}