{
  "id": "2023-10-31T18:04:54.320Z0.06846820294586498",
  "alert": "Start of result\nResult\n\nAmalgamated loan fully repaid.\n\nThe amalgamated loan has been paid in full.\u000bThe private company is not taken under Division 7A to pay a dividend to the shareholder or shareholder's associate.\n\nInterest received by the private company must be included in the income tax return for 2015-16.\n\nMinimum yearly repayment\n\n$3,746.00\n\nBenchmark interest rate\n\n5.45%\n\nOpening balance:\n\nDate: 30/06/2015\n\nBalance: $10,115.00\n\nDays: 63\n\nInterest: $94.89\n\nPayments\n\nDate: 02/09/2015\n\nAmount: $9,796.00\n\nBalance: $319.00\n\nDays: 33\n\nInterest: $1.57\n\n\n\n\nDate: 05/10/2015\n\nAmount: $2,959.00\n\nBalance: $0\n\nDays: 270\n\nInterest: $0\n\n\n\n\nTotal repayments\n\n$12,755.00\n\nTotal interest\n\n$96.46\n\nTotal principal\n\n$12,658.54\n\nClosing balance\n\nDate: 30/06/2016\n\nBalance: $0",
  "outputs": {
    "enquiryRateFormatted": "5.45%",
    "enquiryYearEndMinusOneDisplay": "30/06/2015",
    "amalgamatedLoanNotPaidByEOIYFormatted": "$10,115.00",
    "openingBalancePayDays": "63",
    "openingBalanceInterestFormatted": "$94.89",
    "totalAmountOfRepaymentFormatted": "$12,755.00",
    "totalInterestFormatted": "$96.46",
    "principalFormatted": "$12,658.54",
    "enquiryYearEndDisplay": "30/06/2016",
    "minimumYearRepaymentFormatted": "$3,746.00",
    "loanAmountFormatted": "$0"
  },
  "repayments": [
    {
      "rd": "2/9/2015",
      "ra": 9796
    },
    {
      "rd": "5/10/2015",
      "ra": 2959
    }
  ],
  "inputs": {
    "incomeYearOfLoan": 2012,
    "fullTermOfAmalgamatedLoan": 6,
    "incomeYearOfEnquiring": 2016,
    "amalgamatedLoanNotPaidByEOIY": 10115,
    "repayments": null,
    "lodgement_date": null
  },
  "idx": 3270
}