{
  "id": "2023-09-04T16:36:58.874Z0.520169463933462",
  "alert": "Start of result\nResult\n\nMinimum yearly repayment not met.\n\nThe amount of the loan not repaid at the end of income year 2022-23 is $66,088,466.26.\n\nThe private company may be taken to pay a dividend under Division 7A to the shareholder or shareholder's associate because the amount repaid during income year 2022-23 in relation to the amalgamated loan is less than the minimum yearly repayment required.\n\nInterest received by the private company must be included in the income tax return for 2022-23.\n\nMinimum yearly repayment\n\n$35,426,906.00\n\nBenchmark interest rate\n\n4.77%\n\nOpening balance:\n\nDate: 30/06/2022\n\nBalance: $66,088,466.26\n\nDays: 365\n\nInterest: $3,152,419.84\n\nTotal repayments\n\n$0\n\nTotal interest\n\n$3,152,419.84\n\nTotal principal\n\n$0\n\nClosing balance\n\nDate: 30/06/2023\n\nBalance: $66,088,466.26",
  "outputs": {
    "enquiryRateFormatted": "4.77%",
    "enquiryYearEndMinusOneDisplay": "30/06/2022",
    "amalgamatedLoanNotPaidByEOIYFormatted": "$66,088,466.26",
    "openingBalancePayDays": "365",
    "openingBalanceInterestFormatted": "$3,152,419.84",
    "totalAmountOfRepaymentFormatted": "$0",
    "totalInterestFormatted": "$3,152,419.84",
    "principalFormatted": "$0",
    "enquiryYearEndDisplay": "30/06/2023",
    "minimumYearRepaymentFormatted": "$35,426,906.00"
  },
  "repayments": [],
  "inputs": {
    "incomeYearOfLoan": 2017,
    "fullTermOfAmalgamatedLoan": 7,
    "incomeYearOfEnquiring": 2023,
    "amalgamatedLoanNotPaidByEOIY": 66088466.264645636,
    "repayments": null,
    "lodgement_date": null
  },
  "idx": 865
}