{
  "id": "2023-10-31T19:49:34.628Z0.8767061300484721",
  "alert": "Start of result\nResult\n\nMinimum yearly repayment met.\n\nThe amount of the loan not repaid at the end of income year 2007-08 is $999.98.\n\n\u000b\n\nThe amalgamated loan will not be taken to be a dividend because the total repayments made are equal to or greater than the minimum yearly repayment required for income year 2007-08.\n\nInterest received by the private company must be included in the income tax return for 2007-08.\n\nMinimum yearly repayment\n\n$2,380.00\n\nBenchmark interest rate\n\n8.05%\n\nOpening balance:\n\nDate: 30/06/2007\n\nBalance: $6,129.00\n\nDays: 8\n\nInterest: $10.78\n\nPayments\n\nDate: 09/07/2007\n\nAmount: $5,212.00\n\nBalance: $917.00\n\nDays: 358\n\nInterest: $72.20\n\n\n\n\nTotal repayments\n\n$5,212.00\n\nTotal interest\n\n$82.98\n\nTotal principal\n\n$5,129.02\n\nClosing balance\n\nDate: 30/06/2008\n\nBalance: $999.98",
  "outputs": {
    "enquiryRateFormatted": "8.05%",
    "enquiryYearEndMinusOneDisplay": "30/06/2007",
    "amalgamatedLoanNotPaidByEOIYFormatted": "$6,129.00",
    "openingBalancePayDays": "8",
    "openingBalanceInterestFormatted": "$10.78",
    "totalAmountOfRepaymentFormatted": "$5,212.00",
    "totalInterestFormatted": "$82.98",
    "principalFormatted": "$5,129.02",
    "enquiryYearEndDisplay": "30/06/2008",
    "minimumYearRepaymentFormatted": "$2,380.00",
    "loanAmountFormatted": "$999.98"
  },
  "repayments": [
    {
      "rd": "9/7/2007",
      "ra": 5212
    }
  ],
  "inputs": {
    "incomeYearOfLoan": 2003,
    "fullTermOfAmalgamatedLoan": 7,
    "incomeYearOfEnquiring": 2008,
    "amalgamatedLoanNotPaidByEOIY": 6129,
    "repayments": null,
    "lodgement_date": null
  },
  "idx": 5888
}