{
  "id": "2023-09-04T16:53:56.233Z0.3336068414075173",
  "alert": "Start of result\nResult\n\nMinimum yearly repayment not met.\n\nThe amount of the loan not repaid at the end of income year 2018-19 is $79,792,222.57.\n\nThe private company may be taken to pay a dividend under Division 7A to the shareholder or shareholder's associate because the amount repaid during income year 2018-19 in relation to the amalgamated loan is less than the minimum yearly repayment required.\n\nInterest received by the private company must be included in the income tax return for 2018-19.\n\nMinimum yearly repayment\n\n$43,034,294.00\n\nBenchmark interest rate\n\n5.2%\n\nOpening balance:\n\nDate: 30/06/2018\n\nBalance: $79,792,222.57\n\nDays: 365\n\nInterest: $4,149,195.57\n\nTotal repayments\n\n$0\n\nTotal interest\n\n$4,149,195.57\n\nTotal principal\n\n$0\n\nClosing balance\n\nDate: 30/06/2019\n\nBalance: $79,792,222.57",
  "outputs": {
    "enquiryRateFormatted": "5.2%",
    "enquiryYearEndMinusOneDisplay": "30/06/2018",
    "amalgamatedLoanNotPaidByEOIYFormatted": "$79,792,222.57",
    "openingBalancePayDays": "365",
    "openingBalanceInterestFormatted": "$4,149,195.57",
    "totalAmountOfRepaymentFormatted": "$0",
    "totalInterestFormatted": "$4,149,195.57",
    "principalFormatted": "$0",
    "enquiryYearEndDisplay": "30/06/2019",
    "minimumYearRepaymentFormatted": "$43,034,294.00"
  },
  "repayments": [],
  "inputs": {
    "incomeYearOfLoan": 2015,
    "fullTermOfAmalgamatedLoan": 5,
    "incomeYearOfEnquiring": 2019,
    "amalgamatedLoanNotPaidByEOIY": 79792222.57666221,
    "repayments": null,
    "lodgement_date": null
  },
  "idx": 1370
}