{
  "id": "2023-09-06T16:55:14.442Z0.8357577662521569",
  "alert": "Start of result\nResult\n\nMinimum yearly repayment not met.\n\nThe amount of the loan not repaid at the end of income year 2011-12 is $4,255.20.\n\nThe private company may be taken to pay a dividend under Division 7A to the shareholder or shareholder's associate because the amount repaid during income year 2011-12 in relation to the amalgamated loan is less than the minimum yearly repayment required.\n\nInterest received by the private company must be included in the income tax return for 2011-12.\n\nMinimum yearly repayment\n\n$11,162.00\n\nBenchmark interest rate\n\n7.8%\n\nOpening balance:\n\nDate: 30/06/2011\n\nBalance: $10,354.00\n\nDays: 188\n\nInterest: $414.84\n\nPayments\n\nDate: 05/01/2012\n\nAmount: $6,654.00\n\nBalance: $3,700.00\n\nDays: 178\n\nInterest: $140.36\n\n\n\n\nTotal repayments\n\n$6,654.00\n\nTotal interest\n\n$555.20\n\nTotal principal\n\n$6,098.80\n\nClosing balance\n\nDate: 30/06/2012\n\nBalance: $4,255.20",
  "outputs": {
    "enquiryRateFormatted": "7.8%",
    "enquiryYearEndMinusOneDisplay": "30/06/2011",
    "amalgamatedLoanNotPaidByEOIYFormatted": "$10,354.00",
    "openingBalancePayDays": "188",
    "openingBalanceInterestFormatted": "$414.84",
    "totalAmountOfRepaymentFormatted": "$6,654.00",
    "totalInterestFormatted": "$555.20",
    "principalFormatted": "$6,098.80",
    "enquiryYearEndDisplay": "30/06/2012",
    "minimumYearRepaymentFormatted": "$11,162.00"
  },
  "repayments": [
    {
      "rd": "5/1/2012",
      "ra": 6654
    }
  ],
  "inputs": {
    "incomeYearOfLoan": 2005,
    "fullTermOfAmalgamatedLoan": 7,
    "incomeYearOfEnquiring": 2012,
    "amalgamatedLoanNotPaidByEOIY": 10354,
    "repayments": null,
    "lodgement_date": null
  },
  "idx": 5528
}