{
  "id": "2023-10-31T19:16:09.325Z0.9368172721734962",
  "alert": "Start of result\nResult\n\nAmalgamated loan fully repaid.\n\nThe amalgamated loan has been paid in full.\u000bThe private company is not taken under Division 7A to pay a dividend to the shareholder or shareholder's associate.\n\nInterest received by the private company must be included in the income tax return for 2005-06.\n\nMinimum yearly repayment\n\n-$331.00\n\nBenchmark interest rate\n\n7.3%\n\nOpening balance:\n\nDate: 30/06/2005\n\nBalance: $123.81\n\nDays: 44\n\nInterest: $1.09\n\nPayments\n\nDate: 14/08/2005\n\nAmount: $1,238.17\n\nBalance: $0\n\nDays: 321\n\nInterest: $0\n\n\n\n\nTotal repayments\n\n$1,238.17\n\nTotal interest\n\n$1.09\n\nTotal principal\n\n$1,237.08\n\nClosing balance\n\nDate: 30/06/2006\n\nBalance: $0",
  "outputs": {
    "enquiryRateFormatted": "7.3%",
    "enquiryYearEndMinusOneDisplay": "30/06/2005",
    "amalgamatedLoanNotPaidByEOIYFormatted": "$123.81",
    "openingBalancePayDays": "44",
    "openingBalanceInterestFormatted": "$1.09",
    "totalAmountOfRepaymentFormatted": "$1,238.17",
    "totalInterestFormatted": "$1.09",
    "principalFormatted": "$1,237.08",
    "enquiryYearEndDisplay": "30/06/2006",
    "minimumYearRepaymentFormatted": "-$331.00",
    "loanAmountFormatted": "$0"
  },
  "repayments": [
    {
      "rd": "14/8/2005",
      "ra": 1238.1796269651527
    }
  ],
  "inputs": {
    "incomeYearOfLoan": 2005,
    "fullTermOfAmalgamatedLoan": 4,
    "incomeYearOfEnquiring": 2006,
    "amalgamatedLoanNotPaidByEOIY": 123.81796269651527,
    "repayments": null,
    "lodgement_date": "28/3/2006"
  },
  "idx": 5244
}