{
  "id": "2023-09-06T09:33:33.392Z0.5162358952223081",
  "alert": "Start of result\nResult\n\nMinimum yearly repayment met.\n\nThe amount of the loan not repaid at the end of income year 2009-10 is $1.96.\n\nThe amalgamated loan will not be taken to be a dividend because the total repayments made are equal to or greater than the minimum yearly repayment required for income year 2009-10.\n\nInterest received by the private company must be included in the income tax return for 2009-10.\n\nMinimum yearly repayment\n\n$0\n\nBenchmark interest rate\n\n5.75%\n\nOpening balance:\n\nDate: 30/06/2009\n\nBalance: $62.02\n\nDays: 201\n\nInterest: $1.96\n\nPayments\n\nDate: 18/01/2010\n\nAmount: $62.02\n\nBalance: $0\n\nDays: 164\n\nInterest: $0\n\n\n\n\nTotal repayments\n\n$62.02\n\nTotal interest\n\n$1.96\n\nTotal principal\n\n$60.06\n\nClosing balance\n\nDate: 30/06/2010\n\nBalance: $1.96",
  "outputs": {
    "enquiryRateFormatted": "5.75%",
    "enquiryYearEndMinusOneDisplay": "30/06/2009",
    "amalgamatedLoanNotPaidByEOIYFormatted": "$62.02",
    "openingBalancePayDays": "201",
    "openingBalanceInterestFormatted": "$1.96",
    "totalAmountOfRepaymentFormatted": "$62.02",
    "totalInterestFormatted": "$1.96",
    "principalFormatted": "$60.06",
    "enquiryYearEndDisplay": "30/06/2010",
    "minimumYearRepaymentFormatted": "$0"
  },
  "repayments": [
    {
      "rd": "18/1/2010",
      "ra": 62.02222103597978
    }
  ],
  "inputs": {
    "incomeYearOfLoan": 2009,
    "fullTermOfAmalgamatedLoan": 3,
    "incomeYearOfEnquiring": 2010,
    "amalgamatedLoanNotPaidByEOIY": 62.02222103597962,
    "repayments": null,
    "lodgement_date": "29/6/2010"
  },
  "idx": 7002
}