{
  "id": "2023-09-06T08:00:09.275Z0.7528728248878509",
  "alert": "Start of result\nResult\n\nMinimum yearly repayment not met.\n\nThe amount of the loan not repaid at the end of income year 2013-14 is $1,852.27.\n\nThe private company may be taken to pay a dividend under Division 7A to the shareholder or shareholder's associate because the amount repaid during income year 2013-14 in relation to the amalgamated loan is less than the minimum yearly repayment required.\n\nInterest received by the private company must be included in the income tax return for 2013-14.\n\nMinimum yearly repayment\n\n$3,026.00\n\nBenchmark interest rate\n\n6.2%\n\nOpening balance:\n\nDate: 30/06/2013\n\nBalance: $2,849.00\n\nDays: 166\n\nInterest: $80.33\n\nPayments\n\nDate: 14/12/2013\n\nAmount: $1,135.00\n\nBalance: $1,714.00\n\nDays: 199\n\nInterest: $57.94\n\n\n\n\nTotal repayments\n\n$1,135.00\n\nTotal interest\n\n$138.27\n\nTotal principal\n\n$996.73\n\nClosing balance\n\nDate: 30/06/2014\n\nBalance: $1,852.27",
  "outputs": {
    "enquiryRateFormatted": "6.2%",
    "enquiryYearEndMinusOneDisplay": "30/06/2013",
    "amalgamatedLoanNotPaidByEOIYFormatted": "$2,849.00",
    "openingBalancePayDays": "166",
    "openingBalanceInterestFormatted": "$80.33",
    "totalAmountOfRepaymentFormatted": "$1,135.00",
    "totalInterestFormatted": "$138.27",
    "principalFormatted": "$996.73",
    "enquiryYearEndDisplay": "30/06/2014",
    "minimumYearRepaymentFormatted": "$3,026.00"
  },
  "repayments": [
    {
      "rd": "14/12/2013",
      "ra": 1135
    }
  ],
  "inputs": {
    "incomeYearOfLoan": 2010,
    "fullTermOfAmalgamatedLoan": 4,
    "incomeYearOfEnquiring": 2014,
    "amalgamatedLoanNotPaidByEOIY": 2849,
    "repayments": null,
    "lodgement_date": null
  },
  "idx": 1469
}