{
  "id": "2023-09-06T18:37:22.429Z0.8345717141682665",
  "alert": "Start of result\nResult\n\nMinimum yearly repayment met.\n\nThe amount of the loan not repaid at the end of income year 2005-06 is $9,125.70.\n\nThe amalgamated loan will not be taken to be a dividend because the total repayments made are equal to or greater than the minimum yearly repayment required for income year 2005-06.\n\nInterest received by the private company must be included in the income tax return for 2005-06.\n\nMinimum yearly repayment\n\n$2,317.00\n\nBenchmark interest rate\n\n7.3%\n\nOpening balance:\n\nDate: 30/06/2005\n\nBalance: $10,944.00\n\nDays: 168\n\nInterest: $367.72\n\nPayments\n\nDate: 16/12/2005\n\nAmount: $2,518.00\n\nBalance: $8,426.00\n\nDays: 197\n\nInterest: $331.98\n\n\n\n\nTotal repayments\n\n$2,518.00\n\nTotal interest\n\n$699.70\n\nTotal principal\n\n$1,818.30\n\nClosing balance\n\nDate: 30/06/2006\n\nBalance: $9,125.70",
  "outputs": {
    "enquiryRateFormatted": "7.3%",
    "enquiryYearEndMinusOneDisplay": "30/06/2005",
    "amalgamatedLoanNotPaidByEOIYFormatted": "$10,944.00",
    "openingBalancePayDays": "168",
    "openingBalanceInterestFormatted": "$367.72",
    "totalAmountOfRepaymentFormatted": "$2,518.00",
    "totalInterestFormatted": "$699.70",
    "principalFormatted": "$1,818.30",
    "enquiryYearEndDisplay": "30/06/2006",
    "minimumYearRepaymentFormatted": "$2,317.00"
  },
  "repayments": [
    {
      "rd": "16/12/2005",
      "ra": 2518
    }
  ],
  "inputs": {
    "incomeYearOfLoan": 2004,
    "fullTermOfAmalgamatedLoan": 7,
    "incomeYearOfEnquiring": 2006,
    "amalgamatedLoanNotPaidByEOIY": 10944,
    "repayments": null,
    "lodgement_date": null
  },
  "idx": 2963
}