{
  "id": "2023-09-04T16:31:53.601Z0.19838678779536734",
  "alert": "Start of result\nResult\n\nMinimum yearly repayment not met.\n\nThe amount of the loan not repaid at the end of income year 2021-22 is $117,434,884.22.\n\nThe private company may be taken to pay a dividend under Division 7A to the shareholder or shareholder's associate because the amount repaid during income year 2021-22 in relation to the amalgamated loan is less than the minimum yearly repayment required.\n\nInterest received by the private company must be included in the income tax return for 2021-22.\n\nMinimum yearly repayment\n\n$32,749,547.00\n\nBenchmark interest rate\n\n4.52%\n\nOpening balance:\n\nDate: 30/06/2021\n\nBalance: $117,434,884.22\n\nDays: 365\n\nInterest: $5,308,056.77\n\nTotal repayments\n\n$0\n\nTotal interest\n\n$5,308,056.77\n\nTotal principal\n\n$0\n\nClosing balance\n\nDate: 30/06/2022\n\nBalance: $117,434,884.22",
  "outputs": {
    "enquiryRateFormatted": "4.52%",
    "enquiryYearEndMinusOneDisplay": "30/06/2021",
    "amalgamatedLoanNotPaidByEOIYFormatted": "$117,434,884.22",
    "openingBalancePayDays": "365",
    "openingBalanceInterestFormatted": "$5,308,056.77",
    "totalAmountOfRepaymentFormatted": "$0",
    "totalInterestFormatted": "$5,308,056.77",
    "principalFormatted": "$0",
    "enquiryYearEndDisplay": "30/06/2022",
    "minimumYearRepaymentFormatted": "$32,749,547.00"
  },
  "repayments": [],
  "inputs": {
    "incomeYearOfLoan": 2018,
    "fullTermOfAmalgamatedLoan": 7,
    "incomeYearOfEnquiring": 2022,
    "amalgamatedLoanNotPaidByEOIY": 117434884.22885996,
    "repayments": null,
    "lodgement_date": null
  },
  "idx": 702
}