{
  "id": "2023-09-06T05:04:55.075Z0.11530269999878784",
  "alert": "Start of result\nResult\n\nMinimum yearly repayment met.\n\nThe amount of the loan not repaid at the end of income year 2014-15 is $4,346.35.\n\nThe amalgamated loan will not be taken to be a dividend because the total repayments made are equal to or greater than the minimum yearly repayment required for income year 2014-15.\n\nInterest received by the private company must be included in the income tax return for 2014-15.\n\nMinimum yearly repayment\n\n$3,862.00\n\nBenchmark interest rate\n\n5.95%\n\nOpening balance:\n\nDate: 30/06/2014\n\nBalance: $10,334.00\n\nDays: 158\n\nInterest: $266.16\n\nPayments\n\nDate: 06/12/2014\n\nAmount: $6,387.00\n\nBalance: $3,947.00\n\nDays: 207\n\nInterest: $133.19\n\n\n\n\nTotal repayments\n\n$6,387.00\n\nTotal interest\n\n$399.35\n\nTotal principal\n\n$5,987.65\n\nClosing balance\n\nDate: 30/06/2015\n\nBalance: $4,346.35",
  "outputs": {
    "enquiryRateFormatted": "5.95%",
    "enquiryYearEndMinusOneDisplay": "30/06/2014",
    "amalgamatedLoanNotPaidByEOIYFormatted": "$10,334.00",
    "openingBalancePayDays": "158",
    "openingBalanceInterestFormatted": "$266.16",
    "totalAmountOfRepaymentFormatted": "$6,387.00",
    "totalInterestFormatted": "$399.35",
    "principalFormatted": "$5,987.65",
    "enquiryYearEndDisplay": "30/06/2015",
    "minimumYearRepaymentFormatted": "$3,862.00"
  },
  "repayments": [
    {
      "rd": "6/12/2014",
      "ra": 6387
    }
  ],
  "inputs": {
    "incomeYearOfLoan": 2012,
    "fullTermOfAmalgamatedLoan": 5,
    "incomeYearOfEnquiring": 2015,
    "amalgamatedLoanNotPaidByEOIY": 10334,
    "repayments": null,
    "lodgement_date": null
  },
  "idx": 737
}