{
  "id": "2023-09-04T16:02:59.401Z0.30286486599239615",
  "alert": "Start of result\nResult\n\nMinimum yearly repayment not met.\n\nThe amount of the loan not repaid at the end of income year 2023-24 is $4,523.00.\n\nThe private company may be taken to pay a dividend under Division 7A to the shareholder or shareholder's associate because the amount repaid during income year 2023-24 in relation to the amalgamated loan is less than the minimum yearly repayment required.\n\nInterest received by the private company must be included in the income tax return for 2023-24.\n\nMinimum yearly repayment\n\n$1,764.00\n\nBenchmark interest rate\n\n8.27%\n\nOpening balance:\n\nDate: 30/06/2023\n\nBalance: $4,523.00\n\nDays: 366\n\nInterest: $374.05\n\nTotal repayments\n\n$0\n\nTotal interest\n\n$374.05\n\nTotal principal\n\n$0\n\nClosing balance\n\nDate: 30/06/2024\n\nBalance: $4,523.00",
  "outputs": {
    "enquiryRateFormatted": "8.27%",
    "enquiryYearEndMinusOneDisplay": "30/06/2023",
    "amalgamatedLoanNotPaidByEOIYFormatted": "$4,523.00",
    "openingBalancePayDays": "366",
    "openingBalanceInterestFormatted": "$374.05",
    "totalAmountOfRepaymentFormatted": "$0",
    "totalInterestFormatted": "$374.05",
    "principalFormatted": "$0",
    "enquiryYearEndDisplay": "30/06/2024",
    "minimumYearRepaymentFormatted": "$1,764.00"
  },
  "repayments": [],
  "inputs": {
    "incomeYearOfLoan": 2023,
    "fullTermOfAmalgamatedLoan": 3,
    "incomeYearOfEnquiring": 2024,
    "amalgamatedLoanNotPaidByEOIY": 4523,
    "repayments": null,
    "lodgement_date": "17/1/2024"
  },
  "idx": 2
}