{
  "id": "2023-10-31T18:40:46.683Z0.46716393796817834",
  "alert": "Start of result\nResult\n\nMinimum yearly repayment not met.\n\nThe amount of the loan not repaid at the end of income year 2013-14 is $105.49.\n\nThe private company may be taken to pay a dividend under Division 7A to the shareholder or shareholder's associate because the amount repaid during income year 2013-14 in relation to the amalgamated loan is less than the minimum yearly repayment required.\n\nInterest received by the private company must be included in the income tax return for 2013-14.\n\nMinimum yearly repayment\n\n$112.00\n\nBenchmark interest rate\n\n6.2%\n\nOpening balance:\n\nDate: 30/06/2013\n\nBalance: $105.49\n\nDays: 365\n\nInterest: $6.54\n\nTotal repayments\n\n$0\n\nTotal interest\n\n$6.54\n\nTotal principal\n\n$0\n\nClosing balance\n\nDate: 30/06/2014\n\nBalance: $105.49",
  "outputs": {
    "enquiryRateFormatted": "6.2%",
    "enquiryYearEndMinusOneDisplay": "30/06/2013",
    "amalgamatedLoanNotPaidByEOIYFormatted": "$105.49",
    "openingBalancePayDays": "365",
    "openingBalanceInterestFormatted": "$6.54",
    "totalAmountOfRepaymentFormatted": "$0",
    "totalInterestFormatted": "$6.54",
    "principalFormatted": "$0",
    "enquiryYearEndDisplay": "30/06/2014",
    "minimumYearRepaymentFormatted": "$112.00",
    "loanAmountFormatted": "$105.49"
  },
  "repayments": [],
  "inputs": {
    "incomeYearOfLoan": 2008,
    "fullTermOfAmalgamatedLoan": 6,
    "incomeYearOfEnquiring": 2014,
    "amalgamatedLoanNotPaidByEOIY": 105.49340848242214,
    "repayments": null,
    "lodgement_date": null
  },
  "idx": 4375
}