{
  "id": "2023-09-05T22:33:50.932Z0.22788279779973197",
  "alert": "Start of result\nResult\n\nMinimum yearly repayment met.\n\nThe amount of the loan not repaid at the end of income year 2017-18 is $319.95.\n\nThe amalgamated loan will not be taken to be a dividend because the total repayments made are equal to or greater than the minimum yearly repayment required for income year 2017-18.\n\nInterest received by the private company must be included in the income tax return for 2017-18.\n\nMinimum yearly repayment\n\n$1,446.00\n\nBenchmark interest rate\n\n5.3%\n\nOpening balance:\n\nDate: 30/06/2017\n\nBalance: $7,272.00\n\nDays: 303\n\nInterest: $319.95\n\nPayments\n\nDate: 30/04/2018\n\nAmount: $7,272.00\n\nBalance: $0\n\nDays: 62\n\nInterest: $0\n\n\n\n\nTotal repayments\n\n$7,272.00\n\nTotal interest\n\n$319.95\n\nTotal principal\n\n$6,952.05\n\nClosing balance\n\nDate: 30/06/2018\n\nBalance: $319.95",
  "outputs": {
    "enquiryRateFormatted": "5.3%",
    "enquiryYearEndMinusOneDisplay": "30/06/2017",
    "amalgamatedLoanNotPaidByEOIYFormatted": "$7,272.00",
    "openingBalancePayDays": "303",
    "openingBalanceInterestFormatted": "$319.95",
    "totalAmountOfRepaymentFormatted": "$7,272.00",
    "totalInterestFormatted": "$319.95",
    "principalFormatted": "$6,952.05",
    "enquiryYearEndDisplay": "30/06/2018",
    "minimumYearRepaymentFormatted": "$1,446.00"
  },
  "repayments": [
    {
      "rd": "30/4/2018",
      "ra": 7272
    }
  ],
  "inputs": {
    "incomeYearOfLoan": 2016,
    "fullTermOfAmalgamatedLoan": 7,
    "incomeYearOfEnquiring": 2018,
    "amalgamatedLoanNotPaidByEOIY": 7272,
    "repayments": null,
    "lodgement_date": null
  },
  "idx": 4800
}