{
  "id": "2023-09-04T22:15:38.378Z0.19009406088959313",
  "alert": "Start of result\nResult\n\nMinimum yearly repayment not met.\n\nThe amount of the loan not repaid at the end of income year 2001-02 is $22,592,526.18.\n\nThe private company may be taken to pay a dividend under Division 7A to the shareholder or shareholder's associate because the amount repaid during income year 2001-02 in relation to the amalgamated loan is less than the minimum yearly repayment required.\n\nInterest received by the private company must be included in the income tax return for 2001-02.\n\nMinimum yearly repayment\n\n$24,128,818.00\n\nBenchmark interest rate\n\n6.8%\n\nOpening balance:\n\nDate: 30/06/2001\n\nBalance: $22,592,526.18\n\nDays: 365\n\nInterest: $1,536,291.78\n\nTotal repayments\n\n$0\n\nTotal interest\n\n$1,536,291.78\n\nTotal principal\n\n$0\n\nClosing balance\n\nDate: 30/06/2002\n\nBalance: $22,592,526.18",
  "outputs": {
    "enquiryRateFormatted": "6.8%",
    "enquiryYearEndMinusOneDisplay": "30/06/2001",
    "amalgamatedLoanNotPaidByEOIYFormatted": "$22,592,526.18",
    "openingBalancePayDays": "365",
    "openingBalanceInterestFormatted": "$1,536,291.78",
    "totalAmountOfRepaymentFormatted": "$0",
    "totalInterestFormatted": "$1,536,291.78",
    "principalFormatted": "$0",
    "enquiryYearEndDisplay": "30/06/2002",
    "minimumYearRepaymentFormatted": "$24,128,818.00"
  },
  "repayments": [],
  "inputs": {
    "incomeYearOfLoan": 2001,
    "fullTermOfAmalgamatedLoan": 1,
    "incomeYearOfEnquiring": 2002,
    "amalgamatedLoanNotPaidByEOIY": 22592526.18173764,
    "repayments": null,
    "lodgement_date": "27/4/2002"
  },
  "idx": 574
}