{
  "id": "2023-09-06T05:50:28.885Z0.8665056894955541",
  "alert": "Start of result\nResult\n\nMinimum yearly repayment not met.\n\nThe amount of the loan not repaid at the end of income year 2012-13 is $812.20.\n\nThe private company may be taken to pay a dividend under Division 7A to the shareholder or shareholder's associate because the amount repaid during income year 2012-13 in relation to the amalgamated loan is less than the minimum yearly repayment required.\n\nInterest received by the private company must be included in the income tax return for 2012-13.\n\nMinimum yearly repayment\n\n$7,726.00\n\nBenchmark interest rate\n\n7.05%\n\nOpening balance:\n\nDate: 30/06/2012\n\nBalance: $7,217.00\n\nDays: 144\n\nInterest: $200.73\n\nPayments\n\nDate: 22/11/2012\n\nAmount: $1,381.00\n\nBalance: $5,836.00\n\nDays: 24\n\nInterest: $27.05\n\n\n\n\nDate: 16/12/2012\n\nAmount: $5,273.00\n\nBalance: $563.00\n\nDays: 197\n\nInterest: $21.42\n\n\n\n\nTotal repayments\n\n$6,654.00\n\nTotal interest\n\n$249.20\n\nTotal principal\n\n$6,404.80\n\nClosing balance\n\nDate: 30/06/2013\n\nBalance: $812.20",
  "outputs": {
    "enquiryRateFormatted": "7.05%",
    "enquiryYearEndMinusOneDisplay": "30/06/2012",
    "amalgamatedLoanNotPaidByEOIYFormatted": "$7,217.00",
    "openingBalancePayDays": "144",
    "openingBalanceInterestFormatted": "$200.73",
    "totalAmountOfRepaymentFormatted": "$6,654.00",
    "totalInterestFormatted": "$249.20",
    "principalFormatted": "$6,404.80",
    "enquiryYearEndDisplay": "30/06/2013",
    "minimumYearRepaymentFormatted": "$7,726.00"
  },
  "repayments": [
    {
      "rd": "22/11/2012",
      "ra": 1381
    },
    {
      "rd": "16/12/2012",
      "ra": 5273
    }
  ],
  "inputs": {
    "incomeYearOfLoan": 2011,
    "fullTermOfAmalgamatedLoan": 2,
    "incomeYearOfEnquiring": 2013,
    "amalgamatedLoanNotPaidByEOIY": 7217,
    "repayments": null,
    "lodgement_date": null
  },
  "idx": 3701
}