{
  "id": "2023-09-04T22:09:57.570Z0.9342224899394036",
  "alert": "Start of result\nResult\n\nMinimum yearly repayment met.\n\nThe amount of the loan not repaid at the end of income year 2002-03 is $7,789.66.\n\nThe amalgamated loan will not be taken to be a dividend because the total repayments made are equal to or greater than the minimum yearly repayment required for income year 2002-03.\n\nInterest received by the private company must be included in the income tax return for 2002-03.\n\nMinimum yearly repayment\n\n$2,757.00\n\nBenchmark interest rate\n\n6.3%\n\nOpening balance:\n\nDate: 30/06/2002\n\nBalance: $11,062.00\n\nDays: 0\n\nInterest: $0\n\nPayments\n\nDate: 01/07/2002\n\nAmount: $3,734.00\n\nBalance: $7,328.00\n\nDays: 365\n\nInterest: $461.66\n\n\n\n\nTotal repayments\n\n$3,734.00\n\nTotal interest\n\n$461.66\n\nTotal principal\n\n$3,272.34\n\nClosing balance\n\nDate: 30/06/2003\n\nBalance: $7,789.66",
  "outputs": {
    "enquiryRateFormatted": "6.3%",
    "enquiryYearEndMinusOneDisplay": "30/06/2002",
    "amalgamatedLoanNotPaidByEOIYFormatted": "$11,062.00",
    "openingBalancePayDays": "0",
    "openingBalanceInterestFormatted": "$0",
    "totalAmountOfRepaymentFormatted": "$3,734.00",
    "totalInterestFormatted": "$461.66",
    "principalFormatted": "$3,272.34",
    "enquiryYearEndDisplay": "30/06/2003",
    "minimumYearRepaymentFormatted": "$2,757.00"
  },
  "repayments": [
    {
      "rd": "1/7/2002",
      "ra": 3734
    }
  ],
  "inputs": {
    "incomeYearOfLoan": 2002,
    "fullTermOfAmalgamatedLoan": 3,
    "incomeYearOfEnquiring": 2003,
    "amalgamatedLoanNotPaidByEOIY": 11062,
    "repayments": null,
    "lodgement_date": "17/1/2003"
  },
  "idx": 364
}