{
  "id": "2023-10-31T21:08:00.961Z0.19120478278039776",
  "alert": "Start of result\nResult\n\nMinimum yearly repayment met.\n\nThe amount of the loan not repaid at the end of income year 2002-03 is $3,599.94.\n\n\u000b\n\nThe amalgamated loan will not be taken to be a dividend because the total repayments made are equal to or greater than the minimum yearly repayment required for income year 2002-03.\n\nInterest received by the private company must be included in the income tax return for 2002-03.\n\nMinimum yearly repayment\n\n$4,466.00\n\nBenchmark interest rate\n\n6.3%\n\nOpening balance:\n\nDate: 30/06/2002\n\nBalance: $11,871.00\n\nDays: 347\n\nInterest: $710.99\n\nPayments\n\nDate: 13/06/2003\n\nAmount: $8,991.00\n\nBalance: $2,880.00\n\nDays: 18\n\nInterest: $8.95\n\n\n\n\nTotal repayments\n\n$8,991.00\n\nTotal interest\n\n$719.94\n\nTotal principal\n\n$8,271.06\n\nClosing balance\n\nDate: 30/06/2003\n\nBalance: $3,599.94",
  "outputs": {
    "enquiryRateFormatted": "6.3%",
    "enquiryYearEndMinusOneDisplay": "30/06/2002",
    "amalgamatedLoanNotPaidByEOIYFormatted": "$11,871.00",
    "openingBalancePayDays": "347",
    "openingBalanceInterestFormatted": "$710.99",
    "totalAmountOfRepaymentFormatted": "$8,991.00",
    "totalInterestFormatted": "$719.94",
    "principalFormatted": "$8,271.06",
    "enquiryYearEndDisplay": "30/06/2003",
    "minimumYearRepaymentFormatted": "$4,466.00",
    "loanAmountFormatted": "$3,599.94"
  },
  "repayments": [
    {
      "rd": "13/6/2003",
      "ra": 8991
    }
  ],
  "inputs": {
    "incomeYearOfLoan": 1999,
    "fullTermOfAmalgamatedLoan": 6,
    "incomeYearOfEnquiring": 2003,
    "amalgamatedLoanNotPaidByEOIY": 11871,
    "repayments": null,
    "lodgement_date": null
  },
  "idx": 7039
}