{
  "id": "2023-10-31T17:40:26.338Z0.8779783895819304",
  "alert": "Start of result\nResult\n\nMinimum yearly repayment not met.\n\nThe amount of the loan not repaid at the end of income year 2018-19 is $6,087.00.\n\nThe private company may be taken to pay a dividend under Division 7A to the shareholder or shareholder's associate because the amount repaid during income year 2018-19 in relation to the amalgamated loan is less than the minimum yearly repayment required.\n\nInterest received by the private company must be included in the income tax return for 2018-19.\n\nMinimum yearly repayment\n\n$6,404.00\n\nBenchmark interest rate\n\n5.2%\n\nOpening balance:\n\nDate: 30/06/2018\n\nBalance: $6,087.00\n\nDays: 365\n\nInterest: $316.52\n\nTotal repayments\n\n$0\n\nTotal interest\n\n$316.52\n\nTotal principal\n\n$0\n\nClosing balance\n\nDate: 30/06/2019\n\nBalance: $6,087.00",
  "outputs": {
    "enquiryRateFormatted": "5.2%",
    "enquiryYearEndMinusOneDisplay": "30/06/2018",
    "amalgamatedLoanNotPaidByEOIYFormatted": "$6,087.00",
    "openingBalancePayDays": "365",
    "openingBalanceInterestFormatted": "$316.52",
    "totalAmountOfRepaymentFormatted": "$0",
    "totalInterestFormatted": "$316.52",
    "principalFormatted": "$0",
    "enquiryYearEndDisplay": "30/06/2019",
    "minimumYearRepaymentFormatted": "$6,404.00",
    "loanAmountFormatted": "$6,087.00"
  },
  "repayments": [],
  "inputs": {
    "incomeYearOfLoan": 2015,
    "fullTermOfAmalgamatedLoan": 4,
    "incomeYearOfEnquiring": 2019,
    "amalgamatedLoanNotPaidByEOIY": 6087,
    "repayments": null,
    "lodgement_date": null
  },
  "idx": 2252
}