{
  "id": "2023-09-05T15:19:54.346Z0.08512777890765766",
  "alert": "Start of result\nResult\n\nMinimum yearly repayment met.\n\nThe amount of the loan not repaid at the end of income year 2022-23 is $1,528.31.\n\nThe amalgamated loan will not be taken to be a dividend because the total repayments made are equal to or greater than the minimum yearly repayment required for income year 2022-23.\n\nInterest received by the private company must be included in the income tax return for 2022-23.\n\nMinimum yearly repayment\n\n$2,348.00\n\nBenchmark interest rate\n\n4.77%\n\nOpening balance:\n\nDate: 30/06/2022\n\nBalance: $6,423.00\n\nDays: 131\n\nInterest: $109.96\n\nPayments\n\nDate: 09/11/2022\n\nAmount: $1,526.00\n\nBalance: $4,897.00\n\nDays: 111\n\nInterest: $71.04\n\n\n\n\nDate: 28/02/2023\n\nAmount: $3,571.00\n\nBalance: $1,326.00\n\nDays: 123\n\nInterest: $21.31\n\n\n\n\nTotal repayments\n\n$5,097.00\n\nTotal interest\n\n$202.31\n\nTotal principal\n\n$4,894.69\n\nClosing balance\n\nDate: 30/06/2023\n\nBalance: $1,528.31",
  "outputs": {
    "enquiryRateFormatted": "4.77%",
    "enquiryYearEndMinusOneDisplay": "30/06/2022",
    "amalgamatedLoanNotPaidByEOIYFormatted": "$6,423.00",
    "openingBalancePayDays": "131",
    "openingBalanceInterestFormatted": "$109.96",
    "totalAmountOfRepaymentFormatted": "$5,097.00",
    "totalInterestFormatted": "$202.31",
    "principalFormatted": "$4,894.69",
    "enquiryYearEndDisplay": "30/06/2023",
    "minimumYearRepaymentFormatted": "$2,348.00"
  },
  "repayments": [
    {
      "rd": "9/11/2022",
      "ra": 1526
    },
    {
      "rd": "28/2/2023",
      "ra": 3571
    }
  ],
  "inputs": {
    "incomeYearOfLoan": 2020,
    "fullTermOfAmalgamatedLoan": 5,
    "incomeYearOfEnquiring": 2023,
    "amalgamatedLoanNotPaidByEOIY": 6423,
    "repayments": null,
    "lodgement_date": null
  },
  "idx": 5884
}