{
  "id": "2023-09-04T22:18:51.236Z0.44707141904255",
  "alert": "Start of result\nResult\n\nMinimum yearly repayment not met.\n\nThe amount of the loan not repaid at the end of income year 2002-03 is $414.00.\n\nThe private company may be taken to pay a dividend under Division 7A to the shareholder or shareholder's associate because the amount repaid during income year 2002-03 in relation to the amalgamated loan is less than the minimum yearly repayment required.\n\nInterest received by the private company must be included in the income tax return for 2002-03.\n\nMinimum yearly repayment\n\n$99.00\n\nBenchmark interest rate\n\n6.3%\n\nOpening balance:\n\nDate: 30/06/2002\n\nBalance: $414.00\n\nDays: 365\n\nInterest: $26.08\n\nTotal repayments\n\n$0\n\nTotal interest\n\n$26.08\n\nTotal principal\n\n$0\n\nClosing balance\n\nDate: 30/06/2003\n\nBalance: $414.00",
  "outputs": {
    "enquiryRateFormatted": "6.3%",
    "enquiryYearEndMinusOneDisplay": "30/06/2002",
    "amalgamatedLoanNotPaidByEOIYFormatted": "$414.00",
    "openingBalancePayDays": "365",
    "openingBalanceInterestFormatted": "$26.08",
    "totalAmountOfRepaymentFormatted": "$0",
    "totalInterestFormatted": "$26.08",
    "principalFormatted": "$0",
    "enquiryYearEndDisplay": "30/06/2003",
    "minimumYearRepaymentFormatted": "$99.00"
  },
  "repayments": [],
  "inputs": {
    "incomeYearOfLoan": 2001,
    "fullTermOfAmalgamatedLoan": 6,
    "incomeYearOfEnquiring": 2003,
    "amalgamatedLoanNotPaidByEOIY": 414,
    "repayments": null,
    "lodgement_date": null
  },
  "idx": 687
}