{
  "id": "2023-10-31T17:50:54.845Z0.9427938798019915",
  "alert": "Start of result\nResult\n\nMinimum yearly repayment not met.\n\nThe amount of the loan not repaid at the end of income year 2018-19 is $9,101.17.\n\nThe private company may be taken to pay a dividend under Division 7A to the shareholder or shareholder's associate because the amount repaid during income year 2018-19 in relation to the amalgamated loan is less than the minimum yearly repayment required.\n\nInterest received by the private company must be included in the income tax return for 2018-19.\n\nMinimum yearly repayment\n\n$5,537.00\n\nBenchmark interest rate\n\n5.2%\n\nOpening balance:\n\nDate: 30/06/2018\n\nBalance: $10,266.00\n\nDays: 354\n\nInterest: $517.74\n\nPayments\n\nDate: 20/06/2019\n\nAmount: $1,696.00\n\nBalance: $8,570.00\n\nDays: 11\n\nInterest: $13.43\n\n\n\n\nTotal repayments\n\n$1,696.00\n\nTotal interest\n\n$531.17\n\nTotal principal\n\n$1,164.83\n\nClosing balance\n\nDate: 30/06/2019\n\nBalance: $9,101.17",
  "outputs": {
    "enquiryRateFormatted": "5.2%",
    "enquiryYearEndMinusOneDisplay": "30/06/2018",
    "amalgamatedLoanNotPaidByEOIYFormatted": "$10,266.00",
    "openingBalancePayDays": "354",
    "openingBalanceInterestFormatted": "$517.74",
    "totalAmountOfRepaymentFormatted": "$1,696.00",
    "totalInterestFormatted": "$531.17",
    "principalFormatted": "$1,164.83",
    "enquiryYearEndDisplay": "30/06/2019",
    "minimumYearRepaymentFormatted": "$5,537.00",
    "loanAmountFormatted": "$9,101.17"
  },
  "repayments": [
    {
      "rd": "20/6/2019",
      "ra": 1696
    }
  ],
  "inputs": {
    "incomeYearOfLoan": 2014,
    "fullTermOfAmalgamatedLoan": 6,
    "incomeYearOfEnquiring": 2019,
    "amalgamatedLoanNotPaidByEOIY": 10266,
    "repayments": null,
    "lodgement_date": null
  },
  "idx": 2729
}