{
  "id": "2023-10-31T19:33:09.775Z0.6681911907788078",
  "alert": "Start of result\nResult\n\nMinimum yearly repayment not met.\n\nThe amount of the loan not repaid at the end of income year 2010-11 is $4,454.70.\n\nThe private company may be taken to pay a dividend under Division 7A to the shareholder or shareholder's associate because the amount repaid during income year 2010-11 in relation to the amalgamated loan is less than the minimum yearly repayment required.\n\nInterest received by the private company must be included in the income tax return for 2010-11.\n\nMinimum yearly repayment\n\n$6,758.00\n\nBenchmark interest rate\n\n7.4%\n\nOpening balance:\n\nDate: 30/06/2010\n\nBalance: $6,292.00\n\nDays: 348\n\nInterest: $443.92\n\nPayments\n\nDate: 14/06/2011\n\nAmount: $2,295.00\n\nBalance: $3,997.00\n\nDays: 17\n\nInterest: $13.78\n\n\n\n\nTotal repayments\n\n$2,295.00\n\nTotal interest\n\n$457.70\n\nTotal principal\n\n$1,837.30\n\nClosing balance\n\nDate: 30/06/2011\n\nBalance: $4,454.70",
  "outputs": {
    "enquiryRateFormatted": "7.4%",
    "enquiryYearEndMinusOneDisplay": "30/06/2010",
    "amalgamatedLoanNotPaidByEOIYFormatted": "$6,292.00",
    "openingBalancePayDays": "348",
    "openingBalanceInterestFormatted": "$443.92",
    "totalAmountOfRepaymentFormatted": "$2,295.00",
    "totalInterestFormatted": "$457.70",
    "principalFormatted": "$1,837.30",
    "enquiryYearEndDisplay": "30/06/2011",
    "minimumYearRepaymentFormatted": "$6,758.00",
    "loanAmountFormatted": "$4,454.70"
  },
  "repayments": [
    {
      "rd": "14/6/2011",
      "ra": 2295
    }
  ],
  "inputs": {
    "incomeYearOfLoan": 2004,
    "fullTermOfAmalgamatedLoan": 7,
    "incomeYearOfEnquiring": 2011,
    "amalgamatedLoanNotPaidByEOIY": 6292,
    "repayments": null,
    "lodgement_date": null
  },
  "idx": 5589
}