{
  "id": "2023-10-31T19:31:38.636Z0.1985296440618386",
  "alert": "Start of result\nResult\n\nMinimum yearly repayment not met.\n\nThe amount of the loan not repaid at the end of income year 2005-06 is $62.74.\n\nThe private company may be taken to pay a dividend under Division 7A to the shareholder or shareholder's associate because the amount repaid during income year 2005-06 in relation to the amalgamated loan is less than the minimum yearly repayment required.\n\nInterest received by the private company must be included in the income tax return for 2005-06.\n\nMinimum yearly repayment\n\n$15.00\n\nBenchmark interest rate\n\n7.3%\n\nOpening balance:\n\nDate: 30/06/2005\n\nBalance: $62.74\n\nDays: 365\n\nInterest: $4.58\n\nTotal repayments\n\n$0\n\nTotal interest\n\n$4.58\n\nTotal principal\n\n$0\n\nClosing balance\n\nDate: 30/06/2006\n\nBalance: $62.74",
  "outputs": {
    "enquiryRateFormatted": "7.3%",
    "enquiryYearEndMinusOneDisplay": "30/06/2005",
    "amalgamatedLoanNotPaidByEOIYFormatted": "$62.74",
    "openingBalancePayDays": "365",
    "openingBalanceInterestFormatted": "$4.58",
    "totalAmountOfRepaymentFormatted": "$0",
    "totalInterestFormatted": "$4.58",
    "principalFormatted": "$0",
    "enquiryYearEndDisplay": "30/06/2006",
    "minimumYearRepaymentFormatted": "$15.00",
    "loanAmountFormatted": "$62.74"
  },
  "repayments": [],
  "inputs": {
    "incomeYearOfLoan": 2004,
    "fullTermOfAmalgamatedLoan": 6,
    "incomeYearOfEnquiring": 2006,
    "amalgamatedLoanNotPaidByEOIY": 62.741025724907914,
    "repayments": null,
    "lodgement_date": null
  },
  "idx": 5558
}