{
  "id": "2023-10-31T20:44:35.626Z0.23618006040362527",
  "alert": "Start of result\nResult\n\nMinimum yearly repayment not met.\n\nThe amount of the loan not repaid at the end of income year 2001-02 is $9,873.00.\n\nThe private company may be taken to pay a dividend under Division 7A to the shareholder or shareholder's associate because the amount repaid during income year 2001-02 in relation to the amalgamated loan is less than the minimum yearly repayment required.\n\nInterest received by the private company must be included in the income tax return for 2001-02.\n\nMinimum yearly repayment\n\n$2,059.00\n\nBenchmark interest rate\n\n6.8%\n\nOpening balance:\n\nDate: 30/06/2001\n\nBalance: $9,873.00\n\nDays: 365\n\nInterest: $671.36\n\nTotal repayments\n\n$0\n\nTotal interest\n\n$671.36\n\nTotal principal\n\n$0\n\nClosing balance\n\nDate: 30/06/2002\n\nBalance: $9,873.00",
  "outputs": {
    "enquiryRateFormatted": "6.8%",
    "enquiryYearEndMinusOneDisplay": "30/06/2001",
    "amalgamatedLoanNotPaidByEOIYFormatted": "$9,873.00",
    "openingBalancePayDays": "365",
    "openingBalanceInterestFormatted": "$671.36",
    "totalAmountOfRepaymentFormatted": "$0",
    "totalInterestFormatted": "$671.36",
    "principalFormatted": "$0",
    "enquiryYearEndDisplay": "30/06/2002",
    "minimumYearRepaymentFormatted": "$2,059.00",
    "loanAmountFormatted": "$9,873.00"
  },
  "repayments": [],
  "inputs": {
    "incomeYearOfLoan": 2000,
    "fullTermOfAmalgamatedLoan": 7,
    "incomeYearOfEnquiring": 2002,
    "amalgamatedLoanNotPaidByEOIY": 9873,
    "repayments": null,
    "lodgement_date": null
  },
  "idx": 6728
}