{
  "id": "2023-09-04T16:44:28.543Z0.7715958677608703",
  "alert": "Start of result\nResult\n\nMinimum yearly repayment not met.\n\nThe amount of the loan not repaid at the end of income year 2019-20 is $4,094.68.\n\nThe private company may be taken to pay a dividend under Division 7A to the shareholder or shareholder's associate because the amount repaid during income year 2019-20 in relation to the amalgamated loan is less than the minimum yearly repayment required.\n\nInterest received by the private company must be included in the income tax return for 2019-20.\n\nMinimum yearly repayment\n\n$3,318.00\n\nBenchmark interest rate\n\n5.37%\n\nOpening balance:\n\nDate: 30/06/2019\n\nBalance: $6,138.00\n\nDays: 0\n\nInterest: $0\n\nPayments\n\nDate: 01/07/2019\n\nAmount: $2,252.00\n\nBalance: $3,886.00\n\nDays: 366\n\nInterest: $208.68\n\n\n\n\nTotal repayments\n\n$2,252.00\n\nTotal interest\n\n$208.68\n\nTotal principal\n\n$2,043.32\n\nClosing balance\n\nDate: 30/06/2020\n\nBalance: $4,094.68",
  "outputs": {
    "enquiryRateFormatted": "5.37%",
    "enquiryYearEndMinusOneDisplay": "30/06/2019",
    "amalgamatedLoanNotPaidByEOIYFormatted": "$6,138.00",
    "openingBalancePayDays": "0",
    "openingBalanceInterestFormatted": "$0",
    "totalAmountOfRepaymentFormatted": "$2,252.00",
    "totalInterestFormatted": "$208.68",
    "principalFormatted": "$2,043.32",
    "enquiryYearEndDisplay": "30/06/2020",
    "minimumYearRepaymentFormatted": "$3,318.00"
  },
  "repayments": [
    {
      "rd": "1/7/2019",
      "ra": 2252
    }
  ],
  "inputs": {
    "incomeYearOfLoan": 2016,
    "fullTermOfAmalgamatedLoan": 5,
    "incomeYearOfEnquiring": 2020,
    "amalgamatedLoanNotPaidByEOIY": 6138,
    "repayments": null,
    "lodgement_date": null
  },
  "idx": 1095
}