{
  "id": "2023-10-31T19:31:41.162Z0.810752465055063",
  "alert": "Start of result\nResult\n\nAmalgamated loan fully repaid.\n\nThe amalgamated loan has been paid in full.\u000bThe private company is not taken under Division 7A to pay a dividend to the shareholder or shareholder's associate.\n\nInterest received by the private company must be included in the income tax return for 2005-06.\n\nMinimum yearly repayment\n\n$15.00\n\nBenchmark interest rate\n\n7.3%\n\nOpening balance:\n\nDate: 30/06/2005\n\nBalance: $62.74\n\nDays: 108\n\nInterest: $1.36\n\nPayments\n\nDate: 17/10/2005\n\nAmount: $627.41\n\nBalance: $0\n\nDays: 257\n\nInterest: $0\n\n\n\n\nTotal repayments\n\n$627.41\n\nTotal interest\n\n$1.36\n\nTotal principal\n\n$626.05\n\nClosing balance\n\nDate: 30/06/2006\n\nBalance: $0",
  "outputs": {
    "enquiryRateFormatted": "7.3%",
    "enquiryYearEndMinusOneDisplay": "30/06/2005",
    "amalgamatedLoanNotPaidByEOIYFormatted": "$62.74",
    "openingBalancePayDays": "108",
    "openingBalanceInterestFormatted": "$1.36",
    "totalAmountOfRepaymentFormatted": "$627.41",
    "totalInterestFormatted": "$1.36",
    "principalFormatted": "$626.05",
    "enquiryYearEndDisplay": "30/06/2006",
    "minimumYearRepaymentFormatted": "$15.00",
    "loanAmountFormatted": "$0"
  },
  "repayments": [
    {
      "rd": "17/10/2005",
      "ra": 627.4102572490792
    }
  ],
  "inputs": {
    "incomeYearOfLoan": 2004,
    "fullTermOfAmalgamatedLoan": 6,
    "incomeYearOfEnquiring": 2006,
    "amalgamatedLoanNotPaidByEOIY": 62.741025724907914,
    "repayments": null,
    "lodgement_date": null
  },
  "idx": 5559
}