{
  "id": "2023-09-04T17:16:21.558Z0.6094304535626793",
  "alert": "Start of result\nResult\n\nMinimum yearly repayment not met.\n\nThe amount of the loan not repaid at the end of income year 2015-16 is $3,800.00.\n\nThe private company may be taken to pay a dividend under Division 7A to the shareholder or shareholder's associate because the amount repaid during income year 2015-16 in relation to the amalgamated loan is less than the minimum yearly repayment required.\n\nInterest received by the private company must be included in the income tax return for 2015-16.\n\nMinimum yearly repayment\n\n$889.00\n\nBenchmark interest rate\n\n5.45%\n\nOpening balance:\n\nDate: 30/06/2015\n\nBalance: $3,800.00\n\nDays: 366\n\nInterest: $207.10\n\nTotal repayments\n\n$0\n\nTotal interest\n\n$207.10\n\nTotal principal\n\n$0\n\nClosing balance\n\nDate: 30/06/2016\n\nBalance: $3,800.00",
  "outputs": {
    "enquiryRateFormatted": "5.45%",
    "enquiryYearEndMinusOneDisplay": "30/06/2015",
    "amalgamatedLoanNotPaidByEOIYFormatted": "$3,800.00",
    "openingBalancePayDays": "366",
    "openingBalanceInterestFormatted": "$207.10",
    "totalAmountOfRepaymentFormatted": "$0",
    "totalInterestFormatted": "$207.10",
    "principalFormatted": "$0",
    "enquiryYearEndDisplay": "30/06/2016",
    "minimumYearRepaymentFormatted": "$889.00"
  },
  "repayments": [],
  "inputs": {
    "incomeYearOfLoan": 2014,
    "fullTermOfAmalgamatedLoan": 6,
    "incomeYearOfEnquiring": 2016,
    "amalgamatedLoanNotPaidByEOIY": 3800,
    "repayments": null,
    "lodgement_date": null
  },
  "idx": 1926
}