{
  "id": "2023-10-31T17:30:53.439Z0.9667431987592493",
  "alert": "Start of result\nResult\n\nMinimum yearly repayment not met.\n\nThe amount of the loan not repaid at the end of income year 2017-18 is $3,267.01.\n\nThe private company may be taken to pay a dividend under Division 7A to the shareholder or shareholder's associate because the amount repaid during income year 2017-18 in relation to the amalgamated loan is less than the minimum yearly repayment required.\n\nInterest received by the private company must be included in the income tax return for 2017-18.\n\nMinimum yearly repayment\n\n$618.00\n\nBenchmark interest rate\n\n5.3%\n\nOpening balance:\n\nDate: 30/06/2017\n\nBalance: $3,539.00\n\nDays: 203\n\nInterest: $104.32\n\nPayments\n\nDate: 20/01/2018\n\nAmount: $449.00\n\nBalance: $3,090.00\n\nDays: 162\n\nInterest: $72.69\n\n\n\n\nTotal repayments\n\n$449.00\n\nTotal interest\n\n$177.01\n\nTotal principal\n\n$271.99\n\nClosing balance\n\nDate: 30/06/2018\n\nBalance: $3,267.01",
  "outputs": {
    "enquiryRateFormatted": "5.3%",
    "enquiryYearEndMinusOneDisplay": "30/06/2017",
    "amalgamatedLoanNotPaidByEOIYFormatted": "$3,539.00",
    "openingBalancePayDays": "203",
    "openingBalanceInterestFormatted": "$104.32",
    "totalAmountOfRepaymentFormatted": "$449.00",
    "totalInterestFormatted": "$177.01",
    "principalFormatted": "$271.99",
    "enquiryYearEndDisplay": "30/06/2018",
    "minimumYearRepaymentFormatted": "$618.00",
    "loanAmountFormatted": "$3,267.01"
  },
  "repayments": [
    {
      "rd": "20/1/2018",
      "ra": 449
    }
  ],
  "inputs": {
    "incomeYearOfLoan": 2017,
    "fullTermOfAmalgamatedLoan": 7,
    "incomeYearOfEnquiring": 2018,
    "amalgamatedLoanNotPaidByEOIY": 3539,
    "repayments": null,
    "lodgement_date": "30/8/2017"
  },
  "idx": 1740
}