{
  "id": "2023-10-31T19:33:24.518Z0.9033208096368999",
  "alert": "Start of result\nResult\n\nAmalgamated loan fully repaid.\n\nThe amalgamated loan has been paid in full.\u000bThe private company is not taken under Division 7A to pay a dividend to the shareholder or shareholder's associate.\n\nInterest received by the private company must be included in the income tax return for 2008-09.\n\nMinimum yearly repayment\n\n$1.00\n\nBenchmark interest rate\n\n9.45%\n\nOpening balance:\n\nDate: 30/06/2008\n\nBalance: $2.29\n\nDays: 57\n\nInterest: $0.03\n\nPayments\n\nDate: 27/08/2008\n\nAmount: $22.93\n\nBalance: $0\n\nDays: 308\n\nInterest: $0\n\n\n\n\nTotal repayments\n\n$22.93\n\nTotal interest\n\n$0.03\n\nTotal principal\n\n$22.90\n\nClosing balance\n\nDate: 30/06/2009\n\nBalance: $0",
  "outputs": {
    "enquiryRateFormatted": "9.45%",
    "enquiryYearEndMinusOneDisplay": "30/06/2008",
    "amalgamatedLoanNotPaidByEOIYFormatted": "$2.29",
    "openingBalancePayDays": "57",
    "openingBalanceInterestFormatted": "$0.03",
    "totalAmountOfRepaymentFormatted": "$22.93",
    "totalInterestFormatted": "$0.03",
    "principalFormatted": "$22.90",
    "enquiryYearEndDisplay": "30/06/2009",
    "minimumYearRepaymentFormatted": "$1.00",
    "loanAmountFormatted": "$0"
  },
  "repayments": [
    {
      "rd": "27/8/2008",
      "ra": 22.936228171511175
    }
  ],
  "inputs": {
    "incomeYearOfLoan": 2004,
    "fullTermOfAmalgamatedLoan": 7,
    "incomeYearOfEnquiring": 2009,
    "amalgamatedLoanNotPaidByEOIY": 2.293622817151135,
    "repayments": null,
    "lodgement_date": null
  },
  "idx": 5593
}