{
  "id": "2023-09-06T12:37:57.014Z0.031659969888272466",
  "alert": "Start of result\nResult\n\nMinimum yearly repayment met.\n\nThe amount of the loan not repaid at the end of income year 2008-09 is $2,914.59.\n\nThe amalgamated loan will not be taken to be a dividend because the total repayments made are equal to or greater than the minimum yearly repayment required for income year 2008-09.\n\nInterest received by the private company must be included in the income tax return for 2008-09.\n\nMinimum yearly repayment\n\n$6,362.00\n\nBenchmark interest rate\n\n9.45%\n\nOpening balance:\n\nDate: 30/06/2008\n\nBalance: $11,124.00\n\nDays: 109\n\nInterest: $313.93\n\nPayments\n\nDate: 18/10/2008\n\nAmount: $8,685.00\n\nBalance: $2,439.00\n\nDays: 256\n\nInterest: $161.66\n\n\n\n\nTotal repayments\n\n$8,685.00\n\nTotal interest\n\n$475.59\n\nTotal principal\n\n$8,209.41\n\nClosing balance\n\nDate: 30/06/2009\n\nBalance: $2,914.59",
  "outputs": {
    "enquiryRateFormatted": "9.45%",
    "enquiryYearEndMinusOneDisplay": "30/06/2008",
    "amalgamatedLoanNotPaidByEOIYFormatted": "$11,124.00",
    "openingBalancePayDays": "109",
    "openingBalanceInterestFormatted": "$313.93",
    "totalAmountOfRepaymentFormatted": "$8,685.00",
    "totalInterestFormatted": "$475.59",
    "principalFormatted": "$8,209.41",
    "enquiryYearEndDisplay": "30/06/2009",
    "minimumYearRepaymentFormatted": "$6,362.00"
  },
  "repayments": [
    {
      "rd": "18/10/2008",
      "ra": 8685
    }
  ],
  "inputs": {
    "incomeYearOfLoan": 2007,
    "fullTermOfAmalgamatedLoan": 3,
    "incomeYearOfEnquiring": 2009,
    "amalgamatedLoanNotPaidByEOIY": 11124,
    "repayments": null,
    "lodgement_date": null
  },
  "idx": 8120
}