{
  "id": "2023-10-31T18:03:47.297Z0.3356637710010274",
  "alert": "Start of result\nResult\n\nMinimum yearly repayment not met.\n\nThe amount of the loan not repaid at the end of income year 2014-15 is $5,805.00.\n\nThe private company may be taken to pay a dividend under Division 7A to the shareholder or shareholder's associate because the amount repaid during income year 2014-15 in relation to the amalgamated loan is less than the minimum yearly repayment required.\n\nInterest received by the private company must be included in the income tax return for 2014-15.\n\nMinimum yearly repayment\n\n$2,170.00\n\nBenchmark interest rate\n\n5.95%\n\nOpening balance:\n\nDate: 30/06/2014\n\nBalance: $5,805.00\n\nDays: 365\n\nInterest: $345.40\n\nTotal repayments\n\n$0\n\nTotal interest\n\n$345.40\n\nTotal principal\n\n$0\n\nClosing balance\n\nDate: 30/06/2015\n\nBalance: $5,805.00",
  "outputs": {
    "enquiryRateFormatted": "5.95%",
    "enquiryYearEndMinusOneDisplay": "30/06/2014",
    "amalgamatedLoanNotPaidByEOIYFormatted": "$5,805.00",
    "openingBalancePayDays": "365",
    "openingBalanceInterestFormatted": "$345.40",
    "totalAmountOfRepaymentFormatted": "$0",
    "totalInterestFormatted": "$345.40",
    "principalFormatted": "$0",
    "enquiryYearEndDisplay": "30/06/2015",
    "minimumYearRepaymentFormatted": "$2,170.00",
    "loanAmountFormatted": "$5,805.00"
  },
  "repayments": [],
  "inputs": {
    "incomeYearOfLoan": 2012,
    "fullTermOfAmalgamatedLoan": 5,
    "incomeYearOfEnquiring": 2015,
    "amalgamatedLoanNotPaidByEOIY": 5805,
    "repayments": null,
    "lodgement_date": null
  },
  "idx": 3231
}