{
  "id": "2023-09-04T17:20:48.513Z0.07974237730141254",
  "alert": "Start of result\nResult\n\nAmalgamated loan fully repaid.\n\nThe amalgamated loan has been paid in full.\u000bThe private company is not taken under Division 7A to pay a dividend to the shareholder or shareholder's associate.\n\nInterest received by the private company must be included in the income tax return for 2013-14.\n\nMinimum yearly repayment\n\n$1,548.00\n\nBenchmark interest rate\n\n6.2%\n\nOpening balance:\n\nDate: 30/06/2013\n\nBalance: $2,830.00\n\nDays: 0\n\nInterest: $0\n\nPayments\n\nDate: 01/07/2013\n\nAmount: $2,830.00\n\nBalance: $0\n\nDays: 365\n\nInterest: $0\n\n\n\n\nTotal repayments\n\n$2,830.00\n\nTotal interest\n\n$0\n\nTotal principal\n\n$2,830.00\n\nClosing balance\n\nDate: 30/06/2014\n\nBalance: $0",
  "outputs": {
    "enquiryRateFormatted": "6.2%",
    "enquiryYearEndMinusOneDisplay": "30/06/2013",
    "amalgamatedLoanNotPaidByEOIYFormatted": "$2,830.00",
    "openingBalancePayDays": "0",
    "openingBalanceInterestFormatted": "$0",
    "totalAmountOfRepaymentFormatted": "$2,830.00",
    "totalInterestFormatted": "$0",
    "principalFormatted": "$2,830.00",
    "enquiryYearEndDisplay": "30/06/2014",
    "minimumYearRepaymentFormatted": "$1,548.00"
  },
  "repayments": [
    {
      "rd": "1/7/2013",
      "ra": 2830
    }
  ],
  "inputs": {
    "incomeYearOfLoan": 2013,
    "fullTermOfAmalgamatedLoan": 2,
    "incomeYearOfEnquiring": 2014,
    "amalgamatedLoanNotPaidByEOIY": 2830,
    "repayments": null,
    "lodgement_date": "1/7/2013"
  },
  "idx": 2023
}