{
  "id": "2023-10-31T17:21:26.293Z0.43539208848332167",
  "alert": "Start of result\nResult\n\nMinimum yearly repayment met.\n\nThe amount of the loan not repaid at the end of income year 2021-22 is $5,177.19.\n\n\u000b\n\nThe amalgamated loan will not be taken to be a dividend because the total repayments made are equal to or greater than the minimum yearly repayment required for income year 2021-22.\n\nInterest received by the private company must be included in the income tax return for 2021-22.\n\nMinimum yearly repayment\n\n$2,818.00\n\nBenchmark interest rate\n\n4.52%\n\nOpening balance:\n\nDate: 30/06/2021\n\nBalance: $10,106.00\n\nDays: 103\n\nInterest: $128.90\n\nPayments\n\nDate: 12/10/2021\n\nAmount: $1,559.00\n\nBalance: $8,547.00\n\nDays: 31\n\nInterest: $32.81\n\n\n\n\nDate: 12/11/2021\n\nAmount: $3,671.00\n\nBalance: $4,876.00\n\nDays: 231\n\nInterest: $139.48\n\n\n\n\nTotal repayments\n\n$5,230.00\n\nTotal interest\n\n$301.19\n\nTotal principal\n\n$4,928.81\n\nClosing balance\n\nDate: 30/06/2022\n\nBalance: $5,177.19",
  "outputs": {
    "enquiryRateFormatted": "4.52%",
    "enquiryYearEndMinusOneDisplay": "30/06/2021",
    "amalgamatedLoanNotPaidByEOIYFormatted": "$10,106.00",
    "openingBalancePayDays": "103",
    "openingBalanceInterestFormatted": "$128.90",
    "totalAmountOfRepaymentFormatted": "$5,230.00",
    "totalInterestFormatted": "$301.19",
    "principalFormatted": "$4,928.81",
    "enquiryYearEndDisplay": "30/06/2022",
    "minimumYearRepaymentFormatted": "$2,818.00",
    "loanAmountFormatted": "$5,177.19"
  },
  "repayments": [
    {
      "rd": "12/10/2021",
      "ra": 1559
    },
    {
      "rd": "12/11/2021",
      "ra": 3671
    }
  ],
  "inputs": {
    "incomeYearOfLoan": 2019,
    "fullTermOfAmalgamatedLoan": 6,
    "incomeYearOfEnquiring": 2022,
    "amalgamatedLoanNotPaidByEOIY": 10106,
    "repayments": null,
    "lodgement_date": null
  },
  "idx": 1187
}