{
  "id": "2023-09-06T08:33:30.824Z0.9328393810362794",
  "alert": "Start of result\nResult\n\nMinimum yearly repayment met.\n\nThe amount of the loan not repaid at the end of income year 2010-11 is $1,138.95.\n\nThe amalgamated loan will not be taken to be a dividend because the total repayments made are equal to or greater than the minimum yearly repayment required for income year 2010-11.\n\nInterest received by the private company must be included in the income tax return for 2010-11.\n\nMinimum yearly repayment\n\n$206.00\n\nBenchmark interest rate\n\n7.4%\n\nOpening balance:\n\nDate: 30/06/2010\n\nBalance: $4,131.00\n\nDays: 150\n\nInterest: $125.63\n\nPayments\n\nDate: 28/11/2010\n\nAmount: $3,160.00\n\nBalance: $971.00\n\nDays: 215\n\nInterest: $42.32\n\n\n\n\nTotal repayments\n\n$3,160.00\n\nTotal interest\n\n$167.95\n\nTotal principal\n\n$2,992.05\n\nClosing balance\n\nDate: 30/06/2011\n\nBalance: $1,138.95",
  "outputs": {
    "enquiryRateFormatted": "7.4%",
    "enquiryYearEndMinusOneDisplay": "30/06/2010",
    "amalgamatedLoanNotPaidByEOIYFormatted": "$4,131.00",
    "openingBalancePayDays": "150",
    "openingBalanceInterestFormatted": "$125.63",
    "totalAmountOfRepaymentFormatted": "$3,160.00",
    "totalInterestFormatted": "$167.95",
    "principalFormatted": "$2,992.05",
    "enquiryYearEndDisplay": "30/06/2011",
    "minimumYearRepaymentFormatted": "$206.00"
  },
  "repayments": [
    {
      "rd": "28/11/2010",
      "ra": 3160
    }
  ],
  "inputs": {
    "incomeYearOfLoan": 2010,
    "fullTermOfAmalgamatedLoan": 6,
    "incomeYearOfEnquiring": 2011,
    "amalgamatedLoanNotPaidByEOIY": 4131,
    "repayments": null,
    "lodgement_date": "1/5/2011"
  },
  "idx": 3628
}