{
  "id": "2023-09-05T16:25:41.468Z0.9590888576977419",
  "alert": "Start of result\nResult\n\nMinimum yearly repayment not met.\n\nThe amount of the loan not repaid at the end of income year 2019-20 is $5,444.58.\n\nThe private company may be taken to pay a dividend under Division 7A to the shareholder or shareholder's associate because the amount repaid during income year 2019-20 in relation to the amalgamated loan is less than the minimum yearly repayment required.\n\nInterest received by the private company must be included in the income tax return for 2019-20.\n\nMinimum yearly repayment\n\n$4,480.00\n\nBenchmark interest rate\n\n5.37%\n\nOpening balance:\n\nDate: 30/06/2019\n\nBalance: $8,287.00\n\nDays: 149\n\nInterest: $181.17\n\nPayments\n\nDate: 27/11/2019\n\nAmount: $3,186.00\n\nBalance: $5,101.00\n\nDays: 217\n\nInterest: $162.41\n\n\n\n\nTotal repayments\n\n$3,186.00\n\nTotal interest\n\n$343.58\n\nTotal principal\n\n$2,842.42\n\nClosing balance\n\nDate: 30/06/2020\n\nBalance: $5,444.58",
  "outputs": {
    "enquiryRateFormatted": "5.37%",
    "enquiryYearEndMinusOneDisplay": "30/06/2019",
    "amalgamatedLoanNotPaidByEOIYFormatted": "$8,287.00",
    "openingBalancePayDays": "149",
    "openingBalanceInterestFormatted": "$181.17",
    "totalAmountOfRepaymentFormatted": "$3,186.00",
    "totalInterestFormatted": "$343.58",
    "principalFormatted": "$2,842.42",
    "enquiryYearEndDisplay": "30/06/2020",
    "minimumYearRepaymentFormatted": "$4,480.00"
  },
  "repayments": [
    {
      "rd": "27/11/2019",
      "ra": 3186
    }
  ],
  "inputs": {
    "incomeYearOfLoan": 2019,
    "fullTermOfAmalgamatedLoan": 2,
    "incomeYearOfEnquiring": 2020,
    "amalgamatedLoanNotPaidByEOIY": 8287,
    "repayments": null,
    "lodgement_date": "3/8/2019"
  },
  "idx": 402
}