{
  "id": "2023-10-31T17:50:51.405Z0.08804413929059585",
  "alert": "Start of result\nResult\n\nAmalgamated loan fully repaid.\n\nThe amalgamated loan has been paid in full.\u000bThe private company is not taken under Division 7A to pay a dividend to the shareholder or shareholder's associate.\n\nInterest received by the private company must be included in the income tax return for 2019-20.\n\nMinimum yearly repayment\n\n$87.00\n\nBenchmark interest rate\n\n5.37%\n\nOpening balance:\n\nDate: 30/06/2019\n\nBalance: $82.23\n\nDays: 126\n\nInterest: $1.52\n\nPayments\n\nDate: 04/11/2019\n\nAmount: $103.00\n\nBalance: $0\n\nDays: 42\n\nInterest: $0\n\n\n\n\nDate: 16/12/2019\n\nAmount: $719.35\n\nBalance: $0\n\nDays: 198\n\nInterest: $0\n\n\n\n\nTotal repayments\n\n$822.35\n\nTotal interest\n\n$1.52\n\nTotal principal\n\n$820.83\n\nClosing balance\n\nDate: 30/06/2020\n\nBalance: $0",
  "outputs": {
    "enquiryRateFormatted": "5.37%",
    "enquiryYearEndMinusOneDisplay": "30/06/2019",
    "amalgamatedLoanNotPaidByEOIYFormatted": "$82.23",
    "openingBalancePayDays": "126",
    "openingBalanceInterestFormatted": "$1.52",
    "totalAmountOfRepaymentFormatted": "$822.35",
    "totalInterestFormatted": "$1.52",
    "principalFormatted": "$820.83",
    "enquiryYearEndDisplay": "30/06/2020",
    "minimumYearRepaymentFormatted": "$87.00",
    "loanAmountFormatted": "$0"
  },
  "repayments": [
    {
      "rd": "4/11/2019",
      "ra": 103
    },
    {
      "rd": "16/12/2019",
      "ra": 719.3500847174437
    }
  ],
  "inputs": {
    "incomeYearOfLoan": 2014,
    "fullTermOfAmalgamatedLoan": 6,
    "incomeYearOfEnquiring": 2020,
    "amalgamatedLoanNotPaidByEOIY": 82.23500847174438,
    "repayments": null,
    "lodgement_date": null
  },
  "idx": 2727
}