{
  "id": "2023-11-01T00:34:35.232Z0.2569467874693092",
  "alert": "Start of result\nResult\n\nMinimum yearly repayment not met.\n\nThe amount of the loan not repaid at the end of income year 1999-00 is $38.09.\n\nThe private company may be taken to pay a dividend under Division 7A to the shareholder or shareholder's associate because the amount repaid during income year 1999-00 in relation to the amalgamated loan is less than the minimum yearly repayment required.\n\nInterest received by the private company must be included in the income tax return for 1999-00.\n\nMinimum yearly repayment\n\n$11.00\n\nBenchmark interest rate\n\n6.5%\n\nOpening balance:\n\nDate: 30/06/1999\n\nBalance: $38.09\n\nDays: 366\n\nInterest: $2.48\n\nTotal repayments\n\n$0\n\nTotal interest\n\n$2.48\n\nTotal principal\n\n$0\n\nClosing balance\n\nDate: 30/06/2000\n\nBalance: $38.09",
  "outputs": {
    "enquiryRateFormatted": "6.5%",
    "enquiryYearEndMinusOneDisplay": "30/06/1999",
    "amalgamatedLoanNotPaidByEOIYFormatted": "$38.09",
    "openingBalancePayDays": "366",
    "openingBalanceInterestFormatted": "$2.48",
    "totalAmountOfRepaymentFormatted": "$0",
    "totalInterestFormatted": "$2.48",
    "principalFormatted": "$0",
    "enquiryYearEndDisplay": "30/06/2000",
    "minimumYearRepaymentFormatted": "$11.00",
    "loanAmountFormatted": "$38.09"
  },
  "repayments": [],
  "inputs": {
    "incomeYearOfLoan": 1998,
    "fullTermOfAmalgamatedLoan": 5,
    "incomeYearOfEnquiring": 2000,
    "amalgamatedLoanNotPaidByEOIY": 38.093250075579626,
    "repayments": null,
    "lodgement_date": null
  },
  "idx": 0
}