{
  "id": "2023-10-31T17:36:52.432Z0.5947633510141949",
  "alert": "Start of result\nResult\n\nAmalgamated loan fully repaid.\n\nThe amalgamated loan has been paid in full.\u000bThe private company is not taken under Division 7A to pay a dividend to the shareholder or shareholder's associate.\n\nInterest received by the private company must be included in the income tax return for 2017-18.\n\nMinimum yearly repayment\n\n$1,083.00\n\nBenchmark interest rate\n\n5.3%\n\nOpening balance:\n\nDate: 30/06/2017\n\nBalance: $5,446.00\n\nDays: 284\n\nInterest: $224.58\n\nPayments\n\nDate: 11/04/2018\n\nAmount: $5,676.00\n\nBalance: $0\n\nDays: 81\n\nInterest: $0\n\n\n\n\nTotal repayments\n\n$5,676.00\n\nTotal interest\n\n$224.58\n\nTotal principal\n\n$5,451.42\n\nClosing balance\n\nDate: 30/06/2018\n\nBalance: $0",
  "outputs": {
    "enquiryRateFormatted": "5.3%",
    "enquiryYearEndMinusOneDisplay": "30/06/2017",
    "amalgamatedLoanNotPaidByEOIYFormatted": "$5,446.00",
    "openingBalancePayDays": "284",
    "openingBalanceInterestFormatted": "$224.58",
    "totalAmountOfRepaymentFormatted": "$5,676.00",
    "totalInterestFormatted": "$224.58",
    "principalFormatted": "$5,451.42",
    "enquiryYearEndDisplay": "30/06/2018",
    "minimumYearRepaymentFormatted": "$1,083.00",
    "loanAmountFormatted": "$0"
  },
  "repayments": [
    {
      "rd": "11/4/2018",
      "ra": 5676
    }
  ],
  "inputs": {
    "incomeYearOfLoan": 2016,
    "fullTermOfAmalgamatedLoan": 7,
    "incomeYearOfEnquiring": 2018,
    "amalgamatedLoanNotPaidByEOIY": 5446,
    "repayments": null,
    "lodgement_date": null
  },
  "idx": 2063
}