{
  "id": "2023-10-31T17:24:11.798Z0.7950261694446394",
  "alert": "Start of result\nResult\n\nAmalgamated loan fully repaid.\n\nThe amalgamated loan has been paid in full.\u000bThe private company is not taken under Division 7A to pay a dividend to the shareholder or shareholder's associate.\n\nInterest received by the private company must be included in the income tax return for 2019-20.\n\nMinimum yearly repayment\n\n$95.00\n\nBenchmark interest rate\n\n5.37%\n\nOpening balance:\n\nDate: 30/06/2019\n\nBalance: $257.00\n\nDays: 354\n\nInterest: $13.35\n\nPayments\n\nDate: 19/06/2020\n\nAmount: $1,074.00\n\nBalance: $0\n\nDays: 12\n\nInterest: $0\n\n\n\n\nTotal repayments\n\n$1,074.00\n\nTotal interest\n\n$13.35\n\nTotal principal\n\n$1,060.65\n\nClosing balance\n\nDate: 30/06/2020\n\nBalance: $0",
  "outputs": {
    "enquiryRateFormatted": "5.37%",
    "enquiryYearEndMinusOneDisplay": "30/06/2019",
    "amalgamatedLoanNotPaidByEOIYFormatted": "$257.00",
    "openingBalancePayDays": "354",
    "openingBalanceInterestFormatted": "$13.35",
    "totalAmountOfRepaymentFormatted": "$1,074.00",
    "totalInterestFormatted": "$13.35",
    "principalFormatted": "$1,060.65",
    "enquiryYearEndDisplay": "30/06/2020",
    "minimumYearRepaymentFormatted": "$95.00",
    "loanAmountFormatted": "$0"
  },
  "repayments": [
    {
      "rd": "19/6/2020",
      "ra": 1074
    }
  ],
  "inputs": {
    "incomeYearOfLoan": 2018,
    "fullTermOfAmalgamatedLoan": 4,
    "incomeYearOfEnquiring": 2020,
    "amalgamatedLoanNotPaidByEOIY": 257,
    "repayments": null,
    "lodgement_date": null
  },
  "idx": 1360
}