{
  "id": "2023-09-04T22:19:02.951Z0.2888541509347793",
  "alert": "Start of result\nResult\n\nAmalgamated loan fully repaid.\n\nThe amalgamated loan has been paid in full.\u000bThe private company is not taken under Division 7A to pay a dividend to the shareholder or shareholder's associate.\n\nInterest received by the private company must be included in the income tax return for 2001-02.\n\nMinimum yearly repayment\n\n$62.00\n\nBenchmark interest rate\n\n6.8%\n\nOpening balance:\n\nDate: 30/06/2001\n\nBalance: $297.00\n\nDays: 0\n\nInterest: $0\n\nPayments\n\nDate: 01/07/2001\n\nAmount: $297.00\n\nBalance: $0\n\nDays: 365\n\nInterest: $0\n\n\n\n\nTotal repayments\n\n$297.00\n\nTotal interest\n\n$0\n\nTotal principal\n\n$297.00\n\nClosing balance\n\nDate: 30/06/2002\n\nBalance: $0",
  "outputs": {
    "enquiryRateFormatted": "6.8%",
    "enquiryYearEndMinusOneDisplay": "30/06/2001",
    "amalgamatedLoanNotPaidByEOIYFormatted": "$297.00",
    "openingBalancePayDays": "0",
    "openingBalanceInterestFormatted": "$0",
    "totalAmountOfRepaymentFormatted": "$297.00",
    "totalInterestFormatted": "$0",
    "principalFormatted": "$297.00",
    "enquiryYearEndDisplay": "30/06/2002",
    "minimumYearRepaymentFormatted": "$62.00"
  },
  "repayments": [
    {
      "rd": "1/7/2001",
      "ra": 297
    }
  ],
  "inputs": {
    "incomeYearOfLoan": 2001,
    "fullTermOfAmalgamatedLoan": 6,
    "incomeYearOfEnquiring": 2002,
    "amalgamatedLoanNotPaidByEOIY": 297,
    "repayments": null,
    "lodgement_date": "1/7/2001"
  },
  "idx": 694
}