{
  "id": "2023-10-31T17:28:11.963Z0.08265339828107798",
  "alert": "Start of result\nResult\n\nMinimum yearly repayment not met.\n\nThe amount of the loan not repaid at the end of income year 2019-20 is $53.97.\n\nThe private company may be taken to pay a dividend under Division 7A to the shareholder or shareholder's associate because the amount repaid during income year 2019-20 in relation to the amalgamated loan is less than the minimum yearly repayment required.\n\nInterest received by the private company must be included in the income tax return for 2019-20.\n\nMinimum yearly repayment\n\n$29.00\n\nBenchmark interest rate\n\n5.37%\n\nOpening balance:\n\nDate: 30/06/2019\n\nBalance: $53.97\n\nDays: 366\n\nInterest: $2.90\n\nTotal repayments\n\n$0\n\nTotal interest\n\n$2.90\n\nTotal principal\n\n$0\n\nClosing balance\n\nDate: 30/06/2020\n\nBalance: $53.97",
  "outputs": {
    "enquiryRateFormatted": "5.37%",
    "enquiryYearEndMinusOneDisplay": "30/06/2019",
    "amalgamatedLoanNotPaidByEOIYFormatted": "$53.97",
    "openingBalancePayDays": "366",
    "openingBalanceInterestFormatted": "$2.90",
    "totalAmountOfRepaymentFormatted": "$0",
    "totalInterestFormatted": "$2.90",
    "principalFormatted": "$0",
    "enquiryYearEndDisplay": "30/06/2020",
    "minimumYearRepaymentFormatted": "$29.00",
    "loanAmountFormatted": "$53.97"
  },
  "repayments": [],
  "inputs": {
    "incomeYearOfLoan": 2017,
    "fullTermOfAmalgamatedLoan": 4,
    "incomeYearOfEnquiring": 2020,
    "amalgamatedLoanNotPaidByEOIY": 53.97719819075739,
    "repayments": null,
    "lodgement_date": null
  },
  "idx": 1598
}