{
  "id": "2023-10-31T19:58:52.921Z0.4675100267942338",
  "alert": "Start of result\nResult\n\nMinimum yearly repayment not met.\n\nThe amount of the loan not repaid at the end of income year 2004-05 is $39.20.\n\nThe private company may be taken to pay a dividend under Division 7A to the shareholder or shareholder's associate because the amount repaid during income year 2004-05 in relation to the amalgamated loan is less than the minimum yearly repayment required.\n\nInterest received by the private company must be included in the income tax return for 2004-05.\n\nMinimum yearly repayment\n\n$22.00\n\nBenchmark interest rate\n\n7.05%\n\nOpening balance:\n\nDate: 30/06/2004\n\nBalance: $39.20\n\nDays: 365\n\nInterest: $2.76\n\nTotal repayments\n\n$0\n\nTotal interest\n\n$2.76\n\nTotal principal\n\n$0\n\nClosing balance\n\nDate: 30/06/2005\n\nBalance: $39.20",
  "outputs": {
    "enquiryRateFormatted": "7.05%",
    "enquiryYearEndMinusOneDisplay": "30/06/2004",
    "amalgamatedLoanNotPaidByEOIYFormatted": "$39.20",
    "openingBalancePayDays": "365",
    "openingBalanceInterestFormatted": "$2.76",
    "totalAmountOfRepaymentFormatted": "$0",
    "totalInterestFormatted": "$2.76",
    "principalFormatted": "$0",
    "enquiryYearEndDisplay": "30/06/2005",
    "minimumYearRepaymentFormatted": "$22.00",
    "loanAmountFormatted": "$39.20"
  },
  "repayments": [],
  "inputs": {
    "incomeYearOfLoan": 2002,
    "fullTermOfAmalgamatedLoan": 4,
    "incomeYearOfEnquiring": 2005,
    "amalgamatedLoanNotPaidByEOIY": 39.20930836065202,
    "repayments": null,
    "lodgement_date": null
  },
  "idx": 6051
}