{
  "incomeYearOfLoan": 2023,
  "fullTermOfAmalgamatedLoan": 8,
  "incomeYearOfEnquiring": 2024,
  "amalgamatedLoanNotPaidByEOIY": 39842569.71998953,
  "repayments": [
    {
      "rd": "1/7/2023",
      "ra": 4361
    },
    {
      "rd": "20/10/2023",
      "ra": 9596
    }
  ],
  "lodgement_date_string": "17/1/2024",
  "id": "2023-09-03T22:02:17.078Z0.11217499237779627",
  "alert": "Start of result\nResult\n\nMinimum yearly repayment not met.\n\nThe amount of the loan not repaid at the end of income year 2023-24 is $39,842,569.71.\n\nThe private company may be taken to pay a dividend under Division 7A to the shareholder or shareholder's associate because the amount repaid during income year 2023-24 in relation to the amalgamated loan is less than the minimum yearly repayment required.\n\nInterest received by the private company must be included in the income tax return for 2023-24.\n\nMinimum yearly repayment\n\n$8,686,233.00\n\nBenchmark interest rate\n\n8.27%\n\nOpening balance:\n\nDate: 30/06/2023\n\nBalance: $39,842,569.71\n\nDays: 0\n\nInterest: $0\n\nPayments\n\nDate: 01/07/2023\n\nAmount: $4,361.00\n\nBalance: $39,838,208.71\n\nDays: 111\n\nInterest: $999,187.99\n\n\n\n\nDate: 20/10/2023\n\nAmount: $9,596.00\n\nBalance: $39,828,612.71\n\nDays: 255\n\nInterest: $2,294,878.96\n\n\n\n\nTotal repayments\n\n$13,957.00\n\nTotal interest\n\n$3,294,066.95\n\nTotal principal\n\n$0\n\nClosing balance\n\nDate: 30/06/2024\n\nBalance: $39,842,569.71",
  "enquiryRateFormatted": "8.27%",
  "enquiryYearEndMinusOneDisplay": "30/06/2023",
  "amalgamatedLoanNotPaidByEOIYFormatted": "$39,842,569.71",
  "openingBalancePayDays": "0",
  "openingBalanceInterestFormatted": "$0",
  "totalAmountOfRepaymentFormatted": "$13,957.00",
  "totalInterestFormatted": "$3,294,066.95",
  "principalFormatted": "$0",
  "enquiryYearEndDisplay": "30/06/2024",
  "minimumYearRepaymentFormatted": "$8,686,233.00"
}