{
  "id": "2023-11-01T00:35:31.651Z0.06912565489346434",
  "alert": "Start of result\nResult\n\nAmalgamated loan fully repaid.\n\nThe amalgamated loan has been paid in full.\u000bThe private company is not taken under Division 7A to pay a dividend to the shareholder or shareholder's associate.\n\nInterest received by the private company must be included in the income tax return for 2002-03.\n\nMinimum yearly repayment\n\n$36.00\n\nBenchmark interest rate\n\n6.3%\n\nOpening balance:\n\nDate: 30/06/2002\n\nBalance: $96.86\n\nDays: 277\n\nInterest: $4.63\n\nPayments\n\nDate: 04/04/2003\n\nAmount: $968.66\n\nBalance: $0\n\nDays: 88\n\nInterest: $0\n\n\n\n\nTotal repayments\n\n$968.66\n\nTotal interest\n\n$4.63\n\nTotal principal\n\n$964.03\n\nClosing balance\n\nDate: 30/06/2003\n\nBalance: $0",
  "outputs": {
    "enquiryRateFormatted": "6.3%",
    "enquiryYearEndMinusOneDisplay": "30/06/2002",
    "amalgamatedLoanNotPaidByEOIYFormatted": "$96.86",
    "openingBalancePayDays": "277",
    "openingBalanceInterestFormatted": "$4.63",
    "totalAmountOfRepaymentFormatted": "$968.66",
    "totalInterestFormatted": "$4.63",
    "principalFormatted": "$964.03",
    "enquiryYearEndDisplay": "30/06/2003",
    "minimumYearRepaymentFormatted": "$36.00",
    "loanAmountFormatted": "$0"
  },
  "repayments": [
    {
      "rd": "4/4/2003",
      "ra": 968.6613156547583
    }
  ],
  "inputs": {
    "incomeYearOfLoan": 1998,
    "fullTermOfAmalgamatedLoan": 7,
    "incomeYearOfEnquiring": 2003,
    "amalgamatedLoanNotPaidByEOIY": 96.86613156547584,
    "repayments": null,
    "lodgement_date": null
  },
  "idx": 79
}