{
  "id": "2023-09-04T16:19:59.874Z0.08786956830928516",
  "alert": "Start of result\nResult\n\nMinimum yearly repayment not met.\n\nThe amount of the loan not repaid at the end of income year 2020-21 is $96,528,932.84.\n\nThe private company may be taken to pay a dividend under Division 7A to the shareholder or shareholder's associate because the amount repaid during income year 2020-21 in relation to the amalgamated loan is less than the minimum yearly repayment required.\n\nInterest received by the private company must be included in the income tax return for 2020-21.\n\nMinimum yearly repayment\n\n$22,000,740.00\n\nBenchmark interest rate\n\n4.52%\n\nOpening balance:\n\nDate: 30/06/2020\n\nBalance: $96,528,932.84\n\nDays: 365\n\nInterest: $4,363,107.76\n\nTotal repayments\n\n$0\n\nTotal interest\n\n$4,363,107.76\n\nTotal principal\n\n$0\n\nClosing balance\n\nDate: 30/06/2021\n\nBalance: $96,528,932.84",
  "outputs": {
    "enquiryRateFormatted": "4.52%",
    "enquiryYearEndMinusOneDisplay": "30/06/2020",
    "amalgamatedLoanNotPaidByEOIYFormatted": "$96,528,932.84",
    "openingBalancePayDays": "365",
    "openingBalanceInterestFormatted": "$4,363,107.76",
    "totalAmountOfRepaymentFormatted": "$0",
    "totalInterestFormatted": "$4,363,107.76",
    "principalFormatted": "$0",
    "enquiryYearEndDisplay": "30/06/2021",
    "minimumYearRepaymentFormatted": "$22,000,740.00"
  },
  "repayments": [],
  "inputs": {
    "incomeYearOfLoan": 2020,
    "fullTermOfAmalgamatedLoan": 5,
    "incomeYearOfEnquiring": 2021,
    "amalgamatedLoanNotPaidByEOIY": 96528932.84743099,
    "repayments": null,
    "lodgement_date": "1/7/2020"
  },
  "idx": 287
}