{
  "id": "2023-09-06T06:58:53.458Z0.7132570181480389",
  "alert": "Start of result\nResult\n\nMinimum yearly repayment met.\n\nThe amount of the loan not repaid at the end of income year 2014-15 is $1,032.67.\n\nThe amalgamated loan will not be taken to be a dividend because the total repayments made are equal to or greater than the minimum yearly repayment required for income year 2014-15.\n\nInterest received by the private company must be included in the income tax return for 2014-15.\n\nMinimum yearly repayment\n\n$3,078.00\n\nBenchmark interest rate\n\n5.95%\n\nOpening balance:\n\nDate: 30/06/2014\n\nBalance: $10,677.00\n\nDays: 184\n\nInterest: $320.25\n\nPayments\n\nDate: 01/01/2015\n\nAmount: $9,985.00\n\nBalance: $692.00\n\nDays: 181\n\nInterest: $20.42\n\n\n\n\nTotal repayments\n\n$9,985.00\n\nTotal interest\n\n$340.67\n\nTotal principal\n\n$9,644.33\n\nClosing balance\n\nDate: 30/06/2015\n\nBalance: $1,032.67",
  "outputs": {
    "enquiryRateFormatted": "5.95%",
    "enquiryYearEndMinusOneDisplay": "30/06/2014",
    "amalgamatedLoanNotPaidByEOIYFormatted": "$10,677.00",
    "openingBalancePayDays": "184",
    "openingBalanceInterestFormatted": "$320.25",
    "totalAmountOfRepaymentFormatted": "$9,985.00",
    "totalInterestFormatted": "$340.67",
    "principalFormatted": "$9,644.33",
    "enquiryYearEndDisplay": "30/06/2015",
    "minimumYearRepaymentFormatted": "$3,078.00"
  },
  "repayments": [
    {
      "rd": "1/1/2015",
      "ra": 9985
    }
  ],
  "inputs": {
    "incomeYearOfLoan": 2011,
    "fullTermOfAmalgamatedLoan": 7,
    "incomeYearOfEnquiring": 2015,
    "amalgamatedLoanNotPaidByEOIY": 10677,
    "repayments": null,
    "lodgement_date": null
  },
  "idx": 7413
}