{
  "id": "2023-09-06T20:19:28.419Z0.011660192559411087",
  "alert": "Start of result\nResult\n\nMinimum yearly repayment met.\n\nThe amount of the loan not repaid at the end of income year 2006-07 is $382.86.\n\nThe amalgamated loan will not be taken to be a dividend because the total repayments made are equal to or greater than the minimum yearly repayment required for income year 2006-07.\n\nInterest received by the private company must be included in the income tax return for 2006-07.\n\nMinimum yearly repayment\n\n$3,514.00\n\nBenchmark interest rate\n\n7.55%\n\nOpening balance:\n\nDate: 30/06/2006\n\nBalance: $11,756.00\n\nDays: 134\n\nInterest: $325.85\n\nPayments\n\nDate: 12/11/2006\n\nAmount: $8,475.00\n\nBalance: $3,281.00\n\nDays: 84\n\nInterest: $57.01\n\n\n\n\nDate: 04/02/2007\n\nAmount: $3,281.00\n\nBalance: $0\n\nDays: 147\n\nInterest: $0\n\n\n\n\nTotal repayments\n\n$11,756.00\n\nTotal interest\n\n$382.86\n\nTotal principal\n\n$11,373.14\n\nClosing balance\n\nDate: 30/06/2007\n\nBalance: $382.86",
  "outputs": {
    "enquiryRateFormatted": "7.55%",
    "enquiryYearEndMinusOneDisplay": "30/06/2006",
    "amalgamatedLoanNotPaidByEOIYFormatted": "$11,756.00",
    "openingBalancePayDays": "134",
    "openingBalanceInterestFormatted": "$325.85",
    "totalAmountOfRepaymentFormatted": "$11,756.00",
    "totalInterestFormatted": "$382.86",
    "principalFormatted": "$11,373.14",
    "enquiryYearEndDisplay": "30/06/2007",
    "minimumYearRepaymentFormatted": "$3,514.00"
  },
  "repayments": [
    {
      "rd": "12/11/2006",
      "ra": 8475
    },
    {
      "rd": "4/2/2007",
      "ra": 3281
    }
  ],
  "inputs": {
    "incomeYearOfLoan": 2003,
    "fullTermOfAmalgamatedLoan": 7,
    "incomeYearOfEnquiring": 2007,
    "amalgamatedLoanNotPaidByEOIY": 11756,
    "repayments": null,
    "lodgement_date": null
  },
  "idx": 1486
}