{
  "id": "2023-09-06T14:55:40.133Z0.1580947097808425",
  "alert": "Start of result\nResult\n\nMinimum yearly repayment met.\n\nThe amount of the loan not repaid at the end of income year 2008-09 is $7.49.\n\nThe amalgamated loan will not be taken to be a dividend because the total repayments made are equal to or greater than the minimum yearly repayment required for income year 2008-09.\n\nInterest received by the private company must be included in the income tax return for 2008-09.\n\nMinimum yearly repayment\n\n$31.00\n\nBenchmark interest rate\n\n9.45%\n\nOpening balance:\n\nDate: 30/06/2008\n\nBalance: $98.41\n\nDays: 294\n\nInterest: $7.49\n\nPayments\n\nDate: 21/04/2009\n\nAmount: $98.41\n\nBalance: $0\n\nDays: 71\n\nInterest: $0\n\n\n\n\nTotal repayments\n\n$98.41\n\nTotal interest\n\n$7.49\n\nTotal principal\n\n$90.92\n\nClosing balance\n\nDate: 30/06/2009\n\nBalance: $7.49",
  "outputs": {
    "enquiryRateFormatted": "9.45%",
    "enquiryYearEndMinusOneDisplay": "30/06/2008",
    "amalgamatedLoanNotPaidByEOIYFormatted": "$98.41",
    "openingBalancePayDays": "294",
    "openingBalanceInterestFormatted": "$7.49",
    "totalAmountOfRepaymentFormatted": "$98.41",
    "totalInterestFormatted": "$7.49",
    "principalFormatted": "$90.92",
    "enquiryYearEndDisplay": "30/06/2009",
    "minimumYearRepaymentFormatted": "$31.00"
  },
  "repayments": [
    {
      "rd": "21/4/2009",
      "ra": 98.4175291063566
    }
  ],
  "inputs": {
    "incomeYearOfLoan": 2006,
    "fullTermOfAmalgamatedLoan": 6,
    "incomeYearOfEnquiring": 2009,
    "amalgamatedLoanNotPaidByEOIY": 98.41752910635681,
    "repayments": null,
    "lodgement_date": null
  },
  "idx": 7023
}