{
  "id": "2023-09-04T22:02:07.908Z0.9935502851856086",
  "alert": "Start of result\nResult\n\nMinimum yearly repayment not met.\n\nThe amount of the loan not repaid at the end of income year 2005-06 is $24,799,044.63.\n\nThe private company may be taken to pay a dividend under Division 7A to the shareholder or shareholder's associate because the amount repaid during income year 2005-06 in relation to the amalgamated loan is less than the minimum yearly repayment required.\n\nInterest received by the private company must be included in the income tax return for 2005-06.\n\nMinimum yearly repayment\n\n$9,501,557.00\n\nBenchmark interest rate\n\n7.3%\n\nOpening balance:\n\nDate: 30/06/2005\n\nBalance: $24,799,044.63\n\nDays: 0\n\nInterest: $0\n\nPayments\n\nDate: 01/07/2005\n\nAmount: $2,305.00\n\nBalance: $24,796,739.63\n\nDays: 365\n\nInterest: $1,810,161.99\n\n\n\n\nTotal repayments\n\n$2,305.00\n\nTotal interest\n\n$1,810,161.99\n\nTotal principal\n\n$0\n\nClosing balance\n\nDate: 30/06/2006\n\nBalance: $24,799,044.63",
  "outputs": {
    "enquiryRateFormatted": "7.3%",
    "enquiryYearEndMinusOneDisplay": "30/06/2005",
    "amalgamatedLoanNotPaidByEOIYFormatted": "$24,799,044.63",
    "openingBalancePayDays": "0",
    "openingBalanceInterestFormatted": "$0",
    "totalAmountOfRepaymentFormatted": "$2,305.00",
    "totalInterestFormatted": "$1,810,161.99",
    "principalFormatted": "$0",
    "enquiryYearEndDisplay": "30/06/2006",
    "minimumYearRepaymentFormatted": "$9,501,557.00"
  },
  "repayments": [
    {
      "rd": "1/7/2005",
      "ra": 2305
    }
  ],
  "inputs": {
    "incomeYearOfLoan": 2004,
    "fullTermOfAmalgamatedLoan": 4,
    "incomeYearOfEnquiring": 2006,
    "amalgamatedLoanNotPaidByEOIY": 24799044.632271666,
    "repayments": null,
    "lodgement_date": null
  },
  "idx": 49
}