{
  "id": "2023-09-05T18:13:50.545Z0.6674866198685874",
  "alert": "Start of result\nResult\n\nMinimum yearly repayment not met.\n\nThe amount of the loan not repaid at the end of income year 2019-20 is $4,577.00.\n\nThe private company may be taken to pay a dividend under Division 7A to the shareholder or shareholder's associate because the amount repaid during income year 2019-20 in relation to the amalgamated loan is less than the minimum yearly repayment required.\n\nInterest received by the private company must be included in the income tax return for 2019-20.\n\nMinimum yearly repayment\n\n$1,692.00\n\nBenchmark interest rate\n\n5.37%\n\nOpening balance:\n\nDate: 30/06/2019\n\nBalance: $4,577.00\n\nDays: 53\n\nInterest: $35.59\n\nPayments\n\nDate: 23/08/2019\n\nAmount: $176.00\n\nBalance: $4,401.00\n\nDays: 313\n\nInterest: $202.11\n\n\n\n\nTotal repayments\n\n$176.00\n\nTotal interest\n\n$237.70\n\nTotal principal\n\n$0\n\nClosing balance\n\nDate: 30/06/2020\n\nBalance: $4,577.00",
  "outputs": {
    "enquiryRateFormatted": "5.37%",
    "enquiryYearEndMinusOneDisplay": "30/06/2019",
    "amalgamatedLoanNotPaidByEOIYFormatted": "$4,577.00",
    "openingBalancePayDays": "53",
    "openingBalanceInterestFormatted": "$35.59",
    "totalAmountOfRepaymentFormatted": "$176.00",
    "totalInterestFormatted": "$237.70",
    "principalFormatted": "$0",
    "enquiryYearEndDisplay": "30/06/2020",
    "minimumYearRepaymentFormatted": "$1,692.00"
  },
  "repayments": [
    {
      "rd": "23/8/2019",
      "ra": 176
    }
  ],
  "inputs": {
    "incomeYearOfLoan": 2018,
    "fullTermOfAmalgamatedLoan": 4,
    "incomeYearOfEnquiring": 2020,
    "amalgamatedLoanNotPaidByEOIY": 4577,
    "repayments": null,
    "lodgement_date": null
  },
  "idx": 7018
}