{
  "id": "2023-10-31T17:30:24.909Z0.8496433897509168",
  "alert": "Start of result\nResult\n\nAmalgamated loan fully repaid.\n\nThe amalgamated loan has been paid in full.\u000bThe private company is not taken under Division 7A to pay a dividend to the shareholder or shareholder's associate.\n\nInterest received by the private company must be included in the income tax return for 2022-23.\n\nMinimum yearly repayment\n\n$58.00\n\nBenchmark interest rate\n\n4.77%\n\nOpening balance:\n\nDate: 30/06/2022\n\nBalance: $109.00\n\nDays: 278\n\nInterest: $3.96\n\nPayments\n\nDate: 05/04/2023\n\nAmount: $1,090.00\n\nBalance: $0\n\nDays: 87\n\nInterest: $0\n\n\n\n\nTotal repayments\n\n$1,090.00\n\nTotal interest\n\n$3.96\n\nTotal principal\n\n$1,086.04\n\nClosing balance\n\nDate: 30/06/2023\n\nBalance: $0",
  "outputs": {
    "enquiryRateFormatted": "4.77%",
    "enquiryYearEndMinusOneDisplay": "30/06/2022",
    "amalgamatedLoanNotPaidByEOIYFormatted": "$109.00",
    "openingBalancePayDays": "278",
    "openingBalanceInterestFormatted": "$3.96",
    "totalAmountOfRepaymentFormatted": "$1,090.00",
    "totalInterestFormatted": "$3.96",
    "principalFormatted": "$1,086.04",
    "enquiryYearEndDisplay": "30/06/2023",
    "minimumYearRepaymentFormatted": "$58.00",
    "loanAmountFormatted": "$0"
  },
  "repayments": [
    {
      "rd": "5/4/2023",
      "ra": 1090
    }
  ],
  "inputs": {
    "incomeYearOfLoan": 2017,
    "fullTermOfAmalgamatedLoan": 7,
    "incomeYearOfEnquiring": 2023,
    "amalgamatedLoanNotPaidByEOIY": 109,
    "repayments": null,
    "lodgement_date": null
  },
  "idx": 1715
}