{
  "id": "2023-09-06T10:42:15.398Z0.40247665804874644",
  "alert": "Start of result\nResult\n\nMinimum yearly repayment met.\n\nThe amount of the loan not repaid at the end of income year 2009-10 is $161.36.\n\nThe amalgamated loan will not be taken to be a dividend because the total repayments made are equal to or greater than the minimum yearly repayment required for income year 2009-10.\n\nInterest received by the private company must be included in the income tax return for 2009-10.\n\nMinimum yearly repayment\n\n$0\n\nBenchmark interest rate\n\n5.75%\n\nOpening balance:\n\nDate: 30/06/2009\n\nBalance: $3,181.00\n\nDays: 322\n\nInterest: $161.36\n\nPayments\n\nDate: 19/05/2010\n\nAmount: $3,181.00\n\nBalance: $0\n\nDays: 43\n\nInterest: $0\n\n\n\n\nTotal repayments\n\n$3,181.00\n\nTotal interest\n\n$161.36\n\nTotal principal\n\n$3,019.64\n\nClosing balance\n\nDate: 30/06/2010\n\nBalance: $161.36",
  "outputs": {
    "enquiryRateFormatted": "5.75%",
    "enquiryYearEndMinusOneDisplay": "30/06/2009",
    "amalgamatedLoanNotPaidByEOIYFormatted": "$3,181.00",
    "openingBalancePayDays": "322",
    "openingBalanceInterestFormatted": "$161.36",
    "totalAmountOfRepaymentFormatted": "$3,181.00",
    "totalInterestFormatted": "$161.36",
    "principalFormatted": "$3,019.64",
    "enquiryYearEndDisplay": "30/06/2010",
    "minimumYearRepaymentFormatted": "$0"
  },
  "repayments": [
    {
      "rd": "19/5/2010",
      "ra": 3181
    }
  ],
  "inputs": {
    "incomeYearOfLoan": 2009,
    "fullTermOfAmalgamatedLoan": 7,
    "incomeYearOfEnquiring": 2010,
    "amalgamatedLoanNotPaidByEOIY": 3181,
    "repayments": null,
    "lodgement_date": "11/6/2010"
  },
  "idx": 1455
}