{
  "id": "2023-10-31T17:33:00.964Z0.05239179399825844",
  "alert": "Start of result\nResult\n\nAmalgamated loan fully repaid.\n\nThe amalgamated loan has been paid in full.\u000bThe private company is not taken under Division 7A to pay a dividend to the shareholder or shareholder's associate.\n\nInterest received by the private company must be included in the income tax return for 2017-18.\n\nMinimum yearly repayment\n\n$9,464.00\n\nBenchmark interest rate\n\n5.3%\n\nOpening balance:\n\nDate: 30/06/2017\n\nBalance: $8,988.00\n\nDays: 315\n\nInterest: $411.11\n\nPayments\n\nDate: 12/05/2018\n\nAmount: $9,493.00\n\nBalance: $0\n\nDays: 50\n\nInterest: $0\n\n\n\n\nTotal repayments\n\n$9,493.00\n\nTotal interest\n\n$411.11\n\nTotal principal\n\n$9,081.89\n\nClosing balance\n\nDate: 30/06/2018\n\nBalance: $0",
  "outputs": {
    "enquiryRateFormatted": "5.3%",
    "enquiryYearEndMinusOneDisplay": "30/06/2017",
    "amalgamatedLoanNotPaidByEOIYFormatted": "$8,988.00",
    "openingBalancePayDays": "315",
    "openingBalanceInterestFormatted": "$411.11",
    "totalAmountOfRepaymentFormatted": "$9,493.00",
    "totalInterestFormatted": "$411.11",
    "principalFormatted": "$9,081.89",
    "enquiryYearEndDisplay": "30/06/2018",
    "minimumYearRepaymentFormatted": "$9,464.00",
    "loanAmountFormatted": "$0"
  },
  "repayments": [
    {
      "rd": "12/5/2018",
      "ra": 9493
    }
  ],
  "inputs": {
    "incomeYearOfLoan": 2016,
    "fullTermOfAmalgamatedLoan": 2,
    "incomeYearOfEnquiring": 2018,
    "amalgamatedLoanNotPaidByEOIY": 8988,
    "repayments": null,
    "lodgement_date": null
  },
  "idx": 1865
}