{
  "id": "2023-09-04T16:38:06.159Z0.7381793673316062",
  "alert": "Start of result\nResult\n\nMinimum yearly repayment not met.\n\nThe amount of the loan not repaid at the end of income year 2016-17 is $30,994,979.14.\n\nThe private company may be taken to pay a dividend under Division 7A to the shareholder or shareholder's associate because the amount repaid during income year 2016-17 in relation to the amalgamated loan is less than the minimum yearly repayment required.\n\nInterest received by the private company must be included in the income tax return for 2016-17.\n\nMinimum yearly repayment\n\n$32,668,708.00\n\nBenchmark interest rate\n\n5.4%\n\nOpening balance:\n\nDate: 30/06/2016\n\nBalance: $30,994,979.14\n\nDays: 365\n\nInterest: $1,673,728.87\n\nTotal repayments\n\n$0\n\nTotal interest\n\n$1,673,728.87\n\nTotal principal\n\n$0\n\nClosing balance\n\nDate: 30/06/2017\n\nBalance: $30,994,979.14",
  "outputs": {
    "enquiryRateFormatted": "5.4%",
    "enquiryYearEndMinusOneDisplay": "30/06/2016",
    "amalgamatedLoanNotPaidByEOIYFormatted": "$30,994,979.14",
    "openingBalancePayDays": "365",
    "openingBalanceInterestFormatted": "$1,673,728.87",
    "totalAmountOfRepaymentFormatted": "$0",
    "totalInterestFormatted": "$1,673,728.87",
    "principalFormatted": "$0",
    "enquiryYearEndDisplay": "30/06/2017",
    "minimumYearRepaymentFormatted": "$32,668,708.00"
  },
  "repayments": [],
  "inputs": {
    "incomeYearOfLoan": 2016,
    "fullTermOfAmalgamatedLoan": 1,
    "incomeYearOfEnquiring": 2017,
    "amalgamatedLoanNotPaidByEOIY": 30994979.14028745,
    "repayments": null,
    "lodgement_date": "30/6/2017"
  },
  "idx": 897
}