{
  "id": "2023-09-06T01:36:40.468Z0.8296167589288586",
  "alert": "Start of result\nResult\n\nMinimum yearly repayment met.\n\nThe amount of the loan not repaid at the end of income year 2016-17 is $92.45.\n\nThe amalgamated loan will not be taken to be a dividend because the total repayments made are equal to or greater than the minimum yearly repayment required for income year 2016-17.\n\nInterest received by the private company must be included in the income tax return for 2016-17.\n\nMinimum yearly repayment\n\n$1,016.00\n\nBenchmark interest rate\n\n5.4%\n\nOpening balance:\n\nDate: 30/06/2016\n\nBalance: $3,571.00\n\nDays: 175\n\nInterest: $92.45\n\nPayments\n\nDate: 23/12/2016\n\nAmount: $3,571.00\n\nBalance: $0\n\nDays: 190\n\nInterest: $0\n\n\n\n\nTotal repayments\n\n$3,571.00\n\nTotal interest\n\n$92.45\n\nTotal principal\n\n$3,478.55\n\nClosing balance\n\nDate: 30/06/2017\n\nBalance: $92.45",
  "outputs": {
    "enquiryRateFormatted": "5.4%",
    "enquiryYearEndMinusOneDisplay": "30/06/2016",
    "amalgamatedLoanNotPaidByEOIYFormatted": "$3,571.00",
    "openingBalancePayDays": "175",
    "openingBalanceInterestFormatted": "$92.45",
    "totalAmountOfRepaymentFormatted": "$3,571.00",
    "totalInterestFormatted": "$92.45",
    "principalFormatted": "$3,478.55",
    "enquiryYearEndDisplay": "30/06/2017",
    "minimumYearRepaymentFormatted": "$1,016.00"
  },
  "repayments": [
    {
      "rd": "23/12/2016",
      "ra": 3571
    }
  ],
  "inputs": {
    "incomeYearOfLoan": 2014,
    "fullTermOfAmalgamatedLoan": 6,
    "incomeYearOfEnquiring": 2017,
    "amalgamatedLoanNotPaidByEOIY": 3571,
    "repayments": null,
    "lodgement_date": null
  },
  "idx": 7021
}