{
  "id": "2023-10-31T20:00:48.596Z0.007090170346993663",
  "alert": "Start of result\nResult\n\nAmalgamated loan fully repaid.\n\nThe amalgamated loan has been paid in full.\u000bThe private company is not taken under Division 7A to pay a dividend to the shareholder or shareholder's associate.\n\nInterest received by the private company must be included in the income tax return for 2006-07.\n\nMinimum yearly repayment\n\n$556.00\n\nBenchmark interest rate\n\n7.55%\n\nOpening balance:\n\nDate: 30/06/2006\n\nBalance: $517.00\n\nDays: 121\n\nInterest: $12.94\n\nPayments\n\nDate: 30/10/2006\n\nAmount: $905.00\n\nBalance: $0\n\nDays: 244\n\nInterest: $0\n\n\n\n\nTotal repayments\n\n$905.00\n\nTotal interest\n\n$12.94\n\nTotal principal\n\n$892.06\n\nClosing balance\n\nDate: 30/06/2007\n\nBalance: $0",
  "outputs": {
    "enquiryRateFormatted": "7.55%",
    "enquiryYearEndMinusOneDisplay": "30/06/2006",
    "amalgamatedLoanNotPaidByEOIYFormatted": "$517.00",
    "openingBalancePayDays": "121",
    "openingBalanceInterestFormatted": "$12.94",
    "totalAmountOfRepaymentFormatted": "$905.00",
    "totalInterestFormatted": "$12.94",
    "principalFormatted": "$892.06",
    "enquiryYearEndDisplay": "30/06/2007",
    "minimumYearRepaymentFormatted": "$556.00",
    "loanAmountFormatted": "$0"
  },
  "repayments": [
    {
      "rd": "30/10/2006",
      "ra": 905
    }
  ],
  "inputs": {
    "incomeYearOfLoan": 2002,
    "fullTermOfAmalgamatedLoan": 5,
    "incomeYearOfEnquiring": 2007,
    "amalgamatedLoanNotPaidByEOIY": 517,
    "repayments": null,
    "lodgement_date": null
  },
  "idx": 6084
}