{
  "id": "2023-10-31T18:26:53.382Z0.5599582638611788",
  "alert": "Start of result\nResult\n\nAmalgamated loan fully repaid.\n\nThe amalgamated loan has been paid in full.\u000bThe private company is not taken under Division 7A to pay a dividend to the shareholder or shareholder's associate.\n\nInterest received by the private company must be included in the income tax return for 2009-10.\n\nMinimum yearly repayment\n\n$34.00\n\nBenchmark interest rate\n\n5.75%\n\nOpening balance:\n\nDate: 30/06/2009\n\nBalance: $32.02\n\nDays: 317\n\nInterest: $1.60\n\nPayments\n\nDate: 14/05/2010\n\nAmount: $320.21\n\nBalance: $0\n\nDays: 48\n\nInterest: $0\n\n\n\n\nTotal repayments\n\n$320.21\n\nTotal interest\n\n$1.60\n\nTotal principal\n\n$318.61\n\nClosing balance\n\nDate: 30/06/2010\n\nBalance: $0",
  "outputs": {
    "enquiryRateFormatted": "5.75%",
    "enquiryYearEndMinusOneDisplay": "30/06/2009",
    "amalgamatedLoanNotPaidByEOIYFormatted": "$32.02",
    "openingBalancePayDays": "317",
    "openingBalanceInterestFormatted": "$1.60",
    "totalAmountOfRepaymentFormatted": "$320.21",
    "totalInterestFormatted": "$1.60",
    "principalFormatted": "$318.61",
    "enquiryYearEndDisplay": "30/06/2010",
    "minimumYearRepaymentFormatted": "$34.00",
    "loanAmountFormatted": "$0"
  },
  "repayments": [
    {
      "rd": "14/5/2010",
      "ra": 320.2177115039515
    }
  ],
  "inputs": {
    "incomeYearOfLoan": 2009,
    "fullTermOfAmalgamatedLoan": 1,
    "incomeYearOfEnquiring": 2010,
    "amalgamatedLoanNotPaidByEOIY": 32.02177115039515,
    "repayments": null,
    "lodgement_date": "27/1/2010"
  },
  "idx": 3991
}