{
  "id": "2023-09-06T14:08:36.074Z0.966216454454633",
  "alert": "Start of result\nResult\n\nMinimum yearly repayment not met.\n\nThe amount of the loan not repaid at the end of income year 2008-09 is $2,887.77.\n\nThe private company may be taken to pay a dividend under Division 7A to the shareholder or shareholder's associate because the amount repaid during income year 2008-09 in relation to the amalgamated loan is less than the minimum yearly repayment required.\n\nInterest received by the private company must be included in the income tax return for 2008-09.\n\nMinimum yearly repayment\n\n$4,383.00\n\nBenchmark interest rate\n\n9.45%\n\nOpening balance:\n\nDate: 30/06/2008\n\nBalance: $4,005.00\n\nDays: 246\n\nInterest: $255.08\n\nPayments\n\nDate: 04/03/2009\n\nAmount: $1,451.00\n\nBalance: $2,554.00\n\nDays: 119\n\nInterest: $78.69\n\n\n\n\nTotal repayments\n\n$1,451.00\n\nTotal interest\n\n$333.77\n\nTotal principal\n\n$1,117.23\n\nClosing balance\n\nDate: 30/06/2009\n\nBalance: $2,887.77",
  "outputs": {
    "enquiryRateFormatted": "9.45%",
    "enquiryYearEndMinusOneDisplay": "30/06/2008",
    "amalgamatedLoanNotPaidByEOIYFormatted": "$4,005.00",
    "openingBalancePayDays": "246",
    "openingBalanceInterestFormatted": "$255.08",
    "totalAmountOfRepaymentFormatted": "$1,451.00",
    "totalInterestFormatted": "$333.77",
    "principalFormatted": "$1,117.23",
    "enquiryYearEndDisplay": "30/06/2009",
    "minimumYearRepaymentFormatted": "$4,383.00"
  },
  "repayments": [
    {
      "rd": "4/3/2009",
      "ra": 1451
    }
  ],
  "inputs": {
    "incomeYearOfLoan": 2006,
    "fullTermOfAmalgamatedLoan": 3,
    "incomeYearOfEnquiring": 2009,
    "amalgamatedLoanNotPaidByEOIY": 4005,
    "repayments": null,
    "lodgement_date": null
  },
  "idx": 4435
}