{
  "id": "2023-09-06T12:37:51.312Z0.829108282282607",
  "alert": "Start of result\nResult\n\nMinimum yearly repayment not met.\n\nThe amount of the loan not repaid at the end of income year 2009-10 is $107.47.\n\nThe private company may be taken to pay a dividend under Division 7A to the shareholder or shareholder's associate because the amount repaid during income year 2009-10 in relation to the amalgamated loan is less than the minimum yearly repayment required.\n\nInterest received by the private company must be included in the income tax return for 2009-10.\n\nMinimum yearly repayment\n\n$114.00\n\nBenchmark interest rate\n\n5.75%\n\nOpening balance:\n\nDate: 30/06/2009\n\nBalance: $107.47\n\nDays: 365\n\nInterest: $6.18\n\nTotal repayments\n\n$0\n\nTotal interest\n\n$6.18\n\nTotal principal\n\n$0\n\nClosing balance\n\nDate: 30/06/2010\n\nBalance: $107.47",
  "outputs": {
    "enquiryRateFormatted": "5.75%",
    "enquiryYearEndMinusOneDisplay": "30/06/2009",
    "amalgamatedLoanNotPaidByEOIYFormatted": "$107.47",
    "openingBalancePayDays": "365",
    "openingBalanceInterestFormatted": "$6.18",
    "totalAmountOfRepaymentFormatted": "$0",
    "totalInterestFormatted": "$6.18",
    "principalFormatted": "$0",
    "enquiryYearEndDisplay": "30/06/2010",
    "minimumYearRepaymentFormatted": "$114.00"
  },
  "repayments": [],
  "inputs": {
    "incomeYearOfLoan": 2007,
    "fullTermOfAmalgamatedLoan": 3,
    "incomeYearOfEnquiring": 2010,
    "amalgamatedLoanNotPaidByEOIY": 107.47126239077038,
    "repayments": null,
    "lodgement_date": null
  },
  "idx": 8117
}