{
  "id": "2023-09-06T21:31:42.150Z0.6347988946468164",
  "alert": "Start of result\nResult\n\nMinimum yearly repayment not met.\n\nThe amount of the loan not repaid at the end of income year 2003-04 is $2.19.\n\nThe private company may be taken to pay a dividend under Division 7A to the shareholder or shareholder's associate because the amount repaid during income year 2003-04 in relation to the amalgamated loan is less than the minimum yearly repayment required.\n\nInterest received by the private company must be included in the income tax return for 2003-04.\n\nMinimum yearly repayment\n\n$1.00\n\nBenchmark interest rate\n\n6.55%\n\nOpening balance:\n\nDate: 30/06/2003\n\nBalance: $2.19\n\nDays: 366\n\nInterest: $0.14\n\nTotal repayments\n\n$0\n\nTotal interest\n\n$0.14\n\nTotal principal\n\n$0\n\nClosing balance\n\nDate: 30/06/2004\n\nBalance: $2.19",
  "outputs": {
    "enquiryRateFormatted": "6.55%",
    "enquiryYearEndMinusOneDisplay": "30/06/2003",
    "amalgamatedLoanNotPaidByEOIYFormatted": "$2.19",
    "openingBalancePayDays": "366",
    "openingBalanceInterestFormatted": "$0.14",
    "totalAmountOfRepaymentFormatted": "$0",
    "totalInterestFormatted": "$0.14",
    "principalFormatted": "$0",
    "enquiryYearEndDisplay": "30/06/2004",
    "minimumYearRepaymentFormatted": "$1.00"
  },
  "repayments": [],
  "inputs": {
    "incomeYearOfLoan": 2002,
    "fullTermOfAmalgamatedLoan": 6,
    "incomeYearOfEnquiring": 2004,
    "amalgamatedLoanNotPaidByEOIY": 2.1909450660704177,
    "repayments": null,
    "lodgement_date": null
  },
  "idx": 5918
}