{
  "id": "2023-10-31T17:13:36.341Z0.7612105341361234",
  "alert": "Start of result\nResult\n\nMinimum yearly repayment not met.\n\nThe amount of the loan not repaid at the end of income year 2021-22 is $2,904.05.\n\nThe private company may be taken to pay a dividend under Division 7A to the shareholder or shareholder's associate because the amount repaid during income year 2021-22 in relation to the amalgamated loan is less than the minimum yearly repayment required.\n\nInterest received by the private company must be included in the income tax return for 2021-22.\n\nMinimum yearly repayment\n\n$659.00\n\nBenchmark interest rate\n\n4.52%\n\nOpening balance:\n\nDate: 30/06/2021\n\nBalance: $3,399.00\n\nDays: 231\n\nInterest: $97.23\n\nPayments\n\nDate: 17/02/2022\n\nAmount: $638.00\n\nBalance: $2,761.00\n\nDays: 134\n\nInterest: $45.82\n\n\n\n\nTotal repayments\n\n$638.00\n\nTotal interest\n\n$143.05\n\nTotal principal\n\n$494.95\n\nClosing balance\n\nDate: 30/06/2022\n\nBalance: $2,904.05",
  "outputs": {
    "enquiryRateFormatted": "4.52%",
    "enquiryYearEndMinusOneDisplay": "30/06/2021",
    "amalgamatedLoanNotPaidByEOIYFormatted": "$3,399.00",
    "openingBalancePayDays": "231",
    "openingBalanceInterestFormatted": "$97.23",
    "totalAmountOfRepaymentFormatted": "$638.00",
    "totalInterestFormatted": "$143.05",
    "principalFormatted": "$494.95",
    "enquiryYearEndDisplay": "30/06/2022",
    "minimumYearRepaymentFormatted": "$659.00",
    "loanAmountFormatted": "$2,904.05"
  },
  "repayments": [
    {
      "rd": "17/2/2022",
      "ra": 638
    }
  ],
  "inputs": {
    "incomeYearOfLoan": 2021,
    "fullTermOfAmalgamatedLoan": 6,
    "incomeYearOfEnquiring": 2022,
    "amalgamatedLoanNotPaidByEOIY": 3399,
    "repayments": null,
    "lodgement_date": "27/1/2022"
  },
  "idx": 608
}