{
  "id": "2023-10-31T18:55:23.341Z0.7552642050944816",
  "alert": "Start of result\nResult\n\nMinimum yearly repayment not met.\n\nThe amount of the loan not repaid at the end of income year 2013-14 is $2,161.13.\n\nThe private company may be taken to pay a dividend under Division 7A to the shareholder or shareholder's associate because the amount repaid during income year 2013-14 in relation to the amalgamated loan is less than the minimum yearly repayment required.\n\nInterest received by the private company must be included in the income tax return for 2013-14.\n\nMinimum yearly repayment\n\n$11,080.00\n\nBenchmark interest rate\n\n6.2%\n\nOpening balance:\n\nDate: 30/06/2013\n\nBalance: $10,433.00\n\nDays: 332\n\nInterest: $588.36\n\nPayments\n\nDate: 29/05/2014\n\nAmount: $8,869.00\n\nBalance: $1,564.00\n\nDays: 33\n\nInterest: $8.77\n\n\n\n\nTotal repayments\n\n$8,869.00\n\nTotal interest\n\n$597.13\n\nTotal principal\n\n$8,271.87\n\nClosing balance\n\nDate: 30/06/2014\n\nBalance: $2,161.13",
  "outputs": {
    "enquiryRateFormatted": "6.2%",
    "enquiryYearEndMinusOneDisplay": "30/06/2013",
    "amalgamatedLoanNotPaidByEOIYFormatted": "$10,433.00",
    "openingBalancePayDays": "332",
    "openingBalanceInterestFormatted": "$588.36",
    "totalAmountOfRepaymentFormatted": "$8,869.00",
    "totalInterestFormatted": "$597.13",
    "principalFormatted": "$8,271.87",
    "enquiryYearEndDisplay": "30/06/2014",
    "minimumYearRepaymentFormatted": "$11,080.00",
    "loanAmountFormatted": "$2,161.13"
  },
  "repayments": [
    {
      "rd": "29/5/2014",
      "ra": 8869
    }
  ],
  "inputs": {
    "incomeYearOfLoan": 2007,
    "fullTermOfAmalgamatedLoan": 7,
    "incomeYearOfEnquiring": 2014,
    "amalgamatedLoanNotPaidByEOIY": 10433,
    "repayments": null,
    "lodgement_date": null
  },
  "idx": 4755
}