{
  "id": "2023-09-06T11:02:16.839Z0.6017657317815659",
  "alert": "Start of result\nResult\n\nMinimum yearly repayment met.\n\nThe amount of the loan not repaid at the end of income year 2008-09 is $51.02.\n\nThe amalgamated loan will not be taken to be a dividend because the total repayments made are equal to or greater than the minimum yearly repayment required for income year 2008-09.\n\nInterest received by the private company must be included in the income tax return for 2008-09.\n\nMinimum yearly repayment\n\n$0\n\nBenchmark interest rate\n\n9.45%\n\nOpening balance:\n\nDate: 30/06/2008\n\nBalance: $934.00\n\nDays: 211\n\nInterest: $51.02\n\nPayments\n\nDate: 28/01/2009\n\nAmount: $934.00\n\nBalance: $0\n\nDays: 154\n\nInterest: $0\n\n\n\n\nTotal repayments\n\n$934.00\n\nTotal interest\n\n$51.02\n\nTotal principal\n\n$882.98\n\nClosing balance\n\nDate: 30/06/2009\n\nBalance: $51.02",
  "outputs": {
    "enquiryRateFormatted": "9.45%",
    "enquiryYearEndMinusOneDisplay": "30/06/2008",
    "amalgamatedLoanNotPaidByEOIYFormatted": "$934.00",
    "openingBalancePayDays": "211",
    "openingBalanceInterestFormatted": "$51.02",
    "totalAmountOfRepaymentFormatted": "$934.00",
    "totalInterestFormatted": "$51.02",
    "principalFormatted": "$882.98",
    "enquiryYearEndDisplay": "30/06/2009",
    "minimumYearRepaymentFormatted": "$0"
  },
  "repayments": [
    {
      "rd": "28/1/2009",
      "ra": 934
    }
  ],
  "inputs": {
    "incomeYearOfLoan": 2008,
    "fullTermOfAmalgamatedLoan": 2,
    "incomeYearOfEnquiring": 2009,
    "amalgamatedLoanNotPaidByEOIY": 934,
    "repayments": null,
    "lodgement_date": "10/2/2009"
  },
  "idx": 2800
}