{
  "id": "2023-09-04T20:50:23.553Z0.868746220389029",
  "alert": "Start of result\nResult\n\nMinimum yearly repayment not met.\n\nThe amount of the loan not repaid at the end of income year 2013-14 is $9,485,594.33.\n\nThe private company may be taken to pay a dividend under Division 7A to the shareholder or shareholder's associate because the amount repaid during income year 2013-14 in relation to the amalgamated loan is less than the minimum yearly repayment required.\n\nInterest received by the private company must be included in the income tax return for 2013-14.\n\nMinimum yearly repayment\n\n$5,188,298.00\n\nBenchmark interest rate\n\n6.2%\n\nOpening balance:\n\nDate: 30/06/2013\n\nBalance: $9,485,594.33\n\nDays: 365\n\nInterest: $588,106.85\n\nTotal repayments\n\n$0\n\nTotal interest\n\n$588,106.85\n\nTotal principal\n\n$0\n\nClosing balance\n\nDate: 30/06/2014\n\nBalance: $9,485,594.33",
  "outputs": {
    "enquiryRateFormatted": "6.2%",
    "enquiryYearEndMinusOneDisplay": "30/06/2013",
    "amalgamatedLoanNotPaidByEOIYFormatted": "$9,485,594.33",
    "openingBalancePayDays": "365",
    "openingBalanceInterestFormatted": "$588,106.85",
    "totalAmountOfRepaymentFormatted": "$0",
    "totalInterestFormatted": "$588,106.85",
    "principalFormatted": "$0",
    "enquiryYearEndDisplay": "30/06/2014",
    "minimumYearRepaymentFormatted": "$5,188,298.00"
  },
  "repayments": [],
  "inputs": {
    "incomeYearOfLoan": 2011,
    "fullTermOfAmalgamatedLoan": 4,
    "incomeYearOfEnquiring": 2014,
    "amalgamatedLoanNotPaidByEOIY": 9485594.331129398,
    "repayments": null,
    "lodgement_date": null
  },
  "idx": 126
}