{
  "id": "2023-10-31T17:23:58.414Z0.6478117191676765",
  "alert": "Start of result\nResult\n\nAmalgamated loan fully repaid.\n\nThe amalgamated loan has been paid in full.\u000bThe private company is not taken under Division 7A to pay a dividend to the shareholder or shareholder's associate.\n\nInterest received by the private company must be included in the income tax return for 2018-19.\n\nMinimum yearly repayment\n\n$474.00\n\nBenchmark interest rate\n\n5.2%\n\nOpening balance:\n\nDate: 30/06/2018\n\nBalance: $1,287.00\n\nDays: 343\n\nInterest: $62.89\n\nPayments\n\nDate: 09/06/2019\n\nAmount: $4,540.00\n\nBalance: $0\n\nDays: 22\n\nInterest: $0\n\n\n\n\nTotal repayments\n\n$4,540.00\n\nTotal interest\n\n$62.89\n\nTotal principal\n\n$4,477.11\n\nClosing balance\n\nDate: 30/06/2019\n\nBalance: $0",
  "outputs": {
    "enquiryRateFormatted": "5.2%",
    "enquiryYearEndMinusOneDisplay": "30/06/2018",
    "amalgamatedLoanNotPaidByEOIYFormatted": "$1,287.00",
    "openingBalancePayDays": "343",
    "openingBalanceInterestFormatted": "$62.89",
    "totalAmountOfRepaymentFormatted": "$4,540.00",
    "totalInterestFormatted": "$62.89",
    "principalFormatted": "$4,477.11",
    "enquiryYearEndDisplay": "30/06/2019",
    "minimumYearRepaymentFormatted": "$474.00",
    "loanAmountFormatted": "$0"
  },
  "repayments": [
    {
      "rd": "9/6/2019",
      "ra": 4540
    }
  ],
  "inputs": {
    "incomeYearOfLoan": 2018,
    "fullTermOfAmalgamatedLoan": 3,
    "incomeYearOfEnquiring": 2019,
    "amalgamatedLoanNotPaidByEOIY": 1287,
    "repayments": null,
    "lodgement_date": "26/2/2019"
  },
  "idx": 1348
}