{
  "id": "2023-10-31T21:17:37.113Z0.9722009853072616",
  "alert": "Start of result\nResult\n\nAmalgamated loan fully repaid.\n\nThe amalgamated loan has been paid in full.\u000bThe private company is not taken under Division 7A to pay a dividend to the shareholder or shareholder's associate.\n\nInterest received by the private company must be included in the income tax return for 1998-99.\n\nMinimum yearly repayment\n\n$9.00\n\nBenchmark interest rate\n\n6.7%\n\nOpening balance:\n\nDate: 30/06/1998\n\nBalance: $16.89\n\nDays: 155\n\nInterest: $0.48\n\nPayments\n\nDate: 03/12/1998\n\nAmount: $168.96\n\nBalance: $0\n\nDays: 210\n\nInterest: $0\n\n\n\n\nTotal repayments\n\n$168.96\n\nTotal interest\n\n$0.48\n\nTotal principal\n\n$168.48\n\nClosing balance\n\nDate: 30/06/1999\n\nBalance: $0",
  "outputs": {
    "enquiryRateFormatted": "6.7%",
    "enquiryYearEndMinusOneDisplay": "30/06/1998",
    "amalgamatedLoanNotPaidByEOIYFormatted": "$16.89",
    "openingBalancePayDays": "155",
    "openingBalanceInterestFormatted": "$0.48",
    "totalAmountOfRepaymentFormatted": "$168.96",
    "totalInterestFormatted": "$0.48",
    "principalFormatted": "$168.48",
    "enquiryYearEndDisplay": "30/06/1999",
    "minimumYearRepaymentFormatted": "$9.00",
    "loanAmountFormatted": "$0"
  },
  "repayments": [
    {
      "rd": "3/12/1998",
      "ra": 168.96375929723035
    }
  ],
  "inputs": {
    "incomeYearOfLoan": 1998,
    "fullTermOfAmalgamatedLoan": 2,
    "incomeYearOfEnquiring": 1999,
    "amalgamatedLoanNotPaidByEOIY": 16.896375929722996,
    "repayments": null,
    "lodgement_date": "29/9/1998"
  },
  "idx": 7162
}