{
  "id": "2023-10-31T17:20:10.076Z0.40483412438800226",
  "alert": "Start of result\nResult\n\nMinimum yearly repayment not met.\n\nThe amount of the loan not repaid at the end of income year 2019-20 is $8,901.00.\n\nThe private company may be taken to pay a dividend under Division 7A to the shareholder or shareholder's associate because the amount repaid during income year 2019-20 in relation to the amalgamated loan is less than the minimum yearly repayment required.\n\nInterest received by the private company must be included in the income tax return for 2019-20.\n\nMinimum yearly repayment\n\n$2,532.00\n\nBenchmark interest rate\n\n5.37%\n\nOpening balance:\n\nDate: 30/06/2019\n\nBalance: $8,901.00\n\nDays: 366\n\nInterest: $477.98\n\nTotal repayments\n\n$0\n\nTotal interest\n\n$477.98\n\nTotal principal\n\n$0\n\nClosing balance\n\nDate: 30/06/2020\n\nBalance: $8,901.00",
  "outputs": {
    "enquiryRateFormatted": "5.37%",
    "enquiryYearEndMinusOneDisplay": "30/06/2019",
    "amalgamatedLoanNotPaidByEOIYFormatted": "$8,901.00",
    "openingBalancePayDays": "366",
    "openingBalanceInterestFormatted": "$477.98",
    "totalAmountOfRepaymentFormatted": "$0",
    "totalInterestFormatted": "$477.98",
    "principalFormatted": "$0",
    "enquiryYearEndDisplay": "30/06/2020",
    "minimumYearRepaymentFormatted": "$2,532.00",
    "loanAmountFormatted": "$8,901.00"
  },
  "repayments": [],
  "inputs": {
    "incomeYearOfLoan": 2019,
    "fullTermOfAmalgamatedLoan": 4,
    "incomeYearOfEnquiring": 2020,
    "amalgamatedLoanNotPaidByEOIY": 8901,
    "repayments": null,
    "lodgement_date": "29/9/2019"
  },
  "idx": 1103
}