{
  "id": "2023-10-31T17:30:27.522Z0.04755813196410641",
  "alert": "Start of result\nResult\n\nAmalgamated loan fully repaid.\n\nThe amalgamated loan has been paid in full.\u000bThe private company is not taken under Division 7A to pay a dividend to the shareholder or shareholder's associate.\n\nInterest received by the private company must be included in the income tax return for 2021-22.\n\nMinimum yearly repayment\n\n$1,411.00\n\nBenchmark interest rate\n\n4.52%\n\nOpening balance:\n\nDate: 30/06/2021\n\nBalance: $3,876.00\n\nDays: 48\n\nInterest: $23.04\n\nPayments\n\nDate: 18/08/2021\n\nAmount: $4,922.00\n\nBalance: $0\n\nDays: 317\n\nInterest: $0\n\n\n\n\nTotal repayments\n\n$4,922.00\n\nTotal interest\n\n$23.04\n\nTotal principal\n\n$4,898.96\n\nClosing balance\n\nDate: 30/06/2022\n\nBalance: $0",
  "outputs": {
    "enquiryRateFormatted": "4.52%",
    "enquiryYearEndMinusOneDisplay": "30/06/2021",
    "amalgamatedLoanNotPaidByEOIYFormatted": "$3,876.00",
    "openingBalancePayDays": "48",
    "openingBalanceInterestFormatted": "$23.04",
    "totalAmountOfRepaymentFormatted": "$4,922.00",
    "totalInterestFormatted": "$23.04",
    "principalFormatted": "$4,898.96",
    "enquiryYearEndDisplay": "30/06/2022",
    "minimumYearRepaymentFormatted": "$1,411.00",
    "loanAmountFormatted": "$0"
  },
  "repayments": [
    {
      "rd": "18/8/2021",
      "ra": 4922
    }
  ],
  "inputs": {
    "incomeYearOfLoan": 2017,
    "fullTermOfAmalgamatedLoan": 7,
    "incomeYearOfEnquiring": 2022,
    "amalgamatedLoanNotPaidByEOIY": 3876,
    "repayments": null,
    "lodgement_date": null
  },
  "idx": 1717
}