{
  "id": "2023-09-04T16:03:36.096Z0.2779306854568456",
  "alert": "Start of result\nResult\n\nMinimum yearly repayment not met.\n\nThe amount of the loan not repaid at the end of income year 2023-24 is $106,337,897.81.\n\nThe private company may be taken to pay a dividend under Division 7A to the shareholder or shareholder's associate because the amount repaid during income year 2023-24 in relation to the amalgamated loan is less than the minimum yearly repayment required.\n\nInterest received by the private company must be included in the income tax return for 2023-24.\n\nMinimum yearly repayment\n\n$32,298,789.00\n\nBenchmark interest rate\n\n8.27%\n\nOpening balance:\n\nDate: 30/06/2023\n\nBalance: $106,337,897.81\n\nDays: 366\n\nInterest: $8,794,144.15\n\nTotal repayments\n\n$0\n\nTotal interest\n\n$8,794,144.15\n\nTotal principal\n\n$0\n\nClosing balance\n\nDate: 30/06/2024\n\nBalance: $106,337,897.81",
  "outputs": {
    "enquiryRateFormatted": "8.27%",
    "enquiryYearEndMinusOneDisplay": "30/06/2023",
    "amalgamatedLoanNotPaidByEOIYFormatted": "$106,337,897.81",
    "openingBalancePayDays": "366",
    "openingBalanceInterestFormatted": "$8,794,144.15",
    "totalAmountOfRepaymentFormatted": "$0",
    "totalInterestFormatted": "$8,794,144.15",
    "principalFormatted": "$0",
    "enquiryYearEndDisplay": "30/06/2024",
    "minimumYearRepaymentFormatted": "$32,298,789.00"
  },
  "repayments": [],
  "inputs": {
    "incomeYearOfLoan": 2023,
    "fullTermOfAmalgamatedLoan": 4,
    "incomeYearOfEnquiring": 2024,
    "amalgamatedLoanNotPaidByEOIY": 106337897.81078358,
    "repayments": null,
    "lodgement_date": "26/4/2024"
  },
  "idx": 13
}