{
  "id": "2023-09-04T21:46:07.469Z0.4604057405849791",
  "alert": "Start of result\nResult\n\nMinimum yearly repayment not met.\n\nThe amount of the loan not repaid at the end of income year 2005-06 is $60,710,993.80.\n\nThe private company may be taken to pay a dividend under Division 7A to the shareholder or shareholder's associate because the amount repaid during income year 2005-06 in relation to the amalgamated loan is less than the minimum yearly repayment required.\n\nInterest received by the private company must be included in the income tax return for 2005-06.\n\nMinimum yearly repayment\n\n$23,260,935.00\n\nBenchmark interest rate\n\n7.3%\n\nOpening balance:\n\nDate: 30/06/2005\n\nBalance: $60,710,993.80\n\nDays: 365\n\nInterest: $4,431,902.55\n\nTotal repayments\n\n$0\n\nTotal interest\n\n$4,431,902.55\n\nTotal principal\n\n$0\n\nClosing balance\n\nDate: 30/06/2006\n\nBalance: $60,710,993.80",
  "outputs": {
    "enquiryRateFormatted": "7.3%",
    "enquiryYearEndMinusOneDisplay": "30/06/2005",
    "amalgamatedLoanNotPaidByEOIYFormatted": "$60,710,993.80",
    "openingBalancePayDays": "365",
    "openingBalanceInterestFormatted": "$4,431,902.55",
    "totalAmountOfRepaymentFormatted": "$0",
    "totalInterestFormatted": "$4,431,902.55",
    "principalFormatted": "$0",
    "enquiryYearEndDisplay": "30/06/2006",
    "minimumYearRepaymentFormatted": "$23,260,935.00"
  },
  "repayments": [],
  "inputs": {
    "incomeYearOfLoan": 2005,
    "fullTermOfAmalgamatedLoan": 3,
    "incomeYearOfEnquiring": 2006,
    "amalgamatedLoanNotPaidByEOIY": 60710993.809309974,
    "repayments": null,
    "lodgement_date": "27/4/2006"
  },
  "idx": 1635
}