{
  "id": "2023-11-01T00:34:50.108Z0.5660405315703532",
  "alert": "Start of result\nResult\n\nAmalgamated loan fully repaid.\n\nThe amalgamated loan has been paid in full.\u000bThe private company is not taken under Division 7A to pay a dividend to the shareholder or shareholder's associate.\n\nInterest received by the private company must be included in the income tax return for 1998-99.\n\nMinimum yearly repayment\n\n$29.00\n\nBenchmark interest rate\n\n6.7%\n\nOpening balance:\n\nDate: 30/06/1998\n\nBalance: $119.13\n\nDays: 281\n\nInterest: $6.14\n\nPayments\n\nDate: 08/04/1999\n\nAmount: $1,191.39\n\nBalance: $0\n\nDays: 84\n\nInterest: $0\n\n\n\n\nTotal repayments\n\n$1,191.39\n\nTotal interest\n\n$6.14\n\nTotal principal\n\n$1,185.25\n\nClosing balance\n\nDate: 30/06/1999\n\nBalance: $0",
  "outputs": {
    "enquiryRateFormatted": "6.7%",
    "enquiryYearEndMinusOneDisplay": "30/06/1998",
    "amalgamatedLoanNotPaidByEOIYFormatted": "$119.13",
    "openingBalancePayDays": "281",
    "openingBalanceInterestFormatted": "$6.14",
    "totalAmountOfRepaymentFormatted": "$1,191.39",
    "totalInterestFormatted": "$6.14",
    "principalFormatted": "$1,185.25",
    "enquiryYearEndDisplay": "30/06/1999",
    "minimumYearRepaymentFormatted": "$29.00",
    "loanAmountFormatted": "$0"
  },
  "repayments": [
    {
      "rd": "8/4/1999",
      "ra": 1191.397798951262
    }
  ],
  "inputs": {
    "incomeYearOfLoan": 1998,
    "fullTermOfAmalgamatedLoan": 5,
    "incomeYearOfEnquiring": 1999,
    "amalgamatedLoanNotPaidByEOIY": 119.13977989512621,
    "repayments": null,
    "lodgement_date": "28/3/1999"
  },
  "idx": 25
}