{
  "id": "2023-09-06T14:04:53.895Z0.19577066111950536",
  "alert": "Start of result\nResult\n\nMinimum yearly repayment met.\n\nThe amount of the loan not repaid at the end of income year 2006-07 is $2.26.\n\nThe amalgamated loan will not be taken to be a dividend because the total repayments made are equal to or greater than the minimum yearly repayment required for income year 2006-07.\n\nInterest received by the private company must be included in the income tax return for 2006-07.\n\nMinimum yearly repayment\n\n$0\n\nBenchmark interest rate\n\n7.55%\n\nOpening balance:\n\nDate: 30/06/2006\n\nBalance: $104.11\n\nDays: 105\n\nInterest: $2.26\n\nPayments\n\nDate: 14/10/2006\n\nAmount: $104.11\n\nBalance: $0\n\nDays: 260\n\nInterest: $0\n\n\n\n\nTotal repayments\n\n$104.11\n\nTotal interest\n\n$2.26\n\nTotal principal\n\n$101.85\n\nClosing balance\n\nDate: 30/06/2007\n\nBalance: $2.26",
  "outputs": {
    "enquiryRateFormatted": "7.55%",
    "enquiryYearEndMinusOneDisplay": "30/06/2006",
    "amalgamatedLoanNotPaidByEOIYFormatted": "$104.11",
    "openingBalancePayDays": "105",
    "openingBalanceInterestFormatted": "$2.26",
    "totalAmountOfRepaymentFormatted": "$104.11",
    "totalInterestFormatted": "$2.26",
    "principalFormatted": "$101.85",
    "enquiryYearEndDisplay": "30/06/2007",
    "minimumYearRepaymentFormatted": "$0"
  },
  "repayments": [
    {
      "rd": "14/10/2006",
      "ra": 104.11559799657425
    }
  ],
  "inputs": {
    "incomeYearOfLoan": 2006,
    "fullTermOfAmalgamatedLoan": 2,
    "incomeYearOfEnquiring": 2007,
    "amalgamatedLoanNotPaidByEOIY": 104.1155979965746,
    "repayments": null,
    "lodgement_date": "26/11/2006"
  },
  "idx": 4216
}