{
  "id": "2023-09-04T22:25:57.336Z0.957397230339252",
  "alert": "Start of result\nResult\n\nAmalgamated loan fully repaid.\n\nThe amalgamated loan has been paid in full.\u000bThe private company is not taken under Division 7A to pay a dividend to the shareholder or shareholder's associate.\n\nInterest received by the private company must be included in the income tax return for 2000-01.\n\nMinimum yearly repayment\n\n$815.00\n\nBenchmark interest rate\n\n7.8%\n\nOpening balance:\n\nDate: 30/06/2000\n\nBalance: $3,791.00\n\nDays: 0\n\nInterest: $0\n\nPayments\n\nDate: 01/07/2000\n\nAmount: $3,791.00\n\nBalance: $0\n\nDays: 365\n\nInterest: $0\n\n\n\n\nTotal repayments\n\n$3,791.00\n\nTotal interest\n\n$0\n\nTotal principal\n\n$3,791.00\n\nClosing balance\n\nDate: 30/06/2001\n\nBalance: $0",
  "outputs": {
    "enquiryRateFormatted": "7.8%",
    "enquiryYearEndMinusOneDisplay": "30/06/2000",
    "amalgamatedLoanNotPaidByEOIYFormatted": "$3,791.00",
    "openingBalancePayDays": "0",
    "openingBalanceInterestFormatted": "$0",
    "totalAmountOfRepaymentFormatted": "$3,791.00",
    "totalInterestFormatted": "$0",
    "principalFormatted": "$3,791.00",
    "enquiryYearEndDisplay": "30/06/2001",
    "minimumYearRepaymentFormatted": "$815.00"
  },
  "repayments": [
    {
      "rd": "1/7/2000",
      "ra": 3791
    }
  ],
  "inputs": {
    "incomeYearOfLoan": 2000,
    "fullTermOfAmalgamatedLoan": 6,
    "incomeYearOfEnquiring": 2001,
    "amalgamatedLoanNotPaidByEOIY": 3791,
    "repayments": null,
    "lodgement_date": "1/7/2000"
  },
  "idx": 923
}