{
  "id": "2023-09-05T01:34:04.178Z0.018201747039223504",
  "alert": "Start of result\nResult\n\nMinimum yearly repayment met.\n\nThe amount of the loan not repaid at the end of income year 2000-01 is $1,652.57.\n\nThe amalgamated loan will not be taken to be a dividend because the total repayments made are equal to or greater than the minimum yearly repayment required for income year 2000-01.\n\nInterest received by the private company must be included in the income tax return for 2000-01.\n\nMinimum yearly repayment\n\n$5,145.00\n\nBenchmark interest rate\n\n7.8%\n\nOpening balance:\n\nDate: 30/06/2000\n\nBalance: $9,201.00\n\nDays: 0\n\nInterest: $0\n\nPayments\n\nDate: 01/07/2000\n\nAmount: $7,668.00\n\nBalance: $1,533.00\n\nDays: 365\n\nInterest: $119.57\n\n\n\n\nTotal repayments\n\n$7,668.00\n\nTotal interest\n\n$119.57\n\nTotal principal\n\n$7,548.43\n\nClosing balance\n\nDate: 30/06/2001\n\nBalance: $1,652.57",
  "outputs": {
    "enquiryRateFormatted": "7.8%",
    "enquiryYearEndMinusOneDisplay": "30/06/2000",
    "amalgamatedLoanNotPaidByEOIYFormatted": "$9,201.00",
    "openingBalancePayDays": "0",
    "openingBalanceInterestFormatted": "$0",
    "totalAmountOfRepaymentFormatted": "$7,668.00",
    "totalInterestFormatted": "$119.57",
    "principalFormatted": "$7,548.43",
    "enquiryYearEndDisplay": "30/06/2001",
    "minimumYearRepaymentFormatted": "$5,145.00"
  },
  "repayments": [
    {
      "rd": "1/7/2000",
      "ra": 7668
    }
  ],
  "inputs": {
    "incomeYearOfLoan": 1998,
    "fullTermOfAmalgamatedLoan": 4,
    "incomeYearOfEnquiring": 2001,
    "amalgamatedLoanNotPaidByEOIY": 9201,
    "repayments": null,
    "lodgement_date": null
  },
  "idx": 2574
}