{
  "id": "2023-09-04T22:02:49.440Z0.34581184969279555",
  "alert": "Start of result\nResult\n\nMinimum yearly repayment not met.\n\nThe amount of the loan not repaid at the end of income year 2004-05 is $11,581,550.28.\n\nThe private company may be taken to pay a dividend under Division 7A to the shareholder or shareholder's associate because the amount repaid during income year 2004-05 in relation to the amalgamated loan is less than the minimum yearly repayment required.\n\nInterest received by the private company must be included in the income tax return for 2004-05.\n\nMinimum yearly repayment\n\n$2,828,415.00\n\nBenchmark interest rate\n\n7.05%\n\nOpening balance:\n\nDate: 30/06/2004\n\nBalance: $11,581,550.28\n\nDays: 365\n\nInterest: $816,499.29\n\nTotal repayments\n\n$0\n\nTotal interest\n\n$816,499.29\n\nTotal principal\n\n$0\n\nClosing balance\n\nDate: 30/06/2005\n\nBalance: $11,581,550.28",
  "outputs": {
    "enquiryRateFormatted": "7.05%",
    "enquiryYearEndMinusOneDisplay": "30/06/2004",
    "amalgamatedLoanNotPaidByEOIYFormatted": "$11,581,550.28",
    "openingBalancePayDays": "365",
    "openingBalanceInterestFormatted": "$816,499.29",
    "totalAmountOfRepaymentFormatted": "$0",
    "totalInterestFormatted": "$816,499.29",
    "principalFormatted": "$0",
    "enquiryYearEndDisplay": "30/06/2005",
    "minimumYearRepaymentFormatted": "$2,828,415.00"
  },
  "repayments": [],
  "inputs": {
    "incomeYearOfLoan": 2004,
    "fullTermOfAmalgamatedLoan": 5,
    "incomeYearOfEnquiring": 2005,
    "amalgamatedLoanNotPaidByEOIY": 11581550.28876774,
    "repayments": null,
    "lodgement_date": "27/4/2005"
  },
  "idx": 77
}