{
  "id": "2023-10-31T20:26:00.445Z0.791187172343545",
  "alert": "Start of result\nResult\n\nAmalgamated loan fully repaid.\n\nThe amalgamated loan has been paid in full.\u000bThe private company is not taken under Division 7A to pay a dividend to the shareholder or shareholder's associate.\n\nInterest received by the private company must be included in the income tax return for 2000-01.\n\nMinimum yearly repayment\n\n$333.00\n\nBenchmark interest rate\n\n7.8%\n\nOpening balance:\n\nDate: 30/06/2000\n\nBalance: $309.00\n\nDays: 312\n\nInterest: $20.60\n\nPayments\n\nDate: 09/05/2001\n\nAmount: $3,090.00\n\nBalance: $0\n\nDays: 53\n\nInterest: $0\n\n\n\n\nTotal repayments\n\n$3,090.00\n\nTotal interest\n\n$20.60\n\nTotal principal\n\n$3,069.40\n\nClosing balance\n\nDate: 30/06/2001\n\nBalance: $0",
  "outputs": {
    "enquiryRateFormatted": "7.8%",
    "enquiryYearEndMinusOneDisplay": "30/06/2000",
    "amalgamatedLoanNotPaidByEOIYFormatted": "$309.00",
    "openingBalancePayDays": "312",
    "openingBalanceInterestFormatted": "$20.60",
    "totalAmountOfRepaymentFormatted": "$3,090.00",
    "totalInterestFormatted": "$20.60",
    "principalFormatted": "$3,069.40",
    "enquiryYearEndDisplay": "30/06/2001",
    "minimumYearRepaymentFormatted": "$333.00",
    "loanAmountFormatted": "$0"
  },
  "repayments": [
    {
      "rd": "9/5/2001",
      "ra": 3090
    }
  ],
  "inputs": {
    "incomeYearOfLoan": 2000,
    "fullTermOfAmalgamatedLoan": 1,
    "incomeYearOfEnquiring": 2001,
    "amalgamatedLoanNotPaidByEOIY": 309,
    "repayments": null,
    "lodgement_date": "1/7/2000"
  },
  "idx": 6463
}