{
  "id": "2023-10-31T17:22:08.924Z0.06561647337255672",
  "alert": "Start of result\nResult\n\nAmalgamated loan fully repaid.\n\nThe amalgamated loan has been paid in full.\u000bThe private company is not taken under Division 7A to pay a dividend to the shareholder or shareholder's associate.\n\nInterest received by the private company must be included in the income tax return for 2020-21.\n\nMinimum yearly repayment\n\n$963.00\n\nBenchmark interest rate\n\n4.52%\n\nOpening balance:\n\nDate: 30/06/2020\n\nBalance: $4,964.00\n\nDays: 362\n\nInterest: $222.53\n\nPayments\n\nDate: 28/06/2021\n\nAmount: $6,726.00\n\nBalance: $0\n\nDays: 3\n\nInterest: $0\n\n\n\n\nTotal repayments\n\n$6,726.00\n\nTotal interest\n\n$222.53\n\nTotal principal\n\n$6,503.47\n\nClosing balance\n\nDate: 30/06/2021\n\nBalance: $0",
  "outputs": {
    "enquiryRateFormatted": "4.52%",
    "enquiryYearEndMinusOneDisplay": "30/06/2020",
    "amalgamatedLoanNotPaidByEOIYFormatted": "$4,964.00",
    "openingBalancePayDays": "362",
    "openingBalanceInterestFormatted": "$222.53",
    "totalAmountOfRepaymentFormatted": "$6,726.00",
    "totalInterestFormatted": "$222.53",
    "principalFormatted": "$6,503.47",
    "enquiryYearEndDisplay": "30/06/2021",
    "minimumYearRepaymentFormatted": "$963.00",
    "loanAmountFormatted": "$0"
  },
  "repayments": [
    {
      "rd": "28/6/2021",
      "ra": 6726
    }
  ],
  "inputs": {
    "incomeYearOfLoan": 2019,
    "fullTermOfAmalgamatedLoan": 7,
    "incomeYearOfEnquiring": 2021,
    "amalgamatedLoanNotPaidByEOIY": 4964,
    "repayments": null,
    "lodgement_date": null
  },
  "idx": 1229
}