{
  "id": "2023-10-31T18:03:29.827Z0.18744514936085344",
  "alert": "Start of result\nResult\n\nAmalgamated loan fully repaid.\n\nThe amalgamated loan has been paid in full.\u000bThe private company is not taken under Division 7A to pay a dividend to the shareholder or shareholder's associate.\n\nInterest received by the private company must be included in the income tax return for 2016-17.\n\nMinimum yearly repayment\n\n$6,137.00\n\nBenchmark interest rate\n\n5.4%\n\nOpening balance:\n\nDate: 30/06/2016\n\nBalance: $5,823.00\n\nDays: 4\n\nInterest: $3.45\n\nPayments\n\nDate: 05/07/2016\n\nAmount: $2,495.00\n\nBalance: $3,328.00\n\nDays: 118\n\nInterest: $58.10\n\n\n\n\nDate: 31/10/2016\n\nAmount: $8,944.00\n\nBalance: $0\n\nDays: 45\n\nInterest: $0\n\n\n\n\nDate: 15/12/2016\n\nAmount: $5,912.00\n\nBalance: $0\n\nDays: 198\n\nInterest: $0\n\n\n\n\nTotal repayments\n\n$17,351.00\n\nTotal interest\n\n$61.55\n\nTotal principal\n\n$17,289.45\n\nClosing balance\n\nDate: 30/06/2017\n\nBalance: $0",
  "outputs": {
    "enquiryRateFormatted": "5.4%",
    "enquiryYearEndMinusOneDisplay": "30/06/2016",
    "amalgamatedLoanNotPaidByEOIYFormatted": "$5,823.00",
    "openingBalancePayDays": "4",
    "openingBalanceInterestFormatted": "$3.45",
    "totalAmountOfRepaymentFormatted": "$17,351.00",
    "totalInterestFormatted": "$61.55",
    "principalFormatted": "$17,289.45",
    "enquiryYearEndDisplay": "30/06/2017",
    "minimumYearRepaymentFormatted": "$6,137.00",
    "loanAmountFormatted": "$0"
  },
  "repayments": [
    {
      "rd": "5/7/2016",
      "ra": 2495
    },
    {
      "rd": "31/10/2016",
      "ra": 8944
    },
    {
      "rd": "15/12/2016",
      "ra": 5912
    }
  ],
  "inputs": {
    "incomeYearOfLoan": 2012,
    "fullTermOfAmalgamatedLoan": 5,
    "incomeYearOfEnquiring": 2017,
    "amalgamatedLoanNotPaidByEOIY": 5823,
    "repayments": null,
    "lodgement_date": null
  },
  "idx": 3223
}