{
  "id": "2023-09-05T15:58:09.716Z0.3571439767461819",
  "alert": "Start of result\nResult\n\nMinimum yearly repayment met.\n\nThe amount of the loan not repaid at the end of income year 2020-21 is $1.65.\n\nThe amalgamated loan will not be taken to be a dividend because the total repayments made are equal to or greater than the minimum yearly repayment required for income year 2020-21.\n\nInterest received by the private company must be included in the income tax return for 2020-21.\n\nMinimum yearly repayment\n\n$0\n\nBenchmark interest rate\n\n4.52%\n\nOpening balance:\n\nDate: 30/06/2020\n\nBalance: $117.94\n\nDays: 113\n\nInterest: $1.65\n\nPayments\n\nDate: 22/10/2020\n\nAmount: $117.94\n\nBalance: $0\n\nDays: 252\n\nInterest: $0\n\n\n\n\nTotal repayments\n\n$117.94\n\nTotal interest\n\n$1.65\n\nTotal principal\n\n$116.29\n\nClosing balance\n\nDate: 30/06/2021\n\nBalance: $1.65",
  "outputs": {
    "enquiryRateFormatted": "4.52%",
    "enquiryYearEndMinusOneDisplay": "30/06/2020",
    "amalgamatedLoanNotPaidByEOIYFormatted": "$117.94",
    "openingBalancePayDays": "113",
    "openingBalanceInterestFormatted": "$1.65",
    "totalAmountOfRepaymentFormatted": "$117.94",
    "totalInterestFormatted": "$1.65",
    "principalFormatted": "$116.29",
    "enquiryYearEndDisplay": "30/06/2021",
    "minimumYearRepaymentFormatted": "$0"
  },
  "repayments": [
    {
      "rd": "22/10/2020",
      "ra": 117.94996006794099
    }
  ],
  "inputs": {
    "incomeYearOfLoan": 2020,
    "fullTermOfAmalgamatedLoan": 7,
    "incomeYearOfEnquiring": 2021,
    "amalgamatedLoanNotPaidByEOIY": 117.9499600679402,
    "repayments": null,
    "lodgement_date": "24/11/2020"
  },
  "idx": 7875
}