{
  "id": "2023-09-05T23:52:24.168Z0.4384127271615985",
  "alert": "Start of result\nResult\n\nMinimum yearly repayment not met.\n\nThe amount of the loan not repaid at the end of income year 2019-20 is $1.12.\n\nThe private company may be taken to pay a dividend under Division 7A to the shareholder or shareholder's associate because the amount repaid during income year 2019-20 in relation to the amalgamated loan is less than the minimum yearly repayment required.\n\nInterest received by the private company must be included in the income tax return for 2019-20.\n\nMinimum yearly repayment\n\n$27.00\n\nBenchmark interest rate\n\n5.37%\n\nOpening balance:\n\nDate: 30/06/2019\n\nBalance: $25.61\n\nDays: 297\n\nInterest: $1.12\n\nPayments\n\nDate: 23/04/2020\n\nAmount: $25.61\n\nBalance: $0\n\nDays: 69\n\nInterest: $0\n\n\n\n\nTotal repayments\n\n$25.61\n\nTotal interest\n\n$1.12\n\nTotal principal\n\n$24.49\n\nClosing balance\n\nDate: 30/06/2020\n\nBalance: $1.12",
  "outputs": {
    "enquiryRateFormatted": "5.37%",
    "enquiryYearEndMinusOneDisplay": "30/06/2019",
    "amalgamatedLoanNotPaidByEOIYFormatted": "$25.61",
    "openingBalancePayDays": "297",
    "openingBalanceInterestFormatted": "$1.12",
    "totalAmountOfRepaymentFormatted": "$25.61",
    "totalInterestFormatted": "$1.12",
    "principalFormatted": "$24.49",
    "enquiryYearEndDisplay": "30/06/2020",
    "minimumYearRepaymentFormatted": "$27.00"
  },
  "repayments": [
    {
      "rd": "23/4/2020",
      "ra": 25.619483661280356
    }
  ],
  "inputs": {
    "incomeYearOfLoan": 2015,
    "fullTermOfAmalgamatedLoan": 5,
    "incomeYearOfEnquiring": 2020,
    "amalgamatedLoanNotPaidByEOIY": 25.619483661280444,
    "repayments": null,
    "lodgement_date": null
  },
  "idx": 735
}