{
  "id": "2023-10-31T17:17:45.369Z0.4766721002963087",
  "alert": "Start of result\nResult\n\nAmalgamated loan fully repaid.\n\nThe amalgamated loan has been paid in full.\u000bThe private company is not taken under Division 7A to pay a dividend to the shareholder or shareholder's associate.\n\nInterest received by the private company must be included in the income tax return for 2021-22.\n\nMinimum yearly repayment\n\n$5.00\n\nBenchmark interest rate\n\n4.52%\n\nOpening balance:\n\nDate: 30/06/2021\n\nBalance: $23.19\n\nDays: 197\n\nInterest: $0.57\n\nPayments\n\nDate: 14/01/2022\n\nAmount: $231.96\n\nBalance: $0\n\nDays: 168\n\nInterest: $0\n\n\n\n\nTotal repayments\n\n$231.96\n\nTotal interest\n\n$0.57\n\nTotal principal\n\n$231.39\n\nClosing balance\n\nDate: 30/06/2022\n\nBalance: $0",
  "outputs": {
    "enquiryRateFormatted": "4.52%",
    "enquiryYearEndMinusOneDisplay": "30/06/2021",
    "amalgamatedLoanNotPaidByEOIYFormatted": "$23.19",
    "openingBalancePayDays": "197",
    "openingBalanceInterestFormatted": "$0.57",
    "totalAmountOfRepaymentFormatted": "$231.96",
    "totalInterestFormatted": "$0.57",
    "principalFormatted": "$231.39",
    "enquiryYearEndDisplay": "30/06/2022",
    "minimumYearRepaymentFormatted": "$5.00",
    "loanAmountFormatted": "$0"
  },
  "repayments": [
    {
      "rd": "14/1/2022",
      "ra": 231.96578151273764
    }
  ],
  "inputs": {
    "incomeYearOfLoan": 2020,
    "fullTermOfAmalgamatedLoan": 6,
    "incomeYearOfEnquiring": 2022,
    "amalgamatedLoanNotPaidByEOIY": 23.196578151273762,
    "repayments": null,
    "lodgement_date": null
  },
  "idx": 927
}