{
  "id": "2023-09-04T20:49:59.824Z0.7856382900234229",
  "alert": "Start of result\nResult\n\nMinimum yearly repayment not met.\n\nThe amount of the loan not repaid at the end of income year 2011-12 is $107,527,463.15.\n\nThe private company may be taken to pay a dividend under Division 7A to the shareholder or shareholder's associate because the amount repaid during income year 2011-12 in relation to the amalgamated loan is less than the minimum yearly repayment required.\n\nInterest received by the private company must be included in the income tax return for 2011-12.\n\nMinimum yearly repayment\n\n$41,573,770.00\n\nBenchmark interest rate\n\n7.8%\n\nOpening balance:\n\nDate: 30/06/2011\n\nBalance: $107,527,463.15\n\nDays: 366\n\nInterest: $8,387,142.13\n\nTotal repayments\n\n$0\n\nTotal interest\n\n$8,387,142.13\n\nTotal principal\n\n$0\n\nClosing balance\n\nDate: 30/06/2012\n\nBalance: $107,527,463.15",
  "outputs": {
    "enquiryRateFormatted": "7.8%",
    "enquiryYearEndMinusOneDisplay": "30/06/2011",
    "amalgamatedLoanNotPaidByEOIYFormatted": "$107,527,463.15",
    "openingBalancePayDays": "366",
    "openingBalanceInterestFormatted": "$8,387,142.13",
    "totalAmountOfRepaymentFormatted": "$0",
    "totalInterestFormatted": "$8,387,142.13",
    "principalFormatted": "$0",
    "enquiryYearEndDisplay": "30/06/2012",
    "minimumYearRepaymentFormatted": "$41,573,770.00"
  },
  "repayments": [],
  "inputs": {
    "incomeYearOfLoan": 2011,
    "fullTermOfAmalgamatedLoan": 3,
    "incomeYearOfEnquiring": 2012,
    "amalgamatedLoanNotPaidByEOIY": 107527463.15546964,
    "repayments": null,
    "lodgement_date": "17/1/2012"
  },
  "idx": 109
}