{
  "id": "2023-09-05T15:06:42.876Z0.9971500450375281",
  "alert": "Start of result\nResult\n\nMinimum yearly repayment not met.\n\nThe amount of the loan not repaid at the end of income year 2022-23 is $260.00.\n\nThe private company may be taken to pay a dividend under Division 7A to the shareholder or shareholder's associate because the amount repaid during income year 2022-23 in relation to the amalgamated loan is less than the minimum yearly repayment required.\n\nInterest received by the private company must be included in the income tax return for 2022-23.\n\nMinimum yearly repayment\n\n$139.00\n\nBenchmark interest rate\n\n4.77%\n\nOpening balance:\n\nDate: 30/06/2022\n\nBalance: $260.00\n\nDays: 365\n\nInterest: $12.40\n\nTotal repayments\n\n$0\n\nTotal interest\n\n$12.40\n\nTotal principal\n\n$0\n\nClosing balance\n\nDate: 30/06/2023\n\nBalance: $260.00",
  "outputs": {
    "enquiryRateFormatted": "4.77%",
    "enquiryYearEndMinusOneDisplay": "30/06/2022",
    "amalgamatedLoanNotPaidByEOIYFormatted": "$260.00",
    "openingBalancePayDays": "365",
    "openingBalanceInterestFormatted": "$12.40",
    "totalAmountOfRepaymentFormatted": "$0",
    "totalInterestFormatted": "$12.40",
    "principalFormatted": "$0",
    "enquiryYearEndDisplay": "30/06/2023",
    "minimumYearRepaymentFormatted": "$139.00"
  },
  "repayments": [],
  "inputs": {
    "incomeYearOfLoan": 2020,
    "fullTermOfAmalgamatedLoan": 4,
    "incomeYearOfEnquiring": 2023,
    "amalgamatedLoanNotPaidByEOIY": 260,
    "repayments": null,
    "lodgement_date": null
  },
  "idx": 5144
}