{
  "id": "2023-09-04T20:51:12.731Z0.4295417910087489",
  "alert": "Start of result\nResult\n\nMinimum yearly repayment not met.\n\nThe amount of the loan not repaid at the end of income year 2012-13 is $3,331,955.96.\n\nThe private company may be taken to pay a dividend under Division 7A to the shareholder or shareholder's associate because the amount repaid during income year 2012-13 in relation to the amalgamated loan is less than the minimum yearly repayment required.\n\nInterest received by the private company must be included in the income tax return for 2012-13.\n\nMinimum yearly repayment\n\n$984,798.00\n\nBenchmark interest rate\n\n7.05%\n\nOpening balance:\n\nDate: 30/06/2012\n\nBalance: $3,331,955.96\n\nDays: 365\n\nInterest: $234,902.90\n\nTotal repayments\n\n$0\n\nTotal interest\n\n$234,902.90\n\nTotal principal\n\n$0\n\nClosing balance\n\nDate: 30/06/2013\n\nBalance: $3,331,955.96",
  "outputs": {
    "enquiryRateFormatted": "7.05%",
    "enquiryYearEndMinusOneDisplay": "30/06/2012",
    "amalgamatedLoanNotPaidByEOIYFormatted": "$3,331,955.96",
    "openingBalancePayDays": "365",
    "openingBalanceInterestFormatted": "$234,902.90",
    "totalAmountOfRepaymentFormatted": "$0",
    "totalInterestFormatted": "$234,902.90",
    "principalFormatted": "$0",
    "enquiryYearEndDisplay": "30/06/2013",
    "minimumYearRepaymentFormatted": "$984,798.00"
  },
  "repayments": [],
  "inputs": {
    "incomeYearOfLoan": 2011,
    "fullTermOfAmalgamatedLoan": 5,
    "incomeYearOfEnquiring": 2013,
    "amalgamatedLoanNotPaidByEOIY": 3331955.9667880465,
    "repayments": null,
    "lodgement_date": null
  },
  "idx": 157
}