{
  "id": "2023-09-06T16:29:10.787Z0.32046637622449414",
  "alert": "Start of result\nResult\n\nMinimum yearly repayment not met.\n\nThe amount of the loan not repaid at the end of income year 2007-08 is $9,688.07.\n\nThe private company may be taken to pay a dividend under Division 7A to the shareholder or shareholder's associate because the amount repaid during income year 2007-08 in relation to the amalgamated loan is less than the minimum yearly repayment required.\n\nInterest received by the private company must be included in the income tax return for 2007-08.\n\nMinimum yearly repayment\n\n$4,248.00\n\nBenchmark interest rate\n\n8.05%\n\nOpening balance:\n\nDate: 30/06/2007\n\nBalance: $10,938.00\n\nDays: 134\n\nInterest: $322.37\n\nPayments\n\nDate: 12/11/2007\n\nAmount: $2,027.00\n\nBalance: $8,911.00\n\nDays: 232\n\nInterest: $454.70\n\n\n\n\nTotal repayments\n\n$2,027.00\n\nTotal interest\n\n$777.07\n\nTotal principal\n\n$1,249.93\n\nClosing balance\n\nDate: 30/06/2008\n\nBalance: $9,688.07",
  "outputs": {
    "enquiryRateFormatted": "8.05%",
    "enquiryYearEndMinusOneDisplay": "30/06/2007",
    "amalgamatedLoanNotPaidByEOIYFormatted": "$10,938.00",
    "openingBalancePayDays": "134",
    "openingBalanceInterestFormatted": "$322.37",
    "totalAmountOfRepaymentFormatted": "$2,027.00",
    "totalInterestFormatted": "$777.07",
    "principalFormatted": "$1,249.93",
    "enquiryYearEndDisplay": "30/06/2008",
    "minimumYearRepaymentFormatted": "$4,248.00"
  },
  "repayments": [
    {
      "rd": "12/11/2007",
      "ra": 2027
    }
  ],
  "inputs": {
    "incomeYearOfLoan": 2005,
    "fullTermOfAmalgamatedLoan": 5,
    "incomeYearOfEnquiring": 2008,
    "amalgamatedLoanNotPaidByEOIY": 10938,
    "repayments": null,
    "lodgement_date": null
  },
  "idx": 4046
}