{
  "id": "2023-10-31T18:04:59.497Z0.32812866642327565",
  "alert": "Start of result\nResult\n\nAmalgamated loan fully repaid.\n\nThe amalgamated loan has been paid in full.\u000bThe private company is not taken under Division 7A to pay a dividend to the shareholder or shareholder's associate.\n\nInterest received by the private company must be included in the income tax return for 2014-15.\n\nMinimum yearly repayment\n\n$29.00\n\nBenchmark interest rate\n\n5.95%\n\nOpening balance:\n\nDate: 30/06/2014\n\nBalance: $99.67\n\nDays: 118\n\nInterest: $1.92\n\nPayments\n\nDate: 27/10/2014\n\nAmount: $996.71\n\nBalance: $0\n\nDays: 247\n\nInterest: $0\n\n\n\n\nTotal repayments\n\n$996.71\n\nTotal interest\n\n$1.92\n\nTotal principal\n\n$994.79\n\nClosing balance\n\nDate: 30/06/2015\n\nBalance: $0",
  "outputs": {
    "enquiryRateFormatted": "5.95%",
    "enquiryYearEndMinusOneDisplay": "30/06/2014",
    "amalgamatedLoanNotPaidByEOIYFormatted": "$99.67",
    "openingBalancePayDays": "118",
    "openingBalanceInterestFormatted": "$1.92",
    "totalAmountOfRepaymentFormatted": "$996.71",
    "totalInterestFormatted": "$1.92",
    "principalFormatted": "$994.79",
    "enquiryYearEndDisplay": "30/06/2015",
    "minimumYearRepaymentFormatted": "$29.00",
    "loanAmountFormatted": "$0"
  },
  "repayments": [
    {
      "rd": "27/10/2014",
      "ra": 996.7194292626418
    }
  ],
  "inputs": {
    "incomeYearOfLoan": 2012,
    "fullTermOfAmalgamatedLoan": 6,
    "incomeYearOfEnquiring": 2015,
    "amalgamatedLoanNotPaidByEOIY": 99.67194292626418,
    "repayments": null,
    "lodgement_date": null
  },
  "idx": 3272
}