{
  "id": "2023-09-05T09:58:44.223Z0.9979087130104785",
  "alert": "Start of result\nResult\n\nMinimum yearly repayment met.\n\nThe amount of the loan not repaid at the end of income year 2023-24 is $97.36.\n\nThe amalgamated loan will not be taken to be a dividend because the total repayments made are equal to or greater than the minimum yearly repayment required for income year 2023-24.\n\nInterest received by the private company must be included in the income tax return for 2023-24.\n\nMinimum yearly repayment\n\n$751.00\n\nBenchmark interest rate\n\n8.27%\n\nOpening balance:\n\nDate: 30/06/2023\n\nBalance: $1,334.00\n\nDays: 323\n\nInterest: $97.36\n\nPayments\n\nDate: 19/05/2024\n\nAmount: $1,334.00\n\nBalance: $0\n\nDays: 43\n\nInterest: $0\n\n\n\n\nTotal repayments\n\n$1,334.00\n\nTotal interest\n\n$97.36\n\nTotal principal\n\n$1,236.64\n\nClosing balance\n\nDate: 30/06/2024\n\nBalance: $97.36",
  "outputs": {
    "enquiryRateFormatted": "8.27%",
    "enquiryYearEndMinusOneDisplay": "30/06/2023",
    "amalgamatedLoanNotPaidByEOIYFormatted": "$1,334.00",
    "openingBalancePayDays": "323",
    "openingBalanceInterestFormatted": "$97.36",
    "totalAmountOfRepaymentFormatted": "$1,334.00",
    "totalInterestFormatted": "$97.36",
    "principalFormatted": "$1,236.64",
    "enquiryYearEndDisplay": "30/06/2024",
    "minimumYearRepaymentFormatted": "$751.00"
  },
  "repayments": [
    {
      "rd": "19/5/2024",
      "ra": 1334
    }
  ],
  "inputs": {
    "incomeYearOfLoan": 2023,
    "fullTermOfAmalgamatedLoan": 2,
    "incomeYearOfEnquiring": 2024,
    "amalgamatedLoanNotPaidByEOIY": 1334,
    "repayments": null,
    "lodgement_date": "24/10/2023"
  },
  "idx": 1216
}