{
  "id": "2023-09-04T21:30:18.935Z0.9336948583870521",
  "alert": "Start of result\nResult\n\nMinimum yearly repayment met.\n\nThe amount of the loan not repaid at the end of income year 2008-09 is $1,585.93.\n\nThe amalgamated loan will not be taken to be a dividend because the total repayments made are equal to or greater than the minimum yearly repayment required for income year 2008-09.\n\nInterest received by the private company must be included in the income tax return for 2008-09.\n\nMinimum yearly repayment\n\n$1,314.00\n\nBenchmark interest rate\n\n9.45%\n\nOpening balance:\n\nDate: 30/06/2008\n\nBalance: $5,053.00\n\nDays: 0\n\nInterest: $0\n\nPayments\n\nDate: 01/07/2008\n\nAmount: $3,604.00\n\nBalance: $1,449.00\n\nDays: 365\n\nInterest: $136.93\n\n\n\n\nTotal repayments\n\n$3,604.00\n\nTotal interest\n\n$136.93\n\nTotal principal\n\n$3,467.07\n\nClosing balance\n\nDate: 30/06/2009\n\nBalance: $1,585.93",
  "outputs": {
    "enquiryRateFormatted": "9.45%",
    "enquiryYearEndMinusOneDisplay": "30/06/2008",
    "amalgamatedLoanNotPaidByEOIYFormatted": "$5,053.00",
    "openingBalancePayDays": "0",
    "openingBalanceInterestFormatted": "$0",
    "totalAmountOfRepaymentFormatted": "$3,604.00",
    "totalInterestFormatted": "$136.93",
    "principalFormatted": "$3,467.07",
    "enquiryYearEndDisplay": "30/06/2009",
    "minimumYearRepaymentFormatted": "$1,314.00"
  },
  "repayments": [
    {
      "rd": "1/7/2008",
      "ra": 3604
    }
  ],
  "inputs": {
    "incomeYearOfLoan": 2007,
    "fullTermOfAmalgamatedLoan": 6,
    "incomeYearOfEnquiring": 2009,
    "amalgamatedLoanNotPaidByEOIY": 5053,
    "repayments": null,
    "lodgement_date": null
  },
  "idx": 1317
}