{
  "id": "2023-09-04T17:25:38.636Z0.9605024667137323",
  "alert": "Start of result\nResult\n\nAmalgamated loan fully repaid.\n\nThe amalgamated loan has been paid in full.\u000bThe private company is not taken under Division 7A to pay a dividend to the shareholder or shareholder's associate.\n\nInterest received by the private company must be included in the income tax return for 2017-18.\n\nMinimum yearly repayment\n\n$99.00\n\nBenchmark interest rate\n\n5.3%\n\nOpening balance:\n\nDate: 30/06/2017\n\nBalance: $269.00\n\nDays: 0\n\nInterest: $0\n\nPayments\n\nDate: 01/07/2017\n\nAmount: $269.00\n\nBalance: $0\n\nDays: 365\n\nInterest: $0\n\n\n\n\nTotal repayments\n\n$269.00\n\nTotal interest\n\n$0\n\nTotal principal\n\n$269.00\n\nClosing balance\n\nDate: 30/06/2018\n\nBalance: $0",
  "outputs": {
    "enquiryRateFormatted": "5.3%",
    "enquiryYearEndMinusOneDisplay": "30/06/2017",
    "amalgamatedLoanNotPaidByEOIYFormatted": "$269.00",
    "openingBalancePayDays": "0",
    "openingBalanceInterestFormatted": "$0",
    "totalAmountOfRepaymentFormatted": "$269.00",
    "totalInterestFormatted": "$0",
    "principalFormatted": "$269.00",
    "enquiryYearEndDisplay": "30/06/2018",
    "minimumYearRepaymentFormatted": "$99.00"
  },
  "repayments": [
    {
      "rd": "1/7/2017",
      "ra": 269
    }
  ],
  "inputs": {
    "incomeYearOfLoan": 2013,
    "fullTermOfAmalgamatedLoan": 7,
    "incomeYearOfEnquiring": 2018,
    "amalgamatedLoanNotPaidByEOIY": 269,
    "repayments": null,
    "lodgement_date": null
  },
  "idx": 2126
}