{
  "id": "2023-10-31T21:11:16.715Z0.31968970843723044",
  "alert": "Start of result\nResult\n\nMinimum yearly repayment not met.\n\nThe amount of the loan not repaid at the end of income year 2003-04 is $47.22.\n\nThe private company may be taken to pay a dividend under Division 7A to the shareholder or shareholder's associate because the amount repaid during income year 2003-04 in relation to the amalgamated loan is less than the minimum yearly repayment required.\n\nInterest received by the private company must be included in the income tax return for 2003-04.\n\nMinimum yearly repayment\n\n$18.00\n\nBenchmark interest rate\n\n6.55%\n\nOpening balance:\n\nDate: 30/06/2003\n\nBalance: $47.22\n\nDays: 366\n\nInterest: $3.09\n\nTotal repayments\n\n$0\n\nTotal interest\n\n$3.09\n\nTotal principal\n\n$0\n\nClosing balance\n\nDate: 30/06/2004\n\nBalance: $47.22",
  "outputs": {
    "enquiryRateFormatted": "6.55%",
    "enquiryYearEndMinusOneDisplay": "30/06/2003",
    "amalgamatedLoanNotPaidByEOIYFormatted": "$47.22",
    "openingBalancePayDays": "366",
    "openingBalanceInterestFormatted": "$3.09",
    "totalAmountOfRepaymentFormatted": "$0",
    "totalInterestFormatted": "$3.09",
    "principalFormatted": "$0",
    "enquiryYearEndDisplay": "30/06/2004",
    "minimumYearRepaymentFormatted": "$18.00",
    "loanAmountFormatted": "$47.22"
  },
  "repayments": [],
  "inputs": {
    "incomeYearOfLoan": 1999,
    "fullTermOfAmalgamatedLoan": 7,
    "incomeYearOfEnquiring": 2004,
    "amalgamatedLoanNotPaidByEOIY": 47.22471982220584,
    "repayments": null,
    "lodgement_date": null
  },
  "idx": 7079
}