{
  "id": "2023-09-04T16:22:40.593Z0.278928598639147",
  "alert": "Start of result\nResult\n\nMinimum yearly repayment not met.\n\nThe amount of the loan not repaid at the end of income year 2019-20 is $104,996,637.70.\n\nThe private company may be taken to pay a dividend under Division 7A to the shareholder or shareholder's associate because the amount repaid during income year 2019-20 in relation to the amalgamated loan is less than the minimum yearly repayment required.\n\nInterest received by the private company must be included in the income tax return for 2019-20.\n\nMinimum yearly repayment\n\n$38,823,269.00\n\nBenchmark interest rate\n\n5.37%\n\nOpening balance:\n\nDate: 30/06/2019\n\nBalance: $104,996,637.70\n\nDays: 366\n\nInterest: $5,638,319.44\n\nTotal repayments\n\n$0\n\nTotal interest\n\n$5,638,319.44\n\nTotal principal\n\n$0\n\nClosing balance\n\nDate: 30/06/2020\n\nBalance: $104,996,637.70",
  "outputs": {
    "enquiryRateFormatted": "5.37%",
    "enquiryYearEndMinusOneDisplay": "30/06/2019",
    "amalgamatedLoanNotPaidByEOIYFormatted": "$104,996,637.70",
    "openingBalancePayDays": "366",
    "openingBalanceInterestFormatted": "$5,638,319.44",
    "totalAmountOfRepaymentFormatted": "$0",
    "totalInterestFormatted": "$5,638,319.44",
    "principalFormatted": "$0",
    "enquiryYearEndDisplay": "30/06/2020",
    "minimumYearRepaymentFormatted": "$38,823,269.00"
  },
  "repayments": [],
  "inputs": {
    "incomeYearOfLoan": 2019,
    "fullTermOfAmalgamatedLoan": 3,
    "incomeYearOfEnquiring": 2020,
    "amalgamatedLoanNotPaidByEOIY": 104996637.70697461,
    "repayments": null,
    "lodgement_date": "1/7/2019"
  },
  "idx": 390
}