{
  "id": "2023-10-31T19:20:29.941Z0.9127296595645504",
  "alert": "Start of result\nResult\n\nAmalgamated loan fully repaid.\n\nThe amalgamated loan has been paid in full.\u000bThe private company is not taken under Division 7A to pay a dividend to the shareholder or shareholder's associate.\n\nInterest received by the private company must be included in the income tax return for 2010-11.\n\nMinimum yearly repayment\n\n$17.00\n\nBenchmark interest rate\n\n7.4%\n\nOpening balance:\n\nDate: 30/06/2010\n\nBalance: $30.76\n\nDays: 188\n\nInterest: $1.17\n\nPayments\n\nDate: 05/01/2011\n\nAmount: $307.68\n\nBalance: $0\n\nDays: 177\n\nInterest: $0\n\n\n\n\nTotal repayments\n\n$307.68\n\nTotal interest\n\n$1.17\n\nTotal principal\n\n$306.51\n\nClosing balance\n\nDate: 30/06/2011\n\nBalance: $0",
  "outputs": {
    "enquiryRateFormatted": "7.4%",
    "enquiryYearEndMinusOneDisplay": "30/06/2010",
    "amalgamatedLoanNotPaidByEOIYFormatted": "$30.76",
    "openingBalancePayDays": "188",
    "openingBalanceInterestFormatted": "$1.17",
    "totalAmountOfRepaymentFormatted": "$307.68",
    "totalInterestFormatted": "$1.17",
    "principalFormatted": "$306.51",
    "enquiryYearEndDisplay": "30/06/2011",
    "minimumYearRepaymentFormatted": "$17.00",
    "loanAmountFormatted": "$0"
  },
  "repayments": [
    {
      "rd": "5/1/2011",
      "ra": 307.6870329440169
    }
  ],
  "inputs": {
    "incomeYearOfLoan": 2005,
    "fullTermOfAmalgamatedLoan": 7,
    "incomeYearOfEnquiring": 2011,
    "amalgamatedLoanNotPaidByEOIY": 30.768703294401686,
    "repayments": null,
    "lodgement_date": null
  },
  "idx": 5333
}