{
  "id": "2023-09-04T16:13:59.960Z0.7445922895778556",
  "alert": "Start of result\nResult\n\nMinimum yearly repayment not met.\n\nThe amount of the loan not repaid at the end of income year 2021-22 is $2,455.00.\n\nThe private company may be taken to pay a dividend under Division 7A to the shareholder or shareholder's associate because the amount repaid during income year 2021-22 in relation to the amalgamated loan is less than the minimum yearly repayment required.\n\nInterest received by the private company must be included in the income tax return for 2021-22.\n\nMinimum yearly repayment\n\n$2,566.00\n\nBenchmark interest rate\n\n4.52%\n\nOpening balance:\n\nDate: 30/06/2021\n\nBalance: $2,455.00\n\nDays: 365\n\nInterest: $110.97\n\nTotal repayments\n\n$0\n\nTotal interest\n\n$110.97\n\nTotal principal\n\n$0\n\nClosing balance\n\nDate: 30/06/2022\n\nBalance: $2,455.00",
  "outputs": {
    "enquiryRateFormatted": "4.52%",
    "enquiryYearEndMinusOneDisplay": "30/06/2021",
    "amalgamatedLoanNotPaidByEOIYFormatted": "$2,455.00",
    "openingBalancePayDays": "365",
    "openingBalanceInterestFormatted": "$110.97",
    "totalAmountOfRepaymentFormatted": "$0",
    "totalInterestFormatted": "$110.97",
    "principalFormatted": "$0",
    "enquiryYearEndDisplay": "30/06/2022",
    "minimumYearRepaymentFormatted": "$2,566.00"
  },
  "repayments": [],
  "inputs": {
    "incomeYearOfLoan": 2021,
    "fullTermOfAmalgamatedLoan": 1,
    "incomeYearOfEnquiring": 2022,
    "amalgamatedLoanNotPaidByEOIY": 2455,
    "repayments": null,
    "lodgement_date": "9/10/2021"
  },
  "idx": 49
}