{
  "id": "2023-10-31T21:00:54.076Z0.6294695000805238",
  "alert": "Start of result\nResult\n\nMinimum yearly repayment met.\n\nThe amount of the loan not repaid at the end of income year 1999-00 is $1,713.47.\n\n\u000b\n\nThe amalgamated loan will not be taken to be a dividend because the total repayments made are equal to or greater than the minimum yearly repayment required for income year 1999-00.\n\nInterest received by the private company must be included in the income tax return for 1999-00.\n\nMinimum yearly repayment\n\n$363.00\n\nBenchmark interest rate\n\n6.5%\n\nOpening balance:\n\nDate: 30/06/1999\n\nBalance: $6,331.00\n\nDays: 123\n\nInterest: $138.30\n\nPayments\n\nDate: 01/11/1999\n\nAmount: $4,821.00\n\nBalance: $1,510.00\n\nDays: 243\n\nInterest: $65.17\n\n\n\n\nTotal repayments\n\n$4,821.00\n\nTotal interest\n\n$203.47\n\nTotal principal\n\n$4,617.53\n\nClosing balance\n\nDate: 30/06/2000\n\nBalance: $1,713.47",
  "outputs": {
    "enquiryRateFormatted": "6.5%",
    "enquiryYearEndMinusOneDisplay": "30/06/1999",
    "amalgamatedLoanNotPaidByEOIYFormatted": "$6,331.00",
    "openingBalancePayDays": "123",
    "openingBalanceInterestFormatted": "$138.30",
    "totalAmountOfRepaymentFormatted": "$4,821.00",
    "totalInterestFormatted": "$203.47",
    "principalFormatted": "$4,617.53",
    "enquiryYearEndDisplay": "30/06/2000",
    "minimumYearRepaymentFormatted": "$363.00",
    "loanAmountFormatted": "$1,713.47"
  },
  "repayments": [
    {
      "rd": "1/11/1999",
      "ra": 4821
    }
  ],
  "inputs": {
    "incomeYearOfLoan": 1999,
    "fullTermOfAmalgamatedLoan": 5,
    "incomeYearOfEnquiring": 2000,
    "amalgamatedLoanNotPaidByEOIY": 6331,
    "repayments": null,
    "lodgement_date": "28/11/1999"
  },
  "idx": 6941
}