{
  "id": "2023-10-31T19:49:44.157Z0.5820734581810343",
  "alert": "Start of result\nResult\n\nMinimum yearly repayment not met.\n\nThe amount of the loan not repaid at the end of income year 2006-07 is $8,629.00.\n\nThe private company may be taken to pay a dividend under Division 7A to the shareholder or shareholder's associate because the amount repaid during income year 2006-07 in relation to the amalgamated loan is less than the minimum yearly repayment required.\n\nInterest received by the private company must be included in the income tax return for 2006-07.\n\nMinimum yearly repayment\n\n$2,579.00\n\nBenchmark interest rate\n\n7.55%\n\nOpening balance:\n\nDate: 30/06/2006\n\nBalance: $8,629.00\n\nDays: 6\n\nInterest: $10.71\n\nPayments\n\nDate: 07/07/2006\n\nAmount: $136.00\n\nBalance: $8,493.00\n\nDays: 359\n\nInterest: $630.68\n\n\n\n\nTotal repayments\n\n$136.00\n\nTotal interest\n\n$641.39\n\nTotal principal\n\n$0\n\nClosing balance\n\nDate: 30/06/2007\n\nBalance: $8,629.00",
  "outputs": {
    "enquiryRateFormatted": "7.55%",
    "enquiryYearEndMinusOneDisplay": "30/06/2006",
    "amalgamatedLoanNotPaidByEOIYFormatted": "$8,629.00",
    "openingBalancePayDays": "6",
    "openingBalanceInterestFormatted": "$10.71",
    "totalAmountOfRepaymentFormatted": "$136.00",
    "totalInterestFormatted": "$641.39",
    "principalFormatted": "$0",
    "enquiryYearEndDisplay": "30/06/2007",
    "minimumYearRepaymentFormatted": "$2,579.00",
    "loanAmountFormatted": "$8,629.00"
  },
  "repayments": [
    {
      "rd": "7/7/2006",
      "ra": 136
    }
  ],
  "inputs": {
    "incomeYearOfLoan": 2003,
    "fullTermOfAmalgamatedLoan": 7,
    "incomeYearOfEnquiring": 2007,
    "amalgamatedLoanNotPaidByEOIY": 8629,
    "repayments": null,
    "lodgement_date": null
  },
  "idx": 5890
}