{
  "id": "2023-10-31T18:08:10.982Z0.1549020569146886",
  "alert": "Start of result\nResult\n\nMinimum yearly repayment not met.\n\nThe amount of the loan not repaid at the end of income year 2012-13 is $19.54.\n\nThe private company may be taken to pay a dividend under Division 7A to the shareholder or shareholder's associate because the amount repaid during income year 2012-13 in relation to the amalgamated loan is less than the minimum yearly repayment required.\n\nInterest received by the private company must be included in the income tax return for 2012-13.\n\nMinimum yearly repayment\n\n$21.00\n\nBenchmark interest rate\n\n7.05%\n\nOpening balance:\n\nDate: 30/06/2012\n\nBalance: $19.54\n\nDays: 365\n\nInterest: $1.38\n\nTotal repayments\n\n$0\n\nTotal interest\n\n$1.38\n\nTotal principal\n\n$0\n\nClosing balance\n\nDate: 30/06/2013\n\nBalance: $19.54",
  "outputs": {
    "enquiryRateFormatted": "7.05%",
    "enquiryYearEndMinusOneDisplay": "30/06/2012",
    "amalgamatedLoanNotPaidByEOIYFormatted": "$19.54",
    "openingBalancePayDays": "365",
    "openingBalanceInterestFormatted": "$1.38",
    "totalAmountOfRepaymentFormatted": "$0",
    "totalInterestFormatted": "$1.38",
    "principalFormatted": "$0",
    "enquiryYearEndDisplay": "30/06/2013",
    "minimumYearRepaymentFormatted": "$21.00",
    "loanAmountFormatted": "$19.54"
  },
  "repayments": [],
  "inputs": {
    "incomeYearOfLoan": 2011,
    "fullTermOfAmalgamatedLoan": 2,
    "incomeYearOfEnquiring": 2013,
    "amalgamatedLoanNotPaidByEOIY": 19.5442259471049,
    "repayments": null,
    "lodgement_date": null
  },
  "idx": 3386
}