{
  "id": "2023-10-31T17:37:08.826Z0.9690660350247565",
  "alert": "Start of result\nResult\n\nAmalgamated loan fully repaid.\n\nThe amalgamated loan has been paid in full.\u000bThe private company is not taken under Division 7A to pay a dividend to the shareholder or shareholder's associate.\n\nInterest received by the private company must be included in the income tax return for 2016-17.\n\nMinimum yearly repayment\n\n$847.00\n\nBenchmark interest rate\n\n5.4%\n\nOpening balance:\n\nDate: 30/06/2016\n\nBalance: $4,831.00\n\nDays: 79\n\nInterest: $56.46\n\nPayments\n\nDate: 18/09/2016\n\nAmount: $8,391.00\n\nBalance: $0\n\nDays: 286\n\nInterest: $0\n\n\n\n\nTotal repayments\n\n$8,391.00\n\nTotal interest\n\n$56.46\n\nTotal principal\n\n$8,334.54\n\nClosing balance\n\nDate: 30/06/2017\n\nBalance: $0",
  "outputs": {
    "enquiryRateFormatted": "5.4%",
    "enquiryYearEndMinusOneDisplay": "30/06/2016",
    "amalgamatedLoanNotPaidByEOIYFormatted": "$4,831.00",
    "openingBalancePayDays": "79",
    "openingBalanceInterestFormatted": "$56.46",
    "totalAmountOfRepaymentFormatted": "$8,391.00",
    "totalInterestFormatted": "$56.46",
    "principalFormatted": "$8,334.54",
    "enquiryYearEndDisplay": "30/06/2017",
    "minimumYearRepaymentFormatted": "$847.00",
    "loanAmountFormatted": "$0"
  },
  "repayments": [
    {
      "rd": "18/9/2016",
      "ra": 8391
    }
  ],
  "inputs": {
    "incomeYearOfLoan": 2016,
    "fullTermOfAmalgamatedLoan": 7,
    "incomeYearOfEnquiring": 2017,
    "amalgamatedLoanNotPaidByEOIY": 4831,
    "repayments": null,
    "lodgement_date": "1/7/2016"
  },
  "idx": 2078
}