{
  "id": "2023-09-06T20:53:11.689Z0.577102398931489",
  "alert": "Start of result\nResult\n\nMinimum yearly repayment not met.\n\nThe amount of the loan not repaid at the end of income year 2004-05 is $0.62.\n\nThe private company may be taken to pay a dividend under Division 7A to the shareholder or shareholder's associate because the amount repaid during income year 2004-05 in relation to the amalgamated loan is less than the minimum yearly repayment required.\n\nInterest received by the private company must be included in the income tax return for 2004-05.\n\nMinimum yearly repayment\n\n$17.00\n\nBenchmark interest rate\n\n7.05%\n\nOpening balance:\n\nDate: 30/06/2004\n\nBalance: $15.79\n\nDays: 203\n\nInterest: $0.62\n\nPayments\n\nDate: 20/01/2005\n\nAmount: $15.79\n\nBalance: $0\n\nDays: 162\n\nInterest: $0\n\n\n\n\nTotal repayments\n\n$15.79\n\nTotal interest\n\n$0.62\n\nTotal principal\n\n$15.17\n\nClosing balance\n\nDate: 30/06/2005\n\nBalance: $0.62",
  "outputs": {
    "enquiryRateFormatted": "7.05%",
    "enquiryYearEndMinusOneDisplay": "30/06/2004",
    "amalgamatedLoanNotPaidByEOIYFormatted": "$15.79",
    "openingBalancePayDays": "203",
    "openingBalanceInterestFormatted": "$0.62",
    "totalAmountOfRepaymentFormatted": "$15.79",
    "totalInterestFormatted": "$0.62",
    "principalFormatted": "$15.17",
    "enquiryYearEndDisplay": "30/06/2005",
    "minimumYearRepaymentFormatted": "$17.00"
  },
  "repayments": [
    {
      "rd": "20/1/2005",
      "ra": 15.7936212743125
    }
  ],
  "inputs": {
    "incomeYearOfLoan": 2002,
    "fullTermOfAmalgamatedLoan": 3,
    "incomeYearOfEnquiring": 2005,
    "amalgamatedLoanNotPaidByEOIY": 15.793621274312347,
    "repayments": null,
    "lodgement_date": null
  },
  "idx": 3694
}