{
  "id": "2023-09-06T14:41:29.219Z0.25290869608489497",
  "alert": "Start of result\nResult\n\nMinimum yearly repayment met.\n\nThe amount of the loan not repaid at the end of income year 2007-08 is $2,384.74.\n\nThe amalgamated loan will not be taken to be a dividend because the total repayments made are equal to or greater than the minimum yearly repayment required for income year 2007-08.\n\nInterest received by the private company must be included in the income tax return for 2007-08.\n\nMinimum yearly repayment\n\n$2,097.00\n\nBenchmark interest rate\n\n8.05%\n\nOpening balance:\n\nDate: 30/06/2007\n\nBalance: $6,937.00\n\nDays: 352\n\nInterest: $537.07\n\nPayments\n\nDate: 17/06/2008\n\nAmount: $5,095.00\n\nBalance: $1,842.00\n\nDays: 14\n\nInterest: $5.67\n\n\n\n\nTotal repayments\n\n$5,095.00\n\nTotal interest\n\n$542.74\n\nTotal principal\n\n$4,552.26\n\nClosing balance\n\nDate: 30/06/2008\n\nBalance: $2,384.74",
  "outputs": {
    "enquiryRateFormatted": "8.05%",
    "enquiryYearEndMinusOneDisplay": "30/06/2007",
    "amalgamatedLoanNotPaidByEOIYFormatted": "$6,937.00",
    "openingBalancePayDays": "352",
    "openingBalanceInterestFormatted": "$537.07",
    "totalAmountOfRepaymentFormatted": "$5,095.00",
    "totalInterestFormatted": "$542.74",
    "principalFormatted": "$4,552.26",
    "enquiryYearEndDisplay": "30/06/2008",
    "minimumYearRepaymentFormatted": "$2,097.00"
  },
  "repayments": [
    {
      "rd": "17/6/2008",
      "ra": 5095
    }
  ],
  "inputs": {
    "incomeYearOfLoan": 2006,
    "fullTermOfAmalgamatedLoan": 5,
    "incomeYearOfEnquiring": 2008,
    "amalgamatedLoanNotPaidByEOIY": 6937,
    "repayments": null,
    "lodgement_date": null
  },
  "idx": 6282
}