{
  "id": "2023-09-05T02:17:15.126Z0.5613074560343043",
  "alert": "Start of result\nResult\n\nMinimum yearly repayment not met.\n\nThe amount of the loan not repaid at the end of income year 2004-05 is $474.23.\n\nThe private company may be taken to pay a dividend under Division 7A to the shareholder or shareholder's associate because the amount repaid during income year 2004-05 in relation to the amalgamated loan is less than the minimum yearly repayment required.\n\nInterest received by the private company must be included in the income tax return for 2004-05.\n\nMinimum yearly repayment\n\n$9,315.00\n\nBenchmark interest rate\n\n7.05%\n\nOpening balance:\n\nDate: 30/06/2004\n\nBalance: $8,702.00\n\nDays: 0\n\nInterest: $0\n\nPayments\n\nDate: 01/07/2004\n\nAmount: $8,259.00\n\nBalance: $443.00\n\nDays: 365\n\nInterest: $31.23\n\n\n\n\nTotal repayments\n\n$8,259.00\n\nTotal interest\n\n$31.23\n\nTotal principal\n\n$8,227.77\n\nClosing balance\n\nDate: 30/06/2005\n\nBalance: $474.23",
  "outputs": {
    "enquiryRateFormatted": "7.05%",
    "enquiryYearEndMinusOneDisplay": "30/06/2004",
    "amalgamatedLoanNotPaidByEOIYFormatted": "$8,702.00",
    "openingBalancePayDays": "0",
    "openingBalanceInterestFormatted": "$0",
    "totalAmountOfRepaymentFormatted": "$8,259.00",
    "totalInterestFormatted": "$31.23",
    "principalFormatted": "$8,227.77",
    "enquiryYearEndDisplay": "30/06/2005",
    "minimumYearRepaymentFormatted": "$9,315.00"
  },
  "repayments": [
    {
      "rd": "1/7/2004",
      "ra": 8259
    }
  ],
  "inputs": {
    "incomeYearOfLoan": 1998,
    "fullTermOfAmalgamatedLoan": 7,
    "incomeYearOfEnquiring": 2005,
    "amalgamatedLoanNotPaidByEOIY": 8702,
    "repayments": null,
    "lodgement_date": null
  },
  "idx": 5164
}