{
  "id": "2023-09-06T02:48:43.636Z0.5551909407439231",
  "alert": "Start of result\nResult\n\nMinimum yearly repayment met.\n\nThe amount of the loan not repaid at the end of income year 2013-14 is $256.89.\n\nThe amalgamated loan will not be taken to be a dividend because the total repayments made are equal to or greater than the minimum yearly repayment required for income year 2013-14.\n\nInterest received by the private company must be included in the income tax return for 2013-14.\n\nMinimum yearly repayment\n\n$1,781.00\n\nBenchmark interest rate\n\n6.2%\n\nOpening balance:\n\nDate: 30/06/2013\n\nBalance: $6,496.00\n\nDays: 108\n\nInterest: $119.17\n\nPayments\n\nDate: 17/10/2013\n\nAmount: $3,240.00\n\nBalance: $3,256.00\n\nDays: 249\n\nInterest: $137.72\n\n\n\n\nDate: 23/06/2014\n\nAmount: $3,256.00\n\nBalance: $0\n\nDays: 8\n\nInterest: $0\n\n\n\n\nTotal repayments\n\n$6,496.00\n\nTotal interest\n\n$256.89\n\nTotal principal\n\n$6,239.11\n\nClosing balance\n\nDate: 30/06/2014\n\nBalance: $256.89",
  "outputs": {
    "enquiryRateFormatted": "6.2%",
    "enquiryYearEndMinusOneDisplay": "30/06/2013",
    "amalgamatedLoanNotPaidByEOIYFormatted": "$6,496.00",
    "openingBalancePayDays": "108",
    "openingBalanceInterestFormatted": "$119.17",
    "totalAmountOfRepaymentFormatted": "$6,496.00",
    "totalInterestFormatted": "$256.89",
    "principalFormatted": "$6,239.11",
    "enquiryYearEndDisplay": "30/06/2014",
    "minimumYearRepaymentFormatted": "$1,781.00"
  },
  "repayments": [
    {
      "rd": "17/10/2013",
      "ra": 3240
    },
    {
      "rd": "23/6/2014",
      "ra": 3256
    }
  ],
  "inputs": {
    "incomeYearOfLoan": 2013,
    "fullTermOfAmalgamatedLoan": 2,
    "incomeYearOfEnquiring": 2014,
    "amalgamatedLoanNotPaidByEOIY": 6496,
    "repayments": null,
    "lodgement_date": "8/3/2014"
  },
  "idx": 1716
}