{
  "id": "2023-09-04T16:14:19.253Z0.3910925320200269",
  "alert": "Start of result\nResult\n\nMinimum yearly repayment not met.\n\nThe amount of the loan not repaid at the end of income year 2021-22 is $5,209.28.\n\nThe private company may be taken to pay a dividend under Division 7A to the shareholder or shareholder's associate because the amount repaid during income year 2021-22 in relation to the amalgamated loan is less than the minimum yearly repayment required.\n\nInterest received by the private company must be included in the income tax return for 2021-22.\n\nMinimum yearly repayment\n\n$2,662.00\n\nBenchmark interest rate\n\n4.52%\n\nOpening balance:\n\nDate: 30/06/2021\n\nBalance: $6,980.00\n\nDays: 0\n\nInterest: $0\n\nPayments\n\nDate: 01/07/2021\n\nAmount: $1,996.00\n\nBalance: $4,984.00\n\nDays: 365\n\nInterest: $225.28\n\n\n\n\nTotal repayments\n\n$1,996.00\n\nTotal interest\n\n$225.28\n\nTotal principal\n\n$1,770.72\n\nClosing balance\n\nDate: 30/06/2022\n\nBalance: $5,209.28",
  "outputs": {
    "enquiryRateFormatted": "4.52%",
    "enquiryYearEndMinusOneDisplay": "30/06/2021",
    "amalgamatedLoanNotPaidByEOIYFormatted": "$6,980.00",
    "openingBalancePayDays": "0",
    "openingBalanceInterestFormatted": "$0",
    "totalAmountOfRepaymentFormatted": "$1,996.00",
    "totalInterestFormatted": "$225.28",
    "principalFormatted": "$1,770.72",
    "enquiryYearEndDisplay": "30/06/2022",
    "minimumYearRepaymentFormatted": "$2,662.00"
  },
  "repayments": [
    {
      "rd": "1/7/2021",
      "ra": 1996
    }
  ],
  "inputs": {
    "incomeYearOfLoan": 2021,
    "fullTermOfAmalgamatedLoan": 2,
    "incomeYearOfEnquiring": 2022,
    "amalgamatedLoanNotPaidByEOIY": 6980,
    "repayments": null,
    "lodgement_date": "9/10/2021"
  },
  "idx": 66
}