{
  "id": "2023-09-04T16:14:11.087Z0.6832591642487367",
  "alert": "Start of result\nResult\n\nMinimum yearly repayment not met.\n\nThe amount of the loan not repaid at the end of income year 2022-23 is $89,264,482.01.\n\nThe private company may be taken to pay a dividend under Division 7A to the shareholder or shareholder's associate because the amount repaid during income year 2022-23 in relation to the amalgamated loan is less than the minimum yearly repayment required.\n\nInterest received by the private company must be included in the income tax return for 2022-23.\n\nMinimum yearly repayment\n\n$93,522,398.00\n\nBenchmark interest rate\n\n4.77%\n\nOpening balance:\n\nDate: 30/06/2022\n\nBalance: $89,264,482.01\n\nDays: 0\n\nInterest: $0\n\nPayments\n\nDate: 01/07/2022\n\nAmount: $5,856.00\n\nBalance: $89,258,626.01\n\nDays: 365\n\nInterest: $4,257,636.46\n\n\n\n\nTotal repayments\n\n$5,856.00\n\nTotal interest\n\n$4,257,636.46\n\nTotal principal\n\n$0\n\nClosing balance\n\nDate: 30/06/2023\n\nBalance: $89,264,482.01",
  "outputs": {
    "enquiryRateFormatted": "4.77%",
    "enquiryYearEndMinusOneDisplay": "30/06/2022",
    "amalgamatedLoanNotPaidByEOIYFormatted": "$89,264,482.01",
    "openingBalancePayDays": "0",
    "openingBalanceInterestFormatted": "$0",
    "totalAmountOfRepaymentFormatted": "$5,856.00",
    "totalInterestFormatted": "$4,257,636.46",
    "principalFormatted": "$0",
    "enquiryYearEndDisplay": "30/06/2023",
    "minimumYearRepaymentFormatted": "$93,522,398.00"
  },
  "repayments": [
    {
      "rd": "1/7/2022",
      "ra": 5856
    }
  ],
  "inputs": {
    "incomeYearOfLoan": 2021,
    "fullTermOfAmalgamatedLoan": 2,
    "incomeYearOfEnquiring": 2023,
    "amalgamatedLoanNotPaidByEOIY": 89264482.01651205,
    "repayments": null,
    "lodgement_date": null
  },
  "idx": 59
}