{
  "id": "2023-09-04T20:59:02.511Z0.4576706169583822",
  "alert": "Start of result\nResult\n\nMinimum yearly repayment not met.\n\nThe amount of the loan not repaid at the end of income year 2013-14 is $13,058,783.55.\n\nThe private company may be taken to pay a dividend under Division 7A to the shareholder or shareholder's associate because the amount repaid during income year 2013-14 in relation to the amalgamated loan is less than the minimum yearly repayment required.\n\nInterest received by the private company must be included in the income tax return for 2013-14.\n\nMinimum yearly repayment\n\n$4,903,507.00\n\nBenchmark interest rate\n\n6.2%\n\nOpening balance:\n\nDate: 30/06/2013\n\nBalance: $13,058,783.55\n\nDays: 365\n\nInterest: $809,644.58\n\nTotal repayments\n\n$0\n\nTotal interest\n\n$809,644.58\n\nTotal principal\n\n$0\n\nClosing balance\n\nDate: 30/06/2014\n\nBalance: $13,058,783.55",
  "outputs": {
    "enquiryRateFormatted": "6.2%",
    "enquiryYearEndMinusOneDisplay": "30/06/2013",
    "amalgamatedLoanNotPaidByEOIYFormatted": "$13,058,783.55",
    "openingBalancePayDays": "365",
    "openingBalanceInterestFormatted": "$809,644.58",
    "totalAmountOfRepaymentFormatted": "$0",
    "totalInterestFormatted": "$809,644.58",
    "principalFormatted": "$0",
    "enquiryYearEndDisplay": "30/06/2014",
    "minimumYearRepaymentFormatted": "$4,903,507.00"
  },
  "repayments": [],
  "inputs": {
    "incomeYearOfLoan": 2010,
    "fullTermOfAmalgamatedLoan": 6,
    "incomeYearOfEnquiring": 2014,
    "amalgamatedLoanNotPaidByEOIY": 13058783.554251311,
    "repayments": null,
    "lodgement_date": null
  },
  "idx": 437
}