{
  "id": "2023-09-04T22:17:14.954Z0.5703399587856559",
  "alert": "Start of result\nResult\n\nMinimum yearly repayment not met.\n\nThe amount of the loan not repaid at the end of income year 2003-04 is $87,372,064.91.\n\nThe private company may be taken to pay a dividend under Division 7A to the shareholder or shareholder's associate because the amount repaid during income year 2003-04 in relation to the amalgamated loan is less than the minimum yearly repayment required.\n\nInterest received by the private company must be included in the income tax return for 2003-04.\n\nMinimum yearly repayment\n\n$48,023,555.00\n\nBenchmark interest rate\n\n6.55%\n\nOpening balance:\n\nDate: 30/06/2003\n\nBalance: $87,372,064.91\n\nDays: 0\n\nInterest: $0\n\nPayments\n\nDate: 01/07/2003\n\nAmount: $404.00\n\nBalance: $87,371,660.91\n\nDays: 99\n\nInterest: $1,547,982.34\n\n\n\n\nDate: 08/10/2003\n\nAmount: $4,178.00\n\nBalance: $87,367,482.91\n\nDays: 18\n\nInterest: $281,437.88\n\n\n\n\nDate: 26/10/2003\n\nAmount: $9,925.00\n\nBalance: $87,357,557.91\n\nDays: 249\n\nInterest: $3,892,781.67\n\n\n\n\nTotal repayments\n\n$14,507.00\n\nTotal interest\n\n$5,722,201.89\n\nTotal principal\n\n$0\n\nClosing balance\n\nDate: 30/06/2004\n\nBalance: $87,372,064.91",
  "outputs": {
    "enquiryRateFormatted": "6.55%",
    "enquiryYearEndMinusOneDisplay": "30/06/2003",
    "amalgamatedLoanNotPaidByEOIYFormatted": "$87,372,064.91",
    "openingBalancePayDays": "0",
    "openingBalanceInterestFormatted": "$0",
    "totalAmountOfRepaymentFormatted": "$14,507.00",
    "totalInterestFormatted": "$5,722,201.89",
    "principalFormatted": "$0",
    "enquiryYearEndDisplay": "30/06/2004",
    "minimumYearRepaymentFormatted": "$48,023,555.00"
  },
  "repayments": [
    {
      "rd": "1/7/2003",
      "ra": 404
    },
    {
      "rd": "8/10/2003",
      "ra": 4178
    },
    {
      "rd": "26/10/2003",
      "ra": 9925
    }
  ],
  "inputs": {
    "incomeYearOfLoan": 2001,
    "fullTermOfAmalgamatedLoan": 4,
    "incomeYearOfEnquiring": 2004,
    "amalgamatedLoanNotPaidByEOIY": 87372064.91219437,
    "repayments": null,
    "lodgement_date": null
  },
  "idx": 637
}