{
  "id": "2023-09-06T05:55:04.534Z0.7317304347278242",
  "alert": "Start of result\nResult\n\nMinimum yearly repayment not met.\n\nThe amount of the loan not repaid at the end of income year 2011-12 is $19.28.\n\nThe private company may be taken to pay a dividend under Division 7A to the shareholder or shareholder's associate because the amount repaid during income year 2011-12 in relation to the amalgamated loan is less than the minimum yearly repayment required.\n\nInterest received by the private company must be included in the income tax return for 2011-12.\n\nMinimum yearly repayment\n\n$11.00\n\nBenchmark interest rate\n\n7.8%\n\nOpening balance:\n\nDate: 30/06/2011\n\nBalance: $19.28\n\nDays: 366\n\nInterest: $1.50\n\nTotal repayments\n\n$0\n\nTotal interest\n\n$1.50\n\nTotal principal\n\n$0\n\nClosing balance\n\nDate: 30/06/2012\n\nBalance: $19.28",
  "outputs": {
    "enquiryRateFormatted": "7.8%",
    "enquiryYearEndMinusOneDisplay": "30/06/2011",
    "amalgamatedLoanNotPaidByEOIYFormatted": "$19.28",
    "openingBalancePayDays": "366",
    "openingBalanceInterestFormatted": "$1.50",
    "totalAmountOfRepaymentFormatted": "$0",
    "totalInterestFormatted": "$1.50",
    "principalFormatted": "$0",
    "enquiryYearEndDisplay": "30/06/2012",
    "minimumYearRepaymentFormatted": "$11.00"
  },
  "repayments": [],
  "inputs": {
    "incomeYearOfLoan": 2011,
    "fullTermOfAmalgamatedLoan": 2,
    "incomeYearOfEnquiring": 2012,
    "amalgamatedLoanNotPaidByEOIY": 19.286449396283544,
    "repayments": null,
    "lodgement_date": "29/3/2012"
  },
  "idx": 3975
}