{
  "id": "2023-09-06T19:27:12.535Z0.26043159135809635",
  "alert": "Start of result\nResult\n\nMinimum yearly repayment not met.\n\nThe amount of the loan not repaid at the end of income year 2006-07 is $62.78.\n\nThe private company may be taken to pay a dividend under Division 7A to the shareholder or shareholder's associate because the amount repaid during income year 2006-07 in relation to the amalgamated loan is less than the minimum yearly repayment required.\n\nInterest received by the private company must be included in the income tax return for 2006-07.\n\nMinimum yearly repayment\n\n$68.00\n\nBenchmark interest rate\n\n7.55%\n\nOpening balance:\n\nDate: 30/06/2006\n\nBalance: $62.78\n\nDays: 365\n\nInterest: $4.74\n\nTotal repayments\n\n$0\n\nTotal interest\n\n$4.74\n\nTotal principal\n\n$0\n\nClosing balance\n\nDate: 30/06/2007\n\nBalance: $62.78",
  "outputs": {
    "enquiryRateFormatted": "7.55%",
    "enquiryYearEndMinusOneDisplay": "30/06/2006",
    "amalgamatedLoanNotPaidByEOIYFormatted": "$62.78",
    "openingBalancePayDays": "365",
    "openingBalanceInterestFormatted": "$4.74",
    "totalAmountOfRepaymentFormatted": "$0",
    "totalInterestFormatted": "$4.74",
    "principalFormatted": "$0",
    "enquiryYearEndDisplay": "30/06/2007",
    "minimumYearRepaymentFormatted": "$68.00"
  },
  "repayments": [],
  "inputs": {
    "incomeYearOfLoan": 2003,
    "fullTermOfAmalgamatedLoan": 4,
    "incomeYearOfEnquiring": 2007,
    "amalgamatedLoanNotPaidByEOIY": 62.78290795370228,
    "repayments": null,
    "lodgement_date": null
  },
  "idx": 5904
}