{
  "id": "2023-09-05T23:13:48.014Z0.579609192879105",
  "alert": "Start of result\nResult\n\nMinimum yearly repayment met.\n\nThe amount of the loan not repaid at the end of income year 2016-17 is $36.18.\n\nThe amalgamated loan will not be taken to be a dividend because the total repayments made are equal to or greater than the minimum yearly repayment required for income year 2016-17.\n\nInterest received by the private company must be included in the income tax return for 2016-17.\n\nMinimum yearly repayment\n\n$2,939.00\n\nBenchmark interest rate\n\n5.4%\n\nOpening balance:\n\nDate: 30/06/2016\n\nBalance: $5,434.00\n\nDays: 45\n\nInterest: $36.18\n\nPayments\n\nDate: 15/08/2016\n\nAmount: $5,434.00\n\nBalance: $0\n\nDays: 320\n\nInterest: $0\n\n\n\n\nTotal repayments\n\n$5,434.00\n\nTotal interest\n\n$36.18\n\nTotal principal\n\n$5,397.82\n\nClosing balance\n\nDate: 30/06/2017\n\nBalance: $36.18",
  "outputs": {
    "enquiryRateFormatted": "5.4%",
    "enquiryYearEndMinusOneDisplay": "30/06/2016",
    "amalgamatedLoanNotPaidByEOIYFormatted": "$5,434.00",
    "openingBalancePayDays": "45",
    "openingBalanceInterestFormatted": "$36.18",
    "totalAmountOfRepaymentFormatted": "$5,434.00",
    "totalInterestFormatted": "$36.18",
    "principalFormatted": "$5,397.82",
    "enquiryYearEndDisplay": "30/06/2017",
    "minimumYearRepaymentFormatted": "$2,939.00"
  },
  "repayments": [
    {
      "rd": "15/8/2016",
      "ra": 5434
    }
  ],
  "inputs": {
    "incomeYearOfLoan": 2015,
    "fullTermOfAmalgamatedLoan": 3,
    "incomeYearOfEnquiring": 2017,
    "amalgamatedLoanNotPaidByEOIY": 5434,
    "repayments": null,
    "lodgement_date": null
  },
  "idx": 7006
}