{
  "id": "2023-10-31T19:36:32.260Z0.6853543473636666",
  "alert": "Start of result\nResult\n\nAmalgamated loan fully repaid.\n\nThe amalgamated loan has been paid in full.\u000bThe private company is not taken under Division 7A to pay a dividend to the shareholder or shareholder's associate.\n\nInterest received by the private company must be included in the income tax return for 2003-04.\n\nMinimum yearly repayment\n\n-$838.00\n\nBenchmark interest rate\n\n6.55%\n\nOpening balance:\n\nDate: 30/06/2003\n\nBalance: $87.35\n\nDays: 344\n\nInterest: $5.38\n\nPayments\n\nDate: 09/06/2004\n\nAmount: $873.50\n\nBalance: $0\n\nDays: 22\n\nInterest: $0\n\n\n\n\nTotal repayments\n\n$873.50\n\nTotal interest\n\n$5.38\n\nTotal principal\n\n$868.12\n\nClosing balance\n\nDate: 30/06/2004\n\nBalance: $0",
  "outputs": {
    "enquiryRateFormatted": "6.55%",
    "enquiryYearEndMinusOneDisplay": "30/06/2003",
    "amalgamatedLoanNotPaidByEOIYFormatted": "$87.35",
    "openingBalancePayDays": "344",
    "openingBalanceInterestFormatted": "$5.38",
    "totalAmountOfRepaymentFormatted": "$873.50",
    "totalInterestFormatted": "$5.38",
    "principalFormatted": "$868.12",
    "enquiryYearEndDisplay": "30/06/2004",
    "minimumYearRepaymentFormatted": "-$838.00",
    "loanAmountFormatted": "$0"
  },
  "repayments": [
    {
      "rd": "9/6/2004",
      "ra": 873.5041033398911
    }
  ],
  "inputs": {
    "incomeYearOfLoan": 2003,
    "fullTermOfAmalgamatedLoan": 1,
    "incomeYearOfEnquiring": 2004,
    "amalgamatedLoanNotPaidByEOIY": 87.3504103339891,
    "repayments": null,
    "lodgement_date": "30/6/2004"
  },
  "idx": 5656
}