{
  "id": "2023-09-06T14:41:18.885Z0.0834568495814545",
  "alert": "Start of result\nResult\n\nMinimum yearly repayment met.\n\nThe amount of the loan not repaid at the end of income year 2009-10 is $3,428.05.\n\nThe amalgamated loan will not be taken to be a dividend because the total repayments made are equal to or greater than the minimum yearly repayment required for income year 2009-10.\n\nInterest received by the private company must be included in the income tax return for 2009-10.\n\nMinimum yearly repayment\n\n$6,414.00\n\nBenchmark interest rate\n\n5.75%\n\nOpening balance:\n\nDate: 30/06/2009\n\nBalance: $11,801.00\n\nDays: 138\n\nInterest: $256.55\n\nPayments\n\nDate: 16/11/2009\n\nAmount: $8,739.00\n\nBalance: $3,062.00\n\nDays: 227\n\nInterest: $109.50\n\n\n\n\nTotal repayments\n\n$8,739.00\n\nTotal interest\n\n$366.05\n\nTotal principal\n\n$8,372.95\n\nClosing balance\n\nDate: 30/06/2010\n\nBalance: $3,428.05",
  "outputs": {
    "enquiryRateFormatted": "5.75%",
    "enquiryYearEndMinusOneDisplay": "30/06/2009",
    "amalgamatedLoanNotPaidByEOIYFormatted": "$11,801.00",
    "openingBalancePayDays": "138",
    "openingBalanceInterestFormatted": "$256.55",
    "totalAmountOfRepaymentFormatted": "$8,739.00",
    "totalInterestFormatted": "$366.05",
    "principalFormatted": "$8,372.95",
    "enquiryYearEndDisplay": "30/06/2010",
    "minimumYearRepaymentFormatted": "$6,414.00"
  },
  "repayments": [
    {
      "rd": "16/11/2009",
      "ra": 8739
    }
  ],
  "inputs": {
    "incomeYearOfLoan": 2006,
    "fullTermOfAmalgamatedLoan": 5,
    "incomeYearOfEnquiring": 2010,
    "amalgamatedLoanNotPaidByEOIY": 11801,
    "repayments": null,
    "lodgement_date": null
  },
  "idx": 6277
}