{
  "id": "2023-10-31T20:58:09.662Z0.9545507012850935",
  "alert": "Start of result\nResult\n\nAmalgamated loan fully repaid.\n\nThe amalgamated loan has been paid in full.\u000bThe private company is not taken under Division 7A to pay a dividend to the shareholder or shareholder's associate.\n\nInterest received by the private company must be included in the income tax return for 1999-00.\n\nMinimum yearly repayment\n\n-$216.00\n\nBenchmark interest rate\n\n6.5%\n\nOpening balance:\n\nDate: 30/06/1999\n\nBalance: $3,383.00\n\nDays: 36\n\nInterest: $21.63\n\nPayments\n\nDate: 06/08/1999\n\nAmount: $4,122.00\n\nBalance: $0\n\nDays: 330\n\nInterest: $0\n\n\n\n\nTotal repayments\n\n$4,122.00\n\nTotal interest\n\n$21.63\n\nTotal principal\n\n$4,100.37\n\nClosing balance\n\nDate: 30/06/2000\n\nBalance: $0",
  "outputs": {
    "enquiryRateFormatted": "6.5%",
    "enquiryYearEndMinusOneDisplay": "30/06/1999",
    "amalgamatedLoanNotPaidByEOIYFormatted": "$3,383.00",
    "openingBalancePayDays": "36",
    "openingBalanceInterestFormatted": "$21.63",
    "totalAmountOfRepaymentFormatted": "$4,122.00",
    "totalInterestFormatted": "$21.63",
    "principalFormatted": "$4,100.37",
    "enquiryYearEndDisplay": "30/06/2000",
    "minimumYearRepaymentFormatted": "-$216.00",
    "loanAmountFormatted": "$0"
  },
  "repayments": [
    {
      "rd": "6/8/1999",
      "ra": 4122
    }
  ],
  "inputs": {
    "incomeYearOfLoan": 1999,
    "fullTermOfAmalgamatedLoan": 4,
    "incomeYearOfEnquiring": 2000,
    "amalgamatedLoanNotPaidByEOIY": 3383,
    "repayments": null,
    "lodgement_date": "27/1/2000"
  },
  "idx": 6907
}