{
  "id": "2023-09-06T08:15:06.049Z0.07868490414239515",
  "alert": "Start of result\nResult\n\nMinimum yearly repayment not met.\n\nThe amount of the loan not repaid at the end of income year 2010-11 is $122.86.\n\nThe private company may be taken to pay a dividend under Division 7A to the shareholder or shareholder's associate because the amount repaid during income year 2010-11 in relation to the amalgamated loan is less than the minimum yearly repayment required.\n\nInterest received by the private company must be included in the income tax return for 2010-11.\n\nMinimum yearly repayment\n\n$30.00\n\nBenchmark interest rate\n\n7.4%\n\nOpening balance:\n\nDate: 30/06/2010\n\nBalance: $122.86\n\nDays: 365\n\nInterest: $9.09\n\nTotal repayments\n\n$0\n\nTotal interest\n\n$9.09\n\nTotal principal\n\n$0\n\nClosing balance\n\nDate: 30/06/2011\n\nBalance: $122.86",
  "outputs": {
    "enquiryRateFormatted": "7.4%",
    "enquiryYearEndMinusOneDisplay": "30/06/2010",
    "amalgamatedLoanNotPaidByEOIYFormatted": "$122.86",
    "openingBalancePayDays": "365",
    "openingBalanceInterestFormatted": "$9.09",
    "totalAmountOfRepaymentFormatted": "$0",
    "totalInterestFormatted": "$9.09",
    "principalFormatted": "$0",
    "enquiryYearEndDisplay": "30/06/2011",
    "minimumYearRepaymentFormatted": "$30.00"
  },
  "repayments": [],
  "inputs": {
    "incomeYearOfLoan": 2010,
    "fullTermOfAmalgamatedLoan": 5,
    "incomeYearOfEnquiring": 2011,
    "amalgamatedLoanNotPaidByEOIY": 122.86121234762837,
    "repayments": null,
    "lodgement_date": "11/3/2011"
  },
  "idx": 2468
}