{
  "id": "2023-09-04T22:19:46.348Z0.8464693526787026",
  "alert": "Start of result\nResult\n\nMinimum yearly repayment not met.\n\nThe amount of the loan not repaid at the end of income year 2001-02 is $120,147,959.77.\n\nThe private company may be taken to pay a dividend under Division 7A to the shareholder or shareholder's associate because the amount repaid during income year 2001-02 in relation to the amalgamated loan is less than the minimum yearly repayment required.\n\nInterest received by the private company must be included in the income tax return for 2001-02.\n\nMinimum yearly repayment\n\n$22,138,636.00\n\nBenchmark interest rate\n\n6.8%\n\nOpening balance:\n\nDate: 30/06/2001\n\nBalance: $120,147,959.77\n\nDays: 365\n\nInterest: $8,170,061.26\n\nTotal repayments\n\n$0\n\nTotal interest\n\n$8,170,061.26\n\nTotal principal\n\n$0\n\nClosing balance\n\nDate: 30/06/2002\n\nBalance: $120,147,959.77",
  "outputs": {
    "enquiryRateFormatted": "6.8%",
    "enquiryYearEndMinusOneDisplay": "30/06/2001",
    "amalgamatedLoanNotPaidByEOIYFormatted": "$120,147,959.77",
    "openingBalancePayDays": "365",
    "openingBalanceInterestFormatted": "$8,170,061.26",
    "totalAmountOfRepaymentFormatted": "$0",
    "totalInterestFormatted": "$8,170,061.26",
    "principalFormatted": "$0",
    "enquiryYearEndDisplay": "30/06/2002",
    "minimumYearRepaymentFormatted": "$22,138,636.00"
  },
  "repayments": [],
  "inputs": {
    "incomeYearOfLoan": 2001,
    "fullTermOfAmalgamatedLoan": 7,
    "incomeYearOfEnquiring": 2002,
    "amalgamatedLoanNotPaidByEOIY": 120147959.77930652,
    "repayments": null,
    "lodgement_date": "27/4/2002"
  },
  "idx": 717
}