{
  "id": "2023-09-04T16:19:46.986Z0.006062462019809978",
  "alert": "Start of result\nResult\n\nMinimum yearly repayment not met.\n\nThe amount of the loan not repaid at the end of income year 2022-23 is $8,635.14.\n\nThe private company may be taken to pay a dividend under Division 7A to the shareholder or shareholder's associate because the amount repaid during income year 2022-23 in relation to the amalgamated loan is less than the minimum yearly repayment required.\n\nInterest received by the private company must be included in the income tax return for 2022-23.\n\nMinimum yearly repayment\n\n$4,487.00\n\nBenchmark interest rate\n\n4.77%\n\nOpening balance:\n\nDate: 30/06/2022\n\nBalance: $12,272.00\n\nDays: 0\n\nInterest: $0\n\nPayments\n\nDate: 01/07/2022\n\nAmount: $4,030.00\n\nBalance: $8,242.00\n\nDays: 365\n\nInterest: $393.14\n\n\n\n\nTotal repayments\n\n$4,030.00\n\nTotal interest\n\n$393.14\n\nTotal principal\n\n$3,636.86\n\nClosing balance\n\nDate: 30/06/2023\n\nBalance: $8,635.14",
  "outputs": {
    "enquiryRateFormatted": "4.77%",
    "enquiryYearEndMinusOneDisplay": "30/06/2022",
    "amalgamatedLoanNotPaidByEOIYFormatted": "$12,272.00",
    "openingBalancePayDays": "0",
    "openingBalanceInterestFormatted": "$0",
    "totalAmountOfRepaymentFormatted": "$4,030.00",
    "totalInterestFormatted": "$393.14",
    "principalFormatted": "$3,636.86",
    "enquiryYearEndDisplay": "30/06/2023",
    "minimumYearRepaymentFormatted": "$4,487.00"
  },
  "repayments": [
    {
      "rd": "1/7/2022",
      "ra": 4030
    }
  ],
  "inputs": {
    "incomeYearOfLoan": 2020,
    "fullTermOfAmalgamatedLoan": 5,
    "incomeYearOfEnquiring": 2023,
    "amalgamatedLoanNotPaidByEOIY": 12272,
    "repayments": null,
    "lodgement_date": null
  },
  "idx": 281
}