{
  "id": "2023-09-04T17:41:10.443Z0.2981247674566754",
  "alert": "Start of result\nResult\n\nMinimum yearly repayment not met.\n\nThe amount of the loan not repaid at the end of income year 2012-13 is $122,805,145.22.\n\nThe private company may be taken to pay a dividend under Division 7A to the shareholder or shareholder's associate because the amount repaid during income year 2012-13 in relation to the amalgamated loan is less than the minimum yearly repayment required.\n\nInterest received by the private company must be included in the income tax return for 2012-13.\n\nMinimum yearly repayment\n\n$46,834,893.00\n\nBenchmark interest rate\n\n7.05%\n\nOpening balance:\n\nDate: 30/06/2012\n\nBalance: $122,805,145.22\n\nDays: 0\n\nInterest: $0\n\nPayments\n\nDate: 01/07/2012\n\nAmount: $7,779.00\n\nBalance: $122,797,366.22\n\nDays: 365\n\nInterest: $8,657,214.32\n\n\n\n\nTotal repayments\n\n$7,779.00\n\nTotal interest\n\n$8,657,214.32\n\nTotal principal\n\n$0\n\nClosing balance\n\nDate: 30/06/2013\n\nBalance: $122,805,145.22",
  "outputs": {
    "enquiryRateFormatted": "7.05%",
    "enquiryYearEndMinusOneDisplay": "30/06/2012",
    "amalgamatedLoanNotPaidByEOIYFormatted": "$122,805,145.22",
    "openingBalancePayDays": "0",
    "openingBalanceInterestFormatted": "$0",
    "totalAmountOfRepaymentFormatted": "$7,779.00",
    "totalInterestFormatted": "$8,657,214.32",
    "principalFormatted": "$0",
    "enquiryYearEndDisplay": "30/06/2013",
    "minimumYearRepaymentFormatted": "$46,834,893.00"
  },
  "repayments": [
    {
      "rd": "1/7/2012",
      "ra": 7779
    }
  ],
  "inputs": {
    "incomeYearOfLoan": 2012,
    "fullTermOfAmalgamatedLoan": 3,
    "incomeYearOfEnquiring": 2013,
    "amalgamatedLoanNotPaidByEOIY": 122805145.2267906,
    "repayments": null,
    "lodgement_date": "27/4/2013"
  },
  "idx": 2465
}