{
  "id": "2023-10-31T18:00:07.363Z0.09916065110780792",
  "alert": "Start of result\nResult\n\nMinimum yearly repayment not met.\n\nThe amount of the loan not repaid at the end of income year 2012-13 is $8,447.16.\n\nThe private company may be taken to pay a dividend under Division 7A to the shareholder or shareholder's associate because the amount repaid during income year 2012-13 in relation to the amalgamated loan is less than the minimum yearly repayment required.\n\nInterest received by the private company must be included in the income tax return for 2012-13.\n\nMinimum yearly repayment\n\n$10,018.00\n\nBenchmark interest rate\n\n7.05%\n\nOpening balance:\n\nDate: 30/06/2012\n\nBalance: $9,358.00\n\nDays: 125\n\nInterest: $225.94\n\nPayments\n\nDate: 03/11/2012\n\nAmount: $1,501.00\n\nBalance: $7,857.00\n\nDays: 240\n\nInterest: $364.22\n\n\n\n\nTotal repayments\n\n$1,501.00\n\nTotal interest\n\n$590.16\n\nTotal principal\n\n$910.84\n\nClosing balance\n\nDate: 30/06/2013\n\nBalance: $8,447.16",
  "outputs": {
    "enquiryRateFormatted": "7.05%",
    "enquiryYearEndMinusOneDisplay": "30/06/2012",
    "amalgamatedLoanNotPaidByEOIYFormatted": "$9,358.00",
    "openingBalancePayDays": "125",
    "openingBalanceInterestFormatted": "$225.94",
    "totalAmountOfRepaymentFormatted": "$1,501.00",
    "totalInterestFormatted": "$590.16",
    "principalFormatted": "$910.84",
    "enquiryYearEndDisplay": "30/06/2013",
    "minimumYearRepaymentFormatted": "$10,018.00",
    "loanAmountFormatted": "$8,447.16"
  },
  "repayments": [
    {
      "rd": "3/11/2012",
      "ra": 1501
    }
  ],
  "inputs": {
    "incomeYearOfLoan": 2012,
    "fullTermOfAmalgamatedLoan": 1,
    "incomeYearOfEnquiring": 2013,
    "amalgamatedLoanNotPaidByEOIY": 9358,
    "repayments": null,
    "lodgement_date": "1/7/2012"
  },
  "idx": 3094
}