{
  "id": "2023-09-04T16:43:16.550Z0.759621393127093",
  "alert": "Start of result\nResult\n\nMinimum yearly repayment not met.\n\nThe amount of the loan not repaid at the end of income year 2016-17 is $121,581,127.64.\n\nThe private company may be taken to pay a dividend under Division 7A to the shareholder or shareholder's associate because the amount repaid during income year 2016-17 in relation to the amalgamated loan is less than the minimum yearly repayment required.\n\nInterest received by the private company must be included in the income tax return for 2016-17.\n\nMinimum yearly repayment\n\n$44,980,398.00\n\nBenchmark interest rate\n\n5.4%\n\nOpening balance:\n\nDate: 30/06/2016\n\nBalance: $121,581,127.64\n\nDays: 0\n\nInterest: $0\n\nPayments\n\nDate: 01/07/2016\n\nAmount: $705.00\n\nBalance: $121,580,422.64\n\nDays: 134\n\nInterest: $2,410,290.24\n\n\n\n\nDate: 12/11/2016\n\nAmount: $7,338.00\n\nBalance: $121,573,084.64\n\nDays: 231\n\nInterest: $4,154,801.80\n\n\n\n\nTotal repayments\n\n$8,043.00\n\nTotal interest\n\n$6,565,092.04\n\nTotal principal\n\n$0\n\nClosing balance\n\nDate: 30/06/2017\n\nBalance: $121,581,127.64",
  "outputs": {
    "enquiryRateFormatted": "5.4%",
    "enquiryYearEndMinusOneDisplay": "30/06/2016",
    "amalgamatedLoanNotPaidByEOIYFormatted": "$121,581,127.64",
    "openingBalancePayDays": "0",
    "openingBalanceInterestFormatted": "$0",
    "totalAmountOfRepaymentFormatted": "$8,043.00",
    "totalInterestFormatted": "$6,565,092.04",
    "principalFormatted": "$0",
    "enquiryYearEndDisplay": "30/06/2017",
    "minimumYearRepaymentFormatted": "$44,980,398.00"
  },
  "repayments": [
    {
      "rd": "1/7/2016",
      "ra": 705
    },
    {
      "rd": "12/11/2016",
      "ra": 7338
    }
  ],
  "inputs": {
    "incomeYearOfLoan": 2016,
    "fullTermOfAmalgamatedLoan": 3,
    "incomeYearOfEnquiring": 2017,
    "amalgamatedLoanNotPaidByEOIY": 121581127.64868021,
    "repayments": null,
    "lodgement_date": "9/10/2016"
  },
  "idx": 1060
}