{
  "id": "2023-10-31T17:24:05.344Z0.434122954812903",
  "alert": "Start of result\nResult\n\nMinimum yearly repayment not met.\n\nThe amount of the loan not repaid at the end of income year 2021-22 is $1,621.66.\n\nThe private company may be taken to pay a dividend under Division 7A to the shareholder or shareholder's associate because the amount repaid during income year 2021-22 in relation to the amalgamated loan is less than the minimum yearly repayment required.\n\nInterest received by the private company must be included in the income tax return for 2021-22.\n\nMinimum yearly repayment\n\n$9,027.00\n\nBenchmark interest rate\n\n4.52%\n\nOpening balance:\n\nDate: 30/06/2021\n\nBalance: $8,637.00\n\nDays: 48\n\nInterest: $51.34\n\nPayments\n\nDate: 18/08/2021\n\nAmount: $7,126.00\n\nBalance: $1,511.00\n\nDays: 317\n\nInterest: $59.32\n\n\n\n\nTotal repayments\n\n$7,126.00\n\nTotal interest\n\n$110.66\n\nTotal principal\n\n$7,015.34\n\nClosing balance\n\nDate: 30/06/2022\n\nBalance: $1,621.66",
  "outputs": {
    "enquiryRateFormatted": "4.52%",
    "enquiryYearEndMinusOneDisplay": "30/06/2021",
    "amalgamatedLoanNotPaidByEOIYFormatted": "$8,637.00",
    "openingBalancePayDays": "48",
    "openingBalanceInterestFormatted": "$51.34",
    "totalAmountOfRepaymentFormatted": "$7,126.00",
    "totalInterestFormatted": "$110.66",
    "principalFormatted": "$7,015.34",
    "enquiryYearEndDisplay": "30/06/2022",
    "minimumYearRepaymentFormatted": "$9,027.00",
    "loanAmountFormatted": "$1,621.66"
  },
  "repayments": [
    {
      "rd": "18/8/2021",
      "ra": 7126
    }
  ],
  "inputs": {
    "incomeYearOfLoan": 2018,
    "fullTermOfAmalgamatedLoan": 4,
    "incomeYearOfEnquiring": 2022,
    "amalgamatedLoanNotPaidByEOIY": 8637,
    "repayments": null,
    "lodgement_date": null
  },
  "idx": 1355
}