{
  "id": "2023-09-05T20:35:53.106Z0.24018451733400425",
  "alert": "Start of result\nResult\n\nMinimum yearly repayment met.\n\nThe amount of the loan not repaid at the end of income year 2020-21 is $1.25.\n\nThe amalgamated loan will not be taken to be a dividend because the total repayments made are equal to or greater than the minimum yearly repayment required for income year 2020-21.\n\nInterest received by the private company must be included in the income tax return for 2020-21.\n\nMinimum yearly repayment\n\n$24.00\n\nBenchmark interest rate\n\n4.52%\n\nOpening balance:\n\nDate: 30/06/2020\n\nBalance: $84.50\n\nDays: 119\n\nInterest: $1.25\n\nPayments\n\nDate: 28/10/2020\n\nAmount: $84.50\n\nBalance: $0\n\nDays: 246\n\nInterest: $0\n\n\n\n\nTotal repayments\n\n$84.50\n\nTotal interest\n\n$1.25\n\nTotal principal\n\n$83.25\n\nClosing balance\n\nDate: 30/06/2021\n\nBalance: $1.25",
  "outputs": {
    "enquiryRateFormatted": "4.52%",
    "enquiryYearEndMinusOneDisplay": "30/06/2020",
    "amalgamatedLoanNotPaidByEOIYFormatted": "$84.50",
    "openingBalancePayDays": "119",
    "openingBalanceInterestFormatted": "$1.25",
    "totalAmountOfRepaymentFormatted": "$84.50",
    "totalInterestFormatted": "$1.25",
    "principalFormatted": "$83.25",
    "enquiryYearEndDisplay": "30/06/2021",
    "minimumYearRepaymentFormatted": "$24.00"
  },
  "repayments": [
    {
      "rd": "28/10/2020",
      "ra": 84.50245908144416
    }
  ],
  "inputs": {
    "incomeYearOfLoan": 2017,
    "fullTermOfAmalgamatedLoan": 7,
    "incomeYearOfEnquiring": 2021,
    "amalgamatedLoanNotPaidByEOIY": 84.50245908144417,
    "repayments": null,
    "lodgement_date": null
  },
  "idx": 6639
}