{
  "id": "2023-10-31T17:30:20.483Z0.09079992637459611",
  "alert": "Start of result\nResult\n\nMinimum yearly repayment not met.\n\nThe amount of the loan not repaid at the end of income year 2023-24 is $59.88.\n\nThe private company may be taken to pay a dividend under Division 7A to the shareholder or shareholder's associate because the amount repaid during income year 2023-24 in relation to the amalgamated loan is less than the minimum yearly repayment required.\n\nInterest received by the private company must be included in the income tax return for 2023-24.\n\nMinimum yearly repayment\n\n$65.00\n\nBenchmark interest rate\n\n8.27%\n\nOpening balance:\n\nDate: 30/06/2023\n\nBalance: $59.88\n\nDays: 366\n\nInterest: $4.95\n\nTotal repayments\n\n$0\n\nTotal interest\n\n$4.95\n\nTotal principal\n\n$0\n\nClosing balance\n\nDate: 30/06/2024\n\nBalance: $59.88",
  "outputs": {
    "enquiryRateFormatted": "8.27%",
    "enquiryYearEndMinusOneDisplay": "30/06/2023",
    "amalgamatedLoanNotPaidByEOIYFormatted": "$59.88",
    "openingBalancePayDays": "366",
    "openingBalanceInterestFormatted": "$4.95",
    "totalAmountOfRepaymentFormatted": "$0",
    "totalInterestFormatted": "$4.95",
    "principalFormatted": "$0",
    "enquiryYearEndDisplay": "30/06/2024",
    "minimumYearRepaymentFormatted": "$65.00",
    "loanAmountFormatted": "$59.88"
  },
  "repayments": [],
  "inputs": {
    "incomeYearOfLoan": 2017,
    "fullTermOfAmalgamatedLoan": 7,
    "incomeYearOfEnquiring": 2024,
    "amalgamatedLoanNotPaidByEOIY": 59.881360002507556,
    "repayments": null,
    "lodgement_date": null
  },
  "idx": 1712
}