{
  "id": "2023-10-31T21:21:44.829Z0.8315955846931543",
  "alert": "Start of result\nResult\n\nMinimum yearly repayment not met.\n\nThe amount of the loan not repaid at the end of income year 1998-99 is $49.31.\n\nThe private company may be taken to pay a dividend under Division 7A to the shareholder or shareholder's associate because the amount repaid during income year 1998-99 in relation to the amalgamated loan is less than the minimum yearly repayment required.\n\nInterest received by the private company must be included in the income tax return for 1998-99.\n\nMinimum yearly repayment\n\n$14.00\n\nBenchmark interest rate\n\n6.7%\n\nOpening balance:\n\nDate: 30/06/1998\n\nBalance: $49.31\n\nDays: 365\n\nInterest: $3.30\n\nTotal repayments\n\n$0\n\nTotal interest\n\n$3.30\n\nTotal principal\n\n$0\n\nClosing balance\n\nDate: 30/06/1999\n\nBalance: $49.31",
  "outputs": {
    "enquiryRateFormatted": "6.7%",
    "enquiryYearEndMinusOneDisplay": "30/06/1998",
    "amalgamatedLoanNotPaidByEOIYFormatted": "$49.31",
    "openingBalancePayDays": "365",
    "openingBalanceInterestFormatted": "$3.30",
    "totalAmountOfRepaymentFormatted": "$0",
    "totalInterestFormatted": "$3.30",
    "principalFormatted": "$0",
    "enquiryYearEndDisplay": "30/06/1999",
    "minimumYearRepaymentFormatted": "$14.00",
    "loanAmountFormatted": "$49.31"
  },
  "repayments": [],
  "inputs": {
    "incomeYearOfLoan": 1998,
    "fullTermOfAmalgamatedLoan": 4,
    "incomeYearOfEnquiring": 1999,
    "amalgamatedLoanNotPaidByEOIY": 49.31612961870673,
    "repayments": null,
    "lodgement_date": "31/7/1998"
  },
  "idx": 7213
}