{
  "id": "2023-09-06T04:18:58.764Z0.9983816976240982",
  "alert": "Start of result\nResult\n\nMinimum yearly repayment met.\n\nThe amount of the loan not repaid at the end of income year 2012-13 is $0.06.\n\nThe amalgamated loan will not be taken to be a dividend because the total repayments made are equal to or greater than the minimum yearly repayment required for income year 2012-13.\n\nInterest received by the private company must be included in the income tax return for 2012-13.\n\nMinimum yearly repayment\n\n$1.00\n\nBenchmark interest rate\n\n7.05%\n\nOpening balance:\n\nDate: 30/06/2012\n\nBalance: $2.28\n\nDays: 133\n\nInterest: $0.06\n\nPayments\n\nDate: 11/11/2012\n\nAmount: $2.28\n\nBalance: $0\n\nDays: 232\n\nInterest: $0\n\n\n\n\nTotal repayments\n\n$2.28\n\nTotal interest\n\n$0.06\n\nTotal principal\n\n$2.22\n\nClosing balance\n\nDate: 30/06/2013\n\nBalance: $0.06",
  "outputs": {
    "enquiryRateFormatted": "7.05%",
    "enquiryYearEndMinusOneDisplay": "30/06/2012",
    "amalgamatedLoanNotPaidByEOIYFormatted": "$2.28",
    "openingBalancePayDays": "133",
    "openingBalanceInterestFormatted": "$0.06",
    "totalAmountOfRepaymentFormatted": "$2.28",
    "totalInterestFormatted": "$0.06",
    "principalFormatted": "$2.22",
    "enquiryYearEndDisplay": "30/06/2013",
    "minimumYearRepaymentFormatted": "$1.00"
  },
  "repayments": [
    {
      "rd": "11/11/2012",
      "ra": 2.2871471752114303
    }
  ],
  "inputs": {
    "incomeYearOfLoan": 2012,
    "fullTermOfAmalgamatedLoan": 2,
    "incomeYearOfEnquiring": 2013,
    "amalgamatedLoanNotPaidByEOIY": 2.2871471752113615,
    "repayments": null,
    "lodgement_date": "6/8/2012"
  },
  "idx": 7037
}