{
  "id": "2023-10-31T18:33:45.607Z0.7433353886956385",
  "alert": "Start of result\nResult\n\nMinimum yearly repayment met.\n\nThe amount of the loan not repaid at the end of income year 2012-13 is $2,662.94.\n\n\u000b\n\nThe amalgamated loan will not be taken to be a dividend because the total repayments made are equal to or greater than the minimum yearly repayment required for income year 2012-13.\n\nInterest received by the private company must be included in the income tax return for 2012-13.\n\nMinimum yearly repayment\n\n$2,783.00\n\nBenchmark interest rate\n\n7.05%\n\nOpening balance:\n\nDate: 30/06/2012\n\nBalance: $9,416.00\n\nDays: 37\n\nInterest: $67.29\n\nPayments\n\nDate: 07/08/2012\n\nAmount: $6,975.00\n\nBalance: $2,441.00\n\nDays: 328\n\nInterest: $154.65\n\n\n\n\nTotal repayments\n\n$6,975.00\n\nTotal interest\n\n$221.94\n\nTotal principal\n\n$6,753.06\n\nClosing balance\n\nDate: 30/06/2013\n\nBalance: $2,662.94",
  "outputs": {
    "enquiryRateFormatted": "7.05%",
    "enquiryYearEndMinusOneDisplay": "30/06/2012",
    "amalgamatedLoanNotPaidByEOIYFormatted": "$9,416.00",
    "openingBalancePayDays": "37",
    "openingBalanceInterestFormatted": "$67.29",
    "totalAmountOfRepaymentFormatted": "$6,975.00",
    "totalInterestFormatted": "$221.94",
    "principalFormatted": "$6,753.06",
    "enquiryYearEndDisplay": "30/06/2013",
    "minimumYearRepaymentFormatted": "$2,783.00",
    "loanAmountFormatted": "$2,662.94"
  },
  "repayments": [
    {
      "rd": "7/8/2012",
      "ra": 6975
    }
  ],
  "inputs": {
    "incomeYearOfLoan": 2009,
    "fullTermOfAmalgamatedLoan": 7,
    "incomeYearOfEnquiring": 2013,
    "amalgamatedLoanNotPaidByEOIY": 9416,
    "repayments": null,
    "lodgement_date": null
  },
  "idx": 4179
}