{
  "id": "2023-09-04T21:00:11.938Z0.5270778874400663",
  "alert": "Start of result\nResult\n\nMinimum yearly repayment not met.\n\nThe amount of the loan not repaid at the end of income year 2012-13 is $79,298,584.48.\n\nThe private company may be taken to pay a dividend under Division 7A to the shareholder or shareholder's associate because the amount repaid during income year 2012-13 in relation to the amalgamated loan is less than the minimum yearly repayment required.\n\nInterest received by the private company must be included in the income tax return for 2012-13.\n\nMinimum yearly repayment\n\n$19,366,086.00\n\nBenchmark interest rate\n\n7.05%\n\nOpening balance:\n\nDate: 30/06/2012\n\nBalance: $79,298,584.48\n\nDays: 365\n\nInterest: $5,590,550.21\n\nTotal repayments\n\n$0\n\nTotal interest\n\n$5,590,550.21\n\nTotal principal\n\n$0\n\nClosing balance\n\nDate: 30/06/2013\n\nBalance: $79,298,584.48",
  "outputs": {
    "enquiryRateFormatted": "7.05%",
    "enquiryYearEndMinusOneDisplay": "30/06/2012",
    "amalgamatedLoanNotPaidByEOIYFormatted": "$79,298,584.48",
    "openingBalancePayDays": "365",
    "openingBalanceInterestFormatted": "$5,590,550.21",
    "totalAmountOfRepaymentFormatted": "$0",
    "totalInterestFormatted": "$5,590,550.21",
    "principalFormatted": "$0",
    "enquiryYearEndDisplay": "30/06/2013",
    "minimumYearRepaymentFormatted": "$19,366,086.00"
  },
  "repayments": [],
  "inputs": {
    "incomeYearOfLoan": 2010,
    "fullTermOfAmalgamatedLoan": 7,
    "incomeYearOfEnquiring": 2013,
    "amalgamatedLoanNotPaidByEOIY": 79298584.48258312,
    "repayments": null,
    "lodgement_date": null
  },
  "idx": 474
}