{
  "id": "2023-10-31T20:44:05.242Z0.1608848644923354",
  "alert": "Start of result\nResult\n\nMinimum yearly repayment met.\n\nThe amount of the loan not repaid at the end of income year 2002-03 is $3,854.45.\n\n\u000b\n\nThe amalgamated loan will not be taken to be a dividend because the total repayments made are equal to or greater than the minimum yearly repayment required for income year 2002-03.\n\nInterest received by the private company must be included in the income tax return for 2002-03.\n\nMinimum yearly repayment\n\n$1,970.00\n\nBenchmark interest rate\n\n6.3%\n\nOpening balance:\n\nDate: 30/06/2002\n\nBalance: $8,232.00\n\nDays: 74\n\nInterest: $105.14\n\nPayments\n\nDate: 13/09/2002\n\nAmount: $4,662.00\n\nBalance: $3,570.00\n\nDays: 291\n\nInterest: $179.31\n\n\n\n\nTotal repayments\n\n$4,662.00\n\nTotal interest\n\n$284.45\n\nTotal principal\n\n$4,377.55\n\nClosing balance\n\nDate: 30/06/2003\n\nBalance: $3,854.45",
  "outputs": {
    "enquiryRateFormatted": "6.3%",
    "enquiryYearEndMinusOneDisplay": "30/06/2002",
    "amalgamatedLoanNotPaidByEOIYFormatted": "$8,232.00",
    "openingBalancePayDays": "74",
    "openingBalanceInterestFormatted": "$105.14",
    "totalAmountOfRepaymentFormatted": "$4,662.00",
    "totalInterestFormatted": "$284.45",
    "principalFormatted": "$4,377.55",
    "enquiryYearEndDisplay": "30/06/2003",
    "minimumYearRepaymentFormatted": "$1,970.00",
    "loanAmountFormatted": "$3,854.45"
  },
  "repayments": [
    {
      "rd": "13/9/2002",
      "ra": 4662
    }
  ],
  "inputs": {
    "incomeYearOfLoan": 2000,
    "fullTermOfAmalgamatedLoan": 7,
    "incomeYearOfEnquiring": 2003,
    "amalgamatedLoanNotPaidByEOIY": 8232,
    "repayments": null,
    "lodgement_date": null
  },
  "idx": 6721
}