{
  "id": "2023-10-31T18:48:08.301Z0.6185773503917911",
  "alert": "Start of result\nResult\n\nMinimum yearly repayment not met.\n\nThe amount of the loan not repaid at the end of income year 2008-09 is $119.49.\n\nThe private company may be taken to pay a dividend under Division 7A to the shareholder or shareholder's associate because the amount repaid during income year 2008-09 in relation to the amalgamated loan is less than the minimum yearly repayment required.\n\nInterest received by the private company must be included in the income tax return for 2008-09.\n\nMinimum yearly repayment\n\n$68.00\n\nBenchmark interest rate\n\n9.45%\n\nOpening balance:\n\nDate: 30/06/2008\n\nBalance: $119.49\n\nDays: 365\n\nInterest: $11.29\n\nTotal repayments\n\n$0\n\nTotal interest\n\n$11.29\n\nTotal principal\n\n$0\n\nClosing balance\n\nDate: 30/06/2009\n\nBalance: $119.49",
  "outputs": {
    "enquiryRateFormatted": "9.45%",
    "enquiryYearEndMinusOneDisplay": "30/06/2008",
    "amalgamatedLoanNotPaidByEOIYFormatted": "$119.49",
    "openingBalancePayDays": "365",
    "openingBalanceInterestFormatted": "$11.29",
    "totalAmountOfRepaymentFormatted": "$0",
    "totalInterestFormatted": "$11.29",
    "principalFormatted": "$0",
    "enquiryYearEndDisplay": "30/06/2009",
    "minimumYearRepaymentFormatted": "$68.00",
    "loanAmountFormatted": "$119.49"
  },
  "repayments": [],
  "inputs": {
    "incomeYearOfLoan": 2007,
    "fullTermOfAmalgamatedLoan": 3,
    "incomeYearOfEnquiring": 2009,
    "amalgamatedLoanNotPaidByEOIY": 119.49116033371381,
    "repayments": null,
    "lodgement_date": null
  },
  "idx": 4572
}