{
  "id": "2023-09-04T21:04:45.008Z0.945096170508819",
  "alert": "Start of result\nResult\n\nMinimum yearly repayment not met.\n\nThe amount of the loan not repaid at the end of income year 2011-12 is $112,346,252.15.\n\nThe private company may be taken to pay a dividend under Division 7A to the shareholder or shareholder's associate because the amount repaid during income year 2011-12 in relation to the amalgamated loan is less than the minimum yearly repayment required.\n\nInterest received by the private company must be included in the income tax return for 2011-12.\n\nMinimum yearly repayment\n\n$43,436,878.00\n\nBenchmark interest rate\n\n7.8%\n\nOpening balance:\n\nDate: 30/06/2011\n\nBalance: $112,346,252.15\n\nDays: 366\n\nInterest: $8,763,007.67\n\nTotal repayments\n\n$0\n\nTotal interest\n\n$8,763,007.67\n\nTotal principal\n\n$0\n\nClosing balance\n\nDate: 30/06/2012\n\nBalance: $112,346,252.15",
  "outputs": {
    "enquiryRateFormatted": "7.8%",
    "enquiryYearEndMinusOneDisplay": "30/06/2011",
    "amalgamatedLoanNotPaidByEOIYFormatted": "$112,346,252.15",
    "openingBalancePayDays": "366",
    "openingBalanceInterestFormatted": "$8,763,007.67",
    "totalAmountOfRepaymentFormatted": "$0",
    "totalInterestFormatted": "$8,763,007.67",
    "principalFormatted": "$0",
    "enquiryYearEndDisplay": "30/06/2012",
    "minimumYearRepaymentFormatted": "$43,436,878.00"
  },
  "repayments": [],
  "inputs": {
    "incomeYearOfLoan": 2009,
    "fullTermOfAmalgamatedLoan": 5,
    "incomeYearOfEnquiring": 2012,
    "amalgamatedLoanNotPaidByEOIY": 112346252.15097606,
    "repayments": null,
    "lodgement_date": null
  },
  "idx": 630
}