{
  "id": "2023-10-31T20:29:08.468Z0.6057696651590226",
  "alert": "Start of result\nResult\n\nMinimum yearly repayment not met.\n\nThe amount of the loan not repaid at the end of income year 2002-03 is $6.10.\n\nThe private company may be taken to pay a dividend under Division 7A to the shareholder or shareholder's associate because the amount repaid during income year 2002-03 in relation to the amalgamated loan is less than the minimum yearly repayment required.\n\nInterest received by the private company must be included in the income tax return for 2002-03.\n\nMinimum yearly repayment\n\n$6.00\n\nBenchmark interest rate\n\n6.3%\n\nOpening balance:\n\nDate: 30/06/2002\n\nBalance: $6.10\n\nDays: 365\n\nInterest: $0.38\n\nTotal repayments\n\n$0\n\nTotal interest\n\n$0.38\n\nTotal principal\n\n$0\n\nClosing balance\n\nDate: 30/06/2003\n\nBalance: $6.10",
  "outputs": {
    "enquiryRateFormatted": "6.3%",
    "enquiryYearEndMinusOneDisplay": "30/06/2002",
    "amalgamatedLoanNotPaidByEOIYFormatted": "$6.10",
    "openingBalancePayDays": "365",
    "openingBalanceInterestFormatted": "$0.38",
    "totalAmountOfRepaymentFormatted": "$0",
    "totalInterestFormatted": "$0.38",
    "principalFormatted": "$0",
    "enquiryYearEndDisplay": "30/06/2003",
    "minimumYearRepaymentFormatted": "$6.00",
    "loanAmountFormatted": "$6.10"
  },
  "repayments": [],
  "inputs": {
    "incomeYearOfLoan": 2000,
    "fullTermOfAmalgamatedLoan": 3,
    "incomeYearOfEnquiring": 2003,
    "amalgamatedLoanNotPaidByEOIY": 6.10001116374092,
    "repayments": null,
    "lodgement_date": null
  },
  "idx": 6509
}