{
  "id": "2023-10-31T17:39:55.959Z0.6690430851083833",
  "alert": "Start of result\nResult\n\nMinimum yearly repayment not met.\n\nThe amount of the loan not repaid at the end of income year 2015-16 is $110.33.\n\nThe private company may be taken to pay a dividend under Division 7A to the shareholder or shareholder's associate because the amount repaid during income year 2015-16 in relation to the amalgamated loan is less than the minimum yearly repayment required.\n\nInterest received by the private company must be included in the income tax return for 2015-16.\n\nMinimum yearly repayment\n\n$41.00\n\nBenchmark interest rate\n\n5.45%\n\nOpening balance:\n\nDate: 30/06/2015\n\nBalance: $110.33\n\nDays: 366\n\nInterest: $6.01\n\nTotal repayments\n\n$0\n\nTotal interest\n\n$6.01\n\nTotal principal\n\n$0\n\nClosing balance\n\nDate: 30/06/2016\n\nBalance: $110.33",
  "outputs": {
    "enquiryRateFormatted": "5.45%",
    "enquiryYearEndMinusOneDisplay": "30/06/2015",
    "amalgamatedLoanNotPaidByEOIYFormatted": "$110.33",
    "openingBalancePayDays": "366",
    "openingBalanceInterestFormatted": "$6.01",
    "totalAmountOfRepaymentFormatted": "$0",
    "totalInterestFormatted": "$6.01",
    "principalFormatted": "$0",
    "enquiryYearEndDisplay": "30/06/2016",
    "minimumYearRepaymentFormatted": "$41.00",
    "loanAmountFormatted": "$110.33"
  },
  "repayments": [],
  "inputs": {
    "incomeYearOfLoan": 2015,
    "fullTermOfAmalgamatedLoan": 3,
    "incomeYearOfEnquiring": 2016,
    "amalgamatedLoanNotPaidByEOIY": 110.33275479565737,
    "repayments": null,
    "lodgement_date": "1/7/2015"
  },
  "idx": 2224
}