{
  "id": "2023-09-06T16:50:38.783Z0.9028308433947183",
  "alert": "Start of result\nResult\n\nMinimum yearly repayment met.\n\nThe amount of the loan not repaid at the end of income year 2005-06 is $5.44.\n\nThe amalgamated loan will not be taken to be a dividend because the total repayments made are equal to or greater than the minimum yearly repayment required for income year 2005-06.\n\nInterest received by the private company must be included in the income tax return for 2005-06.\n\nMinimum yearly repayment\n\n$20.00\n\nBenchmark interest rate\n\n7.3%\n\nOpening balance:\n\nDate: 30/06/2005\n\nBalance: $96.72\n\nDays: 281\n\nInterest: $5.44\n\nPayments\n\nDate: 08/04/2006\n\nAmount: $96.72\n\nBalance: $0\n\nDays: 84\n\nInterest: $0\n\n\n\n\nTotal repayments\n\n$96.72\n\nTotal interest\n\n$5.44\n\nTotal principal\n\n$91.28\n\nClosing balance\n\nDate: 30/06/2006\n\nBalance: $5.44",
  "outputs": {
    "enquiryRateFormatted": "7.3%",
    "enquiryYearEndMinusOneDisplay": "30/06/2005",
    "amalgamatedLoanNotPaidByEOIYFormatted": "$96.72",
    "openingBalancePayDays": "281",
    "openingBalanceInterestFormatted": "$5.44",
    "totalAmountOfRepaymentFormatted": "$96.72",
    "totalInterestFormatted": "$5.44",
    "principalFormatted": "$91.28",
    "enquiryYearEndDisplay": "30/06/2006",
    "minimumYearRepaymentFormatted": "$20.00"
  },
  "repayments": [
    {
      "rd": "8/4/2006",
      "ra": 96.7283629050271
    }
  ],
  "inputs": {
    "incomeYearOfLoan": 2005,
    "fullTermOfAmalgamatedLoan": 6,
    "incomeYearOfEnquiring": 2006,
    "amalgamatedLoanNotPaidByEOIY": 96.7283629050265,
    "repayments": null,
    "lodgement_date": "22/10/2005"
  },
  "idx": 5274
}