{
  "id": "2023-09-04T17:41:20.438Z0.09443603508359044",
  "alert": "Start of result\nResult\n\nMinimum yearly repayment not met.\n\nThe amount of the loan not repaid at the end of income year 2015-16 is $1,754.69.\n\nThe private company may be taken to pay a dividend under Division 7A to the shareholder or shareholder's associate because the amount repaid during income year 2015-16 in relation to the amalgamated loan is less than the minimum yearly repayment required.\n\nInterest received by the private company must be included in the income tax return for 2015-16.\n\nMinimum yearly repayment\n\n$2,675.00\n\nBenchmark interest rate\n\n5.45%\n\nOpening balance:\n\nDate: 30/06/2015\n\nBalance: $2,537.00\n\nDays: 0\n\nInterest: $0\n\nPayments\n\nDate: 01/07/2015\n\nAmount: $873.00\n\nBalance: $1,664.00\n\nDays: 366\n\nInterest: $90.69\n\n\n\n\nTotal repayments\n\n$873.00\n\nTotal interest\n\n$90.69\n\nTotal principal\n\n$782.31\n\nClosing balance\n\nDate: 30/06/2016\n\nBalance: $1,754.69",
  "outputs": {
    "enquiryRateFormatted": "5.45%",
    "enquiryYearEndMinusOneDisplay": "30/06/2015",
    "amalgamatedLoanNotPaidByEOIYFormatted": "$2,537.00",
    "openingBalancePayDays": "0",
    "openingBalanceInterestFormatted": "$0",
    "totalAmountOfRepaymentFormatted": "$873.00",
    "totalInterestFormatted": "$90.69",
    "principalFormatted": "$782.31",
    "enquiryYearEndDisplay": "30/06/2016",
    "minimumYearRepaymentFormatted": "$2,675.00"
  },
  "repayments": [
    {
      "rd": "1/7/2015",
      "ra": 873
    }
  ],
  "inputs": {
    "incomeYearOfLoan": 2012,
    "fullTermOfAmalgamatedLoan": 4,
    "incomeYearOfEnquiring": 2016,
    "amalgamatedLoanNotPaidByEOIY": 2537,
    "repayments": null,
    "lodgement_date": null
  },
  "idx": 2468
}