{
  "id": "2023-09-05T13:02:52.660Z0.43735980265528474",
  "alert": "Start of result\nResult\n\nMinimum yearly repayment not met.\n\nThe amount of the loan not repaid at the end of income year 2021-22 is $9,249.00.\n\nThe private company may be taken to pay a dividend under Division 7A to the shareholder or shareholder's associate because the amount repaid during income year 2021-22 in relation to the amalgamated loan is less than the minimum yearly repayment required.\n\nInterest received by the private company must be included in the income tax return for 2021-22.\n\nMinimum yearly repayment\n\n$3,366.00\n\nBenchmark interest rate\n\n4.52%\n\nOpening balance:\n\nDate: 30/06/2021\n\nBalance: $9,249.00\n\nDays: 365\n\nInterest: $418.05\n\nTotal repayments\n\n$0\n\nTotal interest\n\n$418.05\n\nTotal principal\n\n$0\n\nClosing balance\n\nDate: 30/06/2022\n\nBalance: $9,249.00",
  "outputs": {
    "enquiryRateFormatted": "4.52%",
    "enquiryYearEndMinusOneDisplay": "30/06/2021",
    "amalgamatedLoanNotPaidByEOIYFormatted": "$9,249.00",
    "openingBalancePayDays": "365",
    "openingBalanceInterestFormatted": "$418.05",
    "totalAmountOfRepaymentFormatted": "$0",
    "totalInterestFormatted": "$418.05",
    "principalFormatted": "$0",
    "enquiryYearEndDisplay": "30/06/2022",
    "minimumYearRepaymentFormatted": "$3,366.00"
  },
  "repayments": [],
  "inputs": {
    "incomeYearOfLoan": 2021,
    "fullTermOfAmalgamatedLoan": 3,
    "incomeYearOfEnquiring": 2022,
    "amalgamatedLoanNotPaidByEOIY": 9249,
    "repayments": null,
    "lodgement_date": "4/8/2021"
  },
  "idx": 6641
}