{
  "id": "2023-09-04T17:17:54.055Z0.12886197551014278",
  "alert": "Start of result\nResult\n\nMinimum yearly repayment not met.\n\nThe amount of the loan not repaid at the end of income year 2017-18 is $60,377,180.01.\n\nThe private company may be taken to pay a dividend under Division 7A to the shareholder or shareholder's associate because the amount repaid during income year 2017-18 in relation to the amalgamated loan is less than the minimum yearly repayment required.\n\nInterest received by the private company must be included in the income tax return for 2017-18.\n\nMinimum yearly repayment\n\n$17,145,893.00\n\nBenchmark interest rate\n\n5.3%\n\nOpening balance:\n\nDate: 30/06/2017\n\nBalance: $60,377,180.01\n\nDays: 0\n\nInterest: $0\n\nPayments\n\nDate: 01/07/2017\n\nAmount: $992.00\n\nBalance: $60,376,188.01\n\nDays: 365\n\nInterest: $3,199,937.96\n\n\n\n\nTotal repayments\n\n$992.00\n\nTotal interest\n\n$3,199,937.96\n\nTotal principal\n\n$0\n\nClosing balance\n\nDate: 30/06/2018\n\nBalance: $60,377,180.01",
  "outputs": {
    "enquiryRateFormatted": "5.3%",
    "enquiryYearEndMinusOneDisplay": "30/06/2017",
    "amalgamatedLoanNotPaidByEOIYFormatted": "$60,377,180.01",
    "openingBalancePayDays": "0",
    "openingBalanceInterestFormatted": "$0",
    "totalAmountOfRepaymentFormatted": "$992.00",
    "totalInterestFormatted": "$3,199,937.96",
    "principalFormatted": "$0",
    "enquiryYearEndDisplay": "30/06/2018",
    "minimumYearRepaymentFormatted": "$17,145,893.00"
  },
  "repayments": [
    {
      "rd": "1/7/2017",
      "ra": 992
    }
  ],
  "inputs": {
    "incomeYearOfLoan": 2014,
    "fullTermOfAmalgamatedLoan": 7,
    "incomeYearOfEnquiring": 2018,
    "amalgamatedLoanNotPaidByEOIY": 60377180.01272084,
    "repayments": null,
    "lodgement_date": null
  },
  "idx": 1962
}