{
  "id": "2023-10-31T18:13:58.523Z0.9414792113848571",
  "alert": "Start of result\nResult\n\nMinimum yearly repayment met.\n\nThe amount of the loan not repaid at the end of income year 2012-13 is $5,504.75.\n\n\u000b\n\nThe amalgamated loan will not be taken to be a dividend because the total repayments made are equal to or greater than the minimum yearly repayment required for income year 2012-13.\n\nInterest received by the private company must be included in the income tax return for 2012-13.\n\nMinimum yearly repayment\n\n$1,354.00\n\nBenchmark interest rate\n\n7.05%\n\nOpening balance:\n\nDate: 30/06/2012\n\nBalance: $6,444.00\n\nDays: 276\n\nInterest: $343.53\n\nPayments\n\nDate: 03/04/2013\n\nAmount: $1,370.00\n\nBalance: $5,074.00\n\nDays: 89\n\nInterest: $87.22\n\n\n\n\nTotal repayments\n\n$1,370.00\n\nTotal interest\n\n$430.75\n\nTotal principal\n\n$939.25\n\nClosing balance\n\nDate: 30/06/2013\n\nBalance: $5,504.75",
  "outputs": {
    "enquiryRateFormatted": "7.05%",
    "enquiryYearEndMinusOneDisplay": "30/06/2012",
    "amalgamatedLoanNotPaidByEOIYFormatted": "$6,444.00",
    "openingBalancePayDays": "276",
    "openingBalanceInterestFormatted": "$343.53",
    "totalAmountOfRepaymentFormatted": "$1,370.00",
    "totalInterestFormatted": "$430.75",
    "principalFormatted": "$939.25",
    "enquiryYearEndDisplay": "30/06/2013",
    "minimumYearRepaymentFormatted": "$1,354.00",
    "loanAmountFormatted": "$5,504.75"
  },
  "repayments": [
    {
      "rd": "3/4/2013",
      "ra": 1370
    }
  ],
  "inputs": {
    "incomeYearOfLoan": 2011,
    "fullTermOfAmalgamatedLoan": 7,
    "incomeYearOfEnquiring": 2013,
    "amalgamatedLoanNotPaidByEOIY": 6444,
    "repayments": null,
    "lodgement_date": null
  },
  "idx": 3585
}