{
  "id": "2023-09-04T20:49:47.509Z0.23150852890347262",
  "alert": "Start of result\nResult\n\nMinimum yearly repayment not met.\n\nThe amount of the loan not repaid at the end of income year 2012-13 is $1,105,120.82.\n\nThe private company may be taken to pay a dividend under Division 7A to the shareholder or shareholder's associate because the amount repaid during income year 2012-13 in relation to the amalgamated loan is less than the minimum yearly repayment required.\n\nInterest received by the private company must be included in the income tax return for 2012-13.\n\nMinimum yearly repayment\n\n$611,657.00\n\nBenchmark interest rate\n\n7.05%\n\nOpening balance:\n\nDate: 30/06/2012\n\nBalance: $1,105,120.82\n\nDays: 365\n\nInterest: $77,911.02\n\nTotal repayments\n\n$0\n\nTotal interest\n\n$77,911.02\n\nTotal principal\n\n$0\n\nClosing balance\n\nDate: 30/06/2013\n\nBalance: $1,105,120.82",
  "outputs": {
    "enquiryRateFormatted": "7.05%",
    "enquiryYearEndMinusOneDisplay": "30/06/2012",
    "amalgamatedLoanNotPaidByEOIYFormatted": "$1,105,120.82",
    "openingBalancePayDays": "365",
    "openingBalanceInterestFormatted": "$77,911.02",
    "totalAmountOfRepaymentFormatted": "$0",
    "totalInterestFormatted": "$77,911.02",
    "principalFormatted": "$0",
    "enquiryYearEndDisplay": "30/06/2013",
    "minimumYearRepaymentFormatted": "$611,657.00"
  },
  "repayments": [],
  "inputs": {
    "incomeYearOfLoan": 2011,
    "fullTermOfAmalgamatedLoan": 3,
    "incomeYearOfEnquiring": 2013,
    "amalgamatedLoanNotPaidByEOIY": 1105120.828488237,
    "repayments": null,
    "lodgement_date": null
  },
  "idx": 102
}