{
  "id": "2023-09-04T22:02:20.209Z0.5764274937891014",
  "alert": "Start of result\nResult\n\nMinimum yearly repayment not met.\n\nThe amount of the loan not repaid at the end of income year 2008-09 is $17,865,720.68.\n\nThe private company may be taken to pay a dividend under Division 7A to the shareholder or shareholder's associate because the amount repaid during income year 2008-09 in relation to the amalgamated loan is less than the minimum yearly repayment required.\n\nInterest received by the private company must be included in the income tax return for 2008-09.\n\nMinimum yearly repayment\n\n$19,554,031.00\n\nBenchmark interest rate\n\n9.45%\n\nOpening balance:\n\nDate: 30/06/2008\n\nBalance: $17,865,720.68\n\nDays: 365\n\nInterest: $1,688,310.60\n\nTotal repayments\n\n$0\n\nTotal interest\n\n$1,688,310.60\n\nTotal principal\n\n$0\n\nClosing balance\n\nDate: 30/06/2009\n\nBalance: $17,865,720.68",
  "outputs": {
    "enquiryRateFormatted": "9.45%",
    "enquiryYearEndMinusOneDisplay": "30/06/2008",
    "amalgamatedLoanNotPaidByEOIYFormatted": "$17,865,720.68",
    "openingBalancePayDays": "365",
    "openingBalanceInterestFormatted": "$1,688,310.60",
    "totalAmountOfRepaymentFormatted": "$0",
    "totalInterestFormatted": "$1,688,310.60",
    "principalFormatted": "$0",
    "enquiryYearEndDisplay": "30/06/2009",
    "minimumYearRepaymentFormatted": "$19,554,031.00"
  },
  "repayments": [],
  "inputs": {
    "incomeYearOfLoan": 2004,
    "fullTermOfAmalgamatedLoan": 5,
    "incomeYearOfEnquiring": 2009,
    "amalgamatedLoanNotPaidByEOIY": 17865720.6860561,
    "repayments": null,
    "lodgement_date": null
  },
  "idx": 60
}