{
  "id": "2023-09-06T04:40:35.162Z0.7218585005895735",
  "alert": "Start of result\nResult\n\nMinimum yearly repayment met.\n\nThe amount of the loan not repaid at the end of income year 2013-14 is $3.78.\n\nThe amalgamated loan will not be taken to be a dividend because the total repayments made are equal to or greater than the minimum yearly repayment required for income year 2013-14.\n\nInterest received by the private company must be included in the income tax return for 2013-14.\n\nMinimum yearly repayment\n\n$39.00\n\nBenchmark interest rate\n\n6.2%\n\nOpening balance:\n\nDate: 30/06/2013\n\nBalance: $103.46\n\nDays: 215\n\nInterest: $3.78\n\nPayments\n\nDate: 01/02/2014\n\nAmount: $103.46\n\nBalance: $0\n\nDays: 150\n\nInterest: $0\n\n\n\n\nTotal repayments\n\n$103.46\n\nTotal interest\n\n$3.78\n\nTotal principal\n\n$99.68\n\nClosing balance\n\nDate: 30/06/2014\n\nBalance: $3.78",
  "outputs": {
    "enquiryRateFormatted": "6.2%",
    "enquiryYearEndMinusOneDisplay": "30/06/2013",
    "amalgamatedLoanNotPaidByEOIYFormatted": "$103.46",
    "openingBalancePayDays": "215",
    "openingBalanceInterestFormatted": "$3.78",
    "totalAmountOfRepaymentFormatted": "$103.46",
    "totalInterestFormatted": "$3.78",
    "principalFormatted": "$99.68",
    "enquiryYearEndDisplay": "30/06/2014",
    "minimumYearRepaymentFormatted": "$39.00"
  },
  "repayments": [
    {
      "rd": "1/2/2014",
      "ra": 103.46439246769114
    }
  ],
  "inputs": {
    "incomeYearOfLoan": 2012,
    "fullTermOfAmalgamatedLoan": 4,
    "incomeYearOfEnquiring": 2014,
    "amalgamatedLoanNotPaidByEOIY": 103.46439246769114,
    "repayments": null,
    "lodgement_date": null
  },
  "idx": 8108
}