{
  "id": "2023-09-04T16:42:50.109Z0.9975078764200354",
  "alert": "Start of result\nResult\n\nMinimum yearly repayment met.\n\nThe amount of the loan not repaid at the end of income year 2017-18 is $5,465.07.\n\nThe amalgamated loan will not be taken to be a dividend because the total repayments made are equal to or greater than the minimum yearly repayment required for income year 2017-18.\n\nInterest received by the private company must be included in the income tax return for 2017-18.\n\nMinimum yearly repayment\n\n$6,124.00\n\nBenchmark interest rate\n\n5.3%\n\nOpening balance:\n\nDate: 30/06/2017\n\nBalance: $11,339.00\n\nDays: 0\n\nInterest: $0\n\nPayments\n\nDate: 01/07/2017\n\nAmount: $6,149.00\n\nBalance: $5,190.00\n\nDays: 365\n\nInterest: $275.07\n\n\n\n\nTotal repayments\n\n$6,149.00\n\nTotal interest\n\n$275.07\n\nTotal principal\n\n$5,873.93\n\nClosing balance\n\nDate: 30/06/2018\n\nBalance: $5,465.07",
  "outputs": {
    "enquiryRateFormatted": "5.3%",
    "enquiryYearEndMinusOneDisplay": "30/06/2017",
    "amalgamatedLoanNotPaidByEOIYFormatted": "$11,339.00",
    "openingBalancePayDays": "0",
    "openingBalanceInterestFormatted": "$0",
    "totalAmountOfRepaymentFormatted": "$6,149.00",
    "totalInterestFormatted": "$275.07",
    "principalFormatted": "$5,873.93",
    "enquiryYearEndDisplay": "30/06/2018",
    "minimumYearRepaymentFormatted": "$6,124.00"
  },
  "repayments": [
    {
      "rd": "1/7/2017",
      "ra": 6149
    }
  ],
  "inputs": {
    "incomeYearOfLoan": 2016,
    "fullTermOfAmalgamatedLoan": 3,
    "incomeYearOfEnquiring": 2018,
    "amalgamatedLoanNotPaidByEOIY": 11339,
    "repayments": null,
    "lodgement_date": null
  },
  "idx": 1046
}