{
  "id": "2023-09-05T01:17:08.342Z0.1662399202885756",
  "alert": "Start of result\nResult\n\nMinimum yearly repayment not met.\n\nThe amount of the loan not repaid at the end of income year 1998-99 is $123.13.\n\nThe private company may be taken to pay a dividend under Division 7A to the shareholder or shareholder's associate because the amount repaid during income year 1998-99 in relation to the amalgamated loan is less than the minimum yearly repayment required.\n\nInterest received by the private company must be included in the income tax return for 1998-99.\n\nMinimum yearly repayment\n\n$68.00\n\nBenchmark interest rate\n\n6.7%\n\nOpening balance:\n\nDate: 30/06/1998\n\nBalance: $123.13\n\nDays: 365\n\nInterest: $8.25\n\nTotal repayments\n\n$0\n\nTotal interest\n\n$8.25\n\nTotal principal\n\n$0\n\nClosing balance\n\nDate: 30/06/1999\n\nBalance: $123.13",
  "outputs": {
    "enquiryRateFormatted": "6.7%",
    "enquiryYearEndMinusOneDisplay": "30/06/1998",
    "amalgamatedLoanNotPaidByEOIYFormatted": "$123.13",
    "openingBalancePayDays": "365",
    "openingBalanceInterestFormatted": "$8.25",
    "totalAmountOfRepaymentFormatted": "$0",
    "totalInterestFormatted": "$8.25",
    "principalFormatted": "$0",
    "enquiryYearEndDisplay": "30/06/1999",
    "minimumYearRepaymentFormatted": "$68.00"
  },
  "repayments": [],
  "inputs": {
    "incomeYearOfLoan": 1998,
    "fullTermOfAmalgamatedLoan": 2,
    "incomeYearOfEnquiring": 1999,
    "amalgamatedLoanNotPaidByEOIY": 123.13163630258444,
    "repayments": null,
    "lodgement_date": "7/6/1999"
  },
  "idx": 1442
}