{
  "id": "2023-09-04T21:33:55.694Z0.4831943768923872",
  "alert": "Start of result\nResult\n\nMinimum yearly repayment not met.\n\nThe amount of the loan not repaid at the end of income year 2006-07 is $83,838,433.66.\n\nThe private company may be taken to pay a dividend under Division 7A to the shareholder or shareholder's associate because the amount repaid during income year 2006-07 in relation to the amalgamated loan is less than the minimum yearly repayment required.\n\nInterest received by the private company must be included in the income tax return for 2006-07.\n\nMinimum yearly repayment\n\n$32,268,304.00\n\nBenchmark interest rate\n\n7.55%\n\nOpening balance:\n\nDate: 30/06/2006\n\nBalance: $83,838,433.66\n\nDays: 365\n\nInterest: $6,329,801.74\n\nTotal repayments\n\n$0\n\nTotal interest\n\n$6,329,801.74\n\nTotal principal\n\n$0\n\nClosing balance\n\nDate: 30/06/2007\n\nBalance: $83,838,433.66",
  "outputs": {
    "enquiryRateFormatted": "7.55%",
    "enquiryYearEndMinusOneDisplay": "30/06/2006",
    "amalgamatedLoanNotPaidByEOIYFormatted": "$83,838,433.66",
    "openingBalancePayDays": "365",
    "openingBalanceInterestFormatted": "$6,329,801.74",
    "totalAmountOfRepaymentFormatted": "$0",
    "totalInterestFormatted": "$6,329,801.74",
    "principalFormatted": "$0",
    "enquiryYearEndDisplay": "30/06/2007",
    "minimumYearRepaymentFormatted": "$32,268,304.00"
  },
  "repayments": [],
  "inputs": {
    "incomeYearOfLoan": 2006,
    "fullTermOfAmalgamatedLoan": 3,
    "incomeYearOfEnquiring": 2007,
    "amalgamatedLoanNotPaidByEOIY": 83838433.66794816,
    "repayments": null,
    "lodgement_date": "9/10/2006"
  },
  "idx": 1402
}