{
  "id": "2023-10-31T17:07:33.118Z0.8406499274755705",
  "alert": "Start of result\nResult\n\nMinimum yearly repayment not met.\n\nThe amount of the loan not repaid at the end of income year 2023-24 is $34.46.\n\nThe private company may be taken to pay a dividend under Division 7A to the shareholder or shareholder's associate because the amount repaid during income year 2023-24 in relation to the amalgamated loan is less than the minimum yearly repayment required.\n\nInterest received by the private company must be included in the income tax return for 2023-24.\n\nMinimum yearly repayment\n\n$10.00\n\nBenchmark interest rate\n\n8.27%\n\nOpening balance:\n\nDate: 30/06/2023\n\nBalance: $34.46\n\nDays: 366\n\nInterest: $2.85\n\nTotal repayments\n\n$0\n\nTotal interest\n\n$2.85\n\nTotal principal\n\n$0\n\nClosing balance\n\nDate: 30/06/2024\n\nBalance: $34.46",
  "outputs": {
    "enquiryRateFormatted": "8.27%",
    "enquiryYearEndMinusOneDisplay": "30/06/2023",
    "amalgamatedLoanNotPaidByEOIYFormatted": "$34.46",
    "openingBalancePayDays": "366",
    "openingBalanceInterestFormatted": "$2.85",
    "totalAmountOfRepaymentFormatted": "$0",
    "totalInterestFormatted": "$2.85",
    "principalFormatted": "$0",
    "enquiryYearEndDisplay": "30/06/2024",
    "minimumYearRepaymentFormatted": "$10.00",
    "loanAmountFormatted": "$34.46"
  },
  "repayments": [],
  "inputs": {
    "incomeYearOfLoan": 2023,
    "fullTermOfAmalgamatedLoan": 4,
    "incomeYearOfEnquiring": 2024,
    "amalgamatedLoanNotPaidByEOIY": 34.466085339419635,
    "repayments": null,
    "lodgement_date": "26/2/2024"
  },
  "idx": 64
}