{
  "id": "2023-09-05T10:12:39.604Z0.7101220266131354",
  "alert": "Start of result\nResult\n\nMinimum yearly repayment met.\n\nThe amount of the loan not repaid at the end of income year 2023-24 is $33.61.\n\nThe amalgamated loan will not be taken to be a dividend because the total repayments made are equal to or greater than the minimum yearly repayment required for income year 2023-24.\n\nInterest received by the private company must be included in the income tax return for 2023-24.\n\nMinimum yearly repayment\n\n$0\n\nBenchmark interest rate\n\n8.27%\n\nOpening balance:\n\nDate: 30/06/2023\n\nBalance: $1,932.00\n\nDays: 77\n\nInterest: $33.61\n\nPayments\n\nDate: 16/09/2023\n\nAmount: $1,932.00\n\nBalance: $0\n\nDays: 289\n\nInterest: $0\n\n\n\n\nTotal repayments\n\n$1,932.00\n\nTotal interest\n\n$33.61\n\nTotal principal\n\n$1,898.39\n\nClosing balance\n\nDate: 30/06/2024\n\nBalance: $33.61",
  "outputs": {
    "enquiryRateFormatted": "8.27%",
    "enquiryYearEndMinusOneDisplay": "30/06/2023",
    "amalgamatedLoanNotPaidByEOIYFormatted": "$1,932.00",
    "openingBalancePayDays": "77",
    "openingBalanceInterestFormatted": "$33.61",
    "totalAmountOfRepaymentFormatted": "$1,932.00",
    "totalInterestFormatted": "$33.61",
    "principalFormatted": "$1,898.39",
    "enquiryYearEndDisplay": "30/06/2024",
    "minimumYearRepaymentFormatted": "$0"
  },
  "repayments": [
    {
      "rd": "16/9/2023",
      "ra": 1932
    }
  ],
  "inputs": {
    "incomeYearOfLoan": 2023,
    "fullTermOfAmalgamatedLoan": 3,
    "incomeYearOfEnquiring": 2024,
    "amalgamatedLoanNotPaidByEOIY": 1932,
    "repayments": null,
    "lodgement_date": "10/6/2024"
  },
  "idx": 2180
}