{
  "id": "2023-10-31T17:54:51.653Z0.4197502696182228",
  "alert": "Start of result\nResult\n\nAmalgamated loan fully repaid.\n\nThe amalgamated loan has been paid in full.\u000bThe private company is not taken under Division 7A to pay a dividend to the shareholder or shareholder's associate.\n\nInterest received by the private company must be included in the income tax return for 2015-16.\n\nMinimum yearly repayment\n\n$3,604.00\n\nBenchmark interest rate\n\n5.45%\n\nOpening balance:\n\nDate: 30/06/2015\n\nBalance: $3,418.00\n\nDays: 337\n\nInterest: $171.52\n\nPayments\n\nDate: 02/06/2016\n\nAmount: $5,203.00\n\nBalance: $0\n\nDays: 29\n\nInterest: $0\n\n\n\n\nTotal repayments\n\n$5,203.00\n\nTotal interest\n\n$171.52\n\nTotal principal\n\n$5,031.48\n\nClosing balance\n\nDate: 30/06/2016\n\nBalance: $0",
  "outputs": {
    "enquiryRateFormatted": "5.45%",
    "enquiryYearEndMinusOneDisplay": "30/06/2015",
    "amalgamatedLoanNotPaidByEOIYFormatted": "$3,418.00",
    "openingBalancePayDays": "337",
    "openingBalanceInterestFormatted": "$171.52",
    "totalAmountOfRepaymentFormatted": "$5,203.00",
    "totalInterestFormatted": "$171.52",
    "principalFormatted": "$5,031.48",
    "enquiryYearEndDisplay": "30/06/2016",
    "minimumYearRepaymentFormatted": "$3,604.00",
    "loanAmountFormatted": "$0"
  },
  "repayments": [
    {
      "rd": "2/6/2016",
      "ra": 5203
    }
  ],
  "inputs": {
    "incomeYearOfLoan": 2013,
    "fullTermOfAmalgamatedLoan": 3,
    "incomeYearOfEnquiring": 2016,
    "amalgamatedLoanNotPaidByEOIY": 3418,
    "repayments": null,
    "lodgement_date": null
  },
  "idx": 2892
}