{
  "id": "2023-11-01T00:35:36.732Z0.9662293295607666",
  "alert": "Start of result\nResult\n\nAmalgamated loan fully repaid.\n\nThe amalgamated loan has been paid in full.\u000bThe private company is not taken under Division 7A to pay a dividend to the shareholder or shareholder's associate.\n\nInterest received by the private company must be included in the income tax return for 2000-01.\n\nMinimum yearly repayment\n\n$13.00\n\nBenchmark interest rate\n\n7.8%\n\nOpening balance:\n\nDate: 30/06/2000\n\nBalance: $51.35\n\nDays: 320\n\nInterest: $3.51\n\nPayments\n\nDate: 17/05/2001\n\nAmount: $513.55\n\nBalance: $0\n\nDays: 45\n\nInterest: $0\n\n\n\n\nTotal repayments\n\n$513.55\n\nTotal interest\n\n$3.51\n\nTotal principal\n\n$510.04\n\nClosing balance\n\nDate: 30/06/2001\n\nBalance: $0",
  "outputs": {
    "enquiryRateFormatted": "7.8%",
    "enquiryYearEndMinusOneDisplay": "30/06/2000",
    "amalgamatedLoanNotPaidByEOIYFormatted": "$51.35",
    "openingBalancePayDays": "320",
    "openingBalanceInterestFormatted": "$3.51",
    "totalAmountOfRepaymentFormatted": "$513.55",
    "totalInterestFormatted": "$3.51",
    "principalFormatted": "$510.04",
    "enquiryYearEndDisplay": "30/06/2001",
    "minimumYearRepaymentFormatted": "$13.00",
    "loanAmountFormatted": "$0"
  },
  "repayments": [
    {
      "rd": "17/5/2001",
      "ra": 513.5543019718352
    }
  ],
  "inputs": {
    "incomeYearOfLoan": 1998,
    "fullTermOfAmalgamatedLoan": 7,
    "incomeYearOfEnquiring": 2001,
    "amalgamatedLoanNotPaidByEOIY": 51.35543019718354,
    "repayments": null,
    "lodgement_date": null
  },
  "idx": 84
}