{
  "id": "2023-09-04T21:01:02.915Z0.07321632665290934",
  "alert": "Start of result\nResult\n\nMinimum yearly repayment not met.\n\nThe amount of the loan not repaid at the end of income year 2009-10 is $72,069,218.73.\n\nThe private company may be taken to pay a dividend under Division 7A to the shareholder or shareholder's associate because the amount repaid during income year 2009-10 in relation to the amalgamated loan is less than the minimum yearly repayment required.\n\nInterest received by the private company must be included in the income tax return for 2009-10.\n\nMinimum yearly repayment\n\n$76,213,199.00\n\nBenchmark interest rate\n\n5.75%\n\nOpening balance:\n\nDate: 30/06/2009\n\nBalance: $72,069,218.73\n\nDays: 365\n\nInterest: $4,143,980.08\n\nTotal repayments\n\n$0\n\nTotal interest\n\n$4,143,980.08\n\nTotal principal\n\n$0\n\nClosing balance\n\nDate: 30/06/2010\n\nBalance: $72,069,218.73",
  "outputs": {
    "enquiryRateFormatted": "5.75%",
    "enquiryYearEndMinusOneDisplay": "30/06/2009",
    "amalgamatedLoanNotPaidByEOIYFormatted": "$72,069,218.73",
    "openingBalancePayDays": "365",
    "openingBalanceInterestFormatted": "$4,143,980.08",
    "totalAmountOfRepaymentFormatted": "$0",
    "totalInterestFormatted": "$4,143,980.08",
    "principalFormatted": "$0",
    "enquiryYearEndDisplay": "30/06/2010",
    "minimumYearRepaymentFormatted": "$76,213,199.00"
  },
  "repayments": [],
  "inputs": {
    "incomeYearOfLoan": 2009,
    "fullTermOfAmalgamatedLoan": 1,
    "incomeYearOfEnquiring": 2010,
    "amalgamatedLoanNotPaidByEOIY": 72069218.73139359,
    "repayments": null,
    "lodgement_date": "30/6/2010"
  },
  "idx": 503
}