{
  "id": "2023-09-04T17:12:46.454Z0.3155126652580751",
  "alert": "Start of result\nResult\n\nMinimum yearly repayment not met.\n\nThe amount of the loan not repaid at the end of income year 2014-15 is $10,946,255.69.\n\nThe private company may be taken to pay a dividend under Division 7A to the shareholder or shareholder's associate because the amount repaid during income year 2014-15 in relation to the amalgamated loan is less than the minimum yearly repayment required.\n\nInterest received by the private company must be included in the income tax return for 2014-15.\n\nMinimum yearly repayment\n\n$4,091,314.00\n\nBenchmark interest rate\n\n5.95%\n\nOpening balance:\n\nDate: 30/06/2014\n\nBalance: $10,946,255.69\n\nDays: 0\n\nInterest: $0\n\nPayments\n\nDate: 01/07/2014\n\nAmount: $7,081.00\n\nBalance: $10,939,174.69\n\nDays: 365\n\nInterest: $650,880.89\n\n\n\n\nTotal repayments\n\n$7,081.00\n\nTotal interest\n\n$650,880.89\n\nTotal principal\n\n$0\n\nClosing balance\n\nDate: 30/06/2015\n\nBalance: $10,946,255.69",
  "outputs": {
    "enquiryRateFormatted": "5.95%",
    "enquiryYearEndMinusOneDisplay": "30/06/2014",
    "amalgamatedLoanNotPaidByEOIYFormatted": "$10,946,255.69",
    "openingBalancePayDays": "0",
    "openingBalanceInterestFormatted": "$0",
    "totalAmountOfRepaymentFormatted": "$7,081.00",
    "totalInterestFormatted": "$650,880.89",
    "principalFormatted": "$0",
    "enquiryYearEndDisplay": "30/06/2015",
    "minimumYearRepaymentFormatted": "$4,091,314.00"
  },
  "repayments": [
    {
      "rd": "1/7/2014",
      "ra": 7081
    }
  ],
  "inputs": {
    "incomeYearOfLoan": 2014,
    "fullTermOfAmalgamatedLoan": 3,
    "incomeYearOfEnquiring": 2015,
    "amalgamatedLoanNotPaidByEOIY": 10946255.691538304,
    "repayments": null,
    "lodgement_date": "1/7/2014"
  },
  "idx": 1849
}