{
  "id": "2023-09-06T07:09:19.063Z0.8969368913963731",
  "alert": "Start of result\nResult\n\nMinimum yearly repayment met.\n\nThe amount of the loan not repaid at the end of income year 2011-12 is $60.62.\n\nThe amalgamated loan will not be taken to be a dividend because the total repayments made are equal to or greater than the minimum yearly repayment required for income year 2011-12.\n\nInterest received by the private company must be included in the income tax return for 2011-12.\n\nMinimum yearly repayment\n\n$0\n\nBenchmark interest rate\n\n7.8%\n\nOpening balance:\n\nDate: 30/06/2011\n\nBalance: $3,427.00\n\nDays: 83\n\nInterest: $60.62\n\nPayments\n\nDate: 22/09/2011\n\nAmount: $3,427.00\n\nBalance: $0\n\nDays: 283\n\nInterest: $0\n\n\n\n\nTotal repayments\n\n$3,427.00\n\nTotal interest\n\n$60.62\n\nTotal principal\n\n$3,366.38\n\nClosing balance\n\nDate: 30/06/2012\n\nBalance: $60.62",
  "outputs": {
    "enquiryRateFormatted": "7.8%",
    "enquiryYearEndMinusOneDisplay": "30/06/2011",
    "amalgamatedLoanNotPaidByEOIYFormatted": "$3,427.00",
    "openingBalancePayDays": "83",
    "openingBalanceInterestFormatted": "$60.62",
    "totalAmountOfRepaymentFormatted": "$3,427.00",
    "totalInterestFormatted": "$60.62",
    "principalFormatted": "$3,366.38",
    "enquiryYearEndDisplay": "30/06/2012",
    "minimumYearRepaymentFormatted": "$0"
  },
  "repayments": [
    {
      "rd": "22/9/2011",
      "ra": 3427
    }
  ],
  "inputs": {
    "incomeYearOfLoan": 2011,
    "fullTermOfAmalgamatedLoan": 7,
    "incomeYearOfEnquiring": 2012,
    "amalgamatedLoanNotPaidByEOIY": 3427,
    "repayments": null,
    "lodgement_date": "8/11/2011"
  },
  "idx": 7916
}