{
  "id": "2023-10-31T17:07:07.868Z0.6442239355923913",
  "alert": "Start of result\nResult\n\nAmalgamated loan fully repaid.\n\nThe amalgamated loan has been paid in full.\u000bThe private company is not taken under Division 7A to pay a dividend to the shareholder or shareholder's associate.\n\nInterest received by the private company must be included in the income tax return for 2023-24.\n\nMinimum yearly repayment\n\n-$536.00\n\nBenchmark interest rate\n\n8.27%\n\nOpening balance:\n\nDate: 30/06/2023\n\nBalance: $105.72\n\nDays: 16\n\nInterest: $0.38\n\nPayments\n\nDate: 17/07/2023\n\nAmount: $1,057.22\n\nBalance: $0\n\nDays: 350\n\nInterest: $0\n\n\n\n\nTotal repayments\n\n$1,057.22\n\nTotal interest\n\n$0.38\n\nTotal principal\n\n$1,056.84\n\nClosing balance\n\nDate: 30/06/2024\n\nBalance: $0",
  "outputs": {
    "enquiryRateFormatted": "8.27%",
    "enquiryYearEndMinusOneDisplay": "30/06/2023",
    "amalgamatedLoanNotPaidByEOIYFormatted": "$105.72",
    "openingBalancePayDays": "16",
    "openingBalanceInterestFormatted": "$0.38",
    "totalAmountOfRepaymentFormatted": "$1,057.22",
    "totalInterestFormatted": "$0.38",
    "principalFormatted": "$1,056.84",
    "enquiryYearEndDisplay": "30/06/2024",
    "minimumYearRepaymentFormatted": "-$536.00",
    "loanAmountFormatted": "$0"
  },
  "repayments": [
    {
      "rd": "17/7/2023",
      "ra": 1057.2247213167411
    }
  ],
  "inputs": {
    "incomeYearOfLoan": 2023,
    "fullTermOfAmalgamatedLoan": 2,
    "incomeYearOfEnquiring": 2024,
    "amalgamatedLoanNotPaidByEOIY": 105.72247213167407,
    "repayments": null,
    "lodgement_date": "28/12/2023"
  },
  "idx": 20
}