{
  "id": "2023-10-31T17:18:22.077Z0.4672817619794487",
  "alert": "Start of result\nResult\n\nMinimum yearly repayment met.\n\nThe amount of the loan not repaid at the end of income year 2022-23 is $6,619.12.\n\n\u000b\n\nThe amalgamated loan will not be taken to be a dividend because the total repayments made are equal to or greater than the minimum yearly repayment required for income year 2022-23.\n\nInterest received by the private company must be included in the income tax return for 2022-23.\n\nMinimum yearly repayment\n\n$2,253.00\n\nBenchmark interest rate\n\n4.77%\n\nOpening balance:\n\nDate: 30/06/2022\n\nBalance: $9,815.00\n\nDays: 231\n\nInterest: $296.30\n\nPayments\n\nDate: 17/02/2023\n\nAmount: $3,601.00\n\nBalance: $6,214.00\n\nDays: 134\n\nInterest: $108.82\n\n\n\n\nTotal repayments\n\n$3,601.00\n\nTotal interest\n\n$405.12\n\nTotal principal\n\n$3,195.88\n\nClosing balance\n\nDate: 30/06/2023\n\nBalance: $6,619.12",
  "outputs": {
    "enquiryRateFormatted": "4.77%",
    "enquiryYearEndMinusOneDisplay": "30/06/2022",
    "amalgamatedLoanNotPaidByEOIYFormatted": "$9,815.00",
    "openingBalancePayDays": "231",
    "openingBalanceInterestFormatted": "$296.30",
    "totalAmountOfRepaymentFormatted": "$3,601.00",
    "totalInterestFormatted": "$405.12",
    "principalFormatted": "$3,195.88",
    "enquiryYearEndDisplay": "30/06/2023",
    "minimumYearRepaymentFormatted": "$2,253.00",
    "loanAmountFormatted": "$6,619.12"
  },
  "repayments": [
    {
      "rd": "17/2/2023",
      "ra": 3601
    }
  ],
  "inputs": {
    "incomeYearOfLoan": 2020,
    "fullTermOfAmalgamatedLoan": 7,
    "incomeYearOfEnquiring": 2023,
    "amalgamatedLoanNotPaidByEOIY": 9815,
    "repayments": null,
    "lodgement_date": null
  },
  "idx": 973
}