{
  "id": "2023-09-06T10:53:19.142Z0.32959682633268517",
  "alert": "Start of result\nResult\n\nMinimum yearly repayment not met.\n\nThe amount of the loan not repaid at the end of income year 2009-10 is $0.87.\n\nThe private company may be taken to pay a dividend under Division 7A to the shareholder or shareholder's associate because the amount repaid during income year 2009-10 in relation to the amalgamated loan is less than the minimum yearly repayment required.\n\nInterest received by the private company must be included in the income tax return for 2009-10.\n\nMinimum yearly repayment\n\n$99.00\n\nBenchmark interest rate\n\n5.75%\n\nOpening balance:\n\nDate: 30/06/2009\n\nBalance: $93.83\n\nDays: 59\n\nInterest: $0.87\n\nPayments\n\nDate: 29/08/2009\n\nAmount: $93.83\n\nBalance: $0\n\nDays: 306\n\nInterest: $0\n\n\n\n\nTotal repayments\n\n$93.83\n\nTotal interest\n\n$0.87\n\nTotal principal\n\n$92.96\n\nClosing balance\n\nDate: 30/06/2010\n\nBalance: $0.87",
  "outputs": {
    "enquiryRateFormatted": "5.75%",
    "enquiryYearEndMinusOneDisplay": "30/06/2009",
    "amalgamatedLoanNotPaidByEOIYFormatted": "$93.83",
    "openingBalancePayDays": "59",
    "openingBalanceInterestFormatted": "$0.87",
    "totalAmountOfRepaymentFormatted": "$93.83",
    "totalInterestFormatted": "$0.87",
    "principalFormatted": "$92.96",
    "enquiryYearEndDisplay": "30/06/2010",
    "minimumYearRepaymentFormatted": "$99.00"
  },
  "repayments": [
    {
      "rd": "29/8/2009",
      "ra": 93.83932293354917
    }
  ],
  "inputs": {
    "incomeYearOfLoan": 2008,
    "fullTermOfAmalgamatedLoan": 2,
    "incomeYearOfEnquiring": 2010,
    "amalgamatedLoanNotPaidByEOIY": 93.83932293354917,
    "repayments": null,
    "lodgement_date": null
  },
  "idx": 2209
}