{
  "id": "2023-09-04T21:00:42.913Z0.6741306961632938",
  "alert": "Start of result\nResult\n\nMinimum yearly repayment not met.\n\nThe amount of the loan not repaid at the end of income year 2010-11 is $75,051,938.44.\n\nThe private company may be taken to pay a dividend under Division 7A to the shareholder or shareholder's associate because the amount repaid during income year 2010-11 in relation to the amalgamated loan is less than the minimum yearly repayment required.\n\nInterest received by the private company must be included in the income tax return for 2010-11.\n\nMinimum yearly repayment\n\n$14,120,939.00\n\nBenchmark interest rate\n\n7.4%\n\nOpening balance:\n\nDate: 30/06/2010\n\nBalance: $75,051,938.44\n\nDays: 0\n\nInterest: $0\n\nPayments\n\nDate: 01/07/2010\n\nAmount: $3,242.00\n\nBalance: $75,048,696.44\n\nDays: 365\n\nInterest: $5,553,603.54\n\n\n\n\nTotal repayments\n\n$3,242.00\n\nTotal interest\n\n$5,553,603.54\n\nTotal principal\n\n$0\n\nClosing balance\n\nDate: 30/06/2011\n\nBalance: $75,051,938.44",
  "outputs": {
    "enquiryRateFormatted": "7.4%",
    "enquiryYearEndMinusOneDisplay": "30/06/2010",
    "amalgamatedLoanNotPaidByEOIYFormatted": "$75,051,938.44",
    "openingBalancePayDays": "0",
    "openingBalanceInterestFormatted": "$0",
    "totalAmountOfRepaymentFormatted": "$3,242.00",
    "totalInterestFormatted": "$5,553,603.54",
    "principalFormatted": "$0",
    "enquiryYearEndDisplay": "30/06/2011",
    "minimumYearRepaymentFormatted": "$14,120,939.00"
  },
  "repayments": [
    {
      "rd": "1/7/2010",
      "ra": 3242
    }
  ],
  "inputs": {
    "incomeYearOfLoan": 2010,
    "fullTermOfAmalgamatedLoan": 7,
    "incomeYearOfEnquiring": 2011,
    "amalgamatedLoanNotPaidByEOIY": 75051938.44993435,
    "repayments": null,
    "lodgement_date": "1/7/2010"
  },
  "idx": 489
}