{
  "id": "2023-10-31T17:26:01.141Z0.5476989667073111",
  "alert": "Start of result\nResult\n\nAmalgamated loan fully repaid.\n\nThe amalgamated loan has been paid in full.\u000bThe private company is not taken under Division 7A to pay a dividend to the shareholder or shareholder's associate.\n\nInterest received by the private company must be included in the income tax return for 2022-23.\n\nMinimum yearly repayment\n\n$30.00\n\nBenchmark interest rate\n\n4.77%\n\nOpening balance:\n\nDate: 30/06/2022\n\nBalance: $82.01\n\nDays: 241\n\nInterest: $2.58\n\nPayments\n\nDate: 27/02/2023\n\nAmount: $820.16\n\nBalance: $0\n\nDays: 124\n\nInterest: $0\n\n\n\n\nTotal repayments\n\n$820.16\n\nTotal interest\n\n$2.58\n\nTotal principal\n\n$817.58\n\nClosing balance\n\nDate: 30/06/2023\n\nBalance: $0",
  "outputs": {
    "enquiryRateFormatted": "4.77%",
    "enquiryYearEndMinusOneDisplay": "30/06/2022",
    "amalgamatedLoanNotPaidByEOIYFormatted": "$82.01",
    "openingBalancePayDays": "241",
    "openingBalanceInterestFormatted": "$2.58",
    "totalAmountOfRepaymentFormatted": "$820.16",
    "totalInterestFormatted": "$2.58",
    "principalFormatted": "$817.58",
    "enquiryYearEndDisplay": "30/06/2023",
    "minimumYearRepaymentFormatted": "$30.00",
    "loanAmountFormatted": "$0"
  },
  "repayments": [
    {
      "rd": "27/2/2023",
      "ra": 820.1618284289943
    }
  ],
  "inputs": {
    "incomeYearOfLoan": 2018,
    "fullTermOfAmalgamatedLoan": 7,
    "incomeYearOfEnquiring": 2023,
    "amalgamatedLoanNotPaidByEOIY": 82.01618284289944,
    "repayments": null,
    "lodgement_date": null
  },
  "idx": 1468
}