{
  "id": "2023-10-31T19:09:03.658Z0.7449108100535238",
  "alert": "Start of result\nResult\n\nMinimum yearly repayment not met.\n\nThe amount of the loan not repaid at the end of income year 2010-11 is $444.00.\n\nThe private company may be taken to pay a dividend under Division 7A to the shareholder or shareholder's associate because the amount repaid during income year 2010-11 in relation to the amalgamated loan is less than the minimum yearly repayment required.\n\nInterest received by the private company must be included in the income tax return for 2010-11.\n\nMinimum yearly repayment\n\n$170.00\n\nBenchmark interest rate\n\n7.4%\n\nOpening balance:\n\nDate: 30/06/2010\n\nBalance: $444.00\n\nDays: 365\n\nInterest: $32.86\n\nTotal repayments\n\n$0\n\nTotal interest\n\n$32.86\n\nTotal principal\n\n$0\n\nClosing balance\n\nDate: 30/06/2011\n\nBalance: $444.00",
  "outputs": {
    "enquiryRateFormatted": "7.4%",
    "enquiryYearEndMinusOneDisplay": "30/06/2010",
    "amalgamatedLoanNotPaidByEOIYFormatted": "$444.00",
    "openingBalancePayDays": "365",
    "openingBalanceInterestFormatted": "$32.86",
    "totalAmountOfRepaymentFormatted": "$0",
    "totalInterestFormatted": "$32.86",
    "principalFormatted": "$0",
    "enquiryYearEndDisplay": "30/06/2011",
    "minimumYearRepaymentFormatted": "$170.00",
    "loanAmountFormatted": "$444.00"
  },
  "repayments": [],
  "inputs": {
    "incomeYearOfLoan": 2006,
    "fullTermOfAmalgamatedLoan": 7,
    "incomeYearOfEnquiring": 2011,
    "amalgamatedLoanNotPaidByEOIY": 444,
    "repayments": null,
    "lodgement_date": null
  },
  "idx": 5082
}