{
  "id": "2023-10-31T18:13:39.976Z0.28566293143831245",
  "alert": "Start of result\nResult\n\nAmalgamated loan fully repaid.\n\nThe amalgamated loan has been paid in full.\u000bThe private company is not taken under Division 7A to pay a dividend to the shareholder or shareholder's associate.\n\nInterest received by the private company must be included in the income tax return for 2016-17.\n\nMinimum yearly repayment\n\n$29.00\n\nBenchmark interest rate\n\n5.4%\n\nOpening balance:\n\nDate: 30/06/2016\n\nBalance: $54.25\n\nDays: 229\n\nInterest: $1.84\n\nPayments\n\nDate: 15/02/2017\n\nAmount: $542.52\n\nBalance: $0\n\nDays: 136\n\nInterest: $0\n\n\n\n\nTotal repayments\n\n$542.52\n\nTotal interest\n\n$1.84\n\nTotal principal\n\n$540.68\n\nClosing balance\n\nDate: 30/06/2017\n\nBalance: $0",
  "outputs": {
    "enquiryRateFormatted": "5.4%",
    "enquiryYearEndMinusOneDisplay": "30/06/2016",
    "amalgamatedLoanNotPaidByEOIYFormatted": "$54.25",
    "openingBalancePayDays": "229",
    "openingBalanceInterestFormatted": "$1.84",
    "totalAmountOfRepaymentFormatted": "$542.52",
    "totalInterestFormatted": "$1.84",
    "principalFormatted": "$540.68",
    "enquiryYearEndDisplay": "30/06/2017",
    "minimumYearRepaymentFormatted": "$29.00",
    "loanAmountFormatted": "$0"
  },
  "repayments": [
    {
      "rd": "15/2/2017",
      "ra": 542.5286002384548
    }
  ],
  "inputs": {
    "incomeYearOfLoan": 2011,
    "fullTermOfAmalgamatedLoan": 7,
    "incomeYearOfEnquiring": 2017,
    "amalgamatedLoanNotPaidByEOIY": 54.252860023845486,
    "repayments": null,
    "lodgement_date": null
  },
  "idx": 3577
}