{
  "id": "2023-10-31T18:39:13.727Z0.05017542780284456",
  "alert": "Start of result\nResult\n\nMinimum yearly repayment met.\n\nThe amount of the loan not repaid at the end of income year 2008-09 is $3,413.13.\n\n\u000b\n\nThe amalgamated loan will not be taken to be a dividend because the total repayments made are equal to or greater than the minimum yearly repayment required for income year 2008-09.\n\nInterest received by the private company must be included in the income tax return for 2008-09.\n\nMinimum yearly repayment\n\n$912.00\n\nBenchmark interest rate\n\n9.45%\n\nOpening balance:\n\nDate: 30/06/2008\n\nBalance: $7,773.00\n\nDays: 167\n\nInterest: $336.08\n\nPayments\n\nDate: 15/12/2008\n\nAmount: $4,846.00\n\nBalance: $2,927.00\n\nDays: 198\n\nInterest: $150.05\n\n\n\n\nTotal repayments\n\n$4,846.00\n\nTotal interest\n\n$486.13\n\nTotal principal\n\n$4,359.87\n\nClosing balance\n\nDate: 30/06/2009\n\nBalance: $3,413.13",
  "outputs": {
    "enquiryRateFormatted": "9.45%",
    "enquiryYearEndMinusOneDisplay": "30/06/2008",
    "amalgamatedLoanNotPaidByEOIYFormatted": "$7,773.00",
    "openingBalancePayDays": "167",
    "openingBalanceInterestFormatted": "$336.08",
    "totalAmountOfRepaymentFormatted": "$4,846.00",
    "totalInterestFormatted": "$486.13",
    "principalFormatted": "$4,359.87",
    "enquiryYearEndDisplay": "30/06/2009",
    "minimumYearRepaymentFormatted": "$912.00",
    "loanAmountFormatted": "$3,413.13"
  },
  "repayments": [
    {
      "rd": "15/12/2008",
      "ra": 4846
    }
  ],
  "inputs": {
    "incomeYearOfLoan": 2008,
    "fullTermOfAmalgamatedLoan": 4,
    "incomeYearOfEnquiring": 2009,
    "amalgamatedLoanNotPaidByEOIY": 7773,
    "repayments": null,
    "lodgement_date": "27/5/2009"
  },
  "idx": 4336
}