{
  "id": "2023-10-31T17:58:19.310Z0.2020218862779597",
  "alert": "Start of result\nResult\n\nMinimum yearly repayment met.\n\nThe amount of the loan not repaid at the end of income year 2013-14 is $285.37.\n\n\u000b\n\nThe amalgamated loan will not be taken to be a dividend because the total repayments made are equal to or greater than the minimum yearly repayment required for income year 2013-14.\n\nInterest received by the private company must be included in the income tax return for 2013-14.\n\nMinimum yearly repayment\n\n$1,668.00\n\nBenchmark interest rate\n\n6.2%\n\nOpening balance:\n\nDate: 30/06/2013\n\nBalance: $8,153.00\n\nDays: 168\n\nInterest: $232.66\n\nPayments\n\nDate: 16/12/2013\n\nAmount: $8,102.00\n\nBalance: $51.00\n\nDays: 197\n\nInterest: $1.71\n\n\n\n\nTotal repayments\n\n$8,102.00\n\nTotal interest\n\n$234.37\n\nTotal principal\n\n$7,867.63\n\nClosing balance\n\nDate: 30/06/2014\n\nBalance: $285.37",
  "outputs": {
    "enquiryRateFormatted": "6.2%",
    "enquiryYearEndMinusOneDisplay": "30/06/2013",
    "amalgamatedLoanNotPaidByEOIYFormatted": "$8,153.00",
    "openingBalancePayDays": "168",
    "openingBalanceInterestFormatted": "$232.66",
    "totalAmountOfRepaymentFormatted": "$8,102.00",
    "totalInterestFormatted": "$234.37",
    "principalFormatted": "$7,867.63",
    "enquiryYearEndDisplay": "30/06/2014",
    "minimumYearRepaymentFormatted": "$1,668.00",
    "loanAmountFormatted": "$285.37"
  },
  "repayments": [
    {
      "rd": "16/12/2013",
      "ra": 8102
    }
  ],
  "inputs": {
    "incomeYearOfLoan": 2013,
    "fullTermOfAmalgamatedLoan": 6,
    "incomeYearOfEnquiring": 2014,
    "amalgamatedLoanNotPaidByEOIY": 8153,
    "repayments": null,
    "lodgement_date": "1/7/2013"
  },
  "idx": 3025
}