{
  "id": "2023-09-04T22:02:40.700Z0.922966712090574",
  "alert": "Start of result\nResult\n\nMinimum yearly repayment met.\n\nThe amount of the loan not repaid at the end of income year 2006-07 is $107.20.\n\nThe amalgamated loan will not be taken to be a dividend because the total repayments made are equal to or greater than the minimum yearly repayment required for income year 2006-07.\n\nInterest received by the private company must be included in the income tax return for 2006-07.\n\nMinimum yearly repayment\n\n$1,632.00\n\nBenchmark interest rate\n\n7.55%\n\nOpening balance:\n\nDate: 30/06/2006\n\nBalance: $4,239.00\n\nDays: 0\n\nInterest: $0\n\nPayments\n\nDate: 01/07/2006\n\nAmount: $871.00\n\nBalance: $3,368.00\n\nDays: 118\n\nInterest: $82.21\n\n\n\n\nDate: 27/10/2006\n\nAmount: $2,856.00\n\nBalance: $512.00\n\nDays: 236\n\nInterest: $24.99\n\n\n\n\nDate: 20/06/2007\n\nAmount: $512.00\n\nBalance: $0\n\nDays: 11\n\nInterest: $0\n\n\n\n\nTotal repayments\n\n$4,239.00\n\nTotal interest\n\n$107.20\n\nTotal principal\n\n$4,131.80\n\nClosing balance\n\nDate: 30/06/2007\n\nBalance: $107.20",
  "outputs": {
    "enquiryRateFormatted": "7.55%",
    "enquiryYearEndMinusOneDisplay": "30/06/2006",
    "amalgamatedLoanNotPaidByEOIYFormatted": "$4,239.00",
    "openingBalancePayDays": "0",
    "openingBalanceInterestFormatted": "$0",
    "totalAmountOfRepaymentFormatted": "$4,239.00",
    "totalInterestFormatted": "$107.20",
    "principalFormatted": "$4,131.80",
    "enquiryYearEndDisplay": "30/06/2007",
    "minimumYearRepaymentFormatted": "$1,632.00"
  },
  "repayments": [
    {
      "rd": "1/7/2006",
      "ra": 871
    },
    {
      "rd": "27/10/2006",
      "ra": 2856
    },
    {
      "rd": "20/6/2007",
      "ra": 512
    }
  ],
  "inputs": {
    "incomeYearOfLoan": 2004,
    "fullTermOfAmalgamatedLoan": 5,
    "incomeYearOfEnquiring": 2007,
    "amalgamatedLoanNotPaidByEOIY": 4239,
    "repayments": null,
    "lodgement_date": null
  },
  "idx": 71
}