{
  "id": "2023-09-04T15:59:58.059Z0.09287748635441195",
  "alert": "Start of result\nResult\n\nMinimum yearly repayment not met.\n\nThe amount of the loan not repaid at the end of income year 2023-24 is $2,382.38.\n\nThe private company may be taken to pay a dividend under Division 7A to the shareholder or shareholder's associate because the amount repaid during income year 2023-24 in relation to the amalgamated loan is less than the minimum yearly repayment required.\n\nInterest received by the private company must be included in the income tax return for 2023-24.\n\nMinimum yearly repayment\n\n$8,039.00\n\nBenchmark interest rate\n\n8.27%\n\nOpening balance:\n\nDate: 30/06/2023\n\nBalance: $7,425.00\n\nDays: 0\n\nInterest: $0\n\nPayments\n\nDate: 01/07/2023\n\nAmount: $2,910.00\n\nBalance: $4,515.00\n\nDays: 325\n\nInterest: $331.56\n\n\n\n\nDate: 21/05/2024\n\nAmount: $2,483.00\n\nBalance: $2,032.00\n\nDays: 41\n\nInterest: $18.82\n\n\n\n\nTotal repayments\n\n$5,393.00\n\nTotal interest\n\n$350.38\n\nTotal principal\n\n$5,042.62\n\nClosing balance\n\nDate: 30/06/2024\n\nBalance: $2,382.38",
  "outputs": {
    "enquiryRateFormatted": "8.27%",
    "enquiryYearEndMinusOneDisplay": "30/06/2023",
    "amalgamatedLoanNotPaidByEOIYFormatted": "$7,425.00",
    "openingBalancePayDays": "0",
    "openingBalanceInterestFormatted": "$0",
    "totalAmountOfRepaymentFormatted": "$5,393.00",
    "totalInterestFormatted": "$350.38",
    "principalFormatted": "$5,042.62",
    "enquiryYearEndDisplay": "30/06/2024",
    "minimumYearRepaymentFormatted": "$8,039.00"
  },
  "repayments": [
    {
      "rd": "1/7/2023",
      "ra": 2910
    },
    {
      "rd": "21/5/2024",
      "ra": 2483
    }
  ],
  "inputs": {
    "incomeYearOfLoan": 2023,
    "fullTermOfAmalgamatedLoan": 1,
    "incomeYearOfEnquiring": 2024,
    "amalgamatedLoanNotPaidByEOIY": 7425,
    "repayments": null,
    "lodgement_date": "1/7/2023"
  },
  "idx": 10
}