{
  "id": "2023-10-31T17:34:22.060Z0.9360989468160855",
  "alert": "Start of result\nResult\n\nAmalgamated loan fully repaid.\n\nThe amalgamated loan has been paid in full.\u000bThe private company is not taken under Division 7A to pay a dividend to the shareholder or shareholder's associate.\n\nInterest received by the private company must be included in the income tax return for 2019-20.\n\nMinimum yearly repayment\n\n$65.00\n\nBenchmark interest rate\n\n5.37%\n\nOpening balance:\n\nDate: 30/06/2019\n\nBalance: $61.75\n\nDays: 200\n\nInterest: $1.81\n\nPayments\n\nDate: 17/01/2020\n\nAmount: $617.59\n\nBalance: $0\n\nDays: 166\n\nInterest: $0\n\n\n\n\nTotal repayments\n\n$617.59\n\nTotal interest\n\n$1.81\n\nTotal principal\n\n$615.78\n\nClosing balance\n\nDate: 30/06/2020\n\nBalance: $0",
  "outputs": {
    "enquiryRateFormatted": "5.37%",
    "enquiryYearEndMinusOneDisplay": "30/06/2019",
    "amalgamatedLoanNotPaidByEOIYFormatted": "$61.75",
    "openingBalancePayDays": "200",
    "openingBalanceInterestFormatted": "$1.81",
    "totalAmountOfRepaymentFormatted": "$617.59",
    "totalInterestFormatted": "$1.81",
    "principalFormatted": "$615.78",
    "enquiryYearEndDisplay": "30/06/2020",
    "minimumYearRepaymentFormatted": "$65.00",
    "loanAmountFormatted": "$0"
  },
  "repayments": [
    {
      "rd": "17/1/2020",
      "ra": 617.5931486823847
    }
  ],
  "inputs": {
    "incomeYearOfLoan": 2016,
    "fullTermOfAmalgamatedLoan": 4,
    "incomeYearOfEnquiring": 2020,
    "amalgamatedLoanNotPaidByEOIY": 61.75931486823847,
    "repayments": null,
    "lodgement_date": null
  },
  "idx": 1941
}