{
  "id": "2023-10-31T21:08:07.682Z0.49378962693556716",
  "alert": "Start of result\nResult\n\nAmalgamated loan fully repaid.\n\nThe amalgamated loan has been paid in full.\u000bThe private company is not taken under Division 7A to pay a dividend to the shareholder or shareholder's associate.\n\nInterest received by the private company must be included in the income tax return for 2001-02.\n\nMinimum yearly repayment\n\n$286.00\n\nBenchmark interest rate\n\n6.8%\n\nOpening balance:\n\nDate: 30/06/2001\n\nBalance: $973.00\n\nDays: 211\n\nInterest: $38.25\n\nPayments\n\nDate: 28/01/2002\n\nAmount: $6,083.00\n\nBalance: $0\n\nDays: 154\n\nInterest: $0\n\n\n\n\nTotal repayments\n\n$6,083.00\n\nTotal interest\n\n$38.25\n\nTotal principal\n\n$6,044.75\n\nClosing balance\n\nDate: 30/06/2002\n\nBalance: $0",
  "outputs": {
    "enquiryRateFormatted": "6.8%",
    "enquiryYearEndMinusOneDisplay": "30/06/2001",
    "amalgamatedLoanNotPaidByEOIYFormatted": "$973.00",
    "openingBalancePayDays": "211",
    "openingBalanceInterestFormatted": "$38.25",
    "totalAmountOfRepaymentFormatted": "$6,083.00",
    "totalInterestFormatted": "$38.25",
    "principalFormatted": "$6,044.75",
    "enquiryYearEndDisplay": "30/06/2002",
    "minimumYearRepaymentFormatted": "$286.00",
    "loanAmountFormatted": "$0"
  },
  "repayments": [
    {
      "rd": "28/1/2002",
      "ra": 6083
    }
  ],
  "inputs": {
    "incomeYearOfLoan": 1999,
    "fullTermOfAmalgamatedLoan": 6,
    "incomeYearOfEnquiring": 2002,
    "amalgamatedLoanNotPaidByEOIY": 973,
    "repayments": null,
    "lodgement_date": null
  },
  "idx": 7041
}