{
  "id": "2023-10-31T20:43:44.869Z0.7036735981047487",
  "alert": "Start of result\nResult\n\nAmalgamated loan fully repaid.\n\nThe amalgamated loan has been paid in full.\u000bThe private company is not taken under Division 7A to pay a dividend to the shareholder or shareholder's associate.\n\nInterest received by the private company must be included in the income tax return for 2004-05.\n\nMinimum yearly repayment\n\n$43.00\n\nBenchmark interest rate\n\n7.05%\n\nOpening balance:\n\nDate: 30/06/2004\n\nBalance: $111.94\n\nDays: 220\n\nInterest: $4.76\n\nPayments\n\nDate: 06/02/2005\n\nAmount: $1,119.46\n\nBalance: $0\n\nDays: 145\n\nInterest: $0\n\n\n\n\nTotal repayments\n\n$1,119.46\n\nTotal interest\n\n$4.76\n\nTotal principal\n\n$1,114.70\n\nClosing balance\n\nDate: 30/06/2005\n\nBalance: $0",
  "outputs": {
    "enquiryRateFormatted": "7.05%",
    "enquiryYearEndMinusOneDisplay": "30/06/2004",
    "amalgamatedLoanNotPaidByEOIYFormatted": "$111.94",
    "openingBalancePayDays": "220",
    "openingBalanceInterestFormatted": "$4.76",
    "totalAmountOfRepaymentFormatted": "$1,119.46",
    "totalInterestFormatted": "$4.76",
    "principalFormatted": "$1,114.70",
    "enquiryYearEndDisplay": "30/06/2005",
    "minimumYearRepaymentFormatted": "$43.00",
    "loanAmountFormatted": "$0"
  },
  "repayments": [
    {
      "rd": "6/2/2005",
      "ra": 1119.4610745797982
    }
  ],
  "inputs": {
    "incomeYearOfLoan": 2000,
    "fullTermOfAmalgamatedLoan": 7,
    "incomeYearOfEnquiring": 2005,
    "amalgamatedLoanNotPaidByEOIY": 111.94610745797982,
    "repayments": null,
    "lodgement_date": null
  },
  "idx": 6717
}