{
  "id": "2023-09-05T15:33:41.139Z0.04698028759413897",
  "alert": "Start of result\nResult\n\nMinimum yearly repayment met.\n\nThe amount of the loan not repaid at the end of income year 2021-22 is $3.28.\n\nThe amalgamated loan will not be taken to be a dividend because the total repayments made are equal to or greater than the minimum yearly repayment required for income year 2021-22.\n\nInterest received by the private company must be included in the income tax return for 2021-22.\n\nMinimum yearly repayment\n\n$25.00\n\nBenchmark interest rate\n\n4.52%\n\nOpening balance:\n\nDate: 30/06/2021\n\nBalance: $108.43\n\nDays: 244\n\nInterest: $3.28\n\nPayments\n\nDate: 02/03/2022\n\nAmount: $108.43\n\nBalance: $0\n\nDays: 121\n\nInterest: $0\n\n\n\n\nTotal repayments\n\n$108.43\n\nTotal interest\n\n$3.28\n\nTotal principal\n\n$105.15\n\nClosing balance\n\nDate: 30/06/2022\n\nBalance: $3.28",
  "outputs": {
    "enquiryRateFormatted": "4.52%",
    "enquiryYearEndMinusOneDisplay": "30/06/2021",
    "amalgamatedLoanNotPaidByEOIYFormatted": "$108.43",
    "openingBalancePayDays": "244",
    "openingBalanceInterestFormatted": "$3.28",
    "totalAmountOfRepaymentFormatted": "$108.43",
    "totalInterestFormatted": "$3.28",
    "principalFormatted": "$105.15",
    "enquiryYearEndDisplay": "30/06/2022",
    "minimumYearRepaymentFormatted": "$25.00"
  },
  "repayments": [
    {
      "rd": "2/3/2022",
      "ra": 108.43040128634169
    }
  ],
  "inputs": {
    "incomeYearOfLoan": 2020,
    "fullTermOfAmalgamatedLoan": 6,
    "incomeYearOfEnquiring": 2022,
    "amalgamatedLoanNotPaidByEOIY": 108.43040128634168,
    "repayments": null,
    "lodgement_date": null
  },
  "idx": 6624
}