{
  "id": "2023-10-31T18:26:33.542Z0.3206655440747752",
  "alert": "Start of result\nResult\n\nMinimum yearly repayment not met.\n\nThe amount of the loan not repaid at the end of income year 2009-10 is $32.02.\n\nThe private company may be taken to pay a dividend under Division 7A to the shareholder or shareholder's associate because the amount repaid during income year 2009-10 in relation to the amalgamated loan is less than the minimum yearly repayment required.\n\nInterest received by the private company must be included in the income tax return for 2009-10.\n\nMinimum yearly repayment\n\n$34.00\n\nBenchmark interest rate\n\n5.75%\n\nOpening balance:\n\nDate: 30/06/2009\n\nBalance: $32.02\n\nDays: 365\n\nInterest: $1.84\n\nTotal repayments\n\n$0\n\nTotal interest\n\n$1.84\n\nTotal principal\n\n$0\n\nClosing balance\n\nDate: 30/06/2010\n\nBalance: $32.02",
  "outputs": {
    "enquiryRateFormatted": "5.75%",
    "enquiryYearEndMinusOneDisplay": "30/06/2009",
    "amalgamatedLoanNotPaidByEOIYFormatted": "$32.02",
    "openingBalancePayDays": "365",
    "openingBalanceInterestFormatted": "$1.84",
    "totalAmountOfRepaymentFormatted": "$0",
    "totalInterestFormatted": "$1.84",
    "principalFormatted": "$0",
    "enquiryYearEndDisplay": "30/06/2010",
    "minimumYearRepaymentFormatted": "$34.00",
    "loanAmountFormatted": "$32.02"
  },
  "repayments": [],
  "inputs": {
    "incomeYearOfLoan": 2009,
    "fullTermOfAmalgamatedLoan": 1,
    "incomeYearOfEnquiring": 2010,
    "amalgamatedLoanNotPaidByEOIY": 32.02177115039515,
    "repayments": null,
    "lodgement_date": "27/5/2010"
  },
  "idx": 3981
}