{
  "id": "2023-09-05T15:33:36.373Z0.4337802154281134",
  "alert": "Start of result\nResult\n\nMinimum yearly repayment met.\n\nThe amount of the loan not repaid at the end of income year 2022-23 is $0.49.\n\nThe amalgamated loan will not be taken to be a dividend because the total repayments made are equal to or greater than the minimum yearly repayment required for income year 2022-23.\n\nInterest received by the private company must be included in the income tax return for 2022-23.\n\nMinimum yearly repayment\n\n$7.00\n\nBenchmark interest rate\n\n4.77%\n\nOpening balance:\n\nDate: 30/06/2022\n\nBalance: $25.86\n\nDays: 145\n\nInterest: $0.49\n\nPayments\n\nDate: 23/11/2022\n\nAmount: $25.86\n\nBalance: $0\n\nDays: 220\n\nInterest: $0\n\n\n\n\nTotal repayments\n\n$25.86\n\nTotal interest\n\n$0.49\n\nTotal principal\n\n$25.37\n\nClosing balance\n\nDate: 30/06/2023\n\nBalance: $0.49",
  "outputs": {
    "enquiryRateFormatted": "4.77%",
    "enquiryYearEndMinusOneDisplay": "30/06/2022",
    "amalgamatedLoanNotPaidByEOIYFormatted": "$25.86",
    "openingBalancePayDays": "145",
    "openingBalanceInterestFormatted": "$0.49",
    "totalAmountOfRepaymentFormatted": "$25.86",
    "totalInterestFormatted": "$0.49",
    "principalFormatted": "$25.37",
    "enquiryYearEndDisplay": "30/06/2023",
    "minimumYearRepaymentFormatted": "$7.00"
  },
  "repayments": [
    {
      "rd": "23/11/2022",
      "ra": 25.862580867438737
    }
  ],
  "inputs": {
    "incomeYearOfLoan": 2020,
    "fullTermOfAmalgamatedLoan": 6,
    "incomeYearOfEnquiring": 2023,
    "amalgamatedLoanNotPaidByEOIY": 25.86258086743869,
    "repayments": null,
    "lodgement_date": null
  },
  "idx": 6622
}