{
  "id": "2023-09-06T19:27:23.366Z0.29133268025329695",
  "alert": "Start of result\nResult\n\nMinimum yearly repayment met.\n\nThe amount of the loan not repaid at the end of income year 2004-05 is $2.80.\n\nThe amalgamated loan will not be taken to be a dividend because the total repayments made are equal to or greater than the minimum yearly repayment required for income year 2004-05.\n\nInterest received by the private company must be included in the income tax return for 2004-05.\n\nMinimum yearly repayment\n\n$45.00\n\nBenchmark interest rate\n\n7.05%\n\nOpening balance:\n\nDate: 30/06/2004\n\nBalance: $117.79\n\nDays: 123\n\nInterest: $2.80\n\nPayments\n\nDate: 01/11/2004\n\nAmount: $117.79\n\nBalance: $0\n\nDays: 242\n\nInterest: $0\n\n\n\n\nTotal repayments\n\n$117.79\n\nTotal interest\n\n$2.80\n\nTotal principal\n\n$114.99\n\nClosing balance\n\nDate: 30/06/2005\n\nBalance: $2.80",
  "outputs": {
    "enquiryRateFormatted": "7.05%",
    "enquiryYearEndMinusOneDisplay": "30/06/2004",
    "amalgamatedLoanNotPaidByEOIYFormatted": "$117.79",
    "openingBalancePayDays": "123",
    "openingBalanceInterestFormatted": "$2.80",
    "totalAmountOfRepaymentFormatted": "$117.79",
    "totalInterestFormatted": "$2.80",
    "principalFormatted": "$114.99",
    "enquiryYearEndDisplay": "30/06/2005",
    "minimumYearRepaymentFormatted": "$45.00"
  },
  "repayments": [
    {
      "rd": "1/11/2004",
      "ra": 117.79968705117335
    }
  ],
  "inputs": {
    "incomeYearOfLoan": 2003,
    "fullTermOfAmalgamatedLoan": 4,
    "incomeYearOfEnquiring": 2005,
    "amalgamatedLoanNotPaidByEOIY": 117.7996870511735,
    "repayments": null,
    "lodgement_date": null
  },
  "idx": 5909
}