{
  "id": "2023-10-31T19:08:03.214Z0.8837193675699911",
  "alert": "Start of result\nResult\n\nAmalgamated loan fully repaid.\n\nThe amalgamated loan has been paid in full.\u000bThe private company is not taken under Division 7A to pay a dividend to the shareholder or shareholder's associate.\n\nInterest received by the private company must be included in the income tax return for 2006-07.\n\nMinimum yearly repayment\n\n$16.00\n\nBenchmark interest rate\n\n7.55%\n\nOpening balance:\n\nDate: 30/06/2006\n\nBalance: $76.25\n\nDays: 63\n\nInterest: $0.99\n\nPayments\n\nDate: 02/09/2006\n\nAmount: $762.53\n\nBalance: $0\n\nDays: 302\n\nInterest: $0\n\n\n\n\nTotal repayments\n\n$762.53\n\nTotal interest\n\n$0.99\n\nTotal principal\n\n$761.54\n\nClosing balance\n\nDate: 30/06/2007\n\nBalance: $0",
  "outputs": {
    "enquiryRateFormatted": "7.55%",
    "enquiryYearEndMinusOneDisplay": "30/06/2006",
    "amalgamatedLoanNotPaidByEOIYFormatted": "$76.25",
    "openingBalancePayDays": "63",
    "openingBalanceInterestFormatted": "$0.99",
    "totalAmountOfRepaymentFormatted": "$762.53",
    "totalInterestFormatted": "$0.99",
    "principalFormatted": "$761.54",
    "enquiryYearEndDisplay": "30/06/2007",
    "minimumYearRepaymentFormatted": "$16.00",
    "loanAmountFormatted": "$0"
  },
  "repayments": [
    {
      "rd": "2/9/2006",
      "ra": 762.5345969315949
    }
  ],
  "inputs": {
    "incomeYearOfLoan": 2006,
    "fullTermOfAmalgamatedLoan": 6,
    "incomeYearOfEnquiring": 2007,
    "amalgamatedLoanNotPaidByEOIY": 76.25345969315954,
    "repayments": null,
    "lodgement_date": "1/7/2006"
  },
  "idx": 5059
}