{
  "id": "2023-09-06T16:55:18.250Z0.39688580358252024",
  "alert": "Start of result\nResult\n\nMinimum yearly repayment met.\n\nThe amount of the loan not repaid at the end of income year 2010-11 is $24.59.\n\nThe amalgamated loan will not be taken to be a dividend because the total repayments made are equal to or greater than the minimum yearly repayment required for income year 2010-11.\n\nInterest received by the private company must be included in the income tax return for 2010-11.\n\nMinimum yearly repayment\n\n$1,645.00\n\nBenchmark interest rate\n\n7.4%\n\nOpening balance:\n\nDate: 30/06/2010\n\nBalance: $2,958.00\n\nDays: 41\n\nInterest: $24.59\n\nPayments\n\nDate: 11/08/2010\n\nAmount: $2,958.00\n\nBalance: $0\n\nDays: 324\n\nInterest: $0\n\n\n\n\nTotal repayments\n\n$2,958.00\n\nTotal interest\n\n$24.59\n\nTotal principal\n\n$2,933.41\n\nClosing balance\n\nDate: 30/06/2011\n\nBalance: $24.59",
  "outputs": {
    "enquiryRateFormatted": "7.4%",
    "enquiryYearEndMinusOneDisplay": "30/06/2010",
    "amalgamatedLoanNotPaidByEOIYFormatted": "$2,958.00",
    "openingBalancePayDays": "41",
    "openingBalanceInterestFormatted": "$24.59",
    "totalAmountOfRepaymentFormatted": "$2,958.00",
    "totalInterestFormatted": "$24.59",
    "principalFormatted": "$2,933.41",
    "enquiryYearEndDisplay": "30/06/2011",
    "minimumYearRepaymentFormatted": "$1,645.00"
  },
  "repayments": [
    {
      "rd": "11/8/2010",
      "ra": 2958
    }
  ],
  "inputs": {
    "incomeYearOfLoan": 2005,
    "fullTermOfAmalgamatedLoan": 7,
    "incomeYearOfEnquiring": 2011,
    "amalgamatedLoanNotPaidByEOIY": 2958,
    "repayments": null,
    "lodgement_date": null
  },
  "idx": 5530
}