{
  "id": "2023-10-31T20:56:33.842Z0.23345535214928093",
  "alert": "Start of result\nResult\n\nMinimum yearly repayment not met.\n\nThe amount of the loan not repaid at the end of income year 2000-01 is $4,270.00.\n\nThe private company may be taken to pay a dividend under Division 7A to the shareholder or shareholder's associate because the amount repaid during income year 2000-01 in relation to the amalgamated loan is less than the minimum yearly repayment required.\n\nInterest received by the private company must be included in the income tax return for 2000-01.\n\nMinimum yearly repayment\n\n$1,651.00\n\nBenchmark interest rate\n\n7.8%\n\nOpening balance:\n\nDate: 30/06/2000\n\nBalance: $4,270.00\n\nDays: 365\n\nInterest: $333.06\n\nTotal repayments\n\n$0\n\nTotal interest\n\n$333.06\n\nTotal principal\n\n$0\n\nClosing balance\n\nDate: 30/06/2001\n\nBalance: $4,270.00",
  "outputs": {
    "enquiryRateFormatted": "7.8%",
    "enquiryYearEndMinusOneDisplay": "30/06/2000",
    "amalgamatedLoanNotPaidByEOIYFormatted": "$4,270.00",
    "openingBalancePayDays": "365",
    "openingBalanceInterestFormatted": "$333.06",
    "totalAmountOfRepaymentFormatted": "$0",
    "totalInterestFormatted": "$333.06",
    "principalFormatted": "$0",
    "enquiryYearEndDisplay": "30/06/2001",
    "minimumYearRepaymentFormatted": "$1,651.00",
    "loanAmountFormatted": "$4,270.00"
  },
  "repayments": [],
  "inputs": {
    "incomeYearOfLoan": 1999,
    "fullTermOfAmalgamatedLoan": 4,
    "incomeYearOfEnquiring": 2001,
    "amalgamatedLoanNotPaidByEOIY": 4270,
    "repayments": null,
    "lodgement_date": null
  },
  "idx": 6884
}