{
  "id": "2023-09-04T20:47:42.525Z0.4728594577950149",
  "alert": "Start of result\nResult\n\nMinimum yearly repayment not met.\n\nThe amount of the loan not repaid at the end of income year 2018-19 is $99,638,217.19.\n\nThe private company may be taken to pay a dividend under Division 7A to the shareholder or shareholder's associate because the amount repaid during income year 2018-19 in relation to the amalgamated loan is less than the minimum yearly repayment required.\n\nInterest received by the private company must be included in the income tax return for 2018-19.\n\nMinimum yearly repayment\n\n$104,819,404.00\n\nBenchmark interest rate\n\n5.2%\n\nOpening balance:\n\nDate: 30/06/2018\n\nBalance: $99,638,217.19\n\nDays: 365\n\nInterest: $5,181,187.29\n\nTotal repayments\n\n$0\n\nTotal interest\n\n$5,181,187.29\n\nTotal principal\n\n$0\n\nClosing balance\n\nDate: 30/06/2019\n\nBalance: $99,638,217.19",
  "outputs": {
    "enquiryRateFormatted": "5.2%",
    "enquiryYearEndMinusOneDisplay": "30/06/2018",
    "amalgamatedLoanNotPaidByEOIYFormatted": "$99,638,217.19",
    "openingBalancePayDays": "365",
    "openingBalanceInterestFormatted": "$5,181,187.29",
    "totalAmountOfRepaymentFormatted": "$0",
    "totalInterestFormatted": "$5,181,187.29",
    "principalFormatted": "$0",
    "enquiryYearEndDisplay": "30/06/2019",
    "minimumYearRepaymentFormatted": "$104,819,404.00"
  },
  "repayments": [],
  "inputs": {
    "incomeYearOfLoan": 2012,
    "fullTermOfAmalgamatedLoan": 7,
    "incomeYearOfEnquiring": 2019,
    "amalgamatedLoanNotPaidByEOIY": 99638217.19692077,
    "repayments": null,
    "lodgement_date": null
  },
  "idx": 16
}