{
  "id": "2023-09-07T04:10:22.358Z0.26275684365284757",
  "alert": "Start of result\nResult\n\nMinimum yearly repayment not met.\n\nThe amount of the loan not repaid at the end of income year 1999-00 is $11,776.47.\n\nThe private company may be taken to pay a dividend under Division 7A to the shareholder or shareholder's associate because the amount repaid during income year 1999-00 in relation to the amalgamated loan is less than the minimum yearly repayment required.\n\nInterest received by the private company must be included in the income tax return for 1999-00.\n\nMinimum yearly repayment\n\n$2,496.00\n\nBenchmark interest rate\n\n6.5%\n\nOpening balance:\n\nDate: 30/06/1999\n\nBalance: $12,085.00\n\nDays: 39\n\nInterest: $83.70\n\nPayments\n\nDate: 09/08/1999\n\nAmount: $1,034.00\n\nBalance: $11,051.00\n\nDays: 327\n\nInterest: $641.77\n\n\n\n\nTotal repayments\n\n$1,034.00\n\nTotal interest\n\n$725.47\n\nTotal principal\n\n$308.53\n\nClosing balance\n\nDate: 30/06/2000\n\nBalance: $11,776.47",
  "outputs": {
    "enquiryRateFormatted": "6.5%",
    "enquiryYearEndMinusOneDisplay": "30/06/1999",
    "amalgamatedLoanNotPaidByEOIYFormatted": "$12,085.00",
    "openingBalancePayDays": "39",
    "openingBalanceInterestFormatted": "$83.70",
    "totalAmountOfRepaymentFormatted": "$1,034.00",
    "totalInterestFormatted": "$725.47",
    "principalFormatted": "$308.53",
    "enquiryYearEndDisplay": "30/06/2000",
    "minimumYearRepaymentFormatted": "$2,496.00"
  },
  "repayments": [
    {
      "rd": "9/8/1999",
      "ra": 1034
    }
  ],
  "inputs": {
    "incomeYearOfLoan": 1998,
    "fullTermOfAmalgamatedLoan": 7,
    "incomeYearOfEnquiring": 2000,
    "amalgamatedLoanNotPaidByEOIY": 12085,
    "repayments": null,
    "lodgement_date": null
  },
  "idx": 2963
}