{
  "id": "2023-10-31T17:12:23.021Z0.6516347890267773",
  "alert": "Start of result\nResult\n\nMinimum yearly repayment not met.\n\nThe amount of the loan not repaid at the end of income year 2021-22 is $11,684.00.\n\nThe private company may be taken to pay a dividend under Division 7A to the shareholder or shareholder's associate because the amount repaid during income year 2021-22 in relation to the amalgamated loan is less than the minimum yearly repayment required.\n\nInterest received by the private company must be included in the income tax return for 2021-22.\n\nMinimum yearly repayment\n\n$3,258.00\n\nBenchmark interest rate\n\n4.52%\n\nOpening balance:\n\nDate: 30/06/2021\n\nBalance: $11,684.00\n\nDays: 365\n\nInterest: $528.12\n\nTotal repayments\n\n$0\n\nTotal interest\n\n$528.12\n\nTotal principal\n\n$0\n\nClosing balance\n\nDate: 30/06/2022\n\nBalance: $11,684.00",
  "outputs": {
    "enquiryRateFormatted": "4.52%",
    "enquiryYearEndMinusOneDisplay": "30/06/2021",
    "amalgamatedLoanNotPaidByEOIYFormatted": "$11,684.00",
    "openingBalancePayDays": "365",
    "openingBalanceInterestFormatted": "$528.12",
    "totalAmountOfRepaymentFormatted": "$0",
    "totalInterestFormatted": "$528.12",
    "principalFormatted": "$0",
    "enquiryYearEndDisplay": "30/06/2022",
    "minimumYearRepaymentFormatted": "$3,258.00",
    "loanAmountFormatted": "$11,684.00"
  },
  "repayments": [],
  "inputs": {
    "incomeYearOfLoan": 2021,
    "fullTermOfAmalgamatedLoan": 4,
    "incomeYearOfEnquiring": 2022,
    "amalgamatedLoanNotPaidByEOIY": 11684,
    "repayments": null,
    "lodgement_date": "28/11/2021"
  },
  "idx": 509
}