{
  "id": "2023-10-31T17:39:36.929Z0.9587139001482093",
  "alert": "Start of result\nResult\n\nAmalgamated loan fully repaid.\n\nThe amalgamated loan has been paid in full.\u000bThe private company is not taken under Division 7A to pay a dividend to the shareholder or shareholder's associate.\n\nInterest received by the private company must be included in the income tax return for 2015-16.\n\nMinimum yearly repayment\n\n$5,019.00\n\nBenchmark interest rate\n\n5.45%\n\nOpening balance:\n\nDate: 30/06/2015\n\nBalance: $9,274.00\n\nDays: 200\n\nInterest: $276.19\n\nPayments\n\nDate: 17/01/2016\n\nAmount: $7,510.00\n\nBalance: $1,764.00\n\nDays: 31\n\nInterest: $8.14\n\n\n\n\nDate: 17/02/2016\n\nAmount: $5,683.00\n\nBalance: $0\n\nDays: 135\n\nInterest: $0\n\n\n\n\nTotal repayments\n\n$13,193.00\n\nTotal interest\n\n$284.33\n\nTotal principal\n\n$12,908.67\n\nClosing balance\n\nDate: 30/06/2016\n\nBalance: $0",
  "outputs": {
    "enquiryRateFormatted": "5.45%",
    "enquiryYearEndMinusOneDisplay": "30/06/2015",
    "amalgamatedLoanNotPaidByEOIYFormatted": "$9,274.00",
    "openingBalancePayDays": "200",
    "openingBalanceInterestFormatted": "$276.19",
    "totalAmountOfRepaymentFormatted": "$13,193.00",
    "totalInterestFormatted": "$284.33",
    "principalFormatted": "$12,908.67",
    "enquiryYearEndDisplay": "30/06/2016",
    "minimumYearRepaymentFormatted": "$5,019.00",
    "loanAmountFormatted": "$0"
  },
  "repayments": [
    {
      "rd": "17/1/2016",
      "ra": 7510
    },
    {
      "rd": "17/2/2016",
      "ra": 5683
    }
  ],
  "inputs": {
    "incomeYearOfLoan": 2015,
    "fullTermOfAmalgamatedLoan": 2,
    "incomeYearOfEnquiring": 2016,
    "amalgamatedLoanNotPaidByEOIY": 9274,
    "repayments": null,
    "lodgement_date": "28/12/2015"
  },
  "idx": 2212
}