{
  "id": "2023-09-05T18:59:08.951Z0.6672679199497462",
  "alert": "Start of result\nResult\n\nMinimum yearly repayment met.\n\nThe amount of the loan not repaid at the end of income year 2022-23 is $0.04.\n\nThe amalgamated loan will not be taken to be a dividend because the total repayments made are equal to or greater than the minimum yearly repayment required for income year 2022-23.\n\nInterest received by the private company must be included in the income tax return for 2022-23.\n\nMinimum yearly repayment\n\n$1.00\n\nBenchmark interest rate\n\n4.77%\n\nOpening balance:\n\nDate: 30/06/2022\n\nBalance: $2.50\n\nDays: 110\n\nInterest: $0.04\n\nPayments\n\nDate: 19/10/2022\n\nAmount: $2.50\n\nBalance: $0\n\nDays: 255\n\nInterest: $0\n\n\n\n\nTotal repayments\n\n$2.50\n\nTotal interest\n\n$0.04\n\nTotal principal\n\n$2.46\n\nClosing balance\n\nDate: 30/06/2023\n\nBalance: $0.04",
  "outputs": {
    "enquiryRateFormatted": "4.77%",
    "enquiryYearEndMinusOneDisplay": "30/06/2022",
    "amalgamatedLoanNotPaidByEOIYFormatted": "$2.50",
    "openingBalancePayDays": "110",
    "openingBalanceInterestFormatted": "$0.04",
    "totalAmountOfRepaymentFormatted": "$2.50",
    "totalInterestFormatted": "$0.04",
    "principalFormatted": "$2.46",
    "enquiryYearEndDisplay": "30/06/2023",
    "minimumYearRepaymentFormatted": "$1.00"
  },
  "repayments": [
    {
      "rd": "19/10/2022",
      "ra": 2.5030163768242346
    }
  ],
  "inputs": {
    "incomeYearOfLoan": 2018,
    "fullTermOfAmalgamatedLoan": 7,
    "incomeYearOfEnquiring": 2023,
    "amalgamatedLoanNotPaidByEOIY": 2.503016376823834,
    "repayments": null,
    "lodgement_date": null
  },
  "idx": 735
}