{
  "id": "2023-09-05T13:26:29.394Z0.8516627504496068",
  "alert": "Start of result\nResult\n\nMinimum yearly repayment met.\n\nThe amount of the loan not repaid at the end of income year 2021-22 is $8,075.16.\n\nThe amalgamated loan will not be taken to be a dividend because the total repayments made are equal to or greater than the minimum yearly repayment required for income year 2021-22.\n\nInterest received by the private company must be included in the income tax return for 2021-22.\n\nMinimum yearly repayment\n\n$2,144.00\n\nBenchmark interest rate\n\n4.52%\n\nOpening balance:\n\nDate: 30/06/2021\n\nBalance: $11,060.00\n\nDays: 95\n\nInterest: $130.11\n\nPayments\n\nDate: 04/10/2021\n\nAmount: $3,372.00\n\nBalance: $7,688.00\n\nDays: 270\n\nInterest: $257.05\n\n\n\n\nTotal repayments\n\n$3,372.00\n\nTotal interest\n\n$387.16\n\nTotal principal\n\n$2,984.84\n\nClosing balance\n\nDate: 30/06/2022\n\nBalance: $8,075.16",
  "outputs": {
    "enquiryRateFormatted": "4.52%",
    "enquiryYearEndMinusOneDisplay": "30/06/2021",
    "amalgamatedLoanNotPaidByEOIYFormatted": "$11,060.00",
    "openingBalancePayDays": "95",
    "openingBalanceInterestFormatted": "$130.11",
    "totalAmountOfRepaymentFormatted": "$3,372.00",
    "totalInterestFormatted": "$387.16",
    "principalFormatted": "$2,984.84",
    "enquiryYearEndDisplay": "30/06/2022",
    "minimumYearRepaymentFormatted": "$2,144.00"
  },
  "repayments": [
    {
      "rd": "4/10/2021",
      "ra": 3372
    }
  ],
  "inputs": {
    "incomeYearOfLoan": 2021,
    "fullTermOfAmalgamatedLoan": 4,
    "incomeYearOfEnquiring": 2022,
    "amalgamatedLoanNotPaidByEOIY": 11060,
    "repayments": null,
    "lodgement_date": "29/11/2021"
  },
  "idx": 7860
}