{
  "id": "2023-10-31T17:41:02.117Z0.057425134085227314",
  "alert": "Start of result\nResult\n\nAmalgamated loan fully repaid.\n\nThe amalgamated loan has been paid in full.\u000bThe private company is not taken under Division 7A to pay a dividend to the shareholder or shareholder's associate.\n\nInterest received by the private company must be included in the income tax return for 2015-16.\n\nMinimum yearly repayment\n\n-$48.00\n\nBenchmark interest rate\n\n5.45%\n\nOpening balance:\n\nDate: 30/06/2015\n\nBalance: $18.91\n\nDays: 81\n\nInterest: $0.23\n\nPayments\n\nDate: 20/09/2015\n\nAmount: $189.10\n\nBalance: $0\n\nDays: 285\n\nInterest: $0\n\n\n\n\nTotal repayments\n\n$189.10\n\nTotal interest\n\n$0.23\n\nTotal principal\n\n$188.87\n\nClosing balance\n\nDate: 30/06/2016\n\nBalance: $0",
  "outputs": {
    "enquiryRateFormatted": "5.45%",
    "enquiryYearEndMinusOneDisplay": "30/06/2015",
    "amalgamatedLoanNotPaidByEOIYFormatted": "$18.91",
    "openingBalancePayDays": "81",
    "openingBalanceInterestFormatted": "$0.23",
    "totalAmountOfRepaymentFormatted": "$189.10",
    "totalInterestFormatted": "$0.23",
    "principalFormatted": "$188.87",
    "enquiryYearEndDisplay": "30/06/2016",
    "minimumYearRepaymentFormatted": "-$48.00",
    "loanAmountFormatted": "$0"
  },
  "repayments": [
    {
      "rd": "20/9/2015",
      "ra": 189.10839609573577
    }
  ],
  "inputs": {
    "incomeYearOfLoan": 2015,
    "fullTermOfAmalgamatedLoan": 4,
    "incomeYearOfEnquiring": 2016,
    "amalgamatedLoanNotPaidByEOIY": 18.910839609573546,
    "repayments": null,
    "lodgement_date": "27/1/2016"
  },
  "idx": 2280
}