{
  "id": "2023-09-04T21:13:59.694Z0.09043907589013012",
  "alert": "Start of result\nResult\n\nMinimum yearly repayment not met.\n\nThe amount of the loan not repaid at the end of income year 2008-09 is $114,937,265.44.\n\nThe private company may be taken to pay a dividend under Division 7A to the shareholder or shareholder's associate because the amount repaid during income year 2008-09 in relation to the amalgamated loan is less than the minimum yearly repayment required.\n\nInterest received by the private company must be included in the income tax return for 2008-09.\n\nMinimum yearly repayment\n\n$25,965,806.00\n\nBenchmark interest rate\n\n9.45%\n\nOpening balance:\n\nDate: 30/06/2008\n\nBalance: $114,937,265.44\n\nDays: 0\n\nInterest: $0\n\nPayments\n\nDate: 01/07/2008\n\nAmount: $3,128.00\n\nBalance: $114,934,137.44\n\nDays: 365\n\nInterest: $10,861,275.99\n\n\n\n\nTotal repayments\n\n$3,128.00\n\nTotal interest\n\n$10,861,275.99\n\nTotal principal\n\n$0\n\nClosing balance\n\nDate: 30/06/2009\n\nBalance: $114,937,265.44",
  "outputs": {
    "enquiryRateFormatted": "9.45%",
    "enquiryYearEndMinusOneDisplay": "30/06/2008",
    "amalgamatedLoanNotPaidByEOIYFormatted": "$114,937,265.44",
    "openingBalancePayDays": "0",
    "openingBalanceInterestFormatted": "$0",
    "totalAmountOfRepaymentFormatted": "$3,128.00",
    "totalInterestFormatted": "$10,861,275.99",
    "principalFormatted": "$0",
    "enquiryYearEndDisplay": "30/06/2009",
    "minimumYearRepaymentFormatted": "$25,965,806.00"
  },
  "repayments": [
    {
      "rd": "1/7/2008",
      "ra": 3128
    }
  ],
  "inputs": {
    "incomeYearOfLoan": 2008,
    "fullTermOfAmalgamatedLoan": 6,
    "incomeYearOfEnquiring": 2009,
    "amalgamatedLoanNotPaidByEOIY": 114937265.4409543,
    "repayments": null,
    "lodgement_date": "17/1/2009"
  },
  "idx": 886
}