{
  "id": "2023-10-31T18:10:15.621Z0.2747567469750072",
  "alert": "Start of result\nResult\n\nMinimum yearly repayment not met.\n\nThe amount of the loan not repaid at the end of income year 2014-15 is $18.97.\n\nThe private company may be taken to pay a dividend under Division 7A to the shareholder or shareholder's associate because the amount repaid during income year 2014-15 in relation to the amalgamated loan is less than the minimum yearly repayment required.\n\nInterest received by the private company must be included in the income tax return for 2014-15.\n\nMinimum yearly repayment\n\n$20.00\n\nBenchmark interest rate\n\n5.95%\n\nOpening balance:\n\nDate: 30/06/2014\n\nBalance: $18.97\n\nDays: 365\n\nInterest: $1.13\n\nTotal repayments\n\n$0\n\nTotal interest\n\n$1.13\n\nTotal principal\n\n$0\n\nClosing balance\n\nDate: 30/06/2015\n\nBalance: $18.97",
  "outputs": {
    "enquiryRateFormatted": "5.95%",
    "enquiryYearEndMinusOneDisplay": "30/06/2014",
    "amalgamatedLoanNotPaidByEOIYFormatted": "$18.97",
    "openingBalancePayDays": "365",
    "openingBalanceInterestFormatted": "$1.13",
    "totalAmountOfRepaymentFormatted": "$0",
    "totalInterestFormatted": "$1.13",
    "principalFormatted": "$0",
    "enquiryYearEndDisplay": "30/06/2015",
    "minimumYearRepaymentFormatted": "$20.00",
    "loanAmountFormatted": "$18.97"
  },
  "repayments": [],
  "inputs": {
    "incomeYearOfLoan": 2011,
    "fullTermOfAmalgamatedLoan": 4,
    "incomeYearOfEnquiring": 2015,
    "amalgamatedLoanNotPaidByEOIY": 18.97365343001128,
    "repayments": null,
    "lodgement_date": null
  },
  "idx": 3462
}