{
  "id": "2023-10-31T17:26:27.206Z0.5580714806659179",
  "alert": "Start of result\nResult\n\nAmalgamated loan fully repaid.\n\nThe amalgamated loan has been paid in full.\u000bThe private company is not taken under Division 7A to pay a dividend to the shareholder or shareholder's associate.\n\nInterest received by the private company must be included in the income tax return for 2018-19.\n\nMinimum yearly repayment\n\n-$100.00\n\nBenchmark interest rate\n\n5.2%\n\nOpening balance:\n\nDate: 30/06/2018\n\nBalance: $63.99\n\nDays: 69\n\nInterest: $0.63\n\nPayments\n\nDate: 08/09/2018\n\nAmount: $639.93\n\nBalance: $0\n\nDays: 296\n\nInterest: $0\n\n\n\n\nTotal repayments\n\n$639.93\n\nTotal interest\n\n$0.63\n\nTotal principal\n\n$639.30\n\nClosing balance\n\nDate: 30/06/2019\n\nBalance: $0",
  "outputs": {
    "enquiryRateFormatted": "5.2%",
    "enquiryYearEndMinusOneDisplay": "30/06/2018",
    "amalgamatedLoanNotPaidByEOIYFormatted": "$63.99",
    "openingBalancePayDays": "69",
    "openingBalanceInterestFormatted": "$0.63",
    "totalAmountOfRepaymentFormatted": "$639.93",
    "totalInterestFormatted": "$0.63",
    "principalFormatted": "$639.30",
    "enquiryYearEndDisplay": "30/06/2019",
    "minimumYearRepaymentFormatted": "-$100.00",
    "loanAmountFormatted": "$0"
  },
  "repayments": [
    {
      "rd": "8/9/2018",
      "ra": 639.936464944225
    }
  ],
  "inputs": {
    "incomeYearOfLoan": 2018,
    "fullTermOfAmalgamatedLoan": 7,
    "incomeYearOfEnquiring": 2019,
    "amalgamatedLoanNotPaidByEOIY": 63.99364649442259,
    "repayments": null,
    "lodgement_date": "29/10/2018"
  },
  "idx": 1493
}