{
  "id": "2023-09-06T02:27:39.414Z0.6273229823555835",
  "alert": "Start of result\nResult\n\nMinimum yearly repayment not met.\n\nThe amount of the loan not repaid at the end of income year 2013-14 is $60.11.\n\nThe private company may be taken to pay a dividend under Division 7A to the shareholder or shareholder's associate because the amount repaid during income year 2013-14 in relation to the amalgamated loan is less than the minimum yearly repayment required.\n\nInterest received by the private company must be included in the income tax return for 2013-14.\n\nMinimum yearly repayment\n\n$64.00\n\nBenchmark interest rate\n\n6.2%\n\nOpening balance:\n\nDate: 30/06/2013\n\nBalance: $60.11\n\nDays: 365\n\nInterest: $3.73\n\nTotal repayments\n\n$0\n\nTotal interest\n\n$3.73\n\nTotal principal\n\n$0\n\nClosing balance\n\nDate: 30/06/2014\n\nBalance: $60.11",
  "outputs": {
    "enquiryRateFormatted": "6.2%",
    "enquiryYearEndMinusOneDisplay": "30/06/2013",
    "amalgamatedLoanNotPaidByEOIYFormatted": "$60.11",
    "openingBalancePayDays": "365",
    "openingBalanceInterestFormatted": "$3.73",
    "totalAmountOfRepaymentFormatted": "$0",
    "totalInterestFormatted": "$3.73",
    "principalFormatted": "$0",
    "enquiryYearEndDisplay": "30/06/2014",
    "minimumYearRepaymentFormatted": "$64.00"
  },
  "repayments": [],
  "inputs": {
    "incomeYearOfLoan": 2013,
    "fullTermOfAmalgamatedLoan": 1,
    "incomeYearOfEnquiring": 2014,
    "amalgamatedLoanNotPaidByEOIY": 60.11548864670307,
    "repayments": null,
    "lodgement_date": "5/2/2014"
  },
  "idx": 219
}