{
  "id": "2023-09-06T00:32:41.556Z0.8000799852449332",
  "alert": "Start of result\nResult\n\nMinimum yearly repayment not met.\n\nThe amount of the loan not repaid at the end of income year 2014-15 is $0.60.\n\nThe private company may be taken to pay a dividend under Division 7A to the shareholder or shareholder's associate because the amount repaid during income year 2014-15 in relation to the amalgamated loan is less than the minimum yearly repayment required.\n\nInterest received by the private company must be included in the income tax return for 2014-15.\n\nMinimum yearly repayment\n\n$39.00\n\nBenchmark interest rate\n\n5.95%\n\nOpening balance:\n\nDate: 30/06/2014\n\nBalance: $37.08\n\nDays: 100\n\nInterest: $0.60\n\nPayments\n\nDate: 09/10/2014\n\nAmount: $37.08\n\nBalance: $0\n\nDays: 265\n\nInterest: $0\n\n\n\n\nTotal repayments\n\n$37.08\n\nTotal interest\n\n$0.60\n\nTotal principal\n\n$36.48\n\nClosing balance\n\nDate: 30/06/2015\n\nBalance: $0.60",
  "outputs": {
    "enquiryRateFormatted": "5.95%",
    "enquiryYearEndMinusOneDisplay": "30/06/2014",
    "amalgamatedLoanNotPaidByEOIYFormatted": "$37.08",
    "openingBalancePayDays": "100",
    "openingBalanceInterestFormatted": "$0.60",
    "totalAmountOfRepaymentFormatted": "$37.08",
    "totalInterestFormatted": "$0.60",
    "principalFormatted": "$36.48",
    "enquiryYearEndDisplay": "30/06/2015",
    "minimumYearRepaymentFormatted": "$39.00"
  },
  "repayments": [
    {
      "rd": "9/10/2014",
      "ra": 37.089199286101575
    }
  ],
  "inputs": {
    "incomeYearOfLoan": 2014,
    "fullTermOfAmalgamatedLoan": 1,
    "incomeYearOfEnquiring": 2015,
    "amalgamatedLoanNotPaidByEOIY": 37.089199286102044,
    "repayments": null,
    "lodgement_date": "10/9/2014"
  },
  "idx": 3405
}