{
  "id": "2023-09-04T16:19:28.161Z0.6323360176097472",
  "alert": "Start of result\nResult\n\nMinimum yearly repayment met.\n\nThe amount of the loan not repaid at the end of income year 2020-21 is $652.20.\n\nThe amalgamated loan will not be taken to be a dividend because the total repayments made are equal to or greater than the minimum yearly repayment required for income year 2020-21.\n\nInterest received by the private company must be included in the income tax return for 2020-21.\n\nMinimum yearly repayment\n\n$174.00\n\nBenchmark interest rate\n\n4.52%\n\nOpening balance:\n\nDate: 30/06/2020\n\nBalance: $5,397.00\n\nDays: 0\n\nInterest: $0\n\nPayments\n\nDate: 01/07/2020\n\nAmount: $4,773.00\n\nBalance: $624.00\n\nDays: 365\n\nInterest: $28.20\n\n\n\n\nTotal repayments\n\n$4,773.00\n\nTotal interest\n\n$28.20\n\nTotal principal\n\n$4,744.80\n\nClosing balance\n\nDate: 30/06/2021\n\nBalance: $652.20",
  "outputs": {
    "enquiryRateFormatted": "4.52%",
    "enquiryYearEndMinusOneDisplay": "30/06/2020",
    "amalgamatedLoanNotPaidByEOIYFormatted": "$5,397.00",
    "openingBalancePayDays": "0",
    "openingBalanceInterestFormatted": "$0",
    "totalAmountOfRepaymentFormatted": "$4,773.00",
    "totalInterestFormatted": "$28.20",
    "principalFormatted": "$4,744.80",
    "enquiryYearEndDisplay": "30/06/2021",
    "minimumYearRepaymentFormatted": "$174.00"
  },
  "repayments": [
    {
      "rd": "1/7/2020",
      "ra": 4773
    }
  ],
  "inputs": {
    "incomeYearOfLoan": 2020,
    "fullTermOfAmalgamatedLoan": 4,
    "incomeYearOfEnquiring": 2021,
    "amalgamatedLoanNotPaidByEOIY": 5397,
    "repayments": null,
    "lodgement_date": "17/1/2021"
  },
  "idx": 269
}