{
  "id": "2023-10-31T18:10:27.622Z0.6372833335420087",
  "alert": "Start of result\nResult\n\nAmalgamated loan fully repaid.\n\nThe amalgamated loan has been paid in full.\u000bThe private company is not taken under Division 7A to pay a dividend to the shareholder or shareholder's associate.\n\nInterest received by the private company must be included in the income tax return for 2012-13.\n\nMinimum yearly repayment\n\n$28.00\n\nBenchmark interest rate\n\n7.05%\n\nOpening balance:\n\nDate: 30/06/2012\n\nBalance: $72.52\n\nDays: 107\n\nInterest: $1.50\n\nPayments\n\nDate: 16/10/2012\n\nAmount: $725.20\n\nBalance: $0\n\nDays: 258\n\nInterest: $0\n\n\n\n\nTotal repayments\n\n$725.20\n\nTotal interest\n\n$1.50\n\nTotal principal\n\n$723.70\n\nClosing balance\n\nDate: 30/06/2013\n\nBalance: $0",
  "outputs": {
    "enquiryRateFormatted": "7.05%",
    "enquiryYearEndMinusOneDisplay": "30/06/2012",
    "amalgamatedLoanNotPaidByEOIYFormatted": "$72.52",
    "openingBalancePayDays": "107",
    "openingBalanceInterestFormatted": "$1.50",
    "totalAmountOfRepaymentFormatted": "$725.20",
    "totalInterestFormatted": "$1.50",
    "principalFormatted": "$723.70",
    "enquiryYearEndDisplay": "30/06/2013",
    "minimumYearRepaymentFormatted": "$28.00",
    "loanAmountFormatted": "$0"
  },
  "repayments": [
    {
      "rd": "16/10/2012",
      "ra": 725.2045997217141
    }
  ],
  "inputs": {
    "incomeYearOfLoan": 2011,
    "fullTermOfAmalgamatedLoan": 4,
    "incomeYearOfEnquiring": 2013,
    "amalgamatedLoanNotPaidByEOIY": 72.52045997217141,
    "repayments": null,
    "lodgement_date": null
  },
  "idx": 3468
}