{
  "id": "2023-09-07T04:10:15.590Z0.061943653103814444",
  "alert": "Start of result\nResult\n\nMinimum yearly repayment met.\n\nThe amount of the loan not repaid at the end of income year 2001-02 is $0.47.\n\nThe amalgamated loan will not be taken to be a dividend because the total repayments made are equal to or greater than the minimum yearly repayment required for income year 2001-02.\n\nInterest received by the private company must be included in the income tax return for 2001-02.\n\nMinimum yearly repayment\n\n$4.00\n\nBenchmark interest rate\n\n6.8%\n\nOpening balance:\n\nDate: 30/06/2001\n\nBalance: $15.26\n\nDays: 166\n\nInterest: $0.47\n\nPayments\n\nDate: 14/12/2001\n\nAmount: $15.26\n\nBalance: $0\n\nDays: 199\n\nInterest: $0\n\n\n\n\nTotal repayments\n\n$15.26\n\nTotal interest\n\n$0.47\n\nTotal principal\n\n$14.79\n\nClosing balance\n\nDate: 30/06/2002\n\nBalance: $0.47",
  "outputs": {
    "enquiryRateFormatted": "6.8%",
    "enquiryYearEndMinusOneDisplay": "30/06/2001",
    "amalgamatedLoanNotPaidByEOIYFormatted": "$15.26",
    "openingBalancePayDays": "166",
    "openingBalanceInterestFormatted": "$0.47",
    "totalAmountOfRepaymentFormatted": "$15.26",
    "totalInterestFormatted": "$0.47",
    "principalFormatted": "$14.79",
    "enquiryYearEndDisplay": "30/06/2002",
    "minimumYearRepaymentFormatted": "$4.00"
  },
  "repayments": [
    {
      "rd": "14/12/2001",
      "ra": 15.261816573955002
    }
  ],
  "inputs": {
    "incomeYearOfLoan": 1998,
    "fullTermOfAmalgamatedLoan": 7,
    "incomeYearOfEnquiring": 2002,
    "amalgamatedLoanNotPaidByEOIY": 15.261816573955228,
    "repayments": null,
    "lodgement_date": null
  },
  "idx": 2959
}