{
  "id": "2023-09-06T06:59:03.567Z0.8910918773434715",
  "alert": "Start of result\nResult\n\nMinimum yearly repayment not met.\n\nThe amount of the loan not repaid at the end of income year 2012-13 is $81.44.\n\nThe private company may be taken to pay a dividend under Division 7A to the shareholder or shareholder's associate because the amount repaid during income year 2012-13 in relation to the amalgamated loan is less than the minimum yearly repayment required.\n\nInterest received by the private company must be included in the income tax return for 2012-13.\n\nMinimum yearly repayment\n\n$17.00\n\nBenchmark interest rate\n\n7.05%\n\nOpening balance:\n\nDate: 30/06/2012\n\nBalance: $81.44\n\nDays: 365\n\nInterest: $5.74\n\nTotal repayments\n\n$0\n\nTotal interest\n\n$5.74\n\nTotal principal\n\n$0\n\nClosing balance\n\nDate: 30/06/2013\n\nBalance: $81.44",
  "outputs": {
    "enquiryRateFormatted": "7.05%",
    "enquiryYearEndMinusOneDisplay": "30/06/2012",
    "amalgamatedLoanNotPaidByEOIYFormatted": "$81.44",
    "openingBalancePayDays": "365",
    "openingBalanceInterestFormatted": "$5.74",
    "totalAmountOfRepaymentFormatted": "$0",
    "totalInterestFormatted": "$5.74",
    "principalFormatted": "$0",
    "enquiryYearEndDisplay": "30/06/2013",
    "minimumYearRepaymentFormatted": "$17.00"
  },
  "repayments": [],
  "inputs": {
    "incomeYearOfLoan": 2011,
    "fullTermOfAmalgamatedLoan": 7,
    "incomeYearOfEnquiring": 2013,
    "amalgamatedLoanNotPaidByEOIY": 81.44048037757267,
    "repayments": null,
    "lodgement_date": null
  },
  "idx": 7417
}