{
  "id": "2023-10-31T18:11:23.288Z0.5114432478234663",
  "alert": "Start of result\nResult\n\nMinimum yearly repayment met.\n\nThe amount of the loan not repaid at the end of income year 2014-15 is $4,817.90.\n\n\u000b\n\nThe amalgamated loan will not be taken to be a dividend because the total repayments made are equal to or greater than the minimum yearly repayment required for income year 2014-15.\n\nInterest received by the private company must be included in the income tax return for 2014-15.\n\nMinimum yearly repayment\n\n$6,701.00\n\nBenchmark interest rate\n\n5.95%\n\nOpening balance:\n\nDate: 30/06/2014\n\nBalance: $12,295.00\n\nDays: 135\n\nInterest: $270.57\n\nPayments\n\nDate: 13/11/2014\n\nAmount: $7,912.00\n\nBalance: $4,383.00\n\nDays: 230\n\nInterest: $164.33\n\n\n\n\nTotal repayments\n\n$7,912.00\n\nTotal interest\n\n$434.90\n\nTotal principal\n\n$7,477.10\n\nClosing balance\n\nDate: 30/06/2015\n\nBalance: $4,817.90",
  "outputs": {
    "enquiryRateFormatted": "5.95%",
    "enquiryYearEndMinusOneDisplay": "30/06/2014",
    "amalgamatedLoanNotPaidByEOIYFormatted": "$12,295.00",
    "openingBalancePayDays": "135",
    "openingBalanceInterestFormatted": "$270.57",
    "totalAmountOfRepaymentFormatted": "$7,912.00",
    "totalInterestFormatted": "$434.90",
    "principalFormatted": "$7,477.10",
    "enquiryYearEndDisplay": "30/06/2015",
    "minimumYearRepaymentFormatted": "$6,701.00",
    "loanAmountFormatted": "$4,817.90"
  },
  "repayments": [
    {
      "rd": "13/11/2014",
      "ra": 7912
    }
  ],
  "inputs": {
    "incomeYearOfLoan": 2011,
    "fullTermOfAmalgamatedLoan": 5,
    "incomeYearOfEnquiring": 2015,
    "amalgamatedLoanNotPaidByEOIY": 12295,
    "repayments": null,
    "lodgement_date": null
  },
  "idx": 3501
}