{
  "id": "2023-09-06T17:02:49.706Z0.22040016754687142",
  "alert": "Start of result\nResult\n\nMinimum yearly repayment met.\n\nThe amount of the loan not repaid at the end of income year 2005-06 is $0.43.\n\nThe amalgamated loan will not be taken to be a dividend because the total repayments made are equal to or greater than the minimum yearly repayment required for income year 2005-06.\n\nInterest received by the private company must be included in the income tax return for 2005-06.\n\nMinimum yearly repayment\n\n$1.00\n\nBenchmark interest rate\n\n7.3%\n\nOpening balance:\n\nDate: 30/06/2005\n\nBalance: $5.91\n\nDays: 360\n\nInterest: $0.43\n\nPayments\n\nDate: 26/06/2006\n\nAmount: $5.91\n\nBalance: $0\n\nDays: 5\n\nInterest: $0\n\n\n\n\nTotal repayments\n\n$5.91\n\nTotal interest\n\n$0.43\n\nTotal principal\n\n$5.48\n\nClosing balance\n\nDate: 30/06/2006\n\nBalance: $0.43",
  "outputs": {
    "enquiryRateFormatted": "7.3%",
    "enquiryYearEndMinusOneDisplay": "30/06/2005",
    "amalgamatedLoanNotPaidByEOIYFormatted": "$5.91",
    "openingBalancePayDays": "360",
    "openingBalanceInterestFormatted": "$0.43",
    "totalAmountOfRepaymentFormatted": "$5.91",
    "totalInterestFormatted": "$0.43",
    "principalFormatted": "$5.48",
    "enquiryYearEndDisplay": "30/06/2006",
    "minimumYearRepaymentFormatted": "$1.00"
  },
  "repayments": [
    {
      "rd": "26/6/2006",
      "ra": 5.916121273578028
    }
  ],
  "inputs": {
    "incomeYearOfLoan": 2005,
    "fullTermOfAmalgamatedLoan": 7,
    "incomeYearOfEnquiring": 2006,
    "amalgamatedLoanNotPaidByEOIY": 5.916121273578213,
    "repayments": null,
    "lodgement_date": "2/8/2005"
  },
  "idx": 5937
}