{
  "id": "2023-09-04T17:12:42.564Z0.019851597273815136",
  "alert": "Start of result\nResult\n\nMinimum yearly repayment not met.\n\nThe amount of the loan not repaid at the end of income year 2014-15 is $10,946,255.69.\n\nThe private company may be taken to pay a dividend under Division 7A to the shareholder or shareholder's associate because the amount repaid during income year 2014-15 in relation to the amalgamated loan is less than the minimum yearly repayment required.\n\nInterest received by the private company must be included in the income tax return for 2014-15.\n\nMinimum yearly repayment\n\n$4,091,314.00\n\nBenchmark interest rate\n\n5.95%\n\nOpening balance:\n\nDate: 30/06/2014\n\nBalance: $10,946,255.69\n\nDays: 365\n\nInterest: $651,302.21\n\nTotal repayments\n\n$0\n\nTotal interest\n\n$651,302.21\n\nTotal principal\n\n$0\n\nClosing balance\n\nDate: 30/06/2015\n\nBalance: $10,946,255.69",
  "outputs": {
    "enquiryRateFormatted": "5.95%",
    "enquiryYearEndMinusOneDisplay": "30/06/2014",
    "amalgamatedLoanNotPaidByEOIYFormatted": "$10,946,255.69",
    "openingBalancePayDays": "365",
    "openingBalanceInterestFormatted": "$651,302.21",
    "totalAmountOfRepaymentFormatted": "$0",
    "totalInterestFormatted": "$651,302.21",
    "principalFormatted": "$0",
    "enquiryYearEndDisplay": "30/06/2015",
    "minimumYearRepaymentFormatted": "$4,091,314.00"
  },
  "repayments": [],
  "inputs": {
    "incomeYearOfLoan": 2014,
    "fullTermOfAmalgamatedLoan": 3,
    "incomeYearOfEnquiring": 2015,
    "amalgamatedLoanNotPaidByEOIY": 10946255.691538304,
    "repayments": null,
    "lodgement_date": "30/6/2015"
  },
  "idx": 1848
}