{
  "id": "2023-10-31T17:51:35.176Z0.3624197193757043",
  "alert": "Start of result\nResult\n\nAmalgamated loan fully repaid.\n\nThe amalgamated loan has been paid in full.\u000bThe private company is not taken under Division 7A to pay a dividend to the shareholder or shareholder's associate.\n\nInterest received by the private company must be included in the income tax return for 2014-15.\n\nMinimum yearly repayment\n\n$7.00\n\nBenchmark interest rate\n\n5.95%\n\nOpening balance:\n\nDate: 30/06/2014\n\nBalance: $35.91\n\nDays: 225\n\nInterest: $1.32\n\nPayments\n\nDate: 11/02/2015\n\nAmount: $359.16\n\nBalance: $0\n\nDays: 140\n\nInterest: $0\n\n\n\n\nTotal repayments\n\n$359.16\n\nTotal interest\n\n$1.32\n\nTotal principal\n\n$357.84\n\nClosing balance\n\nDate: 30/06/2015\n\nBalance: $0",
  "outputs": {
    "enquiryRateFormatted": "5.95%",
    "enquiryYearEndMinusOneDisplay": "30/06/2014",
    "amalgamatedLoanNotPaidByEOIYFormatted": "$35.91",
    "openingBalancePayDays": "225",
    "openingBalanceInterestFormatted": "$1.32",
    "totalAmountOfRepaymentFormatted": "$359.16",
    "totalInterestFormatted": "$1.32",
    "principalFormatted": "$357.84",
    "enquiryYearEndDisplay": "30/06/2015",
    "minimumYearRepaymentFormatted": "$7.00",
    "loanAmountFormatted": "$0"
  },
  "repayments": [
    {
      "rd": "11/2/2015",
      "ra": 359.16357742055334
    }
  ],
  "inputs": {
    "incomeYearOfLoan": 2014,
    "fullTermOfAmalgamatedLoan": 6,
    "incomeYearOfEnquiring": 2015,
    "amalgamatedLoanNotPaidByEOIY": 35.916357742055304,
    "repayments": null,
    "lodgement_date": "28/12/2014"
  },
  "idx": 2756
}