{
  "id": "2023-10-31T19:30:53.750Z0.7735331464348681",
  "alert": "Start of result\nResult\n\nMinimum yearly repayment not met.\n\nThe amount of the loan not repaid at the end of income year 2008-09 is $6,278.00.\n\nThe private company may be taken to pay a dividend under Division 7A to the shareholder or shareholder's associate because the amount repaid during income year 2008-09 in relation to the amalgamated loan is less than the minimum yearly repayment required.\n\nInterest received by the private company must be included in the income tax return for 2008-09.\n\nMinimum yearly repayment\n\n$3,591.00\n\nBenchmark interest rate\n\n9.45%\n\nOpening balance:\n\nDate: 30/06/2008\n\nBalance: $6,278.00\n\nDays: 365\n\nInterest: $593.27\n\nTotal repayments\n\n$0\n\nTotal interest\n\n$593.27\n\nTotal principal\n\n$0\n\nClosing balance\n\nDate: 30/06/2009\n\nBalance: $6,278.00",
  "outputs": {
    "enquiryRateFormatted": "9.45%",
    "enquiryYearEndMinusOneDisplay": "30/06/2008",
    "amalgamatedLoanNotPaidByEOIYFormatted": "$6,278.00",
    "openingBalancePayDays": "365",
    "openingBalanceInterestFormatted": "$593.27",
    "totalAmountOfRepaymentFormatted": "$0",
    "totalInterestFormatted": "$593.27",
    "principalFormatted": "$0",
    "enquiryYearEndDisplay": "30/06/2009",
    "minimumYearRepaymentFormatted": "$3,591.00",
    "loanAmountFormatted": "$6,278.00"
  },
  "repayments": [],
  "inputs": {
    "incomeYearOfLoan": 2004,
    "fullTermOfAmalgamatedLoan": 6,
    "incomeYearOfEnquiring": 2009,
    "amalgamatedLoanNotPaidByEOIY": 6278,
    "repayments": null,
    "lodgement_date": null
  },
  "idx": 5546
}