{
  "id": "2023-09-05T16:20:10.386Z0.09451093809453548",
  "alert": "Start of result\nResult\n\nMinimum yearly repayment not met.\n\nThe amount of the loan not repaid at the end of income year 2020-21 is $97.62.\n\nThe private company may be taken to pay a dividend under Division 7A to the shareholder or shareholder's associate because the amount repaid during income year 2020-21 in relation to the amalgamated loan is less than the minimum yearly repayment required.\n\nInterest received by the private company must be included in the income tax return for 2020-21.\n\nMinimum yearly repayment\n\n$102.00\n\nBenchmark interest rate\n\n4.52%\n\nOpening balance:\n\nDate: 30/06/2020\n\nBalance: $97.62\n\nDays: 365\n\nInterest: $4.41\n\nTotal repayments\n\n$0\n\nTotal interest\n\n$4.41\n\nTotal principal\n\n$0\n\nClosing balance\n\nDate: 30/06/2021\n\nBalance: $97.62",
  "outputs": {
    "enquiryRateFormatted": "4.52%",
    "enquiryYearEndMinusOneDisplay": "30/06/2020",
    "amalgamatedLoanNotPaidByEOIYFormatted": "$97.62",
    "openingBalancePayDays": "365",
    "openingBalanceInterestFormatted": "$4.41",
    "totalAmountOfRepaymentFormatted": "$0",
    "totalInterestFormatted": "$4.41",
    "principalFormatted": "$0",
    "enquiryYearEndDisplay": "30/06/2021",
    "minimumYearRepaymentFormatted": "$102.00"
  },
  "repayments": [],
  "inputs": {
    "incomeYearOfLoan": 2019,
    "fullTermOfAmalgamatedLoan": 2,
    "incomeYearOfEnquiring": 2021,
    "amalgamatedLoanNotPaidByEOIY": 97.62378831228598,
    "repayments": null,
    "lodgement_date": null
  },
  "idx": 0
}