{
  "id": "2023-09-05T22:20:59.018Z0.928282179153896",
  "alert": "Start of result\nResult\n\nMinimum yearly repayment met.\n\nThe amount of the loan not repaid at the end of income year 2019-20 is $2,267.99.\n\nThe amalgamated loan will not be taken to be a dividend because the total repayments made are equal to or greater than the minimum yearly repayment required for income year 2019-20.\n\nInterest received by the private company must be included in the income tax return for 2019-20.\n\nMinimum yearly repayment\n\n$1,993.00\n\nBenchmark interest rate\n\n5.37%\n\nOpening balance:\n\nDate: 30/06/2019\n\nBalance: $5,391.00\n\nDays: 361\n\nInterest: $285.54\n\nPayments\n\nDate: 26/06/2020\n\nAmount: $3,410.00\n\nBalance: $1,981.00\n\nDays: 5\n\nInterest: $1.45\n\n\n\n\nTotal repayments\n\n$3,410.00\n\nTotal interest\n\n$286.99\n\nTotal principal\n\n$3,123.01\n\nClosing balance\n\nDate: 30/06/2020\n\nBalance: $2,267.99",
  "outputs": {
    "enquiryRateFormatted": "5.37%",
    "enquiryYearEndMinusOneDisplay": "30/06/2019",
    "amalgamatedLoanNotPaidByEOIYFormatted": "$5,391.00",
    "openingBalancePayDays": "361",
    "openingBalanceInterestFormatted": "$285.54",
    "totalAmountOfRepaymentFormatted": "$3,410.00",
    "totalInterestFormatted": "$286.99",
    "principalFormatted": "$3,123.01",
    "enquiryYearEndDisplay": "30/06/2020",
    "minimumYearRepaymentFormatted": "$1,993.00"
  },
  "repayments": [
    {
      "rd": "26/6/2020",
      "ra": 3410
    }
  ],
  "inputs": {
    "incomeYearOfLoan": 2016,
    "fullTermOfAmalgamatedLoan": 6,
    "incomeYearOfEnquiring": 2020,
    "amalgamatedLoanNotPaidByEOIY": 5391,
    "repayments": null,
    "lodgement_date": null
  },
  "idx": 4051
}