{
  "id": "2023-09-05T17:21:32.854Z0.9517154365594727",
  "alert": "Start of result\nResult\n\nMinimum yearly repayment met.\n\nThe amount of the loan not repaid at the end of income year 2023-24 is $1.43.\n\nThe amalgamated loan will not be taken to be a dividend because the total repayments made are equal to or greater than the minimum yearly repayment required for income year 2023-24.\n\nInterest received by the private company must be included in the income tax return for 2023-24.\n\nMinimum yearly repayment\n\n$7.00\n\nBenchmark interest rate\n\n8.27%\n\nOpening balance:\n\nDate: 30/06/2023\n\nBalance: $18.86\n\nDays: 335\n\nInterest: $1.43\n\nPayments\n\nDate: 31/05/2024\n\nAmount: $18.86\n\nBalance: $0\n\nDays: 31\n\nInterest: $0\n\n\n\n\nTotal repayments\n\n$18.86\n\nTotal interest\n\n$1.43\n\nTotal principal\n\n$17.43\n\nClosing balance\n\nDate: 30/06/2024\n\nBalance: $1.43",
  "outputs": {
    "enquiryRateFormatted": "8.27%",
    "enquiryYearEndMinusOneDisplay": "30/06/2023",
    "amalgamatedLoanNotPaidByEOIYFormatted": "$18.86",
    "openingBalancePayDays": "335",
    "openingBalanceInterestFormatted": "$1.43",
    "totalAmountOfRepaymentFormatted": "$18.86",
    "totalInterestFormatted": "$1.43",
    "principalFormatted": "$17.43",
    "enquiryYearEndDisplay": "30/06/2024",
    "minimumYearRepaymentFormatted": "$7.00"
  },
  "repayments": [
    {
      "rd": "31/5/2024",
      "ra": 18.862058442135094
    }
  ],
  "inputs": {
    "incomeYearOfLoan": 2019,
    "fullTermOfAmalgamatedLoan": 7,
    "incomeYearOfEnquiring": 2024,
    "amalgamatedLoanNotPaidByEOIY": 18.862058442135186,
    "repayments": null,
    "lodgement_date": null
  },
  "idx": 4070
}