{
  "id": "2023-09-06T02:50:31.739Z0.8047656272039538",
  "alert": "Start of result\nResult\n\nMinimum yearly repayment met.\n\nThe amount of the loan not repaid at the end of income year 2014-15 is $2.95.\n\nThe amalgamated loan will not be taken to be a dividend because the total repayments made are equal to or greater than the minimum yearly repayment required for income year 2014-15.\n\nInterest received by the private company must be included in the income tax return for 2014-15.\n\nMinimum yearly repayment\n\n$42.00\n\nBenchmark interest rate\n\n5.95%\n\nOpening balance:\n\nDate: 30/06/2014\n\nBalance: $76.76\n\nDays: 236\n\nInterest: $2.95\n\nPayments\n\nDate: 22/02/2015\n\nAmount: $76.76\n\nBalance: $0\n\nDays: 129\n\nInterest: $0\n\n\n\n\nTotal repayments\n\n$76.76\n\nTotal interest\n\n$2.95\n\nTotal principal\n\n$73.81\n\nClosing balance\n\nDate: 30/06/2015\n\nBalance: $2.95",
  "outputs": {
    "enquiryRateFormatted": "5.95%",
    "enquiryYearEndMinusOneDisplay": "30/06/2014",
    "amalgamatedLoanNotPaidByEOIYFormatted": "$76.76",
    "openingBalancePayDays": "236",
    "openingBalanceInterestFormatted": "$2.95",
    "totalAmountOfRepaymentFormatted": "$76.76",
    "totalInterestFormatted": "$2.95",
    "principalFormatted": "$73.81",
    "enquiryYearEndDisplay": "30/06/2015",
    "minimumYearRepaymentFormatted": "$42.00"
  },
  "repayments": [
    {
      "rd": "22/2/2015",
      "ra": 76.76945245531442
    }
  ],
  "inputs": {
    "incomeYearOfLoan": 2013,
    "fullTermOfAmalgamatedLoan": 3,
    "incomeYearOfEnquiring": 2015,
    "amalgamatedLoanNotPaidByEOIY": 76.7694524553141,
    "repayments": null,
    "lodgement_date": null
  },
  "idx": 1835
}