{
  "id": "2023-09-04T16:05:37.403Z0.15732144276196813",
  "alert": "Start of result\nResult\n\nMinimum yearly repayment not met.\n\nThe amount of the loan not repaid at the end of income year 2022-23 is $5,602.05.\n\nThe private company may be taken to pay a dividend under Division 7A to the shareholder or shareholder's associate because the amount repaid during income year 2022-23 in relation to the amalgamated loan is less than the minimum yearly repayment required.\n\nInterest received by the private company must be included in the income tax return for 2022-23.\n\nMinimum yearly repayment\n\n$12,667.00\n\nBenchmark interest rate\n\n4.77%\n\nOpening balance:\n\nDate: 30/06/2022\n\nBalance: $12,090.00\n\nDays: 0\n\nInterest: $0\n\nPayments\n\nDate: 01/07/2022\n\nAmount: $6,743.00\n\nBalance: $5,347.00\n\nDays: 365\n\nInterest: $255.05\n\n\n\n\nTotal repayments\n\n$6,743.00\n\nTotal interest\n\n$255.05\n\nTotal principal\n\n$6,487.95\n\nClosing balance\n\nDate: 30/06/2023\n\nBalance: $5,602.05",
  "outputs": {
    "enquiryRateFormatted": "4.77%",
    "enquiryYearEndMinusOneDisplay": "30/06/2022",
    "amalgamatedLoanNotPaidByEOIYFormatted": "$12,090.00",
    "openingBalancePayDays": "0",
    "openingBalanceInterestFormatted": "$0",
    "totalAmountOfRepaymentFormatted": "$6,743.00",
    "totalInterestFormatted": "$255.05",
    "principalFormatted": "$6,487.95",
    "enquiryYearEndDisplay": "30/06/2023",
    "minimumYearRepaymentFormatted": "$12,667.00"
  },
  "repayments": [
    {
      "rd": "1/7/2022",
      "ra": 6743
    }
  ],
  "inputs": {
    "incomeYearOfLoan": 2022,
    "fullTermOfAmalgamatedLoan": 1,
    "incomeYearOfEnquiring": 2023,
    "amalgamatedLoanNotPaidByEOIY": 12090,
    "repayments": null,
    "lodgement_date": "1/7/2022"
  },
  "idx": 60
}