{
  "id": "2023-10-31T17:15:28.461Z0.5251029616242467",
  "alert": "Start of result\nResult\n\nAmalgamated loan fully repaid.\n\nThe amalgamated loan has been paid in full.\u000bThe private company is not taken under Division 7A to pay a dividend to the shareholder or shareholder's associate.\n\nInterest received by the private company must be included in the income tax return for 2022-23.\n\nMinimum yearly repayment\n\n$9.00\n\nBenchmark interest rate\n\n4.77%\n\nOpening balance:\n\nDate: 30/06/2022\n\nBalance: $9.06\n\nDays: 163\n\nInterest: $0.19\n\nPayments\n\nDate: 11/12/2022\n\nAmount: $90.64\n\nBalance: $0\n\nDays: 202\n\nInterest: $0\n\n\n\n\nTotal repayments\n\n$90.64\n\nTotal interest\n\n$0.19\n\nTotal principal\n\n$90.45\n\nClosing balance\n\nDate: 30/06/2023\n\nBalance: $0",
  "outputs": {
    "enquiryRateFormatted": "4.77%",
    "enquiryYearEndMinusOneDisplay": "30/06/2022",
    "amalgamatedLoanNotPaidByEOIYFormatted": "$9.06",
    "openingBalancePayDays": "163",
    "openingBalanceInterestFormatted": "$0.19",
    "totalAmountOfRepaymentFormatted": "$90.64",
    "totalInterestFormatted": "$0.19",
    "principalFormatted": "$90.45",
    "enquiryYearEndDisplay": "30/06/2023",
    "minimumYearRepaymentFormatted": "$9.00",
    "loanAmountFormatted": "$0"
  },
  "repayments": [
    {
      "rd": "11/12/2022",
      "ra": 90.64063124892351
    }
  ],
  "inputs": {
    "incomeYearOfLoan": 2020,
    "fullTermOfAmalgamatedLoan": 3,
    "incomeYearOfEnquiring": 2023,
    "amalgamatedLoanNotPaidByEOIY": 9.064063124892352,
    "repayments": null,
    "lodgement_date": null
  },
  "idx": 762
}