{
  "id": "2023-10-31T17:23:39.130Z0.2956299254605994",
  "alert": "Start of result\nResult\n\nAmalgamated loan fully repaid.\n\nThe amalgamated loan has been paid in full.\u000bThe private company is not taken under Division 7A to pay a dividend to the shareholder or shareholder's associate.\n\nInterest received by the private company must be included in the income tax return for 2019-20.\n\nMinimum yearly repayment\n\n$14.00\n\nBenchmark interest rate\n\n5.37%\n\nOpening balance:\n\nDate: 30/06/2019\n\nBalance: $25.08\n\nDays: 178\n\nInterest: $0.65\n\nPayments\n\nDate: 26/12/2019\n\nAmount: $250.83\n\nBalance: $0\n\nDays: 188\n\nInterest: $0\n\n\n\n\nTotal repayments\n\n$250.83\n\nTotal interest\n\n$0.65\n\nTotal principal\n\n$250.18\n\nClosing balance\n\nDate: 30/06/2020\n\nBalance: $0",
  "outputs": {
    "enquiryRateFormatted": "5.37%",
    "enquiryYearEndMinusOneDisplay": "30/06/2019",
    "amalgamatedLoanNotPaidByEOIYFormatted": "$25.08",
    "openingBalancePayDays": "178",
    "openingBalanceInterestFormatted": "$0.65",
    "totalAmountOfRepaymentFormatted": "$250.83",
    "totalInterestFormatted": "$0.65",
    "principalFormatted": "$250.18",
    "enquiryYearEndDisplay": "30/06/2020",
    "minimumYearRepaymentFormatted": "$14.00",
    "loanAmountFormatted": "$0"
  },
  "repayments": [
    {
      "rd": "26/12/2019",
      "ra": 250.8380851876982
    }
  ],
  "inputs": {
    "incomeYearOfLoan": 2018,
    "fullTermOfAmalgamatedLoan": 3,
    "incomeYearOfEnquiring": 2020,
    "amalgamatedLoanNotPaidByEOIY": 25.083808518769835,
    "repayments": null,
    "lodgement_date": null
  },
  "idx": 1325
}