{
  "id": "2023-09-06T09:06:13.886Z0.8606207519507898",
  "alert": "Start of result\nResult\n\nMinimum yearly repayment not met.\n\nThe amount of the loan not repaid at the end of income year 2010-11 is $5.88.\n\nThe private company may be taken to pay a dividend under Division 7A to the shareholder or shareholder's associate because the amount repaid during income year 2010-11 in relation to the amalgamated loan is less than the minimum yearly repayment required.\n\nInterest received by the private company must be included in the income tax return for 2010-11.\n\nMinimum yearly repayment\n\n$100.00\n\nBenchmark interest rate\n\n7.4%\n\nOpening balance:\n\nDate: 30/06/2010\n\nBalance: $92.98\n\nDays: 312\n\nInterest: $5.88\n\nPayments\n\nDate: 09/05/2011\n\nAmount: $92.98\n\nBalance: $0\n\nDays: 53\n\nInterest: $0\n\n\n\n\nTotal repayments\n\n$92.98\n\nTotal interest\n\n$5.88\n\nTotal principal\n\n$87.10\n\nClosing balance\n\nDate: 30/06/2011\n\nBalance: $5.88",
  "outputs": {
    "enquiryRateFormatted": "7.4%",
    "enquiryYearEndMinusOneDisplay": "30/06/2010",
    "amalgamatedLoanNotPaidByEOIYFormatted": "$92.98",
    "openingBalancePayDays": "312",
    "openingBalanceInterestFormatted": "$5.88",
    "totalAmountOfRepaymentFormatted": "$92.98",
    "totalInterestFormatted": "$5.88",
    "principalFormatted": "$87.10",
    "enquiryYearEndDisplay": "30/06/2011",
    "minimumYearRepaymentFormatted": "$100.00"
  },
  "repayments": [
    {
      "rd": "9/5/2011",
      "ra": 92.98673972726647
    }
  ],
  "inputs": {
    "incomeYearOfLoan": 2009,
    "fullTermOfAmalgamatedLoan": 2,
    "incomeYearOfEnquiring": 2011,
    "amalgamatedLoanNotPaidByEOIY": 92.98673972726604,
    "repayments": null,
    "lodgement_date": null
  },
  "idx": 5533
}