{
  "id": "2023-09-04T22:13:01.504Z0.8853514862498764",
  "alert": "Start of result\nResult\n\nMinimum yearly repayment not met.\n\nThe amount of the loan not repaid at the end of income year 2004-05 is $14,860,591.84.\n\nThe private company may be taken to pay a dividend under Division 7A to the shareholder or shareholder's associate because the amount repaid during income year 2004-05 in relation to the amalgamated loan is less than the minimum yearly repayment required.\n\nInterest received by the private company must be included in the income tax return for 2004-05.\n\nMinimum yearly repayment\n\n$3,629,214.00\n\nBenchmark interest rate\n\n7.05%\n\nOpening balance:\n\nDate: 30/06/2004\n\nBalance: $14,860,591.84\n\nDays: 365\n\nInterest: $1,047,671.72\n\nTotal repayments\n\n$0\n\nTotal interest\n\n$1,047,671.72\n\nTotal principal\n\n$0\n\nClosing balance\n\nDate: 30/06/2005\n\nBalance: $14,860,591.84",
  "outputs": {
    "enquiryRateFormatted": "7.05%",
    "enquiryYearEndMinusOneDisplay": "30/06/2004",
    "amalgamatedLoanNotPaidByEOIYFormatted": "$14,860,591.84",
    "openingBalancePayDays": "365",
    "openingBalanceInterestFormatted": "$1,047,671.72",
    "totalAmountOfRepaymentFormatted": "$0",
    "totalInterestFormatted": "$1,047,671.72",
    "principalFormatted": "$0",
    "enquiryYearEndDisplay": "30/06/2005",
    "minimumYearRepaymentFormatted": "$3,629,214.00"
  },
  "repayments": [],
  "inputs": {
    "incomeYearOfLoan": 2002,
    "fullTermOfAmalgamatedLoan": 7,
    "incomeYearOfEnquiring": 2005,
    "amalgamatedLoanNotPaidByEOIY": 14860591.849001428,
    "repayments": null,
    "lodgement_date": null
  },
  "idx": 471
}