{
  "id": "2023-10-31T18:13:38.384Z0.4785759519423979",
  "alert": "Start of result\nResult\n\nMinimum yearly repayment not met.\n\nThe amount of the loan not repaid at the end of income year 2016-17 is $54.25.\n\nThe private company may be taken to pay a dividend under Division 7A to the shareholder or shareholder's associate because the amount repaid during income year 2016-17 in relation to the amalgamated loan is less than the minimum yearly repayment required.\n\nInterest received by the private company must be included in the income tax return for 2016-17.\n\nMinimum yearly repayment\n\n$29.00\n\nBenchmark interest rate\n\n5.4%\n\nOpening balance:\n\nDate: 30/06/2016\n\nBalance: $54.25\n\nDays: 365\n\nInterest: $2.93\n\nTotal repayments\n\n$0\n\nTotal interest\n\n$2.93\n\nTotal principal\n\n$0\n\nClosing balance\n\nDate: 30/06/2017\n\nBalance: $54.25",
  "outputs": {
    "enquiryRateFormatted": "5.4%",
    "enquiryYearEndMinusOneDisplay": "30/06/2016",
    "amalgamatedLoanNotPaidByEOIYFormatted": "$54.25",
    "openingBalancePayDays": "365",
    "openingBalanceInterestFormatted": "$2.93",
    "totalAmountOfRepaymentFormatted": "$0",
    "totalInterestFormatted": "$2.93",
    "principalFormatted": "$0",
    "enquiryYearEndDisplay": "30/06/2017",
    "minimumYearRepaymentFormatted": "$29.00",
    "loanAmountFormatted": "$54.25"
  },
  "repayments": [],
  "inputs": {
    "incomeYearOfLoan": 2011,
    "fullTermOfAmalgamatedLoan": 7,
    "incomeYearOfEnquiring": 2017,
    "amalgamatedLoanNotPaidByEOIY": 54.252860023845486,
    "repayments": null,
    "lodgement_date": null
  },
  "idx": 3576
}