{
  "id": "2023-10-31T17:12:18.834Z0.06636206819527446",
  "alert": "Start of result\nResult\n\nAmalgamated loan fully repaid.\n\nThe amalgamated loan has been paid in full.\u000bThe private company is not taken under Division 7A to pay a dividend to the shareholder or shareholder's associate.\n\nInterest received by the private company must be included in the income tax return for 2022-23.\n\nMinimum yearly repayment\n\n$11.00\n\nBenchmark interest rate\n\n4.77%\n\nOpening balance:\n\nDate: 30/06/2022\n\nBalance: $29.97\n\nDays: 277\n\nInterest: $1.08\n\nPayments\n\nDate: 04/04/2023\n\nAmount: $299.76\n\nBalance: $0\n\nDays: 88\n\nInterest: $0\n\n\n\n\nTotal repayments\n\n$299.76\n\nTotal interest\n\n$1.08\n\nTotal principal\n\n$298.68\n\nClosing balance\n\nDate: 30/06/2023\n\nBalance: $0",
  "outputs": {
    "enquiryRateFormatted": "4.77%",
    "enquiryYearEndMinusOneDisplay": "30/06/2022",
    "amalgamatedLoanNotPaidByEOIYFormatted": "$29.97",
    "openingBalancePayDays": "277",
    "openingBalanceInterestFormatted": "$1.08",
    "totalAmountOfRepaymentFormatted": "$299.76",
    "totalInterestFormatted": "$1.08",
    "principalFormatted": "$298.68",
    "enquiryYearEndDisplay": "30/06/2023",
    "minimumYearRepaymentFormatted": "$11.00",
    "loanAmountFormatted": "$0"
  },
  "repayments": [
    {
      "rd": "4/4/2023",
      "ra": 299.76095837139565
    }
  ],
  "inputs": {
    "incomeYearOfLoan": 2021,
    "fullTermOfAmalgamatedLoan": 4,
    "incomeYearOfEnquiring": 2023,
    "amalgamatedLoanNotPaidByEOIY": 29.97609583713956,
    "repayments": null,
    "lodgement_date": null
  },
  "idx": 503
}