{
  "id": "2023-10-31T17:15:08.783Z0.8590874827837969",
  "alert": "Start of result\nResult\n\nMinimum yearly repayment not met.\n\nThe amount of the loan not repaid at the end of income year 2020-21 is $6,677.00.\n\nThe private company may be taken to pay a dividend under Division 7A to the shareholder or shareholder's associate because the amount repaid during income year 2020-21 in relation to the amalgamated loan is less than the minimum yearly repayment required.\n\nInterest received by the private company must be included in the income tax return for 2020-21.\n\nMinimum yearly repayment\n\n$3,567.00\n\nBenchmark interest rate\n\n4.52%\n\nOpening balance:\n\nDate: 30/06/2020\n\nBalance: $6,677.00\n\nDays: 365\n\nInterest: $301.80\n\nTotal repayments\n\n$0\n\nTotal interest\n\n$301.80\n\nTotal principal\n\n$0\n\nClosing balance\n\nDate: 30/06/2021\n\nBalance: $6,677.00",
  "outputs": {
    "enquiryRateFormatted": "4.52%",
    "enquiryYearEndMinusOneDisplay": "30/06/2020",
    "amalgamatedLoanNotPaidByEOIYFormatted": "$6,677.00",
    "openingBalancePayDays": "365",
    "openingBalanceInterestFormatted": "$301.80",
    "totalAmountOfRepaymentFormatted": "$0",
    "totalInterestFormatted": "$301.80",
    "principalFormatted": "$0",
    "enquiryYearEndDisplay": "30/06/2021",
    "minimumYearRepaymentFormatted": "$3,567.00",
    "loanAmountFormatted": "$6,677.00"
  },
  "repayments": [],
  "inputs": {
    "incomeYearOfLoan": 2020,
    "fullTermOfAmalgamatedLoan": 2,
    "incomeYearOfEnquiring": 2021,
    "amalgamatedLoanNotPaidByEOIY": 6677,
    "repayments": null,
    "lodgement_date": "30/8/2020"
  },
  "idx": 735
}