{
  "id": "2023-10-31T17:35:06.712Z0.04904723878858597",
  "alert": "Start of result\nResult\n\nAmalgamated loan fully repaid.\n\nThe amalgamated loan has been paid in full.\u000bThe private company is not taken under Division 7A to pay a dividend to the shareholder or shareholder's associate.\n\nInterest received by the private company must be included in the income tax return for 2018-19.\n\nMinimum yearly repayment\n\n$1,314.00\n\nBenchmark interest rate\n\n5.2%\n\nOpening balance:\n\nDate: 30/06/2018\n\nBalance: $3,565.00\n\nDays: 84\n\nInterest: $42.66\n\nPayments\n\nDate: 23/09/2018\n\nAmount: $3,698.00\n\nBalance: $0\n\nDays: 281\n\nInterest: $0\n\n\n\n\nTotal repayments\n\n$3,698.00\n\nTotal interest\n\n$42.66\n\nTotal principal\n\n$3,655.34\n\nClosing balance\n\nDate: 30/06/2019\n\nBalance: $0",
  "outputs": {
    "enquiryRateFormatted": "5.2%",
    "enquiryYearEndMinusOneDisplay": "30/06/2018",
    "amalgamatedLoanNotPaidByEOIYFormatted": "$3,565.00",
    "openingBalancePayDays": "84",
    "openingBalanceInterestFormatted": "$42.66",
    "totalAmountOfRepaymentFormatted": "$3,698.00",
    "totalInterestFormatted": "$42.66",
    "principalFormatted": "$3,655.34",
    "enquiryYearEndDisplay": "30/06/2019",
    "minimumYearRepaymentFormatted": "$1,314.00",
    "loanAmountFormatted": "$0"
  },
  "repayments": [
    {
      "rd": "23/9/2018",
      "ra": 3698
    }
  ],
  "inputs": {
    "incomeYearOfLoan": 2016,
    "fullTermOfAmalgamatedLoan": 5,
    "incomeYearOfEnquiring": 2019,
    "amalgamatedLoanNotPaidByEOIY": 3565,
    "repayments": null,
    "lodgement_date": null
  },
  "idx": 1979
}