{
  "id": "2023-10-31T18:21:17.187Z0.41568176638991405",
  "alert": "Start of result\nResult\n\nAmalgamated loan fully repaid.\n\nThe amalgamated loan has been paid in full.\u000bThe private company is not taken under Division 7A to pay a dividend to the shareholder or shareholder's associate.\n\nInterest received by the private company must be included in the income tax return for 2010-11.\n\nMinimum yearly repayment\n\n-$84.00\n\nBenchmark interest rate\n\n7.4%\n\nOpening balance:\n\nDate: 30/06/2010\n\nBalance: $31.50\n\nDays: 85\n\nInterest: $0.54\n\nPayments\n\nDate: 24/09/2010\n\nAmount: $315.05\n\nBalance: $0\n\nDays: 280\n\nInterest: $0\n\n\n\n\nTotal repayments\n\n$315.05\n\nTotal interest\n\n$0.54\n\nTotal principal\n\n$314.51\n\nClosing balance\n\nDate: 30/06/2011\n\nBalance: $0",
  "outputs": {
    "enquiryRateFormatted": "7.4%",
    "enquiryYearEndMinusOneDisplay": "30/06/2010",
    "amalgamatedLoanNotPaidByEOIYFormatted": "$31.50",
    "openingBalancePayDays": "85",
    "openingBalanceInterestFormatted": "$0.54",
    "totalAmountOfRepaymentFormatted": "$315.05",
    "totalInterestFormatted": "$0.54",
    "principalFormatted": "$314.51",
    "enquiryYearEndDisplay": "30/06/2011",
    "minimumYearRepaymentFormatted": "-$84.00",
    "loanAmountFormatted": "$0"
  },
  "repayments": [
    {
      "rd": "24/9/2010",
      "ra": 315.0506231823365
    }
  ],
  "inputs": {
    "incomeYearOfLoan": 2010,
    "fullTermOfAmalgamatedLoan": 4,
    "incomeYearOfEnquiring": 2011,
    "amalgamatedLoanNotPaidByEOIY": 31.505062318233723,
    "repayments": null,
    "lodgement_date": "29/9/2010"
  },
  "idx": 3832
}