{
  "id": "2023-10-31T20:58:58.141Z0.5218605227424712",
  "alert": "Start of result\nResult\n\nMinimum yearly repayment not met.\n\nThe amount of the loan not repaid at the end of income year 2002-03 is $22.06.\n\nThe private company may be taken to pay a dividend under Division 7A to the shareholder or shareholder's associate because the amount repaid during income year 2002-03 in relation to the amalgamated loan is less than the minimum yearly repayment required.\n\nInterest received by the private company must be included in the income tax return for 2002-03.\n\nMinimum yearly repayment\n\n$12.00\n\nBenchmark interest rate\n\n6.3%\n\nOpening balance:\n\nDate: 30/06/2002\n\nBalance: $22.06\n\nDays: 365\n\nInterest: $1.39\n\nTotal repayments\n\n$0\n\nTotal interest\n\n$1.39\n\nTotal principal\n\n$0\n\nClosing balance\n\nDate: 30/06/2003\n\nBalance: $22.06",
  "outputs": {
    "enquiryRateFormatted": "6.3%",
    "enquiryYearEndMinusOneDisplay": "30/06/2002",
    "amalgamatedLoanNotPaidByEOIYFormatted": "$22.06",
    "openingBalancePayDays": "365",
    "openingBalanceInterestFormatted": "$1.39",
    "totalAmountOfRepaymentFormatted": "$0",
    "totalInterestFormatted": "$1.39",
    "principalFormatted": "$0",
    "enquiryYearEndDisplay": "30/06/2003",
    "minimumYearRepaymentFormatted": "$12.00",
    "loanAmountFormatted": "$22.06"
  },
  "repayments": [],
  "inputs": {
    "incomeYearOfLoan": 1999,
    "fullTermOfAmalgamatedLoan": 5,
    "incomeYearOfEnquiring": 2003,
    "amalgamatedLoanNotPaidByEOIY": 22.069863890807934,
    "repayments": null,
    "lodgement_date": null
  },
  "idx": 6916
}