{
  "id": "2023-10-31T17:24:09.528Z0.9881438661354236",
  "alert": "Start of result\nResult\n\nAmalgamated loan fully repaid.\n\nThe amalgamated loan has been paid in full.\u000bThe private company is not taken under Division 7A to pay a dividend to the shareholder or shareholder's associate.\n\nInterest received by the private company must be included in the income tax return for 2020-21.\n\nMinimum yearly repayment\n\n$3,171.00\n\nBenchmark interest rate\n\n4.52%\n\nOpening balance:\n\nDate: 30/06/2020\n\nBalance: $5,936.00\n\nDays: 318\n\nInterest: $233.76\n\nPayments\n\nDate: 15/05/2021\n\nAmount: $8,116.00\n\nBalance: $0\n\nDays: 47\n\nInterest: $0\n\n\n\n\nTotal repayments\n\n$8,116.00\n\nTotal interest\n\n$233.76\n\nTotal principal\n\n$7,882.24\n\nClosing balance\n\nDate: 30/06/2021\n\nBalance: $0",
  "outputs": {
    "enquiryRateFormatted": "4.52%",
    "enquiryYearEndMinusOneDisplay": "30/06/2020",
    "amalgamatedLoanNotPaidByEOIYFormatted": "$5,936.00",
    "openingBalancePayDays": "318",
    "openingBalanceInterestFormatted": "$233.76",
    "totalAmountOfRepaymentFormatted": "$8,116.00",
    "totalInterestFormatted": "$233.76",
    "principalFormatted": "$7,882.24",
    "enquiryYearEndDisplay": "30/06/2021",
    "minimumYearRepaymentFormatted": "$3,171.00",
    "loanAmountFormatted": "$0"
  },
  "repayments": [
    {
      "rd": "15/5/2021",
      "ra": 8116
    }
  ],
  "inputs": {
    "incomeYearOfLoan": 2018,
    "fullTermOfAmalgamatedLoan": 4,
    "incomeYearOfEnquiring": 2021,
    "amalgamatedLoanNotPaidByEOIY": 5936,
    "repayments": null,
    "lodgement_date": null
  },
  "idx": 1358
}