{
  "id": "2023-09-06T18:37:15.816Z0.9775900303226068",
  "alert": "Start of result\nResult\n\nMinimum yearly repayment met.\n\nThe amount of the loan not repaid at the end of income year 2007-08 is $3.17.\n\nThe amalgamated loan will not be taken to be a dividend because the total repayments made are equal to or greater than the minimum yearly repayment required for income year 2007-08.\n\nInterest received by the private company must be included in the income tax return for 2007-08.\n\nMinimum yearly repayment\n\n$44.00\n\nBenchmark interest rate\n\n8.05%\n\nOpening balance:\n\nDate: 30/06/2007\n\nBalance: $147.00\n\nDays: 98\n\nInterest: $3.17\n\nPayments\n\nDate: 07/10/2007\n\nAmount: $147.00\n\nBalance: $0\n\nDays: 268\n\nInterest: $0\n\n\n\n\nTotal repayments\n\n$147.00\n\nTotal interest\n\n$3.17\n\nTotal principal\n\n$143.83\n\nClosing balance\n\nDate: 30/06/2008\n\nBalance: $3.17",
  "outputs": {
    "enquiryRateFormatted": "8.05%",
    "enquiryYearEndMinusOneDisplay": "30/06/2007",
    "amalgamatedLoanNotPaidByEOIYFormatted": "$147.00",
    "openingBalancePayDays": "98",
    "openingBalanceInterestFormatted": "$3.17",
    "totalAmountOfRepaymentFormatted": "$147.00",
    "totalInterestFormatted": "$3.17",
    "principalFormatted": "$143.83",
    "enquiryYearEndDisplay": "30/06/2008",
    "minimumYearRepaymentFormatted": "$44.00"
  },
  "repayments": [
    {
      "rd": "7/10/2007",
      "ra": 147
    }
  ],
  "inputs": {
    "incomeYearOfLoan": 2004,
    "fullTermOfAmalgamatedLoan": 7,
    "incomeYearOfEnquiring": 2008,
    "amalgamatedLoanNotPaidByEOIY": 147,
    "repayments": null,
    "lodgement_date": null
  },
  "idx": 2959
}