{
  "id": "2023-09-06T21:45:40.704Z0.5613096309799701",
  "alert": "Start of result\nResult\n\nMinimum yearly repayment met.\n\nThe amount of the loan not repaid at the end of income year 2003-04 is $3,741.02.\n\nThe amalgamated loan will not be taken to be a dividend because the total repayments made are equal to or greater than the minimum yearly repayment required for income year 2003-04.\n\nInterest received by the private company must be included in the income tax return for 2003-04.\n\nMinimum yearly repayment\n\n$2,018.00\n\nBenchmark interest rate\n\n6.55%\n\nOpening balance:\n\nDate: 30/06/2003\n\nBalance: $9,753.00\n\nDays: 96\n\nInterest: $167.56\n\nPayments\n\nDate: 05/10/2003\n\nAmount: $3,516.00\n\nBalance: $6,237.00\n\nDays: 63\n\nInterest: $70.32\n\n\n\n\nDate: 07/12/2003\n\nAmount: $2,859.00\n\nBalance: $3,378.00\n\nDays: 207\n\nInterest: $125.14\n\n\n\n\nTotal repayments\n\n$6,375.00\n\nTotal interest\n\n$363.02\n\nTotal principal\n\n$6,011.98\n\nClosing balance\n\nDate: 30/06/2004\n\nBalance: $3,741.02",
  "outputs": {
    "enquiryRateFormatted": "6.55%",
    "enquiryYearEndMinusOneDisplay": "30/06/2003",
    "amalgamatedLoanNotPaidByEOIYFormatted": "$9,753.00",
    "openingBalancePayDays": "96",
    "openingBalanceInterestFormatted": "$167.56",
    "totalAmountOfRepaymentFormatted": "$6,375.00",
    "totalInterestFormatted": "$363.02",
    "principalFormatted": "$6,011.98",
    "enquiryYearEndDisplay": "30/06/2004",
    "minimumYearRepaymentFormatted": "$2,018.00"
  },
  "repayments": [
    {
      "rd": "5/10/2003",
      "ra": 3516
    },
    {
      "rd": "7/12/2003",
      "ra": 2859
    }
  ],
  "inputs": {
    "incomeYearOfLoan": 2002,
    "fullTermOfAmalgamatedLoan": 7,
    "incomeYearOfEnquiring": 2004,
    "amalgamatedLoanNotPaidByEOIY": 9753,
    "repayments": null,
    "lodgement_date": null
  },
  "idx": 6664
}