{
  "id": "2023-10-31T18:03:36.796Z0.5830796042398804",
  "alert": "Start of result\nResult\n\nMinimum yearly repayment met.\n\nThe amount of the loan not repaid at the end of income year 2015-16 is $3,345.78.\n\n\u000b\n\nThe amalgamated loan will not be taken to be a dividend because the total repayments made are equal to or greater than the minimum yearly repayment required for income year 2015-16.\n\nInterest received by the private company must be included in the income tax return for 2015-16.\n\nMinimum yearly repayment\n\n$3,701.00\n\nBenchmark interest rate\n\n5.45%\n\nOpening balance:\n\nDate: 30/06/2015\n\nBalance: $6,838.00\n\nDays: 125\n\nInterest: $127.28\n\nPayments\n\nDate: 03/11/2015\n\nAmount: $3,731.00\n\nBalance: $3,107.00\n\nDays: 241\n\nInterest: $111.50\n\n\n\n\nTotal repayments\n\n$3,731.00\n\nTotal interest\n\n$238.78\n\nTotal principal\n\n$3,492.22\n\nClosing balance\n\nDate: 30/06/2016\n\nBalance: $3,345.78",
  "outputs": {
    "enquiryRateFormatted": "5.45%",
    "enquiryYearEndMinusOneDisplay": "30/06/2015",
    "amalgamatedLoanNotPaidByEOIYFormatted": "$6,838.00",
    "openingBalancePayDays": "125",
    "openingBalanceInterestFormatted": "$127.28",
    "totalAmountOfRepaymentFormatted": "$3,731.00",
    "totalInterestFormatted": "$238.78",
    "principalFormatted": "$3,492.22",
    "enquiryYearEndDisplay": "30/06/2016",
    "minimumYearRepaymentFormatted": "$3,701.00",
    "loanAmountFormatted": "$3,345.78"
  },
  "repayments": [
    {
      "rd": "3/11/2015",
      "ra": 3731
    }
  ],
  "inputs": {
    "incomeYearOfLoan": 2012,
    "fullTermOfAmalgamatedLoan": 5,
    "incomeYearOfEnquiring": 2016,
    "amalgamatedLoanNotPaidByEOIY": 6838,
    "repayments": null,
    "lodgement_date": null
  },
  "idx": 3226
}