{
  "id": "2023-09-04T21:10:30.153Z0.8055730200129194",
  "alert": "Start of result\nResult\n\nMinimum yearly repayment not met.\n\nThe amount of the loan not repaid at the end of income year 2010-11 is $2,400.39.\n\nThe private company may be taken to pay a dividend under Division 7A to the shareholder or shareholder's associate because the amount repaid during income year 2010-11 in relation to the amalgamated loan is less than the minimum yearly repayment required.\n\nInterest received by the private company must be included in the income tax return for 2010-11.\n\nMinimum yearly repayment\n\n$2,945.00\n\nBenchmark interest rate\n\n7.4%\n\nOpening balance:\n\nDate: 30/06/2010\n\nBalance: $2,742.00\n\nDays: 0\n\nInterest: $0\n\nPayments\n\nDate: 01/07/2010\n\nAmount: $507.00\n\nBalance: $2,235.00\n\nDays: 365\n\nInterest: $165.39\n\n\n\n\nTotal repayments\n\n$507.00\n\nTotal interest\n\n$165.39\n\nTotal principal\n\n$341.61\n\nClosing balance\n\nDate: 30/06/2011\n\nBalance: $2,400.39",
  "outputs": {
    "enquiryRateFormatted": "7.4%",
    "enquiryYearEndMinusOneDisplay": "30/06/2010",
    "amalgamatedLoanNotPaidByEOIYFormatted": "$2,742.00",
    "openingBalancePayDays": "0",
    "openingBalanceInterestFormatted": "$0",
    "totalAmountOfRepaymentFormatted": "$507.00",
    "totalInterestFormatted": "$165.39",
    "principalFormatted": "$341.61",
    "enquiryYearEndDisplay": "30/06/2011",
    "minimumYearRepaymentFormatted": "$2,945.00"
  },
  "repayments": [
    {
      "rd": "1/7/2010",
      "ra": 507
    }
  ],
  "inputs": {
    "incomeYearOfLoan": 2008,
    "fullTermOfAmalgamatedLoan": 3,
    "incomeYearOfEnquiring": 2011,
    "amalgamatedLoanNotPaidByEOIY": 2742,
    "repayments": null,
    "lodgement_date": null
  },
  "idx": 784
}