{
  "id": "2023-09-05T17:09:18.449Z0.04498415381306753",
  "alert": "Start of result\nResult\n\nMinimum yearly repayment met.\n\nThe amount of the loan not repaid at the end of income year 2023-24 is $4,505.55.\n\nThe amalgamated loan will not be taken to be a dividend because the total repayments made are equal to or greater than the minimum yearly repayment required for income year 2023-24.\n\nInterest received by the private company must be included in the income tax return for 2023-24.\n\nMinimum yearly repayment\n\n$5,330.00\n\nBenchmark interest rate\n\n8.27%\n\nOpening balance:\n\nDate: 30/06/2023\n\nBalance: $9,469.00\n\nDays: 284\n\nInterest: $607.64\n\nPayments\n\nDate: 10/04/2024\n\nAmount: $5,642.00\n\nBalance: $3,827.00\n\nDays: 82\n\nInterest: $70.91\n\n\n\n\nTotal repayments\n\n$5,642.00\n\nTotal interest\n\n$678.55\n\nTotal principal\n\n$4,963.45\n\nClosing balance\n\nDate: 30/06/2024\n\nBalance: $4,505.55",
  "outputs": {
    "enquiryRateFormatted": "8.27%",
    "enquiryYearEndMinusOneDisplay": "30/06/2023",
    "amalgamatedLoanNotPaidByEOIYFormatted": "$9,469.00",
    "openingBalancePayDays": "284",
    "openingBalanceInterestFormatted": "$607.64",
    "totalAmountOfRepaymentFormatted": "$5,642.00",
    "totalInterestFormatted": "$678.55",
    "principalFormatted": "$4,963.45",
    "enquiryYearEndDisplay": "30/06/2024",
    "minimumYearRepaymentFormatted": "$5,330.00"
  },
  "repayments": [
    {
      "rd": "10/4/2024",
      "ra": 5642
    }
  ],
  "inputs": {
    "incomeYearOfLoan": 2019,
    "fullTermOfAmalgamatedLoan": 6,
    "incomeYearOfEnquiring": 2024,
    "amalgamatedLoanNotPaidByEOIY": 9469,
    "repayments": null,
    "lodgement_date": null
  },
  "idx": 3327
}