{
  "id": "2023-10-31T19:28:14.880Z0.08352288204645719",
  "alert": "Start of result\nResult\n\nAmalgamated loan fully repaid.\n\nThe amalgamated loan has been paid in full.\u000bThe private company is not taken under Division 7A to pay a dividend to the shareholder or shareholder's associate.\n\nInterest received by the private company must be included in the income tax return for 2004-05.\n\nMinimum yearly repayment\n\n$19.00\n\nBenchmark interest rate\n\n7.05%\n\nOpening balance:\n\nDate: 30/06/2004\n\nBalance: $63.60\n\nDays: 148\n\nInterest: $1.82\n\nPayments\n\nDate: 26/11/2004\n\nAmount: $636.08\n\nBalance: $0\n\nDays: 217\n\nInterest: $0\n\n\n\n\nTotal repayments\n\n$636.08\n\nTotal interest\n\n$1.82\n\nTotal principal\n\n$634.26\n\nClosing balance\n\nDate: 30/06/2005\n\nBalance: $0",
  "outputs": {
    "enquiryRateFormatted": "7.05%",
    "enquiryYearEndMinusOneDisplay": "30/06/2004",
    "amalgamatedLoanNotPaidByEOIYFormatted": "$63.60",
    "openingBalancePayDays": "148",
    "openingBalanceInterestFormatted": "$1.82",
    "totalAmountOfRepaymentFormatted": "$636.08",
    "totalInterestFormatted": "$1.82",
    "principalFormatted": "$634.26",
    "enquiryYearEndDisplay": "30/06/2005",
    "minimumYearRepaymentFormatted": "$19.00",
    "loanAmountFormatted": "$0"
  },
  "repayments": [
    {
      "rd": "26/11/2004",
      "ra": 636.0842460708382
    }
  ],
  "inputs": {
    "incomeYearOfLoan": 2004,
    "fullTermOfAmalgamatedLoan": 4,
    "incomeYearOfEnquiring": 2005,
    "amalgamatedLoanNotPaidByEOIY": 63.608424607083805,
    "repayments": null,
    "lodgement_date": "1/7/2004"
  },
  "idx": 5493
}