{
  "id": "2023-10-31T17:25:26.678Z0.9872257126262746",
  "alert": "Start of result\nResult\n\nAmalgamated loan fully repaid.\n\nThe amalgamated loan has been paid in full.\u000bThe private company is not taken under Division 7A to pay a dividend to the shareholder or shareholder's associate.\n\nInterest received by the private company must be included in the income tax return for 2020-21.\n\nMinimum yearly repayment\n\n$16.00\n\nBenchmark interest rate\n\n4.52%\n\nOpening balance:\n\nDate: 30/06/2020\n\nBalance: $56.58\n\nDays: 263\n\nInterest: $1.84\n\nPayments\n\nDate: 21/03/2021\n\nAmount: $565.89\n\nBalance: $0\n\nDays: 102\n\nInterest: $0\n\n\n\n\nTotal repayments\n\n$565.89\n\nTotal interest\n\n$1.84\n\nTotal principal\n\n$564.05\n\nClosing balance\n\nDate: 30/06/2021\n\nBalance: $0",
  "outputs": {
    "enquiryRateFormatted": "4.52%",
    "enquiryYearEndMinusOneDisplay": "30/06/2020",
    "amalgamatedLoanNotPaidByEOIYFormatted": "$56.58",
    "openingBalancePayDays": "263",
    "openingBalanceInterestFormatted": "$1.84",
    "totalAmountOfRepaymentFormatted": "$565.89",
    "totalInterestFormatted": "$1.84",
    "principalFormatted": "$564.05",
    "enquiryYearEndDisplay": "30/06/2021",
    "minimumYearRepaymentFormatted": "$16.00",
    "loanAmountFormatted": "$0"
  },
  "repayments": [
    {
      "rd": "21/3/2021",
      "ra": 565.8918700126806
    }
  ],
  "inputs": {
    "incomeYearOfLoan": 2018,
    "fullTermOfAmalgamatedLoan": 6,
    "incomeYearOfEnquiring": 2021,
    "amalgamatedLoanNotPaidByEOIY": 56.589187001268066,
    "repayments": null,
    "lodgement_date": null
  },
  "idx": 1434
}