{
  "id": "2023-09-06T01:22:22.401Z0.22657343572009214",
  "alert": "Start of result\nResult\n\nMinimum yearly repayment not met.\n\nThe amount of the loan not repaid at the end of income year 2017-18 is $4,317.32.\n\nThe private company may be taken to pay a dividend under Division 7A to the shareholder or shareholder's associate because the amount repaid during income year 2017-18 in relation to the amalgamated loan is less than the minimum yearly repayment required.\n\nInterest received by the private company must be included in the income tax return for 2017-18.\n\nMinimum yearly repayment\n\n$2,787.00\n\nBenchmark interest rate\n\n5.3%\n\nOpening balance:\n\nDate: 30/06/2017\n\nBalance: $5,160.00\n\nDays: 364\n\nInterest: $272.73\n\nPayments\n\nDate: 30/06/2018\n\nAmount: $1,116.00\n\nBalance: $4,044.00\n\nDays: 1\n\nInterest: $0.59\n\n\n\n\nTotal repayments\n\n$1,116.00\n\nTotal interest\n\n$273.32\n\nTotal principal\n\n$842.68\n\nClosing balance\n\nDate: 30/06/2018\n\nBalance: $4,317.32",
  "outputs": {
    "enquiryRateFormatted": "5.3%",
    "enquiryYearEndMinusOneDisplay": "30/06/2017",
    "amalgamatedLoanNotPaidByEOIYFormatted": "$5,160.00",
    "openingBalancePayDays": "364",
    "openingBalanceInterestFormatted": "$272.73",
    "totalAmountOfRepaymentFormatted": "$1,116.00",
    "totalInterestFormatted": "$273.32",
    "principalFormatted": "$842.68",
    "enquiryYearEndDisplay": "30/06/2018",
    "minimumYearRepaymentFormatted": "$2,787.00"
  },
  "repayments": [
    {
      "rd": "30/6/2018",
      "ra": 1116
    }
  ],
  "inputs": {
    "incomeYearOfLoan": 2014,
    "fullTermOfAmalgamatedLoan": 5,
    "incomeYearOfEnquiring": 2018,
    "amalgamatedLoanNotPaidByEOIY": 5160,
    "repayments": null,
    "lodgement_date": null
  },
  "idx": 6277
}