{
  "id": "2023-09-04T21:27:39.635Z0.14636758930284266",
  "alert": "Start of result\nResult\n\nMinimum yearly repayment not met.\n\nThe amount of the loan not repaid at the end of income year 2011-12 is $32,284,842.62.\n\nThe private company may be taken to pay a dividend under Division 7A to the shareholder or shareholder's associate because the amount repaid during income year 2011-12 in relation to the amalgamated loan is less than the minimum yearly repayment required.\n\nInterest received by the private company must be included in the income tax return for 2011-12.\n\nMinimum yearly repayment\n\n$34,803,060.00\n\nBenchmark interest rate\n\n7.8%\n\nOpening balance:\n\nDate: 30/06/2011\n\nBalance: $32,284,842.62\n\nDays: 366\n\nInterest: $2,518,217.72\n\nTotal repayments\n\n$0\n\nTotal interest\n\n$2,518,217.72\n\nTotal principal\n\n$0\n\nClosing balance\n\nDate: 30/06/2012\n\nBalance: $32,284,842.62",
  "outputs": {
    "enquiryRateFormatted": "7.8%",
    "enquiryYearEndMinusOneDisplay": "30/06/2011",
    "amalgamatedLoanNotPaidByEOIYFormatted": "$32,284,842.62",
    "openingBalancePayDays": "366",
    "openingBalanceInterestFormatted": "$2,518,217.72",
    "totalAmountOfRepaymentFormatted": "$0",
    "totalInterestFormatted": "$2,518,217.72",
    "principalFormatted": "$0",
    "enquiryYearEndDisplay": "30/06/2012",
    "minimumYearRepaymentFormatted": "$34,803,060.00"
  },
  "repayments": [],
  "inputs": {
    "incomeYearOfLoan": 2007,
    "fullTermOfAmalgamatedLoan": 5,
    "incomeYearOfEnquiring": 2012,
    "amalgamatedLoanNotPaidByEOIY": 32284842.629396845,
    "repayments": null,
    "lodgement_date": null
  },
  "idx": 1261
}