{
  "id": "2023-10-31T20:40:09.983Z0.06848202437438011",
  "alert": "Start of result\nResult\n\nAmalgamated loan fully repaid.\n\nThe amalgamated loan has been paid in full.\u000bThe private company is not taken under Division 7A to pay a dividend to the shareholder or shareholder's associate.\n\nInterest received by the private company must be included in the income tax return for 2005-06.\n\nMinimum yearly repayment\n\n$1,245.00\n\nBenchmark interest rate\n\n7.3%\n\nOpening balance:\n\nDate: 30/06/2005\n\nBalance: $1,160.00\n\nDays: 240\n\nInterest: $55.68\n\nPayments\n\nDate: 26/02/2006\n\nAmount: $5,812.00\n\nBalance: $0\n\nDays: 125\n\nInterest: $0\n\n\n\n\nTotal repayments\n\n$5,812.00\n\nTotal interest\n\n$55.68\n\nTotal principal\n\n$5,756.32\n\nClosing balance\n\nDate: 30/06/2006\n\nBalance: $0",
  "outputs": {
    "enquiryRateFormatted": "7.3%",
    "enquiryYearEndMinusOneDisplay": "30/06/2005",
    "amalgamatedLoanNotPaidByEOIYFormatted": "$1,160.00",
    "openingBalancePayDays": "240",
    "openingBalanceInterestFormatted": "$55.68",
    "totalAmountOfRepaymentFormatted": "$5,812.00",
    "totalInterestFormatted": "$55.68",
    "principalFormatted": "$5,756.32",
    "enquiryYearEndDisplay": "30/06/2006",
    "minimumYearRepaymentFormatted": "$1,245.00",
    "loanAmountFormatted": "$0"
  },
  "repayments": [
    {
      "rd": "26/2/2006",
      "ra": 5812
    }
  ],
  "inputs": {
    "incomeYearOfLoan": 2000,
    "fullTermOfAmalgamatedLoan": 6,
    "incomeYearOfEnquiring": 2006,
    "amalgamatedLoanNotPaidByEOIY": 1160,
    "repayments": null,
    "lodgement_date": null
  },
  "idx": 6672
}