{
  "id": "2023-09-06T00:14:16.503Z0.847896051296724",
  "alert": "Start of result\nResult\n\nMinimum yearly repayment met.\n\nThe amount of the loan not repaid at the end of income year 2020-21 is $0.47.\n\nThe amalgamated loan will not be taken to be a dividend because the total repayments made are equal to or greater than the minimum yearly repayment required for income year 2020-21.\n\nInterest received by the private company must be included in the income tax return for 2020-21.\n\nMinimum yearly repayment\n\n$19.00\n\nBenchmark interest rate\n\n4.52%\n\nOpening balance:\n\nDate: 30/06/2020\n\nBalance: $34.81\n\nDays: 110\n\nInterest: $0.47\n\nPayments\n\nDate: 19/10/2020\n\nAmount: $34.81\n\nBalance: $0\n\nDays: 255\n\nInterest: $0\n\n\n\n\nTotal repayments\n\n$34.81\n\nTotal interest\n\n$0.47\n\nTotal principal\n\n$34.34\n\nClosing balance\n\nDate: 30/06/2021\n\nBalance: $0.47",
  "outputs": {
    "enquiryRateFormatted": "4.52%",
    "enquiryYearEndMinusOneDisplay": "30/06/2020",
    "amalgamatedLoanNotPaidByEOIYFormatted": "$34.81",
    "openingBalancePayDays": "110",
    "openingBalanceInterestFormatted": "$0.47",
    "totalAmountOfRepaymentFormatted": "$34.81",
    "totalInterestFormatted": "$0.47",
    "principalFormatted": "$34.34",
    "enquiryYearEndDisplay": "30/06/2021",
    "minimumYearRepaymentFormatted": "$19.00"
  },
  "repayments": [
    {
      "rd": "19/10/2020",
      "ra": 34.81302285930229
    }
  ],
  "inputs": {
    "incomeYearOfLoan": 2015,
    "fullTermOfAmalgamatedLoan": 7,
    "incomeYearOfEnquiring": 2021,
    "amalgamatedLoanNotPaidByEOIY": 34.81302285930231,
    "repayments": null,
    "lodgement_date": null
  },
  "idx": 2225
}