{
  "id": "2023-10-31T19:42:46.441Z0.6052110384707747",
  "alert": "Start of result\nResult\n\nAmalgamated loan fully repaid.\n\nThe amalgamated loan has been paid in full.\u000bThe private company is not taken under Division 7A to pay a dividend to the shareholder or shareholder's associate.\n\nInterest received by the private company must be included in the income tax return for 2004-05.\n\nMinimum yearly repayment\n\n$4.00\n\nBenchmark interest rate\n\n7.05%\n\nOpening balance:\n\nDate: 30/06/2004\n\nBalance: $14.75\n\nDays: 38\n\nInterest: $0.11\n\nPayments\n\nDate: 08/08/2004\n\nAmount: $147.54\n\nBalance: $0\n\nDays: 327\n\nInterest: $0\n\n\n\n\nTotal repayments\n\n$147.54\n\nTotal interest\n\n$0.11\n\nTotal principal\n\n$147.43\n\nClosing balance\n\nDate: 30/06/2005\n\nBalance: $0",
  "outputs": {
    "enquiryRateFormatted": "7.05%",
    "enquiryYearEndMinusOneDisplay": "30/06/2004",
    "amalgamatedLoanNotPaidByEOIYFormatted": "$14.75",
    "openingBalancePayDays": "38",
    "openingBalanceInterestFormatted": "$0.11",
    "totalAmountOfRepaymentFormatted": "$147.54",
    "totalInterestFormatted": "$0.11",
    "principalFormatted": "$147.43",
    "enquiryYearEndDisplay": "30/06/2005",
    "minimumYearRepaymentFormatted": "$4.00",
    "loanAmountFormatted": "$0"
  },
  "repayments": [
    {
      "rd": "8/8/2004",
      "ra": 147.5417202917124
    }
  ],
  "inputs": {
    "incomeYearOfLoan": 2003,
    "fullTermOfAmalgamatedLoan": 5,
    "incomeYearOfEnquiring": 2005,
    "amalgamatedLoanNotPaidByEOIY": 14.754172029171254,
    "repayments": null,
    "lodgement_date": null
  },
  "idx": 5766
}