{
  "id": "2023-09-04T20:55:56.319Z0.6476562270436255",
  "alert": "Start of result\nResult\n\nMinimum yearly repayment not met.\n\nThe amount of the loan not repaid at the end of income year 2010-11 is $43,833,858.65.\n\nThe private company may be taken to pay a dividend under Division 7A to the shareholder or shareholder's associate because the amount repaid during income year 2010-11 in relation to the amalgamated loan is less than the minimum yearly repayment required.\n\nInterest received by the private company must be included in the income tax return for 2010-11.\n\nMinimum yearly repayment\n\n$13,058,041.00\n\nBenchmark interest rate\n\n7.4%\n\nOpening balance:\n\nDate: 30/06/2010\n\nBalance: $43,833,858.65\n\nDays: 365\n\nInterest: $3,243,705.54\n\nTotal repayments\n\n$0\n\nTotal interest\n\n$3,243,705.54\n\nTotal principal\n\n$0\n\nClosing balance\n\nDate: 30/06/2011\n\nBalance: $43,833,858.65",
  "outputs": {
    "enquiryRateFormatted": "7.4%",
    "enquiryYearEndMinusOneDisplay": "30/06/2010",
    "amalgamatedLoanNotPaidByEOIYFormatted": "$43,833,858.65",
    "openingBalancePayDays": "365",
    "openingBalanceInterestFormatted": "$3,243,705.54",
    "totalAmountOfRepaymentFormatted": "$0",
    "totalInterestFormatted": "$3,243,705.54",
    "principalFormatted": "$0",
    "enquiryYearEndDisplay": "30/06/2011",
    "minimumYearRepaymentFormatted": "$13,058,041.00"
  },
  "repayments": [],
  "inputs": {
    "incomeYearOfLoan": 2010,
    "fullTermOfAmalgamatedLoan": 4,
    "incomeYearOfEnquiring": 2011,
    "amalgamatedLoanNotPaidByEOIY": 43833858.650511585,
    "repayments": null,
    "lodgement_date": "27/4/2011"
  },
  "idx": 326
}