{
  "id": "2023-10-31T18:21:57.336Z0.6840122586885132",
  "alert": "Start of result\nResult\n\nAmalgamated loan fully repaid.\n\nThe amalgamated loan has been paid in full.\u000bThe private company is not taken under Division 7A to pay a dividend to the shareholder or shareholder's associate.\n\nInterest received by the private company must be included in the income tax return for 2011-12.\n\nMinimum yearly repayment\n\n$0\n\nBenchmark interest rate\n\n7.8%\n\nOpening balance:\n\nDate: 30/06/2011\n\nBalance: $1.04\n\nDays: 252\n\nInterest: $0.06\n\nPayments\n\nDate: 09/03/2012\n\nAmount: $10.40\n\nBalance: $0\n\nDays: 114\n\nInterest: $0\n\n\n\n\nTotal repayments\n\n$10.40\n\nTotal interest\n\n$0.06\n\nTotal principal\n\n$10.34\n\nClosing balance\n\nDate: 30/06/2012\n\nBalance: $0",
  "outputs": {
    "enquiryRateFormatted": "7.8%",
    "enquiryYearEndMinusOneDisplay": "30/06/2011",
    "amalgamatedLoanNotPaidByEOIYFormatted": "$1.04",
    "openingBalancePayDays": "252",
    "openingBalanceInterestFormatted": "$0.06",
    "totalAmountOfRepaymentFormatted": "$10.40",
    "totalInterestFormatted": "$0.06",
    "principalFormatted": "$10.34",
    "enquiryYearEndDisplay": "30/06/2012",
    "minimumYearRepaymentFormatted": "$0",
    "loanAmountFormatted": "$0"
  },
  "repayments": [
    {
      "rd": "9/3/2012",
      "ra": 10.405748720961583
    }
  ],
  "inputs": {
    "incomeYearOfLoan": 2010,
    "fullTermOfAmalgamatedLoan": 5,
    "incomeYearOfEnquiring": 2012,
    "amalgamatedLoanNotPaidByEOIY": 1.0405748720961712,
    "repayments": null,
    "lodgement_date": null
  },
  "idx": 3851
}