{
  "id": "2023-10-31T20:12:30.523Z0.0021970115064436913",
  "alert": "Start of result\nResult\n\nMinimum yearly repayment not met.\n\nThe amount of the loan not repaid at the end of income year 2003-04 is $5,430.81.\n\nThe private company may be taken to pay a dividend under Division 7A to the shareholder or shareholder's associate because the amount repaid during income year 2003-04 in relation to the amalgamated loan is less than the minimum yearly repayment required.\n\nInterest received by the private company must be included in the income tax return for 2003-04.\n\nMinimum yearly repayment\n\n$12,839.00\n\nBenchmark interest rate\n\n6.55%\n\nOpening balance:\n\nDate: 30/06/2003\n\nBalance: $12,050.00\n\nDays: 109\n\nInterest: $235.06\n\nPayments\n\nDate: 18/10/2003\n\nAmount: $6,851.00\n\nBalance: $5,199.00\n\nDays: 82\n\nInterest: $76.29\n\n\n\n\nDate: 08/01/2004\n\nAmount: $235.00\n\nBalance: $4,964.00\n\nDays: 175\n\nInterest: $155.46\n\n\n\n\nTotal repayments\n\n$7,086.00\n\nTotal interest\n\n$466.81\n\nTotal principal\n\n$6,619.19\n\nClosing balance\n\nDate: 30/06/2004\n\nBalance: $5,430.81",
  "outputs": {
    "enquiryRateFormatted": "6.55%",
    "enquiryYearEndMinusOneDisplay": "30/06/2003",
    "amalgamatedLoanNotPaidByEOIYFormatted": "$12,050.00",
    "openingBalancePayDays": "109",
    "openingBalanceInterestFormatted": "$235.06",
    "totalAmountOfRepaymentFormatted": "$7,086.00",
    "totalInterestFormatted": "$466.81",
    "principalFormatted": "$6,619.19",
    "enquiryYearEndDisplay": "30/06/2004",
    "minimumYearRepaymentFormatted": "$12,839.00",
    "loanAmountFormatted": "$5,430.81"
  },
  "repayments": [
    {
      "rd": "18/10/2003",
      "ra": 6851
    },
    {
      "rd": "8/1/2004",
      "ra": 235
    }
  ],
  "inputs": {
    "incomeYearOfLoan": 2001,
    "fullTermOfAmalgamatedLoan": 3,
    "incomeYearOfEnquiring": 2004,
    "amalgamatedLoanNotPaidByEOIY": 12050,
    "repayments": null,
    "lodgement_date": null
  },
  "idx": 6268
}