{
  "id": "2023-10-31T20:03:27.813Z0.8965096552947565",
  "alert": "Start of result\nResult\n\nMinimum yearly repayment not met.\n\nThe amount of the loan not repaid at the end of income year 2005-06 is $55.34.\n\nThe private company may be taken to pay a dividend under Division 7A to the shareholder or shareholder's associate because the amount repaid during income year 2005-06 in relation to the amalgamated loan is less than the minimum yearly repayment required.\n\nInterest received by the private company must be included in the income tax return for 2005-06.\n\nMinimum yearly repayment\n\n$21.00\n\nBenchmark interest rate\n\n7.3%\n\nOpening balance:\n\nDate: 30/06/2005\n\nBalance: $55.34\n\nDays: 365\n\nInterest: $4.04\n\nTotal repayments\n\n$0\n\nTotal interest\n\n$4.04\n\nTotal principal\n\n$0\n\nClosing balance\n\nDate: 30/06/2006\n\nBalance: $55.34",
  "outputs": {
    "enquiryRateFormatted": "7.3%",
    "enquiryYearEndMinusOneDisplay": "30/06/2005",
    "amalgamatedLoanNotPaidByEOIYFormatted": "$55.34",
    "openingBalancePayDays": "365",
    "openingBalanceInterestFormatted": "$4.04",
    "totalAmountOfRepaymentFormatted": "$0",
    "totalInterestFormatted": "$4.04",
    "principalFormatted": "$0",
    "enquiryYearEndDisplay": "30/06/2006",
    "minimumYearRepaymentFormatted": "$21.00",
    "loanAmountFormatted": "$55.34"
  },
  "repayments": [],
  "inputs": {
    "incomeYearOfLoan": 2002,
    "fullTermOfAmalgamatedLoan": 6,
    "incomeYearOfEnquiring": 2006,
    "amalgamatedLoanNotPaidByEOIY": 55.347369569628356,
    "repayments": null,
    "lodgement_date": null
  },
  "idx": 6125
}