{
  "id": "2023-10-31T18:04:34.586Z0.611662653597485",
  "alert": "Start of result\nResult\n\nMinimum yearly repayment met.\n\nThe amount of the loan not repaid at the end of income year 2012-13 is $3,058.90.\n\n\u000b\n\nThe amalgamated loan will not be taken to be a dividend because the total repayments made are equal to or greater than the minimum yearly repayment required for income year 2012-13.\n\nInterest received by the private company must be included in the income tax return for 2012-13.\n\nMinimum yearly repayment\n\n$656.00\n\nBenchmark interest rate\n\n7.05%\n\nOpening balance:\n\nDate: 30/06/2012\n\nBalance: $5,507.00\n\nDays: 335\n\nInterest: $356.33\n\nPayments\n\nDate: 01/06/2013\n\nAmount: $2,820.00\n\nBalance: $2,687.00\n\nDays: 30\n\nInterest: $15.57\n\n\n\n\nTotal repayments\n\n$2,820.00\n\nTotal interest\n\n$371.90\n\nTotal principal\n\n$2,448.10\n\nClosing balance\n\nDate: 30/06/2013\n\nBalance: $3,058.90",
  "outputs": {
    "enquiryRateFormatted": "7.05%",
    "enquiryYearEndMinusOneDisplay": "30/06/2012",
    "amalgamatedLoanNotPaidByEOIYFormatted": "$5,507.00",
    "openingBalancePayDays": "335",
    "openingBalanceInterestFormatted": "$356.33",
    "totalAmountOfRepaymentFormatted": "$2,820.00",
    "totalInterestFormatted": "$371.90",
    "principalFormatted": "$2,448.10",
    "enquiryYearEndDisplay": "30/06/2013",
    "minimumYearRepaymentFormatted": "$656.00",
    "loanAmountFormatted": "$3,058.90"
  },
  "repayments": [
    {
      "rd": "1/6/2013",
      "ra": 2820
    }
  ],
  "inputs": {
    "incomeYearOfLoan": 2012,
    "fullTermOfAmalgamatedLoan": 5,
    "incomeYearOfEnquiring": 2013,
    "amalgamatedLoanNotPaidByEOIY": 5507,
    "repayments": null,
    "lodgement_date": "30/6/2013"
  },
  "idx": 3262
}