{
  "id": "2023-09-04T22:02:01.367Z0.6369623280787047",
  "alert": "Start of result\nResult\n\nAmalgamated loan fully repaid.\n\nThe amalgamated loan has been paid in full.\u000bThe private company is not taken under Division 7A to pay a dividend to the shareholder or shareholder's associate.\n\nInterest received by the private company must be included in the income tax return for 2007-08.\n\nMinimum yearly repayment\n\n$7,385.00\n\nBenchmark interest rate\n\n8.05%\n\nOpening balance:\n\nDate: 30/06/2007\n\nBalance: $6,835.00\n\nDays: 0\n\nInterest: $0\n\nPayments\n\nDate: 01/07/2007\n\nAmount: $6,835.00\n\nBalance: $0\n\nDays: 366\n\nInterest: $0\n\n\n\n\nTotal repayments\n\n$6,835.00\n\nTotal interest\n\n$0\n\nTotal principal\n\n$6,835.00\n\nClosing balance\n\nDate: 30/06/2008\n\nBalance: $0",
  "outputs": {
    "enquiryRateFormatted": "8.05%",
    "enquiryYearEndMinusOneDisplay": "30/06/2007",
    "amalgamatedLoanNotPaidByEOIYFormatted": "$6,835.00",
    "openingBalancePayDays": "0",
    "openingBalanceInterestFormatted": "$0",
    "totalAmountOfRepaymentFormatted": "$6,835.00",
    "totalInterestFormatted": "$0",
    "principalFormatted": "$6,835.00",
    "enquiryYearEndDisplay": "30/06/2008",
    "minimumYearRepaymentFormatted": "$7,385.00"
  },
  "repayments": [
    {
      "rd": "1/7/2007",
      "ra": 6835
    }
  ],
  "inputs": {
    "incomeYearOfLoan": 2004,
    "fullTermOfAmalgamatedLoan": 4,
    "incomeYearOfEnquiring": 2008,
    "amalgamatedLoanNotPaidByEOIY": 6835,
    "repayments": null,
    "lodgement_date": null
  },
  "idx": 45
}