{
  "id": "2023-10-31T20:12:28.210Z0.04960553429710424",
  "alert": "Start of result\nResult\n\nMinimum yearly repayment not met.\n\nThe amount of the loan not repaid at the end of income year 2003-04 is $5,673.18.\n\nThe private company may be taken to pay a dividend under Division 7A to the shareholder or shareholder's associate because the amount repaid during income year 2003-04 in relation to the amalgamated loan is less than the minimum yearly repayment required.\n\nInterest received by the private company must be included in the income tax return for 2003-04.\n\nMinimum yearly repayment\n\n$12,839.00\n\nBenchmark interest rate\n\n6.55%\n\nOpening balance:\n\nDate: 30/06/2003\n\nBalance: $12,050.00\n\nDays: 109\n\nInterest: $235.06\n\nPayments\n\nDate: 18/10/2003\n\nAmount: $6,851.00\n\nBalance: $5,199.00\n\nDays: 257\n\nInterest: $239.12\n\n\n\n\nTotal repayments\n\n$6,851.00\n\nTotal interest\n\n$474.18\n\nTotal principal\n\n$6,376.82\n\nClosing balance\n\nDate: 30/06/2004\n\nBalance: $5,673.18",
  "outputs": {
    "enquiryRateFormatted": "6.55%",
    "enquiryYearEndMinusOneDisplay": "30/06/2003",
    "amalgamatedLoanNotPaidByEOIYFormatted": "$12,050.00",
    "openingBalancePayDays": "109",
    "openingBalanceInterestFormatted": "$235.06",
    "totalAmountOfRepaymentFormatted": "$6,851.00",
    "totalInterestFormatted": "$474.18",
    "principalFormatted": "$6,376.82",
    "enquiryYearEndDisplay": "30/06/2004",
    "minimumYearRepaymentFormatted": "$12,839.00",
    "loanAmountFormatted": "$5,673.18"
  },
  "repayments": [
    {
      "rd": "18/10/2003",
      "ra": 6851
    }
  ],
  "inputs": {
    "incomeYearOfLoan": 2001,
    "fullTermOfAmalgamatedLoan": 3,
    "incomeYearOfEnquiring": 2004,
    "amalgamatedLoanNotPaidByEOIY": 12050,
    "repayments": null,
    "lodgement_date": null
  },
  "idx": 6267
}