{
  "id": "2023-09-04T20:50:06.332Z0.90601586503672",
  "alert": "Start of result\nResult\n\nMinimum yearly repayment not met.\n\nThe amount of the loan not repaid at the end of income year 2011-12 is $107,527,463.15.\n\nThe private company may be taken to pay a dividend under Division 7A to the shareholder or shareholder's associate because the amount repaid during income year 2011-12 in relation to the amalgamated loan is less than the minimum yearly repayment required.\n\nInterest received by the private company must be included in the income tax return for 2011-12.\n\nMinimum yearly repayment\n\n$41,571,986.00\n\nBenchmark interest rate\n\n7.8%\n\nOpening balance:\n\nDate: 30/06/2011\n\nBalance: $107,527,463.15\n\nDays: 0\n\nInterest: $0\n\nPayments\n\nDate: 01/07/2011\n\nAmount: $4,615.00\n\nBalance: $107,522,848.15\n\nDays: 366\n\nInterest: $8,386,782.16\n\n\n\n\nTotal repayments\n\n$4,615.00\n\nTotal interest\n\n$8,386,782.16\n\nTotal principal\n\n$0\n\nClosing balance\n\nDate: 30/06/2012\n\nBalance: $107,527,463.15",
  "outputs": {
    "enquiryRateFormatted": "7.8%",
    "enquiryYearEndMinusOneDisplay": "30/06/2011",
    "amalgamatedLoanNotPaidByEOIYFormatted": "$107,527,463.15",
    "openingBalancePayDays": "0",
    "openingBalanceInterestFormatted": "$0",
    "totalAmountOfRepaymentFormatted": "$4,615.00",
    "totalInterestFormatted": "$8,386,782.16",
    "principalFormatted": "$0",
    "enquiryYearEndDisplay": "30/06/2012",
    "minimumYearRepaymentFormatted": "$41,571,986.00"
  },
  "repayments": [
    {
      "rd": "1/7/2011",
      "ra": 4615
    }
  ],
  "inputs": {
    "incomeYearOfLoan": 2011,
    "fullTermOfAmalgamatedLoan": 3,
    "incomeYearOfEnquiring": 2012,
    "amalgamatedLoanNotPaidByEOIY": 107527463.15546964,
    "repayments": null,
    "lodgement_date": "26/4/2012"
  },
  "idx": 115
}