{
  "id": "2023-09-05T16:30:27.668Z0.2060810383294036",
  "alert": "Start of result\nResult\n\nMinimum yearly repayment met.\n\nThe amount of the loan not repaid at the end of income year 2020-21 is $342.80.\n\nThe amalgamated loan will not be taken to be a dividend because the total repayments made are equal to or greater than the minimum yearly repayment required for income year 2020-21.\n\nInterest received by the private company must be included in the income tax return for 2020-21.\n\nMinimum yearly repayment\n\n$4,085.00\n\nBenchmark interest rate\n\n4.52%\n\nOpening balance:\n\nDate: 30/06/2020\n\nBalance: $7,647.00\n\nDays: 362\n\nInterest: $342.80\n\nPayments\n\nDate: 28/06/2021\n\nAmount: $7,647.00\n\nBalance: $0\n\nDays: 3\n\nInterest: $0\n\n\n\n\nTotal repayments\n\n$7,647.00\n\nTotal interest\n\n$342.80\n\nTotal principal\n\n$7,304.20\n\nClosing balance\n\nDate: 30/06/2021\n\nBalance: $342.80",
  "outputs": {
    "enquiryRateFormatted": "4.52%",
    "enquiryYearEndMinusOneDisplay": "30/06/2020",
    "amalgamatedLoanNotPaidByEOIYFormatted": "$7,647.00",
    "openingBalancePayDays": "362",
    "openingBalanceInterestFormatted": "$342.80",
    "totalAmountOfRepaymentFormatted": "$7,647.00",
    "totalInterestFormatted": "$342.80",
    "principalFormatted": "$7,304.20",
    "enquiryYearEndDisplay": "30/06/2021",
    "minimumYearRepaymentFormatted": "$4,085.00"
  },
  "repayments": [
    {
      "rd": "28/6/2021",
      "ra": 7647
    }
  ],
  "inputs": {
    "incomeYearOfLoan": 2019,
    "fullTermOfAmalgamatedLoan": 3,
    "incomeYearOfEnquiring": 2021,
    "amalgamatedLoanNotPaidByEOIY": 7647,
    "repayments": null,
    "lodgement_date": null
  },
  "idx": 740
}