{
  "id": "2023-10-31T19:05:24.258Z0.8138223585443062",
  "alert": "Start of result\nResult\n\nMinimum yearly repayment met.\n\nThe amount of the loan not repaid at the end of income year 2007-08 is $1,399.16.\n\n\u000b\n\nThe amalgamated loan will not be taken to be a dividend because the total repayments made are equal to or greater than the minimum yearly repayment required for income year 2007-08.\n\nInterest received by the private company must be included in the income tax return for 2007-08.\n\nMinimum yearly repayment\n\n$718.00\n\nBenchmark interest rate\n\n8.05%\n\nOpening balance:\n\nDate: 30/06/2007\n\nBalance: $2,374.00\n\nDays: 67\n\nInterest: $34.98\n\nPayments\n\nDate: 06/09/2007\n\nAmount: $1,094.00\n\nBalance: $1,280.00\n\nDays: 299\n\nInterest: $84.18\n\n\n\n\nTotal repayments\n\n$1,094.00\n\nTotal interest\n\n$119.16\n\nTotal principal\n\n$974.84\n\nClosing balance\n\nDate: 30/06/2008\n\nBalance: $1,399.16",
  "outputs": {
    "enquiryRateFormatted": "8.05%",
    "enquiryYearEndMinusOneDisplay": "30/06/2007",
    "amalgamatedLoanNotPaidByEOIYFormatted": "$2,374.00",
    "openingBalancePayDays": "67",
    "openingBalanceInterestFormatted": "$34.98",
    "totalAmountOfRepaymentFormatted": "$1,094.00",
    "totalInterestFormatted": "$119.16",
    "principalFormatted": "$974.84",
    "enquiryYearEndDisplay": "30/06/2008",
    "minimumYearRepaymentFormatted": "$718.00",
    "loanAmountFormatted": "$1,399.16"
  },
  "repayments": [
    {
      "rd": "6/9/2007",
      "ra": 1094
    }
  ],
  "inputs": {
    "incomeYearOfLoan": 2006,
    "fullTermOfAmalgamatedLoan": 5,
    "incomeYearOfEnquiring": 2008,
    "amalgamatedLoanNotPaidByEOIY": 2374,
    "repayments": null,
    "lodgement_date": null
  },
  "idx": 5000
}