{
  "id": "2023-09-07T01:18:12.918Z0.05063969019466197",
  "alert": "Start of result\nResult\n\nMinimum yearly repayment not met.\n\nThe amount of the loan not repaid at the end of income year 1999-00 is $7,291.74.\n\nThe private company may be taken to pay a dividend under Division 7A to the shareholder or shareholder's associate because the amount repaid during income year 1999-00 in relation to the amalgamated loan is less than the minimum yearly repayment required.\n\nInterest received by the private company must be included in the income tax return for 1999-00.\n\nMinimum yearly repayment\n\n$11,876.00\n\nBenchmark interest rate\n\n6.5%\n\nOpening balance:\n\nDate: 30/06/1999\n\nBalance: $11,151.00\n\nDays: 361\n\nInterest: $714.91\n\nPayments\n\nDate: 26/06/2000\n\nAmount: $4,580.00\n\nBalance: $6,571.00\n\nDays: 5\n\nInterest: $5.83\n\n\n\n\nTotal repayments\n\n$4,580.00\n\nTotal interest\n\n$720.74\n\nTotal principal\n\n$3,859.26\n\nClosing balance\n\nDate: 30/06/2000\n\nBalance: $7,291.74",
  "outputs": {
    "enquiryRateFormatted": "6.5%",
    "enquiryYearEndMinusOneDisplay": "30/06/1999",
    "amalgamatedLoanNotPaidByEOIYFormatted": "$11,151.00",
    "openingBalancePayDays": "361",
    "openingBalanceInterestFormatted": "$714.91",
    "totalAmountOfRepaymentFormatted": "$4,580.00",
    "totalInterestFormatted": "$720.74",
    "principalFormatted": "$3,859.26",
    "enquiryYearEndDisplay": "30/06/2000",
    "minimumYearRepaymentFormatted": "$11,876.00"
  },
  "repayments": [
    {
      "rd": "26/6/2000",
      "ra": 4580
    }
  ],
  "inputs": {
    "incomeYearOfLoan": 1999,
    "fullTermOfAmalgamatedLoan": 1,
    "incomeYearOfEnquiring": 2000,
    "amalgamatedLoanNotPaidByEOIY": 11151,
    "repayments": null,
    "lodgement_date": "23/11/1999"
  },
  "idx": 512
}