{
  "id": "2023-09-05T09:46:53.194Z0.20582962897249724",
  "alert": "Start of result\nResult\n\nMinimum yearly repayment not met.\n\nThe amount of the loan not repaid at the end of income year 2023-24 is $1.87.\n\nThe private company may be taken to pay a dividend under Division 7A to the shareholder or shareholder's associate because the amount repaid during income year 2023-24 in relation to the amalgamated loan is less than the minimum yearly repayment required.\n\nInterest received by the private company must be included in the income tax return for 2023-24.\n\nMinimum yearly repayment\n\n$53.00\n\nBenchmark interest rate\n\n8.27%\n\nOpening balance:\n\nDate: 30/06/2023\n\nBalance: $49.36\n\nDays: 168\n\nInterest: $1.87\n\nPayments\n\nDate: 16/12/2023\n\nAmount: $49.36\n\nBalance: $0\n\nDays: 198\n\nInterest: $0\n\n\n\n\nTotal repayments\n\n$49.36\n\nTotal interest\n\n$1.87\n\nTotal principal\n\n$47.49\n\nClosing balance\n\nDate: 30/06/2024\n\nBalance: $1.87",
  "outputs": {
    "enquiryRateFormatted": "8.27%",
    "enquiryYearEndMinusOneDisplay": "30/06/2023",
    "amalgamatedLoanNotPaidByEOIYFormatted": "$49.36",
    "openingBalancePayDays": "168",
    "openingBalanceInterestFormatted": "$1.87",
    "totalAmountOfRepaymentFormatted": "$49.36",
    "totalInterestFormatted": "$1.87",
    "principalFormatted": "$47.49",
    "enquiryYearEndDisplay": "30/06/2024",
    "minimumYearRepaymentFormatted": "$53.00"
  },
  "repayments": [
    {
      "rd": "16/12/2023",
      "ra": 49.36600597377878
    }
  ],
  "inputs": {
    "incomeYearOfLoan": 2023,
    "fullTermOfAmalgamatedLoan": 1,
    "incomeYearOfEnquiring": 2024,
    "amalgamatedLoanNotPaidByEOIY": 49.36600597377884,
    "repayments": null,
    "lodgement_date": "8/7/2023"
  },
  "idx": 374
}