{
  "id": "2023-09-05T23:13:43.969Z0.04334522961545528",
  "alert": "Start of result\nResult\n\nMinimum yearly repayment not met.\n\nThe amount of the loan not repaid at the end of income year 2017-18 is $285.98.\n\nThe private company may be taken to pay a dividend under Division 7A to the shareholder or shareholder's associate because the amount repaid during income year 2017-18 in relation to the amalgamated loan is less than the minimum yearly repayment required.\n\nInterest received by the private company must be included in the income tax return for 2017-18.\n\nMinimum yearly repayment\n\n$7,354.00\n\nBenchmark interest rate\n\n5.3%\n\nOpening balance:\n\nDate: 30/06/2017\n\nBalance: $6,984.00\n\nDays: 282\n\nInterest: $285.98\n\nPayments\n\nDate: 09/04/2018\n\nAmount: $6,984.00\n\nBalance: $0\n\nDays: 83\n\nInterest: $0\n\n\n\n\nTotal repayments\n\n$6,984.00\n\nTotal interest\n\n$285.98\n\nTotal principal\n\n$6,698.02\n\nClosing balance\n\nDate: 30/06/2018\n\nBalance: $285.98",
  "outputs": {
    "enquiryRateFormatted": "5.3%",
    "enquiryYearEndMinusOneDisplay": "30/06/2017",
    "amalgamatedLoanNotPaidByEOIYFormatted": "$6,984.00",
    "openingBalancePayDays": "282",
    "openingBalanceInterestFormatted": "$285.98",
    "totalAmountOfRepaymentFormatted": "$6,984.00",
    "totalInterestFormatted": "$285.98",
    "principalFormatted": "$6,698.02",
    "enquiryYearEndDisplay": "30/06/2018",
    "minimumYearRepaymentFormatted": "$7,354.00"
  },
  "repayments": [
    {
      "rd": "9/4/2018",
      "ra": 6984
    }
  ],
  "inputs": {
    "incomeYearOfLoan": 2015,
    "fullTermOfAmalgamatedLoan": 3,
    "incomeYearOfEnquiring": 2018,
    "amalgamatedLoanNotPaidByEOIY": 6984,
    "repayments": null,
    "lodgement_date": null
  },
  "idx": 7004
}