{
  "id": "2023-09-05T19:43:19.512Z0.0911450223461523",
  "alert": "Start of result\nResult\n\nMinimum yearly repayment not met.\n\nThe amount of the loan not repaid at the end of income year 2020-21 is $3,125.16.\n\nThe private company may be taken to pay a dividend under Division 7A to the shareholder or shareholder's associate because the amount repaid during income year 2020-21 in relation to the amalgamated loan is less than the minimum yearly repayment required.\n\nInterest received by the private company must be included in the income tax return for 2020-21.\n\nMinimum yearly repayment\n\n$4,870.00\n\nBenchmark interest rate\n\n4.52%\n\nOpening balance:\n\nDate: 30/06/2020\n\nBalance: $4,659.00\n\nDays: 100\n\nInterest: $57.70\n\nPayments\n\nDate: 09/10/2020\n\nAmount: $1,689.00\n\nBalance: $2,970.00\n\nDays: 265\n\nInterest: $97.46\n\n\n\n\nTotal repayments\n\n$1,689.00\n\nTotal interest\n\n$155.16\n\nTotal principal\n\n$1,533.84\n\nClosing balance\n\nDate: 30/06/2021\n\nBalance: $3,125.16",
  "outputs": {
    "enquiryRateFormatted": "4.52%",
    "enquiryYearEndMinusOneDisplay": "30/06/2020",
    "amalgamatedLoanNotPaidByEOIYFormatted": "$4,659.00",
    "openingBalancePayDays": "100",
    "openingBalanceInterestFormatted": "$57.70",
    "totalAmountOfRepaymentFormatted": "$1,689.00",
    "totalInterestFormatted": "$155.16",
    "principalFormatted": "$1,533.84",
    "enquiryYearEndDisplay": "30/06/2021",
    "minimumYearRepaymentFormatted": "$4,870.00"
  },
  "repayments": [
    {
      "rd": "9/10/2020",
      "ra": 1689
    }
  ],
  "inputs": {
    "incomeYearOfLoan": 2017,
    "fullTermOfAmalgamatedLoan": 4,
    "incomeYearOfEnquiring": 2021,
    "amalgamatedLoanNotPaidByEOIY": 4659,
    "repayments": null,
    "lodgement_date": null
  },
  "idx": 3677
}