{
  "id": "2023-09-06T10:04:02.797Z0.6458009737237715",
  "alert": "Start of result\nResult\n\nMinimum yearly repayment not met.\n\nThe amount of the loan not repaid at the end of income year 2014-15 is $3.73.\n\nThe private company may be taken to pay a dividend under Division 7A to the shareholder or shareholder's associate because the amount repaid during income year 2014-15 in relation to the amalgamated loan is less than the minimum yearly repayment required.\n\nInterest received by the private company must be included in the income tax return for 2014-15.\n\nMinimum yearly repayment\n\n$114.00\n\nBenchmark interest rate\n\n5.95%\n\nOpening balance:\n\nDate: 30/06/2014\n\nBalance: $108.04\n\nDays: 212\n\nInterest: $3.73\n\nPayments\n\nDate: 29/01/2015\n\nAmount: $108.04\n\nBalance: $0\n\nDays: 153\n\nInterest: $0\n\n\n\n\nTotal repayments\n\n$108.04\n\nTotal interest\n\n$3.73\n\nTotal principal\n\n$104.31\n\nClosing balance\n\nDate: 30/06/2015\n\nBalance: $3.73",
  "outputs": {
    "enquiryRateFormatted": "5.95%",
    "enquiryYearEndMinusOneDisplay": "30/06/2014",
    "amalgamatedLoanNotPaidByEOIYFormatted": "$108.04",
    "openingBalancePayDays": "212",
    "openingBalanceInterestFormatted": "$3.73",
    "totalAmountOfRepaymentFormatted": "$108.04",
    "totalInterestFormatted": "$3.73",
    "principalFormatted": "$104.31",
    "enquiryYearEndDisplay": "30/06/2015",
    "minimumYearRepaymentFormatted": "$114.00"
  },
  "repayments": [
    {
      "rd": "29/1/2015",
      "ra": 108.04561624476992
    }
  ],
  "inputs": {
    "incomeYearOfLoan": 2009,
    "fullTermOfAmalgamatedLoan": 6,
    "incomeYearOfEnquiring": 2015,
    "amalgamatedLoanNotPaidByEOIY": 108.04561624476956,
    "repayments": null,
    "lodgement_date": null
  },
  "idx": 8485
}