{
  "id": "2023-10-31T18:05:28.606Z0.5390315247401746",
  "alert": "Start of result\nResult\n\nMinimum yearly repayment met.\n\nThe amount of the loan not repaid at the end of income year 2012-13 is $4,884.91.\n\n\u000b\n\nThe amalgamated loan will not be taken to be a dividend because the total repayments made are equal to or greater than the minimum yearly repayment required for income year 2012-13.\n\nInterest received by the private company must be included in the income tax return for 2012-13.\n\nMinimum yearly repayment\n\n$2,263.00\n\nBenchmark interest rate\n\n7.05%\n\nOpening balance:\n\nDate: 30/06/2012\n\nBalance: $10,771.00\n\nDays: 113\n\nInterest: $235.09\n\nPayments\n\nDate: 22/10/2012\n\nAmount: $6,337.00\n\nBalance: $4,434.00\n\nDays: 252\n\nInterest: $215.82\n\n\n\n\nTotal repayments\n\n$6,337.00\n\nTotal interest\n\n$450.91\n\nTotal principal\n\n$5,886.09\n\nClosing balance\n\nDate: 30/06/2013\n\nBalance: $4,884.91",
  "outputs": {
    "enquiryRateFormatted": "7.05%",
    "enquiryYearEndMinusOneDisplay": "30/06/2012",
    "amalgamatedLoanNotPaidByEOIYFormatted": "$10,771.00",
    "openingBalancePayDays": "113",
    "openingBalanceInterestFormatted": "$235.09",
    "totalAmountOfRepaymentFormatted": "$6,337.00",
    "totalInterestFormatted": "$450.91",
    "principalFormatted": "$5,886.09",
    "enquiryYearEndDisplay": "30/06/2013",
    "minimumYearRepaymentFormatted": "$2,263.00",
    "loanAmountFormatted": "$4,884.91"
  },
  "repayments": [
    {
      "rd": "22/10/2012",
      "ra": 6337
    }
  ],
  "inputs": {
    "incomeYearOfLoan": 2012,
    "fullTermOfAmalgamatedLoan": 6,
    "incomeYearOfEnquiring": 2013,
    "amalgamatedLoanNotPaidByEOIY": 10771,
    "repayments": null,
    "lodgement_date": "31/7/2012"
  },
  "idx": 3290
}