{
  "id": "2023-09-07T03:58:49.397Z0.2532996641525378",
  "alert": "Start of result\nResult\n\nMinimum yearly repayment met.\n\nThe amount of the loan not repaid at the end of income year 2000-01 is $6.01.\n\nThe amalgamated loan will not be taken to be a dividend because the total repayments made are equal to or greater than the minimum yearly repayment required for income year 2000-01.\n\nInterest received by the private company must be included in the income tax return for 2000-01.\n\nMinimum yearly repayment\n\n$36.00\n\nBenchmark interest rate\n\n7.8%\n\nOpening balance:\n\nDate: 30/06/2000\n\nBalance: $121.16\n\nDays: 232\n\nInterest: $6.01\n\nPayments\n\nDate: 18/02/2001\n\nAmount: $121.16\n\nBalance: $0\n\nDays: 133\n\nInterest: $0\n\n\n\n\nTotal repayments\n\n$121.16\n\nTotal interest\n\n$6.01\n\nTotal principal\n\n$115.15\n\nClosing balance\n\nDate: 30/06/2001\n\nBalance: $6.01",
  "outputs": {
    "enquiryRateFormatted": "7.8%",
    "enquiryYearEndMinusOneDisplay": "30/06/2000",
    "amalgamatedLoanNotPaidByEOIYFormatted": "$121.16",
    "openingBalancePayDays": "232",
    "openingBalanceInterestFormatted": "$6.01",
    "totalAmountOfRepaymentFormatted": "$121.16",
    "totalInterestFormatted": "$6.01",
    "principalFormatted": "$115.15",
    "enquiryYearEndDisplay": "30/06/2001",
    "minimumYearRepaymentFormatted": "$36.00"
  },
  "repayments": [
    {
      "rd": "18/2/2001",
      "ra": 121.16179687295153
    }
  ],
  "inputs": {
    "incomeYearOfLoan": 1998,
    "fullTermOfAmalgamatedLoan": 6,
    "incomeYearOfEnquiring": 2001,
    "amalgamatedLoanNotPaidByEOIY": 121.16179687295212,
    "repayments": null,
    "lodgement_date": null
  },
  "idx": 2217
}