{
  "id": "2023-10-31T17:17:39.146Z0.13560821292356873",
  "alert": "Start of result\nResult\n\nMinimum yearly repayment not met.\n\nThe amount of the loan not repaid at the end of income year 2023-24 is $122.71.\n\nThe private company may be taken to pay a dividend under Division 7A to the shareholder or shareholder's associate because the amount repaid during income year 2023-24 in relation to the amalgamated loan is less than the minimum yearly repayment required.\n\nInterest received by the private company must be included in the income tax return for 2023-24.\n\nMinimum yearly repayment\n\n$48.00\n\nBenchmark interest rate\n\n8.27%\n\nOpening balance:\n\nDate: 30/06/2023\n\nBalance: $122.71\n\nDays: 366\n\nInterest: $10.15\n\nTotal repayments\n\n$0\n\nTotal interest\n\n$10.15\n\nTotal principal\n\n$0\n\nClosing balance\n\nDate: 30/06/2024\n\nBalance: $122.71",
  "outputs": {
    "enquiryRateFormatted": "8.27%",
    "enquiryYearEndMinusOneDisplay": "30/06/2023",
    "amalgamatedLoanNotPaidByEOIYFormatted": "$122.71",
    "openingBalancePayDays": "366",
    "openingBalanceInterestFormatted": "$10.15",
    "totalAmountOfRepaymentFormatted": "$0",
    "totalInterestFormatted": "$10.15",
    "principalFormatted": "$0",
    "enquiryYearEndDisplay": "30/06/2024",
    "minimumYearRepaymentFormatted": "$48.00",
    "loanAmountFormatted": "$122.71"
  },
  "repayments": [],
  "inputs": {
    "incomeYearOfLoan": 2020,
    "fullTermOfAmalgamatedLoan": 6,
    "incomeYearOfEnquiring": 2024,
    "amalgamatedLoanNotPaidByEOIY": 122.71917704701474,
    "repayments": null,
    "lodgement_date": null
  },
  "idx": 922
}