{
  "id": "2023-10-31T19:09:26.526Z0.37082647560002147",
  "alert": "Start of result\nResult\n\nMinimum yearly repayment not met.\n\nThe amount of the loan not repaid at the end of income year 2007-08 is $54.89.\n\nThe private company may be taken to pay a dividend under Division 7A to the shareholder or shareholder's associate because the amount repaid during income year 2007-08 in relation to the amalgamated loan is less than the minimum yearly repayment required.\n\nInterest received by the private company must be included in the income tax return for 2007-08.\n\nMinimum yearly repayment\n\n$12.00\n\nBenchmark interest rate\n\n8.05%\n\nOpening balance:\n\nDate: 30/06/2007\n\nBalance: $54.89\n\nDays: 366\n\nInterest: $4.42\n\nTotal repayments\n\n$0\n\nTotal interest\n\n$4.42\n\nTotal principal\n\n$0\n\nClosing balance\n\nDate: 30/06/2008\n\nBalance: $54.89",
  "outputs": {
    "enquiryRateFormatted": "8.05%",
    "enquiryYearEndMinusOneDisplay": "30/06/2007",
    "amalgamatedLoanNotPaidByEOIYFormatted": "$54.89",
    "openingBalancePayDays": "366",
    "openingBalanceInterestFormatted": "$4.42",
    "totalAmountOfRepaymentFormatted": "$0",
    "totalInterestFormatted": "$4.42",
    "principalFormatted": "$0",
    "enquiryYearEndDisplay": "30/06/2008",
    "minimumYearRepaymentFormatted": "$12.00",
    "loanAmountFormatted": "$54.89"
  },
  "repayments": [],
  "inputs": {
    "incomeYearOfLoan": 2006,
    "fullTermOfAmalgamatedLoan": 7,
    "incomeYearOfEnquiring": 2008,
    "amalgamatedLoanNotPaidByEOIY": 54.89324573493705,
    "repayments": null,
    "lodgement_date": null
  },
  "idx": 5089
}