{
  "id": "2023-09-04T16:21:00.679Z0.5328578979899357",
  "alert": "Start of result\nResult\n\nMinimum yearly repayment met.\n\nThe amount of the loan not repaid at the end of income year 2021-22 is $3,094.84.\n\nThe amalgamated loan will not be taken to be a dividend because the total repayments made are equal to or greater than the minimum yearly repayment required for income year 2021-22.\n\nInterest received by the private company must be included in the income tax return for 2021-22.\n\nMinimum yearly repayment\n\n$2,385.00\n\nBenchmark interest rate\n\n4.52%\n\nOpening balance:\n\nDate: 30/06/2021\n\nBalance: $12,294.00\n\nDays: 0\n\nInterest: $0\n\nPayments\n\nDate: 01/07/2021\n\nAmount: $9,333.00\n\nBalance: $2,961.00\n\nDays: 365\n\nInterest: $133.84\n\n\n\n\nTotal repayments\n\n$9,333.00\n\nTotal interest\n\n$133.84\n\nTotal principal\n\n$9,199.16\n\nClosing balance\n\nDate: 30/06/2022\n\nBalance: $3,094.84",
  "outputs": {
    "enquiryRateFormatted": "4.52%",
    "enquiryYearEndMinusOneDisplay": "30/06/2021",
    "amalgamatedLoanNotPaidByEOIYFormatted": "$12,294.00",
    "openingBalancePayDays": "0",
    "openingBalanceInterestFormatted": "$0",
    "totalAmountOfRepaymentFormatted": "$9,333.00",
    "totalInterestFormatted": "$133.84",
    "principalFormatted": "$9,199.16",
    "enquiryYearEndDisplay": "30/06/2022",
    "minimumYearRepaymentFormatted": "$2,385.00"
  },
  "repayments": [
    {
      "rd": "1/7/2021",
      "ra": 9333
    }
  ],
  "inputs": {
    "incomeYearOfLoan": 2020,
    "fullTermOfAmalgamatedLoan": 7,
    "incomeYearOfEnquiring": 2022,
    "amalgamatedLoanNotPaidByEOIY": 12294,
    "repayments": null,
    "lodgement_date": null
  },
  "idx": 327
}