{
  "id": "2023-09-04T17:42:50.329Z0.6141072956021552",
  "alert": "Start of result\nResult\n\nMinimum yearly repayment met.\n\nThe amount of the loan not repaid at the end of income year 2013-14 is $6,704.41.\n\nThe amalgamated loan will not be taken to be a dividend because the total repayments made are equal to or greater than the minimum yearly repayment required for income year 2013-14.\n\nInterest received by the private company must be included in the income tax return for 2013-14.\n\nMinimum yearly repayment\n\n$3,566.00\n\nBenchmark interest rate\n\n6.2%\n\nOpening balance:\n\nDate: 30/06/2013\n\nBalance: $12,299.00\n\nDays: 0\n\nInterest: $0\n\nPayments\n\nDate: 01/07/2013\n\nAmount: $5,986.00\n\nBalance: $6,313.00\n\nDays: 365\n\nInterest: $391.41\n\n\n\n\nTotal repayments\n\n$5,986.00\n\nTotal interest\n\n$391.41\n\nTotal principal\n\n$5,594.59\n\nClosing balance\n\nDate: 30/06/2014\n\nBalance: $6,704.41",
  "outputs": {
    "enquiryRateFormatted": "6.2%",
    "enquiryYearEndMinusOneDisplay": "30/06/2013",
    "amalgamatedLoanNotPaidByEOIYFormatted": "$12,299.00",
    "openingBalancePayDays": "0",
    "openingBalanceInterestFormatted": "$0",
    "totalAmountOfRepaymentFormatted": "$5,986.00",
    "totalInterestFormatted": "$391.41",
    "principalFormatted": "$5,594.59",
    "enquiryYearEndDisplay": "30/06/2014",
    "minimumYearRepaymentFormatted": "$3,566.00"
  },
  "repayments": [
    {
      "rd": "1/7/2013",
      "ra": 5986
    }
  ],
  "inputs": {
    "incomeYearOfLoan": 2012,
    "fullTermOfAmalgamatedLoan": 5,
    "incomeYearOfEnquiring": 2014,
    "amalgamatedLoanNotPaidByEOIY": 12299,
    "repayments": null,
    "lodgement_date": null
  },
  "idx": 2497
}