{
  "id": "2023-09-04T21:30:46.810Z0.5265614849937748",
  "alert": "Start of result\nResult\n\nMinimum yearly repayment not met.\n\nThe amount of the loan not repaid at the end of income year 2013-14 is $14,241,090.51.\n\nThe private company may be taken to pay a dividend under Division 7A to the shareholder or shareholder's associate because the amount repaid during income year 2013-14 in relation to the amalgamated loan is less than the minimum yearly repayment required.\n\nInterest received by the private company must be included in the income tax return for 2013-14.\n\nMinimum yearly repayment\n\n$15,124,038.00\n\nBenchmark interest rate\n\n6.2%\n\nOpening balance:\n\nDate: 30/06/2013\n\nBalance: $14,241,090.51\n\nDays: 365\n\nInterest: $882,947.61\n\nTotal repayments\n\n$0\n\nTotal interest\n\n$882,947.61\n\nTotal principal\n\n$0\n\nClosing balance\n\nDate: 30/06/2014\n\nBalance: $14,241,090.51",
  "outputs": {
    "enquiryRateFormatted": "6.2%",
    "enquiryYearEndMinusOneDisplay": "30/06/2013",
    "amalgamatedLoanNotPaidByEOIYFormatted": "$14,241,090.51",
    "openingBalancePayDays": "365",
    "openingBalanceInterestFormatted": "$882,947.61",
    "totalAmountOfRepaymentFormatted": "$0",
    "totalInterestFormatted": "$882,947.61",
    "principalFormatted": "$0",
    "enquiryYearEndDisplay": "30/06/2014",
    "minimumYearRepaymentFormatted": "$15,124,038.00"
  },
  "repayments": [],
  "inputs": {
    "incomeYearOfLoan": 2007,
    "fullTermOfAmalgamatedLoan": 7,
    "incomeYearOfEnquiring": 2014,
    "amalgamatedLoanNotPaidByEOIY": 14241090.512091585,
    "repayments": null,
    "lodgement_date": null
  },
  "idx": 1329
}