{
  "id": "2023-09-05T20:35:43.922Z0.7153772438053132",
  "alert": "Start of result\nResult\n\nMinimum yearly repayment met.\n\nThe amount of the loan not repaid at the end of income year 2022-23 is $0.26.\n\nThe amalgamated loan will not be taken to be a dividend because the total repayments made are equal to or greater than the minimum yearly repayment required for income year 2022-23.\n\nInterest received by the private company must be included in the income tax return for 2022-23.\n\nMinimum yearly repayment\n\n$4.00\n\nBenchmark interest rate\n\n4.77%\n\nOpening balance:\n\nDate: 30/06/2022\n\nBalance: $6.63\n\nDays: 298\n\nInterest: $0.26\n\nPayments\n\nDate: 25/04/2023\n\nAmount: $6.63\n\nBalance: $0\n\nDays: 67\n\nInterest: $0\n\n\n\n\nTotal repayments\n\n$6.63\n\nTotal interest\n\n$0.26\n\nTotal principal\n\n$6.37\n\nClosing balance\n\nDate: 30/06/2023\n\nBalance: $0.26",
  "outputs": {
    "enquiryRateFormatted": "4.77%",
    "enquiryYearEndMinusOneDisplay": "30/06/2022",
    "amalgamatedLoanNotPaidByEOIYFormatted": "$6.63",
    "openingBalancePayDays": "298",
    "openingBalanceInterestFormatted": "$0.26",
    "totalAmountOfRepaymentFormatted": "$6.63",
    "totalInterestFormatted": "$0.26",
    "principalFormatted": "$6.37",
    "enquiryYearEndDisplay": "30/06/2023",
    "minimumYearRepaymentFormatted": "$4.00"
  },
  "repayments": [
    {
      "rd": "25/4/2023",
      "ra": 6.6389306158425825
    }
  ],
  "inputs": {
    "incomeYearOfLoan": 2017,
    "fullTermOfAmalgamatedLoan": 7,
    "incomeYearOfEnquiring": 2023,
    "amalgamatedLoanNotPaidByEOIY": 6.638930615842315,
    "repayments": null,
    "lodgement_date": null
  },
  "idx": 6635
}