{
  "id": "2023-09-07T00:50:11.275Z0.7311938525273189",
  "alert": "Start of result\nResult\n\nMinimum yearly repayment met.\n\nThe amount of the loan not repaid at the end of income year 2002-03 is $1.79.\n\nThe amalgamated loan will not be taken to be a dividend because the total repayments made are equal to or greater than the minimum yearly repayment required for income year 2002-03.\n\nInterest received by the private company must be included in the income tax return for 2002-03.\n\nMinimum yearly repayment\n\n$0\n\nBenchmark interest rate\n\n6.3%\n\nOpening balance:\n\nDate: 30/06/2002\n\nBalance: $1.79\n\nDays: 365\n\nInterest: $0.11\n\nTotal repayments\n\n$0\n\nTotal interest\n\n$0.11\n\nTotal principal\n\n$0\n\nClosing balance\n\nDate: 30/06/2003\n\nBalance: $1.79",
  "outputs": {
    "enquiryRateFormatted": "6.3%",
    "enquiryYearEndMinusOneDisplay": "30/06/2002",
    "amalgamatedLoanNotPaidByEOIYFormatted": "$1.79",
    "openingBalancePayDays": "365",
    "openingBalanceInterestFormatted": "$0.11",
    "totalAmountOfRepaymentFormatted": "$0",
    "totalInterestFormatted": "$0.11",
    "principalFormatted": "$0",
    "enquiryYearEndDisplay": "30/06/2003",
    "minimumYearRepaymentFormatted": "$0"
  },
  "repayments": [],
  "inputs": {
    "incomeYearOfLoan": 2000,
    "fullTermOfAmalgamatedLoan": 7,
    "incomeYearOfEnquiring": 2003,
    "amalgamatedLoanNotPaidByEOIY": 1.7987418200408836,
    "repayments": null,
    "lodgement_date": null
  },
  "idx": 8130
}