{
  "id": "2023-09-07T01:15:48.760Z0.2801841860743297",
  "alert": "Start of result\nResult\n\nMinimum yearly repayment not met.\n\nThe amount of the loan not repaid at the end of income year 1999-00 is $11,151.00.\n\nThe private company may be taken to pay a dividend under Division 7A to the shareholder or shareholder's associate because the amount repaid during income year 1999-00 in relation to the amalgamated loan is less than the minimum yearly repayment required.\n\nInterest received by the private company must be included in the income tax return for 1999-00.\n\nMinimum yearly repayment\n\n$11,876.00\n\nBenchmark interest rate\n\n6.5%\n\nOpening balance:\n\nDate: 30/06/1999\n\nBalance: $11,151.00\n\nDays: 366\n\nInterest: $724.82\n\nTotal repayments\n\n$0\n\nTotal interest\n\n$724.82\n\nTotal principal\n\n$0\n\nClosing balance\n\nDate: 30/06/2000\n\nBalance: $11,151.00",
  "outputs": {
    "enquiryRateFormatted": "6.5%",
    "enquiryYearEndMinusOneDisplay": "30/06/1999",
    "amalgamatedLoanNotPaidByEOIYFormatted": "$11,151.00",
    "openingBalancePayDays": "366",
    "openingBalanceInterestFormatted": "$724.82",
    "totalAmountOfRepaymentFormatted": "$0",
    "totalInterestFormatted": "$724.82",
    "principalFormatted": "$0",
    "enquiryYearEndDisplay": "30/06/2000",
    "minimumYearRepaymentFormatted": "$11,876.00"
  },
  "repayments": [],
  "inputs": {
    "incomeYearOfLoan": 1999,
    "fullTermOfAmalgamatedLoan": 1,
    "incomeYearOfEnquiring": 2000,
    "amalgamatedLoanNotPaidByEOIY": 11151,
    "repayments": null,
    "lodgement_date": "2/6/2000"
  },
  "idx": 337
}