{
  "id": "2023-10-31T17:38:26.460Z0.7603191962807221",
  "alert": "Start of result\nResult\n\nAmalgamated loan fully repaid.\n\nThe amalgamated loan has been paid in full.\u000bThe private company is not taken under Division 7A to pay a dividend to the shareholder or shareholder's associate.\n\nInterest received by the private company must be included in the income tax return for 2015-16.\n\nMinimum yearly repayment\n\n-$26.00\n\nBenchmark interest rate\n\n5.45%\n\nOpening balance:\n\nDate: 30/06/2015\n\nBalance: $68.64\n\nDays: 7\n\nInterest: $0.07\n\nPayments\n\nDate: 08/07/2015\n\nAmount: $93.00\n\nBalance: $0\n\nDays: 359\n\nInterest: $0\n\n\n\n\nTotal repayments\n\n$93.00\n\nTotal interest\n\n$0.07\n\nTotal principal\n\n$92.93\n\nClosing balance\n\nDate: 30/06/2016\n\nBalance: $0",
  "outputs": {
    "enquiryRateFormatted": "5.45%",
    "enquiryYearEndMinusOneDisplay": "30/06/2015",
    "amalgamatedLoanNotPaidByEOIYFormatted": "$68.64",
    "openingBalancePayDays": "7",
    "openingBalanceInterestFormatted": "$0.07",
    "totalAmountOfRepaymentFormatted": "$93.00",
    "totalInterestFormatted": "$0.07",
    "principalFormatted": "$92.93",
    "enquiryYearEndDisplay": "30/06/2016",
    "minimumYearRepaymentFormatted": "-$26.00",
    "loanAmountFormatted": "$0"
  },
  "repayments": [
    {
      "rd": "8/7/2015",
      "ra": 93
    }
  ],
  "inputs": {
    "incomeYearOfLoan": 2015,
    "fullTermOfAmalgamatedLoan": 1,
    "incomeYearOfEnquiring": 2016,
    "amalgamatedLoanNotPaidByEOIY": 68.64144174296477,
    "repayments": null,
    "lodgement_date": "31/7/2015"
  },
  "idx": 2149
}