{
  "id": "2023-09-05T22:33:31.499Z0.650925802000297",
  "alert": "Start of result\nResult\n\nMinimum yearly repayment not met.\n\nThe amount of the loan not repaid at the end of income year 2022-23 is $9,305.21.\n\nThe private company may be taken to pay a dividend under Division 7A to the shareholder or shareholder's associate because the amount repaid during income year 2022-23 in relation to the amalgamated loan is less than the minimum yearly repayment required.\n\nInterest received by the private company must be included in the income tax return for 2022-23.\n\nMinimum yearly repayment\n\n$11,493.00\n\nBenchmark interest rate\n\n4.77%\n\nOpening balance:\n\nDate: 30/06/2022\n\nBalance: $10,970.00\n\nDays: 262\n\nInterest: $375.61\n\nPayments\n\nDate: 20/03/2023\n\nAmount: $2,159.00\n\nBalance: $8,811.00\n\nDays: 103\n\nInterest: $118.60\n\n\n\n\nTotal repayments\n\n$2,159.00\n\nTotal interest\n\n$494.21\n\nTotal principal\n\n$1,664.79\n\nClosing balance\n\nDate: 30/06/2023\n\nBalance: $9,305.21",
  "outputs": {
    "enquiryRateFormatted": "4.77%",
    "enquiryYearEndMinusOneDisplay": "30/06/2022",
    "amalgamatedLoanNotPaidByEOIYFormatted": "$10,970.00",
    "openingBalancePayDays": "262",
    "openingBalanceInterestFormatted": "$375.61",
    "totalAmountOfRepaymentFormatted": "$2,159.00",
    "totalInterestFormatted": "$494.21",
    "principalFormatted": "$1,664.79",
    "enquiryYearEndDisplay": "30/06/2023",
    "minimumYearRepaymentFormatted": "$11,493.00"
  },
  "repayments": [
    {
      "rd": "20/3/2023",
      "ra": 2159
    }
  ],
  "inputs": {
    "incomeYearOfLoan": 2016,
    "fullTermOfAmalgamatedLoan": 7,
    "incomeYearOfEnquiring": 2023,
    "amalgamatedLoanNotPaidByEOIY": 10970,
    "repayments": null,
    "lodgement_date": null
  },
  "idx": 4790
}