{
  "id": "2023-10-31T19:31:30.642Z0.7123290054255539",
  "alert": "Start of result\nResult\n\nAmalgamated loan fully repaid.\n\nThe amalgamated loan has been paid in full.\u000bThe private company is not taken under Division 7A to pay a dividend to the shareholder or shareholder's associate.\n\nInterest received by the private company must be included in the income tax return for 2006-07.\n\nMinimum yearly repayment\n\n$28.00\n\nBenchmark interest rate\n\n7.55%\n\nOpening balance:\n\nDate: 30/06/2006\n\nBalance: $94.27\n\nDays: 340\n\nInterest: $6.63\n\nPayments\n\nDate: 06/06/2007\n\nAmount: $942.72\n\nBalance: $0\n\nDays: 25\n\nInterest: $0\n\n\n\n\nTotal repayments\n\n$942.72\n\nTotal interest\n\n$6.63\n\nTotal principal\n\n$936.09\n\nClosing balance\n\nDate: 30/06/2007\n\nBalance: $0",
  "outputs": {
    "enquiryRateFormatted": "7.55%",
    "enquiryYearEndMinusOneDisplay": "30/06/2006",
    "amalgamatedLoanNotPaidByEOIYFormatted": "$94.27",
    "openingBalancePayDays": "340",
    "openingBalanceInterestFormatted": "$6.63",
    "totalAmountOfRepaymentFormatted": "$942.72",
    "totalInterestFormatted": "$6.63",
    "principalFormatted": "$936.09",
    "enquiryYearEndDisplay": "30/06/2007",
    "minimumYearRepaymentFormatted": "$28.00",
    "loanAmountFormatted": "$0"
  },
  "repayments": [
    {
      "rd": "6/6/2007",
      "ra": 942.7282304172878
    }
  ],
  "inputs": {
    "incomeYearOfLoan": 2004,
    "fullTermOfAmalgamatedLoan": 6,
    "incomeYearOfEnquiring": 2007,
    "amalgamatedLoanNotPaidByEOIY": 94.27282304172878,
    "repayments": null,
    "lodgement_date": null
  },
  "idx": 5557
}