{
  "id": "2023-10-31T18:38:23.504Z0.5741065059581082",
  "alert": "Start of result\nResult\n\nAmalgamated loan fully repaid.\n\nThe amalgamated loan has been paid in full.\u000bThe private company is not taken under Division 7A to pay a dividend to the shareholder or shareholder's associate.\n\nInterest received by the private company must be included in the income tax return for 2009-10.\n\nMinimum yearly repayment\n\n$953.00\n\nBenchmark interest rate\n\n5.75%\n\nOpening balance:\n\nDate: 30/06/2009\n\nBalance: $2,559.00\n\nDays: 175\n\nInterest: $70.55\n\nPayments\n\nDate: 23/12/2009\n\nAmount: $9,501.00\n\nBalance: $0\n\nDays: 190\n\nInterest: $0\n\n\n\n\nTotal repayments\n\n$9,501.00\n\nTotal interest\n\n$70.55\n\nTotal principal\n\n$9,430.45\n\nClosing balance\n\nDate: 30/06/2010\n\nBalance: $0",
  "outputs": {
    "enquiryRateFormatted": "5.75%",
    "enquiryYearEndMinusOneDisplay": "30/06/2009",
    "amalgamatedLoanNotPaidByEOIYFormatted": "$2,559.00",
    "openingBalancePayDays": "175",
    "openingBalanceInterestFormatted": "$70.55",
    "totalAmountOfRepaymentFormatted": "$9,501.00",
    "totalInterestFormatted": "$70.55",
    "principalFormatted": "$9,430.45",
    "enquiryYearEndDisplay": "30/06/2010",
    "minimumYearRepaymentFormatted": "$953.00",
    "loanAmountFormatted": "$0"
  },
  "repayments": [
    {
      "rd": "23/12/2009",
      "ra": 9501
    }
  ],
  "inputs": {
    "incomeYearOfLoan": 2008,
    "fullTermOfAmalgamatedLoan": 4,
    "incomeYearOfEnquiring": 2010,
    "amalgamatedLoanNotPaidByEOIY": 2559,
    "repayments": null,
    "lodgement_date": null
  },
  "idx": 4310
}