{
  "id": "2023-10-31T20:05:41.991Z0.4484817227582537",
  "alert": "Start of result\nResult\n\nAmalgamated loan fully repaid.\n\nThe amalgamated loan has been paid in full.\u000bThe private company is not taken under Division 7A to pay a dividend to the shareholder or shareholder's associate.\n\nInterest received by the private company must be included in the income tax return for 2008-09.\n\nMinimum yearly repayment\n\n$1,723.00\n\nBenchmark interest rate\n\n9.45%\n\nOpening balance:\n\nDate: 30/06/2008\n\nBalance: $1,574.00\n\nDays: 124\n\nInterest: $50.53\n\nPayments\n\nDate: 02/11/2008\n\nAmount: $5,835.00\n\nBalance: $0\n\nDays: 90\n\nInterest: $0\n\n\n\n\nDate: 31/01/2009\n\nAmount: $8,460.00\n\nBalance: $0\n\nDays: 151\n\nInterest: $0\n\n\n\n\nTotal repayments\n\n$14,295.00\n\nTotal interest\n\n$50.53\n\nTotal principal\n\n$14,244.47\n\nClosing balance\n\nDate: 30/06/2009\n\nBalance: $0",
  "outputs": {
    "enquiryRateFormatted": "9.45%",
    "enquiryYearEndMinusOneDisplay": "30/06/2008",
    "amalgamatedLoanNotPaidByEOIYFormatted": "$1,574.00",
    "openingBalancePayDays": "124",
    "openingBalanceInterestFormatted": "$50.53",
    "totalAmountOfRepaymentFormatted": "$14,295.00",
    "totalInterestFormatted": "$50.53",
    "principalFormatted": "$14,244.47",
    "enquiryYearEndDisplay": "30/06/2009",
    "minimumYearRepaymentFormatted": "$1,723.00",
    "loanAmountFormatted": "$0"
  },
  "repayments": [
    {
      "rd": "2/11/2008",
      "ra": 5835
    },
    {
      "rd": "31/1/2009",
      "ra": 8460
    }
  ],
  "inputs": {
    "incomeYearOfLoan": 2002,
    "fullTermOfAmalgamatedLoan": 7,
    "incomeYearOfEnquiring": 2009,
    "amalgamatedLoanNotPaidByEOIY": 1574,
    "repayments": null,
    "lodgement_date": null
  },
  "idx": 6162
}