{
  "id": "2023-09-04T17:21:51.048Z0.7233460061104737",
  "alert": "Start of result\nResult\n\nMinimum yearly repayment not met.\n\nThe amount of the loan not repaid at the end of income year 2015-16 is $52,374,509.54.\n\nThe private company may be taken to pay a dividend under Division 7A to the shareholder or shareholder's associate because the amount repaid during income year 2015-16 in relation to the amalgamated loan is less than the minimum yearly repayment required.\n\nInterest received by the private company must be included in the income tax return for 2015-16.\n\nMinimum yearly repayment\n\n$28,346,993.00\n\nBenchmark interest rate\n\n5.45%\n\nOpening balance:\n\nDate: 30/06/2015\n\nBalance: $52,374,509.54\n\nDays: 366\n\nInterest: $2,854,410.77\n\nTotal repayments\n\n$0\n\nTotal interest\n\n$2,854,410.77\n\nTotal principal\n\n$0\n\nClosing balance\n\nDate: 30/06/2016\n\nBalance: $52,374,509.54",
  "outputs": {
    "enquiryRateFormatted": "5.45%",
    "enquiryYearEndMinusOneDisplay": "30/06/2015",
    "amalgamatedLoanNotPaidByEOIYFormatted": "$52,374,509.54",
    "openingBalancePayDays": "366",
    "openingBalanceInterestFormatted": "$2,854,410.77",
    "totalAmountOfRepaymentFormatted": "$0",
    "totalInterestFormatted": "$2,854,410.77",
    "principalFormatted": "$0",
    "enquiryYearEndDisplay": "30/06/2016",
    "minimumYearRepaymentFormatted": "$28,346,993.00"
  },
  "repayments": [],
  "inputs": {
    "incomeYearOfLoan": 2013,
    "fullTermOfAmalgamatedLoan": 4,
    "incomeYearOfEnquiring": 2016,
    "amalgamatedLoanNotPaidByEOIY": 52374509.54740634,
    "repayments": null,
    "lodgement_date": null
  },
  "idx": 2046
}