{
  "id": "2023-09-04T16:46:40.688Z0.5226185672795516",
  "alert": "Start of result\nResult\n\nMinimum yearly repayment not met.\n\nThe amount of the loan not repaid at the end of income year 2020-21 is $21,698,735.39.\n\nThe private company may be taken to pay a dividend under Division 7A to the shareholder or shareholder's associate because the amount repaid during income year 2020-21 in relation to the amalgamated loan is less than the minimum yearly repayment required.\n\nInterest received by the private company must be included in the income tax return for 2020-21.\n\nMinimum yearly repayment\n\n$7,896,399.00\n\nBenchmark interest rate\n\n4.52%\n\nOpening balance:\n\nDate: 30/06/2020\n\nBalance: $21,698,735.39\n\nDays: 365\n\nInterest: $980,782.84\n\nTotal repayments\n\n$0\n\nTotal interest\n\n$980,782.84\n\nTotal principal\n\n$0\n\nClosing balance\n\nDate: 30/06/2021\n\nBalance: $21,698,735.39",
  "outputs": {
    "enquiryRateFormatted": "4.52%",
    "enquiryYearEndMinusOneDisplay": "30/06/2020",
    "amalgamatedLoanNotPaidByEOIYFormatted": "$21,698,735.39",
    "openingBalancePayDays": "365",
    "openingBalanceInterestFormatted": "$980,782.84",
    "totalAmountOfRepaymentFormatted": "$0",
    "totalInterestFormatted": "$980,782.84",
    "principalFormatted": "$0",
    "enquiryYearEndDisplay": "30/06/2021",
    "minimumYearRepaymentFormatted": "$7,896,399.00"
  },
  "repayments": [],
  "inputs": {
    "incomeYearOfLoan": 2016,
    "fullTermOfAmalgamatedLoan": 7,
    "incomeYearOfEnquiring": 2021,
    "amalgamatedLoanNotPaidByEOIY": 21698735.392697338,
    "repayments": null,
    "lodgement_date": null
  },
  "idx": 1156
}