{
  "id": "2023-09-05T12:11:25.387Z0.7454438026714316",
  "alert": "Start of result\nResult\n\nMinimum yearly repayment not met.\n\nThe amount of the loan not repaid at the end of income year 2022-23 is $78.69.\n\nThe private company may be taken to pay a dividend under Division 7A to the shareholder or shareholder's associate because the amount repaid during income year 2022-23 in relation to the amalgamated loan is less than the minimum yearly repayment required.\n\nInterest received by the private company must be included in the income tax return for 2022-23.\n\nMinimum yearly repayment\n\n$15.00\n\nBenchmark interest rate\n\n4.77%\n\nOpening balance:\n\nDate: 30/06/2022\n\nBalance: $78.69\n\nDays: 365\n\nInterest: $3.75\n\nTotal repayments\n\n$0\n\nTotal interest\n\n$3.75\n\nTotal principal\n\n$0\n\nClosing balance\n\nDate: 30/06/2023\n\nBalance: $78.69",
  "outputs": {
    "enquiryRateFormatted": "4.77%",
    "enquiryYearEndMinusOneDisplay": "30/06/2022",
    "amalgamatedLoanNotPaidByEOIYFormatted": "$78.69",
    "openingBalancePayDays": "365",
    "openingBalanceInterestFormatted": "$3.75",
    "totalAmountOfRepaymentFormatted": "$0",
    "totalInterestFormatted": "$3.75",
    "principalFormatted": "$0",
    "enquiryYearEndDisplay": "30/06/2023",
    "minimumYearRepaymentFormatted": "$15.00"
  },
  "repayments": [],
  "inputs": {
    "incomeYearOfLoan": 2022,
    "fullTermOfAmalgamatedLoan": 6,
    "incomeYearOfEnquiring": 2023,
    "amalgamatedLoanNotPaidByEOIY": 78.69279264997505,
    "repayments": null,
    "lodgement_date": "9/7/2022"
  },
  "idx": 3679
}