{
  "id": "2023-09-06T08:40:59.476Z0.24871414658653368",
  "alert": "Start of result\nResult\n\nMinimum yearly repayment met.\n\nThe amount of the loan not repaid at the end of income year 2011-12 is $12.51.\n\nThe amalgamated loan will not be taken to be a dividend because the total repayments made are equal to or greater than the minimum yearly repayment required for income year 2011-12.\n\nInterest received by the private company must be included in the income tax return for 2011-12.\n\nMinimum yearly repayment\n\n$123.00\n\nBenchmark interest rate\n\n7.8%\n\nOpening balance:\n\nDate: 30/06/2011\n\nBalance: $570.00\n\nDays: 103\n\nInterest: $12.51\n\nPayments\n\nDate: 12/10/2011\n\nAmount: $570.00\n\nBalance: $0\n\nDays: 263\n\nInterest: $0\n\n\n\n\nTotal repayments\n\n$570.00\n\nTotal interest\n\n$12.51\n\nTotal principal\n\n$557.49\n\nClosing balance\n\nDate: 30/06/2012\n\nBalance: $12.51",
  "outputs": {
    "enquiryRateFormatted": "7.8%",
    "enquiryYearEndMinusOneDisplay": "30/06/2011",
    "amalgamatedLoanNotPaidByEOIYFormatted": "$570.00",
    "openingBalancePayDays": "103",
    "openingBalanceInterestFormatted": "$12.51",
    "totalAmountOfRepaymentFormatted": "$570.00",
    "totalInterestFormatted": "$12.51",
    "principalFormatted": "$557.49",
    "enquiryYearEndDisplay": "30/06/2012",
    "minimumYearRepaymentFormatted": "$123.00"
  },
  "repayments": [
    {
      "rd": "12/10/2011",
      "ra": 570
    }
  ],
  "inputs": {
    "incomeYearOfLoan": 2010,
    "fullTermOfAmalgamatedLoan": 7,
    "incomeYearOfEnquiring": 2012,
    "amalgamatedLoanNotPaidByEOIY": 570,
    "repayments": null,
    "lodgement_date": null
  },
  "idx": 4067
}