{
  "id": "2023-10-31T18:55:05.379Z0.04461910145002923",
  "alert": "Start of result\nResult\n\nAmalgamated loan fully repaid.\n\nThe amalgamated loan has been paid in full.\u000bThe private company is not taken under Division 7A to pay a dividend to the shareholder or shareholder's associate.\n\nInterest received by the private company must be included in the income tax return for 2007-08.\n\nMinimum yearly repayment\n\n-$168.00\n\nBenchmark interest rate\n\n8.05%\n\nOpening balance:\n\nDate: 30/06/2007\n\nBalance: $86.28\n\nDays: 220\n\nInterest: $4.17\n\nPayments\n\nDate: 06/02/2008\n\nAmount: $862.81\n\nBalance: $0\n\nDays: 146\n\nInterest: $0\n\n\n\n\nTotal repayments\n\n$862.81\n\nTotal interest\n\n$4.17\n\nTotal principal\n\n$858.64\n\nClosing balance\n\nDate: 30/06/2008\n\nBalance: $0",
  "outputs": {
    "enquiryRateFormatted": "8.05%",
    "enquiryYearEndMinusOneDisplay": "30/06/2007",
    "amalgamatedLoanNotPaidByEOIYFormatted": "$86.28",
    "openingBalancePayDays": "220",
    "openingBalanceInterestFormatted": "$4.17",
    "totalAmountOfRepaymentFormatted": "$862.81",
    "totalInterestFormatted": "$4.17",
    "principalFormatted": "$858.64",
    "enquiryYearEndDisplay": "30/06/2008",
    "minimumYearRepaymentFormatted": "-$168.00",
    "loanAmountFormatted": "$0"
  },
  "repayments": [
    {
      "rd": "6/2/2008",
      "ra": 862.8130186054623
    }
  ],
  "inputs": {
    "incomeYearOfLoan": 2007,
    "fullTermOfAmalgamatedLoan": 6,
    "incomeYearOfEnquiring": 2008,
    "amalgamatedLoanNotPaidByEOIY": 86.28130186054621,
    "repayments": null,
    "lodgement_date": "26/2/2008"
  },
  "idx": 4748
}