{
  "id": "2023-10-31T19:35:36.723Z0.1940962705991045",
  "alert": "Start of result\nResult\n\nMinimum yearly repayment not met.\n\nThe amount of the loan not repaid at the end of income year 2003-04 is $87.35.\n\nThe private company may be taken to pay a dividend under Division 7A to the shareholder or shareholder's associate because the amount repaid during income year 2003-04 in relation to the amalgamated loan is less than the minimum yearly repayment required.\n\nInterest received by the private company must be included in the income tax return for 2003-04.\n\nMinimum yearly repayment\n\n$93.00\n\nBenchmark interest rate\n\n6.55%\n\nOpening balance:\n\nDate: 30/06/2003\n\nBalance: $87.35\n\nDays: 366\n\nInterest: $5.72\n\nTotal repayments\n\n$0\n\nTotal interest\n\n$5.72\n\nTotal principal\n\n$0\n\nClosing balance\n\nDate: 30/06/2004\n\nBalance: $87.35",
  "outputs": {
    "enquiryRateFormatted": "6.55%",
    "enquiryYearEndMinusOneDisplay": "30/06/2003",
    "amalgamatedLoanNotPaidByEOIYFormatted": "$87.35",
    "openingBalancePayDays": "366",
    "openingBalanceInterestFormatted": "$5.72",
    "totalAmountOfRepaymentFormatted": "$0",
    "totalInterestFormatted": "$5.72",
    "principalFormatted": "$0",
    "enquiryYearEndDisplay": "30/06/2004",
    "minimumYearRepaymentFormatted": "$93.00",
    "loanAmountFormatted": "$87.35"
  },
  "repayments": [],
  "inputs": {
    "incomeYearOfLoan": 2003,
    "fullTermOfAmalgamatedLoan": 1,
    "incomeYearOfEnquiring": 2004,
    "amalgamatedLoanNotPaidByEOIY": 87.3504103339891,
    "repayments": null,
    "lodgement_date": "28/12/2003"
  },
  "idx": 5635
}