{
  "id": "2023-10-31T19:14:48.766Z0.7675033497685899",
  "alert": "Start of result\nResult\n\nMinimum yearly repayment not met.\n\nThe amount of the loan not repaid at the end of income year 2007-08 is $6,862.16.\n\nThe private company may be taken to pay a dividend under Division 7A to the shareholder or shareholder's associate because the amount repaid during income year 2007-08 in relation to the amalgamated loan is less than the minimum yearly repayment required.\n\nInterest received by the private company must be included in the income tax return for 2007-08.\n\nMinimum yearly repayment\n\n$6,756.00\n\nBenchmark interest rate\n\n8.05%\n\nOpening balance:\n\nDate: 30/06/2007\n\nBalance: $12,039.00\n\nDays: 18\n\nInterest: $47.66\n\nPayments\n\nDate: 19/07/2007\n\nAmount: $5,709.00\n\nBalance: $6,330.00\n\nDays: 348\n\nInterest: $484.50\n\n\n\n\nTotal repayments\n\n$5,709.00\n\nTotal interest\n\n$532.16\n\nTotal principal\n\n$5,176.84\n\nClosing balance\n\nDate: 30/06/2008\n\nBalance: $6,862.16",
  "outputs": {
    "enquiryRateFormatted": "8.05%",
    "enquiryYearEndMinusOneDisplay": "30/06/2007",
    "amalgamatedLoanNotPaidByEOIYFormatted": "$12,039.00",
    "openingBalancePayDays": "18",
    "openingBalanceInterestFormatted": "$47.66",
    "totalAmountOfRepaymentFormatted": "$5,709.00",
    "totalInterestFormatted": "$532.16",
    "principalFormatted": "$5,176.84",
    "enquiryYearEndDisplay": "30/06/2008",
    "minimumYearRepaymentFormatted": "$6,756.00",
    "loanAmountFormatted": "$6,862.16"
  },
  "repayments": [
    {
      "rd": "19/7/2007",
      "ra": 5709
    }
  ],
  "inputs": {
    "incomeYearOfLoan": 2005,
    "fullTermOfAmalgamatedLoan": 4,
    "incomeYearOfEnquiring": 2008,
    "amalgamatedLoanNotPaidByEOIY": 12039,
    "repayments": null,
    "lodgement_date": null
  },
  "idx": 5212
}