{
  "id": "2023-10-31T17:22:02.471Z0.6153770597479341",
  "alert": "Start of result\nResult\n\nMinimum yearly repayment not met.\n\nThe amount of the loan not repaid at the end of income year 2022-23 is $77.18.\n\nThe private company may be taken to pay a dividend under Division 7A to the shareholder or shareholder's associate because the amount repaid during income year 2022-23 in relation to the amalgamated loan is less than the minimum yearly repayment required.\n\nInterest received by the private company must be included in the income tax return for 2022-23.\n\nMinimum yearly repayment\n\n$22.00\n\nBenchmark interest rate\n\n4.77%\n\nOpening balance:\n\nDate: 30/06/2022\n\nBalance: $77.18\n\nDays: 365\n\nInterest: $3.68\n\nTotal repayments\n\n$0\n\nTotal interest\n\n$3.68\n\nTotal principal\n\n$0\n\nClosing balance\n\nDate: 30/06/2023\n\nBalance: $77.18",
  "outputs": {
    "enquiryRateFormatted": "4.77%",
    "enquiryYearEndMinusOneDisplay": "30/06/2022",
    "amalgamatedLoanNotPaidByEOIYFormatted": "$77.18",
    "openingBalancePayDays": "365",
    "openingBalanceInterestFormatted": "$3.68",
    "totalAmountOfRepaymentFormatted": "$0",
    "totalInterestFormatted": "$3.68",
    "principalFormatted": "$0",
    "enquiryYearEndDisplay": "30/06/2023",
    "minimumYearRepaymentFormatted": "$22.00",
    "loanAmountFormatted": "$77.18"
  },
  "repayments": [],
  "inputs": {
    "incomeYearOfLoan": 2019,
    "fullTermOfAmalgamatedLoan": 7,
    "incomeYearOfEnquiring": 2023,
    "amalgamatedLoanNotPaidByEOIY": 77.18690205347723,
    "repayments": null,
    "lodgement_date": null
  },
  "idx": 1224
}