{
  "id": "2023-10-31T18:21:55.661Z0.7563036556969032",
  "alert": "Start of result\nResult\n\nMinimum yearly repayment met.\n\nThe amount of the loan not repaid at the end of income year 2011-12 is $1.04.\n\n\u000b\n\nThe amalgamated loan will not be taken to be a dividend because the total repayments made are equal to or greater than the minimum yearly repayment required for income year 2011-12.\n\nInterest received by the private company must be included in the income tax return for 2011-12.\n\nMinimum yearly repayment\n\n$0\n\nBenchmark interest rate\n\n7.8%\n\nOpening balance:\n\nDate: 30/06/2011\n\nBalance: $1.04\n\nDays: 366\n\nInterest: $0.08\n\nTotal repayments\n\n$0\n\nTotal interest\n\n$0.08\n\nTotal principal\n\n$0\n\nClosing balance\n\nDate: 30/06/2012\n\nBalance: $1.04",
  "outputs": {
    "enquiryRateFormatted": "7.8%",
    "enquiryYearEndMinusOneDisplay": "30/06/2011",
    "amalgamatedLoanNotPaidByEOIYFormatted": "$1.04",
    "openingBalancePayDays": "366",
    "openingBalanceInterestFormatted": "$0.08",
    "totalAmountOfRepaymentFormatted": "$0",
    "totalInterestFormatted": "$0.08",
    "principalFormatted": "$0",
    "enquiryYearEndDisplay": "30/06/2012",
    "minimumYearRepaymentFormatted": "$0",
    "loanAmountFormatted": "$1.04"
  },
  "repayments": [],
  "inputs": {
    "incomeYearOfLoan": 2010,
    "fullTermOfAmalgamatedLoan": 5,
    "incomeYearOfEnquiring": 2012,
    "amalgamatedLoanNotPaidByEOIY": 1.0405748720961712,
    "repayments": null,
    "lodgement_date": null
  },
  "idx": 3850
}