{
  "id": "2023-10-31T19:31:19.589Z0.29458806250827996",
  "alert": "Start of result\nResult\n\nMinimum yearly repayment not met.\n\nThe amount of the loan not repaid at the end of income year 2007-08 is $7,600.00.\n\nThe private company may be taken to pay a dividend under Division 7A to the shareholder or shareholder's associate because the amount repaid during income year 2007-08 in relation to the amalgamated loan is less than the minimum yearly repayment required.\n\nInterest received by the private company must be included in the income tax return for 2007-08.\n\nMinimum yearly repayment\n\n$2,952.00\n\nBenchmark interest rate\n\n8.05%\n\nOpening balance:\n\nDate: 30/06/2007\n\nBalance: $7,600.00\n\nDays: 366\n\nInterest: $611.80\n\nTotal repayments\n\n$0\n\nTotal interest\n\n$611.80\n\nTotal principal\n\n$0\n\nClosing balance\n\nDate: 30/06/2008\n\nBalance: $7,600.00",
  "outputs": {
    "enquiryRateFormatted": "8.05%",
    "enquiryYearEndMinusOneDisplay": "30/06/2007",
    "amalgamatedLoanNotPaidByEOIYFormatted": "$7,600.00",
    "openingBalancePayDays": "366",
    "openingBalanceInterestFormatted": "$611.80",
    "totalAmountOfRepaymentFormatted": "$0",
    "totalInterestFormatted": "$611.80",
    "principalFormatted": "$0",
    "enquiryYearEndDisplay": "30/06/2008",
    "minimumYearRepaymentFormatted": "$2,952.00",
    "loanAmountFormatted": "$7,600.00"
  },
  "repayments": [],
  "inputs": {
    "incomeYearOfLoan": 2004,
    "fullTermOfAmalgamatedLoan": 6,
    "incomeYearOfEnquiring": 2008,
    "amalgamatedLoanNotPaidByEOIY": 7600,
    "repayments": null,
    "lodgement_date": null
  },
  "idx": 5554
}