{
  "id": "2023-09-06T13:22:15.019Z0.824086482377741",
  "alert": "Start of result\nResult\n\nMinimum yearly repayment met.\n\nThe amount of the loan not repaid at the end of income year 2010-11 is $300.25.\n\nThe amalgamated loan will not be taken to be a dividend because the total repayments made are equal to or greater than the minimum yearly repayment required for income year 2010-11.\n\nInterest received by the private company must be included in the income tax return for 2010-11.\n\nMinimum yearly repayment\n\n$2,440.00\n\nBenchmark interest rate\n\n7.4%\n\nOpening balance:\n\nDate: 30/06/2010\n\nBalance: $6,356.00\n\nDays: 233\n\nInterest: $300.25\n\nPayments\n\nDate: 19/02/2011\n\nAmount: $6,356.00\n\nBalance: $0\n\nDays: 132\n\nInterest: $0\n\n\n\n\nTotal repayments\n\n$6,356.00\n\nTotal interest\n\n$300.25\n\nTotal principal\n\n$6,055.75\n\nClosing balance\n\nDate: 30/06/2011\n\nBalance: $300.25",
  "outputs": {
    "enquiryRateFormatted": "7.4%",
    "enquiryYearEndMinusOneDisplay": "30/06/2010",
    "amalgamatedLoanNotPaidByEOIYFormatted": "$6,356.00",
    "openingBalancePayDays": "233",
    "openingBalanceInterestFormatted": "$300.25",
    "totalAmountOfRepaymentFormatted": "$6,356.00",
    "totalInterestFormatted": "$300.25",
    "principalFormatted": "$6,055.75",
    "enquiryYearEndDisplay": "30/06/2011",
    "minimumYearRepaymentFormatted": "$2,440.00"
  },
  "repayments": [
    {
      "rd": "19/2/2011",
      "ra": 6356
    }
  ],
  "inputs": {
    "incomeYearOfLoan": 2007,
    "fullTermOfAmalgamatedLoan": 6,
    "incomeYearOfEnquiring": 2011,
    "amalgamatedLoanNotPaidByEOIY": 6356,
    "repayments": null,
    "lodgement_date": null
  },
  "idx": 1482
}