{
  "id": "2023-09-04T15:59:55.648Z0.32044897547060835",
  "alert": "Start of result\nResult\n\nMinimum yearly repayment not met.\n\nThe amount of the loan not repaid at the end of income year 2023-24 is $4,888.39.\n\nThe private company may be taken to pay a dividend under Division 7A to the shareholder or shareholder's associate because the amount repaid during income year 2023-24 in relation to the amalgamated loan is less than the minimum yearly repayment required.\n\nInterest received by the private company must be included in the income tax return for 2023-24.\n\nMinimum yearly repayment\n\n$4,888.00\n\nBenchmark interest rate\n\n8.27%\n\nOpening balance:\n\nDate: 30/06/2023\n\nBalance: $7,425.00\n\nDays: 0\n\nInterest: $0\n\nPayments\n\nDate: 01/07/2023\n\nAmount: $2,910.00\n\nBalance: $4,515.00\n\nDays: 366\n\nInterest: $373.39\n\n\n\n\nTotal repayments\n\n$2,910.00\n\nTotal interest\n\n$373.39\n\nTotal principal\n\n$2,536.61\n\nClosing balance\n\nDate: 30/06/2024\n\nBalance: $4,888.39",
  "outputs": {
    "enquiryRateFormatted": "8.27%",
    "enquiryYearEndMinusOneDisplay": "30/06/2023",
    "amalgamatedLoanNotPaidByEOIYFormatted": "$7,425.00",
    "openingBalancePayDays": "0",
    "openingBalanceInterestFormatted": "$0",
    "totalAmountOfRepaymentFormatted": "$2,910.00",
    "totalInterestFormatted": "$373.39",
    "principalFormatted": "$2,536.61",
    "enquiryYearEndDisplay": "30/06/2024",
    "minimumYearRepaymentFormatted": "$4,888.00"
  },
  "repayments": [
    {
      "rd": "1/7/2023",
      "ra": 2910
    }
  ],
  "inputs": {
    "incomeYearOfLoan": 2023,
    "fullTermOfAmalgamatedLoan": 1,
    "incomeYearOfEnquiring": 2024,
    "amalgamatedLoanNotPaidByEOIY": 7425,
    "repayments": null,
    "lodgement_date": "30/6/2024"
  },
  "idx": 9
}