{
  "id": "2023-09-07T04:10:08.569Z0.8785625697508315",
  "alert": "Start of result\nResult\n\nMinimum yearly repayment not met.\n\nThe amount of the loan not repaid at the end of income year 2003-04 is $3,011.02.\n\nThe private company may be taken to pay a dividend under Division 7A to the shareholder or shareholder's associate because the amount repaid during income year 2003-04 in relation to the amalgamated loan is less than the minimum yearly repayment required.\n\nInterest received by the private company must be included in the income tax return for 2003-04.\n\nMinimum yearly repayment\n\n$2,977.00\n\nBenchmark interest rate\n\n6.55%\n\nOpening balance:\n\nDate: 30/06/2003\n\nBalance: $5,416.00\n\nDays: 139\n\nInterest: $134.73\n\nPayments\n\nDate: 17/11/2003\n\nAmount: $2,652.00\n\nBalance: $2,764.00\n\nDays: 227\n\nInterest: $112.29\n\n\n\n\nTotal repayments\n\n$2,652.00\n\nTotal interest\n\n$247.02\n\nTotal principal\n\n$2,404.98\n\nClosing balance\n\nDate: 30/06/2004\n\nBalance: $3,011.02",
  "outputs": {
    "enquiryRateFormatted": "6.55%",
    "enquiryYearEndMinusOneDisplay": "30/06/2003",
    "amalgamatedLoanNotPaidByEOIYFormatted": "$5,416.00",
    "openingBalancePayDays": "139",
    "openingBalanceInterestFormatted": "$134.73",
    "totalAmountOfRepaymentFormatted": "$2,652.00",
    "totalInterestFormatted": "$247.02",
    "principalFormatted": "$2,404.98",
    "enquiryYearEndDisplay": "30/06/2004",
    "minimumYearRepaymentFormatted": "$2,977.00"
  },
  "repayments": [
    {
      "rd": "17/11/2003",
      "ra": 2652
    }
  ],
  "inputs": {
    "incomeYearOfLoan": 1998,
    "fullTermOfAmalgamatedLoan": 7,
    "incomeYearOfEnquiring": 2004,
    "amalgamatedLoanNotPaidByEOIY": 5416,
    "repayments": null,
    "lodgement_date": null
  },
  "idx": 2955
}