{
  "id": "2023-09-04T14:05:50.768Z0.026472534274451842",
  "alert": "Start of result\nResult\n\nMinimum yearly repayment not met.\n\nThe amount of the loan not repaid at the end of income year 2023-24 is $41,270,709.59.\n\nThe private company may be taken to pay a dividend under Division 7A to the shareholder or shareholder's associate because the amount repaid during income year 2023-24 in relation to the amalgamated loan is less than the minimum yearly repayment required.\n\nInterest received by the private company must be included in the income tax return for 2023-24.\n\nMinimum yearly repayment\n\n$12,535,455.00\n\nBenchmark interest rate\n\n8.27%\n\nOpening balance:\n\nDate: 30/06/2023\n\nBalance: $41,270,709.59\n\nDays: 366\n\nInterest: $3,413,087.68\n\nTotal repayments\n\n$0\n\nTotal interest\n\n$3,413,087.68\n\nTotal principal\n\n$0\n\nClosing balance\n\nDate: 30/06/2024\n\nBalance: $41,270,709.59",
  "outputs": {
    "enquiryRateFormatted": "8.27%",
    "enquiryYearEndMinusOneDisplay": "30/06/2023",
    "amalgamatedLoanNotPaidByEOIYFormatted": "$41,270,709.59",
    "openingBalancePayDays": "366",
    "openingBalanceInterestFormatted": "$3,413,087.68",
    "totalAmountOfRepaymentFormatted": "$0",
    "totalInterestFormatted": "$3,413,087.68",
    "principalFormatted": "$0",
    "enquiryYearEndDisplay": "30/06/2024",
    "minimumYearRepaymentFormatted": "$12,535,455.00"
  },
  "repayments": [],
  "inputs": {
    "incomeYearOfLoan": 2023,
    "fullTermOfAmalgamatedLoan": 4,
    "incomeYearOfEnquiring": 2024,
    "amalgamatedLoanNotPaidByEOIY": 41270709.59451245,
    "repayments": null,
    "lodgement_date": "9/10/2023"
  },
  "idx": 46
}